Workbook
Name Adequacao_Imovel: 'Listas (não utilizar)'!$G$2:$G$7
Name ADEQUAR: 'Listas (não utilizar)'!$G$2:$G$7
Name Apartamento: 'Listas (não utilizar)'!$D$2:$D$21
Name APROVCEF: #REF!
Name Área: 'Listas (não utilizar)'!$A$2:$A$28
Name AREAS: #REF!
Name AVILDATA: #REF!
Name AVILDATA1: #REF!
Name BARCDATA: #REF!
Name BILBDATA: #REF!
Name Bloco: 'Listas (não utilizar)'!$C$2:$C$16
Name CEF: #REF!
Name CEUTDATA: #REF!
Name Condomínio: 'Listas (não utilizar)'!$B$2:$B$15
Name INDDEMAND: #REF!
Name INDEMAND: #REF!
Name it: #REF!
Name Pendência: 'Listas (não utilizar)'!$I$2:$I$7
Name PLANCCO: #REF!
Name Renúncia: 'Listas (não utilizar)'!$H$2:$H$6
Name RetornoSMADS: '[1]Listas (não utilizar)'!$E$2:$E$3
Name selogo: #REF!
Name selomv: #REF!
Name selos_go: #REF!
Name selosgo: #REF!
Name selosgo1: #REF!
Name SITAH_CAIXA: 'Listas (não utilizar)'!$E$2:$E$9
Name StatusCAIXA: 'Listas (não utilizar)'!$F$2:$F$5
Name TEPROC: #REF!
Name TEPROC1: #REF!

Sheet PRIORIDADES
C3: 2 | D3: PRIORITÁRIO | G3: OCUPADO | H3: RESIDENCIAL | I3: PROPRIETÁRIO NÃO RESIDENTE | M3: CADASTRADO | N3: INDENIZAÇÃO | P3: SIM | R3: SIM | X3: SAQUE PENDENTE | AE3: PROPRIETÁRIO NÃO RESIDENTE | AF3: CADASTRADO | AI3: SIM | AK3: SIM | AM3: COMPLETA | AN3: SEM PENDÊNCIAS
C4: 4 | G4: VAZIO | H4: COMERCIAL | I4: PROPRIETÁRIO RESIDENTE | M4: NÃO CADASTRADO | N4: AUXÍLIO ALUGUEL UH | P4: NÃO | R4: NÃO | AE4: PROPRIETÁRIO RESIDENTE | AF4: NÃO CADASTRADO | AI4: NÃO | AK4: NÃO | AM4: PENDENTE | AN4: FALTA TERMO
G5: OCUPADO/RISCO | H5: MISTO | I5: INQULINO | N5: RECUSA AUXÍLIO ALUGUEL UH | AI5: UH | AK5: N/A | AN5: FALTA DOCS
G6: CONSTRUÇÃO | N6: NÃO TEM DIREITO ATENDIMENTO | AI6: ESTUDO DE CASO | AK6: PENDENTE | AN6: FALTA TERMO E DOCS
G7: DEMOLIDO
G8: DESCARACTERIZADO
G9: DESABADO
A12: INFORMAÇÕES INICIAIS | P12: INFORMAÇÕES AUXÍLIO ALUGUEL | AB12: INFORMAÇÕES INDENIZAÇÃO | BB12: PROCESSO | BD12: DEPLAN
A13: ORDEM | B13: ÁREA | C13: FASE | D13: TRECHO | E13: PRIORIDADE | F13: SELO | G13: SITUAÇÃO INICIAL IMÓVEL | H13: USO IMÓVEL | I13: SITUAÇÃO DO RESIDENTE | J13: TITULAR | K13: RG | L13: CPF | M13: CADASTRO HABITA SAMPA | N13: OPÇÃO DE ATENDIMENTO HABITACIONAL | O13: ENVIO PLANILHA DADOS | P13: SOLICITAÇÃO AUXÍLIO ALUGUEL ÁREA | Q13: No PROCESSO SEI (AUXÍLIO ALUGUEL) | R13: ANÁLISE DTS CADASTRO + CHECAGEM DUPLO | S13: INSTRUÇÃO PROCESSO SEI DTS | T13: ANÁLISE CTS ASSINATURA GABINETE | U13: DATA PUBLICAÇÃO DIÁRIO OFICIAL | V13: CONFECÇÃO TERMO | W13: ENVIO TERMO CARTÃO | X13: PREVISÃO PAGAMENTO | Y13: DATA SAQUE | Z13: DATA MUDANÇA | AA13: OBSERVAÇÕES AA | AB13: PROPRIETÁRIO | AC13: RG | AD13: CPF | AE13: SITUAÇÃO DO PROPRIETÁRIO | AF13: CADASTRO HABITASAMPA | AG13: VALOR AVALIAÇÃO | AH13: VALOR FINAL INDENIZAÇÃO | AI13: ACEITA VALOR INDENIZAÇÃO | AJ13: Nº SEI LAUDOS AVALIAÇÃO | AK13: Nº DOCUMENTO LAUDO | AL13: TERMO INDENIZAÇÃO | AM13: DOSSIÊ | AN13: PENDÊNCIA | AO13: OBSERVAÇÕES INDENIZAÇÃO | AP13: No PROCESSO SEI (INDENIZAÇÃO) | AQ13: INSTRUÇÃO PROCESSO SEI DTS | AR13: ASSINATURA DIRETOR DTS | AS13: ELABORAÇÃO DESPACHO CTS | AT13: ASSINATURA DESPACHO GABINETE | AU13: PUBLICAÇÃO DIÁRIO OFICIAL | AV13: ENCAMINHAMENTO DAF/DIF CTS | AW13: LIBERAÇÃO PAGAMENTO DAF/DIF | AX13: PREVISÃO PAGAMENTO | AY13: DATA PAGAMENTO | AZ13: DATA ENTREGA IMÓVEL | BA13: SITUAÇÃO ATUAL IMÓVEL | BB13: STATUS | BC13: DIAS TOTAIS | BD13: OPÇÃO ATENDIMENTO | BE13: NECESSITA BLOQUEIO AA | BF13: SOLICITAÇÃO BLOQUEIO AA DTS | BG13: SOLICITAÇÃO BLOQUEIO AA DTS | BH13: DATA BLOQUEIO AA | BI13: DESPACHO EXCLUSÃO GABINETE | BJ13: ASSINATURA DESPACHO GABINETE | BK13: PUBLICAÇÃO DOC | BL13: ENCAMINHAMENTO SOLICITAÇÃO EXCLUSÃO DEPLAN | BM13: ENCERRAMENTO PROCESSO DTS
A14: 1 | B14: ALFREDO ÁVILA | C14: 1 | D14: 0 | E14: 0 | F14: 001/0001/A | G14: OCUPADO | H14: MISTO | I14: PROPRIETÁRIO RESIDENTE | J14: ANTONIO CARLOS PEREIRA LIMAS | K14: 27.717.269-X | L14: 172.907.418-97 | M14: CADASTRADO | N14: INDENIZAÇÃO | O14: 44900 | P14: N/A | Q14: N/A | R14: N/A | S14: N/A | T14: N/A | U14: N/A | V14: N/A | W14: N/A | X14: N/A | Y14: N/A | Z14: N/A | AB14: ANTONIO CARLOS PEREIRA LIMAS | AC14: 27.717.269-X | AD14: 172.907.418-97 | AE14: PROPRIETÁRIO RESIDENTE | AF14: CADASTRADO | AG14: 39200 | AH14: 60000 | AI14: SIM | AJ14: 6014.2022/0003993-0 | AK14: FINALIZADO | AL14: FINALIZADO | AM14: FINALIZADO | AN14: SEM PENDÊNCIA | AP14: 6014.2023/0001314-2 | AQ14: FINALIZADO | AR14: FINALIZADO | AS14: FINALIZADO | AT14: FINALIZADO | AU14: 45104 | AV14: FINALIZADO | AW14: FINALIZADO | AX14: 45111 | AY14: 45111 | AZ14: 45124 | BA14: DEMOLIDO | BB14: FINALIZADO | BC14: =IF(AY14-ON14=0,"",AY14-O14) -> 211 | BD14: =IF(AND(AI14<>"SIM",AI14="UH"),"AA","INDENIZAÇÃO") -> INDENIZAÇÃO | BE14: =IF(AND(AY14<>"AGUARDANDO",AY14<>"",N14="AUXÍLIO ALUGUEL ATÉ INDENIZAÇÃO"),"SIM","NÃO") -> NÃO | BF14: N/A | BG14: N/A | BH14: N/A | BI14: FINALIZADO | BJ14: FINALIZADO | BK14: 45190 | BL14: FINALIZADO | BM14: FINALIZADO
A15: 2 | B15: ALFREDO ÁVILA | C15: 1 | D15: 0 | E15: 0 | F15: 001/0001/B | G15: OCUPADO | H15: RESIDENCIAL | I15: PROPRIETÁRIO RESIDENTE | J15: ANTONIO CARLOS PEREIRA LIMAS | K15: 27.717.269-X | L15: 172.907.418-97 | M15: CADASTRADO | N15: SELO EXCLUÍDO | O15: 44900 | P15: N/A | Q15: N/A | R15: N/A | S15: N/A | T15: N/A | U15: N/A | V15: N/A | W15: N/A | X15: N/A | Y15: N/A | Z15: N/A | AA15: SELO EXCLUÍDO | AB15: ANTONIO CARLOS PEREIRA LIMAS | AC15: 27.717.269-X | AD15: 172.907.418-97 | AE15: PROPRIETÁRIO RESIDENTE | AF15: N/A | AG15: 0 | AH15: 0 | AI15: SELO EXCLUÍDO | AJ15: 6014.2022/0003993-0 | AK15: N/A | AL15: N/A | AM15: N/A | AN15: N/A | AO15: SELO EXCLUÍDO | AP15: N/A | AQ15: N/A | AR15: N/A | AS15: N/A | AT15: N/A | AU15: N/A | AV15: N/A | AW15: N/A | AX15: N/A | AY15: N/A | AZ15: N/A | BA15: N/A | BB15: FINALIZADO | BC15: N/A | BD15: =IF(AND(AI15<>"SIM",AI15="UH"),"AA","INDENIZAÇÃO") -> INDENIZAÇÃO | BE15: =IF(AND(AY15<>"AGUARDANDO",AY15<>"",N15="AUXÍLIO ALUGUEL ATÉ INDENIZAÇÃO"),"SIM","NÃO") -> NÃO | BF15: N/A | BG15: N/A | BH15: N/A | BI15: N/A | BJ15: N/A | BK15: N/A | BL15: N/A | BM15: FINALIZADO
A16: 3 | B16: ALFREDO ÁVILA | C16: 1 | D16: 0 | E16: 0 | F16: 001/0002/A | G16: OCUPADO | H16: RESIDENCIAL | I16: PROPRIETÁRIO RESIDENTE | J16: WALLACE CARLOS DO NASCIMENTO | K16: 53.833.874-X | L16: 460.742.418-80 | M16: CADASTRADO | N16: AUXÍLIO ALUGUEL UH | O16: 44900 | P16: 44921 | Q16: 6014.2023/0000399-6 | R16: FINALIZADO | S16: FINALIZADO | T16: FINALIZADO | U16: 44992 | V16: FINALIZADO | W16: 44992 | X16: 45019 | Y16: 45019 | Z16: 45029 | AA16: Houve um problema na equipe do pagamento, sendo previsto para 03/04/2023 | AB16: WALLACE CARLOS DO NASCIMENTO | AC16: 53.833.874-X | AD16: 460.742.418-80 | AE16: PROPRIETÁRIO RESIDENTE | AF16: CADASTRADO | AG16: 15600 | AH16: 45600 | AI16: UH | AJ16: 6014.2022/0003993-0 | AK16: FINALIZADO | AL16: N/A | AM16: N/A | AN16: N/A | AP16: N/A | AQ16: N/A | AR16: N/A | AS16: N/A | AT16: N/A | AU16: N/A | AV16: N/A | AW16: N/A | AX16: 45019 | AY16: 45019 | AZ16: 45029 | BA16: DEMOLIDO | BB16: FINALIZADO | BC16: =IF(AY16-ON16=0,"",AY16-O16) -> 119 | BD16: =IF(AND(AI16<>"SIM",AI16="UH"),"AA","INDENIZAÇÃO") -> AA | BE16: =IF(AND(AY16<>"AGUARDANDO",AY16<>"",N16="AUXÍLIO ALUGUEL ATÉ INDENIZAÇÃO"),"SIM","NÃO") -> NÃO | BF16: N/A | BG16: N/A | BH16: N/A | BI16: N/A | BJ16: N/A | BK16: N/A | BL16: N/A | BM16: FINALIZADO
A17: 4 | B17: ALFREDO ÁVILA | C17: 1 | D17: 0 | E17: 0 | F17: 001/0002/B | G17: OCUPADO | H17: RESIDENCIAL | I17: PROPRIETÁRIO RESIDENTE | J17: VANESSA SANTOS DE MARIZ | K17: 54.110.071-3 | L17: 490.323.538-61 | M17: CADASTRADO | N17: AUXÍLIO ALUGUEL UH | O17: 44900 | P17: 44921 | Q17: 6014.2023/0000399-6 | R17: FINALIZADO | S17: FINALIZADO | T17: FINALIZADO | U17: 44992 | V17: FINALIZADO | W17: 44992 | X17: 45019 | Y17: 45020 | Z17: 45029 | AA17: Houve um problema na equipe do pagamento, sendo previsto para 03/04/2023 | AB17: VANESSA SANTOS DE MARIZ | AC17: 54.110.071-3 | AD17: 490.323.538-61 | AE17: PROPRIETÁRIO RESIDENTE | AF17: CADASTRADO | AG17: 14600 | AH17: 54600 | AI17: UH | AJ17: 6014.2022/0003993-0 | AK17: FINALIZADO | AL17: N/A | AM17: N/A | AN17: N/A | AP17: N/A | AQ17: N/A | AR17: N/A | AS17: N/A | AT17: N/A | AU17: N/A | AV17: N/A | AW17: N/A | AX17: 45019 | AY17: 45020 | AZ17: 45029 | BA17: DEMOLIDO | BB17: FINALIZADO | BC17: =IF(AY17-ON17=0,"",AY17-O17) -> 120 | BD17: =IF(AND(AI17<>"SIM",AI17="UH"),"AA","INDENIZAÇÃO") -> AA | BE17: =IF(AND(AY17<>"AGUARDANDO",AY17<>"",N17="AUXÍLIO ALUGUEL ATÉ INDENIZAÇÃO"),"SIM","NÃO") -> NÃO | BF17: N/A | BG17: N/A | BH17: N/A | BI17: N/A | BJ17: N/A | BK17: N/A | BL17: N/A | BM17: FINALIZADO
A18: 5 | B18: ALFREDO ÁVILA | C18: 1 | D18: 0 | E18: 0 | F18: 001/0003/A | G18: OCUPADO | H18: RESIDENCIAL | I18: INQUILINO | J18: JEFFERSON DA CRUZ CORRÊA | K18: 47.815.794-0 | L18: 409.715.758-27 | M18: CADASTRADO | N18: AUXÍLIO ALUGUEL UH | O18: 44900 | P18: 44921 | Q18: 6014.2023/0000399-6 | R18: FINALIZADO | S18: FINALIZADO | T18: FINALIZADO | U18: 44992 | V18: FINALIZADO | W18: 44992 | X18: 45019 | Y18: 45022 | Z18: 45057 | AA18: Houve um problema na equipe do pagamento, sendo previsto para 03/04/2023 | AB18: FRANCISCO MARQUES DE OLIVEIRA | AC18: 26.115..235-X | AD18: 185.112.418-76 | AE18: PROPRIETÁRIO NÃO RESIDENTE | AF18: CADASTRADO | AG18: 107600 | AH18: 107600 | AI18: SIM | AJ18: 6014.2022/0003993-0 | AK18: FINALIZADO | AL18: FINALIZADO | AM18: FINALIZADO | AN18: SEM PENDÊNCIA | AP18: 6014.2022/0003932-8 | AQ18: FINALIZADO | AR18: FINALIZADO | AS18: FINALIZADO | AT18: FINALIZADO | AU18: 44966 | AV18: FINALIZADO | AW18: FINALIZADO | AX18: 45041 | AY18: 45041 | AZ18: 45057 | BA18: DEMOLIDO | BB18: FINALIZADO | BC18: =IF(AY18-ON18=0,"",AY18-O18) -> 141 | BD18: =IF(AND(AI18<>"SIM",AI18="UH"),"AA","INDENIZAÇÃO") -> INDENIZAÇÃO | BE18: =IF(AND(AY18<>"AGUARDANDO",AY18<>"",N18="AUXÍLIO ALUGUEL ATÉ INDENIZAÇÃO"),"SIM","NÃO") -> NÃO | BF18: N/A | BG18: N/A | BH18: N/A | BI18: FINALIZADO | BJ18: FINALIZADO | BK18: 45190 | BL18: FINALIZADO | BM18: FINALIZADO
A19: 6 | B19: ALFREDO ÁVILA | C19: 1 | D19: 0 | E19: 0 | F19: 001/0004/A | G19: OCUPADO | H19: RESIDENCIAL | I19: INQUILINO | J19: ISABELLE LAISLA DA SILVA | K19: 62.680.901-0 | L19: 561.448.138-96 | M19: CADASTRADO | N19: AUXÍLIO ALUGUEL UH | O19: 44900 | P19: 44921 | Q19: 6014.2023/0000399-6 | R19: FINALIZADO | S19: FINALIZADO | T19: FINALIZADO | U19: 44992 | V19: FINALIZADO | W19: 44992 | X19: 45019 | Y19: 45019 | Z19: 45022 | AA19: Houve um problema na equipe do pagamento, sendo previsto para 03/04/2023 | AB19: ELENILDA RIBEIRO BARBOSA | AC19: 37.865.320-9 | AD19: 458.940.945-34 | AE19: PROPRIETÁRIO NÃO RESIDENTE | AF19: CADASTRADO | AG19: 27100 | AH19: 57100 | AI19: SIM | AJ19: 6014.2022/0003993-0 | AK19: FINALIZADO | AL19: FINALIZADO | AM19: FINALIZADO | AN19: SEM PENDÊNCIA | AP19: 6014.2022/0003936-0 | AQ19: FINALIZADO | AR19: FINALIZADO | AS19: FINALIZADO | AT19: FINALIZADO | AU19: 44966 | AV19: FINALIZADO | AW19: FINALIZADO | AX19: 45009 | AY19: 45009 | AZ19: 45022 | BA19: DEMOLIDO | BB19: FINALIZADO | BC19: =IF(AY19-ON19=0,"",AY19-O19) -> 109 | BD19: =IF(AND(AI19<>"SIM",AI19="UH"),"AA","INDENIZAÇÃO") -> INDENIZAÇÃO | BE19: =IF(AND(AY19<>"AGUARDANDO",AY19<>"",N19="AUXÍLIO ALUGUEL ATÉ INDENIZAÇÃO"),"SIM","NÃO") -> NÃO | BF19: N/A | BG19: N/A | BH19: N/A | BI19: FINALIZADO | BJ19: FINALIZADO | BK19: 45190 | BL19: FINALIZADO | BM19: FINALIZADO
A20: 7 | B20: ALFREDO ÁVILA | C20: 1 | D20: 0 | E20: 0 | F20: 001/0005/A | G20: EM CONSTRUÇÃO | H20: RESIDENCIAL | M20: CADASTRADO | N20: INDENIZAÇÃO | O20: 44900 | P20: N/A | Q20: N/A | R20: N/A | S20: N/A | T20: N/A | U20: N/A | V20: N/A | W20: N/A | X20: N/A | Y20: N/A | Z20: N/A | AB20: ANDRÉ VINICIUS DOS SANTOS | AC20: 54.531.709-5 | AD20: 485.192.658-80 | AE20: PROPRIETÁRIO NÃO RESIDENTE | AF20: CADASTRADO | AG20: 15900 | AH20: 45900 | AI20: SIM | AJ20: 6014.2022/0003993-0 | AK20: FINALIZADO | AL20: FINALIZADO | AM20: FINALIZADO | AN20: SEM PENDÊNCIA | AP20: 6014.2022/0003939-5 | AQ20: FINALIZADO | AR20: FINALIZADO | AS20: FINALIZADO | AT20: FINALIZADO | AU20: 44966 | AV20: FINALIZADO | AW20: FINALIZADO | AX20: 45009 | AY20: 45009 | AZ20: 45021 | BA20: DEMOLIDO | BB20: FINALIZADO | BC20: =IF(AY20-ON20=0,"",AY20-O20) -> 109 | BD20: =IF(AND(AI20<>"SIM",AI20="UH"),"AA","INDENIZAÇÃO") -> INDENIZAÇÃO | BE20: =IF(AND(AY20<>"AGUARDANDO",AY20<>"",N20="AUXÍLIO ALUGUEL ATÉ INDENIZAÇÃO"),"SIM","NÃO") -> NÃO | BF20: N/A | BG20: N/A | BH20: N/A | BI20: FINALIZADO | BJ20: FINALIZADO | BK20: 45190 | BL20: FINALIZADO | BM20: FINALIZADO
A21: 8 | B21: ALFREDO ÁVILA | C21: 1 | D21: 0 | E21: 0 | F21: 001/0006/A | G21: OCUPADO | H21: RESIDENCIAL | I21: PROPRIETÁRIO RESIDENTE | J21: MARIA DA GLORIA CARMO SANTOS | K21: 22.334.891-0 | L21: 128.114.308-14 | M21: CADASTRADO | N21: INDENIZAÇÃO | O21: 44900 | P21: N/A | Q21: N/A | R21: N/A | S21: N/A | T21: N/A | U21: N/A | V21: N/A | W21: N/A | X21: N/A | Y21: N/A | Z21: N/A | AB21: MARIA DA GLORIA CARMO SANTOS | AC21: 22.334.891-0 | AD21: 128.114.308-14 | AE21: PROPRIETÁRIO RESIDENTE | AF21: CADASTRADO | AG21: 48500 | AH21: 60000 | AI21: SIM | AJ21: 6014.2022/0003993-0 | AK21: FINALIZADO | AL21: FINALIZADO | AM21: FINALIZADO | AN21: SEM PENDÊNCIA | AP21: 6014.2022/0003947-6 | AQ21: FINALIZADO | AR21: FINALIZADO | AS21: FINALIZADO | AT21: FINALIZADO | AU21: 44966 | AV21: FINALIZADO | AW21: FINALIZADO | AX21: 45009 | AY21: 45009 | AZ21: 45033 | BA21: DEMOLIDO | BB21: FINALIZADO | BC21: =IF(AY21-ON21=0,"",AY21-O21) -> 109 | BD21: =IF(AND(AI21<>"SIM",AI21="UH"),"AA","INDENIZAÇÃO") -> INDENIZAÇÃO | BE21: =IF(AND(AY21<>"AGUARDANDO",AY21<>"",N21="AUXÍLIO ALUGUEL ATÉ INDENIZAÇÃO"),"SIM","NÃO") -> NÃO | BF21: N/A | BG21: N/A | BH21: N/A | BI21: FINALIZADO | BJ21: FINALIZADO | BK21: 45190 | BL21: FINALIZADO | BM21: FINALIZADO
A22: 9 | B22: ALFREDO ÁVILA | C22: 1 | D22: 0 | E22: 0 | F22: 001/0006/B | G22: OCUPADO | H22: RESIDENCIAL | I22: PROPRIETÁRIO RESIDENTE | J22: CINTIA CARMO MIRANDA DE OLIVEIRA | K22: 47.503.428-1 | L22: 394.343.598-99 | M22: CADASTRADO | N22: AUXÍLIO ALUGUEL UH | O22: 44900 | P22: 44921 | Q22: 6014.2023/0000399-6 | R22: FINALIZADO | S22: FINALIZADO | T22: FINALIZADO | U22: 44992 | V22: FINALIZADO | W22: 44992 | X22: 45019 | Y22: 45019 | Z22: 45033 | AA22: Houve um problema na equipe do pagamento, sendo previsto para 03/04/2023 | AB22: CINTIA CARMO MIRANDA DE OLIVEIRA | AC22: 47.503.428-1 | AD22: 394.343.598-99 | AE22: PROPRIETÁRIO RESIDENTE | AF22: CADASTRADO | AG22: 19900 | AH22: 49900 | AI22: UH | AJ22: 6014.2022/0003993-0 | AK22: FINALIZADO | AL22: N/A | AM22: N/A | AN22: N/A | AP22: N/A | AQ22: N/A | AR22: N/A | AS22: N/A | AT22: N/A | AU22: N/A | AV22: N/A | AW22: N/A | AX22: 45019 | AY22: 45019 | AZ22: 45033 | BA22: DEMOLIDO | BB22: FINALIZADO | BC22: =IF(AY22-ON22=0,"",AY22-O22) -> 119 | BD22: =IF(AND(AI22<>"SIM",AI22="UH"),"AA","INDENIZAÇÃO") -> AA | BE22: =IF(AND(AY22<>"AGUARDANDO",AY22<>"",N22="AUXÍLIO ALUGUEL ATÉ INDENIZAÇÃO"),"SIM","NÃO") -> NÃO | BF22: N/A | BG22: N/A | BH22: N/A | BI22: N/A | BJ22: N/A | BK22: N/A | BL22: N/A | BM22: FINALIZADO
A23: 10 | B23: ALFREDO ÁVILA | C23: 1 | D23: 0 | E23: 0 | F23: 001/0007/A | G23: OCUPADO | H23: RESIDENCIAL | I23: PROPRIETÁRIO RESIDENTE | J23: ELIANE RIBEIRO BARBOSA | K23: 58.837.007-1 | L23: 020.661.135-81 | M23: CADASTRADO | N23: INDENIZAÇÃO | O23: 44900 | P23: N/A | Q23: N/A | R23: N/A | S23: N/A | T23: N/A | U23: N/A | V23: N/A | W23: N/A | X23: N/A | Y23: N/A | Z23: N/A | AB23: ELIANE RIBEIRO BARBOSA | AC23: 58.837.007-1 | AD23: 020.661.135-81 | AE23: PROPRIETÁRIO RESIDENTE | AF23: CADASTRADO | AG23: 19800 | AH23: 49800 | AI23: SIM | AJ23: 6014.2022/0003993-0 | AK23: FINALIZADO | AL23: FINALIZADO | AM23: FINALIZADO | AN23: SEM PENDÊNCIA | AP23: 6014.2022/0004025-3 | AQ23: FINALIZADO | AR23: FINALIZADO | AS23: FINALIZADO | AT23: FINALIZADO | AU23: 44922 | AV23: FINALIZADO | AW23: FINALIZADO | AX23: 44924 | AY23: 44924 | AZ23: 44935 | BA23: DEMOLIDO | BB23: FINALIZADO | BC23: =IF(AY23-ON23=0,"",AY23-O23) -> 24 | BD23: =IF(AND(AI23<>"SIM",AI23="UH"),"AA","INDENIZAÇÃO") -> INDENIZAÇÃO | BE23: =IF(AND(AY23<>"AGUARDANDO",AY23<>"",N23="AUXÍLIO ALUGUEL ATÉ INDENIZAÇÃO"),"SIM","NÃO") -> NÃO | BF23: N/A | BG23: N/A | BH23: N/A | BI23: FINALIZADO | BJ23: FINALIZADO | BK23: 45057 | BL23: FINALIZADO | BM23: FINALIZADO
A24: 11 | B24: ALFREDO ÁVILA | C24: 1 | D24: 0 | E24: 0 | F24: 001/0008/A | G24: OCUPADO | H24: RESIDENCIAL | I24: PROPRIETÁRIO RESIDENTE | J24: NOELIA RIBEIRO BARBOSA | K24: 28.191.025-X | L24: 184.917.628-09 | M24: CADASTRADO | N24: INDENIZAÇÃO | O24: 44900 | P24: N/A | Q24: N/A | R24: N/A | S24: N/A | T24: N/A | U24: N/A | V24: N/A | W24: N/A | X24: N/A | Y24: N/A | Z24: N/A | AB24: NOELIA RIBEIRO BARBOSA | AC24: 28.191.025-X | AD24: 184.917.628-09 | AE24: PROPRIETÁRIO RESIDENTE | AF24: CADASTRADO | AG24: 30400 | AH24: 60000 | AI24: SIM | AJ24: 6014.2022/0003993-0 | AK24: FINALIZADO | AL24: FINALIZADO | AM24: FINALIZADO | AN24: SEM PENDÊNCIA | AP24: 6014.2022/0004026-1 | AQ24: FINALIZADO | AR24: FINALIZADO | AS24: FINALIZADO | AT24: FINALIZADO | AU24: 44922 | AV24: FINALIZADO | AW24: FINALIZADO | AX24: 44924 | AY24: 44924 | AZ24: 44935 | BA24: DEMOLIDO | BB24: FINALIZADO | BC24: =IF(AY24-ON24=0,"",AY24-O24) -> 24 | BD24: =IF(AND(AI24<>"SIM",AI24="UH"),"AA","INDENIZAÇÃO") -> INDENIZAÇÃO | BE24: =IF(AND(AY24<>"AGUARDANDO",AY24<>"",N24="AUXÍLIO ALUGUEL ATÉ INDENIZAÇÃO"),"SIM","NÃO") -> NÃO | BF24: N/A | BG24: N/A | BH24: N/A | BI24: FINALIZADO | BJ24: FINALIZADO | BK24: 45057 | BL24: FINALIZADO | BM24: FINALIZADO
A25: 12 | B25: ALFREDO ÁVILA | C25: 1 | D25: 0 | E25: 0 | F25: 001/0008/B | G25: OCUPADO | H25: RESIDENCIAL | I25: PROPRIETÁRIO RESIDENTE | J25: LUCAS DA SILVA PEREIRA | K25: 45.668.154-8 | L25: 459.407.808-73 | M25: CADASTRADO | N25: AUXÍLIO ALUGUEL UH | O25: 44900 | P25: 44921 | Q25: 6014.2023/0000399-6 | R25: FINALIZADO | S25: FINALIZADO | T25: FINALIZADO | U25: 44992 | V25: FINALIZADO | W25: 44992 | X25: 45019 | Y25: 45019 | Z25: 45203 | AA25: Houve um problema na equipe do pagamento, sendo previsto para 03/04/2023 | AB25: LUCAS DA SILVA PEREIRA | AC25: 45.668.154-8 | AD25: 459.407.808-73 | AE25: PROPRIETÁRIO RESIDENTE | AF25: CADASTRADO | AG25: 13000 | AH25: 43000 | AI25: UH | AJ25: 6014.2022/0003993-0 | AK25: FINALIZADO | AL25: N/A | AM25: N/A | AN25: N/A | AP25: N/A | AQ25: N/A | AR25: N/A | AS25: N/A | AT25: N/A | AU25: N/A | AV25: N/A | AW25: N/A | AX25: 45019 | AY25: 45019 | AZ25: 45026 | BA25: DEMOLIDO | BB25: FINALIZADO | BC25: =IF(AY25-ON25=0,"",AY25-O25) -> 119 | BD25: =IF(AND(AI25<>"SIM",AI25="UH"),"AA","INDENIZAÇÃO") -> AA | BE25: =IF(AND(AY25<>"AGUARDANDO",AY25<>"",N25="AUXÍLIO ALUGUEL ATÉ INDENIZAÇÃO"),"SIM","NÃO") -> NÃO | BF25: N/A | BG25: N/A | BH25: N/A | BI25: N/A | BJ25: N/A | BK25: N/A | BL25: N/A | BM25: FINALIZADO
A26: 13 | B26: ALFREDO ÁVILA | C26: 1 | D26: 0 | E26: 0 | F26: 001/0009/A | G26: OCUPADO | H26: RESIDENCIAL | I26: PROPRIETÁRIO RESIDENTE | J26: MIRNA ELIZABETH CABRERA CUEVA | K26: RNM G065972-9 | L26: 237.484.388-26 | M26: CADASTRADO | N26: AUXÍLIO ALUGUEL UH | O26: 44900 | P26: 44921 | Q26: 6014.2023/0000399-6 | R26: FINALIZADO | S26: FINALIZADO | T26: FINALIZADO | U26: 44992 | V26: FINALIZADO | W26: 44992 | X26: 45019 | Y26: 45019 | Z26: 45203 | AA26: Houve um problema na equipe do pagamento, sendo previsto para 03/04/2023 | AB26: MIRNA ELIZABETH CABRERA CUEVA | AC26: RNM G065972-9 | AD26: 237.484.388-26 | AE26: PROPRIETÁRIO RESIDENTE | AF26: CADASTRADO | AG26: 22700 | AH26: 52700 | AI26: UH | AJ26: 6014.2022/0003993-0 | AK26: FINALIZADO | AL26: N/A | AM26: N/A | AN26: N/A | AP26: N/A | AQ26: N/A | AR26: N/A | AS26: N/A | AT26: N/A | AU26: N/A | AV26: N/A | AW26: N/A | AX26: 45019 | AY26: 45019 | AZ26: 45026 | BA26: DEMOLIDO | BB26: FINALIZADO | BC26: =IF(AY26-ON26=0,"",AY26-O26) -> 119 | BD26: =IF(AND(AI26<>"SIM",AI26="UH"),"AA","INDENIZAÇÃO") -> AA | BE26: =IF(AND(AY26<>"AGUARDANDO",AY26<>"",N26="AUXÍLIO ALUGUEL ATÉ INDENIZAÇÃO"),"SIM","NÃO") -> NÃO | BF26: N/A | BG26: N/A | BH26: N/A | BI26: N/A | BJ26: N/A | BK26: N/A | BL26: N/A | BM26: FINALIZADO
A27: 14 | B27: ALFREDO ÁVILA | C27: 1 | D27: 0 | E27: 0 | F27: 001/0010/A | G27: OCUPADO | H27: RESIDENCIAL | I27: INQUILINO | O27: 44900 | P27: N/A | Q27: N/A | R27: N/A | S27: N/A | T27: N/A | U27: N/A | V27: N/A | W27: N/A | X27: N/A | Y27: N/A | Z27: N/A | AB27: ALEXSANDRO BARBOSA PEREIRA | AC27: 46.789.605-7 | AD27: 393.482.118-97 | AE27: PROPRIETÁRIO NÃO RESIDENTE | AF27: CADASTRADO | AG27: 21400 | AH27: 51400 | AI27: SIM | AJ27: 6014.2022/0003993-0 | AK27: FINALIZADO | AL27: FINALIZADO | AM27: FINALIZADO | AN27: SEM PENDÊNCIA | AP27: 6014.2022/0003940-9 | AQ27: FINALIZADO | AR27: FINALIZADO | AS27: FINALIZADO | AT27: FINALIZADO | AU27: 44966 | AV27: FINALIZADO | AW27: FINALIZADO | AX27: 45012 | AY27: 45012 | AZ27: 45035 | BA27: DEMOLIDO | BB27: FINALIZADO | BC27: =IF(AY27-ON27=0,"",AY27-O27) -> 112 | BD27: =IF(AND(AI27<>"SIM",AI27="UH"),"AA","INDENIZAÇÃO") -> INDENIZAÇÃO | BE27: =IF(AND(AY27<>"AGUARDANDO",AY27<>"",N27="AUXÍLIO ALUGUEL ATÉ INDENIZAÇÃO"),"SIM","NÃO") -> NÃO | BF27: N/A | BG27: N/A | BH27: N/A | BI27: FINALIZADO | BJ27: FINALIZADO | BK27: 45190 | BL27: FINALIZADO | BM27: FINALIZADO
A28: 15 | B28: ALFREDO ÁVILA | C28: 1 | D28: 0 | E28: 0 | F28: 001/0010/B | G28: OCUPADO | H28: RESIDENCIAL | I28: INQUILINO | J28: ANTONIO IZAU DOS SANTOS | K28: 38.478.412-4 | L28: 099.702.388-09 | M28: CADASTRADO | N28: AUXÍLIO ALUGUEL UH | O28: 44900 | P28: 44921 | Q28: 6014.2023/0000399-6 | R28: FINALIZADO | S28: FINALIZADO | T28: FINALIZADO | U28: 44992 | V28: FINALIZADO | W28: 44992 | X28: 45019 | Y28: 45019 | Z28: 45034 | AA28: Houve um problema na equipe do pagamento, sendo previsto para 03/04/2023 | AB28: ALEXSANDRO BARBOSA PEREIRA | AC28: 46.789.605-7 | AD28: 393.482.118-97 | AE28: PROPRIETÁRIO NÃO RESIDENTE | AF28: N/A | AG28: 18700 | AH28: 48700 | AI28: RECEBEU INDENIZAÇÃO PELO SELO 001/0010/A | AJ28: 6014.2022/0003993-0 | AK28: N/A | AL28: N/A | AM28: N/A | AN28: N/A | AP28: N/A | AQ28: N/A | AR28: N/A | AS28: N/A | AT28: N/A | AU28: N/A | AV28: N/A | AW28: N/A | AX28: N/A | AY28: N/A | AZ28: 45034 | BA28: DEMOLIDO | BB28: FINALIZADO | BC28: N/A | BD28: =IF(AND(AI28<>"SIM",AI28="UH"),"AA","INDENIZAÇÃO") -> INDENIZAÇÃO | BE28: =IF(AND(AY28<>"AGUARDANDO",AY28<>"",N28="AUXÍLIO ALUGUEL ATÉ INDENIZAÇÃO"),"SIM","NÃO") -> NÃO | BF28: N/A | BG28: N/A | BH28: N/A | BI28: N/A | BJ28: N/A | BK28: N/A | BL28: N/A | BM28: FINALIZADO
A29: 16 | B29: ALFREDO ÁVILA | C29: 1 | D29: 0 | E29: 0 | F29: 001/0011/A | G29: OCUPADO | H29: RESIDENCIAL | I29: INQUILINO | J29: DIVANI MARTINS DO SANTOS | K29: 34.812.789-3 | L29: 272.878.048-08 | M29: CADASTRADO | N29: AUXÍLIO ALUGUEL UH | O29: 44900 | P29: 44921 | Q29: 6014.2023/0000399-6 | R29: FINALIZADO | S29: FINALIZADO | T29: FINALIZADO | U29: 44992 | V29: FINALIZADO | W29: 44992 | X29: 45019 | Y29: 45019 | Z29: 45040 | AA29: Houve um problema na equipe do pagamento, sendo previsto para 03/04/2023 | AB29: IVONE FERREIRA MENDES | AC29: 54.246.610-7 | AD29: 060.155.126-52 | AE29: PROPRIETÁRIO NÃO RESIDENTE | AF29: CADASTRADO | AG29: 35900 | AH29: 60000 | AI29: SIM | AJ29: 6014.2022/0003993-0 | AK29: FINALIZADO | AL29: FINALIZADO | AM29: FINALIZADO | AN29: SEM PENDÊNCIA | AO29: Conta bancaria da Sra. Ivone Ferreira Mendes está ilegível e o termo de chaves está faltando um número no RG. Verificar com Cibele | AP29: 6014.2022/0004134-9 | AQ29: FINALIZADO | AR29: FINALIZADO | AS29: FINALIZADO | AT29: FINALIZADO | AU29: 45014 | AV29: FINALIZADO | AW29: FINALIZADO | AX29: 45022 | AY29: 45022 | AZ29: 45040 | BA29: DEMOLIDO | BB29: FINALIZADO | BC29: =IF(AY29-ON29=0,"",AY29-O29) -> 122 | BD29: =IF(AND(AI29<>"SIM",AI29="UH"),"AA","INDENIZAÇÃO") -> INDENIZAÇÃO | BE29: =IF(AND(AY29<>"AGUARDANDO",AY29<>"",N29="AUXÍLIO ALUGUEL ATÉ INDENIZAÇÃO"),"SIM","NÃO") -> NÃO | BF29: N/A | BG29: N/A | BH29: N/A | BI29: FINALIZADO | BJ29: FINALIZADO | BK29: 45190 | BL29: FINALIZADO | BM29: FINALIZADO
A30: 17 | B30: ALFREDO ÁVILA | C30: 1 | D30: 0 | E30: 0 | F30: 001/0012/A | G30: OCUPADO | H30: RESIDENCIAL | I30: PROPRIETÁRIO RESIDENTE | J30: VITORIA RAFAELA LIMA DA COSTA | K30: 60.076.130-7 | L30: 505.195.648-39 | M30: CADASTRADO | N30: AUXÍLIO ALUGUEL UH | O30: 44900 | P30: 44921 | Q30: 6014.2023/0000399-6 | R30: FINALIZADO | S30: FINALIZADO | T30: FINALIZADO | U30: 44992 | V30: FINALIZADO | W30: 44992 | X30: 45019 | Y30: 45019 | Z30: 45049 | AA30: Houve um problema na equipe do pagamento, sendo previsto para 03/04/2023 | AB30: VITORIA RAFAELA LIMA DA COSTA | AC30: 60.076.130-7 | AD30: 505.195.648-39 | AE30: PROPRIETÁRIO RESIDENTE | AF30: CADASTRADO | AG30: 20500 | AH30: 50500 | AI30: UH | AJ30: 6014.2022/0003993-0 | AK30: FINALIZADO | AL30: N/A | AM30: N/A | AN30: N/A | AP30: N/A | AQ30: N/A | AR30: N/A | AS30: N/A | AT30: N/A | AU30: N/A | AV30: N/A | AW30: N/A | AX30: 45019 | AY30: 45019 | AZ30: 45049 | BA30: DEMOLIDO | BB30: FINALIZADO | BC30: =IF(AY30-ON30=0,"",AY30-O30) -> 119 | BD30: =IF(AND(AI30<>"SIM",AI30="UH"),"AA","INDENIZAÇÃO") -> AA | BE30: =IF(AND(AY30<>"AGUARDANDO",AY30<>"",N30="AUXÍLIO ALUGUEL ATÉ INDENIZAÇÃO"),"SIM","NÃO") -> NÃO | BF30: N/A | BG30: N/A | BH30: N/A | BI30: N/A | BJ30: N/A | BK30: N/A | BL30: N/A | BM30: FINALIZADO
A31: 18 | B31: ALFREDO ÁVILA | C31: 1 | D31: 0 | E31: 0 | F31: 001/0012/B | G31: OCUPADO | H31: RESIDENCIAL | I31: PROPRIETÁRIO RESIDENTE | J31: CLAUDIO FERREIRA DE LIMA | K31: 37.095.609-6 | L31: 533.218.121-34 | M31: CADASTRADO | N31: INDENIZAÇÃO | O31: 44900 | P31: N/A | Q31: N/A | R31: N/A | S31: N/A | T31: N/A | U31: N/A | V31: N/A | W31: N/A | X31: N/A | Y31: N/A | Z31: N/A | AB31: CLAUDIO FERREIRA DE LIMA | AC31: 37.095.609-6 | AD31: 533.218.121-34 | AE31: PROPRIETÁRIO RESIDENTE | AF31: CADASTRADO | AG31: 20700 | AH31: 50700 | AI31: SIM | AJ31: 6014.2022/0003993-0 | AK31: FINALIZADO | AL31: FINALIZADO | AM31: FINALIZADO | AN31: SEM PENDÊNCIA | AP31: 6014.2022/0003941-7 | AQ31: FINALIZADO | AR31: FINALIZADO | AS31: FINALIZADO | AT31: FINALIZADO | AU31: 44966 | AV31: FINALIZADO | AW31: FINALIZADO | AX31: 45012 | AY31: 45012 | AZ31: 45048 | BA31: DEMOLIDO | BB31: FINALIZADO | BC31: =IF(AY31-ON31=0,"",AY31-O31) -> 112 | BD31: =IF(AND(AI31<>"SIM",AI31="UH"),"AA","INDENIZAÇÃO") -> INDENIZAÇÃO | BE31: =IF(AND(AY31<>"AGUARDANDO",AY31<>"",N31="AUXÍLIO ALUGUEL ATÉ INDENIZAÇÃO"),"SIM","NÃO") -> NÃO | BF31: N/A | BG31: N/A | BH31: N/A | BI31: FINALIZADO | BJ31: FINALIZADO | BK31: 45190 | BL31: FINALIZADO | BM31: FINALIZADO
A32: 19 | B32: ALFREDO ÁVILA | C32: 1 | D32: 0 | E32: 0 | F32: 001/0014/A | G32: OCUPADO | H32: RESIDENCIAL | I32: PROPRIETÁRIO RESIDENTE | J32: JAILSON SANTOS SILVA | K32: 34.302.386-6 | L32: 553.313.785-87 | M32: CADASTRADO | N32: INDENIZAÇÃO | O32: 44900 | P32: N/A | Q32: N/A | R32: N/A | S32: N/A | T32: N/A | U32: N/A | V32: N/A | W32: N/A | X32: N/A | Y32: N/A | Z32: N/A | AB32: JAILSON SANTOS SILVA | AC32: 34.302.386-6 | AD32: 553.313.785-87 | AE32: PROPRIETÁRIO RESIDENTE | AF32: CADASTRADO | AG32: 19800 | AH32: 39800 | AI32: SIM | AJ32: 6014.2022/0003993-0 | AK32: FINALIZADO | AL32: FINALIZADO | AM32: FINALIZADO | AN32: SEM PENDÊNCIA | AP32: 6014.2022/0004135-7 | AQ32: FINALIZADO | AR32: FINALIZADO | AS32: FINALIZADO | AT32: FINALIZADO | AU32: 44966 | AV32: FINALIZADO | AW32: FINALIZADO | AX32: 45012 | AY32: 45012 | AZ32: 45042 | BA32: DEMOLIDO | BB32: FINALIZADO | BC32: =IF(AY32-ON32=0,"",AY32-O32) -> 112 | BD32: =IF(AND(AI32<>"SIM",AI32="UH"),"AA","INDENIZAÇÃO") -> INDENIZAÇÃO | BE32: =IF(AND(AY32<>"AGUARDANDO",AY32<>"",N32="AUXÍLIO ALUGUEL ATÉ INDENIZAÇÃO"),"SIM","NÃO") -> NÃO | BF32: N/A | BG32: N/A | BH32: N/A | BI32: FINALIZADO | BJ32: FINALIZADO | BK32: 45190 | BL32: FINALIZADO | BM32: FINALIZADO
A33: 20 | B33: ALFREDO ÁVILA | C33: 1 | D33: 0 | E33: 0 | F33: 001/0017/A | G33: OCUPADO | H33: RESIDENCIAL | I33: PROPRIETÁRIO RESIDENTE | J33: CREUZA ROSA MARQUES | K33: 53.083.084-X | L33: 130.250.141-81 | M33: CADASTRADO | N33: INDENIZAÇÃO | O33: 44900 | P33: N/A | Q33: N/A | R33: N/A | S33: N/A | T33: N/A | U33: N/A | V33: N/A | W33: N/A | X33: N/A | Y33: N/A | Z33: N/A | AB33: CREUZA ROSA MARQUES | AC33: 53.083.084-X | AD33: 130.250.148-81 | AE33: PROPRIETÁRIO RESIDENTE | AF33: CADASTRADO | AG33: 92800 | AH33: 92800 | AI33: SIM | AJ33: 6014.2022/0003993-0 | AK33: FINALIZADO | AL33: FINALIZADO | AM33: FINALIZADO | AN33: SEM PENDÊNCIA | AP33: 6014.2022/0004030-0 | AQ33: FINALIZADO | AR33: FINALIZADO | AS33: FINALIZADO | AT33: FINALIZADO | AU33: 44966 | AV33: FINALIZADO | AW33: FINALIZADO | AX33: 45012 | AY33: 45012 | AZ33: 45040 | BA33: DEMOLIDO | BB33: FINALIZADO | BC33: =IF(AY33-ON33=0,"",AY33-O33) -> 112 | BD33: =IF(AND(AI33<>"SIM",AI33="UH"),"AA","INDENIZAÇÃO") -> INDENIZAÇÃO | BE33: =IF(AND(AY33<>"AGUARDANDO",AY33<>"",N33="AUXÍLIO ALUGUEL ATÉ INDENIZAÇÃO"),"SIM","NÃO") -> NÃO | BF33: N/A | BG33: N/A | BH33: N/A | BI33: FINALIZADO | BJ33: FINALIZADO | BK33: 45190 | BL33: FINALIZADO | BM33: FINALIZADO
A34: 21 | B34: ALFREDO ÁVILA | C34: 1 | D34: 0 | E34: 0 | F34: 001/0017/B | G34: OCUPADO | H34: RESIDENCIAL | I34: PROPRIETÁRIO RESIDENTE | J34: STELA MARQUES DA SILVA | K34: 39.626.761-0 | L34: 402.625.628-63 | M34: CADASTRADO | N34: INDENIZAÇÃO | O34: 44900 | P34: N/A | Q34: N/A | R34: N/A | S34: N/A | T34: N/A | U34: N/A | V34: N/A | W34: N/A | X34: N/A | Y34: N/A | Z34: N/A | AB34: STELA MARQUES DA SILVA | AC34: 39.626.761-0 | AD34: 402.625.628-63 | AE34: PROPRIETÁRIO RESIDENTE | AF34: CADASTRADO | AG34: 49800 | AH34: 60000 | AI34: SIM | AJ34: 6014.2022/0003993-0 | AK34: FINALIZADO | AL34: FINALIZADO | AM34: FINALIZADO | AN34: SEM PENDÊNCIA | AP34: 6014.2022/0004136-5 | AQ34: FINALIZADO | AR34: FINALIZADO | AS34: FINALIZADO | AT34: FINALIZADO | AU34: 44966 | AV34: FINALIZADO | AW34: FINALIZADO | AX34: 45012 | AY34: 45012 | AZ34: 45040 | BA34: DEMOLIDO | BB34: FINALIZADO | BC34: =IF(AY34-ON34=0,"",AY34-O34) -> 112 | BD34: =IF(AND(AI34<>"SIM",AI34="UH"),"AA","INDENIZAÇÃO") -> INDENIZAÇÃO | BE34: =IF(AND(AY34<>"AGUARDANDO",AY34<>"",N34="AUXÍLIO ALUGUEL ATÉ INDENIZAÇÃO"),"SIM","NÃO") -> NÃO | BF34: N/A | BG34: N/A | BH34: N/A | BI34: FINALIZADO | BJ34: FINALIZADO | BK34: 45190 | BL34: FINALIZADO | BM34: FINALIZADO
A35: 22 | B35: ALFREDO ÁVILA | C35: 1 | D35: 0 | E35: 0 | F35: 001/0019/A | G35: OCUPADO | H35: RESIDENCIAL | I35: PROPRIETÁRIO RESIDENTE | J35: SUELI GOMES DE SOUZA | K35: 19.370.643-X | L35: 087.913.138-13 | M35: CADASTRADO | N35: INDENIZAÇÃO | O35: 45065 | P35: N/A | Q35: N/A | R35: N/A | S35: N/A | T35: N/A | U35: N/A | V35: N/A | W35: N/A | X35: N/A | Y35: N/A | Z35: N/A | AB35: SUELI GOMES DE SOUZA | AC35: 19.370.643-X | AD35: 087.913.138-13 | AE35: PROPRIETÁRIO RESIDENTE | AF35: N/A | AG35: 0 | AH35: 60000 | AI35: RECEBEU INDENIZAÇÃO PELO SELO 001/0019/B | AJ35: 6014.2022/0003993-0 | AK35: N/A | AL35: N/A | AM35: N/A | AN35: N/A | AP35: N/A | AQ35: N/A | AR35: N/A | AS35: N/A | AT35: N/A | AU35: N/A | AV35: N/A | AW35: N/A | AX35: N/A | AY35: N/A | AZ35: AGUARDANDO | BA35: DEMOLIDO | BB35: FINALIZADO | BC35: N/A | BD35: =IF(AND(AI35<>"SIM",AI35="UH"),"AA","INDENIZAÇÃO") -> INDENIZAÇÃO | BE35: =IF(AND(AY35<>"AGUARDANDO",AY35<>"",N35="AUXÍLIO ALUGUEL ATÉ INDENIZAÇÃO"),"SIM","NÃO") -> NÃO | BF35: N/A | BG35: N/A | BH35: N/A | BI35: N/A | BJ35: N/A | BK35: N/A | BL35: N/A | BM35: FINALIZADO
A36: 23 | B36: ALFREDO ÁVILA | C36: 1 | D36: 0 | E36: 0 | F36: 001/0019/B | G36: OCUPADO | H36: RESIDENCIAL | I36: INQUILINO | J36: LUCAS DANIEL GOMES PEREIRA | K36: 52.281.364-1 | L36: 439.284.308-40 | M36: CADASTRADO | N36: AUXÍLIO ALUGUEL UH | O36: 44900 | P36: 44921 | Q36: 6014.2023/0000399-6 | R36: FINALIZADO | S36: FINALIZADO | T36: FINALIZADO | U36: 45128 | V36: 45135 | W36: 45135 | X36: 45160 | Y36: 45160 | Z36: 45180 | AB36: SUELI GOMES DE SOUZA | AC36: 19.370.643-X | AD36: 087.913.138-13 | AE36: PROPRIETÁRIO NÃO RESIDENTE | AF36: CADASTRADO | AG36: 110600 | AH36: 110600 | AI36: SIM | AJ36: 6014.2022/0003993-0 | AK36: FINALIZADO | AL36: FINALIZADO | AM36: FINALIZADO | AN36: SEM PENDÊNCIA | AP36: 6014.2023/0002325-3 | AQ36: FINALIZADO | AR36: FINALIZADO | AS36: FINALIZADO | AT36: FINALIZADO | AU36: 45146 | AV36: FINALIZADO | AW36: FINALIZADO | AX36: 45153 | AY36: 45153 | AZ36: 45179 | BA36: DEMOLIDO | BB36: FINALIZADO | BC36: =IF(AY36-ON36=0,"",AY36-O36) -> 253 | BD36: =IF(AND(AI36<>"SIM",AI36="UH"),"AA","INDENIZAÇÃO") -> INDENIZAÇÃO | BE36: =IF(AND(AY36<>"AGUARDANDO",AY36<>"",N36="AUXÍLIO ALUGUEL ATÉ INDENIZAÇÃO"),"SIM","NÃO") -> NÃO | BF36: N/A | BG36: N/A | BH36: N/A | BI36: FINALIZADO | BJ36: FINALIZADO | BK36: 45310 | BL36: FINALIZADO | BM36: FINALIZADO
A37: 24 | B37: ALFREDO ÁVILA | C37: 1 | D37: 0 | E37: 0 | F37: 001/0024/A | G37: OCUPADO | H37: RESIDENCIAL | I37: INQUILINO | J37: GLEDY MARISE DOS SANTOS ROSA | K37: 30.557.844-3 | L37: 301.750.188-47 | M37: CADASTRADO | N37: AUXÍLIO ALUGUEL UH | O37: 44900 | P37: 44921 | Q37: 6014.2023/0000399-6 | R37: FINALIZADO | S37: FINALIZADO | T37: FINALIZADO | U37: 45128 | V37: 45135 | W37: 45135 | X37: 45191 | Y37: 45194 | Z37: 45209 | AB37: CALINE DOS SANTOS CONVENTO | AC37: 43.781.566-3 | AD37: 229.019.538-32 | AE37: PROPRIETÁRIO NÃO RESIDENTE | AF37: CADASTRADO | AG37: 49000 | AH37: 60000 | AI37: SIM | AJ37: 6014.2022/0003993-0 | AK37: FINALIZADO | AL37: FINALIZADO | AM37: FINALIZADO | AN37: SEM PENDÊNCIA | AP37: 6014.2023/0001998-1 | AQ37: FINALIZADO | AR37: FINALIZADO | AS37: FINALIZADO | AT37: FINALIZADO | AU37: 45114 | AV37: FINALIZADO | AW37: FINALIZADO | AX37: 45152 | AY37: 45152 | AZ37: 45209 | BA37: DEMOLIDO | BB37: FINALIZADO | BC37: =IF(AY37-ON37=0,"",AY37-O37) -> 252 | BD37: =IF(AND(AI37<>"SIM",AI37="UH"),"AA","INDENIZAÇÃO") -> INDENIZAÇÃO | BE37: =IF(AND(AY37<>"AGUARDANDO",AY37<>"",N37="AUXÍLIO ALUGUEL ATÉ INDENIZAÇÃO"),"SIM","NÃO") -> NÃO | BF37: N/A | BG37: N/A | BH37: N/A | BI37: FINALIZADO | BJ37: FINALIZADO | BK37: 45246 | BL37: FINALIZADO | BM37: FINALIZADO
A38: 25 | B38: ALFREDO ÁVILA | C38: 1 | D38: 0 | E38: 0 | F38: 001/0025/A | G38: OCUPADO | H38: RESIDENCIAL | I38: INQUILINO | J38: RUANA PORTILLA | K38: 50.384.970-4 | L38: 461.003.518-97 | M38: CADASTRADO | N38: AUXÍLIO ALUGUEL UH | O38: 44900 | P38: 44921 | Q38: 6014.2023/0000399-6 | R38: FINALIZADO | S38: FINALIZADO | T38: FINALIZADO | U38: 44992 | V38: FINALIZADO | W38: 44992 | X38: 45019 | Y38: NÃO SACOU | Z38: 45127 | AA38: Equipe social não consegue entrar em contato para entregar o termo do cartão. AA Bloqueado | AB38: DANILO AUGUSTO DA SILVA SANTOS | AC38: 49.188.880-6 | AD38: 439.612.578-09 | AE38: PROPRIETÁRIO NÃO RESIDENTE | AF38: CADASTRADO | AG38: 46500 | AH38: 60000 | AI38: SIM | AJ38: 6014.2022/0003993-0 | AK38: FINALIZADO | AL38: FINALIZADO | AM38: FINALIZADO | AN38: SEM PENDÊNCIA | AP38: 6014.2022/0004083-0 | AQ38: FINALIZADO | AR38: FINALIZADO | AS38: FINALIZADO | AT38: FINALIZADO | AU38: 45014 | AV38: FINALIZADO | AW38: FINALIZADO | AX38: 45022 | AY38: 45022 | AZ38: 45134 | BA38: DEMOLIDO | BB38: FINALIZADO | BC38: =IF(AY38-ON38=0,"",AY38-O38) -> 122 | BD38: =IF(AND(AI38<>"SIM",AI38="UH"),"AA","INDENIZAÇÃO") -> INDENIZAÇÃO | BE38: =IF(AND(AY38<>"AGUARDANDO",AY38<>"",N38="AUXÍLIO ALUGUEL ATÉ INDENIZAÇÃO"),"SIM","NÃO") -> NÃO | BF38: N/A | BG38: N/A | BH38: N/A | BI38: FINALIZADO | BJ38: FINALIZADO | BK38: 45190 | BL38: FINALIZADO | BM38: FINALIZADO
A39: 26 | B39: ALFREDO ÁVILA | C39: 1 | D39: 0 | E39: 0 | F39: 001/0025/B | G39: OCUPADO | H39: RESIDENCIAL | I39: PROPRIETÁRIO RESIDENTE | J39: CARLOS ROBERTO BATISTA DE SOUZA | K39: 27.245.037-6 | L39: 564.518.226-04 | M39: CADASTRADO | N39: INDENIZAÇÃO | O39: 44900 | P39: N/A | Q39: N/A | R39: N/A | S39: N/A | T39: N/A | U39: N/A | V39: N/A | W39: N/A | X39: N/A | Y39: N/A | Z39: N/A | AB39: CARLOS ROBERTO BATISTA DE SOUZA | AC39: 27.245.037-6 | AD39: 564.518.226-04 | AE39: PROPRIETÁRIO RESIDENTE | AF39: CADASTRADO | AG39: 48100 | AH39: 60000 | AI39: SIM | AJ39: 6014.2022/0003993-0 | AK39: FINALIZADO | AL39: FINALIZADO | AM39: FINALIZADO | AN39: SEM PENDÊNCIA | AP39: 6014.2022/0004137-3 | AQ39: FINALIZADO | AR39: FINALIZADO | AS39: FINALIZADO | AT39: FINALIZADO | AU39: 44966 | AV39: FINALIZADO | AW39: FINALIZADO | AX39: 45012 | AY39: 45012 | AZ39: 45127 | BA39: DEMOLIDO | BB39: FINALIZADO | BC39: =IF(AY39-ON39=0,"",AY39-O39) -> 112 | BD39: =IF(AND(AI39<>"SIM",AI39="UH"),"AA","INDENIZAÇÃO") -> INDENIZAÇÃO | BE39: =IF(AND(AY39<>"AGUARDANDO",AY39<>"",N39="AUXÍLIO ALUGUEL ATÉ INDENIZAÇÃO"),"SIM","NÃO") -> NÃO | BF39: N/A | BG39: N/A | BH39: N/A | BI39: FINALIZADO | BJ39: FINALIZADO | BK39: 45190 | BL39: FINALIZADO | BM39: FINALIZADO
A40: 27 | B40: ALFREDO ÁVILA | C40: 1 | D40: 0 | E40: 0 | F40: 001/0026/A | G40: OCUPADO | H40: RESIDENCIAL | I40: PROPRIETÁRIO RESIDENTE | J40: RENATA RODRIGUES DA SILVA | K40: 39.316.490-1 | L40: 371.973.748-98 | M40: CADASTRADO | N40: INDENIZAÇÃO | O40: 44900 | P40: N/A | Q40: N/A | R40: N/A | S40: N/A | T40: N/A | U40: N/A | V40: N/A | W40: N/A | X40: N/A | Y40: N/A | Z40: N/A | AB40: RENATA RODRIGUES DA SILVA | AC40: 39.316.490-1 | AD40: 371.973.748-98 | AE40: PROPRIETÁRIO RESIDENTE | AF40: CADASTRADO | AG40: 27500 | AH40: 57500 | AI40: SIM | AJ40: 6014.2022/0003993-0 | AK40: FINALIZADO | AL40: FINALIZADO | AM40: FINALIZADO | AN40: SEM PENDÊNCIA | AP40: 6014.2022/0004081-4 | AQ40: FINALIZADO | AR40: FINALIZADO | AS40: FINALIZADO | AT40: FINALIZADO | AU40: 44966 | AV40: FINALIZADO | AW40: FINALIZADO | AX40: 45012 | AY40: 45012 | AZ40: 45063 | BA40: DEMOLIDO | BB40: FINALIZADO | BC40: =IF(AY40-ON40=0,"",AY40-O40) -> 112 | BD40: =IF(AND(AI40<>"SIM",AI40="UH"),"AA","INDENIZAÇÃO") -> INDENIZAÇÃO | BE40: =IF(AND(AY40<>"AGUARDANDO",AY40<>"",N40="AUXÍLIO ALUGUEL ATÉ INDENIZAÇÃO"),"SIM","NÃO") -> NÃO | BF40: N/A | BG40: N/A | BH40: N/A | BI40: FINALIZADO | BJ40: FINALIZADO | BK40: 45190 | BL40: FINALIZADO | BM40: FINALIZADO
A41: 28 | B41: ALFREDO ÁVILA | C41: 1 | D41: 0 | E41: 0 | F41: 001/0026/B | G41: OCUPADO | H41: RESIDENCIAL | I41: INQUILINO | J41: LAIS DA SILVA PEREIRA | K41: 57.273.865-1 | L41: 495.928.678-44 | M41: CADASTRADO | N41: AUXÍLIO ALUGUEL UH | O41: 44900 | P41: 44921 | Q41: 6014.2023/0000399-6 | R41: FINALIZADO | S41: FINALIZADO | T41: FINALIZADO | U41: 44992 | V41: FINALIZADO | W41: 44992 | X41: 45019 | Y41: 45020 | Z41: 45063 | AA41: Houve um problema na equipe do pagamento, sendo previsto para 03/04/2023 | AB41: GERINALDO RIBEIRO BARBOSA | AC41: 32.770.534-6 | AD41: 873.034.935-49 | AE41: PROPRIETÁRIO NÃO RESIDENTE | AF41: CADASTRADO | AG41: 0 | AH41: 60000 | AI41: RECEBEU INDENIZAÇÃO PELO SELO 001/0026/C | AJ41: 6014.2022/0003993-0 | AK41: FINALIZADO | AL41: N/A | AM41: N/A | AN41: N/A | AO41: MUNÍCIPE RECEBEU INDENIZAÇÃO PELO SELO 001/0026/C | AP41: N/A | AQ41: N/A | AR41: N/A | AS41: N/A | AT41: N/A | AU41: N/A | AV41: N/A | AW41: N/A | AX41: N/A | AY41: N/A | AZ41: 45063 | BA41: DEMOLIDO | BB41: FINALIZADO | BC41: =IF(AY41-ON41=0,"",AY41-O41) -> #VALUE! | BD41: =IF(AND(AI41<>"SIM",AI41="UH"),"AA","INDENIZAÇÃO") -> INDENIZAÇÃO | BE41: =IF(AND(AY41<>"AGUARDANDO",AY41<>"",N41="AUXÍLIO ALUGUEL ATÉ INDENIZAÇÃO"),"SIM","NÃO") -> NÃO
A42: 29 | B42: ALFREDO ÁVILA | C42: 1 | D42: 0 | E42: 0 | F42: 001/0026/C | G42: OCUPADO | H42: RESIDENCIAL | I42: INQUILINO | J42: MARILUCE DA SILVA | K42: 37.373.261-2 | L42: 271.024.958-89 | M42: CADASTRADO | N42: AUXÍLIO ALUGUEL UH | O42: 44900 | P42: 45081 | Q42: 6014.2023/0000399-6 | R42: FINALIZADO | S42: FINALIZADO | T42: FINALIZADO | U42: 02-mai-23 | V42: FINALIZADO | W42: 05-mai-23 | X42: 22-mai-23 | Y42: 23-mai-23 | Z42: 45063 | AB42: GERINALDO RIBEIRO BARBOSA | AC42: 32.770.534-6 | AD42: 873.034.935-49 | AE42: PROPRIETÁRIO NÃO RESIDENTE | AF42: CADASTRADO | AG42: 38000 | AH42: 60000 | AI42: SIM | AJ42: 6014.2022/0003993-0 | AK42: FINALIZADO | AL42: FINALIZADO | AM42: FINALIZADO | AN42: SEM PENDÊNCIA | AP42: 6014.2022/0004138-1 | AQ42: FINALIZADO | AR42: FINALIZADO | AS42: FINALIZADO | AT42: FINALIZADO | AU42: 45016 | AV42: FINALIZADO | AW42: FINALIZADO | AX42: 45022 | AY42: 45022 | AZ42: 45063 | BA42: DEMOLIDO | BB42: FINALIZADO | BC42: =IF(AY42-ON42=0,"",AY42-O42) -> 122 | BD42: =IF(AND(AI42<>"SIM",AI42="UH"),"AA","INDENIZAÇÃO") -> INDENIZAÇÃO | BE42: =IF(AND(AY42<>"AGUARDANDO",AY42<>"",N42="AUXÍLIO ALUGUEL ATÉ INDENIZAÇÃO"),"SIM","NÃO") -> NÃO | BF42: N/A | BG42: N/A | BH42: N/A | BI42: FINALIZADO | BJ42: FINALIZADO | BK42: 45190 | BL42: FINALIZADO | BM42: FINALIZADO
A43: 30 | B43: ALFREDO ÁVILA | C43: 1 | D43: 0 | E43: 0 | F43: 001/0027/A | G43: OCUPADO | H43: RESIDENCIAL | I43: PROPRIETÁRIO RESIDENTE | J43: JOSIELE DE OLIVEIRA SILVA | K43: 47.114.574-9 | L43: 388.201.958-10 | M43: CADASTRADO | N43: INDENIZAÇÃO | O43: 44900 | P43: N/A | Q43: N/A | R43: N/A | S43: N/A | T43: N/A | U43: N/A | V43: N/A | W43: N/A | X43: N/A | Y43: N/A | Z43: N/A | AB43: JOSIELE DE OLIVEIRA SILVA | AC43: 47.114.574-9 | AD43: 388.201.958-10 | AE43: PROPRIETÁRIO RESIDENTE | AF43: CADASTRADO | AG43: 37500 | AH43: 60000 | AI43: SIM | AJ43: 6014.2022/0003993-0 | AK43: FINALIZADO | AL43: FINALIZADO | AM43: FINALIZADO | AN43: SEM PENDÊNCIA | AP43: 6014.2022/0004029-6 | AQ43: FINALIZADO | AR43: FINALIZADO | AS43: FINALIZADO | AT43: FINALIZADO | AU43: 44922 | AV43: FINALIZADO | AW43: FINALIZADO | AX43: 44924 | AY43: 44924 | AZ43: 44936 | BA43: DEMOLIDO | BB43: FINALIZADO | BC43: =IF(AY43-ON43=0,"",AY43-O43) -> 24 | BD43: =IF(AND(AI43<>"SIM",AI43="UH"),"AA","INDENIZAÇÃO") -> INDENIZAÇÃO | BE43: =IF(AND(AY43<>"AGUARDANDO",AY43<>"",N43="AUXÍLIO ALUGUEL ATÉ INDENIZAÇÃO"),"SIM","NÃO") -> NÃO | BF43: N/A | BG43: N/A | BH43: N/A | BI43: FINALIZADO | BJ43: FINALIZADO | BK43: 45057 | BL43: FINALIZADO | BM43: FINALIZADO
A44: 31 | B44: ALFREDO ÁVILA | C44: 1 | D44: 0 | E44: 0 | F44: 001/0028/A | G44: OCUPADO | H44: RESIDENCIAL | I44: PROPRIETÁRIO RESIDENTE | J44: THAIS DE OLIVEIRA SILVA FERREIRA | K44: 34.615.609-9 | L44: 387.066.978-01 | M44: CADASTRADO | N44: AUXÍLIO ALUGUEL UH | O44: 44900 | P44: 44921 | Q44: 6014.2023/0000399-6 | R44: FINALIZADO | S44: FINALIZADO | T44: FINALIZADO | U44: 44992 | V44: FINALIZADO | W44: 44992 | X44: 45019 | Y44: 45019 | Z44: 45063 | AA44: Houve um problema na equipe do pagamento, sendo previsto para 03/04/2023 | AB44: THAIS DE OLIVEIRA SILVA FERREIRA | AC44: 34.615.609-9 | AD44: 387.066.978-01 | AE44: PROPRIETÁRIO RESIDENTE | AF44: CADASTRADO | AG44: 31100 | AH44: 60000 | AI44: UH | AJ44: 6014.2022/0003993-0 | AK44: FINALIZADO | AL44: N/A | AM44: N/A | AN44: N/A | AP44: N/A | AQ44: N/A | AR44: N/A | AS44: N/A | AT44: N/A | AU44: N/A | AV44: N/A | AW44: N/A | AX44: 45019 | AY44: 45019 | AZ44: 45063 | BA44: DEMOLIDO | BB44: FINALIZADO | BC44: =IF(AY44-ON44=0,"",AY44-O44) -> 119 | BD44: =IF(AND(AI44<>"SIM",AI44="UH"),"AA","INDENIZAÇÃO") -> AA | BE44: =IF(AND(AY44<>"AGUARDANDO",AY44<>"",N44="AUXÍLIO ALUGUEL ATÉ INDENIZAÇÃO"),"SIM","NÃO") -> NÃO | BF44: N/A | BG44: N/A | BH44: N/A | BI44: N/A | BJ44: N/A | BK44: N/A | BL44: N/A | BM44: FINALIZADO
A45: 32 | B45: ALFREDO ÁVILA | C45: 1 | D45: 0 | E45: 0 | F45: 001/0029/A | G45: OCUPADO | H45: RESIDENCIAL | I45: PROPRIETÁRIO RESIDENTE | J45: FRANCISCO DA CRUZ NANTES | K45: 21.271.587-2 | L45: 383.527.615-87 | M45: CADASTRADO | N45: AUXÍLIO ALUGUEL UH | O45: 44900 | P45: 44921 | Q45: 6014.2023/0000399-6 | R45: FINALIZADO | S45: FINALIZADO | T45: FINALIZADO | U45: 44992 | V45: FINALIZADO | W45: 44992 | X45: 45019 | Y45: 45019 | Z45: 45063 | AA45: Houve um problema na equipe do pagamento, sendo previsto para 03/04/2023 | AB45: FRANCISCO DA CRUZ NANTES | AC45: 21.271.587-2 | AD45: 383.527.615-87 | AE45: PROPRIETÁRIO RESIDENTE | AF45: CADASTRADO | AG45: 3400 | AH45: 33400 | AI45: UH | AJ45: 6014.2022/0003993-0 | AK45: FINALIZADO | AL45: N/A | AM45: N/A | AN45: N/A | AP45: N/A | AQ45: N/A | AR45: N/A | AS45: N/A | AT45: N/A | AU45: N/A | AV45: N/A | AW45: N/A | AX45: 45019 | AY45: 45019 | AZ45: 45063 | BA45: DEMOLIDO | BB45: FINALIZADO | BC45: =IF(AY45-ON45=0,"",AY45-O45) -> 119 | BD45: =IF(AND(AI45<>"SIM",AI45="UH"),"AA","INDENIZAÇÃO") -> AA | BE45: =IF(AND(AY45<>"AGUARDANDO",AY45<>"",N45="AUXÍLIO ALUGUEL ATÉ INDENIZAÇÃO"),"SIM","NÃO") -> NÃO | BF45: N/A | BG45: N/A | BH45: N/A | BI45: N/A | BJ45: N/A | BK45: N/A | BL45: N/A | BM45: FINALIZADO
A46: 33 | B46: ALFREDO ÁVILA | C46: 1 | D46: 0 | E46: 0 | F46: 001/0029/B | G46: OCUPADO | H46: RESIDENCIAL | I46: INQUILINO | J46: JULIO CESAR DOS SANTOS | K46: 53.036.759-2 | L46: 425.874.268-63 | M46: CADASTRADO | N46: AUXÍLIO ALUGUEL UH | O46: 44900 | P46: 44921 | Q46: 6014.2023/0000399-6 | R46: FINALIZADO | S46: FINALIZADO | T46: FINALIZADO | U46: 44992 | V46: FINALIZADO | W46: 44992 | X46: 45019 | Y46: 45019 | Z46: 45063 | AA46: Houve um problema na equipe do pagamento, sendo previsto para 03/04/2023 | AB46: FRANCISCO DA CRUZ NANTES | AC46: 21.271.587-2 | AD46: 383.527.615-87 | AE46: PROPRIETÁRIO NÃO RESIDENTE | AF46: N/A | AG46: 34900 | AH46: 60000 | AI46: PROPRIETÁRIO DOS SELOS 001/0029/A, 001/0029/B E 001/0029/C, OPTOU POR UH | AJ46: 6014.2022/0003993-0 | AK46: N/A | AL46: N/A | AM46: N/A | AN46: N/A | AP46: N/A | AQ46: N/A | AR46: N/A | AS46: N/A | AT46: N/A | AU46: N/A | AV46: N/A | AW46: N/A | AX46: N/A | AY46: N/A | AZ46: 45063 | BA46: DEMOLIDO | BB46: FINALIZADO | BC46: N/A | BD46: =IF(AND(AI46<>"SIM",AI46="UH"),"AA","INDENIZAÇÃO") -> INDENIZAÇÃO | BE46: =IF(AND(AY46<>"AGUARDANDO",AY46<>"",N46="AUXÍLIO ALUGUEL ATÉ INDENIZAÇÃO"),"SIM","NÃO") -> NÃO | BF46: N/A | BG46: N/A | BH46: N/A | BI46: N/A | BJ46: N/A | BK46: N/A | BL46: N/A | BM46: FINALIZADO
A47: 34 | B47: ALFREDO ÁVILA | C47: 1 | D47: 0 | E47: 0 | F47: 001/0029/C | G47: OCUPADO | H47: RESIDENCIAL | I47: INQUILINO | J47: NIVANILDA RISALVA DA SILVA | K47: 62.212.140-6 | L47: 111.222.474-27 | M47: CADASTRADO | N47: AUXÍLIO ALUGUEL UH | O47: 44900 | P47: 44921 | Q47: 6014.2023/0000399-6 | R47: FINALIZADO | S47: FINALIZADO | T47: FINALIZADO | U47: 44992 | V47: FINALIZADO | W47: 44992 | X47: 45019 | Y47: 45019 | Z47: 45063 | AA47: Houve um problema na equipe do pagamento, sendo previsto para 03/04/2023 | AB47: FRANCISCO DA CRUZ NANTES | AC47: 21.271.587-2 | AD47: 383.527.615-87 | AE47: PROPRIETÁRIO NÃO RESIDENTE | AF47: N/A | AG47: 20300 | AH47: 50300 | AI47: PROPRIETÁRIO DOS SELOS 001/0029/A, 001/0029/B E 001/0029/C, OPTOU POR UH | AJ47: 6014.2022/0003993-0 | AK47: N/A | AL47: N/A | AM47: N/A | AN47: N/A | AP47: N/A | AQ47: N/A | AR47: N/A | AS47: N/A | AT47: N/A | AU47: N/A | AV47: N/A | AW47: N/A | AX47: N/A | AY47: N/A | AZ47: 45063 | BA47: DEMOLIDO | BB47: FINALIZADO | BC47: N/A | BD47: =IF(AND(AI47<>"SIM",AI47="UH"),"AA","INDENIZAÇÃO") -> INDENIZAÇÃO | BE47: =IF(AND(AY47<>"AGUARDANDO",AY47<>"",N47="AUXÍLIO ALUGUEL ATÉ INDENIZAÇÃO"),"SIM","NÃO") -> NÃO | BF47: N/A | BG47: N/A | BH47: N/A | BI47: N/A | BJ47: N/A | BK47: N/A | BL47: N/A | BM47: FINALIZADO
A48: 35 | B48: ALFREDO ÁVILA | C48: 1 | D48: 0 | E48: 0 | F48: 001/0030/A | G48: EM CONSTRUÇÃO | H48: RESIDENCIAL | I48: N/A | M48: CADASTRADO | N48: INDENIZAÇÃO | O48: 44900 | P48: N/A | AB48: AMANDA OLIVEIRA DE ARAUJO | AC48: 43.521.928-5 | AD48: 435.738.668-32 | AE48: PROPRIETÁRIO NÃO RESIDENTE | AF48: CADASTRADO | AG48: 8500 | AH48: 38500 | AI48: SIM | AJ48: 6014.2022/0003993-0 | AK48: FINALIZADO | AL48: FINALIZADO | AM48: FINALIZADO | AN48: SEM PENDÊNCIA | AP48: 6014.2022/0004027-0 | AQ48: FINALIZADO | AR48: FINALIZADO | AS48: FINALIZADO | AT48: FINALIZADO | AU48: 44922 | AV48: FINALIZADO | AW48: FINALIZADO | AX48: 44924 | AY48: 44924 | AZ48: 44936 | BA48: DEMOLIDO | BB48: FINALIZADO | BC48: =IF(AY48-ON48=0,"",AY48-O48) -> 24 | BD48: =IF(AND(AI48<>"SIM",AI48="UH"),"AA","INDENIZAÇÃO") -> INDENIZAÇÃO | BE48: =IF(AND(AY48<>"AGUARDANDO",AY48<>"",N48="AUXÍLIO ALUGUEL ATÉ INDENIZAÇÃO"),"SIM","NÃO") -> NÃO | BF48: N/A | BG48: N/A | BH48: N/A | BI48: FINALIZADO | BJ48: FINALIZADO | BK48: 45057 | BL48: FINALIZADO | BM48: FINALIZADO
A49: 36 | B49: ALFREDO ÁVILA | C49: 1 | D49: 0 | E49: 0 | F49: 001/0031/A | G49: OCUPADO | H49: RESIDENCIAL | I49: INQUILINO | J49: VANESSA CRISTINA PEREIRA DE SOUZA | K49: 44.357.626-9 | L49: 337.076.398-27 | M49: CADASTRADO | N49: AUXÍLIO ALUGUEL UH | O49: 44900 | P49: 45081 | Q49: 6014.2023/0000399-6 | R49: FINALIZADO | S49: FINALIZADO | T49: FINALIZADO | U49: 02-mai-23 | V49: FINALIZADO | W49: 03-mai-23 | X49: 22-mai-23 | Y49: 22-mai-23 | Z49: 45099 | AB49: DIOGO SILVA BENTO | AC49: 29.766.411-6 | AD49: 334.043.458-19 | AE49: PROPRIETÁRIO NÃO RESIDENTE | AF49: CADASTRADO | AG49: 33500 | AH49: 60000 | AI49: SIM | AJ49: 6014.2022/0003993-0 | AK49: FINALIZADO | AL49: FINALIZADO | AM49: FINALIZADO | AN49: SEM PENDÊNCIA | AP49: 6014.2023/0004452-8 | AQ49: FINALIZADO | AR49: FINALIZADO | AS49: FINALIZADO | AT49: FINALIZADO | AU49: 45351 | AV49: FINALIZADO | AW49: FINALIZADO | AX49: 45372 | AY49: 45372 | AZ49: 45099 | BA49: DEMOLIDO | BB49: FINALIZADO | BC49: =IF(AY49-ON49=0,"",AY49-O49) -> 472 | BD49: =IF(AND(AI49<>"SIM",AI49="UH"),"AA","INDENIZAÇÃO") -> INDENIZAÇÃO | BE49: =IF(AND(AY49<>"AGUARDANDO",AY49<>"",N49="AUXÍLIO ALUGUEL ATÉ INDENIZAÇÃO"),"SIM","NÃO") -> NÃO | BF49: N/A | BG49: N/A | BH49: N/A | BI49: FINALIZADO | BJ49: FINALIZADO | BK49: 45510 | BL49: FINALIZADO | BM49: AGUARDANDO
A50: 37 | B50: ALFREDO ÁVILA | C50: 1 | D50: 0 | E50: 0 | F50: 001/0032/A | G50: OCUPADO | H50: RESIDENCIAL | I50: INQUILINO | J50: DEBORAH SALLES DA SILVA | K50: 25.769.760-3 | L50: 215.312.868-44 | M50: CADASTRADO | N50: NÃO TEM ATENDIMENTO | O50: 44900 | P50: 44921 | Q50: 6014.2023/0000399-6 | R50: N/A | S50: N/A | T50: N/A | U50: N/A | V50: N/A | W50: N/A | X50: N/A | Y50: N/A | Z50: 45128 | AA50: RENDA SUPERIOR PARA RECEBER AUXÍLIO ALUGUEL | AB50: LÚCIA JERONYMA SALLES | AC50: 36973178 | AD50: 040.770.428-01 | AE50: PROPRIETÁRIO NÃO RESIDENTE | AF50: CADASTRADO | AG50: 0 | AH50: 60000 | AI50: SIM | AJ50: 6014.2022/0003993-0 | AK50: FINALIZADO | AL50: FINALIZADO | AM50: FINALIZADO | AN50: SEM PENDÊNCIA | AP50: 6014.2022/0004031-8 | AQ50: FINALIZADO | AR50: FINALIZADO | AS50: FINALIZADO | AT50: FINALIZADO | AU50: 44922 | AV50: FINALIZADO | AW50: FINALIZADO | AX50: 45013 | AY50: 45013 | AZ50: 45128 | BA50: DEMOLIDO | BB50: FINALIZADO | BC50: =IF(AY50-ON50=0,"",AY50-O50) -> 113 | BD50: =IF(AND(AI50<>"SIM",AI50="UH"),"AA","INDENIZAÇÃO") -> INDENIZAÇÃO | BE50: =IF(AND(AY50<>"AGUARDANDO",AY50<>"",N50="AUXÍLIO ALUGUEL ATÉ INDENIZAÇÃO"),"SIM","NÃO") -> NÃO | BF50: N/A | BG50: N/A | BH50: N/A | BI50: FINALIZADO | BJ50: FINALIZADO | BK50: 45190 | BL50: FINALIZADO | BM50: FINALIZADO
A51: 38 | B51: ALFREDO ÁVILA | C51: 1 | D51: 0 | E51: 0 | F51: 001/0032/B | G51: OCUPADO | H51: RESIDENCIAL | I51: INQUILINO | J51: NATIELE BARBOSA SOUZA | K51: 59.909.486-2 | L51: 075.602.185-55 | M51: CADASTRADO | N51: AUXÍLIO ALUGUEL UH | O51: 44900 | P51: 44921 | Q51: 6014.2023/0000399-6 | R51: FINALIZADO | S51: FINALIZADO | T51: FINALIZADO | U51: 44992 | V51: FINALIZADO | W51: 44992 | X51: 45019 | Y51: 45020 | Z51: 45128 | AA51: Houve um problema na equipe do pagamento, sendo previsto para 03/04/2023 | AB51: ADRIANA FERREIRA MARQUES | AC51: 38.775.449-0 | AD51: 382.605.788-08 | AE51: PROPRIETÁRIO NÃO RESIDENTE | AF51: CADASTRADO | AG51: 53700 | AH51: 60000 | AI51: SIM | AJ51: 6014.2022/0003993-0 | AK51: FINALIZADO | AL51: FINALIZADO | AM51: FINALIZADO | AN51: SEM PENDÊNCIA | AP51: 6014.2023/0000025-3 | AQ51: FINALIZADO | AR51: FINALIZADO | AS51: FINALIZADO | AT51: FINALIZADO | AU51: 44966 | AV51: FINALIZADO | AW51: FINALIZADO | AX51: 45020 | AY51: 45020 | AZ51: 45128 | BA51: DEMOLIDO | BB51: FINALIZADO | BC51: =IF(AY51-ON51=0,"",AY51-O51) -> 120 | BD51: =IF(AND(AI51<>"SIM",AI51="UH"),"AA","INDENIZAÇÃO") -> INDENIZAÇÃO | BE51: =IF(AND(AY51<>"AGUARDANDO",AY51<>"",N51="AUXÍLIO ALUGUEL ATÉ INDENIZAÇÃO"),"SIM","NÃO") -> NÃO | BF51: N/A | BG51: N/A | BH51: N/A | BI51: FINALIZADO | BJ51: FINALIZADO | BK51: 45190 | BL51: FINALIZADO | BM51: FINALIZADO
A52: 39 | B52: ALFREDO ÁVILA | C52: 1 | D52: 0 | E52: 0 | F52: 001/0032/C | G52: OCUPADO | H52: RESIDENCIAL | I52: INQUILINO | J52: JOÃO GABRIEL PEREIRA SORIANO | K52: 38.643.918-7 | L52: 439.476.688-56 | M52: CADASTRADO | N52: AUXÍLIO ALUGUEL UH | O52: 44900 | P52: 44921 | Q52: 6014.2023/0000399-6 | R52: FINALIZADO | S52: FINALIZADO | T52: FINALIZADO | U52: 02-mai-23 | V52: FINALIZADO | W52: 45049 | X52: 45068 | Y52: 22-mai-23 | Z52: 45128 | AB52: LUCIVANIA MARIA DA SILVA NOVAES | AC52: 42.178.340-0 | AD52: 316.656.868-98 | AE52: PROPRIETÁRIO NÃO RESIDENTE | AF52: CADASTRADO | AG52: 41500 | AH52: 60000 | AI52: SIM | AJ52: 6014.2022/0003993-0 | AK52: FINALIZADO | AL52: FINALIZADO | AM52: FINALIZADO | AN52: SEM PENDÊNCIA | AP52: 6014.2022/0004032-6 | AQ52: FINALIZADO | AR52: FINALIZADO | AS52: FINALIZADO | AT52: FINALIZADO | AU52: 44966 | AV52: FINALIZADO | AW52: FINALIZADO | AX52: 45012 | AY52: 45012 | AZ52: 45128 | BA52: DEMOLIDO | BB52: FINALIZADO | BC52: =IF(AY52-ON52=0,"",AY52-O52) -> 112 | BD52: =IF(AND(AI52<>"SIM",AI52="UH"),"AA","INDENIZAÇÃO") -> INDENIZAÇÃO | BE52: =IF(AND(AY52<>"AGUARDANDO",AY52<>"",N52="AUXÍLIO ALUGUEL ATÉ INDENIZAÇÃO"),"SIM","NÃO") -> NÃO | BF52: N/A | BG52: N/A | BH52: N/A | BI52: FINALIZADO | BJ52: FINALIZADO | BK52: 45190 | BL52: FINALIZADO | BM52: FINALIZADO
A53: 40 | B53: ALFREDO ÁVILA | C53: 1 | D53: 0 | E53: 0 | F53: 001/0033/A | G53: OCUPADO | H53: RESIDENCIAL | I53: PROPRIETÁRIO RESIDENTE | J53: MARIA JOSE DA SILVA COSTA | K53: 29.063.583-4 | L53: 301.137.638-75 | M53: CADASTRADO | N53: AUXÍLIO ALUGUEL UH | O53: 45170 | P53: N/A | Q53: N/A | R53: N/A | S53: N/A | T53: N/A | U53: N/A | V53: N/A | W53: N/A | X53: N/A | Y53: N/A | Z53: N/A | AA53: RECEBEU AA PELO SELO 001/0133/A | AB53: MARIA JOSE DA SILVA COSTA | AC53: 29.063.583-4 | AD53: 301.137.638-75 | AE53: PROPRIETÁRIO RESIDENTE | AF53: CADASTRADO | AG53: 0 | AH53: 0 | AI53: N/A | AJ53: 6014.2022/0003993-0 | AK53: FINALIZADO | AL53: N/A | AM53: N/A | AN53: N/A | AO53: RECEBEU AA PELO SELO 001/0133/A | AP53: N/A | AQ53: N/A | AR53: N/A | AS53: N/A | AT53: N/A | AU53: N/A | AV53: N/A | AW53: N/A | BC53: =IF(AY53-ON53=0,"",AY53-O53) | BD53: =IF(AND(AI53<>"SIM",AI53="UH"),"AA","INDENIZAÇÃO") -> INDENIZAÇÃO | BE53: =IF(AND(AY53<>"AGUARDANDO",AY53<>"",N53="AUXÍLIO ALUGUEL ATÉ INDENIZAÇÃO"),"SIM","NÃO") -> NÃO
A54: 41 | B54: ALFREDO ÁVILA | C54: 1 | D54: 0 | E54: 0 | F54: 001/0036/A | G54: OCUPADO | H54: RESIDENCIAL | I54: INQUILINO | J54: BARBARA LUIZA LUCHETTI BOCALETI | K54: 39.811.659-3 | L54: 471.526.338-60 | M54: CADASTRADO | N54: AUXÍLIO ALUGUEL UH | O54: 44900 | P54: 45081 | Q54: 6014.2023/0000399-6 | R54: FINALIZADO | S54: FINALIZADO | T54: FINALIZADO | U54: 02-mai-23 | V54: FINALIZADO | W54: 05-mai-23 | X54: 22-mai-23 | Y54: 22-mai-23 | Z54: 45128 | AB54: ALICE BARBOSA PEREIRA | AC54: 50.347.964-0 | AD54: 489.240.398-90 | AE54: PROPRIETÁRIO NÃO RESIDENTE | AF54: CADASTRADO | AG54: 38700 | AH54: 60000 | AI54: SIM | AJ54: 6014.2022/0003993-0 | AK54: FINALIZADO | AL54: FINALIZADO | AM54: FINALIZADO | AN54: SEM PENDÊNCIA | AP54: 6014.2022/0004139-0 | AQ54: FINALIZADO | AR54: FINALIZADO | AS54: FINALIZADO | AT54: FINALIZADO | AU54: 44966 | AV54: FINALIZADO | AW54: FINALIZADO | AX54: 45012 | AY54: 45012 | AZ54: 45128 | BA54: DEMOLIDO | BB54: FINALIZADO | BC54: =IF(AY54-ON54=0,"",AY54-O54) -> 112 | BD54: =IF(AND(AI54<>"SIM",AI54="UH"),"AA","INDENIZAÇÃO") -> INDENIZAÇÃO | BE54: =IF(AND(AY54<>"AGUARDANDO",AY54<>"",N54="AUXÍLIO ALUGUEL ATÉ INDENIZAÇÃO"),"SIM","NÃO") -> NÃO | BF54: N/A | BG54: N/A | BH54: N/A | BI54: FINALIZADO | BJ54: FINALIZADO | BK54: 45310 | BL54: FINALIZADO | BM54: FINALIZADO
A55: 42 | B55: ALFREDO ÁVILA | C55: 1 | D55: 0 | E55: 0 | F55: 001/0036/B | G55: VAZIO | H55: RESIDENCIAL | M55: CADASTRADO | N55: INDENIZAÇÃO | O55: 44900 | P55: N/A | Q55: N/A | R55: N/A | S55: N/A | T55: N/A | U55: N/A | V55: N/A | W55: N/A | X55: N/A | Y55: N/A | Z55: N/A | AB55: ALISSON BARBOSA PEREIRA | AC55: 50.347.972-X | AD55: 489.240.878-60 | AE55: PROPRIETÁRIO NÃO RESIDENTE | AF55: CADASTRADO | AG55: 21400 | AH55: 51400 | AI55: SIM | AJ55: 6014.2022/0003993-0 | AK55: FINALIZADO | AL55: FINALIZADO | AM55: FINALIZADO | AN55: SEM PENDÊNCIA | AP55: 6014.2022/0004140-3 | AQ55: FINALIZADO | AR55: FINALIZADO | AS55: FINALIZADO | AT55: FINALIZADO | AU55: 44966 | AV55: FINALIZADO | AW55: FINALIZADO | AX55: 45012 | AY55: 45012 | AZ55: 45128 | BA55: DEMOLIDO | BB55: FINALIZADO | BC55: =IF(AY55-ON55=0,"",AY55-O55) -> 112 | BD55: =IF(AND(AI55<>"SIM",AI55="UH"),"AA","INDENIZAÇÃO") -> INDENIZAÇÃO | BE55: =IF(AND(AY55<>"AGUARDANDO",AY55<>"",N55="AUXÍLIO ALUGUEL ATÉ INDENIZAÇÃO"),"SIM","NÃO") -> NÃO | BF55: N/A | BG55: N/A | BH55: N/A | BI55: FINALIZADO | BJ55: FINALIZADO | BK55: 45190 | BL55: FINALIZADO | BM55: FINALIZADO
A56: 43 | B56: ALFREDO ÁVILA | C56: 1 | D56: 0 | E56: 0 | F56: 001/0037/A | G56: OCUPADO | H56: RESIDENCIAL | I56: INQUILINO | J56: ANA LUCIA RAMOS DUARTE | K56: 62.219.271-1 | L56: 241.475.398-66 | M56: CADASTRADO | N56: AUXÍLIO ALUGUEL UH | O56: 44900 | P56: 44921 | Q56: 6014.2023/0000399-6 | R56: FINALIZADO | S56: FINALIZADO | T56: FINALIZADO | U56: 44992 | V56: FINALIZADO | W56: 44992 | X56: 45019 | Y56: 45019 | Z56: 45127 | AA56: Houve um problema na equipe do pagamento, sendo previsto para 03/04/2023 | AB56: LUIS CAETANO | AC56: 21.966.817-6 | AD56: 166.820.668-73 | AE56: PROPRIETÁRIO NÃO RESIDENTE | AF56: CADASTRADO | AG56: 26300 | AH56: 56300 | AI56: SIM | AJ56: 6014.2022/0003993-0 | AK56: FINALIZADO | AL56: FINALIZADO | AM56: FINALIZADO | AN56: SEM PENDÊNCIA | AP56: 6014.2023/0000339-2 | AQ56: FINALIZADO | AR56: FINALIZADO | AS56: FINALIZADO | AT56: FINALIZADO | AU56: 45078 | AV56: FINALIZADO | AW56: FINALIZADO | AX56: 45167 | AY56: 45167 | AZ56: 45127 | BA56: DEMOLIDO | BB56: FINALIZADO | BC56: =IF(AY56-ON56=0,"",AY56-O56) -> 267 | BD56: =IF(AND(AI56<>"SIM",AI56="UH"),"AA","INDENIZAÇÃO") -> INDENIZAÇÃO | BE56: =IF(AND(AY56<>"AGUARDANDO",AY56<>"",N56="AUXÍLIO ALUGUEL ATÉ INDENIZAÇÃO"),"SIM","NÃO") -> NÃO | BF56: N/A | BG56: N/A | BH56: N/A | BI56: FINALIZADO | BJ56: FINALIZADO | BK56: 45310 | BL56: FINALIZADO | BM56: FINALIZADO
A57: 44 | B57: ALFREDO ÁVILA | C57: 1 | D57: 0 | E57: 0 | F57: 001/0037/B | G57: OCUPADO | H57: RESIDENCIAL | I57: RESIDENTE AUSENTE | M57: PENDENTE | N57: PENDENTE | O57: 44900 | AJ57: 6014.2022/0003993-0 | BC57: =IF(AY57-ON57=0,"",AY57-O57) | BD57: =IF(AND(AI57<>"SIM",AI57="UH"),"AA","INDENIZAÇÃO") -> INDENIZAÇÃO | BE57: =IF(AND(AY57<>"AGUARDANDO",AY57<>"",N57="AUXÍLIO ALUGUEL ATÉ INDENIZAÇÃO"),"SIM","NÃO") -> NÃO
A58: 45 | B58: ALFREDO ÁVILA | C58: 1 | D58: 0 | E58: 0 | F58: 001/0037/C | G58: OCUPADO | H58: RESIDENCIAL | I58: PROPRIETÁRIO RESIDENTE | J58: ANGÉLICA SUELLEN RAMOS SERGINA | K58: 52.373.516-9 | L58: 474.575.748-40 | M58: CADASTRADO | N58: AUXÍLIO ALUGUEL UH | O58: 44900 | P58: 44921 | Q58: 6014.2023/0000399-6 | R58: FINALIZADO | S58: FINALIZADO | T58: FINALIZADO | U58: 44992 | V58: FINALIZADO | W58: 44992 | X58: 45019 | Y58: 45019 | Z58: 45064 | AA58: Houve um problema na equipe do pagamento, sendo previsto para 03/04/2023 | AB58: ANGÉLICA SUELLEN RAMOS SERGINA | AC58: 52.373.516-9 | AD58: 474.575.748-40 | AE58: PROPRIETÁRIO RESIDENTE | AF58: CADASTRADO | AG58: 35700 | AH58: 60000 | AI58: UH | AJ58: 6014.2022/0003993-0 | AK58: FINALIZADO | AL58: N/A | AM58: N/A | AN58: N/A | AP58: N/A | AQ58: N/A | AR58: N/A | AS58: N/A | AT58: N/A | AU58: N/A | AV58: N/A | AW58: N/A | AX58: 45019 | AY58: 45019 | AZ58: 45064 | BA58: DEMOLIDO | BB58: FINALIZADO | BC58: =IF(AY58-ON58=0,"",AY58-O58) -> 119 | BD58: =IF(AND(AI58<>"SIM",AI58="UH"),"AA","INDENIZAÇÃO") -> AA | BE58: =IF(AND(AY58<>"AGUARDANDO",AY58<>"",N58="AUXÍLIO ALUGUEL ATÉ INDENIZAÇÃO"),"SIM","NÃO") -> NÃO | BF58: N/A | BG58: N/A | BH58: N/A | BI58: N/A | BJ58: N/A | BK58: N/A | BL58: N/A | BM58: FINALIZADO
A59: 46 | B59: ALFREDO ÁVILA | C59: 1 | D59: 0 | E59: 0 | F59: 001/0038/A | G59: OCUPADO | H59: NÃO RESIDENCIAL | I59: PROPRIETÁRIO NÃO RESIDENTE | J59: WAGNER FERREIRA | K59: 29.988.378-4 | L59: 213.110.988-10 | M59: CADASTRADO | N59: NÃO TEM ATENDIMENTO | O59: 44900 | P59: N/A | Q59: N/A | R59: N/A | S59: N/A | T59: N/A | U59: N/A | V59: N/A | W59: N/A | X59: N/A | Y59: N/A | Z59: N/A | AB59: WAGNER FERREIRA | AC59: 29.988.378-4 | AD59: 213.110.988-10 | AE59: PROPRIETÁRIO NÃO RESIDENTE | AF59: CADASTRADO | AG59: 17700 | AH59: 47700 | AI59: SIM | AJ59: 6014.2022/0003993-0 | AK59: FINALIZADO | AL59: FINALIZADO | AM59: FINALIZADO | AN59: SEM PENDÊNCIA | AP59: 6014.2022/0003943-3 | AQ59: FINALIZADO | AR59: FINALIZADO | AS59: FINALIZADO | AT59: FINALIZADO | AU59: 45014 | AV59: FINALIZADO | AW59: FINALIZADO | AX59: 45022 | AY59: 45022 | AZ59: 45127 | BA59: DEMOLIDO | BB59: FINALIZADO | BC59: =IF(AY59-ON59=0,"",AY59-O59) -> 122 | BD59: =IF(AND(AI59<>"SIM",AI59="UH"),"AA","INDENIZAÇÃO") -> INDENIZAÇÃO | BE59: =IF(AND(AY59<>"AGUARDANDO",AY59<>"",N59="AUXÍLIO ALUGUEL ATÉ INDENIZAÇÃO"),"SIM","NÃO") -> NÃO | BF59: N/A | BG59: N/A | BH59: N/A | BI59: FINALIZADO | BJ59: FINALIZADO | BK59: 45190 | BL59: FINALIZADO | BM59: FINALIZADO
A60: 47 | B60: ALFREDO ÁVILA | C60: 1 | D60: 0 | E60: 0 | F60: 001/0038/B | G60: OCUPADO | H60: RESIDENCIAL | I60: PROPRIETÁRIO RESIDENTE | J60: WIRNA JOSÉ DE PAULA | K60: 22.282.027-5 | L60: 115.086.198-32 | M60: CADASTRADO | N60: INDENIZAÇÃO | O60: 44900 | P60: N/A | Q60: N/A | R60: N/A | S60: N/A | T60: N/A | U60: N/A | V60: N/A | W60: N/A | X60: N/A | Y60: N/A | Z60: N/A | AB60: WIRNA JOSÉ DE PAULA | AC60: 22.282.027-5 | AD60: 115.086.198-32 | AE60: PROPRIETÁRIO RESIDENTE | AF60: CADASTRADO | AG60: 27300 | AH60: 57300 | AI60: SIM | AJ60: 6014.2022/0003993-0 | AK60: FINALIZADO | AL60: FINALIZADO | AM60: FINALIZADO | AN60: SEM PENDÊNCIA | AP60: 6014.2022/0003962-0 | AQ60: FINALIZADO | AR60: FINALIZADO | AS60: FINALIZADO | AT60: FINALIZADO | AU60: 44966 | AV60: FINALIZADO | AW60: FINALIZADO | AX60: 45020 | AY60: 45020 | AZ60: 45127 | BA60: DEMOLIDO | BB60: FINALIZADO | BC60: =IF(AY60-ON60=0,"",AY60-O60) -> 120 | BD60: =IF(AND(AI60<>"SIM",AI60="UH"),"AA","INDENIZAÇÃO") -> INDENIZAÇÃO | BE60: =IF(AND(AY60<>"AGUARDANDO",AY60<>"",N60="AUXÍLIO ALUGUEL ATÉ INDENIZAÇÃO"),"SIM","NÃO") -> NÃO | BF60: N/A | BG60: N/A | BH60: N/A | BI60: FINALIZADO | BJ60: FINALIZADO | BK60: 45190 | BL60: FINALIZADO | BM60: FINALIZADO
A61: 48 | B61: ALFREDO ÁVILA | C61: 1 | D61: 0 | E61: 0 | F61: 001/0039/A | G61: OCUPADO | H61: RESIDENCIAL | I61: PROPRIETÁRIO RESIDENTE | J61: BEATRIZ RODRIGUES DOS SANTOS | K61: 39.897.214-X | L61: 496.357.038-64 | M61: CADASTRADO | N61: AUXÍLIO ALUGUEL UH | O61: 44900 | P61: 44921 | Q61: 6014.2023/0000399-6 | R61: FINALIZADO | S61: FINALIZADO | T61: FINALIZADO | U61: 44992 | V61: FINALIZADO | W61: 44992 | X61: 45019 | Y61: 45021 | Z61: 45106 | AA61: Houve um problema na equipe do pagamento, sendo previsto para 03/04/2023 | AB61: BEATRIZ RODRIGUES DOS SANTOS | AC61: 39.897.214-X | AD61: 496.357.038-64 | AE61: PROPRIETÁRIO RESIDENTE | AF61: CADASTRADO | AG61: 15800 | AH61: 45800 | AI61: UH | AJ61: 6014.2022/0003993-0 | AK61: FINALIZADO | AL61: N/A | AM61: N/A | AN61: N/A | AP61: N/A | AQ61: N/A | AR61: N/A | AS61: N/A | AT61: N/A | AU61: N/A | AV61: N/A | AW61: N/A | AX61: 45019 | AY61: 45021 | AZ61: 45106 | BA61: DEMOLIDO | BB61: FINALIZADO | BC61: =IF(AY61-ON61=0,"",AY61-O61) -> 121 | BD61: =IF(AND(AI61<>"SIM",AI61="UH"),"AA","INDENIZAÇÃO") -> AA | BE61: =IF(AND(AY61<>"AGUARDANDO",AY61<>"",N61="AUXÍLIO ALUGUEL ATÉ INDENIZAÇÃO"),"SIM","NÃO") -> NÃO | BF61: N/A | BG61: N/A | BH61: N/A | BI61: N/A | BJ61: N/A | BK61: N/A | BL61: N/A | BM61: FINALIZADO
A62: 49 | B62: ALFREDO ÁVILA | C62: 1 | D62: 0 | E62: 0 | F62: 001/0039/B | G62: OCUPADO | H62: NÃO RESIDENCIAL | I62: INQUILINO | J62: MIRIAN MACIEL DE SOUZA DA SILVA | K62: 49.302.245-4 | L62: 401.466.968-83 | M62: CADASTRADO | N62: NÃO TEM ATENDIMENTO | O62: 44900 | P62: N/A | Q62: N/A | R62: N/A | S62: N/A | T62: N/A | U62: N/A | V62: N/A | W62: N/A | X62: N/A | Y62: N/A | Z62: N/A | AB62: ANA PAULA SIMÕES CUNHA NOGUEIRA | AD62: 194.609.818-36 | AE62: PROPRIETÁRIO NÃO RESIDENTE | AF62: CADASTRADO | AI62: N/A | AJ62: 6014.2022/0003993-0 | AK62: FINALIZADO | AL62: N/A | AM62: N/A | AN62: N/A | AP62: N/A | AQ62: N/A | AR62: N/A | AS62: N/A | AT62: N/A | AU62: N/A | AV62: N/A | AW62: N/A | AX62: N/A | AY62: N/A | BC62: =IF(AY62-ON62=0,"",AY62-O62) -> #VALUE! | BD62: =IF(AND(AI62<>"SIM",AI62="UH"),"AA","INDENIZAÇÃO") -> INDENIZAÇÃO | BE62: =IF(AND(AY62<>"AGUARDANDO",AY62<>"",N62="AUXÍLIO ALUGUEL ATÉ INDENIZAÇÃO"),"SIM","NÃO") -> NÃO
A63: 50 | B63: ALFREDO ÁVILA | C63: 1 | D63: 0 | E63: 0 | F63: 001/0039/C | G63: OCUPADO | H63: RESIDENCIAL | I63: INQUILINO | J63: MIRIAN MACIEL DE SOUZA DA SILVA | K63: 49.302.245-4 | L63: 401.466.968-83 | M63: CADASTRADO | N63: AUXÍLIO ALUGUEL UH | O63: 45237 | P63: N/A | Q63: N/A | R63: N/A | S63: N/A | T63: N/A | U63: N/A | V63: N/A | W63: N/A | X63: N/A | Y63: N/A | Z63: N/A | AB63: ANA PAULA SIMÕES CUNHA NOGUEIRA | AD63: 194.609.818-36 | AE63: PROPRIETÁRIO NÃO RESIDENTE | AJ63: 6014.2022/0003993-0 | BC63: =IF(AY63-ON63=0,"",AY63-O63) | BD63: =IF(AND(AI63<>"SIM",AI63="UH"),"AA","INDENIZAÇÃO") -> INDENIZAÇÃO | BE63: =IF(AND(AY63<>"AGUARDANDO",AY63<>"",N63="AUXÍLIO ALUGUEL ATÉ INDENIZAÇÃO"),"SIM","NÃO") -> NÃO
A64: 51 | B64: ALFREDO ÁVILA | C64: 1 | D64: 0 | E64: 0 | F64: 001/0047/A | G64: OCUPADO | H64: RESIDENCIAL | I64: PROPRIETÁRIO RESIDENTE | J64: DEBORA EVELLYN DOS SANTOS FLORES | K64: 53.045.343-5 | L64: 457.431.978-06 | M64: CADASTRADO | N64: AUXÍLIO ALUGUEL UH | O64: 44900 | P64: 44921 | Q64: 6014.2023/0000399-6 | R64: FINALIZADO | S64: FINALIZADO | T64: FINALIZADO | U64: 44992 | V64: FINALIZADO | W64: 44992 | X64: 45019 | Y64: 45021 | Z64: 45042 | AA64: Houve um problema na equipe do pagamento, sendo previsto para 03/04/2023 | AB64: DEBORA EVELLYN DOS SANTOS FLORES | AC64: 53.045.343-5 | AD64: 457.431.978-06 | AE64: PROPRIETÁRIO RESIDENTE | AF64: CADASTRADO | AG64: 17500 | AH64: 47500 | AI64: UH | AJ64: 6014.2022/0003993-0 | AK64: FINALIZADO | AL64: N/A | AM64: N/A | AN64: N/A | AP64: N/A | AQ64: N/A | AR64: N/A | AS64: N/A | AT64: N/A | AU64: N/A | AV64: N/A | AW64: N/A | AX64: 45019 | AY64: 45021 | AZ64: 45042 | BA64: DEMOLIDO | BB64: FINALIZADO | BC64: =IF(AY64-ON64=0,"",AY64-O64) -> 121 | BD64: =IF(AND(AI64<>"SIM",AI64="UH"),"AA","INDENIZAÇÃO") -> AA | BE64: =IF(AND(AY64<>"AGUARDANDO",AY64<>"",N64="AUXÍLIO ALUGUEL ATÉ INDENIZAÇÃO"),"SIM","NÃO") -> NÃO | BF64: N/A | BG64: N/A | BH64: N/A | BI64: N/A | BJ64: N/A | BK64: N/A | BL64: N/A | BM64: FINALIZADO
A65: 52 | B65: ALFREDO ÁVILA | C65: 1 | D65: 0 | E65: 0 | F65: 001/0047/B | G65: OCUPADO | H65: RESIDENCIAL | I65: PROPRIETÁRIO RESIDENTE | J65: ELOY SANTOS FLORES | K65: 53.045.236-4 | L65: 454.872.348-09 | M65: CADASTRADO | N65: AUXÍLIO ALUGUEL UH | O65: 44900 | P65: 44921 | Q65: 6014.2023/0000399-6 | R65: FINALIZADO | S65: FINALIZADO | T65: FINALIZADO | U65: 44992 | V65: FINALIZADO | W65: 44992 | X65: 45019 | Y65: 45026 | Z65: 45042 | AA65: Houve um problema na equipe do pagamento, sendo previsto para 03/04/2023 | AB65: ELOY SANTOS FLORES | AC65: 53.045.236-4 | AD65: 454.872.348-09 | AE65: PROPRIETÁRIO RESIDENTE | AF65: CADASTRADO | AG65: 24200 | AH65: 54200 | AI65: UH | AJ65: 6014.2022/0003993-0 | AK65: FINALIZADO | AL65: N/A | AM65: N/A | AN65: N/A | AP65: N/A | AQ65: N/A | AR65: N/A | AS65: N/A | AT65: N/A | AU65: N/A | AV65: N/A | AW65: N/A | AX65: 45019 | AY65: 45026 | AZ65: 45042 | BA65: DEMOLIDO | BB65: FINALIZADO | BC65: =IF(AY65-ON65=0,"",AY65-O65) -> 126 | BD65: =IF(AND(AI65<>"SIM",AI65="UH"),"AA","INDENIZAÇÃO") -> AA | BE65: =IF(AND(AY65<>"AGUARDANDO",AY65<>"",N65="AUXÍLIO ALUGUEL ATÉ INDENIZAÇÃO"),"SIM","NÃO") -> NÃO | BF65: N/A | BG65: N/A | BH65: N/A | BI65: N/A | BJ65: N/A | BK65: N/A | BL65: N/A | BM65: FINALIZADO
A66: 53 | B66: ALFREDO ÁVILA | C66: 1 | D66: 0 | E66: 0 | F66: 001/0047/C | G66: OCUPADO | H66: RESIDENCIAL | I66: PROPRIETÁRIO RESIDENTE | J66: DIEGO DOS SANTOS FLORES | K66: 34.199.065-4 | L66: 344.130.078-59 | M66: CADASTRADO | N66: INDENIZAÇÃO | O66: 44900 | P66: N/A | Q66: N/A | R66: N/A | S66: N/A | T66: N/A | U66: N/A | V66: N/A | W66: N/A | X66: N/A | Y66: N/A | Z66: N/A | AB66: DIEGO DOS SANTOS FLORES | AC66: 34.199.065-4 | AD66: 344.130.078-59 | AE66: PROPRIETÁRIO RESIDENTE | AF66: CADASTRADO | AG66: =AH66-30000 -> 17900 | AH66: 47900 | AI66: SIM | AJ66: 6014.2022/0003993-0 | AK66: FINALIZADO | AL66: FINALIZADO | AM66: FINALIZADO | AN66: SEM PENDÊNCIA | AP66: 6014.2023/0000168-3 | AQ66: FINALIZADO | AR66: FINALIZADO | AS66: FINALIZADO | AT66: FINALIZADO | AU66: 44966 | AV66: FINALIZADO | AW66: FINALIZADO | AX66: 45012 | AY66: 45012 | AZ66: 45042 | BA66: DEMOLIDO | BB66: FINALIZADO | BC66: =IF(AY66-ON66=0,"",AY66-O66) -> 112 | BD66: =IF(AND(AI66<>"SIM",AI66="UH"),"AA","INDENIZAÇÃO") -> INDENIZAÇÃO | BE66: =IF(AND(AY66<>"AGUARDANDO",AY66<>"",N66="AUXÍLIO ALUGUEL ATÉ INDENIZAÇÃO"),"SIM","NÃO") -> NÃO | BF66: N/A | BG66: N/A | BH66: N/A | BI66: FINALIZADO | BJ66: FINALIZADO | BK66: 45190 | BL66: FINALIZADO | BM66: FINALIZADO
A67: 54 | B67: ALFREDO ÁVILA | C67: 1 | D67: 0 | E67: 0 | F67: 001/0048/A | G67: OCUPADO | H67: RESIDENCIAL | I67: PROPRIETÁRIO RESIDENTE | J67: LETÍCIA SOARES SOUSA | K67: 53.906.268-6 | L67: 557.850.828-61 | M67: CADASTRADO | N67: INDENIZAÇÃO | O67: 44900 | P67: N/A | Q67: N/A | R67: N/A | S67: N/A | T67: N/A | U67: N/A | V67: N/A | W67: N/A | X67: N/A | Y67: N/A | Z67: N/A | AB67: LETÍCIA SOARES SOUSA | AC67: 53.906.268-6 | AD67: 557.850.828-61 | AE67: PROPRIETÁRIO RESIDENTE | AF67: CADASTRADO | AG67: 18100 | AH67: 48100 | AI67: SIM | AJ67: 6014.2022/0003993-0 | AK67: FINALIZADO | AL67: FINALIZADO | AM67: FINALIZADO | AN67: SEM PENDÊNCIA | AP67: 6014.2022/0004033-4 | AQ67: FINALIZADO | AR67: FINALIZADO | AS67: FINALIZADO | AT67: FINALIZADO | AU67: 44922 | AV67: FINALIZADO | AW67: FINALIZADO | AX67: 44924 | AY67: 44924 | AZ67: 44936 | BA67: DEMOLIDO | BB67: FINALIZADO | BC67: =IF(AY67-ON67=0,"",AY67-O67) -> 24 | BD67: =IF(AND(AI67<>"SIM",AI67="UH"),"AA","INDENIZAÇÃO") -> INDENIZAÇÃO | BE67: =IF(AND(AY67<>"AGUARDANDO",AY67<>"",N67="AUXÍLIO ALUGUEL ATÉ INDENIZAÇÃO"),"SIM","NÃO") -> NÃO | BF67: N/A | BG67: N/A | BH67: N/A | BI67: FINALIZADO | BJ67: FINALIZADO | BK67: 45057 | BL67: FINALIZADO | BM67: FINALIZADO
A68: 55 | B68: ALFREDO ÁVILA | C68: 1 | D68: 0 | E68: 0 | F68: 001/0049/A | G68: OCUPADO | H68: RESIDENCIAL | I68: INQUILINO | J68: WENDEL ENRIQUE SANTANA SOUZA | K68: 62.514.646-3 | L68: 516.094.758-28 | M68: CADASTRADO | N68: AUXÍLIO ALUGUEL UH | O68: 44900 | P68: 44921 | Q68: 6014.2023/0000399-6 | R68: FINALIZADO | S68: FINALIZADO | T68: FINALIZADO | U68: 44992 | V68: FINALIZADO | W68: 44992 | X68: 45019 | Y68: 45019 | Z68: 45054 | AA68: Houve um problema na equipe do pagamento, sendo previsto para 03/04/2023 | AB68: CLAUDIA BARBOSA DA SILVA SANTOS | AC68: 44.876.275-4 | AD68: 393.752.108-98 | AE68: PROPRIETÁRIO NÃO RESIDENTE | AF68: CADASTRADO | AG68: 18400 | AH68: 48400 | AI68: SIM | AJ68: 6014.2022/0003993-0 | AK68: FINALIZADO | AL68: FINALIZADO | AM68: FINALIZADO | AN68: SEM PENDÊNCIA | AP68: 6014.2022/0003955-7 | AQ68: FINALIZADO | AR68: FINALIZADO | AS68: FINALIZADO | AT68: FINALIZADO | AU68: 44966 | AV68: FINALIZADO | AW68: FINALIZADO | AX68: 45012 | AY68: 45012 | AZ68: 45054 | BA68: DEMOLIDO | BB68: FINALIZADO | BC68: =IF(AY68-ON68=0,"",AY68-O68) -> 112 | BD68: =IF(AND(AI68<>"SIM",AI68="UH"),"AA","INDENIZAÇÃO") -> INDENIZAÇÃO | BE68: =IF(AND(AY68<>"AGUARDANDO",AY68<>"",N68="AUXÍLIO ALUGUEL ATÉ INDENIZAÇÃO"),"SIM","NÃO") -> NÃO | BF68: N/A | BG68: N/A | BH68: N/A | BI68: FINALIZADO | BJ68: FINALIZADO | BK68: 45310 | BL68: FINALIZADO | BM68: FINALIZADO
A69: 56 | B69: ALFREDO ÁVILA | C69: 1 | D69: 0 | E69: 0 | F69: 001/0049/B | G69: OCUPADO | H69: RESIDENCIAL | I69: INQUILINO | J69: JOSEILDO FERNANDO DA SILVA | K69: 44.926.182-7 | L69: 370.264.498-93 | M69: CADASTRADO | N69: AUXÍLIO ALUGUEL UH | O69: 44900 | P69: 44921 | Q69: 6014.2023/0000399-6 | R69: FINALIZADO | S69: FINALIZADO | T69: FINALIZADO | U69: 44992 | V69: FINALIZADO | W69: 44992 | X69: 45019 | Y69: 45019 | Z69: 45054 | AA69: Houve um problema na equipe do pagamento, sendo previsto para 03/04/2023 | AB69: CLAUDIA BARBOSA DA SILVA SANTOS | AC69: 44.876.275-4 | AD69: 393.752.108-98 | AE69: PROPRIETÁRIO NÃO RESIDENTE | AF69: N/A | AG69: 13300 | AH69: 43300 | AI69: RECEBEU INDENIZAÇÃO PELO SELO 001/0049A | AJ69: 6014.2022/0003993-0 | AK69: N/A | AL69: N/A | AM69: N/A | AN69: N/A | AP69: N/A | AQ69: N/A | AR69: N/A | AS69: N/A | AT69: N/A | AU69: N/A | AV69: N/A | AW69: N/A | AX69: N/A | AY69: N/A | AZ69: 45054 | BA69: DEMOLIDO | BB69: FINALIZADO | BC69: N/A | BD69: =IF(AND(AI69<>"SIM",AI69="UH"),"AA","INDENIZAÇÃO") -> INDENIZAÇÃO | BE69: =IF(AND(AY69<>"AGUARDANDO",AY69<>"",N69="AUXÍLIO ALUGUEL ATÉ INDENIZAÇÃO"),"SIM","NÃO") -> NÃO | BF69: N/A | BG69: N/A | BH69: N/A | BI69: N/A | BJ69: N/A | BK69: N/A | BL69: N/A | BM69: FINALIZADO
A70: 57 | B70: ALFREDO ÁVILA | C70: 1 | D70: 0 | E70: 0 | F70: 001/0050/A | G70: OCUPADO | H70: RESIDENCIAL | I70: PROPRIETÁRIO RESIDENTE | J70: ÁGATHA ALESSANDRA DE PAULA CALABRESI | K70: 39.897.247-3 | L70: 390.685.488-40 | M70: CADASTRADO | N70: INDENIZAÇÃO | O70: 44900 | P70: N/A | Q70: N/A | R70: N/A | S70: N/A | T70: N/A | U70: N/A | V70: N/A | W70: N/A | X70: N/A | Y70: N/A | Z70: N/A | AB70: ÁGATHA ALESSANDRA DE PAULA CALABRESI | AC70: 39.897.247-3 | AD70: 390.685.488-40 | AE70: PROPRIETÁRIO RESIDENTE | AF70: CADASTRADO | AG70: 13800 | AH70: 43800 | AI70: SIM | AJ70: 6014.2022/0003993-0 | AK70: FINALIZADO | AL70: FINALIZADO | AM70: FINALIZADO | AN70: SEM PENDÊNCIA | AP70: 6014.2023/0000370-8 | AQ70: FINALIZADO | AR70: FINALIZADO | AS70: FINALIZADO | AT70: FINALIZADO | AU70: 45014 | AV70: FINALIZADO | AW70: FINALIZADO | AX70: 45022 | AY70: 45022 | AZ70: 45054 | BA70: DEMOLIDO | BB70: FINALIZADO | BC70: =IF(AY70-ON70=0,"",AY70-O70) -> 122 | BD70: =IF(AND(AI70<>"SIM",AI70="UH"),"AA","INDENIZAÇÃO") -> INDENIZAÇÃO | BE70: =IF(AND(AY70<>"AGUARDANDO",AY70<>"",N70="AUXÍLIO ALUGUEL ATÉ INDENIZAÇÃO"),"SIM","NÃO") -> NÃO | BF70: N/A | BG70: N/A | BH70: N/A | BI70: FINALIZADO | BJ70: FINALIZADO | BK70: 45190 | BL70: FINALIZADO | BM70: FINALIZADO
A71: 58 | B71: ALFREDO ÁVILA | C71: 1 | D71: 0 | E71: 0 | F71: 001/0051/A | G71: EM CONSTRUÇÃO | H71: RESIDENCIAL | I71: PROPRIETÁRIO RESIDENTE | J71: ANDRÉ FERREIRA DE FRANÇA | K71: 42.348.779-6 | L71: 359.457.468-78 | M71: CADASTRADO | N71: INDENIZAÇÃO | O71: 44900 | P71: N/A | Q71: N/A | R71: N/A | S71: N/A | T71: N/A | U71: N/A | V71: N/A | W71: N/A | X71: N/A | Y71: N/A | Z71: N/A | AB71: ANDRÉ FERREIRA DE FRANÇA | AC71: 42.348.779-6 | AD71: 359.457.468-78 | AE71: PROPRIETÁRIO RESIDENTE | AF71: CADASTRADO | AG71: 12600 | AH71: 42600 | AI71: SIM | AJ71: 6014.2022/0003993-0 | AK71: FINALIZADO | AL71: FINALIZADO | AM71: FINALIZADO | AN71: SEM PENDÊNCIA | AP71: 6014.2023/0000353-8 | AQ71: FINALIZADO | AR71: FINALIZADO | AS71: FINALIZADO | AT71: FINALIZADO | AU71: 45014 | AV71: FINALIZADO | AW71: FINALIZADO | AX71: 45022 | AY71: 45022 | AZ71: 45054 | BA71: DEMOLIDO | BB71: FINALIZADO | BC71: =IF(AY71-ON71=0,"",AY71-O71) -> 122 | BD71: =IF(AND(AI71<>"SIM",AI71="UH"),"AA","INDENIZAÇÃO") -> INDENIZAÇÃO | BE71: =IF(AND(AY71<>"AGUARDANDO",AY71<>"",N71="AUXÍLIO ALUGUEL ATÉ INDENIZAÇÃO"),"SIM","NÃO") -> NÃO | BF71: N/A | BG71: N/A | BH71: N/A | BI71: FINALIZADO | BJ71: FINALIZADO | BK71: 45310 | BL71: FINALIZADO | BM71: FINALIZADO
A72: 59 | B72: ALFREDO ÁVILA | C72: 1 | D72: 0 | E72: 0 | F72: 001/0052/A | G72: OCUPADO | H72: RESIDENCIAL | I72: PROPRIETÁRIO RESIDENTE | J72: WAGNER RAMALHO QUEIROZ | K72: 37.142.909-2 | L72: 453.314.278-80 | M72: CADASTRADO | N72: INDENIZAÇÃO | O72: 44900 | P72: N/A | Q72: N/A | R72: N/A | S72: N/A | T72: N/A | U72: N/A | V72: N/A | W72: N/A | X72: N/A | Y72: N/A | Z72: N/A | AB72: WAGNER RAMALHO QUEIROZ | AC72: 37.142.909-2 | AD72: 453.314.278-80 | AE72: PROPRIETÁRIO RESIDENTE | AF72: CADASTRADO | AG72: 23400 | AH72: 53400 | AI72: SIM | AJ72: 6014.2022/0003993-0 | AK72: FINALIZADO | AL72: FINALIZADO | AM72: FINALIZADO | AN72: SEM PENDÊNCIA | AP72: 6014.2022/0003960-3 | AQ72: FINALIZADO | AR72: FINALIZADO | AS72: FINALIZADO | AT72: FINALIZADO | AU72: 44966 | AV72: FINALIZADO | AW72: FINALIZADO | AX72: 45012 | AY72: 45012 | AZ72: 45055 | BA72: DEMOLIDO | BB72: FINALIZADO | BC72: =IF(AY72-ON72=0,"",AY72-O72) -> 112 | BD72: =IF(AND(AI72<>"SIM",AI72="UH"),"AA","INDENIZAÇÃO") -> INDENIZAÇÃO | BE72: =IF(AND(AY72<>"AGUARDANDO",AY72<>"",N72="AUXÍLIO ALUGUEL ATÉ INDENIZAÇÃO"),"SIM","NÃO") -> NÃO | BF72: N/A | BG72: N/A | BH72: N/A | BI72: FINALIZADO | BJ72: FINALIZADO | BK72: 45190 | BL72: FINALIZADO | BM72: FINALIZADO
A73: 60 | B73: ALFREDO ÁVILA | C73: 1 | D73: 0 | E73: 0 | F73: 001/0052/B | G73: OCUPADO | H73: RESIDENCIAL | I73: PROPRIETÁRIO RESIDENTE | J73: SIMONE DE JESUS ROCHA | K73: 62.057.806-3 | L73: 418.163.808-14 | M73: CADASTRADO | N73: AUXÍLIO ALUGUEL UH | O73: 44900 | P73: 44921 | Q73: 6014.2023/0000399-6 | R73: FINALIZADO | S73: FINALIZADO | T73: FINALIZADO | U73: 44992 | V73: FINALIZADO | W73: 44992 | X73: 45019 | Y73: 45019 | Z73: 45055 | AA73: Houve um problema na equipe do pagamento, sendo previsto para 03/04/2023 | AB73: SIMONE DE JESUS ROCHA | AC73: 62.057.806-3 | AD73: 418.163.308-14 | AE73: PROPRIETÁRIO RESIDENTE | AF73: CADASTRADO | AG73: 35800 | AH73: 60000 | AI73: UH | AJ73: 6014.2022/0003993-0 | AK73: FINALIZADO | AL73: N/A | AM73: N/A | AN73: N/A | AP73: N/A | AQ73: N/A | AR73: N/A | AS73: N/A | AT73: N/A | AU73: N/A | AV73: N/A | AW73: N/A | AX73: 45019 | AY73: 45019 | AZ73: 45055 | BA73: DEMOLIDO | BB73: FINALIZADO | BC73: =IF(AY73-ON73=0,"",AY73-O73) -> 119 | BD73: =IF(AND(AI73<>"SIM",AI73="UH"),"AA","INDENIZAÇÃO") -> AA | BE73: =IF(AND(AY73<>"AGUARDANDO",AY73<>"",N73="AUXÍLIO ALUGUEL ATÉ INDENIZAÇÃO"),"SIM","NÃO") -> NÃO | BF73: N/A | BG73: N/A | BH73: N/A | BI73: N/A | BJ73: N/A | BK73: N/A | BL73: N/A | BM73: FINALIZADO
A74: 61 | B74: ALFREDO ÁVILA | C74: 1 | D74: 0 | E74: 0 | F74: 001/0053/A | G74: OCUPADO | H74: RESIDENCIAL | I74: INQUILINO | J74: EDUARDO VIEIRA GABRIEL | K74: MG-10.085.479 | L74: 041.884.086-50 | M74: CADASTRADO | N74: AUXÍLIO ALUGUEL UH | O74: 44900 | P74: 44921 | Q74: 6014.2023/0000399-6 | R74: FINALIZADO | S74: FINALIZADO | T74: FINALIZADO | U74: 44992 | V74: FINALIZADO | W74: 44992 | X74: 45019 | Y74: 45070 | Z74: 45056 | AA74: Houve um problema na equipe do pagamento, sendo previsto para 03/04/2023 | AB74: NILVA DA SILVEIRA VARGAS | AC74: 52.751.188-2 | AD74: 033.699.229-75 | AE74: PROPRIETÁRIO NÃO RESIDENTE | AF74: CADASTRADO | AG74: 37800 | AH74: 60000 | AI74: SIM | AJ74: 6014.2022/0003993-0 | AK74: FINALIZADO | AL74: FINALIZADO | AM74: FINALIZADO | AN74: SEM PENDÊNCIA | AP74: 6014.2022/0004089-0 | AQ74: FINALIZADO | AR74: FINALIZADO | AS74: FINALIZADO | AT74: FINALIZADO | AU74: 44922 | AV74: FINALIZADO | AW74: FINALIZADO | AX74: 44924 | AY74: 44924 | AZ74: 45056 | BA74: DEMOLIDO | BB74: FINALIZADO | BC74: =IF(AY74-ON74=0,"",AY74-O74) -> 24 | BD74: =IF(AND(AI74<>"SIM",AI74="UH"),"AA","INDENIZAÇÃO") -> INDENIZAÇÃO | BE74: =IF(AND(AY74<>"AGUARDANDO",AY74<>"",N74="AUXÍLIO ALUGUEL ATÉ INDENIZAÇÃO"),"SIM","NÃO") -> NÃO | BF74: N/A | BG74: N/A | BH74: N/A | BI74: FINALIZADO | BJ74: FINALIZADO | BK74: 45190 | BL74: FINALIZADO | BM74: FINALIZADO
A75: 62 | B75: ALFREDO ÁVILA | C75: 1 | D75: 0 | E75: 0 | F75: 001/0053/B | G75: OCUPADO | H75: RESIDENCIAL | I75: INQUILINO | J75: FERNANDA MERCES DA SILVEIRA | K75: 50.771.152-X | L75: 528.864.978-27 | M75: CADASTRADO | N75: AUXÍLIO ALUGUEL UH | O75: 44900 | P75: 44921 | Q75: 6014.2023/0000399-6 | R75: FINALIZADO | S75: FINALIZADO | T75: FINALIZADO | U75: 44992 | V75: FINALIZADO | W75: 44992 | X75: 45019 | Y75: 45070 | Z75: 45056 | AA75: Houve um problema na equipe do pagamento, sendo previsto para 03/04/2023 | AB75: NILVA DA SILVEIRA VARGAS | AC75: 52.751.188-2 | AD75: 033.699.229-75 | AE75: PROPRIETÁRIO NÃO RESIDENTE | AF75: N/A | AG75: 40100 | AH75: 60000 | AI75: RECEBEU INDENIZAÇÃO PELO SELO 001/0053/A | AJ75: 6014.2022/0003993-0 | AK75: N/A | AL75: N/A | AM75: N/A | AN75: N/A | AO75: RECEBEU INDENIZAÇÃO PELO SELO 001/0053/A | AP75: N/A | AQ75: N/A | AR75: N/A | AS75: N/A | AT75: N/A | AU75: N/A | AV75: N/A | AW75: N/A | AX75: N/A | AY75: N/A | AZ75: 45056 | BA75: DEMOLIDO | BB75: FINALIZADO | BC75: N/A | BD75: =IF(AND(AI75<>"SIM",AI75="UH"),"AA","INDENIZAÇÃO") -> INDENIZAÇÃO | BE75: =IF(AND(AY75<>"AGUARDANDO",AY75<>"",N75="AUXÍLIO ALUGUEL ATÉ INDENIZAÇÃO"),"SIM","NÃO") -> NÃO | BF75: N/A | BG75: N/A | BH75: N/A | BI75: N/A | BJ75: N/A | BK75: N/A | BL75: N/A | BM75: FINALIZADO
A76: 63 | B76: ALFREDO ÁVILA | C76: 1 | D76: 0 | E76: 0 | F76: 001/0054/A | G76: OCUPADO | H76: RESIDENCIAL | I76: PROPRIETÁRIO RESIDENTE | J76: RYCK VINNICIUS DA SILVA | K76: 39.313.802-1 | L76: 412.686.548-92 | M76: CADASTRADO | N76: INDENIZAÇÃO | O76: 44900 | P76: N/A | Q76: N/A | R76: N/A | S76: N/A | T76: N/A | U76: N/A | V76: N/A | W76: N/A | X76: N/A | Y76: N/A | Z76: N/A | AB76: RYCK VINNICIUS DA SILVA | AC76: 39.313.802-1 | AD76: 412.686.548-92 | AE76: PROPRIETÁRIO RESIDENTE | AF76: CADASTRADO | AG76: 12100 | AH76: 42100 | AI76: SIM | AJ76: 6014.2022/0003993-0 | AK76: FINALIZADO | AL76: FINALIZADO | AM76: FINALIZADO | AN76: SEM PENDÊNCIA | AP76: 6014.2022/0004086-5 | AQ76: FINALIZADO | AR76: FINALIZADO | AS76: FINALIZADO | AT76: FINALIZADO | AU76: 44922 | AV76: FINALIZADO | AW76: FINALIZADO | AX76: 45020 | AY76: 45020 | AZ76: 45055 | BA76: DEMOLIDO | BB76: FINALIZADO | BC76: =IF(AY76-ON76=0,"",AY76-O76) -> 120 | BD76: =IF(AND(AI76<>"SIM",AI76="UH"),"AA","INDENIZAÇÃO") -> INDENIZAÇÃO | BE76: =IF(AND(AY76<>"AGUARDANDO",AY76<>"",N76="AUXÍLIO ALUGUEL ATÉ INDENIZAÇÃO"),"SIM","NÃO") -> NÃO | BF76: N/A | BG76: N/A | BH76: N/A | BI76: FINALIZADO | BJ76: FINALIZADO | BK76: 45190 | BL76: FINALIZADO | BM76: FINALIZADO
A77: 64 | B77: ALFREDO ÁVILA | C77: 1 | D77: 0 | E77: 0 | F77: 001/0055/A | G77: OCUPADO | H77: RESIDENCIAL | I77: PROPRIETÁRIO RESIDENTE | J77: ROGERIO ALEX RAMOS SERGINA | K77: 43.273.271-8 | L77: 445.951.018-99 | M77: CADASTRADO | N77: AUXÍLIO ALUGUEL UH | O77: 44900 | P77: 44921 | Q77: 6014.2023/0000399-6 | R77: FINALIZADO | S77: FINALIZADO | T77: FINALIZADO | U77: 44992 | V77: FINALIZADO | W77: 44992 | X77: 45019 | Y77: 45021 | Z77: 45055 | AA77: Houve um problema na equipe do pagamento, sendo previsto para 03/04/2023 | AB77: ROGERIO ALEX RAMOS SERGINA | AC77: 43.273.271-8 | AD77: 445.951.018-99 | AE77: PROPRIETÁRIO RESIDENTE | AF77: CADASTRADO | AG77: 19600 | AH77: 49600 | AI77: UH | AJ77: 6014.2022/0003993-0 | AK77: FINALIZADO | AL77: N/A | AM77: N/A | AN77: N/A | AP77: N/A | AQ77: N/A | AR77: N/A | AS77: N/A | AT77: N/A | AU77: N/A | AV77: N/A | AW77: N/A | AX77: 45019 | AY77: 45021 | AZ77: 45055 | BA77: DEMOLIDO | BB77: FINALIZADO | BC77: =IF(AY77-ON77=0,"",AY77-O77) -> 121 | BD77: =IF(AND(AI77<>"SIM",AI77="UH"),"AA","INDENIZAÇÃO") -> AA | BE77: =IF(AND(AY77<>"AGUARDANDO",AY77<>"",N77="AUXÍLIO ALUGUEL ATÉ INDENIZAÇÃO"),"SIM","NÃO") -> NÃO | BF77: N/A | BG77: N/A | BH77: N/A | BI77: N/A | BJ77: N/A | BK77: N/A | BL77: N/A | BM77: FINALIZADO
A78: 65 | B78: ALFREDO ÁVILA | C78: 1 | D78: 0 | E78: 0 | F78: 001/0056/A | G78: EM CONSTRUÇÃO | H78: RESIDENCIAL | I78: N/A | M78: N/A | N78: NÃO TEM ATENDIMENTO | O78: 44900 | P78: N/A | Q78: N/A | R78: N/A | S78: N/A | T78: N/A | U78: N/A | V78: N/A | W78: N/A | X78: N/A | Y78: N/A | Z78: N/A | AB78: ROSIEL DE BARROS CARDOSO BATISTA | AC78: 42.363.207-3 | AD78: 420.017.688-26 | AE78: PROPRIETÁRIO NÃO RESIDENTE | AF78: CADASTRADO | AG78: 8500 | AH78: 38500 | AI78: SIM | AJ78: 6014.2022/0003993-0 | AK78: FINALIZADO | AL78: FINALIZADO | AM78: FINALIZADO | AN78: SEM PENDÊNCIA | AP78: 6014.2022/0004143-8 | AQ78: FINALIZADO | AR78: FINALIZADO | AS78: FINALIZADO | AT78: FINALIZADO | AU78: 44966 | AV78: FINALIZADO | AW78: FINALIZADO | AX78: 45012 | AY78: 45012 | AZ78: 45055 | BA78: DEMOLIDO | BB78: FINALIZADO | BC78: =IF(AY78-ON78=0,"",AY78-O78) -> 112 | BD78: =IF(AND(AI78<>"SIM",AI78="UH"),"AA","INDENIZAÇÃO") -> INDENIZAÇÃO | BE78: =IF(AND(AY78<>"AGUARDANDO",AY78<>"",N78="AUXÍLIO ALUGUEL ATÉ INDENIZAÇÃO"),"SIM","NÃO") -> NÃO | BF78: N/A | BG78: N/A | BH78: N/A | BI78: FINALIZADO | BJ78: FINALIZADO | BK78: 45190 | BL78: FINALIZADO | BM78: FINALIZADO
A79: 66 | B79: ALFREDO ÁVILA | C79: 3 | D79: 0 | E79: 0 | F79: 001/0057/A | G79: OCUPADO | H79: RESIDENCIAL | J79: GUILHERME DOS SANTOS GARCIA | N79: RECUSA | AI79: RECUSA | AJ79: 6014.2022/0003993-0 | AO79: RECUSA | BB79: RECUSA | BC79: =IF(AY79-ON79=0,"",AY79-O79) | BD79: =IF(AND(AI79<>"SIM",AI79="UH"),"AA","INDENIZAÇÃO") -> INDENIZAÇÃO | BE79: =IF(AND(AY79<>"AGUARDANDO",AY79<>"",N79="AUXÍLIO ALUGUEL ATÉ INDENIZAÇÃO"),"SIM","NÃO") -> NÃO
A80: 67 | B80: ALFREDO ÁVILA | C80: 3 | D80: 0 | E80: 0 | F80: 001/0057/B | G80: OCUPADO | H80: RESIDENCIAL | J80: LETICIA BISPO DOS SANTOS | N80: RECUSA | AI80: RECUSA | AJ80: 6014.2022/0003993-0 | AO80: RECUSA | BB80: RECUSA | BC80: =IF(AY80-ON80=0,"",AY80-O80) | BD80: =IF(AND(AI80<>"SIM",AI80="UH"),"AA","INDENIZAÇÃO") -> INDENIZAÇÃO | BE80: =IF(AND(AY80<>"AGUARDANDO",AY80<>"",N80="AUXÍLIO ALUGUEL ATÉ INDENIZAÇÃO"),"SIM","NÃO") -> NÃO
A81: 68 | B81: ALFREDO ÁVILA | C81: 3 | D81: 0 | E81: 0 | F81: 001/0057/C | G81: OCUPADO | H81: NÃO RESIDENCIAL | J81: ANTONIO CARLOS DOS SANTOS | N81: RECUSA | AI81: RECUSA | AJ81: 6014.2022/0003993-0 | AO81: RECUSA | BB81: RECUSA | BC81: =IF(AY81-ON81=0,"",AY81-O81) | BD81: =IF(AND(AI81<>"SIM",AI81="UH"),"AA","INDENIZAÇÃO") -> INDENIZAÇÃO | BE81: =IF(AND(AY81<>"AGUARDANDO",AY81<>"",N81="AUXÍLIO ALUGUEL ATÉ INDENIZAÇÃO"),"SIM","NÃO") -> NÃO
A82: 69 | B82: ALFREDO ÁVILA | C82: 3 | D82: 0 | E82: 0 | F82: 001/0057/D | G82: OCUPADO | H82: RESIDENCIAL | I82: MORADOR AUSENTE | N82: RECUSA | AI82: RECUSA | AJ82: 6014.2022/0003993-0 | AO82: RECUSA | BB82: RECUSA | BC82: =IF(AY82-ON82=0,"",AY82-O82) | BD82: =IF(AND(AI82<>"SIM",AI82="UH"),"AA","INDENIZAÇÃO") -> INDENIZAÇÃO | BE82: =IF(AND(AY82<>"AGUARDANDO",AY82<>"",N82="AUXÍLIO ALUGUEL ATÉ INDENIZAÇÃO"),"SIM","NÃO") -> NÃO
A83: 70 | B83: ALFREDO ÁVILA | C83: 3 | D83: 0 | E83: 0 | F83: 001/0057/E | G83: OCUPADO | H83: RESIDENCIAL | I83: INQUILINO | J83: CAMILA JAQUELINE DOS SANTOS SAMPAIO | K83: 66.468.985-1 | L83: 076.625.779-70 | N83: RECUSA | AB83: JENIFFER VITORIA OLIVEIRA BASILIO | AC83: 54.635.131-1 | AD83: 449.539.958-64 | AE83: PROPRIETÁRIO NÃO RESIDENTE | AI83: RECUSA | AJ83: 6014.2022/0003993-0 | AO83: RECUSA | BB83: RECUSA | BC83: =IF(AY83-ON83=0,"",AY83-O83) | BD83: =IF(AND(AI83<>"SIM",AI83="UH"),"AA","INDENIZAÇÃO") -> INDENIZAÇÃO | BE83: =IF(AND(AY83<>"AGUARDANDO",AY83<>"",N83="AUXÍLIO ALUGUEL ATÉ INDENIZAÇÃO"),"SIM","NÃO") -> NÃO
A84: 71 | B84: ALFREDO ÁVILA | C84: 3 | D84: 0 | E84: 0 | F84: 001/0059/A | G84: OCUPADO | H84: RESIDENCIAL | I84: PROPRIETÁRIO RESIDENTE | J84: EVELINE SPINOLA SILVA LIMAS | K84: 41.354.041-8 | L84: 341.196.818-40 | M84: CADASTRADO | N84: INDENIZAÇÃO | O84: 45467 | P84: N/A | Q84: N/A | R84: N/A | S84: N/A | T84: N/A | U84: N/A | V84: N/A | W84: N/A | X84: N/A | Y84: N/A | Z84: N/A | AB84: EVELINE SPINOLA SILVA LIMAS | AC84: 41.354.041-8 | AD84: 341.196.818-40 | AE84: PROPRIETÁRIO RESIDENTE | AF84: CADASTRADO | AG84: 96200 | AH84: 96200 | AI84: SIM | AJ84: 6014.2022/0003993-0 | AK84: FINALIZADO | AL84: FINALIZADO | AM84: FINALIZADO | AN84: SEM PENDÊNCIA | AP84: 6014.2024/0003145-2 | AQ84: DUPLO ATENDIMENTO - DEVOLVIDO DTS | BA84: OCUPADO | BC84: =IF(AY84-ON84=0,"",AY84-O84) | BD84: =IF(AND(AI84<>"SIM",AI84="UH"),"AA","INDENIZAÇÃO") -> INDENIZAÇÃO | BE84: =IF(AND(AY84<>"AGUARDANDO",AY84<>"",N84="AUXÍLIO ALUGUEL ATÉ INDENIZAÇÃO"),"SIM","NÃO") -> NÃO
A85: 72 | B85: ALFREDO ÁVILA | C85: 3 | D85: 0 | E85: 0 | F85: 001/0060/A | G85: OCUPADO | H85: RESIDENCIAL | I85: PROPRIETÁRIO RESIDENTE | J85: FERNANDO DA COSTA RODRIGUES | K85: 43.398.162-3 | L85: 457.370.858-80 | M85: CADASTRADO | N85: INDENIZAÇÃO | O85: 45433 | P85: N/A | Q85: N/A | R85: N/A | S85: N/A | T85: N/A | U85: N/A | V85: N/A | W85: N/A | X85: N/A | Y85: N/A | Z85: N/A | AB85: FERNANDO DA COSTA RODRIGUES | AC85: 43.398.162-3 | AD85: 457.370.858-80 | AE85: PROPRIETÁRIO RESIDENTE | AF85: CADASTRADO | AG85: 525400 | AH85: 525400 | AI85: SIM | AJ85: 6014.2022/0003993-0 | AK85: 101157896 | AL85: AGUARDANDO ASSINATURA COORDENAÇÃO CTS - TERMO VALOR ALTO | AM85: FINALIZADO | AN85: TERMO ASSINADO SECRETÁRIO | AO85: TERMO VALOR ALTO | AP85: 6014.2024/0002531-2 | AQ85: TERMO VALOR ALTO | BC85: =IF(AY85-ON85=0,"",AY85-O85) | BD85: =IF(AND(AI85<>"SIM",AI85="UH"),"AA","INDENIZAÇÃO") -> INDENIZAÇÃO | BE85: =IF(AND(AY85<>"AGUARDANDO",AY85<>"",N85="AUXÍLIO ALUGUEL ATÉ INDENIZAÇÃO"),"SIM","NÃO") -> NÃO
A86: 73 | B86: ALFREDO ÁVILA | C86: 3 | D86: 0 | E86: 0 | F86: 001/0061/A | G86: OCUPADO | H86: RESIDENCIAL | I86: PROPRIETÁRIO RESIDENTE | J86: VERENE REGINA NOGUEIRA DA SILVA | K86: 63.135.833-X | L86: 770.777.684-49 | M86: CADASTRADO | N86: INDENIZAÇÃO | O86: 45463 | P86: N/A | Q86: N/A | R86: N/A | S86: N/A | T86: N/A | U86: N/A | V86: N/A | W86: N/A | X86: N/A | Y86: N/A | Z86: N/A | AB86: VERENE REGINA NOGUEIRA DA SILVA | AC86: 63.135.833-X | AD86: 770.777.684-49 | AE86: PROPRIETÁRIO RESIDENTE | AF86: CADASTRADO | AG86: 10665.64 | AH86: =AG86+30000 -> 40665.64 | AI86: SIM | AJ86: 6014.2022/0003993-0 | AK86: FINALIZADO | AL86: FINALIZADO | AM86: FINALIZADO | AN86: SEM PENDÊNCIA | AO86: Aguardando assinatura do Secretário no Termo de Indenização | AP86: 6014.2024/0002698-0 | AQ86: FINALIZADO | AR86: FINALIZADO | AS86: FINALIZADO | AT86: FINALIZADO | AU86: 45510 | AV86: FINALIZADO | AW86: FINALIZADO | AX86: 45544 | AY86: 45544 | AZ86: AGUARDANDO | BA86: LIBERADO DEMOLIÇÃO | BB86: FINALIZADO | BC86: =IF(AY86-ON86=0,"",AY86-O86) -> 81 | BD86: =IF(AND(AI86<>"SIM",AI86="UH"),"AA","INDENIZAÇÃO") -> INDENIZAÇÃO | BE86: =IF(AND(AY86<>"AGUARDANDO",AY86<>"",N86="AUXÍLIO ALUGUEL ATÉ INDENIZAÇÃO"),"SIM","NÃO") -> NÃO | BF86: N/A | BG86: N/A | BH86: N/A | BI86: FINALIZADO | BJ86: FINALIZADO | BK86: 45621 | BL86: FINALIZADO | BM86: AGUARDANDO
A87: 74 | B87: ALFREDO ÁVILA | C87: 3 | D87: 0 | E87: 0 | F87: 001/0061/B | G87: OCUPADO | H87: RESIDENCIAL | I87: INQUILINO | J87: LEONARDO BORGES DOS SANTOS | K87: 52.367.321-8 | L87: 489.206.338-00 | N87: RECUSA | AB87: MARCOS ANTONIO PEREIRA DOS SANTOS | AC87: 29.828.562-9 | AD87: 270.342.998-38 | AE87: PROPRIETÁRIO NÃO RESIDENTE | AI87: RECUSA | AJ87: 6014.2022/0003993-0 | AO87: RECUSA | BB87: RECUSA | BC87: =IF(AY87-ON87=0,"",AY87-O87) | BD87: =IF(AND(AI87<>"SIM",AI87="UH"),"AA","INDENIZAÇÃO") -> INDENIZAÇÃO | BE87: =IF(AND(AY87<>"AGUARDANDO",AY87<>"",N87="AUXÍLIO ALUGUEL ATÉ INDENIZAÇÃO"),"SIM","NÃO") -> NÃO
A88: 75 | B88: ALFREDO ÁVILA | C88: 1 | D88: 0 | E88: 0 | F88: 001/0062/A | G88: OCUPADO | H88: RESIDENCIAL | I88: PROPRIETÁRIO RESIDENTE | J88: INGRID DALYLLA DE PAULA CAETANO | K88: 43.572.592-0 | L88: 390.685.508-29 | M88: CADASTRADO | N88: INDENIZAÇÃO | O88: 44900 | P88: N/A | Q88: N/A | R88: N/A | S88: N/A | T88: N/A | U88: N/A | V88: N/A | W88: N/A | X88: N/A | Y88: N/A | Z88: N/A | AB88: INGRID DALYLLA DE PAULA CAETANO | AC88: 43.572.592-0 | AD88: 390.685.508-29 | AE88: PROPRIETÁRIO RESIDENTE | AF88: CADASTRADO | AG88: 7000 | AH88: 37000 | AI88: SIM | AJ88: 6014.2022/0003993-0 | AK88: FINALIZADO | AL88: FINALIZADO | AM88: FINALIZADO | AN88: SEM PENDÊNCIA | AP88: 6014.2023/0000358-9 | AQ88: FINALIZADO | AR88: FINALIZADO | AS88: FINALIZADO | AT88: FINALIZADO | AU88: 45014 | AV88: FINALIZADO | AW88: FINALIZADO | AX88: 45022 | AY88: 45022 | AZ88: 45056 | BA88: DEMOLIDO | BB88: FINALIZADO | BC88: =IF(AY88-ON88=0,"",AY88-O88) -> 122 | BD88: =IF(AND(AI88<>"SIM",AI88="UH"),"AA","INDENIZAÇÃO") -> INDENIZAÇÃO | BE88: =IF(AND(AY88<>"AGUARDANDO",AY88<>"",N88="AUXÍLIO ALUGUEL ATÉ INDENIZAÇÃO"),"SIM","NÃO") -> NÃO | BF88: N/A | BG88: N/A | BH88: N/A | BI88: FINALIZADO | BJ88: FINALIZADO | BK88: 45190 | BL88: FINALIZADO | BM88: FINALIZADO
A89: 76 | B89: ALFREDO ÁVILA | C89: 1 | D89: 0 | E89: 0 | F89: 001/0063/A | G89: OCUPADO | H89: RESIDENCIAL | I89: PROPRIETÁRIO RESIDENTE | J89: VITORIA REGINA NOGUEIRA OLIVEIRA | K89: 50532157-9 | L89: 497.368.808-85 | M89: CADASTRADO | N89: INDENIZAÇÃO | O89: 44900 | P89: N/A | Q89: N/A | R89: N/A | S89: N/A | T89: N/A | U89: N/A | V89: N/A | W89: N/A | X89: N/A | Y89: N/A | Z89: N/A | AB89: VITORIA REGINA NOGUEIRA OLIVEIRA | AC89: 50532157-9 | AD89: 497.368.808-85 | AE89: PROPRIETÁRIO RESIDENTE | AF89: CADASTRADO | AG89: 37500 | AH89: 60000 | AI89: SIM | AJ89: 6014.2022/0003993-0 | AK89: FINALIZADO | AL89: FINALIZADO | AM89: FINALIZADO | AN89: SEM PENDÊNCIA | AP89: 6014.2023/0000363-5 | AQ89: FINALIZADO | AR89: FINALIZADO | AS89: FINALIZADO | AT89: FINALIZADO | AU89: 45014 | AV89: FINALIZADO | AW89: FINALIZADO | AX89: 45022 | AY89: 45022 | AZ89: 45056 | BA89: DEMOLIDO | BB89: FINALIZADO | BC89: =IF(AY89-ON89=0,"",AY89-O89) -> 122 | BD89: =IF(AND(AI89<>"SIM",AI89="UH"),"AA","INDENIZAÇÃO") -> INDENIZAÇÃO | BE89: =IF(AND(AY89<>"AGUARDANDO",AY89<>"",N89="AUXÍLIO ALUGUEL ATÉ INDENIZAÇÃO"),"SIM","NÃO") -> NÃO | BF89: N/A | BG89: N/A | BH89: N/A | BI89: FINALIZADO | BJ89: FINALIZADO | BK89: 45190 | BL89: FINALIZADO | BM89: FINALIZADO
A90: 77 | B90: ALFREDO ÁVILA | C90: 3 | D90: 0 | E90: 0 | F90: 001/0064/A | G90: OCUPADO | H90: RESIDENCIAL | I90: PROPRIETÁRIO RESIDENTE | J90: ELOANA CRISTINA DE SOUZA MELO | K90: 41.392.693-X | L90: 420.430.358-78 | M90: CADASTRADO | N90: INDENIZAÇÃO | O90: 45467 | P90: N/A | Q90: N/A | R90: N/A | S90: N/A | T90: N/A | U90: N/A | V90: N/A | W90: N/A | X90: N/A | Y90: N/A | Z90: N/A | AB90: ELOANA CRISTINA DE SOUZA MELO | AC90: 41.392.693-X | AD90: 420.430.358-78 | AE90: PROPRIETÁRIO RESIDENTE | AF90: CADASTRADO | AG90: 37300 | AH90: 60000 | AI90: SIM | AJ90: 6014.2022/0003993-0 | AK90: FINALIZADO | AL90: FINALIZADO | AM90: FINALIZADO | AN90: SEM PENDÊNCIA | AP90: 6014.2024/0002948-2 | AQ90: FINALIZADO | AR90: FINALIZADO | AS90: FINALIZADO | AT90: FINALIZADO | AU90: 45587 | AV90: FINALIZADO | AW90: FINALIZADO | AX90: 45600 | AY90: 45600 | AZ90: AGUARDANDO | BA90: LIBERADO DEMOLIÇÃO | BB90: FINALIZADO | BC90: =IF(AY90-ON90=0,"",AY90-O90) -> 133 | BD90: =IF(AND(AI90<>"SIM",AI90="UH"),"AA","INDENIZAÇÃO") -> INDENIZAÇÃO | BE90: =IF(AND(AY90<>"AGUARDANDO",AY90<>"",N90="AUXÍLIO ALUGUEL ATÉ INDENIZAÇÃO"),"SIM","NÃO") -> NÃO | BF90: N/A | BG90: N/A | BH90: N/A | BI90: FINALIZADO | BJ90: FINALIZADO | BK90: 45652 | BL90: FINALIZADO | BM90: AGUARDANDO
A91: 78 | B91: ALFREDO ÁVILA | C91: 3 | D91: 0 | E91: 0 | F91: 001/0065/A | G91: OCUPADO | H91: RESIDENCIAL | I91: PROPRIETÁRIO RESIDENTE | J91: HENRIQUE MELLO ELIAS | K91: 59.554.673-0 | L91: 504.344.890-34 | M91: CADASTRADO | N91: INDENIZAÇÃO | O91: 45470 | P91: N/A | Q91: N/A | R91: N/A | S91: N/A | T91: N/A | U91: N/A | V91: N/A | W91: N/A | X91: N/A | Y91: N/A | Z91: N/A | AB91: HENRIQUE MELLO ELIAS | AC91: 59.554.673-0 | AD91: 504.344.890-34 | AE91: PROPRIETÁRIO RESIDENTE | AF91: CADASTRADO | AG91: 9300 | AH91: =AG91+30000 -> 39300 | AI91: SIM | AJ91: 6014.2022/0003993-0 | AK91: FINALIZADO | AL91: FINALIZADO | AM91: FINALIZADO | AN91: SEM PENDÊNCIA | AP91: 6014.2024/0003150-9 | AQ91: FINALIZADO | AR91: FINALIZADO | AS91: FINALIZADO | AT91: FINALIZADO | AU91: 45537 | AV91: FINALIZADO | AW91: FINALIZADO | AX91: 45545 | AY91: 45545 | AZ91: AGUARDANDO | BA91: DEMOLIDO | BB91: FINALIZADO | BC91: =IF(AY91-ON91=0,"",AY91-O91) -> 75 | BD91: =IF(AND(AI91<>"SIM",AI91="UH"),"AA","INDENIZAÇÃO") -> INDENIZAÇÃO | BE91: =IF(AND(AY91<>"AGUARDANDO",AY91<>"",N91="AUXÍLIO ALUGUEL ATÉ INDENIZAÇÃO"),"SIM","NÃO") -> NÃO | BF91: N/A | BG91: N/A | BH91: N/A | BI91: FINALIZADO | BJ91: FINALIZADO | BK91: 45621 | BL91: FINALIZADO | BM91: AGUARDANDO
A92: 79 | B92: ALFREDO ÁVILA | C92: 3 | D92: 0 | E92: 0 | F92: 001/0066/A | G92: OCUPADO | H92: RESIDENCIAL | I92: PROPRIETÁRIO RESIDENTE | J92: SONIA JOSEFA DA SILVA | K92: 25.106.292-2 | L92: 328.783.108-96 | M92: CADASTRADO | N92: AUXÍLIO ALUGUEL UH | O92: 45019 | P92: 45435 | Q92: 6014.2023/0000399-6 | R92: FINALIZADO | S92: FINALIZADO | T92: FINALIZADO | U92: 45475 | V92: FINALIZADO | X92: 45492 | Z92: 45499 | AB92: SONIA JOSEFA DA SILVA | AC92: 25.106.292-2 | AD92: 328.783.108-96 | AE92: PROPRIETÁRIO RESIDENTE | AJ92: 6014.2022/0003993-0 | BC92: =IF(AY92-ON92=0,"",AY92-O92) | BD92: =IF(AND(AI92<>"SIM",AI92="UH"),"AA","INDENIZAÇÃO") -> INDENIZAÇÃO | BE92: =IF(AND(AY92<>"AGUARDANDO",AY92<>"",N92="AUXÍLIO ALUGUEL ATÉ INDENIZAÇÃO"),"SIM","NÃO") -> NÃO
A93: 80 | B93: ALFREDO ÁVILA | C93: 3 | D93: 0 | E93: 0 | F93: 001/0067/A | G93: OCUPADO | H93: RESIDENCIAL | I93: PROPRIETÁRIO RESIDENTE | J93: WILLIAM ALVES DOS SANTOS | K93: 48.449.047-3 | L93: 376.241.098-40 | M93: CADASTRADO | N93: AUXÍLIO ALUGUEL UH | O93: 45019 | P93: 45485 | Q93: 6014.2023/0000399-6 | R93: FINALIZADO | S93: FINALIZADO | T93: FINALIZADO | U93: 45505 | V93: FINALIZADO | AB93: WILLIAM ALVES DOS SANTOS | AC93: 48.449.047-3 | AD93: 376.241.098-40 | AE93: PROPRIETÁRIO RESIDENTE | AF93: CADASTRADO | AJ93: 6014.2022/0003993-0 | BC93: =IF(AY93-ON93=0,"",AY93-O93) | BD93: =IF(AND(AI93<>"SIM",AI93="UH"),"AA","INDENIZAÇÃO") -> INDENIZAÇÃO | BE93: =IF(AND(AY93<>"AGUARDANDO",AY93<>"",N93="AUXÍLIO ALUGUEL ATÉ INDENIZAÇÃO"),"SIM","NÃO") -> NÃO
A94: 81 | B94: ALFREDO ÁVILA | C94: 3 | D94: 0 | E94: 0 | F94: 001/0068/A | G94: OCUPADO | H94: RESIDENCIAL | I94: INQUILINO | J94: THAIS SANTANA DA SILVA | K94: 55.055.138-4 | L94: 708.965.224-66 | M94: CADASTRADO | N94: AUXÍLIO ALUGUEL UH | O94: 45467 | P94: 23-fev-24 | Q94: 6014.2023/0000399-6 | R94: FINALIZADO | S94: FINALIZADO | T94: FINALIZADO | U94: 45385 | V94: FINALIZADO | W94: 45385 | X94: 45404 | Y94: 45414 | AB94: IVANISE PESSOA SANTANA SILVA | AC94: 67.186.188-8 | AD94: 024.686.954-29 | AE94: PROPRIETARIO NÃO RESIDENTE | AF94: CADASTRADO | AG94: 47600 | AH94: 47600 | AI94: SIM | AJ94: 6014.2022/0003993-0 | AK94: FINALIZADO | AL94: FINALIZADO | AM94: FINALIZADO | AN94: SEM PENDÊNCIA | AP94: 6014.2024/0002995-4 | AQ94: FINALIZADO | AR94: FINALIZADO | AS94: FINALIZADO | AT94: FINALIZADO | AU94: 45558 | AV94: FINALIZADO | AW94: FINALIZADO | AX94: 45561 | AY94: 45561 | AZ94: AGUARDANDO | BA94: LIBERADO DEMOLIÇÃO | BB94: FINALIZADO | BC94: =IF(AY94-ON94=0,"",AY94-O94) -> 94 | BD94: =IF(AND(AI94<>"SIM",AI94="UH"),"AA","INDENIZAÇÃO") -> INDENIZAÇÃO | BE94: =IF(AND(AY94<>"AGUARDANDO",AY94<>"",N94="AUXÍLIO ALUGUEL ATÉ INDENIZAÇÃO"),"SIM","NÃO") -> NÃO | BF94: N/A | BG94: N/A | BH94: N/A | BI94: FINALIZADO | BJ94: FINALIZADO | BK94: 45621 | BL94: FINALIZADO | BM94: AGUARDANDO
A95: 82 | B95: ALFREDO ÁVILA | C95: 3 | D95: 0 | E95: 0 | F95: 001/0068/B | G95: OCUPADO | H95: RESIDENCIAL | I95: INQUILINO | J95: TALITA RAMOS CAETANO | K95: 42.649.234-1 | L95: 447.768.748-65 | M95: CADASTRADO | N95: AUXÍLIO ALUGUEL UH | O95: 45467 | P95: 23-fev-24 | Q95: 6014.2023/0000399-6 | R95: FINALIZADO | S95: FINALIZADO | T95: FINALIZADO | U95: 45385 | V95: FINALIZADO | W95: 45385 | X95: 45404 | Y95: 45406 | AB95: DENISE FELIX DE ANDRADE | AC95: 50.272.562-X | AD95: 387.337.268-17 | AE95: PROPRIETARIO NÃO RESIDENTE | AF95: CADASTRADO | AG95: 23500 | AH95: 23500 | AI95: SIM | AJ95: 6014.2022/0003993-0 | AK95: FINALIZADO | AL95: FINALIZADO | AM95: FINALIZADO | AN95: SEM PENDÊNCIA | AP95: 6014.2024/0002940-7 | AQ95: FINALIZADO | AR95: FINALIZADO | AS95: FINALIZADO | AT95: FINALIZADO | AU95: 45569 | AV95: FINALIZADO | AW95: FINALIZADO | AX95: 45579 | AY95: 45579 | AZ95: AGUARDANDO | BA95: LIBERADO DEMOLIÇÃO | BB95: FINALIZADO | BC95: =IF(AY95-ON95=0,"",AY95-O95) -> 112 | BD95: =IF(AND(AI95<>"SIM",AI95="UH"),"AA","INDENIZAÇÃO") -> INDENIZAÇÃO | BE95: =IF(AND(AY95<>"AGUARDANDO",AY95<>"",N95="AUXÍLIO ALUGUEL ATÉ INDENIZAÇÃO"),"SIM","NÃO") -> NÃO | BF95: N/A | BG95: N/A | BH95: N/A | BI95: FINALIZADO | BJ95: FINALIZADO | BK95: 45621 | BL95: FINALIZADO | BM95: AGUARDANDO
A96: 83 | B96: ALFREDO ÁVILA | C96: 3 | D96: 0 | E96: 0 | F96: 001/0069/A | G96: OCUPADO | H96: RESIDENCIAL | I96: PROPRIETÁRIO RESIDENTE | J96: ESPEDITO ANSELMO LIMA | K96: 11.118.783-7 | L96: 163.138.218-74 | M96: CADASTRADO | N96: AUXÍLIO ALUGUEL UH | O96: 45019 | P96: 45435 | Q96: 6014.2023/0000399-6 | R96: FINALIZADO | S96: FINALIZADO | T96: FINALIZADO | U96: 45475 | V96: FINALIZADO | X96: 45492 | AB96: ESPEDITO ANSELMO LIMA | AC96: 11.118.783-7 | AD96: 163.138.218-74 | AE96: PROPRIETÁRIO RESIDENTE | AF96: CADASTRADO | AJ96: 6014.2022/0003993-0 | BC96: =IF(AY96-ON96=0,"",AY96-O96) | BD96: =IF(AND(AI96<>"SIM",AI96="UH"),"AA","INDENIZAÇÃO") -> INDENIZAÇÃO | BE96: =IF(AND(AY96<>"AGUARDANDO",AY96<>"",N96="AUXÍLIO ALUGUEL ATÉ INDENIZAÇÃO"),"SIM","NÃO") -> NÃO
A97: 84 | B97: ALFREDO ÁVILA | C97: 3 | D97: 0 | E97: 0 | F97: 001/0069/B | G97: VAZIO | H97: RESIDENCIAL | I97: PROPRIETÁRIO NÃO RESIDENTE | J97: EMILIO ANSELMO LIMA | K97: 200.758.4307-4 | L97: 389.364.103-34 | M97: CADASTRADO | N97: INDENIZAÇÃO | O97: 45474 | P97: N/A | Q97: N/A | R97: N/A | S97: N/A | T97: N/A | U97: N/A | V97: N/A | W97: N/A | X97: N/A | Y97: N/A | Z97: N/A | AB97: EMILIO ANSELMO LIMA | AC97: 200.758.4307-4 | AD97: 389.364.103-34 | AE97: PROPRIETARIO NÃO RESIDENTE | AF97: CADASTRADO | AG97: 36400 | AH97: 60000 | AI97: SIM | AJ97: 6014.2022/0003993-0 | AK97: FINALIZADO | AL97: FINALIZADO | AM97: FINALIZADO | AN97: SEM PENDÊNCIA | AP97: 6014.2024/0003126-6 | AQ97: FINALIZADO | AR97: FINALIZADO | AS97: FINALIZADO | AT97: FINALIZADO | AU97: 45537 | AV97: FINALIZADO | AW97: FINALIZADO | AX97: 45545 | AY97: 45545 | AZ97: AGUARDANDO | BA97: LIBERADO DEMOLIÇÃO | BB97: FINALIZADO | BC97: =IF(AY97-ON97=0,"",AY97-O97) -> 71 | BD97: =IF(AND(AI97<>"SIM",AI97="UH"),"AA","INDENIZAÇÃO") -> INDENIZAÇÃO | BE97: =IF(AND(AY97<>"AGUARDANDO",AY97<>"",N97="AUXÍLIO ALUGUEL ATÉ INDENIZAÇÃO"),"SIM","NÃO") -> NÃO | BF97: N/A | BG97: N/A | BH97: N/A | BI97: FINALIZADO | BJ97: FINALIZADO | BK97: 45621 | BL97: FINALIZADO | BM97: AGUARDANDO
A98: 85 | B98: ALFREDO ÁVILA | C98: 3 | D98: 0 | E98: 0 | F98: 001/0070/A | G98: OCUPADO | H98: RESIDENCIAL | I98: PROPRIETÁRIO RESIDENTE | J98: ISAURA CONCEIÇÃO ASSIS DOS NASCIMENTO SILVA | K98: 43.315.561-9 | L98: 323.090.218-14 | M98: CADASTRADO | N98: INDENIZAÇÃO | O98: 45467 | P98: N/A | Q98: N/A | R98: N/A | S98: N/A | T98: N/A | U98: N/A | V98: N/A | W98: N/A | X98: N/A | Y98: N/A | Z98: N/A | AB98: ISAURA CONCEIÇÃO ASSIS DOS NASCIMENTO SILVA | AC98: 43.315.561-9 | AD98: 323.090.218-14 | AE98: PROPRIETÁRIO RESIDENTE | AF98: CADASTRADO | AG98: 82000 | AH98: 82000 | AI98: SIM | AJ98: 6014.2022/0003993-0 | AK98: FINALIZADO | AL98: FINALIZADO | AM98: FINALIZADO | AN98: SEM PENDÊNCIA | AP98: 6014.2024/0002994-6 | AQ98: FINALIZADO | AR98: FINALIZADO | AS98: FINALIZADO | AT98: FINALIZADO | AU98: 45537 | AV98: FINALIZADO | AW98: FINALIZADO | AX98: 45545 | AY98: 45545 | AZ98: AGUARDANDO | BA98: LIBERADO DEMOLIÇÃO | BB98: FINALIZADO | BC98: =IF(AY98-ON98=0,"",AY98-O98) -> 78 | BD98: =IF(AND(AI98<>"SIM",AI98="UH"),"AA","INDENIZAÇÃO") -> INDENIZAÇÃO | BE98: =IF(AND(AY98<>"AGUARDANDO",AY98<>"",N98="AUXÍLIO ALUGUEL ATÉ INDENIZAÇÃO"),"SIM","NÃO") -> NÃO | BF98: N/A | BG98: N/A | BH98: N/A | BI98: FINALIZADO | BJ98: FINALIZADO | BK98: 45621 | BL98: FINALIZADO | BM98: AGUARDANDO
A99: 86 | B99: ALFREDO ÁVILA | C99: 3 | D99: 0 | E99: 0 | F99: 001/0070/B | G99: OCUPADO | H99: RESIDENCIAL | I99: PROPRIETÁRIO RESIDENTE | J99: VERA LUCIA DE LIMA | K99: 13.493.781-8 | L99: 009.925.518-97 | M99: CADASTRADO | N99: INDENIZAÇÃO | O99: 45467 | P99: N/A | Q99: N/A | R99: N/A | S99: N/A | T99: N/A | U99: N/A | V99: N/A | W99: N/A | X99: N/A | Y99: N/A | Z99: N/A | AB99: VERA LUCIA DE LIMA | AC99: 13.493.781-8 | AD99: 009.925.518-97 | AE99: PROPRIETÁRIO RESIDENTE | AF99: CADASTRADO | AG99: 70200 | AH99: 70200 | AI99: SIM | AJ99: 6014.2022/0003993-0 | AK99: FINALIZADO | AL99: FINALIZADO | AM99: FINALIZADO | AN99: SEM PENDÊNCIA | AP99: 6014.2024/0003048-0 | AQ99: FINALIZADO | AR99: FINALIZADO | AS99: FINALIZADO | AT99: FINALIZADO | AU99: 45537 | AV99: FINALIZADO | AW99: FINALIZADO | AX99: 45545 | AY99: 45545 | AZ99: AGUARDANDO | BA99: LIBERADO DEMOLIÇÃO | BB99: FINALIZADO | BC99: =IF(AY99-ON99=0,"",AY99-O99) -> 78 | BD99: =IF(AND(AI99<>"SIM",AI99="UH"),"AA","INDENIZAÇÃO") -> INDENIZAÇÃO | BE99: =IF(AND(AY99<>"AGUARDANDO",AY99<>"",N99="AUXÍLIO ALUGUEL ATÉ INDENIZAÇÃO"),"SIM","NÃO") -> NÃO | BF99: N/A | BG99: N/A | BH99: N/A | BI99: FINALIZADO | BJ99: FINALIZADO | BK99: 45621 | BL99: FINALIZADO | BM99: AGUARDANDO
A100: 87 | B100: ALFREDO ÁVILA | C100: 3 | D100: 0 | E100: 0 | F100: 001/0070/C | G100: OCUPADO | H100: RESIDENCIAL | I100: PROPRIETÁRIO RESIDENTE | J100: CRISTIANE GOMES FAGUNDES SILVA | K100: 44.554.232-9 | L100: 351.956.718-00 | M100: CADASTRADO | N100: INDENIZAÇÃO | O100: 45467 | P100: N/A | Q100: N/A | R100: N/A | S100: N/A | T100: N/A | U100: N/A | V100: N/A | W100: N/A | X100: N/A | Y100: N/A | Z100: N/A | AB100: CRISTIANE GOMES FAGUNDES SILVA | AC100: 44.554.232-9 | AD100: 351.956.718-00 | AE100: PROPRIETÁRIO RESIDENTE | AF100: CADASTRADO | AG100: 47400 | AH100: 60000 | AI100: SIM | AJ100: 6014.2022/0003993-0 | AK100: FINALIZADO | AL100: FINALIZADO | AM100: FINALIZADO | AN100: SEM PENDÊNCIA | AP100: 6014.2024/0002937-7 | AQ100: FINALIZADO | AR100: FINALIZADO | AS100: FINALIZADO | AT100: FINALIZADO | AU100: 45537 | AV100: FINALIZADO | AW100: FINALIZADO | AX100: 45545 | AY100: 45545 | AZ100: AGUARDANDO | BA100: LIBERADO DEMOLIÇÃO | BB100: FINALIZADO | BC100: =IF(AY100-ON100=0,"",AY100-O100) -> 78 | BD100: =IF(AND(AI100<>"SIM",AI100="UH"),"AA","INDENIZAÇÃO") -> INDENIZAÇÃO | BE100: =IF(AND(AY100<>"AGUARDANDO",AY100<>"",N100="AUXÍLIO ALUGUEL ATÉ INDENIZAÇÃO"),"SIM","NÃO") -> NÃO | BF100: N/A | BG100: N/A | BH100: N/A | BI100: FINALIZADO | BJ100: FINALIZADO | BK100: 45621 | BL100: FINALIZADO | BM100: AGUARDANDO
A101: 88 | B101: ALFREDO ÁVILA | C101: 3 | D101: 0 | E101: 0 | F101: 001/0071/A | G101: OCUPADO | H101: RESIDENCIAL | N101: RECUSA | AI101: RECUSA | AJ101: 6014.2022/0003993-0 | AO101: RECUSA | BB101: RECUSA | BC101: =IF(AY101-ON101=0,"",AY101-O101) | BD101: =IF(AND(AI101<>"SIM",AI101="UH"),"AA","INDENIZAÇÃO") -> INDENIZAÇÃO | BE101: =IF(AND(AY101<>"AGUARDANDO",AY101<>"",N101="AUXÍLIO ALUGUEL ATÉ INDENIZAÇÃO"),"SIM","NÃO") -> NÃO
A102: 89 | B102: ALFREDO ÁVILA | C102: 3 | D102: 0 | E102: 0 | F102: 001/0072/A | G102: OCUPADO | H102: RESIDENCIAL | I102: PROPRIETÁRIO RESIDENTE | J102: JANAINA MARIA DOS SANTOS | K102: 36.063.131-9 | L102: 463.855.868-20 | M102: CADASTRADO | N102: INDENIZAÇÃO | O102: 45587 | P102: N/A | Q102: N/A | R102: N/A | S102: N/A | T102: N/A | U102: N/A | V102: N/A | W102: N/A | X102: N/A | Y102: N/A | Z102: N/A | AB102: JANAINA MARIA DOS SANTOS | AC102: 36.063.131-9 | AD102: 463.855.868-20 | AE102: PROPRIETÁRIO RESIDENTE | AF102: CADASTRADO | AG102: 34300 | AH102: 60000 | AI102: SIM | AJ102: 6014.2022/0003993-0 | AK102: FINALIZADO | AL102: FINALIZADO | AM102: FINALIZADO | AN102: SEM PENDÊNCIA | AP102: 6014.2024/0005237-9 | AQ102: FINALIZADO | AR102: FINALIZADO | AS102: FINALIZADO | AT102: FINALIZADO | AU102: 45755 | AV102: FINALIZADO | AW102: FINALIZADO | AX102: 45763 | AY102: 45763 | AZ102: AGUARDANDO | BA102: LIBERADO DEMOLIÇÃO | BB102: FINALIZADO | BC102: =IF(AY102-ON102=0,"",AY102-O102) -> 176 | BD102: =IF(AND(AI102<>"SIM",AI102="UH"),"AA","INDENIZAÇÃO") -> INDENIZAÇÃO | BE102: =IF(AND(AY102<>"AGUARDANDO",AY102<>"",N102="AUXÍLIO ALUGUEL ATÉ INDENIZAÇÃO"),"SIM","NÃO") -> NÃO | BF102: N/A | BG102: N/A | BH102: N/A | BI102: FINALIZADO | BJ102: FINALIZADO | BK102: 45783 | BL102: FINALIZADO | BM102: AGUARDANDO
A103: 90 | B103: ALFREDO ÁVILA | C103: 3 | D103: 0 | E103: 0 | F103: 001/0073/A | G103: OCUPADO | H103: NÃO RESIDENCIAL | I103: PROPRIETÁRIO NÃO RESIDENTE | J103: MARIA DOS SANTOS | K103: 54.966.487-7 | L103: 867.154.705-10 | M103: CADASTRADO | N103: INDENIZAÇÃO COMÉRCIO | O103: 45477 | P103: N/A | Q103: N/A | R103: N/A | S103: N/A | T103: N/A | U103: N/A | V103: N/A | W103: N/A | X103: N/A | Y103: N/A | Z103: N/A | AB103: MARIA DOS SANTOS | AC103: 54.966.487-7 | AD103: 867.154.705-10 | AE103: PROPRIETARIO NÃO RESIDENTE | AF103: CADASTRADO | AG103: 44800 | AH103: 60000 | AI103: SIM | AJ103: 6014.2022/0003993-0 | AK103: FINALIZADO | AL103: FINALIZADO | AM103: FINALIZADO | AN103: SEM PENDÊNCIA | AP103: 6014.2024/0003151-7 | AQ103: FINALIZADO | AR103: FINALIZADO | AS103: FINALIZADO | AT103: FINALIZADO | AU103: 45537 | AV103: FINALIZADO | AW103: FINALIZADO | AX103: 45541 | AY103: 45541 | AZ103: AGUARDANDO | BA103: LIBERADO DEMOLIÇÃO | BB103: FINALIZADO | BC103: =IF(AY103-ON103=0,"",AY103-O103) -> 64 | BD103: =IF(AND(AI103<>"SIM",AI103="UH"),"AA","INDENIZAÇÃO") -> INDENIZAÇÃO | BE103: =IF(AND(AY103<>"AGUARDANDO",AY103<>"",N103="AUXÍLIO ALUGUEL ATÉ INDENIZAÇÃO"),"SIM","NÃO") -> NÃO | BF103: N/A | BG103: N/A | BH103: N/A | BI103: FINALIZADO | BJ103: FINALIZADO | BK103: 45621 | BL103: FINALIZADO | BM103: AGUARDANDO
A104: 91 | B104: ALFREDO ÁVILA | C104: 3 | D104: 0 | E104: 0 | F104: 001/0073/B | G104: OCUPADO | H104: RESIDENCIAL | I104: PROPRIETÁRIO RESIDENTE | J104: MARIA DOS SANTOS | K104: 54.966.487-7 | L104: 867.154.705-10 | M104: CADASTRADO | N104: NÃO TEM ATENDIMENTO | O104: 45477 | P104: N/A | Q104: N/A | R104: N/A | S104: N/A | T104: N/A | U104: N/A | V104: N/A | W104: N/A | X104: N/A | Y104: N/A | Z104: N/A | AA104: RECEBEU INDENIZAÇÃO PELO SELO 001/0073/A | AB104: MARIA DOS SANTOS | AC104: 54.966.487-7 | AD104: 867.154.705-10 | AE104: PROPRIETÁRIO RESIDENTE | AF104: CADASTRADO | AG104: 0 | AH104: 0 | AI104: RECEBEU INDENIZAÇÃO PELO SELO 001/0073/A | AJ104: 6014.2022/0003993-0 | AK104: FINALIZADO | AL104: N/A | AM104: N/A | AN104: N/A | AO104: RECEBEU INDENIZAÇÃO PELO SELO 001/0073/A | AP104: N/A | AQ104: N/A | AR104: N/A | AS104: N/A | AT104: N/A | AU104: N/A | AV104: N/A | AW104: N/A | AX104: N/A | AY104: N/A | AZ104: AGUARDANDO | BA104: LIBERADO DEMOLIÇÃO | BB104: FINALIZADO | BC104: N/A | BD104: =IF(AND(AI104<>"SIM",AI104="UH"),"AA","INDENIZAÇÃO") -> INDENIZAÇÃO | BE104: =IF(AND(AY104<>"AGUARDANDO",AY104<>"",N104="AUXÍLIO ALUGUEL ATÉ INDENIZAÇÃO"),"SIM","NÃO") -> NÃO | BF104: N/A | BG104: N/A | BH104: N/A | BI104: N/A | BJ104: N/A | BK104: N/A | BL104: N/A | BM104: FINALIZADO
...

Sheet Quantitativo Fora da Demanda
A1: REPROVADOS QUE NÃO DEVERÃO SER REASSENTADOS NO ESPANHA | E1: APROVADOS SEM CONDOMÍNIO QUE DEVERÃO SER REASSENTADOS NO CHÁCARA DO CONDE
A2: ÁREA | B2: QTD | E2: ÁREA | F2: QTD
A3: AUXÍLIO ALUGUEL | B3: 39 | E3: AUXÍLIO ALUGUEL | F3: 54
A4: CANTINHO DO CÉU (OBRAS) | B4: 15 | E4: CANTINHO DO CÉU (OBRAS) SETORES: 138 E 140 | F4: 13
A5: FUMAÇA | B5: 7 | E5: FUMAÇA | F5: 15
A6: NEBLINA | B6: 2 | E6: NEBLINA | F6: 9
A7: LEBLON | B7: 0 | E7: LEBLON | F7: 9
A8: PABREU / PRAINHA | B8: 15 | E8: PABREU / PRAINHA | F8: 21
A9: TOTAL | B9: =SUM(B3:B8) -> 78 | E9: TOTAL | F9: =SUM(F3:F8) -> 121

Sheet Listas (não utilizar)
A1: Área | B1: Condomínio | C1: Bloco | D1: Apartamento | E1: SITAH / CAIXA | F1: Status CAIXA | G1: Adequacao Imovel | H1: Renúncia | I1: Pendência | J1: Pendências / Reprovados caixa
A2: ALTO DA ALEGRIA | B2: AVILA | C2: 1 | D2: 101 | E2: AGENDADO | F2: APROVADO | G2: NÃO | H2: NÃO | I2: CRAS | J2: RENDA SUPERIOR
A3: ALTO DA ALEGRIA (OBRAS) | B3: BARCELONA | C3: 2 | D3: 102 | E3: AGUARDANDO OFICIO | F3: REPROVADO | G3: FÍSICA | H3: RENDA | I3: CRAS + DOCUMENTOS | J3: CADMUT
A4: ALTO DA ALEGRIA (RESERVA) | B4: BILBAO | C4: 3 | D4: 103 | E4: ATENDIMENTO CANCELADO | F4: PENDENCIA | G4: VISUAL | H4: CADIN | I4: DOCUMENTOS | J4: CADIN
A5: ANTERO GOMES | B5: CEUTA | C5: 4 | D5: 104 | E5: CADMUT | F5: SEM DOSSIE | G5: INTELECTUAL | H5: ESTADO CIVIL | I5: CADIN
A6: CANTINHO DO CEU / GAIVOTAS | B6: IBIZA | C6: 5 | D6: 201 | E6: CHACARA DO CONDE | G6: AUDITIVA | H6: SEPARACAO | I6: CRAS + CADIN
A7: CANTINHO DO CEU / OBRAS | B7: LEAO | C7: 6 | D7: 202 | E7: CONFLITO | G7: NANISMO | I7: R.LI.AV.
A8: CASTRO ALVES | B8: MADRID | C8: 7 | D8: 203 | E8: ENVIADO CAIXA | I8: IEME
A9: COCAIA | B9: MELILLA | C9: 8 | D9: 204 | E9: FALECEU
A10: ERUNDINA | B10: PAMPLONA | C10: 9 | D10: 301 | E10: FALTANTE DOSSIÊ
A11: FUMACA | B11: SALAMANCA | C11: 10 | D11: 302 | E11: HABISP ACERTO DE ÁREA
A12: GUAICURI (OBRAS) | B12: TERUEL | C12: 11 | D12: 303 | E12: HABISP AGUARDANDO CRÍTICA
A13: GUAICURI / CIDADE JULIA | B13: VALENCIA | C13: 12 | D13: 304 | E13: HABISP PEND DE ATUALIZ CADASTRAL
A14: JARDIM MIRNA | B14: VALVERDE | C14: 13 | D14: 401 | E14: INDENIZACAO
A15: JARDIM SELMA II | B15: VITORIA | C15: 14 | D15: 402 | E15: PENDENCIA
A16: JARDIM TUBO | C16: 15 | D16: 403 | E16: PERMUTA
A17: LEBLON | D17: 404 | E17: PESQUISA SMADS
A18: MARGINAL DOIS / FUNDAO | D18: 501 | E18: REANALISE
A19: MATA VIRGEM / JD ELDORADO | D19: 502 | E19: RECLUSO
A20: NEBLINA | D20: 503 | E20: RELATÓRIO SOCIAL
A21: NORONHA | D21: 504 | E21: RENDA SUPERIOR
A22: NOVA GRAJAU | E22: RESISTENTE
A23: NOVA MARILDA | E23: TROCA DE TITULARIDADE
A24: NOVA VARGINHA
A25: PABREU / PRAINHA
A26: PENDENCIA GABINETE
A27: PILAO / APURA
A28: PILAO / DOIS
A29: PILAO / PAULISTAS
A30: SANTA AMELIA
A31: VALE VERDE / MONTE VERDE
A32: VILA BREJINHO
A33: VILA NASCENTE
A34: ZR / COSTA BRANCA
A35: VILA RUBI

Sheet QUANT COND
A1: CONDOMINIOS | B1: QUANT
A2: AVILA | B2: =COUNTIF(#REF!,'QUANT COND'!A2) -> #REF!
A3: BARCELONA | B3: =COUNTIF(#REF!,'QUANT COND'!A3) -> #REF!
A4: BILBAO | B4: =COUNTIF(#REF!,'QUANT COND'!A4) -> #REF!
A5: CEUTA | B5: =COUNTIF(#REF!,'QUANT COND'!A5) -> #REF!
A6: IBIZA | B6: =COUNTIF(#REF!,'QUANT COND'!A6) -> #REF!
A7: LEAO | B7: =COUNTIF(#REF!,'QUANT COND'!A7) -> #REF!
A8: MADRID | B8: =COUNTIF(#REF!,'QUANT COND'!A8) -> #REF!
A9: MELILLA | B9: =COUNTIF(#REF!,'QUANT COND'!A9) -> #REF!
A10: PAMPLONA | B10: =COUNTIF(#REF!,'QUANT COND'!A10) -> #REF!
A11: SALAMANCA | B11: =COUNTIF(#REF!,'QUANT COND'!A11) -> #REF!
A12: TERUEL | B12: =COUNTIF(#REF!,'QUANT COND'!A12) -> #REF!
A13: VALENCIA | B13: =COUNTIF(#REF!,'QUANT COND'!A13) -> #REF!
... A15: VITORIA | B15: =COUNTIF(#REF!,'QUANT COND'!A15) -> #REF!

Sheet OFÍCIOS
A1: PLANILHA DE CONFRONTO OFÍCIOS DE INDICAÇÃO COM ENVIADOS CAIXA ECONÔMICA FEDERAL - CEF
A2: TITULAR | B2: CPF | C2: Cônjuge | D2: CPF | E2: OFÍCIO | F2: DATA | G2: STATUS CEF | H2: DATA ENVIO CAIXA | I2: DUPLICIDADE OFÍCIO | J2: DATA | K2: DATA ENVIO CAIXA | L2: OFÍCIO DE INDICAÇÃO | M2: DATA OFÍCIO INDICAÇÃO | O2: NR OFICIO | P2: QUANT | Q2: APROV | R2: REPROV | S2: PEND | T2: SEM STATUS (ANÁLISE) | Y2: CEF BD | Z2: CEF OFICIOS | AA2: CEF PLANILHA
A3: ABEL MEDEIROS FILHO | B3: 27140979871 | E3: 1128 | F3: 42972 | G3: APROVADO | H3: 42979 | O3: 810 | P3: =COUNTIF(OFÍCIOS!E:E,O3) -> 156 | Q3: =COUNTIFS(OFÍCIOS!$E:$E,$O3,OFÍCIOS!$G:$G,"APROVADO") -> 149 | R3: =COUNTIFS(OFÍCIOS!$E:$E,$O3,OFÍCIOS!$G:$G,"REPROVADO") -> 3 | S3: =COUNTIFS(OFÍCIOS!$E:$E,$O3,OFÍCIOS!$G:$G,"PENDENCIA") -> 2 | T3: =COUNTIFS(OFÍCIOS!$E:$E,$O3,OFÍCIOS!$G:$G,"") -> 2 | U3: =SUM(Q3:T3) -> 156 | X3: FEITOS | Y3: 1850 | Z3: 1827 | AA3: =SUM(AA4:AA7) -> 1615
A4: ABELINA FERREIRA DOS SANTOS | B4: 39200633846 | O4: 1417 | P4: =COUNTIF(OFÍCIOS!E:E,O4) -> 42 | Q4: =COUNTIFS(OFÍCIOS!$E:$E,$O4,OFÍCIOS!$G:$G,"APROVADO") -> 36 | R4: =COUNTIFS(OFÍCIOS!$E:$E,$O4,OFÍCIOS!$G:$G,"REPROVADO") -> 3 | S4: =COUNTIFS(OFÍCIOS!$E:$E,$O4,OFÍCIOS!$G:$G,"PENDENCIA") -> 3 | T4: =COUNTIFS(OFÍCIOS!$E:$E,$O4,OFÍCIOS!$G:$G,"") -> 0 | U4: =SUM(Q4:T4) -> 42 | X4: APROVADOS | Y4: 1517 | Z4: 1427 | AA4: 1559
A5: ABIGAIL DE OLIVEIRA PAULINO | B5: 75489104872 | E5: 1752 | F5: 43051 | G5: APROVADO | H5: 43089 | L5: 1759 | O5: 1359 | P5: =COUNTIF(OFÍCIOS!E:E,O5) -> 14 | Q5: =COUNTIFS(OFÍCIOS!$E:$E,$O5,OFÍCIOS!$G:$G,"APROVADO") -> 13 | R5: =COUNTIFS(OFÍCIOS!$E:$E,$O5,OFÍCIOS!$G:$G,"REPROVADO") -> 1 | S5: =COUNTIFS(OFÍCIOS!$E:$E,$O5,OFÍCIOS!$G:$G,"PENDENCIA") -> 0 | T5: =COUNTIFS(OFÍCIOS!$E:$E,$O5,OFÍCIOS!$G:$G,"") -> 0 | U5: =SUM(Q5:T5) -> 14 | X5: REPROVADOS | Y5: 73 | Z5: 79 | AA5: 28
A6: ABILIO OLIVEIRA SANTOS | B6: 43286003620 | O6: 1350 | P6: =COUNTIF(OFÍCIOS!E:E,O6) -> 79 | Q6: =COUNTIFS(OFÍCIOS!$E:$E,$O6,OFÍCIOS!$G:$G,"APROVADO") -> 75 | R6: =COUNTIFS(OFÍCIOS!$E:$E,$O6,OFÍCIOS!$G:$G,"REPROVADO") -> 3 | S6: =COUNTIFS(OFÍCIOS!$E:$E,$O6,OFÍCIOS!$G:$G,"PENDENCIA") -> 0 | T6: =COUNTIFS(OFÍCIOS!$E:$E,$O6,OFÍCIOS!$G:$G,"") -> 1 | U6: =SUM(Q6:T6) -> 79 | X6: PENDENCIAS | Y6: 36 | Z6: 32 | AA6: 11
A7: ABRAHAO SANTOS SILVA | O7: 1343 | P7: =COUNTIF(OFÍCIOS!E:E,O7) -> 6 | Q7: =COUNTIFS(OFÍCIOS!$E:$E,$O7,OFÍCIOS!$G:$G,"APROVADO") -> 5 | R7: =COUNTIFS(OFÍCIOS!$E:$E,$O7,OFÍCIOS!$G:$G,"REPROVADO") -> 0 | S7: =COUNTIFS(OFÍCIOS!$E:$E,$O7,OFÍCIOS!$G:$G,"PENDENCIA") -> 0 | T7: =COUNTIFS(OFÍCIOS!$E:$E,$O7,OFÍCIOS!$G:$G,"") -> 1 | U7: =SUM(Q7:T7) -> 6 | X7: SS / ANALISE | Y7: 224 | Z7: 275 | AA7: 17
A8: ADAIR DA SILVA BARROS | B8: 97443271620 | E8: 1106 | F8: 42965 | G8: APROVADO | H8: 42978 | O8: 1267 | P8: =COUNTIF(OFÍCIOS!E:E,O8) -> 34 | Q8: =COUNTIFS(OFÍCIOS!$E:$E,$O8,OFÍCIOS!$G:$G,"APROVADO") -> 28 | R8: =COUNTIFS(OFÍCIOS!$E:$E,$O8,OFÍCIOS!$G:$G,"REPROVADO") -> 5 | S8: =COUNTIFS(OFÍCIOS!$E:$E,$O8,OFÍCIOS!$G:$G,"PENDENCIA") -> 1 | T8: =COUNTIFS(OFÍCIOS!$E:$E,$O8,OFÍCIOS!$G:$G,"") -> 0 | U8: =SUM(Q8:T8) -> 34
A9: ADALBERTO CARVALHO DE OLIVEIRA | B9: 98058690597 | E9: 423 | F9: 43182 | G9: APROVADO | O9: 1262 | P9: =COUNTIF(OFÍCIOS!E:E,O9) -> 8 | Q9: =COUNTIFS(OFÍCIOS!$E:$E,$O9,OFÍCIOS!$G:$G,"APROVADO") -> 7 | R9: =COUNTIFS(OFÍCIOS!$E:$E,$O9,OFÍCIOS!$G:$G,"REPROVADO") -> 1 | S9: =COUNTIFS(OFÍCIOS!$E:$E,$O9,OFÍCIOS!$G:$G,"PENDENCIA") -> 0 | T9: =COUNTIFS(OFÍCIOS!$E:$E,$O9,OFÍCIOS!$G:$G,"") -> 0 | U9: =SUM(Q9:T9) -> 8
A10: ADALBERTO CAVALCANTE DOS SANTOS | B10: 38088438888 | O10: 1106 | P10: =COUNTIF(OFÍCIOS!E:E,O10) -> 78 | Q10: =COUNTIFS(OFÍCIOS!$E:$E,$O10,OFÍCIOS!$G:$G,"APROVADO") -> 73 | R10: =COUNTIFS(OFÍCIOS!$E:$E,$O10,OFÍCIOS!$G:$G,"REPROVADO") -> 5 | S10: =COUNTIFS(OFÍCIOS!$E:$E,$O10,OFÍCIOS!$G:$G,"PENDENCIA") -> 0 | T10: =COUNTIFS(OFÍCIOS!$E:$E,$O10,OFÍCIOS!$G:$G,"") -> 0 | U10: =SUM(Q10:T10) -> 78
A11: ADALMA MOREIRA DA ROCHA | B11: 26939799869 | E11: 573 | F11: 43224 | O11: 1128 | P11: =COUNTIF(OFÍCIOS!E:E,O11) -> 92 | Q11: =COUNTIFS(OFÍCIOS!$E:$E,$O11,OFÍCIOS!$G:$G,"APROVADO") -> 91 | R11: =COUNTIFS(OFÍCIOS!$E:$E,$O11,OFÍCIOS!$G:$G,"REPROVADO") -> 1 | S11: =COUNTIFS(OFÍCIOS!$E:$E,$O11,OFÍCIOS!$G:$G,"PENDENCIA") -> 0 | T11: =COUNTIFS(OFÍCIOS!$E:$E,$O11,OFÍCIOS!$G:$G,"") -> 0 | U11: =SUM(Q11:T11) -> 92
A12: ADAMILTON PEREIRA DA SILVA ( ALANA ) | B12: 34470559873 | E12: 292 | F12: 43168 | G12: APROVADO | H12: 43182 | L12: 318 | O12: 1214 | P12: =COUNTIF(OFÍCIOS!E:E,O12) -> 76 | Q12: =COUNTIFS(OFÍCIOS!$E:$E,$O12,OFÍCIOS!$G:$G,"APROVADO") -> 71 | R12: =COUNTIFS(OFÍCIOS!$E:$E,$O12,OFÍCIOS!$G:$G,"REPROVADO") -> 3 | S12: =COUNTIFS(OFÍCIOS!$E:$E,$O12,OFÍCIOS!$G:$G,"PENDENCIA") -> 0 | T12: =COUNTIFS(OFÍCIOS!$E:$E,$O12,OFÍCIOS!$G:$G,"") -> 2 | U12: =SUM(Q12:T12) -> 76
A13: ADAO MENDES AGOSTINHO | B13: 14369564808 | O13: 1241 | P13: =COUNTIF(OFÍCIOS!E:E,O13) -> 33 | Q13: =COUNTIFS(OFÍCIOS!$E:$E,$O13,OFÍCIOS!$G:$G,"APROVADO") -> 32 | R13: =COUNTIFS(OFÍCIOS!$E:$E,$O13,OFÍCIOS!$G:$G,"REPROVADO") -> 0 | S13: =COUNTIFS(OFÍCIOS!$E:$E,$O13,OFÍCIOS!$G:$G,"PENDENCIA") -> 1 | T13: =COUNTIFS(OFÍCIOS!$E:$E,$O13,OFÍCIOS!$G:$G,"") -> 0 | U13: =SUM(Q13:T13) -> 33
A14: ADEGMARIO DOS SANTOS | B14: 39544185844 | E14: 810 | F14: 42915 | G14: APROVADO | H14: 42921 | L14: 568-17 | O14: 1422 | P14: =COUNTIF(OFÍCIOS!E:E,O14) -> 7 | Q14: =COUNTIFS(OFÍCIOS!$E:$E,$O14,OFÍCIOS!$G:$G,"APROVADO") -> 7 | R14: =COUNTIFS(OFÍCIOS!$E:$E,$O14,OFÍCIOS!$G:$G,"REPROVADO") -> 0 | S14: =COUNTIFS(OFÍCIOS!$E:$E,$O14,OFÍCIOS!$G:$G,"PENDENCIA") -> 0 | T14: =COUNTIFS(OFÍCIOS!$E:$E,$O14,OFÍCIOS!$G:$G,"") -> 0 | U14: =SUM(Q14:T14) -> 7
A15: ADEILDA GABRIELA CAITANO SILVA | B15: 38772276860 | C15: LUCIANO MANOEL DA SILVA | D15: 3808243457 | O15: 1439 | P15: =COUNTIF(OFÍCIOS!E:E,O15) -> 16 | Q15: =COUNTIFS(OFÍCIOS!$E:$E,$O15,OFÍCIOS!$G:$G,"APROVADO") -> 14 | R15: =COUNTIFS(OFÍCIOS!$E:$E,$O15,OFÍCIOS!$G:$G,"REPROVADO") -> 1 | S15: =COUNTIFS(OFÍCIOS!$E:$E,$O15,OFÍCIOS!$G:$G,"PENDENCIA") -> 1 | T15: =COUNTIFS(OFÍCIOS!$E:$E,$O15,OFÍCIOS!$G:$G,"") -> 0 | U15: =SUM(Q15:T15) -> 16
A16: ADEILDA RODRIGUES DE OLIVEIRA | B16: 21538837846 | C16: PEDRO LUIZ SANTOS OLIVEIRA | D16: 94203180520 | E16: 810 | F16: 42915 | G16: APROVADO | H16: 42921 | L16: 568-17 | O16: 1451 | P16: =COUNTIF(OFÍCIOS!E:E,O16) -> 4 | Q16: =COUNTIFS(OFÍCIOS!$E:$E,$O16,OFÍCIOS!$G:$G,"APROVADO") -> 3 | R16: =COUNTIFS(OFÍCIOS!$E:$E,$O16,OFÍCIOS!$G:$G,"REPROVADO") -> 1 | S16: =COUNTIFS(OFÍCIOS!$E:$E,$O16,OFÍCIOS!$G:$G,"PENDENCIA") -> 0 | T16: =COUNTIFS(OFÍCIOS!$E:$E,$O16,OFÍCIOS!$G:$G,"") -> 0 | U16: =SUM(Q16:T16) -> 4
A17: ADEILDO ADELINO DE CARVALHO | B17: 57455392591 | O17: 1470 | P17: =COUNTIF(OFÍCIOS!E:E,O17) -> 4 | Q17: =COUNTIFS(OFÍCIOS!$E:$E,$O17,OFÍCIOS!$G:$G,"APROVADO") -> 4 | R17: =COUNTIFS(OFÍCIOS!$E:$E,$O17,OFÍCIOS!$G:$G,"REPROVADO") -> 0 | S17: =COUNTIFS(OFÍCIOS!$E:$E,$O17,OFÍCIOS!$G:$G,"PENDENCIA") -> 0 | T17: =COUNTIFS(OFÍCIOS!$E:$E,$O17,OFÍCIOS!$G:$G,"") -> 0 | U17: =SUM(Q17:T17) -> 4
A18: ADELCIDES DA CONCEICAO ALMEIDA | B18: 5304941594 | E18: 1106 | F18: 42965 | G18: APROVADO | H18: 42978 | O18: 1489 | P18: =COUNTIF(OFÍCIOS!E:E,O18) -> 35 | Q18: =COUNTIFS(OFÍCIOS!$E:$E,$O18,OFÍCIOS!$G:$G,"APROVADO") -> 34 | R18: =COUNTIFS(OFÍCIOS!$E:$E,$O18,OFÍCIOS!$G:$G,"REPROVADO") -> 0 | S18: =COUNTIFS(OFÍCIOS!$E:$E,$O18,OFÍCIOS!$G:$G,"PENDENCIA") -> 1 | T18: =COUNTIFS(OFÍCIOS!$E:$E,$O18,OFÍCIOS!$G:$G,"") -> 0 | U18: =SUM(Q18:T18) -> 35
A19: ADELIA MARIA DE OLIVEIRA | B19: 21600057896 | E19: 262 | F19: 43160 | G19: REPROVADO | H19: 43164 | L19: 255 | O19: 1555 | P19: =COUNTIF(OFÍCIOS!E:E,O19) -> 25 | Q19: =COUNTIFS(OFÍCIOS!$E:$E,$O19,OFÍCIOS!$G:$G,"APROVADO") -> 22 | R19: =COUNTIFS(OFÍCIOS!$E:$E,$O19,OFÍCIOS!$G:$G,"REPROVADO") -> 1 | S19: =COUNTIFS(OFÍCIOS!$E:$E,$O19,OFÍCIOS!$G:$G,"PENDENCIA") -> 2 | T19: =COUNTIFS(OFÍCIOS!$E:$E,$O19,OFÍCIOS!$G:$G,"") -> 0 | U19: =SUM(Q19:T19) -> 25
A20: ADEMARIO FERREIRA DOS SANTOS | B20: 18419589802 | O20: 1570 | P20: =COUNTIF(OFÍCIOS!E:E,O20) -> 24 | Q20: =COUNTIFS(OFÍCIOS!$E:$E,$O20,OFÍCIOS!$G:$G,"APROVADO") -> 23 | R20: =COUNTIFS(OFÍCIOS!$E:$E,$O20,OFÍCIOS!$G:$G,"REPROVADO") -> 1 | S20: =COUNTIFS(OFÍCIOS!$E:$E,$O20,OFÍCIOS!$G:$G,"PENDENCIA") -> 0 | T20: =COUNTIFS(OFÍCIOS!$E:$E,$O20,OFÍCIOS!$G:$G,"") -> 0 | U20: =SUM(Q20:T20) -> 24
A21: ADEMIR DA SILVA LIMA | B21: 15538537846 | E21: 573 | F21: 43224 | O21: 1752 | P21: =COUNTIF(OFÍCIOS!E:E,O21) -> 89 | Q21: =COUNTIFS(OFÍCIOS!$E:$E,$O21,OFÍCIOS!$G:$G,"APROVADO") -> 80 | R21: =COUNTIFS(OFÍCIOS!$E:$E,$O21,OFÍCIOS!$G:$G,"REPROVADO") -> 2 | S21: =COUNTIFS(OFÍCIOS!$E:$E,$O21,OFÍCIOS!$G:$G,"PENDENCIA") -> 5 | T21: =COUNTIFS(OFÍCIOS!$E:$E,$O21,OFÍCIOS!$G:$G,"") -> 2 | U21: =SUM(Q21:T21) -> 89
A22: ADENILDE SANTOS DA SILVA | B22: 899837506 | E22: 1824 | F22: 43091 | G22: APROVADO | H22: 43097 | L22: 1828 | O22: 1824 | P22: =COUNTIF(OFÍCIOS!E:E,O22) -> 81 | Q22: =COUNTIFS(OFÍCIOS!$E:$E,$O22,OFÍCIOS!$G:$G,"APROVADO") -> 67 | R22: =COUNTIFS(OFÍCIOS!$E:$E,$O22,OFÍCIOS!$G:$G,"REPROVADO") -> 7 | S22: =COUNTIFS(OFÍCIOS!$E:$E,$O22,OFÍCIOS!$G:$G,"PENDENCIA") -> 6 | T22: =COUNTIFS(OFÍCIOS!$E:$E,$O22,OFÍCIOS!$G:$G,"") -> 1 | U22: =SUM(Q22:T22) -> 81
A23: ADENILSON DA CONCEICAO | B23: 36197160803 | E23: 229 | F23: 43151 | G23: APROVADO | L23: 232 | O23: 1628 | P23: =COUNTIF(OFÍCIOS!E:E,O23) -> 6 | Q23: =COUNTIFS(OFÍCIOS!$E:$E,$O23,OFÍCIOS!$G:$G,"APROVADO") -> 5 | R23: =COUNTIFS(OFÍCIOS!$E:$E,$O23,OFÍCIOS!$G:$G,"REPROVADO") -> 1 | S23: =COUNTIFS(OFÍCIOS!$E:$E,$O23,OFÍCIOS!$G:$G,"PENDENCIA") -> 0 | T23: =COUNTIFS(OFÍCIOS!$E:$E,$O23,OFÍCIOS!$G:$G,"") -> 0 | U23: =SUM(Q23:T23) -> 6
A24: ADENIR MODESTO RIBEIRO | B24: 39248826814 | E24: 292 | F24: 43168 | G24: APROVADO | H24: 43182 | L24: 318 | O24: 608 | P24: =COUNTIF(OFÍCIOS!E:E,O24) -> 35 | Q24: =COUNTIFS(OFÍCIOS!$E:$E,$O24,OFÍCIOS!$G:$G,"APROVADO") -> 31 | R24: =COUNTIFS(OFÍCIOS!$E:$E,$O24,OFÍCIOS!$G:$G,"REPROVADO") -> 3 | S24: =COUNTIFS(OFÍCIOS!$E:$E,$O24,OFÍCIOS!$G:$G,"PENDENCIA") -> 1 | T24: =COUNTIFS(OFÍCIOS!$E:$E,$O24,OFÍCIOS!$G:$G,"") -> 0 | U24: =SUM(Q24:T24) -> 35
A25: ADILINA FARIAS DO NASCIMENTO | B25: 48925276534 | E25: 229 | F25: 43151 | L25: 232 | O25: 527 | P25: =COUNTIF(OFÍCIOS!E:E,O25) -> 29 | Q25: =COUNTIFS(OFÍCIOS!$E:$E,$O25,OFÍCIOS!$G:$G,"APROVADO") -> 0 | R25: =COUNTIFS(OFÍCIOS!$E:$E,$O25,OFÍCIOS!$G:$G,"REPROVADO") -> 0 | S25: =COUNTIFS(OFÍCIOS!$E:$E,$O25,OFÍCIOS!$G:$G,"PENDENCIA") -> 0 | T25: =COUNTIFS(OFÍCIOS!$E:$E,$O25,OFÍCIOS!$G:$G,"") -> 29 | U25: =SUM(Q25:T25) -> 29
A26: ADILSON SOARES DA COSTA | O26: 509 | P26: =COUNTIF(OFÍCIOS!E:E,O26) -> 14 | Q26: =COUNTIFS(OFÍCIOS!$E:$E,$O26,OFÍCIOS!$G:$G,"APROVADO") -> 0 | R26: =COUNTIFS(OFÍCIOS!$E:$E,$O26,OFÍCIOS!$G:$G,"REPROVADO") -> 0 | S26: =COUNTIFS(OFÍCIOS!$E:$E,$O26,OFÍCIOS!$G:$G,"PENDENCIA") -> 0 | T26: =COUNTIFS(OFÍCIOS!$E:$E,$O26,OFÍCIOS!$G:$G,"") -> 14 | U26: =SUM(Q26:T26) -> 14
A27: ADMEIA BARBOSA DE SOUZA | B27: 25894152810 | C27: REINALDO SANTOS REIS | D27: 8263008808 | E27: 292 | F27: 43168 | G27: APROVADO | H27: 43182 | L27: 318 | O27: 292 | P27: =COUNTIF(OFÍCIOS!E:E,O27) -> 233 | Q27: =COUNTIFS(OFÍCIOS!$E:$E,$O27,OFÍCIOS!$G:$G,"APROVADO") -> 212 | R27: =COUNTIFS(OFÍCIOS!$E:$E,$O27,OFÍCIOS!$G:$G,"REPROVADO") -> 9 | S27: =COUNTIFS(OFÍCIOS!$E:$E,$O27,OFÍCIOS!$G:$G,"PENDENCIA") -> 0 | T27: =COUNTIFS(OFÍCIOS!$E:$E,$O27,OFÍCIOS!$G:$G,"") -> 12 | U27: =SUM(Q27:T27) -> 233
A28: ADONES FERREIRA JORGE | B28: 43026389587 | C28: EUNICE FELICIANA BRITO JORGE | D28: 29124464813 | E28: 485 | F28: 43196 | H28: 43206 | L28: 483 | O28: 573 | P28: =COUNTIF(OFÍCIOS!E:E,O28) -> 43 | Q28: =COUNTIFS(OFÍCIOS!$E:$E,$O28,OFÍCIOS!$G:$G,"APROVADO") -> 0 | R28: =COUNTIFS(OFÍCIOS!$E:$E,$O28,OFÍCIOS!$G:$G,"REPROVADO") -> 0 | S28: =COUNTIFS(OFÍCIOS!$E:$E,$O28,OFÍCIOS!$G:$G,"PENDENCIA") -> 0 | T28: =COUNTIFS(OFÍCIOS!$E:$E,$O28,OFÍCIOS!$G:$G,"") -> 43 | U28: =SUM(Q28:T28) -> 43
A29: ADRIANA ALVES DA SILVA | B29: 26245112885 | E29: 262 | F29: 43160 | G29: REPROVADO | H29: 43164 | L29: 255 | O29: 563 | P29: =COUNTIF(OFÍCIOS!E:E,O29) -> 64 | Q29: =COUNTIFS(OFÍCIOS!$E:$E,$O29,OFÍCIOS!$G:$G,"APROVADO") -> 0 | R29: =COUNTIFS(OFÍCIOS!$E:$E,$O29,OFÍCIOS!$G:$G,"REPROVADO") -> 0 | S29: =COUNTIFS(OFÍCIOS!$E:$E,$O29,OFÍCIOS!$G:$G,"PENDENCIA") -> 0 | T29: =COUNTIFS(OFÍCIOS!$E:$E,$O29,OFÍCIOS!$G:$G,"") -> 64 | U29: =SUM(Q29:T29) -> 64
A30: ADRIANA ALVES FERREIRA | B30: 36531080809 | C30: MARCIO ROSA DE MIRA | D30: 22485483892 | E30: 1489 | F30: 43038 | G30: APROVADO | L30: 1647-17 | O30: 443 | P30: =COUNTIF(OFÍCIOS!E:E,O30) -> 66 | Q30: =COUNTIFS(OFÍCIOS!$E:$E,$O30,OFÍCIOS!$G:$G,"APROVADO") -> 0 | R30: =COUNTIFS(OFÍCIOS!$E:$E,$O30,OFÍCIOS!$G:$G,"REPROVADO") -> 0 | S30: =COUNTIFS(OFÍCIOS!$E:$E,$O30,OFÍCIOS!$G:$G,"PENDENCIA") -> 0 | T30: =COUNTIFS(OFÍCIOS!$E:$E,$O30,OFÍCIOS!$G:$G,"") -> 66 | U30: =SUM(Q30:T30) -> 66
A31: ADRIANA APARECIDA ROBERTO | B31: 28147186819 | C31: CARLOS ANTONIO BATISTA DOS SANTOS | D31: 24499714400 | O31: 423 | P31: =COUNTIF(OFÍCIOS!E:E,O31) -> 9 | Q31: =COUNTIFS(OFÍCIOS!$E:$E,$O31,OFÍCIOS!$G:$G,"APROVADO") -> 7 | R31: =COUNTIFS(OFÍCIOS!$E:$E,$O31,OFÍCIOS!$G:$G,"REPROVADO") -> 1 | S31: =COUNTIFS(OFÍCIOS!$E:$E,$O31,OFÍCIOS!$G:$G,"PENDENCIA") -> 0 | T31: =COUNTIFS(OFÍCIOS!$E:$E,$O31,OFÍCIOS!$G:$G,"") -> 1 | U31: =SUM(Q31:T31) -> 9
A32: ADRIANA ARAUJO DE LIMA | B32: 37559228860 | C32: ALEXANDRO ARAUJO DE LIMA | D32: 28072024892 | E32: 1555 | F32: 43049 | G32: APROVADO | O32: 229 | P32: =COUNTIF(OFÍCIOS!E:E,O32) -> 89 | Q32: =COUNTIFS(OFÍCIOS!$E:$E,$O32,OFÍCIOS!$G:$G,"APROVADO") -> 81 | R32: =COUNTIFS(OFÍCIOS!$E:$E,$O32,OFÍCIOS!$G:$G,"REPROVADO") -> 2 | S32: =COUNTIFS(OFÍCIOS!$E:$E,$O32,OFÍCIOS!$G:$G,"PENDENCIA") -> 5 | T32: =COUNTIFS(OFÍCIOS!$E:$E,$O32,OFÍCIOS!$G:$G,"") -> 1 | U32: =SUM(Q32:T32) -> 89
A33: ADRIANA CORDEIRO MACHADO | B33: 23635229822 | C33: ANDERSON DE MORAIS SANTOS | D33: 21668057875 | E33: 262 | F33: 43160 | G33: APROVADO | H33: 43164 | L33: 255 | O33: 262 | P33: =COUNTIF(OFÍCIOS!E:E,O33) -> 224 | Q33: =COUNTIFS(OFÍCIOS!$E:$E,$O33,OFÍCIOS!$G:$G,"APROVADO") -> 181 | R33: =COUNTIFS(OFÍCIOS!$E:$E,$O33,OFÍCIOS!$G:$G,"REPROVADO") -> 15 | S33: =COUNTIFS(OFÍCIOS!$E:$E,$O33,OFÍCIOS!$G:$G,"PENDENCIA") -> 0 | T33: =COUNTIFS(OFÍCIOS!$E:$E,$O33,OFÍCIOS!$G:$G,"") -> 28 | U33: =SUM(Q33:T33) -> 224
A34: ADRIANA DA SILVA | O34: 117 | P34: =COUNTIF(OFÍCIOS!E:E,O34) -> 91 | Q34: =COUNTIFS(OFÍCIOS!$E:$E,$O34,OFÍCIOS!$G:$G,"APROVADO") -> 77 | R34: =COUNTIFS(OFÍCIOS!$E:$E,$O34,OFÍCIOS!$G:$G,"REPROVADO") -> 7 | S34: =COUNTIFS(OFÍCIOS!$E:$E,$O34,OFÍCIOS!$G:$G,"PENDENCIA") -> 5 | T34: =COUNTIFS(OFÍCIOS!$E:$E,$O34,OFÍCIOS!$G:$G,"") -> 2 | U34: =SUM(Q34:T34) -> 91
A35: ADRIANA DA SILVA SANTOS | B35: 40902634844 | C35: GUILHERME DE OLIVEIRA SOUZA | D35: 23795007895 | E35: 117 | F35: 43117 | G35: APROVADO | H35: 43151 | L35: 118-18 | O35: 485 | P35: =COUNTIF(OFÍCIOS!E:E,O35) -> 23 | Q35: =COUNTIFS(OFÍCIOS!$E:$E,$O35,OFÍCIOS!$G:$G,"APROVADO") -> 0 | R35: =COUNTIFS(OFÍCIOS!$E:$E,$O35,OFÍCIOS!$G:$G,"REPROVADO") -> 3 | S35: =COUNTIFS(OFÍCIOS!$E:$E,$O35,OFÍCIOS!$G:$G,"PENDENCIA") -> 0 | T35: =COUNTIFS(OFÍCIOS!$E:$E,$O35,OFÍCIOS!$G:$G,"") -> 20 | U35: =SUM(Q35:T35) -> 23
A36: ADRIANA DE SA ROCHA | B36: 39615629898 | C36: MARCELO FERNANDES LIMA | D36: 43328275894 | E36: 423 | F36: 43182 | G36: APROVADO | O36: 85 | P36: =COUNTIF(OFÍCIOS!E:E,O36) -> 93 | Q36: =COUNTIFS(OFÍCIOS!$E:$E,$O36,OFÍCIOS!$G:$G,"APROVADO") -> 86 | R36: =COUNTIFS(OFÍCIOS!$E:$E,$O36,OFÍCIOS!$G:$G,"REPROVADO") -> 4 | S36: =COUNTIFS(OFÍCIOS!$E:$E,$O36,OFÍCIOS!$G:$G,"PENDENCIA") -> 3 | T36: =COUNTIFS(OFÍCIOS!$E:$E,$O36,OFÍCIOS!$G:$G,"") -> 0 | U36: =SUM(Q36:T36) -> 93
A37: ADRIANA DOS SANTOS | P37: =COUNTIF(OFÍCIOS!E:E,O37) -> 0 | Q37: =COUNTIFS(OFÍCIOS!$E:$E,$O37,OFÍCIOS!$G:$G,"APROVADO") -> 0 | R37: =COUNTIFS(OFÍCIOS!$E:$E,$O37,OFÍCIOS!$G:$G,"REPROVADO") -> 0 | S37: =COUNTIFS(OFÍCIOS!$E:$E,$O37,OFÍCIOS!$G:$G,"PENDENCIA") -> 0 | T37: =COUNTIFS(OFÍCIOS!$E:$E,$O37,OFÍCIOS!$G:$G,"") -> 0 | U37: =SUM(Q37:T37) -> 0
A38: ADRIANA FERREIRA DA SILVA | C38: LOURIVAL CANDIDO SILVA | P38: =COUNTIF(OFÍCIOS!E:E,O38) -> 0 | Q38: =COUNTIFS(OFÍCIOS!$E:$E,$O38,OFÍCIOS!$G:$G,"APROVADO") -> 0 | R38: =COUNTIFS(OFÍCIOS!$E:$E,$O38,OFÍCIOS!$G:$G,"REPROVADO") -> 0 | S38: =COUNTIFS(OFÍCIOS!$E:$E,$O38,OFÍCIOS!$G:$G,"PENDENCIA") -> 0 | T38: =COUNTIFS(OFÍCIOS!$E:$E,$O38,OFÍCIOS!$G:$G,"") -> 0 | U38: =SUM(Q38:T38) -> 0
A39: ADRIANA HELENA DE MORAIS | B39: 14268808809 | E39: 262 | F39: 43160 | G39: APROVADO | H39: 43164 | L39: 255 | P39: =COUNTIF(OFÍCIOS!E:E,O39) -> 0 | Q39: =COUNTIFS(OFÍCIOS!$E:$E,$O39,OFÍCIOS!$G:$G,"APROVADO") -> 0 | R39: =COUNTIFS(OFÍCIOS!$E:$E,$O39,OFÍCIOS!$G:$G,"REPROVADO") -> 0 | S39: =COUNTIFS(OFÍCIOS!$E:$E,$O39,OFÍCIOS!$G:$G,"PENDENCIA") -> 0 | T39: =COUNTIFS(OFÍCIOS!$E:$E,$O39,OFÍCIOS!$G:$G,"") -> 0 | U39: =SUM(Q39:T39) -> 0
A40: ADRIANA JESUS DA CUNHA | B40: 29628693867 | E40: 292 | F40: 43168 | G40: APROVADO | H40: 43182 | L40: 318 | P40: =COUNTIF(OFÍCIOS!E:E,O40) -> 0 | Q40: =COUNTIFS(OFÍCIOS!$E:$E,$O40,OFÍCIOS!$G:$G,"APROVADO") -> 0 | R40: =COUNTIFS(OFÍCIOS!$E:$E,$O40,OFÍCIOS!$G:$G,"REPROVADO") -> 0 | S40: =COUNTIFS(OFÍCIOS!$E:$E,$O40,OFÍCIOS!$G:$G,"PENDENCIA") -> 0 | T40: =COUNTIFS(OFÍCIOS!$E:$E,$O40,OFÍCIOS!$G:$G,"") -> 0 | U40: =SUM(Q40:T40) -> 0
A41: ADRIANA LINO PEIXOTO | B41: 35762862844 | E41: 1106 | F41: 42965 | G41: APROVADO | H41: 42978 | P41: =COUNTIF(OFÍCIOS!E:E,O41) -> 0 | Q41: =COUNTIFS(OFÍCIOS!$E:$E,$O41,OFÍCIOS!$G:$G,"APROVADO") -> 0 | R41: =COUNTIFS(OFÍCIOS!$E:$E,$O41,OFÍCIOS!$G:$G,"REPROVADO") -> 0 | S41: =COUNTIFS(OFÍCIOS!$E:$E,$O41,OFÍCIOS!$G:$G,"PENDENCIA") -> 0 | T41: =COUNTIFS(OFÍCIOS!$E:$E,$O41,OFÍCIOS!$G:$G,"") -> 0 | U41: =SUM(Q41:T41) -> 0
A42: ADRIANA MARIA ALVES XAVIER (ALTERACAO DE NOME ADRIANA MARIA ALVES DOS SANTOS) | B42: 10201704412 | C42: CLAUDIO XAVIER SANTANA | D42: 33674895811 | E42: 262 | F42: 43160 | G42: APROVADO | H42: 43164 | L42: 255 | O42: TOTAIS | P42: =SUM(P3:P36) -> 1922 | Q42: =SUM(Q3:Q36) -> 1514 | R42: =SUM(R3:R36) -> 83 | S42: =SUM(S3:S36) -> 36 | T42: =SUM(T3:T36) -> 289 | U42: =SUM(U3:U36) -> 1922
A43: ADRIANA MEDEIROS DE OLIVEIRA SANTOS | B43: 35271487873 | C43: CLEITON SOUSA SANTOS | D43: 557351502 | E43: 1128 | F43: 42972 | G43: APROVADO | H43: 42979
A44: ADRIANA PEREIRA DE JESUS | B44: 22360217801 | E44: 1128 | F44: 42972 | G44: APROVADO | H44: 42979
A45: ADRIANA PINHEIRO MOREIRA | B45: 36930783862 | E45: 443 | F45: 43188 | H45: 43192
A46: ADRIANA PONCIANO DA SILVA | B46: 36647299866 | E46: 292 | F46: 43168 | G46: APROVADO | H46: 43182 | L46: 318
A47: ADRIANA PORTE | B47: 31801479895 | C47: ISAQUE PINTO DA SILVA | D47: 23103908873
A48: ADRIANA ROBERTA SILVA ANDRADE | B48: 28638653824 | C48: JOSE ROMILDO SILVA ANDRADE | D48: 50160249520
A49: ADRIANA ROQUE DOS SANTOS | B49: 17766101807 | C49: MARCOS ELIAS DOS SANTOS | D49: 31993041842 | E49: 1824 | F49: 43091 | G49: APROVADO | H49: 43097 | L49: 1828
A50: ADRIANA SABINO NOGUEIRA | B50: 17902799840 | C50: JOYCE CRISTINA NOGUEIRA DO CARMO | D50: 44230035896
A51: ADRIANA SANTANA SANTOS | B51: 49122403892 | C51: ETVALDO BERTO DA SILVA | D51: 1478139560 | E51: 608 | F51: 43012 | G51: APROVADO | H51: 43024 | O51: OFÍCIO DE REANÁLISE 019/18 - 05/06/18
A52: ADRIANA SANTOS RIBEIRO | B52: 37534302854 | C52: EDLANDIO BISPO SILVA | D52: 1689246502
A53: ADRIANA SEVERINO SANTANA | B53: 14699996841 | C53: FERNANDO FERREIRA SILVA | D53: 15089706883 | E53: 1128 | F53: 42972 | G53: APROVADO | H53: 42979
A54: ADRIANA TENORIO DA SILVA | B54: 47077408809
A55: ADRIANE MOREIRA DOS SANTOS | B55: 40396239838 | C55: JEFERSON DA SILVA DE JESUS | D55: 39420747883 | E55: 262 | F55: 43160 | G55: APROVADO | H55: 43164 | L55: 255
A56: ADRIANO ALVES BARBOSA | B56: 41333062877 | E56: 292 | F56: 43168 | G56: APROVADO | H56: 43182 | L56: 318
A57: ADRIANO HENRIQUE DA COSTA | B57: 38781151802
A58: ADRIANO PEREIRA DOS SANTOS
A59: ADRIELLE DOS PASSOS DE SOUZA | B59: 2428277219 | C59: DIVANILDO SOUZA DOS PASSOS | D59: 909805229 | E59: 810 | F59: 42915 | G59: APROVADO | H59: 42921 | L59: 568-17
A60: AGDA APARECIDA PEREIRA | B60: 16417464830
A61: AGNALDO ALTMANN | B61: 7104481800 | E61: 262 | F61: 43160 | G61: APROVADO | H61: 43164 | L61: 255
A62: AGNALDO LOPES GONCALVES FILHO | B62: 25023266800
A63: AGOSTINHO FERNANDES SILVA | B63: 3722493889 | C63: FRANCISCA GOMES DE OLIVEIRA | D63: 32416642871
A64: AIDEE MARIA DOS SANTOS | B64: 14519340845 | C64: SIORLANDIO DOS SANTOS FALCAO | D64: 88489795568 | E64: 262 | F64: 43160 | H64: 43164 | L64: 255
A65: AILTON WILLIAN MELLO | B65: 19266484806
A66: ALADIM PINHEIRO DOS SANTOS | B66: 15322188851
A67: ALAILTON COSTA DE SOUZA | B67: 36392955879 | C67: AMANDA CRISTINA SILVEIRA DA SILVA | D67: 5242864346 | E67: 117 | F67: 43117 | G67: APROVADO | H67: 43151 | L67: 118-18
A68: ALAN DE JESUS PASSOS | B68: 41482647800 | E68: 1262 | F68: 42997 | G68: APROVADO | H68: 43000
A69: ALBERT PEREIRA DOS SANTOS | B69: 47629183852
A70: ALBERTINA CANDIDO RIBEIRO GOMES | B70: 9882942490 | C70: DENIS JOSE GOMES | D70: 9704111460
A71: ALBERTINA PEREIRA COSTA | B71: 14777572870 | C71: EDIVALDO ALVES DE SOUZA | D71: 12874739898 | E71: 1824 | F71: 43091 | G71: APROVADO | H71: 43097 | L71: 1828
A72: ALCIDINEY DA SILVA | B72: 31996709895
A73: ALCILENE GUEDES DA SILVA | B73: 26824046850 | E73: 1824 | F73: 43091 | G73: APROVADO | H73: 43097 | L73: 1828
A74: ALCIONE BARBOSA DE SOUSA | B74: 3523524342 | E74: 85 | F74: 43109 | G74: APROVADO | H74: 43151
A75: ALDA DE JESUS GONCALVES | B75: 26940268855 | C75: JUCELINO ALVES DE LIMA
A76: ALDA MARIA DE JESUS | B76: 24828498885 | E76: 1489 | F76: 43038 | G76: APROVADO | L76: 1647-17
A77: ALDA REJANE SANTOS | B77: 11482307855 | E77: 85 | F77: 43109 | G77: APROVADO | H77: 43151
A78: ALDERLANDIA DE OLIVEIRA MONTEIRO | B78: 42352732808 | C78: JOSE SOARES DA SILVA | D78: 281893373 | E78: 1214 | F78: 42989 | G78: APROVADO | H78: 43000
A79: ALESILVIA RAIMUNDO DA SILVA NEVES | B79: 13480043801 | C79: CLAUDIO RIBEIRO NEVES | D79: 67141536604
A80: ALESSANDRA APARECIDA DE JESUS | B80: 31874522804 | E80: 292 | F80: 43168 | G80: APROVADO | H80: 43182 | L80: 318
A81: ALESSANDRA CABRAL DA SILVA | B81: 28889575824 | E81: 1241 | F81: 42992 | G81: APROVADO | H81: 42998
A82: ALESSANDRA JUVINA DA SILVA | B82: 21734589817 | E82: 229 | F82: 43151 | G82: APROVADO | L82: 232
A83: ALESSANDRA LIMA DA SILVA
A84: ALESSANDRA LUNA DA SILVA | B84: 18475875858
A85: ALESSANDRA MARQUES DOS SANTOS | B85: 40443882886 | E85: 509 | F85: 43203 | H85: 43213
A86: ALESSANDRA MARTINS DA SILVA | B86: 43053250802 | C86: IUDARLAN MARTINS DA SILVA | D86: 35893147880 | E86: 1128 | F86: 42972 | G86: APROVADO
A87: ALESSANDRA MILAGRES PIROTTI | B87: 28255807837 | E87: 292 | F87: 43168 | G87: APROVADO | L87: 318
A88: ALESSANDRA MONTEIRO DA SILVA | B88: 33617584837 | C88: ASTROGILDO APARECIDO CURY DE ARAUJO | D88: 26520094862 | E88: 608 | F88: 43012 | G88: APROVADO
A89: ALESSANDRA QUARESMA DA SILVA | B89: 38168161858 | C89: WALLACE DIEGO HENRIQUE BISPO | D89: 24059422835
A90: ALESSANDRO ARAUJO DA SILVA COSTA | B90: 38728353862 | C90: LIZIANE ROCHA DA SILVA COSTA | D90: 37650358828 | E90: 1417 | F90: 43017 | G90: APROVADO | L90: 1017-17
A91: ALEX DE JESUS PEREIRA | B91: 29479419858 | C91: JOILMA DE JESUS FERREIRA | D91: 71909656534
A92: ALEX JOSE CATARINO ASSUNCAO | B92: 37634689866 | E92: 443 | F92: 43188
A93: ALEXANDRA APARECIDA DA SILVA BARBOZA | B93: 22656606802 | E93: 1555 | F93: 43049 | G93: APROVADO
A94: ALEXANDRA SANTOS DE PAULA | B94: 4248144638 | E94: 229 | F94: 43151 | G94: APROVADO | L94: 232
A95: ALEXANDRE OLIVEIRA SILVA | B95: 29998933889
A96: ALEXANDRE SATELES DOS SANTOS | B96: 2963904533 | E96: 1489 | F96: 43038 | G96: APROVADO | L96: 1647-17
A97: ALEXANDRE VALENTIN DE SOUZA | B97: 23256005802 | E97: 1350 | F97: 43006 | G97: APROVADO
A98: ALEXSANDRA BORGES GONCALVES | B98: 3317260505 | C98: GILDECI FERREIRA CORDEIRO | D98: 92396607634
A99: ALEXSANDRA FRANCA DA SILVA | B99: 36234875890 | E99: 1128 | F99: 42972 | G99: APROVADO
A100: ALEXSANDRA MARIA DA SILVA | B100: 1243618469 | E100: 262 | F100: 43160 | G100: APROVADO | H100: 43164 | L100: 255
...

Sheet Planilha1
B6: ÁREA | C6: SELO | D6: PROPRIETÁRIO | E6: CONFIRMAÇÃO PAGAMENTO
B7: ALFREDO ÁVILA | C7: 001/0076/A | D7: ANTONIA FERREIRA DE OLIVEIRA AMORIM | E7: 45939
B30: ALFREDO ÁVILA
B31: ALFREDO ÁVILA
B32: ALFREDO ÁVILA
B33: ALFREDO ÁVILA | C33: 001/0206/B | D33: ANTONIO CARLOS DE ANDRADE JUNIOR | E33: 44924
B34: ALFREDO ÁVILA
B35: ALFREDO ÁVILA
B36: ALFREDO ÁVILA
B42: PARAISÓPOLIS/ANTONICO | C42: 029/0063/A | D42: ADELICIO DOS SANTOS PINTO | E42: 44896
B43: PARAISÓPOLIS/ANTONICO | C43: 029/0071/H | D43: MARIA LÚCIA ANACLETO DE SOUZA | E43: 44896
B44: PARAISÓPOLIS/ANTONICO | C44: 029/0085/F | D44: ORLANDO CONCEIÇÃO SANTIAGO | E44: 44896
B45: PARAISÓPOLIS/ANTONICO | C45: 031/0028/I | D45: WELLINGTON SANTOS SILVA | E45: 44896
A88: 024/0049/A | B88: INQUILINO | C88: 50.515.164-9 | D88: 465.224.188-78
A89: 024/0049/B | B89: INQUILINO | C89: 53.287.750-0 | D89: 466.311.188-24
A90: 024/0049/C | B90: INQUILINO | C90: 39.750.401-9 | D90: 495.178.508-08
A91: 024/0050/A | B91: PROPRIETÁRIO RESIDENTE | C91: 38.760.115-6 | D91: 351.584.248-96
A92: 024/0071/C | B92: INQUILINO | C92: 14293532 87 | D92: 039.532.515-38
A93: 024/0074/A | B93: INQUILINO | C93: 38.246.276-2 | D93: 495.627.538-24
A94: 024/0074/B | B94: INQUILINO | C94: 35.079.616-6 | D94: 324.991.728-19
A95: 024/0074/C | B95: INQUILINO | C95: 50.430.230-9 | D95: 314.455.978-45
A96: 024/0079/B | B96: INQUILINO | C96: 63.979.050-1 | D96: 093.493.334-06
A97: 024/0079/H | B97: INQUILINO | C97: 43.855.972-1 | D97: 433.413.978-76
A98: 024/0093/C | B98: PROPRIETÁRIO RESIDENTE | C98: 58.762.209-X | D98: 514.705.188-05
A99: 029/0028/B | B99: INQUILINO | C99: 44.939.752-X | D99: 376.785.558-57
... A104: 031/0034/F | B104: INQUILINO | C104: 56.704.987-5 | D104: 007.748.893-81
A114: 093.493.334-06
A115: 477.249.348-43
A116: 553.783.358-17

Sheet Planilha2
B3: PARAISÓPOLIS/ANTONICO | C3: 4 | D3: 029/0023/B | E3: FRANCISCO WILLIAN GOMES DO NASCIMENTO | F3: 58.276.710-6 | G3: 519.576.918-40
B4: PARAISÓPOLIS/ANTONICO | C4: 4 | D4: 029/0036/G | E4: JANAINA SANTOS DE MELO | F4: 52.949.011-0 | G4: 417.618.098-65 | L4: ÁREA | M4: SELO | N4: PROPRIETÁRIO | O4: CPF | P4: No PROCESSO SEI (INDENIZAÇÃO)
B5: PARAISÓPOLIS/ANTONICO | C5: 4 | D5: 029/0036/H | E5: DJAILSON FREITAS DE LIMA | F5: 57.410.954-7 | G5: 105.534.934-00 | L5: ALFREDO ÁVILA | M5: 001/0093/G | N5: ELIVANIA CRISTINA FERREIRA | O5: 322.186.628-33 | P5: 6014.2025/0004730-0
B6: PARAISÓPOLIS/ANTONICO | C6: 4 | D6: 029/0043/B | E6: MARIVANEIDE MOREIRA SILVA | F6: 50.175.775-2 | G6: 371.473.818-58 | L6: ALFREDO ÁVILA | M6: 001/0093/F | N6: JOSE EDILSON FERREIRA | O6: 728.822.474-00 | P6: 6014.2025/0004713-0
B7: PARAISÓPOLIS/ANTONICO | C7: 4 | D7: 029/0049/A | E7: FLAVIA SANTOS SOUZA | F7: 49.345.172-9 | G7: 435.377.298-80 | L7: ALFREDO ÁVILA
B8: PARAISÓPOLIS/ANTONICO | C8: 4 | D8: 029/0055/A | E8: GLEICON CARLOS CESAR GOMES | F8: 49.183.499-8 | G8: 344.351.508-83
B9: PARAISÓPOLIS/ANTONICO | C9: 4 | D9: 029/0056/A | E9: MARIA GERLANE DE SOUZA BOÍBA | F9: 57.816.422-X | G9: 494.665.018-01
B10: PARAISÓPOLIS/ANTONICO | C10: 4 | D10: 029/0056/B | E10: MAICO JONHATAS ALVARES PINTO | F10: 53.032.399-0 | G10: 428.355.978-40
B11: PARAISÓPOLIS/ANTONICO | C11: 4 | D11: 029/0085/F | E11: ORLANDO CONCEIÇÃO SANTIAGO | F11: 41.041.836-5 | G11: 353.178.248-77
D13: 024/0041/D | E13: MARICÉLIA OLIMPIO DE OLIVEIRA
D14: 024/0069/A | E14: LOURISMAR LIMA BRAGA
E19: 6014.2022/0002993-4
E20: 6014.2022/0003157-2
E21: 6014.2022/0002667-6

Sheet Planilha3
C3: 2 | D3: PRIORITÁRIO | G3: OCUPADO | H3: RESIDENCIAL | I3: PROPRIETÁRIO NÃO RESIDENTE | M3: CADASTRADO | N3: INDENIZAÇÃO | P3: SIM | R3: SIM | X3: SAQUE PENDENTE | AE3: PROPRIETÁRIO NÃO RESIDENTE | AH3: SIM | AI3: SIM | AJ3: CADASTRADO | AL3: COMPLETA | AM3: SEM PENDÊNCIAS
C4: 4 | G4: VAZIO | H4: COMERCIAL | I4: PROPRIETÁRIO RESIDENTE | M4: NÃO CADASTRADO | N4: AUXÍLIO ALUGUEL UH | P4: NÃO | R4: NÃO | AE4: PROPRIETÁRIO RESIDENTE | AH4: NÃO | AI4: NÃO | AJ4: NÃO CADASTRADO | AL4: PENDENTE | AM4: FALTA TERMO
G5: OCUPADO/RISCO | H5: MISTO | I5: INQULINO | N5: RECUSA AUXÍLIO ALUGUEL UH | AH5: UH | AI5: N/A | AM5: FALTA DOCS
G6: CONSTRUÇÃO | N6: NÃO TEM DIREITO ATENDIMENTO | AH6: ESTUDO DE CASO | AI6: PENDENTE | AM6: FALTA TERMO E DOCS
G7: DEMOLIDO
G8: DESCARACTERIZADO
G9: DESABADO
AU11: ** NOVO PROCEDIMENTO **
A12: INFORMAÇÕES INICIAIS | P12: INFORMAÇÕES AUXÍLIO ALUGUEL | AB12: INFORMAÇÕES INDENIZAÇÃO | BB12: PROCESSO
A13: ORDEM | B13: ÁREA | C13: FASE | D13: TRECHO | E13: PRIORIDADE | F13: SELO | G13: SITUAÇÃO INICIAL IMÓVEL | H13: USO IMÓVEL | I13: SITUAÇÃO DO RESIDENTE | J13: TITULAR | K13: RG | L13: CPF | M13: CADASTRO HABITA SAMPA | N13: OPÇÃO DE ATENDIMENTO HABITACIONAL | O13: ENVIO PLANILHA DADOS | P13: SOLICITAÇÃO AUXÍLIO ALUGUEL ÁREA | Q13: No PROCESSO SEI (AUXÍLIO ALUGUEL) | R13: SOLICITAÇÃO AUXÍLIO ALUGUEL DTS | S13: INSTRUÇÃO PROCESSO SEI DTS | T13: ASSINATURA GABINETE | U13: DATA PUBLICAÇÃO DIÁRIO OFICIAL | V13: CONFECÇÃO TERMO | W13: ENVIO TERMO CARTÃO | X13: PREVISÃO PAGAMENTO | Y13: DATA SAQUE | Z13: DATA MUDANÇA | AA13: OBSERVAÇÕES AA | AB13: PROPRIETÁRIO | AC13: RG | AD13: CPF | AE13: SITUAÇÃO DO PROPRIETÁRIO | AF13: VALOR INDENIZAÇÃO | AG13: VALOR COM BONIFICAÇÃO | AH13: ACEITA VALOR INDENIZAÇÃO | AI13: LAUDO VALOR INDENIZAÇÃO | AJ13: CADASTRO HABITASAMPA | AK13: TERMO INDENIZAÇÃO | AL13: DOSSIÊ | AM13: PENDÊNCIA | AN13: OBSERVAÇÕES INDENIZAÇÃO | AO13: No PROCESSO SEI (INDENIZAÇÃO) | AP13: INSTRUÇÃO PROCESSO SEI DTS | AQ13: ASSINATURA DIRETOR DTS | AR13: ELABORAÇÃO DESPACHO CTS | AS13: ASSINATURA DESPACHO GABINETE | AT13: PUBLICAÇÃO DIÁRIO OFICIAL | AU13: RRT TERMO ENTREGA CHAVES | AV13: ENCAMINHAMENTO DAF/DIF CTS | AW13: LIBERAÇÃO PAGAMENTO DAF/DIF | AX13: PREVISÃO PAGAMENTO | AY13: DATA PAGAMENTO | AZ13: DATA ENTREGA IMÓVEL | BA13: SITUAÇÃO ATUAL IMÓVEL | BB13: STATUS | BC13: DIAS TOTAIS
A14: 1 | B14: ALFREDO ÁVILA | C14: 1 | D14: 0 | E14: 0 | F14: 001/0001/A | G14: OCUPADO | H14: MISTO | I14: PROPRIETÁRIO RESIDENTE | J14: ANTONIO CARLOS PEREIRA LIMAS | K14: 27.717269-X | L14: 172.907.418-97 | M14: CADASTRADO | N14: INDENIZAÇÃO | O14: 44900 | P14: N/A | Q14: N/A | R14: N/A | S14: N/A | T14: N/A | U14: N/A | V14: N/A | W14: N/A | X14: N/A | Y14: N/A | Z14: N/A | AB14: ANTONIO CARLOS PEREIRA LIMAS | AC14: 27.717269-X | AD14: 172.907.418-97 | AE14: PROPRIETÁRIO RESIDENTE | AF14: 0 | AG14: 60000 | AH14: SIM | AI14: FINALIZADO | AJ14: CADASTRADO | AK14: FINALIZADO | AL14: PENDENTE | AM14: DOSSIÊ | BB14: DOSSIÊ PENDENTE | BC14: =IF(AY14-ON14=0,"",AY14-O14)
A15: 2 | B15: ALFREDO ÁVILA | C15: 1 | D15: 0 | E15: 0 | F15: 001/0001/B | G15: OCUPADO | H15: RESIDENCIAL | I15: PROPRIETÁRIO RESIDENTE | J15: ANTONIO CARLOS PEREIRA LIMAS | K15: 27.717269-X | L15: 172.907.418-97 | M15: CADASTRADO | N15: PENDENTE | O15: 44900 | AB15: ANTONIO CARLOS PEREIRA LIMAS | AC15: 27.717269-X | AD15: 172.907.418-97 | AE15: PROPRIETÁRIO RESIDENTE | AF15: 26600 | AG15: 56600 | BC15: =IF(AY15-ON15=0,"",AY15-O15)
A16: 3 | B16: ALFREDO ÁVILA | C16: 1 | D16: 0 | E16: 0 | F16: 001/0002/A | G16: OCUPADO | H16: RESIDENCIAL | I16: PROPRIETÁRIO RESIDENTE | J16: WALLACE CARLOS DO NASCIMENTO | K16: 53.833.874-X | L16: 460.742.418-80 | M16: CADASTRADO | N16: PENDENTE | O16: 44900 | AB16: WALLACE CARLOS DO NASCIMENTO | AC16: 53.833.874-X | AD16: 460.742.418-80 | AE16: PROPRIETÁRIO RESIDENTE | AF16: 15600 | AG16: 45600 | BC16: =IF(AY16-ON16=0,"",AY16-O16)
A17: 4 | B17: ALFREDO ÁVILA | C17: 1 | D17: 0 | E17: 0 | F17: 001/0002/B | G17: OCUPADO | H17: RESIDENCIAL | I17: PROPRIETÁRIO RESIDENTE | J17: VANESSA SANTOS DE MARIZ | K17: 54.110.071-3 | L17: 490.323.538-61 | M17: CADASTRADO | N17: PENDENTE | O17: 44900 | AB17: VANESSA SANTOS DE MARIZ | AC17: 54.110.071-3 | AD17: 490.323.538-61 | AE17: PROPRIETÁRIO RESIDENTE | AF17: 14600 | AG17: 44600 | BC17: =IF(AY17-ON17=0,"",AY17-O17)
A18: 5 | B18: ALFREDO ÁVILA | C18: 1 | D18: 0 | E18: 0 | F18: 001/0003/A | G18: OCUPADO | H18: RESIDENCIAL | I18: INQUILINO | J18: JEFFERSON DA CRUZ CORRÊA | K18: 47.815.794-0 | L18: 409.715.758-27 | M18: CADASTRADO | N18: AUXÍLIO ALUGUEL UH | O18: 44900 | P18: PENDENTE | AB18: FRANCISCO MARQUES DE OLIVEIRA | AC18: 26.115..235-X | AD18: 185.112.418-76 | AE18: PROPRIETÁRIO NÃO RESIDENTE | AF18: 107600 | AG18: 107600 | AH18: SIM | AI18: FINALIZADO | AJ18: CADASTRADO | AK18: FINALIZADO | AL18: FINALIZADO | AM18: SEM PENDÊNCIA | AO18: 6014.2022/0003932-8 | AP18: FINALIZADO | AQ18: FINALIZADO | AR18: AGUARDANDO ENCAMINHAMENTO | BB18: AA PENDENTE - INDENIZAÇÃO EM ANDAMENTO | BC18: =IF(AY18-ON18=0,"",AY18-O18) | BL18: SE(A2-A3=0;"";A2-A3)
A19: 6 | B19: ALFREDO ÁVILA | C19: 1 | D19: 0 | E19: 0 | F19: 001/0004/A | G19: OCUPADO | H19: RESIDENCIAL | I19: INQUILINO | J19: ISABELLE LAISLA DA SILVA | K19: 62.680.901-0 | L19: 561.448.138-96 | M19: CADASTRADO | N19: AUXÍLIO ALUGUEL UH | O19: 44900 | P19: PENDENTE | AB19: ELENILDA RIBEIRO SANTOS | AC19: 37.865.320-9 | AD19: 458.940.945-34 | AE19: PROPRIETÁRIO NÃO RESIDENTE | AF19: 27100 | AG19: 57100 | AH19: SIM | AI19: FINALIZADO | AJ19: CADASTRADO | AK19: FINALIZADO | AL19: FINALIZADO | AM19: SEM PENDÊNCIA | AO19: 6014.2022/0003936-0 | AP19: FINALIZADO | AQ19: FINALIZADO | AR19: AGUARDANDO ENCAMINHAMENTO | BC19: =IF(AY19-ON19=0,"",AY19-O19)
A20: 7 | B20: ALFREDO ÁVILA | C20: 1 | D20: 0 | E20: 0 | F20: 001/0005/A | G20: OCUPADO | H20: RESIDENCIAL | I20: PROPRIETÁRIO RESIDENTE | J20: ANDRÉ VINICIUS DOS SANTOS | K20: 54.531.709-5 | L20: 485.192.658-80 | M20: CADASTRADO | N20: INDENIZAÇÃO | O20: 44900 | P20: N/A | Q20: N/A | R20: N/A | S20: N/A | T20: N/A | U20: N/A | V20: N/A | W20: N/A | X20: N/A | Y20: N/A | Z20: N/A | AB20: ANDRÉ VINICIUS DOS SANTOS | AC20: 54.531.709-5 | AD20: 485.192.658-80 | AE20: PROPRIETÁRIO RESIDENTE | AF20: 15900 | AG20: 45900 | AH20: SIM | AI20: FINALIZADO | AJ20: CADASTRADO | AK20: FINALIZADO | AL20: FINALIZADO | AM20: SEM PENDÊNCIA | AO20: 6014.2022/0003939-5 | AP20: FINALIZADO | AQ20: FINALIZADO | AR20: AGUARDANDO ENCAMINHAMENTO | BB20: INDENIZAÇÃO EM ANDAMENTO | BC20: =IF(AY20-ON20=0,"",AY20-O20)
A21: 8 | B21: ALFREDO ÁVILA | C21: 1 | D21: 0 | E21: 0 | F21: 001/0006/A | G21: OCUPADO | H21: RESIDENCIAL | I21: PROPRIETÁRIO RESIDENTE | J21: MARIA DO CARMO SANTOS | K21: 22.334.891-0 | L21: 128.114.308-14 | M21: CADASTRADO | N21: INDENIZAÇÃO | O21: 44900 | P21: N/A | Q21: N/A | R21: N/A | S21: N/A | T21: N/A | U21: N/A | V21: N/A | W21: N/A | X21: N/A | Y21: N/A | Z21: N/A | AB21: MARIA DO CARMO SANTOS | AC21: 22.334.891-0 | AD21: 128.114.308-14 | AE21: PROPRIETÁRIO RESIDENTE | AF21: 48500 | AG21: 60000 | AH21: SIM | AI21: FINALIZADO | AJ21: CADASTRADO | AK21: FINALIZADO | AL21: FINALIZADO | AM21: SEM PENDÊNCIA | AO21: 6014.2022/0003947-6 | AP21: FINALIZADO | AQ21: FINALIZADO | AR21: AGUARDANDO ENCAMINHAMENTO | BB21: INDENIZAÇÃO EM ANDAMENTO | BC21: =IF(AY21-ON21=0,"",AY21-O21)
A22: 9 | B22: ALFREDO ÁVILA | C22: 1 | D22: 0 | E22: 0 | F22: 001/0006/B | G22: OCUPADO | H22: RESIDENCIAL | I22: PROPRIETÁRIO RESIDENTE | J22: CINTIA CARMO MIRANDA DE OLIVEIRA | K22: 47.503.428-1 | L22: 394.343.598-99 | M22: CADASTRADO | N22: PENDENTE | O22: 44900 | AB22: CINTIA CARMO MIRANDA DE OLIVEIRA | AC22: 47.503.428-1 | AD22: 394.343.598-99 | AE22: PROPRIETÁRIO RESIDENTE | AF22: 19900 | AG22: 49900 | BC22: =IF(AY22-ON22=0,"",AY22-O22)
A23: 10 | B23: ALFREDO ÁVILA | C23: 1 | D23: 0 | E23: 0 | F23: 001/0007/A | G23: OCUPADO | H23: RESIDENCIAL | I23: PROPRIETÁRIO RESIDENTE | J23: ELIANE BARBOSA RIBEIRO | K23: 58.837.007-1 | L23: 020.661.135-81 | M23: CADASTRADO | N23: INDENIZAÇÃO | O23: 44900 | P23: N/A | Q23: N/A | R23: N/A | S23: N/A | T23: N/A | U23: N/A | V23: N/A | W23: N/A | X23: N/A | Y23: N/A | Z23: N/A | AB23: ELIANE BARBOSA RIBEIRO | AC23: 58.837.007-1 | AD23: 020.661.135-81 | AE23: PROPRIETÁRIO RESIDENTE | AF23: 19800 | AG23: 49800 | AH23: SIM | AI23: FINALIZADO | AJ23: CADASTRADO | AK23: FINALIZADO | AL23: FINALIZADO | AM23: SEM PENDÊNCIA | AO23: 6014.2022/0004025-3 | AP23: FINALIZADO | AQ23: FINALIZADO | AR23: FINALIZADO | AS23: FINALIZADO | AT23: 44922 | AU23: FINALIZADO | AV23: FINALIZADO | AW23: FINALIZADO | AX23: 44924 | AY23: 44924 | AZ23: AGUARDANDO | BA23: OCUPADO | BB23: FINALIZADO | BC23: =IF(AY23-ON23=0,"",AY23-O23) -> 24
A24: 11 | B24: ALFREDO ÁVILA | C24: 1 | D24: 0 | E24: 0 | F24: 001/0008/A | G24: OCUPADO | H24: RESIDENCIAL | I24: PROPRIETÁRIO RESIDENTE | J24: NOELIA RIBEIRO BARBOSA | K24: 28.191.025-X | L24: 184.917.628-09 | M24: CADASTRADO | N24: INDENIZAÇÃO | O24: 44900 | P24: N/A | Q24: N/A | R24: N/A | S24: N/A | T24: N/A | U24: N/A | V24: N/A | W24: N/A | X24: N/A | Y24: N/A | Z24: N/A | AB24: NOELIA RIBEIROI BARBOSA | AC24: 28.191.025-X | AD24: 184.917.628-09 | AE24: PROPRIETÁRIO RESIDENTE | AF24: 30400 | AG24: 60000 | AH24: SIM | AI24: FINALIZADO | AJ24: CADASTRADO | AK24: FINALIZADO | AL24: FINALIZADO | AM24: SEM PENDÊNCIA | AO24: 6014.2022/0004026-1 | AP24: FINALIZADO | AQ24: FINALIZADO | AR24: FINALIZADO | AS24: FINALIZADO | AT24: 44922 | AU24: FINALIZADO | AV24: FINALIZADO | AW24: FINALIZADO | AX24: 44924 | AY24: 44924 | AZ24: AGUARDANDO | BA24: OCUPADO | BB24: FINALIZADO | BC24: =IF(AY24-ON24=0,"",AY24-O24) -> 24
A25: 12 | B25: ALFREDO ÁVILA | C25: 1 | D25: 0 | E25: 0 | F25: 001/0008/B | G25: OCUPADO | H25: RESIDENCIAL | I25: PROPRIETÁRIO RESIDENTE | J25: LUCAS DA SILVA PEREIRA | K25: 45.668.154-8 | L25: 459.407.808-73 | M25: CADASTRADO | N25: PENDENTE | O25: 44900 | AB25: LUCAS DA SILVA PEREIRA | AC25: 45.668.154-8 | AD25: 459.407.808-73 | AE25: PROPRIETÁRIO RESIDENTE | AF25: 13000 | AG25: 43000 | BC25: =IF(AY25-ON25=0,"",AY25-O25)
A26: 13 | B26: ALFREDO ÁVILA | C26: 1 | D26: 0 | E26: 0 | F26: 001/0009/A | G26: OCUPADO | H26: RESIDENCIAL | I26: PROPRIETÁRIO RESIDENTE | J26: MIRNA ELIZABETH CABRERA CUEVA | K26: RNM G065972-9 | L26: 237.484.388-26 | M26: CADASTRADO | N26: PENDENTE | O26: 44900 | AB26: MIRNA ELIZABETH CABRERA CUEVA | AC26: RNM G065972-9 | AD26: 237.484.388-26 | AE26: PROPRIETÁRIO RESIDENTE | AF26: 22700 | AG26: 52700 | BC26: =IF(AY26-ON26=0,"",AY26-O26)
A27: 14 | B27: ALFREDO ÁVILA | C27: 1 | D27: 0 | E27: 0 | F27: 001/0010/A | G27: OCUPADO | H27: RESIDENCIAL | I27: PROPRIETÁRIO RESIDENTE | J27: ALEXSANDRO BARBOSA PEREIRA | K27: 46.789.605-7 | L27: 393.482.118-97 | M27: CADASTRADO | N27: INDENIZAÇÃO | O27: 44900 | P27: N/A | Q27: N/A | R27: N/A | S27: N/A | T27: N/A | U27: N/A | V27: N/A | W27: N/A | X27: N/A | Y27: N/A | Z27: N/A | AB27: ALEXSANDRO BARBOSA PEREIRA | AC27: 46.789.605-7 | AD27: 393.482.118-97 | AE27: PROPRIETÁRIO RESIDENTE | AF27: 21400 | AG27: 51400 | AH27: SIM | AI27: FINALIZADO | AJ27: CADASTRADO | AK27: FINALIZADO | AL27: FINALIZADO | AM27: SEM PENDÊNCIA | AO27: 6014.2022/0003940-9 | AP27: FINALIZADO | AQ27: FINALIZADO | AR27: AGUARDANDO ENCAMINHAMENTO | BB27: INDENIZAÇÃO EM ANDAMENTO | BC27: =IF(AY27-ON27=0,"",AY27-O27)
A28: 15 | B28: ALFREDO ÁVILA | C28: 1 | D28: 0 | E28: 0 | F28: 001/0010/B | G28: OCUPADO | H28: RESIDENCIAL | I28: INQUILINO | J28: ANTONIO IZAU DOS SANTOS | K28: 38.478.412-4 | L28: 099.702.388-09 | M28: CADASTRADO | N28: AUXÍLIO ALUGUEL UH | O28: 44900 | P28: PENDENTE | AB28: ALEXSANDRO BARBOSA PEREIRA | AC28: 46.789.605-7 | AD28: 393.482.118-97 | AE28: PROPRIETÁRIO NÃO RESIDENTE | AF28: 18700 | AG28: 48700 | BC28: =IF(AY28-ON28=0,"",AY28-O28)
A29: 16 | B29: ALFREDO ÁVILA | C29: 1 | D29: 0 | E29: 0 | F29: 001/0011/A | G29: OCUPADO | H29: RESIDENCIAL | I29: INQUILINO | J29: DIVANI MARTINS DO SANTOS | K29: 34.812.789-3 | L29: 272.878.048-08 | M29: CADASTRADO | N29: AUXÍLIO ALUGUEL UH | O29: 44900 | P29: PENDENTE | AB29: IVONE FERREIRA MENDES | AC29: 54.246.610-7 | AD29: 060.155.126-52 | AE29: PROPRIETÁRIO NÃO RESIDENTE | AF29: 0 | AG29: 60000 | AH29: SIM | AI29: FINALIZADO | AJ29: CADASTRADO | AK29: AGUARDANDO ENVIO ÁREA | AL29: PENDENTE | AM29: DOSSIÊ + TERMO ASSINADO MORADOR | AN29: Conta bancaria da Sra. Ivone Ferreira Mendes está ilegível e o termo de chaves está faltando um número no RG. Verificar com Cibele | AO29: 6014.2022/0004134-9 | BB29: DOSSIÊ PENDENTE | BC29: =IF(AY29-ON29=0,"",AY29-O29)
A30: 17 | B30: ALFREDO ÁVILA | C30: 1 | D30: 0 | E30: 0 | F30: 001/0012/A | G30: OCUPADO | H30: RESIDENCIAL | I30: PROPRIETÁRIO RESIDENTE | J30: VITORIA RAFAELA LIMA DA COSTA | K30: 60.076.130-7 | L30: 505.195.648-39 | M30: CADASTRADO | N30: PENDENTE | O30: 44900 | AB30: VITORIA RAFAELA LIMA DA COSTA | AC30: 60.076.130-7 | AD30: 505.195.648-39 | AE30: PROPRIETÁRIO RESIDENTE | AF30: 20500 | AG30: 50500 | BC30: =IF(AY30-ON30=0,"",AY30-O30)
A31: 18 | B31: ALFREDO ÁVILA | C31: 1 | D31: 0 | E31: 0 | F31: 001/0012/B | G31: OCUPADO | H31: RESIDENCIAL | I31: PROPRIETÁRIO RESIDENTE | J31: CLAUDIO FERREIRA DE LIMA | K31: 37.095.609-6 | L31: 533.218.121-34 | M31: CADASTRADO | N31: INDENIZAÇÃO | O31: 44900 | P31: N/A | Q31: N/A | R31: N/A | S31: N/A | T31: N/A | U31: N/A | V31: N/A | W31: N/A | X31: N/A | Y31: N/A | Z31: N/A | AB31: CLAUDIO FERREIRA DE LIMA | AC31: 37.095.609-6 | AD31: 533.218.121-34 | AE31: PROPRIETÁRIO RESIDENTE | AF31: 20700 | AG31: 50700 | AH31: SIM | AI31: FINALIZADO | AJ31: CADASTRADO | AK31: FINALIZADO | AL31: FINALIZADO | AM31: SEM PENDÊNCIA | AO31: 6014.2022/0003941-7 | AP31: FINALIZADO | AQ31: FINALIZADO | AR31: AGUARDANDO ENCAMINHAMENTO | BB31: INDENIZAÇÃO EM ANDAMENTO | BC31: =IF(AY31-ON31=0,"",AY31-O31)
A32: 19 | B32: ALFREDO ÁVILA | C32: 1 | D32: 0 | E32: 0 | F32: 001/0014/A | G32: OCUPADO | H32: RESIDENCIAL | I32: PROPRIETÁRIO RESIDENTE | J32: JAILSON SANTOS SILVA | K32: 34.302.386-6 | L32: 553.313.785-87 | M32: CADASTRADO | N32: INDENIZAÇÃO | O32: 44900 | P32: N/A | Q32: N/A | R32: N/A | S32: N/A | T32: N/A | U32: N/A | V32: N/A | W32: N/A | X32: N/A | Y32: N/A | Z32: N/A | AB32: JAILSON SANTOS SILVA | AC32: 34.302.386-6 | AD32: 553.313.785-87 | AE32: PROPRIETÁRIO RESIDENTE | AF32: 19800 | AG32: 49800 | AH32: SIM | AI32: FINALIZADO | AJ32: CADASTRADO | AK32: FINALIZADO | AL32: FINALIZADO | AM32: SEM PENDÊNCIA | AO32: 6014.2022/0004135-7 | AP32: FINALIZADO | AQ32: FINALIZADO | AR32: AGUARDANDO ENCAMINHAMENTO | BB32: INDENIZAÇÃO EM ANDAMENTO | BC32: =IF(AY32-ON32=0,"",AY32-O32)
A33: 20 | B33: ALFREDO ÁVILA | C33: 1 | D33: 0 | E33: 0 | F33: 001/0017/A | G33: OCUPADO | H33: RESIDENCIAL | I33: PROPRIETÁRIO RESIDENTE | J33: CREUZA ROSA MARQUES | K33: 53.083.084-X | L33: 130.250.148-81 | M33: CADASTRADO | N33: INDENIZAÇÃO | O33: 44900 | P33: N/A | Q33: N/A | R33: N/A | S33: N/A | T33: N/A | U33: N/A | V33: N/A | W33: N/A | X33: N/A | Y33: N/A | Z33: N/A | AB33: CREUZA ROSA MARQUES | AC33: 53.083.084-X | AD33: 130.250.148-81 | AE33: PROPRIETÁRIO RESIDENTE | AF33: 92800 | AG33: 92800 | AH33: SIM | AI33: FINALIZADO | AJ33: CADASTRADO | AK33: FINALIZADO | AL33: FINALIZADO | AM33: SEM PENDÊNCIA | AO33: 6014.2022/0004030-0 | AP33: FINALIZADO | AQ33: FINALIZADO | AR33: AGUARDANDO ENCAMINHAMENTO | BB33: INDENIZAÇÃO EM ANDAMENTO | BC33: =IF(AY33-ON33=0,"",AY33-O33)
A34: 21 | B34: ALFREDO ÁVILA | C34: 1 | D34: 0 | E34: 0 | F34: 001/0017/B | G34: OCUPADO | H34: RESIDENCIAL | I34: PROPRIETÁRIO RESIDENTE | J34: STELA MARQUES DA SILVA | K34: 39.626.761-0 | L34: 402.625.628-63 | M34: CADASTRADO | N34: INDENIZAÇÃO | O34: 44900 | P34: N/A | Q34: N/A | R34: N/A | S34: N/A | T34: N/A | U34: N/A | V34: N/A | W34: N/A | X34: N/A | Y34: N/A | Z34: N/A | AB34: STELA MARQUES DA SILVA | AC34: 39.626.761-0 | AD34: 402.625.628-63 | AE34: PROPRIETÁRIO RESIDENTE | AF34: 49800 | AG34: 60000 | AH34: SIM | AI34: FINALIZADO | AJ34: CADASTRADO | AK34: FINALIZADO | AL34: FINALIZADO | AM34: SEM PENDÊNCIA | AO34: 6014.2022/0004136-5 | AP34: FINALIZADO | AQ34: FINALIZADO | AR34: AGUARDANDO ENCAMINHAMENTO | BB34: INDENIZAÇÃO EM ANDAMENTO | BC34: =IF(AY34-ON34=0,"",AY34-O34)
A35: 22 | B35: ALFREDO ÁVILA | C35: 1 | D35: 0 | E35: 0 | F35: 001/0019/A | G35: OCUPADO | H35: RESIDENCIAL | I35: PROPRIETÁRIO RESIDENTE | J35: SUELI GOMES DE SOUZA | K35: 19.370.643-X | L35: 087.913.138-13 | M35: PENDENTE | N35: PENDENTE | O35: 44900 | AB35: SUELI GOMES DE SOUZA | AC35: 19.370.643-X | AD35: 087.913.138-13 | AE35: PROPRIETÁRIO RESIDENTE | AF35: 58100 | AG35: 60000 | BC35: =IF(AY35-ON35=0,"",AY35-O35)
A36: 23 | B36: ALFREDO ÁVILA | C36: 1 | D36: 0 | E36: 0 | F36: 001/0019/B | G36: OCUPADO | H36: RESIDENCIAL | I36: INQUILINO | J36: LUCAS DANIEL GOMES PEREIRA | K36: 52.281.364-1 | L36: 439.284.308-40 | M36: CADASTRADO | N36: AUXÍLIO ALUGUEL UH | O36: 44900 | P36: PENDENTE | AB36: SUELI GOMES DE SOUZA | AC36: 19.370.643-X | AD36: 087.913.138-13 | AE36: PROPRIETÁRIO NÃO RESIDENTE | AF36: 110600 | AG36: 110600 | BC36: =IF(AY36-ON36=0,"",AY36-O36)
A37: 24 | B37: ALFREDO ÁVILA | C37: 1 | D37: 0 | E37: 0 | F37: 001/0024/A | G37: OCUPADO | H37: RESIDENCIAL | I37: INQUILINO | J37: GLEDY MARISE DOS SANTOS ROSA | K37: 30.557.844-3 | L37: 301.750.188-47 | M37: CADASTRADO | N37: AUXÍLIO ALUGUEL UH | O37: 44900 | P37: PENDENTE | AB37: CALINE DOS SANTOS CONVENTO | AC37: 43.781.566-3 | AD37: 229.019.538-32 | AE37: PROPRIETÁRIO NÃO RESIDENTE | AF37: 49000 | AG37: 60000 | BC37: =IF(AY37-ON37=0,"",AY37-O37)
A38: 25 | B38: ALFREDO ÁVILA | C38: 1 | D38: 0 | E38: 0 | F38: 001/0025/A | G38: OCUPADO | H38: RESIDENCIAL | I38: INQUILINO | J38: RUANA PORTILLA | K38: 50.384.970-4 | L38: 461.003.518-97 | M38: CADASTRADO | N38: AUXÍLIO ALUGUEL UH | O38: 44900 | P38: PENDENTE | AB38: DANILO AUGUSTO DA SILVA SANTOS | AC38: 49.188.880-6 | AD38: 439.612.578-09 | AE38: PROPRIETÁRIO NÃO RESIDENTE | AF38: 46500 | AG38: 60000 | AH38: SIM | AI38: FINALIZADO | AJ38: CADASTRADO | AK38: AGUARDANDO ASSINATURA MORADOR | AL38: FINALIZADO | AM38: TERMO ASSINADO MORADOR | AN38: termo de indenização, o nome e o número de CPF estão errados do Sr. Danilo Augusto da Silva Santos, sendo o correto: Danilo Augusto da Silva dos Santos CPF 439.612.578-09 | AO38: 6014.2022/0004083-0 | BB38: DOSSIÊ PENDENTE | BC38: =IF(AY38-ON38=0,"",AY38-O38)
A39: 26 | B39: ALFREDO ÁVILA | C39: 1 | D39: 0 | E39: 0 | F39: 001/0025/B | G39: OCUPADO | H39: RESIDENCIAL | I39: PROPRIETÁRIO RESIDENTE | J39: CARLOS ROBERTO BATISTA DE SOUZA | K39: 27.245.037-6 | L39: 564.518.226-04 | M39: CADASTRADO | N39: INDENIZAÇÃO | O39: 44900 | P39: N/A | Q39: N/A | R39: N/A | S39: N/A | T39: N/A | U39: N/A | V39: N/A | W39: N/A | X39: N/A | Y39: N/A | Z39: N/A | AB39: CARLOS ROBERTO BATISTA DE SOUZA | AC39: 27.245.037-6 | AD39: 564.518.226-04 | AE39: PROPRIETÁRIO RESIDENTE | AF39: 48100 | AG39: 60000 | AH39: SIM | AI39: FINALIZADO | AJ39: CADASTRADO | AK39: FINALIZADO | AL39: FINALIZADO | AM39: SEM PENDÊNCIA | AO39: 6014.2022/0004137-3 | AP39: FINALIZADO | AQ39: FINALIZADO | AR39: AGUARDANDO ENCAMINHAMENTO | BB39: INDENIZAÇÃO EM ANDAMENTO | BC39: =IF(AY39-ON39=0,"",AY39-O39)
A40: 27 | B40: ALFREDO ÁVILA | C40: 1 | D40: 0 | E40: 0 | F40: 001/0026/A | G40: OCUPADO | H40: RESIDENCIAL | I40: PROPRIETÁRIO RESIDENTE | J40: RENATA RODRIGUES DA SILVA | K40: 39.316.490-1 | L40: 371.973.748-98 | M40: CADASTRADO | N40: INDENIZAÇÃO | O40: 44900 | P40: N/A | Q40: N/A | R40: N/A | S40: N/A | T40: N/A | U40: N/A | V40: N/A | W40: N/A | X40: N/A | Y40: N/A | Z40: N/A | AB40: RENATA RODRIGUES DA SILVA | AC40: 39.316.490-1 | AD40: 371.973.748-98 | AE40: PROPRIETÁRIO RESIDENTE | AF40: 27500 | AG40: =AF40+30000 -> 57500 | AH40: SIM | AI40: FINALIZADO | AJ40: CADASTRADO | AK40: FINALIZADO | AL40: FINALIZADO | AM40: SEM PENDÊNCIA | AO40: 6014.2022/0004081-4 | AP40: FINALIZADO | AQ40: FINALIZADO | AR40: AGUARDANDO ENCAMINHAMENTO | BB40: INDENIZAÇÃO EM ANDAMENTO | BC40: =IF(AY40-ON40=0,"",AY40-O40)
A41: 28 | B41: ALFREDO ÁVILA | C41: 1 | D41: 0 | E41: 0 | F41: 001/0026/B | G41: OCUPADO | H41: RESIDENCIAL | I41: INQUILINO | J41: LAIS DA SILVA PEREIRA | K41: 57.273.865-1 | L41: 495.928.678-44 | M41: CADASTRADO | N41: AUXÍLIO ALUGUEL UH | O41: 44900 | P41: PENDENTE | AB41: GERINALDO RIBEIRO BARBOSA | AC41: 32.7770.534-6 | AD41: 873.034.935-49 | AE41: PROPRIETÁRIO NÃO RESIDENTE | AF41: 0 | AG41: 60000 | AH41: SIM | AI41: FINALIZADO | AJ41: CADASTRADO | AK41: AGUARDANDO ENVIO ÁREA | AL41: PENDENTE | AM41: DOSSIÊ + TERMO ASSINADO MORADOR | AN41: Nome da conta bancaria ilegível e laudo consta RG 32.7770.534-6 | AO41: 6014.2022/0004138-1 | BB41: DOSSIÊ PENDENTE | BC41: =IF(AY41-ON41=0,"",AY41-O41)
A42: 29 | B42: ALFREDO ÁVILA | C42: 1 | D42: 0 | E42: 0 | F42: 001/0026/C | G42: OCUPADO | H42: RESIDENCIAL | I42: PROPRIETÁRIO RESIDENTE | J42: GERINALDO RIBEIRO BARBOSA | K42: 32.7770.534-6 | L42: 873.034.935-49 | M42: CADASTRADO | N42: INDENIZAÇÃO | O42: 44900 | P42: N/A | Q42: N/A | R42: N/A | S42: N/A | T42: N/A | U42: N/A | V42: N/A | W42: N/A | X42: N/A | Y42: N/A | Z42: N/A | AB42: GERINALDO RIBEIRO BARBOSA | AC42: 32.7770.534-6 | AD42: 873.034.935-49 | AE42: PROPRIETÁRIO RESIDENTE | AF42: 0 | AG42: 60000 | AH42: SIM | AI42: FINALIZADO | AJ42: CADASTRADO | AK42: AGUARDANDO ENVIO ÁREA | AL42: PENDENTE | AM42: DOSSIÊ + TERMO ASSINADO MORADOR | BB42: DOSSIÊ PENDENTE | BC42: =IF(AY42-ON42=0,"",AY42-O42)
A43: 30 | B43: ALFREDO ÁVILA | C43: 1 | D43: 0 | E43: 0 | F43: 001/0027/A | G43: OCUPADO | H43: RESIDENCIAL | I43: PROPRIETÁRIO RESIDENTE | J43: JOSIELE DE OLIVEIRA SILVA | K43: 47.114.574-9 | L43: 388.201.958-10 | M43: CADASTRADO | N43: INDENIZAÇÃO | O43: 44900 | P43: N/A | Q43: N/A | R43: N/A | S43: N/A | T43: N/A | U43: N/A | V43: N/A | W43: N/A | X43: N/A | Y43: N/A | Z43: N/A | AB43: JOSIELE DE OLIVEIRA SILVA | AC43: 47.114.574-9 | AD43: 388.201.958-10 | AE43: PROPRIETÁRIO RESIDENTE | AF43: 37500 | AG43: 60000 | AH43: SIM | AI43: FINALIZADO | AJ43: CADASTRADO | AK43: FINALIZADO | AL43: FINALIZADO | AM43: SEM PENDÊNCIA | AO43: 6014.2022/0004029-6 | AP43: FINALIZADO | AQ43: FINALIZADO | AR43: FINALIZADO | AS43: FINALIZADO | AT43: 44922 | AU43: FINALIZADO | AV43: FINALIZADO | AW43: FINALIZADO | AX43: 44924 | AY43: 44924 | AZ43: AGUARDANDO | BA43: OCUPADO | BB43: FINALIZADO | BC43: =IF(AY43-ON43=0,"",AY43-O43) -> 24
A44: 31 | B44: ALFREDO ÁVILA | C44: 1 | D44: 0 | E44: 0 | F44: 001/0028/A | G44: OCUPADO | H44: RESIDENCIAL | I44: PROPRIETÁRIO RESIDENTE | J44: THAIS DE OLIVEIRA SILVA FERREIRA | K44: 34.615.609-9 | L44: 387.066.978-01 | M44: CADASTRADO | N44: PENDENTE | O44: 44900 | AB44: THAIS DE OLIVEIRA SILVA FERREIRA | AC44: 34.615.609-9 | AD44: 387.066.978-01 | AE44: PROPRIETÁRIO RESIDENTE | AF44: 31100 | AG44: 60000 | BC44: =IF(AY44-ON44=0,"",AY44-O44)
A45: 32 | B45: ALFREDO ÁVILA | C45: 1 | D45: 0 | E45: 0 | F45: 001/0029/A | G45: OCUPADO | H45: RESIDENCIAL | I45: PROPRIETÁRIO RESIDENTE | J45: FRANCISCO DA CRUZ NANTES | K45: 21.271.587-2 | L45: 383.527.615-87 | M45: CADASTRADO | N45: PENDENTE | O45: 44900 | AB45: FRANCISCO DA CRUZ NANTES | AC45: 21.271.587-2 | AD45: 383.527.615-87 | AE45: PROPRIETÁRIO RESIDENTE | AF45: 3400 | AG45: 33400 | BC45: =IF(AY45-ON45=0,"",AY45-O45)
A46: 33 | B46: ALFREDO ÁVILA | C46: 1 | D46: 0 | E46: 0 | F46: 001/0029/B | G46: OCUPADO | H46: RESIDENCIAL | I46: INQUILINO | J46: JULIO CESAR DOS SANTOS | K46: 53.036.759-2 | L46: 425.874.268-63 | M46: CADASTRADO | N46: AUXÍLIO ALUGUEL UH | O46: 44900 | P46: PENDENTE | AB46: FRANCISCO DA CRUZ NANTES | AC46: 21.271.587-2 | AD46: 383.527.615-87 | AE46: PROPRIETÁRIO NÃO RESIDENTE | AF46: 34900 | AG46: 60000 | BC46: =IF(AY46-ON46=0,"",AY46-O46)
A47: 34 | B47: ALFREDO ÁVILA | C47: 1 | D47: 0 | E47: 0 | F47: 001/0029/C | G47: OCUPADO | H47: RESIDENCIAL | I47: INQUILINO | J47: NIVANILDA RISALVA DA SILVA | K47: 62.212.140-6 | L47: 111.222.474-27 | M47: CADASTRADO | N47: AUXÍLIO ALUGUEL UH | O47: 44900 | P47: PENDENTE | AB47: FRANCISCO DA CRUZ NANTES | AC47: 21.271.587-2 | AD47: 383.527.615-87 | AE47: PROPRIETÁRIO NÃO RESIDENTE | AF47: 20300 | AG47: 50300 | BC47: =IF(AY47-ON47=0,"",AY47-O47)
A48: 35 | B48: ALFREDO ÁVILA | C48: 1 | D48: 0 | E48: 0 | F48: 001/0030/A | G48: CONSTRUÇÃO | H48: RESIDENCIAL | I48: RESIDENTE AUSENTE | M48: PENDENTE | N48: PENDENTE | O48: 44900 | P48: PENDENTE | AB48: AMANDA OLIVEIRA DE ARAUJO | AC48: 43.521.928-5 | AD48: 435.738.668-32 | AE48: PROPRIETÁRIO NÃO RESIDENTE | AF48: =AG48-30000 -> 8500 | AG48: 38500 | AH48: SIM | AI48: FINALIZADO | AJ48: CADASTRADO | AK48: FINALIZADO | AL48: FINALIZADO | AM48: SEM PENDÊNCIA | AO48: 6014.2022/0004027-0 | AP48: FINALIZADO | AQ48: FINALIZADO | AR48: FINALIZADO | AS48: FINALIZADO | AT48: 44922 | AU48: FINALIZADO | AV48: FINALIZADO | AW48: FINALIZADO | AX48: 44924 | AY48: 44924 | AZ48: AGUARDANDO | BA48: OCUPADO | BB48: AA PENDENTE - INDENIZAÇÃO FINALIZADA | BC48: =IF(AY48-ON48=0,"",AY48-O48) -> 24
A49: 36 | B49: ALFREDO ÁVILA | C49: 1 | D49: 0 | E49: 0 | F49: 001/0031/A | G49: OCUPADO | H49: RESIDENCIAL | I49: INQUILINO | J49: VANESSA BEATRIZ SOUZA SANTOS | K49: 44.557.726-9 | L49: 435.738.668-32 | M49: PENDENTE | N49: PENDENTE | O49: 44900 | AB49: VANESSA BEATRIZ SOUZA SANTOS | AC49: 44.557.726-9 | AD49: 435.738.668-32 | AE49: PROPRIETÁRIO NÃO RESIDENTE | AF49: 33500 | AG49: 60000 | BC49: =IF(AY49-ON49=0,"",AY49-O49)
A50: 37 | B50: ALFREDO ÁVILA | C50: 1 | D50: 0 | E50: 0 | F50: 001/0032/A | G50: OCUPADO | H50: RESIDENCIAL | I50: INQUILINO | J50: DEBORAH SALLES DA SILVA | K50: 25.769.760-3 | L50: 215.312.868-44 | M50: CADASTRADO | N50: AUXÍLIO ALUGUEL UH | O50: 44900 | P50: PENDENTE | AB50: LÚCIA JERONYMA SALLES | AC50: 36973178 | AD50: 040.770.428-01 | AE50: PROPRIETÁRIO NÃO RESIDENTE | AF50: 0 | AG50: 60000 | AH50: SIM | AI50: FINALIZADO | AJ50: CADASTRADO | AK50: FINALIZADO | AL50: FINALIZADO | AM50: SEM PENDÊNCIA | AO50: 6014.2022/0004031-8 | AP50: FINALIZADO | AQ50: FINALIZADO | AR50: FINALIZADO | AS50: FINALIZADO | AT50: 44922 | AU50: FINALIZADO | AV50: FINALIZADO | AW50: PENDENTE REGULARIZAÇÃO RF | BB50: AA PENDENTE - INDENIZAÇÃO EM ANDAMENTO | BC50: =IF(AY50-ON50=0,"",AY50-O50)
A51: 38 | B51: ALFREDO ÁVILA | C51: 1 | D51: 0 | E51: 0 | F51: 001/0032/B | G51: OCUPADO | H51: RESIDENCIAL | I51: INQUILINO | J51: NATIELE BARBOSA SOUZA | K51: 59.909.486-2 | L51: 075.602.185-55 | M51: CADASTRADO | N51: AUXÍLIO ALUGUEL UH | O51: 44900 | P51: PENDENTE | AB51: ADRIANA FERREIRA MARQUES | AC51: 38.775.449-0 | AD51: 382.605.788-08 | AE51: PROPRIETÁRIO NÃO RESIDENTE | AF51: 53700 | AG51: 60000 | AH51: SIM | AI51: FINALIZADO | AJ51: CADASTRADO | AK51: FINALIZADO | AL51: FINALIZADO | AM51: SEM PENDÊNCIA | AO51: 6014.2023/0000025-3 | AP51: FINALIZADO | AQ51: FINALIZADO | AR51: AGUARDANDO ENCAMINHAMENTO | BC51: =IF(AY51-ON51=0,"",AY51-O51)
A52: 39 | B52: ALFREDO ÁVILA | C52: 1 | D52: 0 | E52: 0 | F52: 001/0032/C | G52: OCUPADO | H52: RESIDENCIAL | I52: INQUILINO | J52: JOÃO GABRIEL PEREIRA SORIANO | K52: 38.643.918-7 | L52: 439.476.688-56 | M52: CADASTRADO | N52: AUXÍLIO ALUGUEL UH | O52: 44900 | P52: PENDENTE | AB52: LUCIVANIA MARIA DA SILVA NOVAES | AC52: 42.178.340-0 | AD52: 316.656.868-98 | AE52: PROPRIETÁRIO NÃO RESIDENTE | AF52: 0 | AG52: 60000 | AH52: SIM | AI52: FINALIZADO | AJ52: CADASTRADO | AK52: FINALIZADO | AL52: FINALIZADO | AM52: SEM PENDÊNCIA | AO52: 6014.2022/0004032-6 | AP52: FINALIZADO | AQ52: FINALIZADO | AR52: AGUARDANDO ENCAMINHAMENTO | BB52: AA PENDENTE - INDENIZAÇÃO EM ANDAMENTO | BC52: =IF(AY52-ON52=0,"",AY52-O52)
A53: 40 | B53: ALFREDO ÁVILA | C53: 1 | D53: 0 | E53: 0 | F53: 001/0036/A | G53: OCUPADO | H53: RESIDENCIAL | I53: PROPRIETÁRIO RESIDENTE | J53: ALICE BARBOSA PEREIRA | K53: 50.347.964-0 | L53: 489.240.398-90 | M53: CADASTRADO | N53: INDENIZAÇÃO | O53: 44900 | P53: N/A | Q53: N/A | R53: N/A | S53: N/A | T53: N/A | U53: N/A | V53: N/A | W53: N/A | X53: N/A | Y53: N/A | Z53: N/A | AB53: ALICE BARBOSA PEREIRA | AC53: 50.347.964-0 | AD53: 489.240.398-90 | AE53: PROPRIETÁRIO RESIDENTE | AF53: 38700 | AG53: 60000 | AH53: SIM | AI53: FINALIZADO | AJ53: CADASTRADO | AK53: FINALIZADO | AL53: FINALIZADO | AM53: SEM PENDÊNCIA | AO53: 6014.2022/0004139-0 | AP53: FINALIZADO | AQ53: FINALIZADO | AR53: AGUARDANDO ENCAMINHAMENTO | BB53: INDENIZAÇÃO EM ANDAMENTO | BC53: =IF(AY53-ON53=0,"",AY53-O53)
A54: 41 | B54: ALFREDO ÁVILA | C54: 1 | D54: 0 | E54: 0 | F54: 001/0036/B | G54: OCUPADO | H54: RESIDENCIAL | I54: PROPRIETÁRIO RESIDENTE | J54: ALISSON BARBOSA PEREIRA | K54: 50.347.972-X | L54: 489.240.878-60 | M54: CADASTRADO | N54: INDENIZAÇÃO | O54: 44900 | P54: N/A | Q54: N/A | R54: N/A | S54: N/A | T54: N/A | U54: N/A | V54: N/A | W54: N/A | X54: N/A | Y54: N/A | Z54: N/A | AB54: ALISSON BARBOSA PEREIRA | AC54: 50.347.972-X | AD54: 489.240.878-60 | AE54: PROPRIETÁRIO RESIDENTE | AF54: 21400 | AG54: 51400 | AH54: SIM | AI54: FINALIZADO | AJ54: CADASTRADO | AK54: FINALIZADO | AL54: FINALIZADO | AM54: SEM PENDÊNCIA | AO54: 6014.2022/0004140-3 | AP54: FINALIZADO | AQ54: FINALIZADO | AR54: AGUARDANDO ENCAMINHAMENTO | BB54: INDENIZAÇÃO EM ANDAMENTO | BC54: =IF(AY54-ON54=0,"",AY54-O54)
A55: 42 | B55: ALFREDO ÁVILA | C55: 1 | D55: 0 | E55: 0 | F55: 001/0037/A | G55: OCUPADO | H55: RESIDENCIAL | I55: INQUILINO | J55: ANA LUCIA RAMOS DUARTE | K55: 62.219.271-1 | L55: 241.475.398-66 | M55: CADASTRADO | N55: AUXÍLIO ALUGUEL UH | O55: 44900 | P55: PENDENTE | AB55: LUIS CAETANO | AC55: 21.966.817-6 | AD55: 166.820.668-73 | AE55: PROPRIETÁRIO NÃO RESIDENTE | AF55: 26300 | AG55: 56300 | AH55: SIM | AI55: FINALIZADO | AJ55: CADASTRADO | AK55: FINALIZADO | AL55: PENDENTE | AM55: DOSSIÊ | AN55: Número do CPF está errado no Termo Indenização e no Laudo | AO55: 6014.2023/0000339-2 | BC55: =IF(AY55-ON55=0,"",AY55-O55)
A56: 43 | B56: ALFREDO ÁVILA | C56: 1 | D56: 0 | E56: 0 | F56: 001/0037/B | G56: OCUPADO | H56: RESIDENCIAL | I56: RESIDENTE AUSENTE | M56: PENDENTE | N56: PENDENTE | O56: 44900 | BC56: =IF(AY56-ON56=0,"",AY56-O56)
A57: 44 | B57: ALFREDO ÁVILA | C57: 1 | D57: 0 | E57: 0 | F57: 001/0037/C | G57: OCUPADO | H57: RESIDENCIAL | I57: PROPRIETÁRIO RESIDENTE | J57: ANGÉLICA SUELLEN RAMOS SERGINA | K57: 52.373.516-9 | L57: 474.575.748-40 | M57: CADASTRADO | N57: PENDENTE | O57: 44900 | AB57: ANGÉLICA SUELLEN RAMOS SERGINA | AC57: 52.373.516-9 | AD57: 474.575.748-40 | AE57: PROPRIETÁRIO RESIDENTE | AF57: 35700 | AG57: 60000 | BC57: =IF(AY57-ON57=0,"",AY57-O57)
A58: 45 | B58: ALFREDO ÁVILA | C58: 1 | D58: 0 | E58: 0 | F58: 001/0038/A | G58: OCUPADO | H58: NÃO RESIDENCIAL | N58: PENDENTE | O58: 44900 | AB58: WAGNER FERREIRA | AC58: 29.988.378-4 | AD58: 213.110.988-10 | AE58: PROPRIETÁRIO RESIDENTE | AF58: 17700 | AG58: 47700 | AN58: O Wagner Ferreira no e-mail consta como não residente e não consta cadastrado no sistema Habitasampa como não residente. Falta validar o cadastro? | AO58: 6014.2022/0003943-3 | BC58: =IF(AY58-ON58=0,"",AY58-O58)
A59: 46 | B59: ALFREDO ÁVILA | C59: 1 | D59: 0 | E59: 0 | F59: 001/0038/B | G59: OCUPADO | H59: RESIDENCIAL | I59: PROPRIETÁRIO RESIDENTE | J59: WIRNA JOSÉ DE PAULA | K59: 22.282.027-5 | L59: 115.086.198-32 | M59: CADASTRADO | N59: INDENIZAÇÃO | O59: 44900 | P59: N/A | Q59: N/A | R59: N/A | S59: N/A | T59: N/A | U59: N/A | V59: N/A | W59: N/A | X59: N/A | Y59: N/A | Z59: N/A | AB59: WIRNA JOSÉ DE PAULA | AC59: 22.282.027-5 | AD59: 115.086.198-32 | AE59: PROPRIETÁRIO RESIDENTE | AF59: 27300 | AG59: 57300 | AH59: SIM | AI59: FINALIZADO | AJ59: CADASTRADO | AK59: FINALIZADO | AL59: FINALIZADO | AM59: SEM PENDÊNCIA | AO59: 6014.2022/0003962-0 | AP59: FINALIZADO | AQ59: FINALIZADO | AR59: AGUARDANDO ENCAMINHAMENTO | BB59: INDENIZAÇÃO EM ANDAMENTO | BC59: =IF(AY59-ON59=0,"",AY59-O59)
A60: 47 | B60: ALFREDO ÁVILA | C60: 1 | D60: 0 | E60: 0 | F60: 001/0039/A | G60: OCUPADO | H60: RESIDENCIAL | I60: PROPRIETÁRIO RESIDENTE | J60: BEATRIZ RODRIGUES DOS SANTOS | K60: 39.897.214-X | L60: 496.357.038-64 | M60: PENDENTE | N60: PENDENTE | O60: 44900 | AB60: BEATRIZ RODRIGUES DOS SANTOS | AC60: 39.897.214-X | AD60: 496.357.038-64 | AE60: PROPRIETÁRIO RESIDENTE | AF60: 15800 | AG60: =AF60+30000 -> 45800 | BC60: =IF(AY60-ON60=0,"",AY60-O60)
A61: 48 | B61: ALFREDO ÁVILA | C61: 1 | D61: 0 | E61: 0 | F61: 001/0047/A | G61: OCUPADO | H61: RESIDENCIAL | I61: PROPRIETÁRIO RESIDENTE | J61: DEBORA EVELLYN DOS SANTOS FLORES | K61: 53.045.343-5 | L61: 457.431.978-06 | M61: PENDENTE | N61: PENDENTE | O61: 44900 | AB61: DEBORA EVELLYN DOS SANTOS FLORES | AC61: 53.045.343-5 | AD61: 457.431.978-06 | AE61: PROPRIETÁRIO RESIDENTE | AF61: 17500 | AG61: =AF61+30000 -> 47500 | BC61: =IF(AY61-ON61=0,"",AY61-O61)
A62: 49 | B62: ALFREDO ÁVILA | C62: 1 | D62: 0 | E62: 0 | F62: 001/0047/B | G62: OCUPADO | H62: RESIDENCIAL | I62: PROPRIETÁRIO RESIDENTE | J62: ELOY SANTOS FLORES | K62: 53.045.236-4 | L62: 454.872.348-09 | M62: PENDENTE | N62: PENDENTE | O62: 44900 | AB62: ELOY SANTOS FLORES | AC62: 53.045.236-4 | AD62: 454.872.348-09 | AE62: PROPRIETÁRIO RESIDENTE | AF62: 24200 | AG62: =AF62+30000 -> 54200 | BC62: =IF(AY62-ON62=0,"",AY62-O62)
A63: 50 | B63: ALFREDO ÁVILA | C63: 1 | D63: 0 | E63: 0 | F63: 001/0047/C | G63: OCUPADO | H63: RESIDENCIAL | I63: PROPRIETÁRIO RESIDENTE | J63: DIEGO DOS SANTOS FLORES | K63: 34.199.065-4 | L63: 344.130.078-59 | M63: CADASTRADO | N63: INDENIZAÇÃO | O63: 44900 | P63: N/A | Q63: N/A | R63: N/A | S63: N/A | T63: N/A | U63: N/A | V63: N/A | W63: N/A | X63: N/A | Y63: N/A | Z63: N/A | AB63: DIEGO DOS SANTOS FLORES | AC63: 34.199.065-4 | AD63: 344.130.078-59 | AE63: PROPRIETÁRIO RESIDENTE | AF63: =AG63-30000 -> 8500 | AG63: 38500 | AH63: SIM | AI63: FINALIZADO | AJ63: CADASTRADO | AK63: FINALIZADO | AL63: FINALIZADO | AM63: SEM PENDÊNCIA | AO63: 6014.2023/0000168-3 | AP63: FINALIZADO | AQ63: FINALIZADO | AR63: AGUARDANDO ENCAMINHAMENTO | BB63: DOSSIÊ PENDENTE
A64: 51 | B64: ALFREDO ÁVILA | C64: 1 | D64: 0 | E64: 0 | F64: 001/0048/A | G64: OCUPADO | H64: RESIDENCIAL | I64: PROPRIETÁRIO RESIDENTE | J64: LETÍCIA SOARES SOUSA | K64: 53.906.268-6 | L64: 557.850.828-61 | M64: CADASTRADO | N64: INDENIZAÇÃO | O64: 44900 | P64: N/A | Q64: N/A | R64: N/A | S64: N/A | T64: N/A | U64: N/A | V64: N/A | W64: N/A | X64: N/A | Y64: N/A | Z64: N/A | AB64: LETÍCIA SOARES SOUSA | AC64: 53.906.268-6 | AD64: 557.850.828-61 | AE64: PROPRIETÁRIO RESIDENTE | AF64: =AG64-30000 -> 18100 | AG64: 48100 | AH64: SIM | AI64: FINALIZADO | AJ64: CADASTRADO | AK64: FINALIZADO | AL64: FINALIZADO | AM64: SEM PENDÊNCIA | AO64: 6014.2022/0004033-4 | AP64: FINALIZADO | AQ64: FINALIZADO | AR64: FINALIZADO | AS64: FINALIZADO | AT64: 44922 | AU64: FINALIZADO | AV64: FINALIZADO | AW64: FINALIZADO | AX64: 44924 | AY64: 44924 | AZ64: AGUARDANDO | BA64: OCUPADO | BB64: FINALIZADO | BC64: =IF(AY64-ON64=0,"",AY64-O64) -> 24
A65: 52 | B65: ALFREDO ÁVILA | C65: 1 | D65: 0 | E65: 0 | F65: 001/0049/A | G65: OCUPADO | H65: RESIDENCIAL | I65: INQUILINO | J65: WENDEL ENRIQUE SANTANA SOUZA | K65: 62.514.646-3 | L65: 516.094.758-28 | M65: CADASTRADO | N65: AUXÍLIO ALUGUEL UH | O65: 44900 | P65: PENDENTE | AB65: CLAUDIA BARBOSA DA SILVA SANTOS | AC65: 44.876.275-4 | AD65: 393.752.108-98 | AE65: PROPRIETÁRIO NÃO RESIDENTE | AF65: 18400 | AG65: =AF65+30000 -> 48400 | AH65: SIM | AI65: FINALIZADO | AJ65: CADASTRADO | AK65: FINALIZADO | AL65: FINALIZADO | AM65: SEM PENDÊNCIA | AO65: 6014.2022/0003955-7 | AP65: FINALIZADO | AQ65: FINALIZADO | AR65: AGUARDANDO ENCAMINHAMENTO | BB65: AA PENDENTE - INDENIZAÇÃO EM ANDAMENTO | BC65: =IF(AY65-ON65=0,"",AY65-O65)
A66: 53 | B66: ALFREDO ÁVILA | C66: 1 | D66: 0 | E66: 0 | F66: 001/0049/B | G66: OCUPADO | H66: RESIDENCIAL | I66: INQUILINO | J66: JOSEILDO FERNANDO DA SILVA | K66: 44.926.182-7 | L66: 370.264.498-93 | M66: CADASTRADO | N66: AUXÍLIO ALUGUEL UH | O66: 44900 | P66: PENDENTE | AB66: CLAUDIA BARBOSA DA SILVA SANTOS | AC66: 44.876.275-4 | AD66: 393.752.108-98 | AE66: PROPRIETÁRIO NÃO RESIDENTE | AF66: 13300 | AG66: =AF66+30000 -> 43300 | BC66: =IF(AY66-ON66=0,"",AY66-O66)
A67: 54 | B67: ALFREDO ÁVILA | C67: 1 | D67: 0 | E67: 0 | F67: 001/0050/A | G67: OCUPADO | H67: RESIDENCIAL | I67: PROPRIETÁRIO RESIDENTE | J67: ÁGATHA ALESSANDRA DE PAULA | K67: 39.897.247-3 | L67: 390.685.488-40 | M67: CADASTRADO | N67: INDENIZAÇÃO | O67: 44900 | P67: N/A | Q67: N/A | R67: N/A | S67: N/A | T67: N/A | U67: N/A | V67: N/A | W67: N/A | X67: N/A | Y67: N/A | Z67: N/A | AB67: ÁGATHA ALESSANDRA DE PAULA | AC67: 39.897.247-3 | AD67: 390.685.488-40 | AE67: PROPRIETÁRIO RESIDENTE | AF67: =AG67-30000 -> 13800 | AG67: 43800 | AH67: SIM | AI67: FINALIZADO | AJ67: CADASTRADO | AK67: AGUARDANDO ASSINATURA MORADOR | AL67: PENDENTE | AM67: DOSSIÊ + TERMO ASSINADO MORADOR | BB67: DOSSIÊ PENDENTE | BC67: =IF(AY67-ON67=0,"",AY67-O67)
A68: 55 | B68: ALFREDO ÁVILA | C68: 1 | D68: 0 | E68: 0 | F68: 001/0051/A | G68: CONSTRUÇÃO | H68: RESIDENCIAL | I68: PROPRIETÁRIO RESIDENTE | J68: ANDRÉ FERREIRA DE FRANÇA | K68: 42.348.779-6 | L68: 359.457.468-78 | M68: CADASTRADO | N68: INDENIZAÇÃO | O68: 44900 | P68: N/A | Q68: N/A | R68: N/A | S68: N/A | T68: N/A | U68: N/A | V68: N/A | W68: N/A | X68: N/A | Y68: N/A | Z68: N/A | AB68: ANDRÉ FERREIRA DE FRANÇA | AC68: 42.348.779-6 | AD68: 359.457.468-78 | AE68: PROPRIETÁRIO RESIDENTE | AF68: 12600 | AG68: =AF68+30000 -> 42600 | AH68: SIM | AI68: FINALIZADO | AJ68: CADASTRADO | AK68: FINALIZADO | AL68: PENDENTE | AM68: DOSSIÊ | BC68: =IF(AY68-ON68=0,"",AY68-O68)
A69: 56 | B69: ALFREDO ÁVILA | C69: 1 | D69: 0 | E69: 0 | F69: 001/0052/A | G69: OCUPADO | H69: RESIDENCIAL | I69: PROPRIETÁRIO RESIDENTE | J69: WAGNER RAMALHO QUEIROZ | K69: 37.142.909-2 | L69: 453.314.278-80 | M69: CADASTRADO | N69: INDENIZAÇÃO | O69: 44900 | P69: N/A | Q69: N/A | R69: N/A | S69: N/A | T69: N/A | U69: N/A | V69: N/A | W69: N/A | X69: N/A | Y69: N/A | Z69: N/A | AB69: WAGNER RAMALHO QUEIROZ | AC69: 37.142.909-2 | AD69: 453.314.278-80 | AE69: PROPRIETÁRIO RESIDENTE | AF69: 23400 | AG69: =AF69+30000 -> 53400 | AH69: SIM | AI69: FINALIZADO | AJ69: CADASTRADO | AK69: FINALIZADO | AL69: FINALIZADO | AM69: SEM PENDÊNCIA | AO69: 6014.2022/0003960-3 | AP69: FINALIZADO | AQ69: FINALIZADO | AR69: AGUARDANDO ENCAMINHAMENTO | BB69: INDENIZAÇÃO EM ANDAMENTO | BC69: =IF(AY69-ON69=0,"",AY69-O69)
A70: 57 | B70: ALFREDO ÁVILA | C70: 1 | D70: 0 | E70: 0 | F70: 001/0052/B | G70: OCUPADO | H70: RESIDENCIAL | I70: PROPRIETÁRIO RESIDENTE | J70: SIMONE DE JESUS ROCHA | K70: 62.057.806-3 | L70: 418.163.308-14 | M70: CADASTRADO | N70: PENDENTE | O70: 44900 | AB70: SIMONE DE JESUS ROCHA | AC70: 62.057.806-3 | AD70: 418.163.308-14 | AE70: PROPRIETÁRIO RESIDENTE | AF70: 35800 | AG70: 60000 | BC70: =IF(AY70-ON70=0,"",AY70-O70)
A71: 58 | B71: ALFREDO ÁVILA | C71: 1 | D71: 0 | E71: 0 | F71: 001/0053/A | G71: OCUPADO | H71: RESIDENCIAL | I71: INQUILINO | J71: EDUARDO VIEIRA GABRIEL | K71: 10.085.479 | L71: 041.884.086-50 | M71: CADASTRADO | N71: AUXÍLIO ALUGUEL UH | O71: 44900 | P71: PENDENTE | AB71: NILVA DA SILVEIRA VARGAS | AC71: 52.751.188-2 | AD71: 033.699.229-75 | AE71: PROPRIETÁRIO NÃO RESIDENTE | AF71: 37800 | AG71: 60000 | AH71: SIM | AI71: FINALIZADO | AJ71: CADASTRADO | AK71: FINALIZADO | AL71: FINALIZADO | AM71: SEM PENDÊNCIA | AO71: 6014.2022/0004089-0 | AP71: FINALIZADO | AQ71: FINALIZADO | AR71: FINALIZADO | AS71: FINALIZADO | AT71: 44922 | AU71: FINALIZADO | AV71: FINALIZADO | AW71: FINALIZADO | AX71: 44924 | AY71: 44924 | AZ71: AGUARDANDO | BA71: OCUPADO | BB71: FINALIZADO | BC71: =IF(AY71-ON71=0,"",AY71-O71) -> 24
A72: 59 | B72: ALFREDO ÁVILA | C72: 1 | D72: 0 | E72: 0 | F72: 001/0053/B | G72: OCUPADO | H72: RESIDENCIAL | I72: INQUILINO | J72: FERNANDA MERCES DA SILVEIRA | K72: 50.771.152-X | L72: 528.864.978-27 | M72: CADASTRADO | N72: AUXÍLIO ALUGUEL UH | O72: 44900 | P72: PENDENTE | AB72: NILVA DA SILVEIRA VARGAS | AC72: 52.751.188-2 | AD72: 033.699.229-75 | AE72: PROPRIETÁRIO NÃO RESIDENTE | AF72: 40100 | AG72: 60000 | AH72: N/A | AI72: N/A | AJ72: N/A | AK72: N/A | AL72: N/A | AM72: N/A | AN72: RECEBEU INDENIZAÇÃO PELO SELO 001/0053/A | AO72: N/A | AP72: N/A | AQ72: N/A | AR72: N/A | AS72: N/A | AT72: N/A | AU72: N/A | AV72: N/A | AW72: N/A | BB72: AA PENDENTE | BC72: =IF(AY72-ON72=0,"",AY72-O72)
A73: 60 | B73: ALFREDO ÁVILA | C73: 1 | D73: 0 | E73: 0 | F73: 001/0054/A | G73: OCUPADO | H73: RESIDENCIAL | I73: PROPRIETÁRIO RESIDENTE | J73: RYCK VINNICIUS DA SILVA | K73: 39.313.802-1 | L73: 412.686.548-92 | M73: CADASTRADO | N73: INDENIZAÇÃO | O73: 44900 | P73: N/A | Q73: N/A | R73: N/A | S73: N/A | T73: N/A | U73: N/A | V73: N/A | W73: N/A | X73: N/A | Y73: N/A | Z73: N/A | AB73: RYCK VINNICIUS DA SILVA | AC73: 39.313.802-1 | AD73: 412.686.548-92 | AE73: PROPRIETÁRIO RESIDENTE | AF73: 12100 | AG73: =AF73+30000 -> 42100 | AH73: SIM | AI73: FINALIZADO | AJ73: CADASTRADO | AK73: FINALIZADO | AL73: FINALIZADO | AM73: SEM PENDÊNCIA | AO73: 6014.2022/0004086-5 | AP73: FINALIZADO | AQ73: FINALIZADO | AR73: FINALIZADO | AS73: FINALIZADO | AT73: 44922 | AU73: FINALIZADO | AV73: FINALIZADO | AW73: PENDENTE REGULARIZAÇÃO RF | BB73: INDENIZAÇÃO EM ANDAMENTO | BC73: =IF(AY73-ON73=0,"",AY73-O73)
A74: 61 | B74: ALFREDO ÁVILA | C74: 1 | D74: 0 | E74: 0 | F74: 001/0055/A | G74: OCUPADO | H74: RESIDENCIAL | I74: PROPRIETÁRIO RESIDENTE | J74: ROGERIO ALEX RAMOS SERGINA | K74: 43.273.271-8 | L74: 445.951.018-99 | M74: CADASTRADO | N74: INDENIZAÇÃO | O74: 44900 | P74: N/A | Q74: N/A | R74: N/A | S74: N/A | T74: N/A | U74: N/A | V74: N/A | W74: N/A | X74: N/A | Y74: N/A | Z74: N/A | AB74: ROGERIO ALEX RAMOS SERGINA | AC74: 43.273.271-8 | AD74: 445.951.018-99 | AE74: PROPRIETÁRIO RESIDENTE | AF74: =AG74-30000 -> 19600 | AG74: 49600 | AH74: SIM | AI74: FINALIZADO | AJ74: CADASTRADO | AK74: AGUARDANDO ENVIO ÁREA | AL74: PENDENTE | AM74: DOSSIÊ + TERMO ASSINADO MORADOR | BB74: DOSSIÊ PENDENTE | BC74: =IF(AY74-ON74=0,"",AY74-O74)
A75: 62 | B75: ALFREDO ÁVILA | C75: 1 | D75: 0 | E75: 0 | F75: 001/0056/A | G75: CONSTRUÇÃO | H75: RESIDENCIAL | I75: INQUILINO | N75: AUXÍLIO ALUGUEL UH | O75: 44900 | P75: PENDENTE | AB75: ROSIEL DE BARROS CARDOSO BATISTA | AC75: 42.363.207-3 | AD75: 420.017.688-26 | AE75: PROPRIETÁRIO NÃO RESIDENTE | AF75: =AG75-30000 -> 8500 | AG75: 38500 | AH75: SIM | AI75: FINALIZADO | AJ75: CADASTRADO | AK75: FINALIZADO | AL75: FINALIZADO | AM75: SEM PENDÊNCIA | AO75: 6014.2022/0004143-8 | AP75: FINALIZADO | AQ75: FINALIZADO | AR75: AGUARDANDO ENCAMINHAMENTO | BB75: AA PENDENTE - INDENIZAÇÃO EM ANDAMENTO | BC75: =IF(AY75-ON75=0,"",AY75-O75)
A76: 63 | B76: ALFREDO ÁVILA | C76: 2 | D76: 0 | E76: 0 | F76: 001/0057/A | G76: OCUPADO | H76: RESIDENCIAL | J76: GUILHERME DOS SANTOS GARCIA
A77: 64 | B77: ALFREDO ÁVILA | C77: 2 | D77: 0 | E77: 0 | F77: 001/0057/B | G77: OCUPADO | H77: RESIDENCIAL | J77: LETICIA BISPO DOS SANTOS
A78: 65 | B78: ALFREDO ÁVILA | C78: 2 | D78: 0 | E78: 0 | F78: 001/0057/C | G78: OCUPADO | H78: NÃO RESIDENCIAL | J78: ANTONIO CARLOS DOS SANTOS
A79: 66 | B79: ALFREDO ÁVILA | C79: 2 | D79: 0 | E79: 0 | F79: 001/0057/D | G79: OCUPADO | H79: RESIDENCIAL | I79: RESIDENTE AUSENTE
A80: 67 | B80: ALFREDO ÁVILA | C80: 2 | D80: 0 | E80: 0 | F80: 001/0059/A | G80: OCUPADO | H80: RESIDENCIAL | J80: EVELINE SPINOLA SILVA
A81: 68 | B81: ALFREDO ÁVILA | C81: 2 | D81: 0 | E81: 0 | F81: 001/0060/A | G81: OCUPADO | H81: NÃO RESIDENCIAL | J81: FERNANDO DA COSTA RODRIGUES
A82: 69 | B82: ALFREDO ÁVILA | C82: 2 | D82: 0 | E82: 0 | F82: 001/0061/A | G82: OCUPADO | H82: RESIDENCIAL | J82: VERENE REGINA NOGUEIRA DA SILVA
A83: 70 | B83: ALFREDO ÁVILA | C83: 2 | D83: 0 | E83: 0 | F83: 001/0061/B | G83: OCUPADO | H83: RESIDENCIAL | J83: LEONARDO BORGES DOS SANTOS
A84: 71 | B84: ALFREDO ÁVILA | C84: 1 | D84: 0 | E84: 0 | F84: 001/0062/A | G84: OCUPADO | H84: RESIDENCIAL | I84: PROPRIETÁRIO RESIDENTE | J84: INGRID DALYLLA DE PAULA CAETANO | K84: 43.572.592-0 | L84: 390.685.508-29 | M84: CADASTRADO | N84: INDENIZAÇÃO | O84: 44900 | P84: N/A | Q84: N/A | R84: N/A | S84: N/A | T84: N/A | U84: N/A | V84: N/A | W84: N/A | X84: N/A | Y84: N/A | Z84: N/A | AB84: INGRID DALYLLA DE PAULA CAETANO | AC84: 43.572.592-0 | AD84: 390.685.508-29 | AE84: PROPRIETÁRIO RESIDENTE | AF84: =AG84-30000 -> 16900 | AG84: 46900 | AH84: SIM | AI84: FINALIZADO | AJ84: CADASTRADO | AK84: AGUARDANDO ASSINATURA MORADOR | AL84: PENDENTE | AM84: DOSSIÊ + TERMO ASSINADO MORADOR | AN84: VALOR INDENIZAÇÃO TERMO INCORRETO | BB84: DOSSIÊ PENDENTE | BC84: =IF(AY84-ON84=0,"",AY84-O84)
A85: 72 | B85: ALFREDO ÁVILA | C85: 1 | D85: 0 | E85: 0 | F85: 001/0063/A | G85: OCUPADO | H85: RESIDENCIAL | I85: PROPRIETÁRIO RESIDENTE | J85: VITORIA REGINA NOGUEIRA OLIVEIRA | K85: 50532157-9 | L85: 497.368.808-85 | M85: CADASTRADO | N85: INDENIZAÇÃO | O85: 44900 | P85: N/A | Q85: N/A | R85: N/A | S85: N/A | T85: N/A | U85: N/A | V85: N/A | W85: N/A | X85: N/A | Y85: N/A | Z85: N/A | AB85: VITORIA REGINA NOGUEIRA OLIVEIRA | AC85: 50532157-9 | AD85: 497.368.808-85 | AE85: PROPRIETÁRIO RESIDENTE | AF85: 23200 | AG85: =AF85+30000 -> 53200 | AH85: SIM | AI85: FINALIZADO | AJ85: CADASTRADO | AK85: FINALIZADO | AL85: PENDENTE | AM85: DOSSIÊ | BB85: DOSSIÊ PENDENTE | BC85: =IF(AY85-ON85=0,"",AY85-O85)
A86: 73 | B86: ALFREDO ÁVILA | C86: 2 | D86: 0 | E86: 0 | F86: 001/0064/A | G86: OCUPADO | H86: RESIDENCIAL | J86: ELOANA CRISTINA DE SOUZA MELO
A87: 74 | B87: ALFREDO ÁVILA | C87: 2 | D87: 0 | E87: 0 | F87: 001/0065/A | G87: OCUPADO | H87: RESIDENCIAL | J87: HENRIQUE MELLO ELIAS
A88: 75 | B88: ALFREDO ÁVILA | C88: 2 | D88: 0 | E88: 0 | F88: 001/0066/A | G88: OCUPADO | H88: RESIDENCIAL | J88: SONIA JOSEFA DA SILVA
A89: 76 | B89: ALFREDO ÁVILA | C89: 2 | D89: 0 | E89: 0 | F89: 001/0067/A | G89: OCUPADO | H89: RESIDENCIAL | J89: WILLIAM ALVES DOS SANTOS
A90: 77 | B90: ALFREDO ÁVILA | C90: 2 | D90: 0 | E90: 0 | F90: 001/0068/A | G90: OCUPADO | H90: RESIDENCIAL | J90: IVANISE PESSOA DE SANTANA
A91: 78 | B91: ALFREDO ÁVILA | C91: 2 | D91: 0 | E91: 0 | F91: 001/0068/B | G91: OCUPADO | H91: RESIDENCIAL | J91: TALITA RAMOS CAETANO
A92: 79 | B92: ALFREDO ÁVILA | C92: 2 | D92: 0 | E92: 0 | F92: 001/0069/A | G92: OCUPADO | H92: RESIDENCIAL | J92: EMILIO ANSELMO LIMA
A93: 80 | B93: ALFREDO ÁVILA | C93: 2 | D93: 0 | E93: 0 | F93: 001/0069/B | G93: OCUPADO | H93: RESIDENCIAL | J93: ESPEDITO ANSELMO LIMA
A94: 81 | B94: ALFREDO ÁVILA | C94: 2 | D94: 0 | E94: 0 | F94: 001/0070/A | G94: OCUPADO | H94: RESIDENCIAL | J94: ISAURA ASSIS DO NASCIMENTO
A95: 82 | B95: ALFREDO ÁVILA | C95: 2 | D95: 0 | E95: 0 | F95: 001/0070/B | G95: OCUPADO | H95: RESIDENCIAL | J95: VERA LUCIA DE LIMA
A96: 83 | B96: ALFREDO ÁVILA | C96: 2 | D96: 0 | E96: 0 | F96: 001/0070/C | G96: OCUPADO | H96: RESIDENCIAL | J96: CRISTIANE GOMES FAGUNDES SILVA
A97: 84 | B97: ALFREDO ÁVILA | C97: 2 | D97: 0 | E97: 0 | F97: 001/0071/A | G97: OCUPADO | H97: RESIDENCIAL
A98: 85 | B98: ALFREDO ÁVILA | C98: 2 | D98: 0 | E98: 0 | F98: 001/0072/A | G98: OCUPADO | H98: RESIDENCIAL | J98: JANAINA MARIA DOS SANTOS
A99: 86 | B99: ALFREDO ÁVILA | C99: 2 | D99: 0 | E99: 0 | F99: 001/0073/A | G99: OCUPADO | H99: NÃO RESIDENCIAL | J99: MARIA DOS SANTOS
A100: 87 | B100: ALFREDO ÁVILA | C100: 2 | D100: 0 | E100: 0 | F100: 001/0073/B | G100: OCUPADO | H100: RESIDENCIAL | J100: MARIA DOS SANTOS
A101: 88 | B101: ALFREDO ÁVILA | C101: 2 | D101: 0 | E101: 0 | F101: 001/0073/C | G101: OCUPADO | H101: RESIDENCIAL | J101: CLAUDIANE DOS SANTOS PEREIRA
A102: 89 | B102: ALFREDO ÁVILA | C102: 2 | D102: 0 | E102: 0 | F102: 001/0074/A | G102: OCUPADO | H102: RESIDENCIAL | J102: ADRIELE PEREIRA DO SANTOS
A103: 90 | B103: ALFREDO ÁVILA | C103: 2 | D103: 0 | E103: 0 | F103: 001/0075/A | G103: OCUPADO | H103: RESIDENCIAL | J103: ERICK NASCIMENTO LOPES
...
