Workbook
Name Adequacao_Imovel: 'Listas (não utilizar)'!$G$2:$G$7
Name ADEQUAR: 'Listas (não utilizar)'!$G$2:$G$7
Name Apartamento: 'Listas (não utilizar)'!$D$2:$D$21
Name APROVCEF: #REF!
Name Área: 'Listas (não utilizar)'!$A$2:$A$28
Name AREAS: #REF!
Name AVILDATA: #REF!
Name AVILDATA1: #REF!
Name BARCDATA: #REF!
Name BILBDATA: #REF!
Name Bloco: 'Listas (não utilizar)'!$C$2:$C$16
Name CEF: #REF!
Name CEUTDATA: #REF!
Name Condomínio: 'Listas (não utilizar)'!$B$2:$B$15
Name INDDEMAND: #REF!
Name INDEMAND: #REF!
Name it: #REF!
Name Pendência: 'Listas (não utilizar)'!$I$2:$I$7
Name PLANCCO: #REF!
Name Renúncia: 'Listas (não utilizar)'!$H$2:$H$6
Name RetornoSMADS: '[1]Listas (não utilizar)'!$E$2:$E$3
Name selogo: #REF!
Name selomv: #REF!
Name selos_go: #REF!
Name selosgo: #REF!
Name selosgo1: #REF!
Name SITAH_CAIXA: 'Listas (não utilizar)'!$E$2:$E$9
Name StatusCAIXA: 'Listas (não utilizar)'!$F$2:$F$5
Name TEPROC: #REF!
Name TEPROC1: #REF!

Sheet PRIORIDADES
C3: 2 | D3: PRIORITÁRIO | G3: OCUPADO | H3: RESIDENCIAL | I3: PROPRIETÁRIO NÃO RESIDENTE | M3: CADASTRADO | N3: INDENIZAÇÃO | P3: SIM | R3: SIM | X3: SAQUE PENDENTE | AE3: PROPRIETÁRIO NÃO RESIDENTE | AI3: SIM | AJ3: SIM | AK3: CADASTRADO | AM3: COMPLETA | AN3: SEM PENDÊNCIAS
C4: 4 | G4: VAZIO | H4: COMERCIAL | I4: PROPRIETÁRIO RESIDENTE | M4: NÃO CADASTRADO | N4: AUXÍLIO ALUGUEL UH | P4: NÃO | R4: NÃO | AE4: PROPRIETÁRIO RESIDENTE | AI4: NÃO | AJ4: NÃO | AK4: NÃO CADASTRADO | AM4: PENDENTE | AN4: FALTA TERMO
G5: OCUPADO/RISCO | H5: MISTO | I5: INQULINO | N5: RECUSA AUXÍLIO ALUGUEL UH | AI5: UH | AJ5: N/A | AN5: FALTA DOCS
G6: CONSTRUÇÃO | N6: NÃO TEM DIREITO ATENDIMENTO | AI6: ESTUDO DE CASO | AJ6: PENDENTE | AN6: FALTA TERMO E DOCS
G7: DEMOLIDO
G8: DESCARACTERIZADO
G9: DESABADO
AP10: AGUARDANDO
A12: INFORMAÇÕES INICIAIS | P12: INFORMAÇÕES AUXÍLIO ALUGUEL | AB12: INFORMAÇÕES INDENIZAÇÃO | BB12: PROCESSO ATENDIMENTO HABITACIONAL
A13: ORDEM | B13: ÁREA | C13: FASE | D13: TRECHO | E13: PRIORIDADE | F13: SELO | G13: SITUAÇÃO INICIAL IMÓVEL | H13: USO IMÓVEL | I13: SITUAÇÃO DO RESIDENTE | J13: TITULAR | K13: RG | L13: CPF | M13: CADASTRO HABITA SAMPA | N13: OPÇÃO DE ATENDIMENTO HABITACIONAL | O13: ENVIO DADOS | P13: SOLICITAÇÃO AUXÍLIO ALUGUEL ÁREA | Q13: No PROCESSO SEI (AUXÍLIO ALUGUEL) | R13: ANÁLISE DTS CADASTRO + CHECAGEM DUPLO | S13: INSTRUÇÃO PROCESSO SEI DTS | T13: ANÁLISE CTS ASSINATURA GABINETE | U13: DATA PUBLICAÇÃO DIÁRIO OFICIAL | V13: CONFECÇÃO TERMO | W13: ENVIO TERMO CARTÃO | X13: PREVISÃO PAGAMENTO | Y13: DATA SAQUE | Z13: DATA MUDANÇA | AA13: OBSERVAÇÕES AA | AB13: PROPRIETÁRIO | AC13: RG | AD13: CPF | AE13: SITUAÇÃO DO PROPRIETÁRIO | AF13: CADASTRO HABITASAMPA | AG13: VALOR AVALIAÇÃO | AH13: VALOR INDENIZAÇÃO | AI13: ACEITA VALOR INDENIZAÇÃO | AJ13: Nº SEI LAUDOS AVALIAÇÃO | AK13: Nº DOCUMENTO LAUDO | AL13: TERMO INDENIZAÇÃO | AM13: DOSSIÊ | AN13: PENDÊNCIA | AO13: OBSERVAÇÕES INDENIZAÇÃO | AP13: No PROCESSO SEI (INDENIZAÇÃO) | AQ13: INSTRUÇÃO PROCESSO SEI DTS | AR13: ASSINATURA DIRETOR DTS | AS13: ELABORAÇÃO DESPACHO CTS | AT13: ASSINATURA DESPACHO GABINETE | AU13: PUBLICAÇÃO DIÁRIO OFICIAL | AV13: ENCAMINHAMENTO DAF/DIF CTS | AW13: LIBERAÇÃO PAGAMENTO DAF/DIF | AX13: PREVISÃO PAGAMENTO | AY13: DATA PAGAMENTO | AZ13: DATA ENTREGA IMÓVEL | BA13: SITUAÇÃO ATUAL IMÓVEL | BB13: STATUS | BC13: DIAS TOTAIS | BD13: OPÇÃO ATENDIMENTO | BE13: NECESSITA BLOQUEIO AA | BF13: SOLICITAÇÃO BLOQUEIO AA DTS | BG13: SOLICITAÇÃO BLOQUEIO AA | BH13: DATA BLOQUEIO AA | BI13: DESPACHO EXCLUSÃO GABINETE | BJ13: ASSINATURA DESPACHO GABINETE | BK13: PUBLICAÇÃO DOC | BL13: ENCAMINHAMENTO SOLICITAÇÃO EXCLUSÃO DEPLAN | BM13: ENCERRAMENTO PROCESSO DTS
A14: 1 | B14: JD. VITÓRIA | C14: FASE 1 - CÓRREGO | D14: -- | E14: -- | F14: 002/0001/A | G14: OCUPADO | H14: CONSTRUÇÃO | I14: PROPRIETARIO NÃO RESIDENTE | J14: - | K14: - | L14: - | M14: NÃO | AJ14: 6014.2024/0006500-4 | BC14: =IF(AY14-KG14=0,"",AY14-O14) | BD14: =IF(AND(AI14<>"SIM",AI14="UH"),"AA","INDENIZAÇÃO") -> INDENIZAÇÃO | BE14: =IF(AND(AY14<>"AGUARDANDO",AY14<>"",N14="AUXÍLIO ALUGUEL ATÉ INDENIZAÇÃO"),"SIM","NÃO") -> NÃO
A15: 2 | B15: JD. VITÓRIA | C15: FASE 1 - CÓRREGO | D15: -- | E15: -- | F15: 002/0002/A | G15: OCUPADO | H15: COMERCIAL | I15: PROPRIETÁRIO RESIDENTE | J15: ELIAS FERREIRA DE SOUSA | K15: 39.826.994-4 | L15: 530.102.098-60 | M15: CONCLUÍDO | N15: INDENIZAÇÃO | O15: 45859 | P15: N/A | Q15: NA | R15: NA | S15: NA | T15: NA | U15: NA | V15: NA | W15: NA | X15: NA | Y15: NA | Z15: NA | AB15: ELIAS FERREIRA DE SOUSA | AC15: 39.826.994-4 | AD15: 530.102.098-60 | AE15: PROPRIETÁRIO RESIDENTE | AF15: CONCLUÍDO | AG15: 14192.93 | AH15: =AG15+30000 -> 44192.93 | AI15: SIM | AJ15: 6014.2024/0006500-4 | AK15: 125243277 | AL15: FINALIZADO | AM15: FINALIZADO | AN15: SEM PENDÊNCIA | AP15: 6014.2025/0004924-8 | AQ15: FINALIZADO | AR15: FINALIZADO | AS15: FINALIZADO | AT15: FINALIZADO | AU15: 45978 | AV15: FINALIZADO | AW15: FINALIZADO | AX15: 45985 | AY15: 45985 | AZ15: 46029 | BA15: LIBERADO DEMOLIÇÃO | BB15: FINALIZADO | BC15: =IF(AY15-KG15=0,"",AY15-O15) -> 126 | BD15: =IF(AND(AI15<>"SIM",AI15="UH"),"AA","INDENIZAÇÃO") -> INDENIZAÇÃO | BE15: =IF(AND(AY15<>"AGUARDANDO",AY15<>"",N15="AUXÍLIO ALUGUEL ATÉ INDENIZAÇÃO"),"SIM","NÃO") -> NÃO | BF15: N/A | BG15: N/A | BH15: N/A | BI15: FINALIZADO | BJ15: FINALIZADO | BK15: 46112 | BL15: FINALIZADO | BM15: AGUARDANDO
A16: 3 | B16: JD. VITÓRIA | C16: FASE 2 - RISCO E URBANIZAÇÃO | D16: -- | E16: -- | F16: 007/0057/A | G16: OCUPADO | H16: RESIDENCIAL | I16: PROPRIETÁRIO RESIDENTE | J16: CLAUDETE DOS SANTOS BONFIM | K16: 38.849.113-9 | L16: 308.753.998-86 | N16: INDENIZAÇÃO | O16: 46161 | P16: N/A | Q16: N/A | R16: N/A | S16: N/A | T16: N/A | U16: N/A | V16: N/A | W16: N/A | X16: N/A | Y16: N/A | Z16: N/A | AB16: CLAUDETE DOS SANTOS BONFIM | AC16: 38.849.113-9 | AD16: 308.753.998-86 | AE16: PROPRIETÁRIO RESIDENTE | AF16: CONCLUÍDO | AG16: 66944.06 | AH16: 66944.06 | AI16: SIM | AJ16: 6014.2024/0006500-4 | AK16: 150716185 | AL16: FINALIZADO | AM16: FINALIZADO | AN16: SEM PENDÊNCIA | AP16: 6014.2026/0004264-4 | AQ16: FINALIZADO | AR16: FINALIZADO | AS16: FINALIZADO | AT16: FINALIZADO | AU16: 46226 | AV16: FINALIZADO | AW16: FINALIZADO | AX16: 46233 | AY16: 46233 | AZ16: AGUARDANDO | BA16: LIBERADO DEMOLIÇÃO | BB16: FINALIZADO | BC16: =IF(AY16-KG16=0,"",AY16-O16) -> 72 | BD16: =IF(AND(AI16<>"SIM",AI16="UH"),"AA","INDENIZAÇÃO") -> INDENIZAÇÃO | BE16: =IF(AND(AY16<>"AGUARDANDO",AY16<>"",N16="AUXÍLIO ALUGUEL ATÉ INDENIZAÇÃO"),"SIM","NÃO") -> NÃO | BF16: N/A | BG16: N/A | BH16: N/A | BI16: AGUARDANDO ELABORAÇÃO
A17: 4 | B17: JD. VITÓRIA | C17: FASE 1 - CÓRREGO | D17: -- | E17: -- | F17: 002/0013/A | G17: OCUPADO | H17: RESIDENCIAL | I17: PROPRIETÁRIO RESIDENTE | J17: ANDRESSA RAQUEL FERNANDES DA COSTA | K17: 49.597.936-3 | L17: 398.166.698-46 | M17: CONCLUÍDO | N17: AUXILIO ALUGUEL UH | O17: 45726 | P17: 03-abr-25 | Q17: 6014.2024/0005020-1 | R17: 45728 | S17: 45750 | AJ17: 6014.2024/0006500-4 | BC17: =IF(AY17-KG17=0,"",AY17-O17) | BD17: =IF(AND(AI17<>"SIM",AI17="UH"),"AA","INDENIZAÇÃO") -> INDENIZAÇÃO | BE17: =IF(AND(AY17<>"AGUARDANDO",AY17<>"",N17="AUXÍLIO ALUGUEL ATÉ INDENIZAÇÃO"),"SIM","NÃO") -> NÃO
A18: 5 | B18: JD. VITÓRIA | C18: FASE 1 - CÓRREGO | D18: -- | E18: -- | F18: 002/0025/A | G18: OCUPADO | H18: RESIDENCIAL | I18: PROPRIETÁRIO RESIDENTE | J18: JOSÉ CARLOS LIMA DOS SANTOS | K18: 229681578 | L18: 16310451804 | AJ18: 6014.2024/0006500-4 | BC18: =IF(AY18-KG18=0,"",AY18-O18) | BD18: =IF(AND(AI18<>"SIM",AI18="UH"),"AA","INDENIZAÇÃO") -> INDENIZAÇÃO | BE18: =IF(AND(AY18<>"AGUARDANDO",AY18<>"",N18="AUXÍLIO ALUGUEL ATÉ INDENIZAÇÃO"),"SIM","NÃO") -> NÃO
A19: 6 | B19: JD. VITÓRIA | C19: FASE 1 - CÓRREGO | D19: -- | E19: -- | F19: 002/0028/B | G19: OCUPADO | H19: RESIDENCIAL | I19: PROPRIETÁRIO RESIDENTE | J19: MARIA IVANETE FERNANDES DE SOUZA | K19: 27.928.247-3 | L19: 814.354.284-04 | AJ19: 6014.2024/0006500-4 | BC19: =IF(AY19-KG19=0,"",AY19-O19) | BD19: =IF(AND(AI19<>"SIM",AI19="UH"),"AA","INDENIZAÇÃO") -> INDENIZAÇÃO | BE19: =IF(AND(AY19<>"AGUARDANDO",AY19<>"",N19="AUXÍLIO ALUGUEL ATÉ INDENIZAÇÃO"),"SIM","NÃO") -> NÃO
A20: 7 | B20: JD. VITÓRIA | C20: FASE 1 - CÓRREGO | D20: -- | E20: -- | F20: 002/0029/A | G20: OCUPADO | H20: RESIDENCIAL | I20: PROPRIETÁRIO RESIDENTE | J20: SIMONE DE SOUSA RODRIGUES | K20: 57.540.706-2 | L20: 352.449.708-01 | AJ20: 6014.2024/0006500-4 | BC20: =IF(AY20-KG20=0,"",AY20-O20) | BD20: =IF(AND(AI20<>"SIM",AI20="UH"),"AA","INDENIZAÇÃO") -> INDENIZAÇÃO | BE20: =IF(AND(AY20<>"AGUARDANDO",AY20<>"",N20="AUXÍLIO ALUGUEL ATÉ INDENIZAÇÃO"),"SIM","NÃO") -> NÃO
A21: 8 | B21: JD. VITÓRIA | C21: FASE 1 - CÓRREGO | D21: -- | E21: -- | F21: 002/0039/B | G21: OCUPADO | H21: RESIDENCIAL | I21: PROPRIETÁRIO RESIDENTE | J21: CRISTINA DA CONSOLAÇÃO ASSIS | K21: 35.880.213-1 | L21: 225.601.888-14 | AJ21: 6014.2024/0006500-4 | BC21: =IF(AY21-KG21=0,"",AY21-O21) | BD21: =IF(AND(AI21<>"SIM",AI21="UH"),"AA","INDENIZAÇÃO") -> INDENIZAÇÃO | BE21: =IF(AND(AY21<>"AGUARDANDO",AY21<>"",N21="AUXÍLIO ALUGUEL ATÉ INDENIZAÇÃO"),"SIM","NÃO") -> NÃO
A22: 9 | B22: JD. VITÓRIA | C22: FASE 1 - CÓRREGO | D22: -- | E22: -- | F22: 002/0052/B | G22: OCUPADO | H22: RESIDENCIAL | I22: PROPRIETÁRIO RESIDENTE | J22: MARIANA SANTOS RAMOS DA SILVA MIRAVETE | K22: 52.955.950-X | L22: 457.182.918-37 | M22: CONCLUÍDO | N22: INDENIZAÇÃO | O22: 45838 | P22: N/A | Q22: N/A | R22: N/A | S22: N/A | T22: N/A | U22: N/A | V22: N/A | W22: N/A | X22: N/A | Y22: N/A | Z22: N/A | AB22: MARIANA SANTOS RAMOS DA SILVA MIRAVETE | AC22: 52.955.950-X | AD22: 457.182.918-37 | AE22: PROPRIETÁRIO RESIDENTE | AF22: CONCLUÍDO | AG22: 35088.83 | AH22: 60000 | AI22: SIM | AJ22: 6014.2024/0006500-4 | AK22: 123202718 | AL22: FINALIZADO | AM22: FINALIZADO | AN22: SEM PENDÊNCIA | AP22: 6014.2025/0004708-3 | AQ22: FINALIZADO | AR22: FINALIZADO | AS22: FINALIZADO | AT22: FINALIZADO | AU22: 45909 | AV22: FINALIZADO | AW22: FINALIZADO | AX22: 45915 | AY22: 45915 | AZ22: 45957 | BA22: LIBERADO DEMOLIÇÃO | BB22: FINALIZADO | BC22: =IF(AY22-KG22=0,"",AY22-O22) -> 77 | BD22: =IF(AND(AI22<>"SIM",AI22="UH"),"AA","INDENIZAÇÃO") -> INDENIZAÇÃO | BE22: =IF(AND(AY22<>"AGUARDANDO",AY22<>"",N22="AUXÍLIO ALUGUEL ATÉ INDENIZAÇÃO"),"SIM","NÃO") -> NÃO | BF22: N/A | BG22: N/A | BH22: N/A | BI22: FINALIZADO | BJ22: FINALIZADO | BK22: 45937 | BL22: FINALIZADO | BM22: AGUARDANDO
A23: 10 | B23: JD. VITÓRIA | C23: FASE 1 - CÓRREGO | D23: -- | E23: -- | F23: 002/0053/A | G23: OCUPADO | H23: RESIDENCIAL | I23: PROPRIETÁRIO RESIDENTE | J23: GEOVANE SOUZA SANTOS | K23: 37.985.888-5 | L23: 429.418.998-39 | M23: CONCLUÍDO | N23: INDENIZAÇÃO | O23: 45954 | P23: N/A | Q23: N/A | R23: N/A | S23: N/A | T23: N/A | U23: N/A | V23: N/A | W23: N/A | X23: N/A | Y23: N/A | Z23: N/A | AB23: GEOVANE SOUZA SANTOS | AC23: 37.985.888-5 | AD23: 429.418.998-39 | AE23: PROPRIETÁRIO RESIDENTE | AF23: CONCLUÍDO | AG23: 121242.56 | AH23: 121242.56 | AI23: SIM | AJ23: 6014.2024/0006500-4 | AK23: 128252519 | AL23: FINALIZADO | AM23: FINALIZADO | AN23: SEM PENDÊNCIA | AP23: 6014.2025/0008040-4 | AQ23: FINALIZADO | AR23: FINALIZADO | AS23: FINALIZADO | AT23: FINALIZADO | AU23: 46024 | AV23: FINALIZADO | AW23: FINALIZADO | AX23: 46038 | AY23: 46038 | AZ23: 46085 | BA23: LIBERADO DEMOLIÇÃO | BB23: FINALIZADO | BC23: =IF(AY23-KG23=0,"",AY23-O23) -> 84 | BD23: =IF(AND(AI23<>"SIM",AI23="UH"),"AA","INDENIZAÇÃO") -> INDENIZAÇÃO | BE23: =IF(AND(AY23<>"AGUARDANDO",AY23<>"",N23="AUXÍLIO ALUGUEL ATÉ INDENIZAÇÃO"),"SIM","NÃO") -> NÃO | BF23: N/A | BG23: N/A | BH23: N/A | BI23: FINALIZADO | BJ23: FINALIZADO | BK23: 46112 | BL23: FINALIZADO | BM23: AGUARDANDO
A24: 11 | B24: JD. VITÓRIA | C24: FASE 1 - CÓRREGO | D24: -- | E24: -- | F24: 003/0001/A | G24: OCUPADO | H24: INSTITUCIONAL | I24: NA | J24: - | K24: - | L24: - | M24: NÃO | AJ24: 6014.2024/0006500-4 | BC24: =IF(AY24-KG24=0,"",AY24-O24) | BD24: =IF(AND(AI24<>"SIM",AI24="UH"),"AA","INDENIZAÇÃO") -> INDENIZAÇÃO | BE24: =IF(AND(AY24<>"AGUARDANDO",AY24<>"",N24="AUXÍLIO ALUGUEL ATÉ INDENIZAÇÃO"),"SIM","NÃO") -> NÃO
A25: 12 | B25: JD. VITÓRIA | C25: FASE 1 - CÓRREGO | D25: -- | E25: -- | F25: 003/0013/A | G25: OCUPADO | H25: RESIDENCIAL | I25: PROPRIETÁRIO RESIDENTE | J25: ANGELA NETTO | K25: 34164013 | L25: 312.549.168.14 | M25: NÃO | AJ25: 6014.2024/0006500-4 | BC25: =IF(AY25-KG25=0,"",AY25-O25) | BD25: =IF(AND(AI25<>"SIM",AI25="UH"),"AA","INDENIZAÇÃO") -> INDENIZAÇÃO | BE25: =IF(AND(AY25<>"AGUARDANDO",AY25<>"",N25="AUXÍLIO ALUGUEL ATÉ INDENIZAÇÃO"),"SIM","NÃO") -> NÃO
A26: 13 | B26: JD. VITÓRIA | C26: FASE 1 - CÓRREGO | D26: -- | E26: -- | F26: 003/0014/A | G26: OCUPADO | H26: RESIDENCIAL | I26: PROPRIETÁRIO RESIDENTE | J26: LAURINDA SILVA DO NASCIMENTO | K26: 331023 | L26: 336.719.233-34 | M26: CONCLUÍDO | N26: INDENIZAÇÃO | O26: 46161 | P26: N/A | Q26: N/A | R26: N/A | S26: N/A | T26: N/A | U26: N/A | V26: N/A | W26: N/A | X26: N/A | Y26: N/A | Z26: N/A | AB26: LAURINDA SILVA DO NASCIMENTO | AC26: 331023 | AD26: 336.719.233-34 | AE26: PROPRIETÁRIO RESIDENTE | AF26: CONCLUÍDO | AG26: 30923.52 | AH26: 60000 | AI26: SIM | AJ26: 6014.2024/0006500-4 | AK26: 149303607 | AL26: FINALIZADO | AM26: FINALIZADO | AN26: SEM PENDÊNCIA | AP26: 6014.2026/0004251-2 | AQ26: FINALIZADO | AR26: FINALIZADO | AS26: FINALIZADO | AT26: FINALIZADO | AU26: 46226 | AV26: FINALIZADO | AW26: FINALIZADO | AX26: 46233 | AY26: 46233 | AZ26: AGUARDANDO | BA26: LIBERADO DEMOLIÇÃO | BB26: FINALIZADO | BC26: =IF(AY26-KG26=0,"",AY26-O26) -> 72 | BD26: =IF(AND(AI26<>"SIM",AI26="UH"),"AA","INDENIZAÇÃO") -> INDENIZAÇÃO | BE26: =IF(AND(AY26<>"AGUARDANDO",AY26<>"",N26="AUXÍLIO ALUGUEL ATÉ INDENIZAÇÃO"),"SIM","NÃO") -> NÃO | BF26: N/A | BG26: N/A | BH26: N/A | BI26: AGUARDANDO ELABORAÇÃO
A27: 14 | B27: JD. VITÓRIA | C27: FASE 1 - CÓRREGO | D27: -- | E27: -- | F27: 003/0015/A | G27: OCUPADO | H27: RESIDENCIAL | I27: PROPRIETÁRIO RESIDENTE | J27: ALEXANDRE NETTO | K27: 284659812 | L27: 19342655866 | M27: NÃO | AJ27: 6014.2024/0006500-4 | BC27: =IF(AY27-KG27=0,"",AY27-O27) | BD27: =IF(AND(AI27<>"SIM",AI27="UH"),"AA","INDENIZAÇÃO") -> INDENIZAÇÃO | BE27: =IF(AND(AY27<>"AGUARDANDO",AY27<>"",N27="AUXÍLIO ALUGUEL ATÉ INDENIZAÇÃO"),"SIM","NÃO") -> NÃO
A28: 15 | B28: JD. VITÓRIA | C28: FASE 1 - CÓRREGO | D28: -- | E28: -- | F28: 003/0016/A | G28: OCUPADO | H28: RESIDENCIAL | I28: PROPRIETÁRIO RESIDENTE | J28: ANA LÚCIA RODRIGUES CAVALCANTE | K28: 390508299 | L28: 17016043886 | M28: NÃO | AJ28: 6014.2024/0006500-4 | BC28: =IF(AY28-KG28=0,"",AY28-O28) | BD28: =IF(AND(AI28<>"SIM",AI28="UH"),"AA","INDENIZAÇÃO") -> INDENIZAÇÃO | BE28: =IF(AND(AY28<>"AGUARDANDO",AY28<>"",N28="AUXÍLIO ALUGUEL ATÉ INDENIZAÇÃO"),"SIM","NÃO") -> NÃO
A29: 16 | B29: JD. VITÓRIA | C29: FASE 1 - CÓRREGO | D29: -- | E29: -- | F29: 003/0017/A | G29: OCUPADO | H29: RESIDENCIAL | I29: PROPRIETÁRIO RESIDENTE | J29: VERA LUCIA DA SILVA ROCHA | K29: 383588790 | L29: 352.816.568.56 | M29: CONCLUÍDO | N29: AUXILIO ALUGUEL UH | O29: 45726 | P29: 03-ABR-25 | Q29: 6014.2024/0005020-1 | R29: 45744 | S29: 45750 | AJ29: 6014.2024/0006500-4 | BC29: =IF(AY29-KG29=0,"",AY29-O29) | BD29: =IF(AND(AI29<>"SIM",AI29="UH"),"AA","INDENIZAÇÃO") -> INDENIZAÇÃO | BE29: =IF(AND(AY29<>"AGUARDANDO",AY29<>"",N29="AUXÍLIO ALUGUEL ATÉ INDENIZAÇÃO"),"SIM","NÃO") -> NÃO
A30: 17 | B30: JD. VITÓRIA | C30: FASE 2 - RISCO E URBANIZAÇÃO | D30: -- | E30: -- | F30: 003/0018/A | G30: OCUPADO | H30: RESIDENCIAL | I30: PROPRIETÁRIO RESIDENTE | J30: FRANCISCO EUGÊNIO | M30: NÃO | AJ30: 6014.2024/0006500-4 | BC30: =IF(AY30-KG30=0,"",AY30-O30) | BD30: =IF(AND(AI30<>"SIM",AI30="UH"),"AA","INDENIZAÇÃO") -> INDENIZAÇÃO | BE30: =IF(AND(AY30<>"AGUARDANDO",AY30<>"",N30="AUXÍLIO ALUGUEL ATÉ INDENIZAÇÃO"),"SIM","NÃO") -> NÃO
A31: 18 | B31: JD. VITÓRIA | C31: FASE 2 - RISCO E URBANIZAÇÃO | D31: -- | E31: -- | F31: 003/0019/A | G31: OCUPADO | H31: RESIDENCIAL | I31: PROPRIETÁRIO RESIDENTE | J31: STEFANIE FERNANDES ORTEGA | K31: 572846733 | L31: 46653357880 | M31: NÃO | AJ31: 6014.2024/0006500-4 | BC31: =IF(AY31-KG31=0,"",AY31-O31) | BD31: =IF(AND(AI31<>"SIM",AI31="UH"),"AA","INDENIZAÇÃO") -> INDENIZAÇÃO | BE31: =IF(AND(AY31<>"AGUARDANDO",AY31<>"",N31="AUXÍLIO ALUGUEL ATÉ INDENIZAÇÃO"),"SIM","NÃO") -> NÃO
A32: 19 | B32: JD. VITÓRIA | C32: FASE 2 - RISCO E URBANIZAÇÃO | D32: -- | E32: -- | F32: 003/0021/A | G32: OCUPADO | H32: OUTROS | I32: NA | J32: - | K32: - | L32: - | M32: NÃO | AJ32: 6014.2024/0006500-4 | BC32: =IF(AY32-KG32=0,"",AY32-O32) | BD32: =IF(AND(AI32<>"SIM",AI32="UH"),"AA","INDENIZAÇÃO") -> INDENIZAÇÃO | BE32: =IF(AND(AY32<>"AGUARDANDO",AY32<>"",N32="AUXÍLIO ALUGUEL ATÉ INDENIZAÇÃO"),"SIM","NÃO") -> NÃO
A33: 20 | B33: JD. VITÓRIA | C33: FASE 1 - CÓRREGO | D33: -- | E33: -- | F33: 004/0001/A | G33: OCUPADO | H33: RESIDENCIAL | I33: PROPRIETÁRIO RESIDENTE | J33: ADRIANA DIAS NARRERO | K33: 229657904 | L33: 130.085.138.40 | AJ33: 6014.2024/0006500-4 | BC33: =IF(AY33-KG33=0,"",AY33-O33) | BD33: =IF(AND(AI33<>"SIM",AI33="UH"),"AA","INDENIZAÇÃO") -> INDENIZAÇÃO | BE33: =IF(AND(AY33<>"AGUARDANDO",AY33<>"",N33="AUXÍLIO ALUGUEL ATÉ INDENIZAÇÃO"),"SIM","NÃO") -> NÃO
A34: 21 | B34: JD. VITÓRIA | C34: FASE 1 - CÓRREGO | D34: -- | E34: -- | F34: 004/0008/A | G34: OCUPADO | H34: RESIDENCIAL | I34: PROPRIETÁRIO RESIDENTE | J34: EMILIO DE ALMEIDA SANTOS | K34: 25.164.457-1 | L34: 146.239.288-10 | M34: CONCLUÍDO | N34: INDENIZAÇÃO | O34: 46097 | P34: N/A | Q34: N/A | R34: N/A | S34: N/A | T34: N/A | U34: N/A | V34: N/A | W34: N/A | X34: N/A | Y34: N/A | Z34: N/A | AB34: EMILIO DE ALMEIDA SANTOS | AC34: 25.164.457-1 | AD34: 146.239.288-10 | AE34: PROPRIETÁRIO RESIDENTE | AF34: CONCLUÍDO | AG34: 92014.59 | AH34: 92014.59 | AI34: SIM | AJ34: 6014.2024/0006500-4 | AK34: 152010700 | AL34: FINALIZADO | AM34: FINALIZADO | AN34: SEM PENDÊNCIA | AP34: 6014.2026/0001191-9 | AQ34: FINALIZADO | AR34: FINALIZADO | AS34: FINALIZADO | AT34: FINALIZADO | AU34: 46174 | AV34: FINALIZADO | AW34: FINALIZADO | AX34: 46182 | AY34: 46182 | AZ34: AGUARDANDO | BA34: LIBERADO DEMOLIÇÃO | BB34: FINALIZADO | BC34: =IF(AY34-KG34=0,"",AY34-O34) -> 85 | BD34: =IF(AND(AI34<>"SIM",AI34="UH"),"AA","INDENIZAÇÃO") -> INDENIZAÇÃO | BE34: =IF(AND(AY34<>"AGUARDANDO",AY34<>"",N34="AUXÍLIO ALUGUEL ATÉ INDENIZAÇÃO"),"SIM","NÃO") -> NÃO | BF34: N/A | BG34: N/A | BH34: N/A | BI34: FINALIZADO | BJ34: FINALIZADO | BK34: 46224 | BL34: AGUARDANDO PUBLICAÇÃO DOC
A35: 22 | B35: JD. VITÓRIA | C35: FASE 1 - CÓRREGO | D35: -- | E35: -- | F35: 004/0010/A | G35: OCUPADO | H35: RESIDENCIAL | I35: PROPRIETÁRIO RESIDENTE | J35: ARLETE ALMEIDA SANTOS | K35: 44.022.838-4 | L35: 347.356.388-90 | M35: CONCLUÍDO | N35: INDENIZAÇÃO | O35: 45999 | P35: N/A | Q35: N/A | R35: N/A | S35: N/A | T35: N/A | U35: N/A | V35: N/A | W35: N/A | X35: N/A | Y35: N/A | Z35: N/A | AB35: ARLETE ALMEIDA SANTOS | AC35: 44.022.838-4 | AD35: 347.356.388-90 | AE35: PROPRIETÁRIO RESIDENTE | AF35: CONCLUÍDO | AG35: 47925.28 | AH35: 60000 | AI35: SIM | AJ35: 6014.2024/0006500-4 | AK35: 125262584 | AL35: FINALIZADO | AM35: FINALIZADO | AN35: SEM PENDÊNCIA | AP35: 6014.2025/0008120-6 | AQ35: FINALIZADO | AR35: FINALIZADO | AS35: FINALIZADO | AT35: FINALIZADO | AU35: 46071 | AV35: FINALIZADO | AW35: FINALIZADO | AX35: 46087 | AY35: 46087 | AZ35: AGUARDANDO | BA35: LIBERADO DEMOLIÇÃO | BB35: FINALIZADO | BC35: =IF(AY35-KG35=0,"",AY35-O35) -> 88 | BD35: =IF(AND(AI35<>"SIM",AI35="UH"),"AA","INDENIZAÇÃO") -> INDENIZAÇÃO | BE35: =IF(AND(AY35<>"AGUARDANDO",AY35<>"",N35="AUXÍLIO ALUGUEL ATÉ INDENIZAÇÃO"),"SIM","NÃO") -> NÃO | BF35: N/A | BG35: N/A | BH35: N/A | BI35: FINALIZADO | BJ35: FINALIZADO | BK35: 46139 | BL35: AGUARDANDO PUBLICAÇÃO DOC
A36: 23 | B36: JD. VITÓRIA | C36: FASE 2 - RISCO E URBANIZAÇÃO | D36: -- | E36: -- | F36: 007/0041/A | G36: OCUPADO | H36: RESIDENCIAL | I36: PROPRIETÁRIO RESIDENTE | J36: REINALDO MOREIRA SILVA | K36: 23.098.114-32 | L36: 702.612.337-72 | M36: CONCLUÍDO | N36: INDENIZAÇÃO | O36: 45999 | P36: N/A | Q36: N/A | R36: N/A | S36: N/A | T36: N/A | U36: N/A | V36: N/A | W36: N/A | X36: N/A | Y36: N/A | Z36: N/A | AB36: REINALDO MOREIRA SILVA | AC36: 23.098.114-32 | AD36: 702.612.337-72 | AE36: PROPRIETÁRIO RESIDENTE | AF36: CONCLUÍDO | AG36: 20411.84 | AH36: =AG36+30000 -> 50411.84 | AI36: SIM | AJ36: 6014.2024/0006500-4 | AK36: 130899556 | AL36: FINALIZADO | AM36: FINALIZADO | AN36: SEM PENDÊNCIA | AP36: 6014.2025/0008179-6 | AQ36: FINALIZADO | AR36: FINALIZADO | AS36: FINALIZADO | AT36: FINALIZADO | AU36: 46024 | AV36: FINALIZADO | AW36: FINALIZADO | AX36: 46038 | AY36: 46038 | AZ36: 46085 | BA36: LIBERADO DEMOLIÇÃO | BB36: FINALIZADO | BC36: =IF(AY36-KG36=0,"",AY36-O36) -> 39 | BD36: =IF(AND(AI36<>"SIM",AI36="UH"),"AA","INDENIZAÇÃO") -> INDENIZAÇÃO | BE36: =IF(AND(AY36<>"AGUARDANDO",AY36<>"",N36="AUXÍLIO ALUGUEL ATÉ INDENIZAÇÃO"),"SIM","NÃO") -> NÃO | BF36: N/A | BG36: N/A | BH36: N/A | BI36: FINALIZADO | BJ36: FINALIZADO | BK36: 46112 | BL36: FINALIZADO | BM36: AGUARDANDO
A37: 24 | B37: JD. VITÓRIA | C37: FASE 2 - RISCO E URBANIZAÇÃO | D37: -- | E37: -- | F37: 007/0047/A | G37: OCUPADO | H37: RESIDENCIAL | I37: PROPRIETÁRIO RESIDENTE | J37: CRISTIANE BISPO DOS SANTOS | K37: 34.628.281-0 | L37: 306.344.508-83 | M37: CONCLUÍDO | N37: INDENIZAÇÃO | O37: 46097 | P37: N/A | Q37: N/A | R37: N/A | S37: N/A | T37: N/A | U37: N/A | V37: N/A | W37: N/A | X37: N/A | Y37: N/A | Z37: N/A | AB37: CRISTIANE BISPO DOS SANTOS | AC37: 34.628.281-0 | AD37: 306.344.508-83 | AE37: PROPRIETÁRIO RESIDENTE | AF37: CONCLUÍDO | AG37: 12575.25 | AH37: 42575.25 | AI37: SIM | AJ37: 6014.2024/0006500-4 | AK37: 141878559 | AL37: FINALIZADO | AM37: FINALIZADO | AN37: SEM PENDÊNCIA | AP37: 6014.2026/0002500-6 | AQ37: FINALIZADO | AR37: FINALIZADO | AS37: FINALIZADO | AT37: FINALIZADO | AU37: 46174 | AV37: FINALIZADO | AW37: FINALIZADO | AX37: 46182 | AY37: 46182 | AZ37: AGUARDANDO | BA37: LIBERADO DEMOLIÇÃO | BB37: FINALIZADO | BC37: =IF(AY37-KG37=0,"",AY37-O37) -> 85 | BD37: =IF(AND(AI37<>"SIM",AI37="UH"),"AA","INDENIZAÇÃO") -> INDENIZAÇÃO | BE37: =IF(AND(AY37<>"AGUARDANDO",AY37<>"",N37="AUXÍLIO ALUGUEL ATÉ INDENIZAÇÃO"),"SIM","NÃO") -> NÃO | BF37: N/A | BG37: N/A | BH37: N/A | BI37: FINALIZADO | BJ37: FINALIZADO | BK37: 46224 | BL37: AGUARDANDO PUBLICAÇÃO DOC
A38: 25 | B38: JD. VITÓRIA | C38: FASE 2 - RISCO E URBANIZAÇÃO | D38: -- | E38: -- | F38: 007/0048/A | G38: OCUPADO | H38: RESIDENCIAL | I38: PROPRIETÁRIO RESIDENTE | J38: GABRIEL CRUZ DE OLIVEIRA | L38: 46115804825 | AJ38: 6014.2024/0006500-4 | BC38: =IF(AY38-KG38=0,"",AY38-O38) | BD38: =IF(AND(AI38<>"SIM",AI38="UH"),"AA","INDENIZAÇÃO") -> INDENIZAÇÃO | BE38: =IF(AND(AY38<>"AGUARDANDO",AY38<>"",N38="AUXÍLIO ALUGUEL ATÉ INDENIZAÇÃO"),"SIM","NÃO") -> NÃO
A39: 26 | B39: JD. VITÓRIA | C39: FASE 2 - RISCO E URBANIZAÇÃO | D39: -- | E39: -- | F39: 007/0049/A | G39: OCUPADO | H39: MISTO | I39: PROPRIETÁRIO RESIDENTE | J39: SIMONE SOUSA GONÇALVES | K39: 234277105 | L39: 142.791.268.09 | AJ39: 6014.2024/0006500-4 | BC39: =IF(AY39-KG39=0,"",AY39-O39) | BD39: =IF(AND(AI39<>"SIM",AI39="UH"),"AA","INDENIZAÇÃO") -> INDENIZAÇÃO | BE39: =IF(AND(AY39<>"AGUARDANDO",AY39<>"",N39="AUXÍLIO ALUGUEL ATÉ INDENIZAÇÃO"),"SIM","NÃO") -> NÃO
A40: 27 | B40: JD. VITÓRIA | C40: FASE 2 - RISCO E URBANIZAÇÃO | D40: -- | E40: -- | F40: 007/0050/A | G40: OCUPADO | H40: RESIDENCIAL | I40: PROPRIETÁRIO RESIDENTE | J40: FRANCISCA ROSEANE DA CONCEIÇÃO OLIVEIRA | AJ40: 6014.2024/0006500-4 | BC40: =IF(AY40-KG40=0,"",AY40-O40) | BD40: =IF(AND(AI40<>"SIM",AI40="UH"),"AA","INDENIZAÇÃO") -> INDENIZAÇÃO | BE40: =IF(AND(AY40<>"AGUARDANDO",AY40<>"",N40="AUXÍLIO ALUGUEL ATÉ INDENIZAÇÃO"),"SIM","NÃO") -> NÃO
A41: 28 | B41: JD. VITÓRIA | C41: FASE 2 - RISCO E URBANIZAÇÃO | D41: -- | E41: -- | F41: 007/0051/A | G41: OCUPADO | H41: RESIDENCIAL | I41: PROPRIETÁRIO RESIDENTE | J41: EDVANIA GOMES DA ROCHA | K41: 47.302.049-x | L41: 369.927.308-35 | M41: CONCLUÍDO | N41: INDENIZAÇÃO | O41: 46077 | P41: N/A | Q41: N/A | R41: N/A | S41: N/A | T41: N/A | U41: N/A | V41: N/A | W41: N/A | X41: N/A | Y41: N/A | Z41: N/A | AB41: EDVANIA GOMES DA ROCHA | AC41: 47.302.049-x | AD41: 369.927.308-35 | AE41: PROPRIETÁRIO RESIDENTE | AF41: CONCLUÍDO | AG41: 39862.27 | AH41: 60000 | AI41: SIM | AJ41: 6014.2024/0006500-4 | AK41: 125233430 | AL41: FINALIZADO | AM41: FINALIZADO | AN41: SEM PENDÊNCIA | AP41: 6014.2026/0000666-4 | AQ41: FINALIZADO | AR41: FINALIZADO | AS41: FINALIZADO | AT41: FINALIZADO | AU41: 46174 | AV41: FINALIZADO | AW41: FINALIZADO | AX41: 46182 | AY41: 46182 | AZ41: AGUARDANDO | BA41: LIBERADO DEMOLIÇÃO | BB41: FINALIZADO | BC41: =IF(AY41-KG41=0,"",AY41-O41) -> 105 | BD41: =IF(AND(AI41<>"SIM",AI41="UH"),"AA","INDENIZAÇÃO") -> INDENIZAÇÃO | BE41: =IF(AND(AY41<>"AGUARDANDO",AY41<>"",N41="AUXÍLIO ALUGUEL ATÉ INDENIZAÇÃO"),"SIM","NÃO") -> NÃO | BF41: N/A | BG41: N/A | BH41: N/A | BI41: FINALIZADO | BJ41: FINALIZADO | BK41: 46224 | BL41: AGUARDANDO PUBLICAÇÃO DOC
A42: 29 | B42: JD. VITÓRIA | C42: FASE 2 - RISCO E URBANIZAÇÃO | D42: -- | E42: -- | F42: 007/0052/A | G42: OCUPADO | H42: RESIDENCIAL | I42: PROPRIETÁRIO RESIDENTE | J42: ADÃO FERNANDES GUIMARÃES | K42: 55.256.402.3 | L42: 266.274.968-79 | M42: CONCLUÍDO | N42: INDENIZAÇÃO | O42: 45999 | P42: N/A | Q42: N/A | R42: N/A | S42: N/A | T42: N/A | U42: N/A | V42: N/A | W42: N/A | X42: N/A | Y42: N/A | Z42: N/A | AB42: ADÃO FERNANDES GUIMARÃES | AC42: 55.256.402.3 | AD42: 266.274.968-79 | AE42: PROPRIETÁRIO RESIDENTE | AF42: CONCLUÍDO | AG42: 39309.12 | AH42: 60000 | AI42: SIM | AJ42: 6014.2024/0006500-4 | AK42: 146194147 | AL42: FINALIZADO | AM42: FINALIZADO | AN42: SEM PENDÊNCIA | AP42: 6014.2025/0008191-5 | AQ42: FINALIZADO | AR42: FINALIZADO | AS42: FINALIZADO | AT42: FINALIZADO | AU42: 46024 | AV42: FINALIZADO | AW42: FINALIZADO | AX42: 45798 | AY42: 46163 | AZ42: AGUARDANDO | BA42: LIBERADO DEMOLIÇÃO | BB42: FINALIZADO | BC42: =IF(AY42-KG42=0,"",AY42-O42) -> 164 | BD42: =IF(AND(AI42<>"SIM",AI42="UH"),"AA","INDENIZAÇÃO") -> INDENIZAÇÃO | BE42: =IF(AND(AY42<>"AGUARDANDO",AY42<>"",N42="AUXÍLIO ALUGUEL ATÉ INDENIZAÇÃO"),"SIM","NÃO") -> NÃO | BF42: N/A | BG42: N/A | BH42: N/A | BI42: FINALIZADO | BJ42: FINALIZADO | BK42: 46224 | BL42: AGUARDANDO PUBLICAÇÃO DOC
A43: 30 | B43: JD. VITÓRIA | C43: FASE 2 - RISCO E URBANIZAÇÃO | D43: -- | E43: -- | F43: 007/0053/A | G43: OCUPADO | H43: RESIDENCIAL | I43: PROPRIETÁRIO RESIDENTE | J43: LEIDIANE DE CARVALHO RODRIGUES | K43: 66.820.449-1 | L43: 038.409.453-80 | M43: CONCLUÍDO | N43: INDENIZAÇÃO | O43: 46073 | P43: N/A | Q43: N/A | R43: N/A | S43: N | T43: N/A | U43: N/A | V43: N/A | W43: N/A | X43: N/A | Y43: N/A | Z43: N/A | AB43: LEIDIANE DE CARVALHO RODRIGUES | AC43: 66.820.449-1 | AD43: 038.409.453-80 | AE43: PROPRIETÁRIO RESIDENTE | AF43: CONCLUÍDO | AG43: 69699.33 | AH43: 69699.33 | AI43: SIM | AJ43: 6014.2024/0006500-4 | AK43: 125286282 | AL43: FINALIZADO | AM43: FINALIZADO | AN43: SEM PENDÊNCIA | AP43: 6014.2026/0002516-2 | AQ43: FINALIZADO | AR43: FINALIZADO | AS43: FINALIZADO | AT43: FINALIZADO | AU43: 46174 | AV43: FINALIZADO | AW43: FINALIZADO | AX43: 46182 | AY43: 46182 | AZ43: AGUARDANDO | BA43: LIBERADO DEMOLIÇÃO | BB43: FINALIZADO | BC43: =IF(AY43-KG43=0,"",AY43-O43) -> 109 | BD43: =IF(AND(AI43<>"SIM",AI43="UH"),"AA","INDENIZAÇÃO") -> INDENIZAÇÃO | BE43: =IF(AND(AY43<>"AGUARDANDO",AY43<>"",N43="AUXÍLIO ALUGUEL ATÉ INDENIZAÇÃO"),"SIM","NÃO") -> NÃO | BF43: N/A | BG43: N/A | BH43: N/A | BI43: FINALIZADO | BJ43: FINALIZADO | BK43: 46224 | BL43: AGUARDANDO PUBLICAÇÃO DOC
A44: 31 | B44: JD. VITÓRIA | C44: FASE 1 - CÓRREGO | D44: -- | E44: -- | F44: 007/0054/A | G44: OCUPADO | H44: RESIDENCIAL | I44: PROPRIETÁRIO RESIDENTE | J44: JOELMA MARQUES DE SOUZA | K44: 44.652.253-3 | L44: 017.418.215-50 | M44: CONCLUÍDO | N44: INDENIZAÇÃO | O44: 45859 | P44: N/A | Q44: N/A | R44: N/A | S44: N/A | T44: N/A | U44: N/A | V44: N/A | W44: N/A | X44: N/A | Y44: N/A | Z44: N/A | AB44: JOELMA MARQUES DE SOUZA | AC44: 44.652.253-3 | AD44: 017.418.215-50 | AE44: PROPRIETÁRIO RESIDENTE | AF44: CONCLUÍDO | AG44: 43918.86 | AH44: 60000 | AI44: SIM | AJ44: 6014.2024/0006500-4 | AK44: 125234025 | AL44: FINALIZADO | AM44: FINALIZADO | AN44: SEM PENDÊNCIA | AO44: CORREÇÃO DTS - VALOR TERMO INCORRETO | AP44: 6014.2025/0005013-0 | AQ44: FINALIZADO | AR44: FINALIZADO | AS44: FINALIZADO | AT44: FINALIZADO | AU44: 45911 | AV44: FINALIZADO | AW44: FINALIZADO | AX44: 45917 | AY44: 45917 | AZ44: 45944 | BA44: LIBERADO DEMOLIÇÃO | BB44: FINALIZADO | BC44: =IF(AY44-KG44=0,"",AY44-O44) -> 58 | BD44: =IF(AND(AI44<>"SIM",AI44="UH"),"AA","INDENIZAÇÃO") -> INDENIZAÇÃO | BE44: =IF(AND(AY44<>"AGUARDANDO",AY44<>"",N44="AUXÍLIO ALUGUEL ATÉ INDENIZAÇÃO"),"SIM","NÃO") -> NÃO | BF44: N/A | BG44: N/A | BH44: N/A | BI44: FINALIZADO | BJ44: FINALIZADO | BK44: 45937 | BL44: FINALIZADO | BM44: AGUARDANDO
A45: 32 | B45: JD. VITÓRIA | C45: FASE 1 - CÓRREGO | D45: -- | E45: -- | F45: 007/0055/A | G45: OCUPADO | H45: RESIDENCIAL | I45: PROPRIETÁRIO RESIDENTE | J45: IVANILDA PEREIRA DE SOUZA | K45: 48.110.940-7 | L45: 346.774.738-89 | M45: CONCLUÍDO | N45: INDENIZAÇÃO | O45: 45859 | P45: N/A | Q45: N/A | R45: N/A | S45: N/A | T45: N/A | U45: N/A | V45: N/A | W45: N/A | X45: N/A | Y45: N/A | Z45: N/A | AB45: IVANILDA PEREIRA DE SOUZA | AC45: 48.110.940-7 | AD45: 346.774.738-89 | AE45: PROPRIETÁRIO RESIDENTE | AF45: CONCLUÍDO | AG45: 22821.56 | AH45: 52821.56 | AI45: SIM | AJ45: 6014.2024/0006500-4 | AK45: 130055018 | AL45: FINALIZADO | AM45: FINALIZADO | AN45: SEM PENDÊNCIA | AO45: CORREÇÃO DTS - NOME TERMO DIVERGENTE LAUDO AVALIAÇÃO | AP45: 6014.2025/0005014-9 | AQ45: FINALIZADO | AR45: FINALIZADO | AS45: FINALIZADO | AT45: FINALIZADO | AU45: 45937 | AV45: FINALIZADO | AW45: FINALIZADO | AX45: 45985 | AY45: 45985 | AZ45: 45993 | BA45: LIBERADO DEMOLIÇÃO | BB45: FINALIZADO | BC45: =IF(AY45-KG45=0,"",AY45-O45) -> 126 | BD45: =IF(AND(AI45<>"SIM",AI45="UH"),"AA","INDENIZAÇÃO") -> INDENIZAÇÃO | BE45: =IF(AND(AY45<>"AGUARDANDO",AY45<>"",N45="AUXÍLIO ALUGUEL ATÉ INDENIZAÇÃO"),"SIM","NÃO") -> NÃO | BF45: N/A | BG45: N/A | BH45: N/A | BI45: FINALIZADO | BJ45: FINALIZADO | BK45: 46112 | BL45: FINALIZADO | BM45: AGUARDANDO
A46: 33 | B46: JD. VITÓRIA | C46: FASE 1 - CÓRREGO | D46: -- | E46: -- | F46: 007/0056/A | G46: OCUPADO | H46: RESIDENCIAL | I46: PROPRIETÁRIO RESIDENTE | J46: ROSANGELA DE SOUZA SANTOS | K46: 44.300.223-X | L46: 345.349.188-28 | M46: CONCLUÍDO | N46: INDENIZAÇÃO | O46: 45859 | P46: N/A | Q46: N/A | R46: N/A | S46: N/A | T46: N/A | U46: N/A | V46: N/A | W46: N/A | X46: N/A | Y46: N/A | Z46: N/A | AB46: ROSANGELA DE SOUZA SANTOS | AC46: 44.300.223-X | AD46: 345.349.188-28 | AE46: PROPRIETÁRIO RESIDENTE | AF46: CONCLUÍDO | AG46: 27282.45 | AH46: 57282.45 | AI46: SIM | AJ46: 6014.2024/0006500-4 | AK46: 125287053 | AL46: FINALIZADO | AM46: FINALIZADO | AN46: SEM PENDÊNCIA | AP46: 6014.2025/0005037-8 | AQ46: FINALIZADO | AR46: FINALIZADO | AS46: FINALIZADO | AT46: FINALIZADO | AU46: 45911 | AV46: FINALIZADO | AW46: FINALIZADO | AX46: 45917 | AY46: 45917 | AZ46: 45944 | BA46: LIBERADO DEMOLIÇÃO | BB46: FINALIZADO | BC46: =IF(AY46-KG46=0,"",AY46-O46) -> 58 | BD46: =IF(AND(AI46<>"SIM",AI46="UH"),"AA","INDENIZAÇÃO") -> INDENIZAÇÃO | BE46: =IF(AND(AY46<>"AGUARDANDO",AY46<>"",N46="AUXÍLIO ALUGUEL ATÉ INDENIZAÇÃO"),"SIM","NÃO") -> NÃO | BF46: N/A | BG46: N/A | BH46: N/A | BI46: FINALIZADO | BJ46: FINALIZADO | BK46: 45937 | BL46: FINALIZADO | BM46: AGUARDANDO
A47: 34 | B47: JD. VITÓRIA | C47: FASE 1 - RISCO EMERGENCIAL | D47: -- | E47: -- | F47: 016/0026/B | G47: OCUPADO | H47: RESIDENCIAL | I47: PROPRIETÁRIO RESIDENTE | J47: LUZINETE GUILHERME ALVES FERREIRA | K47: 38.436.999-6 | L47: 157.758.068-08 | M47: CONCLUÍDO | N47: INDENIZAÇÃO | O47: 46164 | P47: N/A | Q47: N/A | R47: N/A | S47: N/A | T47: N/A | U47: N/A | V47: N/A | W47: N/A | X47: N/A | Y47: N/A | Z47: N/A | AB47: LUZINETE GUILHERME ALVES FERREIRA | AC47: 38.436.999-6 | AD47: 157.758.068-08 | AE47: PROPRIETÁRIO RESIDENTE | AF47: CONCLUÍDO | AG47: 17259.92 | AH47: 47259.92 | AI47: SIM | AJ47: 6014.2024/0006500-4 | AK47: 157082848 | AL47: FINALIZADO | AM47: FINALIZADO | AN47: SEM PENDÊNCIA | AP47: 6014.2026/0004253-9 | AQ47: FINALIZADO | AR47: FINALIZADO | AS47: FINALIZADO | AT47: FINALIZADO | AU47: 46226 | AV47: FINALIZADO | AW47: FINALIZADO | AX47: 46259 | AY47: AGUARDANDO | BA47: OCUPADO | BC47: =IF(AY47-KG47=0,"",AY47-O47) -> #VALUE! | BD47: =IF(AND(AI47<>"SIM",AI47="UH"),"AA","INDENIZAÇÃO") -> INDENIZAÇÃO | BE47: =IF(AND(AY47<>"AGUARDANDO",AY47<>"",N47="AUXÍLIO ALUGUEL ATÉ INDENIZAÇÃO"),"SIM","NÃO") -> NÃO
A48: 35 | B48: JD. VITÓRIA | C48: FASE 1 - CÓRREGO | D48: -- | E48: -- | F48: 007/0058/A | G48: OCUPADO | H48: RESIDENCIAL | I48: PROPRIETÁRIO RESIDENTE | J48: MARLENE DE JESUS SANTOS | K48: 54.880.534-8 | L48: 194.769.528.22 | M48: CONCLUÍDO | N48: INDENIZAÇÃO | O48: 46164 | P48: N/A | Q48: N/A | R48: N/A | S48: N/A | T48: N/A | U48: N/A | V48: N/A | W48: N/A | X48: N/A | Y48: N/A | Z48: N/A | AB48: MARLENE DE JESUS SANTOS | AC48: 54.880.534-8 | AD48: 194.769.528.22 | AE48: PROPRIETÁRIO RESIDENTE | AF48: CONCLUÍDO | AG48: 90840.63 | AH48: 90840.63 | AI48: SIM | AJ48: 6014.2024/0006500-4 | AK48: 153707545 | AL48: FINALIZADO | AM48: FINALIZADO | AN48: SEM PENDÊNCIA | AP48: 6014.2026/0004746-8 | AQ48: LIBERADO INSTRUÇÃO | BA48: OCUPADO | BC48: =IF(AY48-KG48=0,"",AY48-O48) | BD48: =IF(AND(AI48<>"SIM",AI48="UH"),"AA","INDENIZAÇÃO") -> INDENIZAÇÃO | BE48: =IF(AND(AY48<>"AGUARDANDO",AY48<>"",N48="AUXÍLIO ALUGUEL ATÉ INDENIZAÇÃO"),"SIM","NÃO") -> NÃO
A49: 36 | B49: JD. VITÓRIA | C49: FASE 1 - CÓRREGO | D49: _ | E49: _ | F49: 007/0059/A | G49: OCUPADO | H49: RESIDENCIAL | I49: PROPRIETÁRIO RESIDENTE | J49: THAYNA ANTUNES DA SILVA | K49: 43.570.294-4 | L49: 450.725.958-46 | M49: CONCLUÍDO | N49: INDENIZAÇÃO | O49: 45999 | P49: N/A | Q49: N/A | R49: N/A | S49: N/A | T49: N/A | U49: N/A | V49: N/A | W49: N/A | X49: N/A | Y49: N/A | Z49: N/A | AB49: THAYNA ANTUNES DA SILVA | AC49: 43.570.294-4 | AD49: 450.725.958-46 | AE49: PROPRIETÁRIO RESIDENTE | AF49: CONCLUÍDO | AG49: 58674.22 | AH49: 60000 | AI49: SIM | AJ49: 6014.2024/0006500-4 | AK49: 145585512 | AL49: FINALIZADO | AM49: FINALIZADO | AN49: SEM PENDÊNCIA | AP49: 6014.2025/0008195-8 | AQ49: FINALIZADO | AR49: FINALIZADO | AS49: FINALIZADO | AT49: FINALIZADO | AU49: 46017 | AV49: FINALIZADO | AW49: FINALIZADO | AX49: 46093 | AY49: 46093 | AZ49: AGUARDANDO | BA49: LIBERADO INSTRUÇÃO | BB49: FINALIZADO | BC49: =IF(AY49-KG49=0,"",AY49-O49) -> 94 | BD49: =IF(AND(AI49<>"SIM",AI49="UH"),"AA","INDENIZAÇÃO") -> INDENIZAÇÃO | BE49: =IF(AND(AY49<>"AGUARDANDO",AY49<>"",N49="AUXÍLIO ALUGUEL ATÉ INDENIZAÇÃO"),"SIM","NÃO") -> NÃO | BF49: N/A | BG49: N/A | BH49: N/A | BI49: FINALIZADO | BJ49: FINALIZADO | BK49: 46139 | BL49: AGUARDANDO PUBLICAÇÃO DOC
A50: 37 | B50: JD. VITÓRIA | C50: FASE 1 - RISCO EMERGENCIAL | D50: -- | E50: -- | F50: 016/0026/A | G50: OCUPADO | H50: RESIDENCIAL | I50: PROPRIETÁRIO RESIDENTE | J50: NAYARA APARECIDA ALVES VIANA | K50: 62.145.033-9 | L50: 511.613.778-32 | M50: CONCLUÍDO | N50: INDENIZAÇÃO | O50: 46164 | P50: N/A | Q50: N/A | R50: N/A | S50: N/A | T50: N/A | U50: N/A | V50: N/A | W50: N/A | X50: N/A | Y50: N/A | Z50: N/A | AB50: NAYARA APARECIDA ALVES VIANA | AC50: 62.145.033-9 | AD50: 511.613.778-32 | AE50: PROPRIETÁRIO RESIDENTE | AF50: CONCLUÍDO | AG50: 16061.24 | AH50: 46061.24 | AI50: SIM | AJ50: 6014.2024/0006500-4 | AK50: 157082691 | AL50: FINALIZADO | AM50: FINALIZADO | AN50: SEM PENDÊNCIA | AP50: 6014.2026/0004254-7 | AQ50: FINALIZADO | AR50: FINALIZADO | AS50: FINALIZADO | AT50: FINALIZADO | AU50: 46226 | AV50: FINALIZADO | AW50: FINALIZADO | AX50: 46233 | AY50: 46233 | AZ50: AGUARDANDO | BA50: LIBERADO DEMOLIÇÃO | BB50: FINALIZADO | BC50: =IF(AY50-KG50=0,"",AY50-O50) -> 69 | BD50: =IF(AND(AI50<>"SIM",AI50="UH"),"AA","INDENIZAÇÃO") -> INDENIZAÇÃO | BE50: =IF(AND(AY50<>"AGUARDANDO",AY50<>"",N50="AUXÍLIO ALUGUEL ATÉ INDENIZAÇÃO"),"SIM","NÃO") -> NÃO | BF50: N/A | BG50: N/A | BH50: N/A | BI50: AGUARDANDO ELABORAÇÃO
A51: 38 | B51: JD. VITÓRIA | C51: FASE 1 - CÓRREGO | D51: -- | E51: -- | F51: 007/0061/A | G51: OCUPADO | H51: RESIDENCIAL | I51: PROPRIETÁRIO RESIDENTE | J51: DIRLENE MARTINS SALES | K51: 35.820.858-0 | L51: 288.012.218-00 | M51: CONCLUÍDO | N51: INDENIZAÇÃO | O51: 45859 | P51: N/A | Q51: N/A | R51: N/A | S51: N/A | T51: N/A | U51: N/A | V51: N/A | W51: N/A | X51: N/A | Y51: N/A | Z51: N/A | AB51: DIRLENE MARTINS SALES | AC51: 35.820.858-0 | AD51: 288.012.218-00 | AE51: PROPRIETÁRIO RESIDENTE | AF51: CONCLUÍDO | AG51: 18153.19 | AH51: 48153.19 | AI51: SIM | AJ51: 6014.2024/0006500-4 | AK51: 127190120 | AL51: FINALIZADO | AM51: FINALIZADO | AN51: SEM PENDÊNCIA | AP51: 6014.2025/0005210-9 | AQ51: FINALIZADO | AR51: FINALIZADO | AS51: FINALIZADO | AT51: FINALIZADO | AU51: 45911 | AV51: FINALIZADO | AW51: FINALIZADO | AX51: 45917 | AY51: 45917 | AZ51: 45944 | BA51: LIBERADO DEMOLIÇÃO | BB51: FINALIZADO | BC51: =IF(AY51-KG51=0,"",AY51-O51) -> 58 | BD51: =IF(AND(AI51<>"SIM",AI51="UH"),"AA","INDENIZAÇÃO") -> INDENIZAÇÃO | BE51: =IF(AND(AY51<>"AGUARDANDO",AY51<>"",N51="AUXÍLIO ALUGUEL ATÉ INDENIZAÇÃO"),"SIM","NÃO") -> NÃO | BF51: N/A | BG51: N/A | BH51: N/A | BI51: FINALIZADO | BJ51: FINALIZADO | BK51: 45937 | BL51: FINALIZADO | BM51: AGUARDANDO
A52: 39 | B52: JD. VITÓRIA | C52: FASE 1 - CÓRREGO | D52: -- | E52: -- | F52: 009/0004/A | G52: OCUPADO | H52: RESIDENCIAL | I52: PROPRIETÁRIO RESIDENTE | J52: ADAIL JOSÉ LIMA | K52: 26.253.486-1 | L52: 166.050.258.65 | M52: CONCLUÍDO | N52: INDENIZAÇÃO | O52: 46027 | P52: N/A | Q52: N/A | R52: N/A | S52: N/A | T52: N/A | U52: N/A | V52: N/A | W52: N/A | X52: N/A | Y52: N/A | Z52: N/A | AB52: ADAIL JOSÉ LIMA | AC52: 26.253.486-1 | AD52: 166.050.258.65 | AE52: PROPRIETÁRIO RESIDENTE | AF52: CONCLUÍDO | AG52: 27293.35 | AH52: =AG52+30000 -> 57293.35 | AI52: SIM | AJ52: 6014.2024/0006500-4 | AK52: 144750197 | AL52: FINALIZADO | AM52: FINALIZADO | AN52: SEM PENDÊNCIA | AP52: 6014.2026/0000682-6 | AQ52: FINALIZADO | AR52: FINALIZADO | AS52: FINALIZADO | AT52: FINALIZADO | AU52: 46142 | AV52: FINALIZADO | AW52: FINALIZADO | AX52: 46170 | AY52: 46170 | AZ52: AGUARDANDO | BA52: LIBERADO DEMOLIÇÃO | BB52: FINALIZADO | BC52: =IF(AY52-KG52=0,"",AY52-O52) -> 143 | BD52: =IF(AND(AI52<>"SIM",AI52="UH"),"AA","INDENIZAÇÃO") -> INDENIZAÇÃO | BE52: =IF(AND(AY52<>"AGUARDANDO",AY52<>"",N52="AUXÍLIO ALUGUEL ATÉ INDENIZAÇÃO"),"SIM","NÃO") -> NÃO | BF52: N/A | BG52: N/A | BH52: N/A | BI52: FINALIZADO | BJ52: FINALIZADO | BK52: 46224 | BL52: AGUARDANDO PUBLICAÇÃO DOC
A53: 40 | B53: JD. VITÓRIA | C53: FASE 1 - CÓRREGO | D53: -- | E53: -- | F53: 009/0005/A | G53: OCUPADO | H53: MISTO | I53: PROPRIETÁRIO RESIDENTE | J53: ALINE CRISTINA MACIEL DE MOURA | K53: 41.367.508-7 | L53: 320.309.628-56 | M53: CONCLUÍDO | N53: INDENIZAÇÃO | O53: 45859 | P53: N/A | Q53: N/A | R53: N/A | S53: N/A | T53: N/A | U53: N/A | V53: N/A | W53: N/A | X53: N/A | Y53: N/A | Z53: N/A | AB53: ALINE CRISTINA MACIEL DE MOURA | AC53: 41.367.508-7 | AD53: 320.309.628-56 | AE53: PROPRIETÁRIO RESIDENTE | AF53: CONCLUÍDO | AG53: 96318.36 | AH53: 96318.36 | AI53: SIM | AJ53: 6014.2024/0006500-4 | AK53: 127190213 | AL53: FINALIZADO | AM53: FINALIZADO | AN53: SEM PENDÊNCIA | AP53: 6014.2025/0005216-8 | AQ53: FINALIZADO | AR53: FINALIZADO | AS53: FINALIZADO | AT53: FINALIZADO | AU53: 45911 | AV53: FINALIZADO | AW53: FINALIZADO | AX53: 45917 | AY53: 45917 | AZ53: 45951 | BA53: LIBERADO DEMOLIÇÃO | BB53: FINALIZADO | BC53: =IF(AY53-KG53=0,"",AY53-O53) -> 58 | BD53: =IF(AND(AI53<>"SIM",AI53="UH"),"AA","INDENIZAÇÃO") -> INDENIZAÇÃO | BE53: =IF(AND(AY53<>"AGUARDANDO",AY53<>"",N53="AUXÍLIO ALUGUEL ATÉ INDENIZAÇÃO"),"SIM","NÃO") -> NÃO | BF53: N/A | BG53: N/A | BH53: N/A | BI53: FINALIZADO | BJ53: FINALIZADO | BK53: 45937 | BL53: FINALIZADO | BM53: AGUARDANDO
A54: 41 | B54: JD. VITÓRIA | C54: FASE 1 - CÓRREGO | D54: -- | E54: -- | F54: 009/0006/A | G54: OCUPADO | H54: CONSTRUÇÃO | I54: PROPRIETARIO NÃO RESIDENTE | J54: LORRANY FARIA DE CARVALHO | K54: 64.690.013-4 | L54: 241.315.908-83 | M54: CONCLUÍDO | N54: INDENIZAÇÃO | O54: 46051 | P54: N/A | Q54: N/A | R54: N/A | S54: N/A | T54: N/A | U54: N/A | V54: N/A | W54: N/A | X54: N/A | Y54: N/A | Z54: N/A | AB54: LORRANY FARIA DE CARVALHO | AC54: 64.690.013-4 | AD54: 241.315.908-83 | AE54: PROPRIETÁRIO NÃO RESIDENTE | AF54: CONCLUÍDO | AG54: 2871.66 | AH54: 2871.66 | AI54: SIM | AJ54: 6014.2024/0006500-4 | AK54: 144750381 | AL54: FINALIZADO | AM54: FINALIZADO | AN54: SEM PENDÊNCIA | AP54: 6014.2026/0002257-0 | AQ54: FINALIZADO | AR54: FINALIZADO | AS54: FINALIZADO | AT54: FINALIZADO | AU54: 46174 | AV54: FINALIZADO | AW54: FINALIZADO | AX54: 46183 | AY54: 46183 | AZ54: AGUARDANDO | BA54: LIBERADO DEMOLIÇÃO | BB54: FINALIZADO | BC54: =IF(AY54-KG54=0,"",AY54-O54) -> 132 | BD54: =IF(AND(AI54<>"SIM",AI54="UH"),"AA","INDENIZAÇÃO") -> INDENIZAÇÃO | BE54: =IF(AND(AY54<>"AGUARDANDO",AY54<>"",N54="AUXÍLIO ALUGUEL ATÉ INDENIZAÇÃO"),"SIM","NÃO") -> NÃO | BF54: N/A | BG54: N/A | BH54: N/A | BI54: FINALIZADO | BJ54: FINALIZADO | BK54: 46224 | BL54: AGUARDANDO PUBLICAÇÃO DOC
A55: 42 | B55: JD. VITÓRIA | C55: FASE 1 - CÓRREGO | D55: -- | E55: -- | F55: 009/0007/A | G55: OCUPADO | H55: RESIDENCIAL | I55: PROPRIETÁRIO RESIDENTE | J55: VIVIAN FARIA DE SOUZA | K55: 56.074.125-X | L55: 118.515.867-76 | M55: CONCLUÍDO | N55: INDENIZAÇÃO | O55: 46051 | P55: N/A | Q55: N/A | R55: N/A | S55: N/A | T55: N/A | U55: N/A | V55: N/A | W55: N/A | X55: N/A | Y55: N/A | Z55: N/A | AB55: VIVIAN FARIA DE SOUZA | AC55: 56.074.125-X | AD55: 118.515.867-76 | AE55: PROPRIETÁRIO RESIDENTE | AF55: CONCLUÍDO | AG55: 246510.89 | AH55: 246510.89 | AI55: SIM | AJ55: 6014.2024/0006500-4 | AK55: 150526484 | AL55: FINALIZADO | AM55: FINALIZADO | AN55: SEM PENDÊNCIA | AP55: 6014.2026/0000684-2 | AQ55: FINALIZADO | AR55: FINALIZADO | AS55: FINALIZADO | AT55: FINALIZADO | AU55: 46174 | AV55: FINALIZADO | AW55: FINALIZADO | AX55: 46183 | AY55: 46183 | AZ55: AGUARDANDO | BA55: LIBERADO DEMOLIÇÃO | BB55: FINALIZADO | BC55: =IF(AY55-KG55=0,"",AY55-O55) -> 132 | BD55: =IF(AND(AI55<>"SIM",AI55="UH"),"AA","INDENIZAÇÃO") -> INDENIZAÇÃO | BE55: =IF(AND(AY55<>"AGUARDANDO",AY55<>"",N55="AUXÍLIO ALUGUEL ATÉ INDENIZAÇÃO"),"SIM","NÃO") -> NÃO | BF55: N/A | BG55: N/A | BH55: N/A | BI55: FINALIZADO | BJ55: FINALIZADO | BK55: 46224 | BL55: AGUARDANDO PUBLICAÇÃO DOC
A56: 43 | B56: JD. VITÓRIA | C56: FASE 1 - CÓRREGO | D56: -- | E56: -- | F56: 009/0008/A | G56: OCUPADO | H56: RESIDENCIAL | I56: PROPRIETÁRIO RESIDENTE | J56: REMBERTO NAVARRO TORRICO | K56: Rne 252336bdirexex | L56: 21791258875 | AJ56: 6014.2024/0006500-4 | BC56: =IF(AY56-KG56=0,"",AY56-O56) | BD56: =IF(AND(AI56<>"SIM",AI56="UH"),"AA","INDENIZAÇÃO") -> INDENIZAÇÃO | BE56: =IF(AND(AY56<>"AGUARDANDO",AY56<>"",N56="AUXÍLIO ALUGUEL ATÉ INDENIZAÇÃO"),"SIM","NÃO") -> NÃO
A57: 44 | B57: JD. VITÓRIA | C57: FASE 1 - CÓRREGO | D57: -- | E57: -- | F57: 009/0008/B | G57: OCUPADO | H57: COMERCIAL | I57: NA | J57: REMBERTO NAVARRO TORRICO | K57: Y252336bdirexex | L57: 21791258875 | O57: .84 | AJ57: 6014.2024/0006500-4 | BC57: =IF(AY57-KG57=0,"",AY57-O57) | BD57: =IF(AND(AI57<>"SIM",AI57="UH"),"AA","INDENIZAÇÃO") -> INDENIZAÇÃO | BE57: =IF(AND(AY57<>"AGUARDANDO",AY57<>"",N57="AUXÍLIO ALUGUEL ATÉ INDENIZAÇÃO"),"SIM","NÃO") -> NÃO
A58: 45 | B58: JD. VITÓRIA | C58: FASE 1 - CÓRREGO | D58: -- | E58: -- | F58: 009/0009/A | G58: OCUPADO | H58: RESIDENCIAL | I58: PROPRIETÁRIO RESIDENTE | J58: JANDIRA MARIA DE SOUZA | K58: 39.580.531-4 | L58: 063.538.568-65 | M58: CONCLUÍDO | N58: INDENIZAÇÃO | O58: 46027 | P58: N/A | Q58: N/A | R58: N/A | S58: N/A | T58: N/A | U58: N/A | V58: N/A | W58: N/A | X58: N/A | Y58: N/A | Z58: N/A | AB58: JANDIRA MARIA DE SOUZA | AC58: 39.580.531-4 | AD58: 063.538.568-65 | AE58: PROPRIETÁRIO RESIDENTE | AF58: CONCLUÍDO | AG58: 19841.15 | AH58: =AG58+30000 -> 49841.15 | AI58: SIM | AJ58: 6014.2024/0006500-4 | AK58: 143290554 | AL58: FINALIZADO | AM58: FINALIZADO | AN58: SEM PENDÊNCIA | AP58: 6014.2026/0000714-8 | AQ58: FINALIZADO | AR58: FINALIZADO | AS58: FINALIZADO | AT58: FINALIZADO | AU58: 46142 | AV58: FINALIZADO | AW58: FINALIZADO | AX58: 46153 | AY58: 46153 | AZ58: AGUARDANDO | BA58: LIBERADO DEMOLIÇÃO | BB58: FINALIZADO | BC58: =IF(AY58-KG58=0,"",AY58-O58) -> 126 | BD58: =IF(AND(AI58<>"SIM",AI58="UH"),"AA","INDENIZAÇÃO") -> INDENIZAÇÃO | BE58: =IF(AND(AY58<>"AGUARDANDO",AY58<>"",N58="AUXÍLIO ALUGUEL ATÉ INDENIZAÇÃO"),"SIM","NÃO") -> NÃO | BF58: N/A | BG58: N/A | BH58: N/A | BI58: FINALIZADO | BJ58: FINALIZADO | BK58: 46224 | BL58: AGUARDANDO PUBLICAÇÃO DOC
A59: 46 | B59: JD. VITÓRIA | C59: FASE 1 - CÓRREGO | D59: -- | E59: -- | F59: 009/0009/B | G59: OCUPADO | H59: RESIDENCIAL | I59: PROPRIETÁRIO RESIDENTE | J59: MANOEL JOSÉ DOS SANTOS | K59: 19.634.050-0 | L59: 840.401.575-91 | M59: CONCLUÍDO | N59: INDENIZAÇÃO | O59: 46051 | P59: N/A | Q59: N/A | R59: N/A | S59: N/A | T59: N/A | U59: N/A | V59: N/A | W59: N/A | X59: N/A | Y59: N/A | Z59: N/A | AB59: MANOEL JOSÉ DOS SANTOS | AC59: 19.634.050-0 | AD59: 840.401.575-91 | AE59: PROPRIETÁRIO RESIDENTE | AF59: CONCLUÍDO | AG59: 12298.44 | AH59: =AG59+30000 -> 42298.44 | AI59: SIM | AJ59: 6014.2024/0006500-4 | AK59: 143290698 | AL59: FINALIZADO | AM59: FINALIZADO | AN59: SEM PENDÊNCIA | AP59: 6014.2026/0000742-3 | AQ59: FINALIZADO | AR59: FINALIZADO | AS59: FINALIZADO | AT59: FINALIZADO | AU59: 46174 | AV59: FINALIZADO | AW59: FINALIZADO | AX59: 46183 | AY59: 46183 | AZ59: AGUARDANDO | BA59: LIBERADO DEMOLIÇÃO | BB59: FINALIZADO | BC59: =IF(AY59-KG59=0,"",AY59-O59) -> 132 | BD59: =IF(AND(AI59<>"SIM",AI59="UH"),"AA","INDENIZAÇÃO") -> INDENIZAÇÃO | BE59: =IF(AND(AY59<>"AGUARDANDO",AY59<>"",N59="AUXÍLIO ALUGUEL ATÉ INDENIZAÇÃO"),"SIM","NÃO") -> NÃO | BF59: N/A | BG59: N/A | BH59: N/A | BI59: FINALIZADO | BJ59: FINALIZADO | BK59: 46224 | BL59: AGUARDANDO PUBLICAÇÃO DOC
A60: 47 | B60: JD. VITÓRIA | C60: FASE 1 - CÓRREGO | D60: -- | E60: -- | F60: 009/0012/A | G60: OCUPADO | H60: RESIDENCIAL | I60: PROPRIETÁRIO RESIDENTE | J60: JACKSON NASCIMENTO DOS SANTOS | K60: 54.789.705-5 | L60: 433.472.938-00 | M60: CONCLUÍDO | N60: INDENIZAÇÃO | O60: 45911 | P60: N/A | Q60: N/A | R60: N/A | S60: N/A | T60: N/A | U60: N/A | V60: N/A | W60: N/A | X60: N/A | Y60: N/A | Z60: N/A | AB60: JACKSON NASCIMENTO DOS SANTOS | AC60: 54.789.705-5 | AD60: 433.472.938-00 | AE60: PROPRIETÁRIO RESIDENTE | AF60: CONCLUÍDO | AG60: 17838.15 | AH60: 47838.15 | AI60: SIM | AJ60: 6014.2024/0006500-4 | AK60: 125287369 | AL60: FINALIZADO | AM60: FINALIZADO | AN60: SEM PENDÊNCIA | AP60: 6014.2025/0006392-5 | AQ60: FINALIZADO | AR60: FINALIZADO | AS60: FINALIZADO | AT60: FINALIZADO | AU60: 45992 | AV60: FINALIZADO | AW60: FINALIZADO | AX60: 46013 | AY60: 46013 | AZ60: AGUARDANDO | BA60: LIBERADO DEMOLIÇÃO | BB60: FINALIZADO | BC60: =IF(AY60-KG60=0,"",AY60-O60) -> 102 | BD60: =IF(AND(AI60<>"SIM",AI60="UH"),"AA","INDENIZAÇÃO") -> INDENIZAÇÃO | BE60: =IF(AND(AY60<>"AGUARDANDO",AY60<>"",N60="AUXÍLIO ALUGUEL ATÉ INDENIZAÇÃO"),"SIM","NÃO") -> NÃO | BF60: N/A | BG60: N/A | BH60: N/A | BI60: FINALIZADO | BJ60: FINALIZADO | BK60: 46112 | BL60: FINALIZADO | BM60: AGUARDANDO
A61: 48 | B61: JD. VITÓRIA | C61: FASE 1 - CÓRREGO | D61: -- | E61: -- | F61: 009/0012/B | G61: OCUPADO | H61: RESIDENCIAL | I61: PROPRIETÁRIO RESIDENTE | J61: ELIANE MARIA NASCIMENTO DOS SANTOS | K61: 30.486.533-3 | L61: 012.722.274-05 | M61: CONCLUÍDO | N61: INDENIZAÇÃO | O61: 45911 | P61: N/A | Q61: N/A | R61: N/A | S61: N/A | T61: N/A | U61: N/A | V61: N/A | W61: N/A | X61: N/A | Y61: N/A | Z61: N/A | AB61: ELIANE MARIA NASCIMENTO DOS SANTOS | AC61: 30.486.533-3 | AD61: 012.722.274-05 | AE61: PROPRIETÁRIO RESIDENTE | AF61: CONCLUÍDO | AG61: 30788.4 | AH61: 60000 | AI61: SIM | AJ61: 6014.2024/0006500-4 | AK61: 125287463 | AL61: FINALIZADO | AM61: FINALIZADO | AN61: SEM PENDÊNCIA | AP61: 6014.2025/0006669-0 | AQ61: FINALIZADO | AR61: FINALIZADO | AS61: FINALIZADO | AT61: FINALIZADO | AU61: 45992 | AV61: FINALIZADO | AW61: FINALIZADO | AX61: 46013 | AY61: 46013 | AZ61: AGUARDANDO | BA61: LIBERADO DEMOLIÇÃO | BB61: FINALIZADO | BC61: =IF(AY61-KG61=0,"",AY61-O61) -> 102 | BD61: =IF(AND(AI61<>"SIM",AI61="UH"),"AA","INDENIZAÇÃO") -> INDENIZAÇÃO | BE61: =IF(AND(AY61<>"AGUARDANDO",AY61<>"",N61="AUXÍLIO ALUGUEL ATÉ INDENIZAÇÃO"),"SIM","NÃO") -> NÃO | BF61: N/A | BG61: N/A | BH61: N/A | BI61: FINALIZADO | BJ61: FINALIZADO | BK61: 46112 | BL61: FINALIZADO | BM61: AGUARDANDO
A62: 49 | B62: JD. VITÓRIA | C62: FASE 1 - CÓRREGO | D62: -- | E62: -- | F62: 009/0012/C | G62: OCUPADO | H62: RESIDENCIAL | I62: PROPRIETÁRIO RESIDENTE | J62: JOICE NASCIMENTO DOS SANTOS | K62: 60.350.850-9 | L62: 506.567.788-30 | M62: CONCLUÍDO | N62: INDENIZAÇÃO | O62: 45911 | P62: N/A | Q62: N/A | R62: N/A | S62: N/A | T62: N/A | U62: N/A | V62: N/A | W62: N/A | X62: N/A | Y62: N/A | Z62: N/A | AB62: JOICE NASCIMENTO DOS SANTOS | AC62: 60.350.850-9 | AD62: 506.567.788-30 | AE62: PROPRIETÁRIO RESIDENTE | AF62: CONCLUÍDO | AG62: 33677.61 | AH62: 60000 | AI62: SIM | AJ62: 6014.2024/0006500-4 | AK62: 141879050 | AL62: FINALIZADO | AM62: FINALIZADO | AN62: SEM PENDÊNCIA | AP62: 6014.2025/0006662-2 | AQ62: FINALIZADO | AR62: FINALIZADO | AS62: FINALIZADO | AT62: FINALIZADO | AU62: 45992 | AV62: FINALIZADO | AW62: FINALIZADO | AX62: 46013 | AY62: 46013 | AZ62: AGUARDANDO | BA62: LIBERADO DEMOLIÇÃO | BB62: FINALIZADO | BC62: =IF(AY62-KG62=0,"",AY62-O62) -> 102 | BD62: =IF(AND(AI62<>"SIM",AI62="UH"),"AA","INDENIZAÇÃO") -> INDENIZAÇÃO | BE62: =IF(AND(AY62<>"AGUARDANDO",AY62<>"",N62="AUXÍLIO ALUGUEL ATÉ INDENIZAÇÃO"),"SIM","NÃO") -> NÃO | BF62: N/A | BG62: N/A | BH62: N/A | BI62: FINALIZADO | BJ62: FINALIZADO | BK62: 46112 | BL62: FINALIZADO | BM62: AGUARDANDO
A63: 50 | B63: JD. VITÓRIA | C63: FASE 1 - CÓRREGO | D63: -- | E63: -- | F63: 009/0013/A | G63: OCUPADO | H63: RESIDENCIAL | I63: PROPRIETÁRIO RESIDENTE | J63: MAURO SOUZA DOS SANTOS | K63: 53.024.907-8 | L63: 412.621.808-48 | M63: CONCLUÍDO | N63: INDENIZAÇÃO | O63: 46027 | P63: N/A | Q63: N/A | R63: N/A | S63: N/A | T63: N/A | U63: N/A | V63: N/A | W63: N/A | X63: N/A | Y63: N/A | Z63: N/A | AB63: MAURO SOUZA DOS SANTOS | AC63: 53.024.907-8 | AD63: 412.621.808-48 | AE63: PROPRIETÁRIO RESIDENTE | AF63: CONCLUÍDO | AG63: 102297.21 | AH63: 102297.21 | AI63: SIM | AJ63: 6014.2024/0006500-4 | AK63: 143292175 | AL63: FINALIZADO | AM63: FINALIZADO | AN63: SEM PENDÊNCIA | AP63: 6014.2026/0000747-4 | AQ63: FINALIZADO | AR63: FINALIZADO | AS63: FINALIZADO | AT63: FINALIZADO | AU63: 46142 | AV63: FINALIZADO | AW63: FINALIZADO | AX63: 46153 | AY63: 46153 | AZ63: AGUARDANDO | BA63: LIBERADO DEMOLIÇÃO | BB63: FINALIZADO | BC63: =IF(AY63-KG63=0,"",AY63-O63) -> 126 | BD63: =IF(AND(AI63<>"SIM",AI63="UH"),"AA","INDENIZAÇÃO") -> INDENIZAÇÃO | BE63: =IF(AND(AY63<>"AGUARDANDO",AY63<>"",N63="AUXÍLIO ALUGUEL ATÉ INDENIZAÇÃO"),"SIM","NÃO") -> NÃO | BF63: N/A | BG63: N/A | BH63: N/A | BI63: FINALIZADO | BJ63: FINALIZADO | BK63: 46224 | BL63: AGUARDANDO PUBLICAÇÃO DOC
A64: 51 | B64: JD. VITÓRIA | C64: FASE 1 - CÓRREGO | D64: -- | E64: -- | F64: 009/0014/A | G64: OCUPADO | H64: RESIDENCIAL | I64: PROPRIETÁRIO RESIDENTE | J64: MARIA JOSÉ DE ALBUQUERQUE SANTANA | K64: 55.850.839-X | L64: 369.941.998-35 | M64: CONCLUÍDO | N64: INDENIZAÇÃO | O64: 45859 | P64: N/A | Q64: N/A | R64: N/A | S64: N/A | T64: N/A | U64: N/A | V64: N/A | W64: N/A | X64: N/A | Y64: N/A | Z64: N/A | AB64: MARIA JOSÉ DE ALBUQUERQUE SANTANA | AC64: 55.850.839-X | AD64: 369.941.998-35 | AE64: PROPRIETÁRIO RESIDENTE | AF64: CONCLUÍDO | AG64: 47154.97 | AH64: 60000 | AI64: SIM | AJ64: 6014.2024/0006500-4 | AK64: 125287573 | AL64: FINALIZADO | AM64: FINALIZADO | AN64: SEM PENDÊNCIA | AO64: CORREÇÃO DTS - NÃO CONSTA RG NO TERMO | AP64: 6014.2025/0005231-1 | AQ64: FINALIZADO | AR64: FINALIZADO | AS64: FINALIZADO | AT64: FINALIZADO | AU64: 45911 | AV64: FINALIZADO | AW64: FINALIZADO | AX64: 45917 | AY64: 45917 | AZ64: 44489 | BA64: LIBERADO DEMOLIÇÃO | BB64: FINALIZADO | BC64: =IF(AY64-KG64=0,"",AY64-O64) -> 58 | BD64: =IF(AND(AI64<>"SIM",AI64="UH"),"AA","INDENIZAÇÃO") -> INDENIZAÇÃO | BE64: =IF(AND(AY64<>"AGUARDANDO",AY64<>"",N64="AUXÍLIO ALUGUEL ATÉ INDENIZAÇÃO"),"SIM","NÃO") -> NÃO | BF64: N/A | BG64: N/A | BH64: N/A | BI64: FINALIZADO | BJ64: FINALIZADO | BK64: 45937 | BL64: FINALIZADO | BM64: AGUARDANDO
A65: 52 | B65: JD. VITÓRIA | C65: FASE 1 - CÓRREGO | D65: -- | E65: -- | F65: 009/0015/A | G65: OCUPADO | H65: RESIDENCIAL | I65: PROPRIETÁRIO RESIDENTE | J65: DANIELE MONTEIRO NASCIMENTO | K65: 41.578.577-7 | L65: 361.074.488-02 | AJ65: 6014.2024/0006500-4 | BC65: =IF(AY65-KG65=0,"",AY65-O65) | BD65: =IF(AND(AI65<>"SIM",AI65="UH"),"AA","INDENIZAÇÃO") -> INDENIZAÇÃO | BE65: =IF(AND(AY65<>"AGUARDANDO",AY65<>"",N65="AUXÍLIO ALUGUEL ATÉ INDENIZAÇÃO"),"SIM","NÃO") -> NÃO
A66: 53 | B66: JD. VITÓRIA | C66: FASE 1 - CÓRREGO | D66: -- | E66: -- | F66: 009/0015/B | G66: OCUPADO | H66: RESIDENCIAL | I66: PROPRIETÁRIO RESIDENTE | J66: VALÉRIA ALESSANDRA DE SOUZA JESUS | K66: 428100971 | L66: 45922929879 | AJ66: 6014.2024/0006500-4 | BC66: =IF(AY66-KG66=0,"",AY66-O66) | BD66: =IF(AND(AI66<>"SIM",AI66="UH"),"AA","INDENIZAÇÃO") -> INDENIZAÇÃO | BE66: =IF(AND(AY66<>"AGUARDANDO",AY66<>"",N66="AUXÍLIO ALUGUEL ATÉ INDENIZAÇÃO"),"SIM","NÃO") -> NÃO
A67: 54 | B67: JD. VITÓRIA | C67: FASE 1 - CÓRREGO | D67: -- | E67: -- | F67: 009/0016/A | G67: OCUPADO | H67: RESIDENCIAL | I67: PROPRIETÁRIO RESIDENTE | J67: MAYCON ROBSON GUEDES DE OLIVEIRA | L67: 24003059867 | AJ67: 6014.2024/0006500-4 | BC67: =IF(AY67-KG67=0,"",AY67-O67) | BD67: =IF(AND(AI67<>"SIM",AI67="UH"),"AA","INDENIZAÇÃO") -> INDENIZAÇÃO | BE67: =IF(AND(AY67<>"AGUARDANDO",AY67<>"",N67="AUXÍLIO ALUGUEL ATÉ INDENIZAÇÃO"),"SIM","NÃO") -> NÃO
A68: 55 | B68: JD. VITÓRIA | C68: FASE 1 - CÓRREGO | D68: -- | E68: -- | F68: 009/0016/B | G68: OCUPADO | H68: RESIDENCIAL | I68: PROPRIETÁRIO RESIDENTE | J68: - | K68: - | L68: - | AJ68: 6014.2024/0006500-4 | BC68: =IF(AY68-KG68=0,"",AY68-O68) | BD68: =IF(AND(AI68<>"SIM",AI68="UH"),"AA","INDENIZAÇÃO") -> INDENIZAÇÃO | BE68: =IF(AND(AY68<>"AGUARDANDO",AY68<>"",N68="AUXÍLIO ALUGUEL ATÉ INDENIZAÇÃO"),"SIM","NÃO") -> NÃO
A69: 56 | B69: JD. VITÓRIA | C69: FASE 1 - CÓRREGO | D69: -- | E69: -- | F69: 009/0017/A | G69: OCUPADO | H69: RESIDENCIAL | I69: PROPRIETÁRIO RESIDENTE | J69: MARIA DE FÁTIMA DE LIMA SALES | K69: 37.051.756-8 | L69: 226.059.538-31 | M69: CONCLUÍDO | N69: INDENIZAÇÃO | O69: 45819 | P69: N/A | Q69: N/A | R69: N/A | S69: N/A | T69: N/A | U69: N/A | V69: N/A | W69: N/A | X69: N/A | Y69: N/A | Z69: N/A | AB69: MARIA DE FÁTIMA DE LIMA SALES | AC69: 37.051.756-8 | AD69: 226.059.538-31 | AE69: PROPRIETÁRIO RESIDENTE | AF69: CONCLUÍDO | AG69: 65418.42 | AH69: 65418.42 | AI69: SIM | AJ69: 6014.2024/0006500-4 | AK69: 122002748 | AL69: FINALIZADO | AM69: FINALIZADO | AN69: SEM PENDÊNCIA | AP69: 6014.2025/0004188-3 | AQ69: FINALIZADO | AR69: FINALIZADO | AS69: FINALIZADO | AT69: FINALIZADO | AU69: 45911 | AV69: FINALIZADO | AW69: FINALIZADO | AX69: 45917 | AY69: 45917 | AZ69: 45932 | BA69: DEMOLIDA | BB69: FINALIZADO | BC69: =IF(AY69-KG69=0,"",AY69-O69) -> 98 | BD69: =IF(AND(AI69<>"SIM",AI69="UH"),"AA","INDENIZAÇÃO") -> INDENIZAÇÃO | BE69: =IF(AND(AY69<>"AGUARDANDO",AY69<>"",N69="AUXÍLIO ALUGUEL ATÉ INDENIZAÇÃO"),"SIM","NÃO") -> NÃO | BF69: N/A | BG69: N/A | BH69: N/A | BI69: FINALIZADO | BJ69: FINALIZADO | BK69: 45937 | BL69: FINALIZADO | BM69: AGUARDANDO
A70: 57 | B70: JD. VITÓRIA | C70: FASE 1 - CÓRREGO | D70: -- | E70: -- | F70: 009/0018/A | G70: OCUPADO | H70: RESIDENCIAL | I70: PROPRIETÁRIO RESIDENTE | J70: EVERTON FORTUNATO DA SILVA | K70: 486111817 | L70: 23602437809 | AJ70: 6014.2024/0006500-4 | BC70: =IF(AY70-KG70=0,"",AY70-O70) | BD70: =IF(AND(AI70<>"SIM",AI70="UH"),"AA","INDENIZAÇÃO") -> INDENIZAÇÃO | BE70: =IF(AND(AY70<>"AGUARDANDO",AY70<>"",N70="AUXÍLIO ALUGUEL ATÉ INDENIZAÇÃO"),"SIM","NÃO") -> NÃO
A71: 58 | B71: JD. VITÓRIA | C71: FASE 1 - CÓRREGO | D71: -- | E71: -- | F71: 009/0019/A | G71: OCUPADO | H71: RESIDENCIAL | I71: PROPRIETÁRIO RESIDENTE | J71: EDNA MARIA MENDONÇA DE SOUZA | K71: 39.243.832-X | L71: 039.307.614-83 | M71: CONCLUÍDO | N71: INDENIZAÇÃO | O71: 45859 | P71: N/A | Q71: N/A | R71: N/A | S71: N/A | T71: N/A | U71: N/A | V71: N/A | W71: N/A | X71: N/A | Y71: N/A | Z71: N/A | AB71: EDNA MARIA MENDONÇA DE SOUZA | AC71: 39.243.832-X | AD71: 039.307.614-83 | AE71: PROPRIETÁRIO RESIDENTE | AF71: CONCLUÍDO | AG71: 67716.65 | AH71: 67716.65 | AI71: SIM | AJ71: 6014.2024/0006500-4 | AK71: 125234559 | AL71: FINALIZADO | AM71: FINALIZADO | AN71: SEM PENDÊNCIA | AP71: 6014.2025/0005372-5 | AQ71: FINALIZADO | AR71: FINALIZADO | AS71: FINALIZADO | AT71: FINALIZADO | AU71: 45911 | AV71: FINALIZADO | AW71: FINALIZADO | AX71: 45917 | AY71: 45917 | AZ71: 45952 | BA71: LIBERADO DEMOLIÇÃO | BB71: FINALIZADO | BC71: =IF(AY71-KG71=0,"",AY71-O71) -> 58 | BD71: =IF(AND(AI71<>"SIM",AI71="UH"),"AA","INDENIZAÇÃO") -> INDENIZAÇÃO | BE71: =IF(AND(AY71<>"AGUARDANDO",AY71<>"",N71="AUXÍLIO ALUGUEL ATÉ INDENIZAÇÃO"),"SIM","NÃO") -> NÃO | BF71: N/A | BG71: N/A | BH71: N/A | BI71: FINALIZADO | BJ71: FINALIZADO | BK71: 45937 | BL71: FINALIZADO | BM71: AGUARDANDO
A72: 59 | B72: JD. VITÓRIA | C72: FASE 1 - CÓRREGO | D72: -- | E72: -- | F72: 009/0020/A | G72: OCUPADO | H72: RESIDENCIAL | I72: PROPRIETÁRIO RESIDENTE | J72: MILTON PEREIRA DOS SANTOS | K72: 17.502.863-1 | L72: 011.914.478-63 | M72: CONCLUÍDO | N72: INDENIZAÇÃO | O72: 45859 | P72: N/A | Q72: N/A | R72: N/A | S72: N/A | T72: N/A | U72: N/A | V72: N/A | W72: N/A | X72: N/A | Y72: N/A | Z72: N/A | AB72: MILTON PEREIRA DOS SANTOS | AC72: 17.502.863-1 | AD72: 011.914.478-63 | AE72: PROPRIETÁRIO RESIDENTE | AF72: CONCLUÍDO | AG72: 25624.26 | AH72: 55624.26 | AI72: SIM | AJ72: 6014.2024/0006500-4 | AK72: 125287678 | AL72: FINALIZADO | AM72: FINALIZADO | AN72: SEM PENDÊNCIA | AP72: 6014.2025/0005381-4 | AQ72: FINALIZADO | AR72: FINALIZADO | AS72: FINALIZADO | AT72: FINALIZADO | AU72: 45923 | AV72: FINALIZADO | AW72: FINALIZADO | AX72: 45929 | AY72: 45929 | AZ72: 45965 | BA72: LIBERADO DEMOLIÇÃO | BB72: FINALIZADO | BC72: =IF(AY72-KG72=0,"",AY72-O72) -> 70 | BD72: =IF(AND(AI72<>"SIM",AI72="UH"),"AA","INDENIZAÇÃO") -> INDENIZAÇÃO | BE72: =IF(AND(AY72<>"AGUARDANDO",AY72<>"",N72="AUXÍLIO ALUGUEL ATÉ INDENIZAÇÃO"),"SIM","NÃO") -> NÃO | BF72: N/A | BG72: N/A | BH72: N/A | BI72: FINALIZADO | BJ72: FINALIZADO | BK72: 45951 | BL72: FINALIZADO | BM72: AGUARDANDO
A73: 60 | B73: JD. VITÓRIA | C73: FASE 1 - CÓRREGO | D73: -- | E73: -- | F73: 009/0021/A | G73: OCUPADO | H73: RESIDENCIAL | I73: PROPRIETÁRIO RESIDENTE | J73: VALDENICE OLIVEIRA DA SILVA | K73: 36.692.100-9 | L73: 222.238.978-00 | M73: CONCLUÍDO | N73: INDENIZAÇÃO | O73: 46051 | P73: N/A | Q73: N/A | R73: N/A | S73: N/A | T73: N/A | U73: N/A | V73: N/A | W73: N/A | X73: N/A | Y73: N/A | Z73: N/A | AB73: VALDENICE OLIVEIRA DA SILVA | AC73: 36.692.100-9 | AD73: 222.238.978-00 | AE73: PROPRIETÁRIO RESIDENTE | AF73: CONCLUÍDO | AG73: 201468.21 | AH73: 201468.21 | AI73: SIM | AJ73: 6014.2024/0006500-4 | AK73: 143295794 | AL73: FINALIZADO | AM73: FINALIZADO | AN73: SEM PENDÊNCIA | AP73: 6014.2026/0000752-0 | AQ73: FINALIZADO | AR73: FINALIZADO | AS73: FINALIZADO | AT73: FINALIZADO | AU73: 46174 | AV73: FINALIZADO | AW73: FINALIZADO | AX73: 46183 | AY73: 46183 | AZ73: AGUARDANDO | BA73: LIBERADO DEMOLIÇÃO | BB73: FINALIZADO | BC73: =IF(AY73-KG73=0,"",AY73-O73) -> 132 | BD73: =IF(AND(AI73<>"SIM",AI73="UH"),"AA","INDENIZAÇÃO") -> INDENIZAÇÃO | BE73: =IF(AND(AY73<>"AGUARDANDO",AY73<>"",N73="AUXÍLIO ALUGUEL ATÉ INDENIZAÇÃO"),"SIM","NÃO") -> NÃO | BF73: N/A | BG73: N/A | BH73: N/A | BI73: FINALIZADO | BJ73: FINALIZADO | BK73: 46224 | BL73: AGUARDANDO PUBLICAÇÃO DOC
A74: 61 | B74: JD. VITÓRIA | C74: FASE 1 - CÓRREGO | D74: -- | E74: -- | F74: 009/0022/A | G74: OCUPADO | H74: RESIDENCIAL | I74: PROPRIETÁRIO RESIDENTE | J74: RONALDO MONTEIRO ARRUDA | K74: 18.361.327-2 | L74: 101.532.468-12 | M74: CONCLUÍDO | N74: INDENIZAÇÃO | O74: 46051 | P74: N/A | Q74: N/A | R74: N/A | S74: N/A | T74: N/A | U74: N/A | V74: N/A | W74: N/A | X74: N/A | Y74: N/A | Z74: N/A | AB74: RONALDO MONTEIRO ARRUDA | AC74: 18.361.327-2 | AD74: 101.532.468-12 | AE74: PROPRIETÁRIO RESIDENTE | AF74: CONCLUÍDO | AG74: 42948.2 | AH74: 60000 | AI74: SIM | AJ74: 6014.2024/0006500-4 | AK74: 143296261 | AL74: FINALIZADO | AM74: FINALIZADO | AN74: SEM PENDÊNCIA | AP74: 6014.2026/0000758-0 | AQ74: FINALIZADO | AR74: FINALIZADO | AS74: FINALIZADO | AT74: FINALIZADO | AU74: 46174 | AV74: FINALIZADO | AW74: FINALIZADO | AX74: 46183 | AY74: 46183 | AZ74: AGUARDANDO | BA74: LIBERADO DEMOLIÇÃO | BB74: FINALIZADO | BC74: =IF(AY74-KG74=0,"",AY74-O74) -> 132 | BD74: =IF(AND(AI74<>"SIM",AI74="UH"),"AA","INDENIZAÇÃO") -> INDENIZAÇÃO | BE74: =IF(AND(AY74<>"AGUARDANDO",AY74<>"",N74="AUXÍLIO ALUGUEL ATÉ INDENIZAÇÃO"),"SIM","NÃO") -> NÃO | BF74: N/A | BG74: N/A | BH74: N/A | BI74: AGUARDANDO ELABORAÇÃO
A75: 62 | B75: JD. VITÓRIA | C75: FASE 1 - CÓRREGO | D75: -- | E75: -- | F75: 009/0023/A | G75: OCUPADO | H75: RESIDENCIAL | I75: INQUILINO | J75: JOSÉ ROBERTO DA SILVA SANTANA | K75: 544961328 | L75: 5487605432 | M75: CONCLUÍDO | N75: AUXILIO ALUGUEL UH | O75: 45959 | P75: PENDENTE | Q75: 6014.2024/0005020-1 | AB75: ELIZABETH DE MENDONÇA ALMEIDA SANTANA | AC75: 50.682.862-1 | AD75: 064.108.154-50 | AE75: PROPRIETÁRIO NÃO RESIDENTE | AF75: CONCLUÍDO | AG75: 78603.25 | AH75: 78603.25 | AI75: SIM | AJ75: 6014.2024/0006500-4 | AK75: 122002970 | AL75: FINALIZADO | AM75: FINALIZADO | AN75: SEM PENDÊNCIA | AP75: 6014.2025/0007987-2 | AQ75: FINALIZADO | AR75: FINALIZADO | AS75: FINALIZADO | AT75: FINALIZADO | AU75: 46017 | AV75: FINALIZADO | AW75: FINALIZADO | AX75: 46024 | AY75: 46024 | AZ75: AGUARDANDO | BA75: LIBERADO DEMOLIÇÃO | BB75: FINALIZADO | BC75: =IF(AY75-KG75=0,"",AY75-O75) -> 65 | BD75: =IF(AND(AI75<>"SIM",AI75="UH"),"AA","INDENIZAÇÃO") -> INDENIZAÇÃO | BE75: =IF(AND(AY75<>"AGUARDANDO",AY75<>"",N75="AUXÍLIO ALUGUEL ATÉ INDENIZAÇÃO"),"SIM","NÃO") -> NÃO | BF75: N/A | BG75: N/A | BH75: N/A | BI75: FINALIZADO | BJ75: FINALIZADO | BK75: 46112 | BL75: FINALIZADO | BM75: AGUARDANDO
A76: 63 | B76: JD. VITÓRIA | C76: FASE 1 - CÓRREGO | D76: -- | E76: -- | F76: 009/0024/A | G76: OCUPADO | H76: RESIDENCIAL | I76: PROPRIETÁRIO RESIDENTE | J76: SILENE CRISTINA SCAPELLE MALOSTI | K76: 26.544.913-3 | L76: 162.866.578-51 | M76: CONCLUÍDO | N76: INDENIZAÇÃO | O76: 46077 | P76: N/A | Q76: N/A | R76: N/A | S76: N/A | T76: N/A | U76: N/A | V76: N/A | W76: N/A | X76: N/A | Y76: N/A | Z76: N/A | AB76: SILENE CRISTINA SCAPELLE MALOSTI | AC76: 26.544.913-3 | AD76: 162.866.578-51 | AE76: PROPRIETÁRIO RESIDENTE | AF76: CONCLUÍDO | AG76: 47466.71 | AH76: 60000 | AI76: SIM | AJ76: 6014.2024/0006500-4 | AK76: 143296873 | AL76: FINALIZADO | AM76: FINALIZADO | AN76: SEM PENDÊNCIA | AP76: 6014.2026/0000771-7 | AQ76: FINALIZADO | AR76: FINALIZADO | AS76: FINALIZADO | AT76: FINALIZADO | AU76: 46174 | AV76: FINALIZADO | AW76: FINALIZADO | AX76: 46183 | AY76: 46183 | AZ76: AGUARDANDO | BA76: LIBERADO DEMOLIÇÃO | BB76: FINALIZADO | BC76: =IF(AY76-KG76=0,"",AY76-O76) -> 106 | BD76: =IF(AND(AI76<>"SIM",AI76="UH"),"AA","INDENIZAÇÃO") -> INDENIZAÇÃO | BE76: =IF(AND(AY76<>"AGUARDANDO",AY76<>"",N76="AUXÍLIO ALUGUEL ATÉ INDENIZAÇÃO"),"SIM","NÃO") -> NÃO | BF76: N/A | BG76: N/A | BH76: N/A | BI76: AGUARDANDO ELABORAÇÃO
A77: 64 | B77: JD. VITÓRIA | C77: FASE 1 - CÓRREGO | D77: -- | E77: -- | F77: 009/0025/A | G77: OCUPADO | H77: MISTO | I77: PROPRIETÁRIO RESIDENTE | J77: LUZINETE AMELIA GONÇALVES | K77: 36.846.893-8 | L77: 260.999.598-90 | M77: CONCLUÍDO | N77: INDENIZAÇÃO | O77: 46051 | P77: N/A | Q77: N/A | R77: N/A | S77: N/A | T77: N/A | U77: N/A | V77: N/A | W77: N/A | X77: N/A | Y77: N/A | Z77: N/A | AB77: LUZINETE AMELIA GONÇALVES | AC77: 36.846.893-8 | AD77: 260.999.598-90 | AE77: PROPRIETÁRIO RESIDENTE | AF77: CONCLUÍDO | AG77: 105867.59 | AH77: 105867.59 | AI77: SIM | AJ77: 6014.2024/0006500-4 | AK77: 143297662 | AL77: FINALIZADO | AM77: FINALIZADO | AN77: SEM PENDÊNCIA | AP77: 6014.2026/0000773-3 | AQ77: FINALIZADO | AR77: FINALIZADO | AS77: FINALIZADO | AT77: FINALIZADO | AU77: 46184 | AV77: FINALIZADO | AW77: FINALIZADO | AX77: 46192 | AY77: 46192 | AZ77: AGUARDANDO | BA77: LIBERADO DEMOLIÇÃO | BB77: FINALIZADO | BC77: =IF(AY77-KG77=0,"",AY77-O77) -> 141 | BD77: =IF(AND(AI77<>"SIM",AI77="UH"),"AA","INDENIZAÇÃO") -> INDENIZAÇÃO | BE77: =IF(AND(AY77<>"AGUARDANDO",AY77<>"",N77="AUXÍLIO ALUGUEL ATÉ INDENIZAÇÃO"),"SIM","NÃO") -> NÃO | BF77: N/A | BG77: N/A | BH77: N/A | BI77: AGUARDANDO ELABORAÇÃO
A78: 65 | B78: JD. VITÓRIA | C78: FASE 1 - CÓRREGO | D78: -- | E78: -- | F78: 009/0025/B | G78: OCUPADO | H78: RESIDENCIAL | I78: PROPRIETÁRIO RESIDENTE | J78: CAROLINE AMELIA BARBOZA | K78: 44.110.743-6 | L78: 350.253.178-19 | M78: CONCLUÍDO | N78: INDENIZAÇÃO | O78: 46027 | P78: N/A | Q78: N/A | R78: N/A | S78: N/A | T78: N/A | U78: N/A | V78: N/A | W78: N/A | X78: N/A | Y78: N/A | Z78: N/A | AB78: CAROLINE AMELIA BARBOZA | AC78: 44.110.743-6 | AD78: 350.253.178-19 | AE78: PROPRIETÁRIO RESIDENTE | AF78: CONCLUÍDO | AG78: 21456.82 | AH78: =AG78+30000 -> 51456.82 | AI78: SIM | AJ78: 6014.2024/0006500-5 | AK78: 143301424 | AL78: FINALIZADO | AM78: FINALIZADO | AN78: SEM PENDÊNCIA | AP78: 6014.2026/0000775-0 | AQ78: FINALIZADO | AR78: FINALIZADO | AS78: FINALIZADO | AT78: FINALIZADO | AU78: 46142 | AV78: FINALIZADO | AW78: FINALIZADO | AX78: 46154 | AY78: 46154 | AZ78: AGUARDANDO | BA78: LIBERADO DEMOLIÇÃO | BB78: FINALIZADO | BC78: =IF(AY78-KG78=0,"",AY78-O78) -> 127 | BD78: =IF(AND(AI78<>"SIM",AI78="UH"),"AA","INDENIZAÇÃO") -> INDENIZAÇÃO | BE78: =IF(AND(AY78<>"AGUARDANDO",AY78<>"",N78="AUXÍLIO ALUGUEL ATÉ INDENIZAÇÃO"),"SIM","NÃO") -> NÃO | BF78: N/A | BG78: N/A | BH78: N/A | BI78: AGUARDANDO ELABORAÇÃO
A79: 66 | B79: JD. VITÓRIA | C79: FASE 1 - CÓRREGO | D79: -- | E79: -- | F79: 009/0026/A | G79: OCUPADO | H79: RESIDENCIAL | I79: PROPRIETÁRIO RESIDENTE | J79: JOSIRENE DA SILVA SANTOS | K79: 33.651.732-4 | L79: 282.734.908-66 | M79: CONCLUÍDO | N79: INDENIZAÇÃO | O79: 45819 | P79: N/A | Q79: N/A | R79: N/A | S79: N/A | T79: N/A | U79: N/A | V79: N/A | W79: N/A | X79: N/A | Y79: N/A | Z79: N/A | AB79: JOSIRENE DA SILVA SANTOS | AC79: 33.651.732-4 | AD79: 282.734.908-66 | AE79: PROPRIETÁRIO RESIDENTE | AF79: CONCLUÍDO | AG79: 40880.85 | AH79: 60000 | AI79: SIM | AJ79: 6014.2024/0006500-4 | AK79: 122003153 | AL79: FINALIZADO | AM79: FINALIZADO | AN79: SEM PENDÊNCIA | AP79: 6014.2025/0003623-5 | AQ79: FINALIZADO | AR79: FINALIZADO | AS79: FINALIZADO | AT79: FINALIZADO | AU79: 45911 | AV79: FINALIZADO | AW79: FINALIZADO | AX79: 45917 | AY79: 45917 | AZ79: 45932 | BA79: DEMOLIDA | BB79: FINALIZADO | BC79: =IF(AY79-KG79=0,"",AY79-O79) -> 98 | BD79: =IF(AND(AI79<>"SIM",AI79="UH"),"AA","INDENIZAÇÃO") -> INDENIZAÇÃO | BE79: =IF(AND(AY79<>"AGUARDANDO",AY79<>"",N79="AUXÍLIO ALUGUEL ATÉ INDENIZAÇÃO"),"SIM","NÃO") -> NÃO | BF79: N/A | BG79: N/A | BH79: N/A | BI79: FINALIZADO | BJ79: FINALIZADO | BK79: 45937 | BL79: FINALIZADO | BM79: AGUARDANDO
A80: 67 | B80: JD. VITÓRIA | C80: FASE 1 - CÓRREGO | D80: -- | E80: -- | F80: 009/0026/B | G80: VAZIO | H80: RESIDENCIAL | I80: NA | J80: JÉSSICA GUALBERTO MARTINS DOS SANTOS | K80: 50.563.605-0 | L80: 461.416.998-80 | AJ80: 6014.2024/0006500-4 | BC80: =IF(AY80-KG80=0,"",AY80-O80) | BD80: =IF(AND(AI80<>"SIM",AI80="UH"),"AA","INDENIZAÇÃO") -> INDENIZAÇÃO | BE80: =IF(AND(AY80<>"AGUARDANDO",AY80<>"",N80="AUXÍLIO ALUGUEL ATÉ INDENIZAÇÃO"),"SIM","NÃO") -> NÃO
A81: 68 | B81: JD. VITÓRIA | C81: FASE 1 - CÓRREGO | D81: -- | E81: -- | F81: 009/0027/A | G81: OCUPADO | H81: RESIDENCIAL | I81: PROPRIETÁRIO RESIDENTE | J81: MANOEL MESSIAS EVANGELISTA DOS SANTOS | K81: 53.172.376-8 | L81: 026.545.915-06 | M81: CONCLUÍDO | N81: INDENIZAÇÃO | O81: 45859 | P81: N/A | Q81: N/A | R81: N/A | S81: N/A | T81: N/A | U81: N/A | V81: N/A | W81: N/A | X81: N/A | Y81: N/A | Z81: N/A | AB81: MANOEL MESSIAS EVANGELISTA DOS SANTOS | AC81: 53.172.376-8 | AD81: 026.545.915-06 | AE81: PROPRIETÁRIO RESIDENTE | AF81: CONCLUÍDO | AG81: 26115.17 | AH81: 56115.17 | AI81: SIM | AJ81: 6014.2024/0006500-4 | AK81: 125234639 | AL81: FINALIZADO | AM81: FINALIZADO | AN81: SEM PENDÊNCIA | AP81: 6014.2025/0005383-0 | AQ81: FINALIZADO | AR81: FINALIZADO | AS81: FINALIZADO | AT81: FINALIZADO | AU81: 45911 | AV81: FINALIZADO | AW81: FINALIZADO | AX81: 45917 | AY81: 45917 | AZ81: 45944 | BA81: LIBERADO DEMOLIÇÃO | BB81: FINALIZADO | BC81: =IF(AY81-KG81=0,"",AY81-O81) -> 58 | BD81: =IF(AND(AI81<>"SIM",AI81="UH"),"AA","INDENIZAÇÃO") -> INDENIZAÇÃO | BE81: =IF(AND(AY81<>"AGUARDANDO",AY81<>"",N81="AUXÍLIO ALUGUEL ATÉ INDENIZAÇÃO"),"SIM","NÃO") -> NÃO | BF81: N/A | BG81: N/A | BH81: N/A | BI81: FINALIZADO | BJ81: FINALIZADO | BK81: 45937 | BL81: FINALIZADO | BM81: AGUARDANDO
A82: 69 | B82: JD. VITÓRIA | C82: FASE 1 - CÓRREGO | D82: -- | E82: -- | F82: 009/0029/A | G82: OCUPADO | H82: RESIDENCIAL | I82: PROPRIETÁRIO RESIDENTE | J82: MARINA DE FÁTIMA DA COSTA | K82: 133064888 | L82: 8855378821 | AJ82: 6014.2024/0006500-4 | BC82: =IF(AY82-KG82=0,"",AY82-O82) | BD82: =IF(AND(AI82<>"SIM",AI82="UH"),"AA","INDENIZAÇÃO") -> INDENIZAÇÃO | BE82: =IF(AND(AY82<>"AGUARDANDO",AY82<>"",N82="AUXÍLIO ALUGUEL ATÉ INDENIZAÇÃO"),"SIM","NÃO") -> NÃO
A83: 70 | B83: JD. VITÓRIA | C83: FASE 1 - CÓRREGO | D83: -- | E83: -- | F83: 009/0030/A | G83: OCUPADO | H83: RESIDENCIAL | I83: PROPRIETÁRIO RESIDENTE | J83: ALDINETE JOSEFA PESSOA | K83: 30.762.232-0 | L83: 224.346.198-60 | M83: CONCLUÍDO | N83: INDENIZAÇÃO | O83: 46027 | P83: N/A | Q83: N/A | R83: N/A | S83: N/A | T83: N/A | U83: N/A | V83: N/A | W83: N/A | X83: N/A | Y83: N/A | Z83: N/A | AB83: ALDINETE JOSEFA PESSOA | AC83: 30.762.232-0 | AD83: 224.346.198-60 | AE83: PROPRIETÁRIO RESIDENTE | AF83: CONCLUÍDO | AG83: 68701.59 | AH83: 68701.59 | AI83: SIM | AJ83: 6014.2024/0006500-4 | AK83: 143303203 | AL83: FINALIZADO | AM83: FINALIZADO | AN83: SEM PENDÊNCIA | AP83: 6014.2026/0000777-6 | AQ83: FINALIZADO | AR83: FINALIZADO | AS83: FINALIZADO | AT83: FINALIZADO | AU83: 46142 | AV83: FINALIZADO | AW83: FINALIZADO | AX83: 46154 | AY83: 46154 | AZ83: AGUARDANDO | BA83: LIBERADO DEMOLIÇÃO | BB83: FINALIZADO | BC83: =IF(AY83-KG83=0,"",AY83-O83) -> 127 | BD83: =IF(AND(AI83<>"SIM",AI83="UH"),"AA","INDENIZAÇÃO") -> INDENIZAÇÃO | BE83: =IF(AND(AY83<>"AGUARDANDO",AY83<>"",N83="AUXÍLIO ALUGUEL ATÉ INDENIZAÇÃO"),"SIM","NÃO") -> NÃO | BF83: N/A | BG83: N/A | BH83: N/A | BI83: AGUARDANDO ELABORAÇÃO
A84: 71 | B84: JD. VITÓRIA | C84: FASE 1 - CÓRREGO | F84: 009/0030/B | G84: OCUPADO | H84: RESIDENCIAL | I84: PROPRIETÁRIO RESIDENTE | J84: KLEBER PESSOA DA SILVA | K84: 49.388.650-3 | L84: 396.335.238-85 | M84: CONCLUÍDO | N84: INDENIZAÇÃO | O84: 46014 | P84: N/A | Q84: N/A | R84: N/A | S84: N/A | T84: N/A | U84: N/A | V84: N/A | W84: N/A | X84: N/A | Y84: N/A | Z84: N/A | AB84: KLEBER PESSOA DA SILVA | AC84: 49.388.650-3 | AD84: 396.335.238-85 | AE84: PROPRIETÁRIO RESIDENTE | AF84: CONCLUÍDO | AG84: 54112.17 | AH84: 60000 | AI84: SIM | AJ84: 6014.2024/0006500-4 | AK84: 143303589 | AL84: FINALIZADO | AM84: FINALIZADO | AN84: SEM PENDÊNCIA | AP84: 6014.2026/0000778-4 | AQ84: FINALIZADO | AR84: FINALIZADO | AS84: FINALIZADO | AT84: FINALIZADO | AU84: 46174 | AV84: FINALIZADO | AW84: FINALIZADO | AX84: 46183 | AY84: 46183 | AZ84: AGUARDANDO | BA84: LIBERADO DEMOLIÇÃO | BB84: FINALIZADO | BC84: =IF(AY84-KG84=0,"",AY84-O84) -> 169 | BD84: =IF(AND(AI84<>"SIM",AI84="UH"),"AA","INDENIZAÇÃO") -> INDENIZAÇÃO | BE84: =IF(AND(AY84<>"AGUARDANDO",AY84<>"",N84="AUXÍLIO ALUGUEL ATÉ INDENIZAÇÃO"),"SIM","NÃO") -> NÃO | BF84: N/A | BG84: N/A | BH84: N/A | BI84: AGUARDANDO ELABORAÇÃO
A85: 72 | B85: JD. VITÓRIA | C85: FASE 1 - CÓRREGO | D85: -- | E85: -- | F85: 009/0030/C | G85: OCUPADO | H85: CONSTRUÇÃO | I85: PROPRIETARIO NÃO RESIDENTE | J85: MARCOS COSTA ALVES DA SILVA | K85: 38.358.826-1 | L85: 213.440.768-90 | M85: CONCLUÍDO | N85: INDENIZAÇÃO | O85: 46097 | P85: N/A | Q85: N/A | R85: N/A | S85: N/A | T85: N/A | U85: N/A | V85: N/A | W85: N/A | X85: N/A | Y85: N/A | Z85: N/A | AB85: MARCOS COSTA ALVES DA SILVA | AC85: 38.358.826-1 | AD85: 213.440.768-90 | AE85: PROPRIETÁRIO NÃO RESIDENTE | AF85: CONCLUÍDO | AG85: 5460.7 | AH85: 5460.7 | AI85: SIM | AJ85: 6014.2024/0006500-4 | AK85: 143305205 | AL85: FINALIZADO | AM85: FINALIZADO | AN85: SEM PENDÊNCIA | AP85: 6014.2026/0000779-2 | AQ85: FINALIZADO | AR85: FINALIZADO | AS85: FINALIZADO | AT85: FINALIZADO | AU85: 46174 | AV85: FINALIZADO | AW85: FINALIZADO | AX85: 46183 | AY85: 46183 | AZ85: AGUARDANDO | BA85: LIBERADO DEMOLIÇÃO | BB85: FINALIZADO | BC85: =IF(AY85-KG85=0,"",AY85-O85) -> 86 | BD85: =IF(AND(AI85<>"SIM",AI85="UH"),"AA","INDENIZAÇÃO") -> INDENIZAÇÃO | BE85: =IF(AND(AY85<>"AGUARDANDO",AY85<>"",N85="AUXÍLIO ALUGUEL ATÉ INDENIZAÇÃO"),"SIM","NÃO") -> NÃO | BF85: N/A | BG85: N/A | BH85: N/A | BI85: AGUARDANDO ELABORAÇÃO
A86: 73 | B86: JD. VITÓRIA | C86: FASE 1 - CÓRREGO | D86: -- | E86: -- | F86: 009/0031/A | G86: OCUPADO | H86: RESIDENCIAL | I86: PROPRIETÁRIO RESIDENTE | J86: ARARI DE FÁTIMA DOS SANTOS | K86: 21.214.069-3 | L86: 166.906.338-02 | M86: CONCLUÍDO | N86: INDENIZAÇÃO | O86: 45831 | P86: N/A | Q86: N/A | R86: N/A | S86: N/A | T86: N/A | U86: N/A | V86: N/A | W86: N/A | X86: N/A | Y86: N/A | Z86: N/A | AB86: ARARI DE FÁTIMA DOS SANTOS | AC86: 21.214.069-3 | AD86: 166.906.338-02 | AE86: PROPRIETÁRIO RESIDENTE | AF86: CONCLUÍDO | AG86: 37489.31 | AH86: 60000 | AI86: SIM | AJ86: 6014.2024/0006500-4 | AK86: 123203000 | AL86: FINALIZADO | AM86: FINALIZADO | AN86: SEM PENDÊNCIA | AP86: 6014.2025/0004211-1 | AQ86: FINALIZADO | AR86: FINALIZADO | AS86: FINALIZADO | AT86: FINALIZADO | AU86: 45911 | AV86: FINALIZADO | AW86: FINALIZADO | AX86: 45917 | AY86: 45917 | AZ86: 45944 | BA86: LIBERADO DEMOLIÇÃO | BB86: FINALIZADO | BC86: =IF(AY86-KG86=0,"",AY86-O86) -> 86 | BD86: =IF(AND(AI86<>"SIM",AI86="UH"),"AA","INDENIZAÇÃO") -> INDENIZAÇÃO | BE86: =IF(AND(AY86<>"AGUARDANDO",AY86<>"",N86="AUXÍLIO ALUGUEL ATÉ INDENIZAÇÃO"),"SIM","NÃO") -> NÃO | BF86: N/A | BG86: N/A | BH86: N/A | BI86: FINALIZADO | BJ86: FINALIZADO | BK86: 45937 | BL86: FINALIZADO | BM86: AGUARDANDO
A87: 74 | B87: JD. VITÓRIA | C87: FASE 1 - CÓRREGO | F87: 009/0032/A | G87: OCUPADO | H87: RESIDENCIAL | I87: PROPRIETÁRIO RESIDENTE | J87: DANIELLE CAVALCANTE VIEIRA | K87: 44.117.725-6 | L87: 394.198.258-33 | M87: CONCLUIDO | N87: INDENIZAÇÃO | O87: 46014 | P87: N/A | Q87: N/A | R87: N/A | S87: N/A | T87: N/A | U87: N/A | V87: N/A | W87: N/A | X87: N/A | Y87: N/A | Z87: N/A | AB87: DANIELLE CAVALCANTE VIEIRA | AC87: 44.117.725-6 | AD87: 394.198.258-33 | AE87: PROPRIETÁRIO RESIDENTE | AF87: CONCLUÍDO | AG87: 36153.61 | AH87: 60000 | AI87: SIM | AJ87: 6014.2024/0006500-4 | AK87: 143305284 | AL87: FINALIZADO | AM87: FINALIZADO | AN87: SEM PENDÊNCIA | AP87: 6014.2026/0000795-4 | AQ87: FINALIZADO | AR87: FINALIZADO | AS87: FINALIZADO | AT87: FINALIZADO | AU87: 46184 | AV87: FINALIZADO | AW87: FINALIZADO | AX87: 46191 | AY87: 46191 | AZ87: AGUARDANDO | BA87: LIBERADO DEMOLIÇÃO | BB87: FINALIZADO | BC87: =IF(AY87-KG87=0,"",AY87-O87) -> 177 | BD87: =IF(AND(AI87<>"SIM",AI87="UH"),"AA","INDENIZAÇÃO") -> INDENIZAÇÃO | BE87: =IF(AND(AY87<>"AGUARDANDO",AY87<>"",N87="AUXÍLIO ALUGUEL ATÉ INDENIZAÇÃO"),"SIM","NÃO") -> NÃO | BF87: N/A | BG87: N/A | BH87: N/A | BI87: AGUARDANDO ELABORAÇÃO
A88: 75 | B88: JD. VITÓRIA | C88: FASE 1 - CÓRREGO | F88: 009/0033/A | G88: OCUPADO | H88: RESIDENCIAL | I88: PROPRIETÁRIO RESIDENTE | J88: PERIELDA SILVA SANTOS | K88: 41.170.560-X | L88: 341.386.448-30 | M88: CONCLUÍDO | N88: INDENIZAÇÃO | O88: 46014 | P88: N/A | Q88: N/A | R88: N/A | S88: N/A | T88: N/A | U88: N/A | V88: N/A | W88: N/A | X88: N/A | Y88: N/A | Z88: N/A | AB88: PERIELDA SILVA SANTOS | AC88: 41.170.560-X | AD88: 341.386.448-30 | AE88: PROPRIETÁRIO RESIDENTE | AF88: CONCLUÍDO | AG88: 65429.76 | AH88: 65429.76 | AI88: SIM | AJ88: 6014.2024/0006500-4 | AK88: 143305402 | AL88: FINALIZADO | AM88: FINALIZADO | AN88: SEM PENDÊNCIA | AP88: 6014.2026/0000796-2 | AQ88: FINALIZADO | AR88: FINALIZADO | AS88: FINALIZADO | AT88: FINALIZADO | AU88: 46142 | AV88: FINALIZADO | AW88: FINALIZADO | AX88: 46154 | AY88: 46154 | AZ88: AGUARDANDO | BA88: LIBERADO DEMOLIÇÃO | BB88: FINALIZADO | BC88: =IF(AY88-KG88=0,"",AY88-O88) -> 140 | BD88: =IF(AND(AI88<>"SIM",AI88="UH"),"AA","INDENIZAÇÃO") -> INDENIZAÇÃO | BE88: =IF(AND(AY88<>"AGUARDANDO",AY88<>"",N88="AUXÍLIO ALUGUEL ATÉ INDENIZAÇÃO"),"SIM","NÃO") -> NÃO | BF88: N/A | BG88: N/A | BH88: N/A | BI88: AGUARDANDO ELABORAÇÃO
A89: 76 | B89: JD. VITÓRIA | C89: FASE 1 - CÓRREGO | D89: -- | E89: -- | F89: 009/0034/A | G89: OCUPADO | H89: RESIDENCIAL | I89: PROPRIETÁRIO RESIDENTE | J89: NEUZA FERREIRA DA SILVA | K89: 33.486.650-9 | L89: 239.577.004-34 | M89: CONCLUÍDO | N89: INDENIZAÇÃO | O89: 45859 | P89: N/A | Q89: N/A | R89: N/A | S89: N/A | T89: N/A | U89: N/A | V89: N/A | W89: N/A | X89: N/A | Y89: N/A | Z89: N/A | AB89: NEUZA FERREIRA DA SILVA | AC89: 33.486.650-9 | AD89: 239.577.004-34 | AE89: PROPRIETÁRIO RESIDENTE | AF89: CONCLUÍDO | AG89: 10224.67 | AH89: 40224.67 | AI89: SIM | AJ89: 6014.2024/0006500-4 | AK89: 129343214 | AL89: FINALIZADO | AM89: FINALIZADO | AN89: SEM PENDÊNCIA | AP89: 6014.2025/0005386-5 | AQ89: FINALIZADO | AR89: FINALIZADO | AS89: FINALIZADO | AT89: FINALIZADO | AU89: 45911 | AV89: FINALIZADO | AW89: FINALIZADO | AX89: 45917 | AY89: 45917 | AZ89: 45952 | BA89: LIBERADO DEMOLIÇÃO | BB89: FINALIZADO | BC89: =IF(AY89-KG89=0,"",AY89-O89) -> 58 | BD89: =IF(AND(AI89<>"SIM",AI89="UH"),"AA","INDENIZAÇÃO") -> INDENIZAÇÃO | BE89: =IF(AND(AY89<>"AGUARDANDO",AY89<>"",N89="AUXÍLIO ALUGUEL ATÉ INDENIZAÇÃO"),"SIM","NÃO") -> NÃO | BF89: N/A | BG89: N/A | BH89: N/A | BI89: FINALIZADO | BJ89: FINALIZADO | BK89: 45937 | BL89: FINALIZADO | BM89: AGUARDANDO
A90: 77 | B90: JD. VITÓRIA | C90: FASE 1 - CÓRREGO | D90: -- | E90: -- | F90: 010/0007/A | G90: OCUPADO | H90: RESIDENCIAL | I90: PROPRIETÁRIO RESIDENTE | J90: LUIS PEREIRA DOS SANTOS FILHO | K90: 34.878.004-7 | L90: 272.213.318-04 | AJ90: 6014.2024/0006500-4 | BC90: =IF(AY90-KG90=0,"",AY90-O90) | BD90: =IF(AND(AI90<>"SIM",AI90="UH"),"AA","INDENIZAÇÃO") -> INDENIZAÇÃO | BE90: =IF(AND(AY90<>"AGUARDANDO",AY90<>"",N90="AUXÍLIO ALUGUEL ATÉ INDENIZAÇÃO"),"SIM","NÃO") -> NÃO
A91: 78 | B91: JD. VITÓRIA | C91: FASE 1 - CÓRREGO | D91: -- | E91: -- | F91: 010/0009/A | G91: OCUPADO | H91: RESIDENCIAL | I91: PROPRIETÁRIO RESIDENTE | J91: LUCIENE CARDOSO PEREIRA | K91: 32.672.505-2 | L91: 256.444.508-06 | M91: CONCLUÍDO | N91: INDENIZAÇÃO | O91: 45887 | P91: N/A | Q91: N/A | R91: N/A | S91: N/A | T91: N/A | U91: N/A | V91: N/A | W91: N/A | X91: N/A | Y91: N/A | Z91: N/A | AB91: LUCIENE CARDOSO PEREIRA | AC91: 32.672.505-2 | AD91: 256.444.508-06 | AE91: PROPRIETÁRIO RESIDENTE | AF91: CONCLUÍDO | AG91: 75631.73 | AH91: 75631.73 | AI91: SIM | AJ91: 6014.2024/0006500-4 | AK91: 125234906 | AL91: FINALIZADO | AM91: FINALIZADO | AN91: SEM PENDÊNCIA | AP91: 6014.2025/0006290-2 | AQ91: FINALIZADO | AR91: FINALIZADO | AS91: FINALIZADO | AT91: FINALIZADO | AU91: 45992 | AV91: FINALIZADO | AW91: FINALIZADO | AX91: 46014 | AY91: 46014 | AZ91: AGUARDANDO | BA91: LIBERADO DEMOLIÇÃO | BB91: FINALIZADO | BC91: =IF(AY91-KG91=0,"",AY91-O91) -> 127 | BD91: =IF(AND(AI91<>"SIM",AI91="UH"),"AA","INDENIZAÇÃO") -> INDENIZAÇÃO | BE91: =IF(AND(AY91<>"AGUARDANDO",AY91<>"",N91="AUXÍLIO ALUGUEL ATÉ INDENIZAÇÃO"),"SIM","NÃO") -> NÃO | BF91: N/A | BG91: N/A | BH91: N/A | BI91: FINALIZADO | BJ91: FINALIZADO | BK91: 46112 | BL91: FINALIZADO | BM91: AGUARDANDO
A92: 79 | B92: JD. VITÓRIA | C92: FASE 1 - CÓRREGO | D92: -- | E92: -- | F92: 010/0012/A | G92: OCUPADO | H92: RESIDENCIAL | I92: PROPRIETÁRIO RESIDENTE | J92: GLAUSIEL DE JESUS MACIEL | K92: 54. 732.483.2 | L92: 041.406.735.59 | M92: CONCLUÍDO | N92: INDENIZAÇÃO | O92: 45911 | P92: N/A | Q92: N/A | R92: N/A | S92: N/A | T92: N/A | U92: N/A | V92: N/A | W92: N/A | X92: N/A | Y92: N/A | Z92: N/A | AB92: GLAUSIEL DE JESUS MACIEL | AC92: 54. 732.483.2 | AD92: 041.406.735.59 | AE92: PROPRIETÁRIO RESIDENTE | AF92: CONCLUÍDO | AG92: 28555.37 | AH92: 58555.37 | AI92: SIM | AJ92: 6014.2024/0006500-4 | AK92: 141879410 | AL92: FINALIZADO | AM92: FINALIZADO | AN92: SEM PENDÊNCIA | AP92: 6014.2025/0006005-5 | AQ92: FINALIZADO | AR92: FINALIZADO | AS92: FINALIZADO | AT92: FINALIZADO | AU92: 45992 | AV92: FINALIZADO | AW92: FINALIZADO | AX92: 46014 | AY92: 46014 | AZ92: AGUARDANDO | BA92: LIBERADO DEMOLIÇÃO | BB92: FINALIZADO | BC92: =IF(AY92-KG92=0,"",AY92-O92) -> 103 | BD92: =IF(AND(AI92<>"SIM",AI92="UH"),"AA","INDENIZAÇÃO") -> INDENIZAÇÃO | BE92: =IF(AND(AY92<>"AGUARDANDO",AY92<>"",N92="AUXÍLIO ALUGUEL ATÉ INDENIZAÇÃO"),"SIM","NÃO") -> NÃO | BF92: N/A | BG92: N/A | BH92: N/A | BI92: FINALIZADO | BJ92: FINALIZADO | BK92: 46112 | BL92: FINALIZADO | BM92: AGUARDANDO
A93: 80 | B93: JD. VITÓRIA | C93: FASE 1 - CÓRREGO | D93: -- | E93: -- | F93: 010/0013/A | G93: OCUPADO | H93: RESIDENCIAL | I93: PROPRIETÁRIO RESIDENTE | J93: AURILENE MARIA DE SOUZA | K93: 50.297.874.0 | L93: 866.801.964-34 | M93: CONCLUÍDO | N93: INDENIZAÇÃO | O93: 45894 | P93: N/A | Q93: N/A | R93: N/A | S93: N/A | T93: N/A | U93: N/A | V93: N/A | W93: N/A | X93: N/A | Y93: N/A | Z93: N/A | AB93: AURILENE MARIA DE SOUZA | AC93: 50.297.874.0 | AD93: 866.801.964-34 | AE93: PROPRIETÁRIO RESIDENTE | AF93: CONCLUÍDO | AG93: 59170.54 | AH93: 60000 | AI93: SIM | AJ93: 6014.2024/0006500-4 | AK93: 125235166 | AL93: FINALIZADO | AM93: FINALIZADO | AN93: SEM PENDÊNCIA | AP93: 6014.2025/0006382-8 | AQ93: FINALIZADO | AR93: FINALIZADO | AS93: FINALIZADO | AT93: FINALIZADO | AU93: 46071 | AV93: FINALIZADO | AW93: FINALIZADO | AX93: 46087 | AY93: 46087 | AZ93: AGUARDANDO | BA93: LIBERADO DEMOLIÇÃO | BB93: FINALIZADO | BC93: =IF(AY93-KG93=0,"",AY93-O93) -> 193 | BD93: =IF(AND(AI93<>"SIM",AI93="UH"),"AA","INDENIZAÇÃO") -> INDENIZAÇÃO | BE93: =IF(AND(AY93<>"AGUARDANDO",AY93<>"",N93="AUXÍLIO ALUGUEL ATÉ INDENIZAÇÃO"),"SIM","NÃO") -> NÃO | BF93: N/A | BG93: N/A | BH93: N/A | BI93: FINALIZADO | BJ93: FINALIZADO | BK93: 46139 | BL93: AGUARDANDO PUBLICAÇÃO DOC
A94: 81 | B94: JD. VITÓRIA | C94: FASE 1 - CÓRREGO | D94: -- | E94: -- | F94: 010/0014/A | G94: OCUPADO | H94: RESIDENCIAL | I94: PROPRIETÁRIO RESIDENTE | J94: MIKAELLY SANTANA SILVA | K94: 65.620.591-X | L94: 086.244.685-66 | M94: CONCLUÍDO | N94: INDENIZAÇÃO | O94: 45819 | P94: N/A | Q94: N/A | R94: N/A | S94: N/A | T94: N/A | U94: N/A | V94: N/A | W94: N/A | X94: N/A | Y94: N/A | Z94: N/A | AB94: MIKAELLY SANTANA SILVA | AC94: 65.620.591-X | AD94: 086.244.685-66 | AE94: PROPRIETÁRIO RESIDENTE | AF94: CONCLUÍDO | AG94: 19293.57 | AH94: 49293.57 | AI94: SIM | AJ94: 6014.2024/0006500-4 | AK94: 123203151 | AL94: FINALIZADO | AM94: FINALIZADO | AN94: SEM PENDÊNCIA | AP94: 6014.2025/0003626-0 | AQ94: FINALIZADO | AR94: FINALIZADO | AS94: FINALIZADO | AT94: FINALIZADO | AU94: 45909 | AV94: FINALIZADO | AW94: FINALIZADO | AX94: 45915 | AY94: 45915 | AZ94: 45944 | BA94: LIBERADO DEMOLIÇÃO | BB94: FINALIZADO | BC94: =IF(AY94-KG94=0,"",AY94-O94) -> 96 | BD94: =IF(AND(AI94<>"SIM",AI94="UH"),"AA","INDENIZAÇÃO") -> INDENIZAÇÃO | BE94: =IF(AND(AY94<>"AGUARDANDO",AY94<>"",N94="AUXÍLIO ALUGUEL ATÉ INDENIZAÇÃO"),"SIM","NÃO") -> NÃO | BF94: N/A | BG94: N/A | BH94: N/A | BI94: FINALIZADO | BJ94: FINALIZADO | BK94: 45937 | BL94: FINALIZADO | BM94: AGUARDANDO
A95: 82 | B95: JD. VITÓRIA | C95: FASE 1 - CÓRREGO | D95: -- | E95: -- | F95: 010/0015/A | G95: OCUPADO | H95: RESIDENCIAL | I95: PROPRIETÁRIO RESIDENTE | J95: ROSIANE MONTEIRO DOS SANTOS | K95: 32.220.405-7 | L95: 650.467.654-20 | M95: CONCLUÍDO | N95: INDENIZAÇÃO | O95: 45819 | P95: N/A | Q95: N/A | R95: N/A | S95: N/A | T95: N/A | U95: N/A | V95: N/A | W95: N/A | X95: N/A | Y95: N/A | Z95: N/A | AB95: ROSIANE MONTEIRO DOS SANTOS | AC95: 32.220.405-7 | AD95: 650.467.654-20 | AE95: PROPRIETÁRIO RESIDENTE | AF95: CONCLUÍDO | AG95: 27056.78 | AH95: 57056.78 | AI95: SIM | AJ95: 6014.2024/0006500-4 | AK95: 123203198 | AL95: FINALIZADO | AM95: FINALIZADO | AN95: SEM PENDÊNCIA | AP95: 6014.2025/0004023-2 | AQ95: FINALIZADO | AR95: FINALIZADO | AS95: FINALIZADO | AT95: FINALIZADO | AU95: 45911 | AV95: FINALIZADO | AW95: FINALIZADO | AX95: 45917 | AY95: 45917 | AZ95: 45952 | BA95: LIBERADO DEMOLIÇÃO | BB95: FINALIZADO | BC95: =IF(AY95-KG95=0,"",AY95-O95) -> 98 | BD95: =IF(AND(AI95<>"SIM",AI95="UH"),"AA","INDENIZAÇÃO") -> INDENIZAÇÃO | BE95: =IF(AND(AY95<>"AGUARDANDO",AY95<>"",N95="AUXÍLIO ALUGUEL ATÉ INDENIZAÇÃO"),"SIM","NÃO") -> NÃO | BF95: N/A | BG95: N/A | BH95: N/A | BI95: FINALIZADO | BJ95: FINALIZADO | BK95: 45937 | BL95: FINALIZADO | BM95: AGUARDANDO
A96: 83 | B96: JD. VITÓRIA | C96: FASE 1 - CÓRREGO | D96: -- | E96: -- | F96: 010/0015/B | G96: OCUPADO | H96: RESIDENCIAL | I96: PROPRIETÁRIO RESIDENTE | J96: WENDY MARIANA MONTEIRO DOS SANTOS | K96: 43.058.479-9 | L96: 422.794.188-19 | M96: CONCLUÍDO | N96: INDENIZAÇÃO | O96: 45819 | P96: N/A | Q96: N/A | R96: N/A | S96: N/A | T96: N/A | U96: N/A | V96: N/A | W96: N/A | X96: N/A | Y96: N/A | Z96: N/A | AB96: WENDY MARIANA MONTEIRO DOS SANTOS | AC96: 43.058.479-9 | AD96: 422.794.188-19 | AE96: PROPRIETÁRIO RESIDENTE | AF96: CONCLUÍDO | AG96: 22968 | AH96: 52968 | AI96: SIM | AJ96: 6014.2024/0006500-4 | AK96: 123203298 | AL96: FINALIZADO | AM96: FINALIZADO | AN96: SEM PENDÊNCIA | AP96: 6014.2025/0004025-9 | AQ96: FINALIZADO | AR96: FINALIZADO | AS96: FINALIZADO | AT96: FINALIZADO | AU96: 45911 | AV96: FINALIZADO | AW96: FINALIZADO | AX96: 45917 | AY96: 45917 | AZ96: 45952 | BA96: LIBERADO DEMOLIÇÃO | BB96: FINALIZADO | BC96: =IF(AY96-KG96=0,"",AY96-O96) -> 98 | BD96: =IF(AND(AI96<>"SIM",AI96="UH"),"AA","INDENIZAÇÃO") -> INDENIZAÇÃO | BE96: =IF(AND(AY96<>"AGUARDANDO",AY96<>"",N96="AUXÍLIO ALUGUEL ATÉ INDENIZAÇÃO"),"SIM","NÃO") -> NÃO | BF96: N/A | BG96: N/A | BH96: N/A | BI96: FINALIZADO | BJ96: FINALIZADO | BK96: 45937 | BL96: FINALIZADO | BM96: AGUARDANDO
A97: 84 | B97: JD. VITÓRIA | C97: FASE 1 - CÓRREGO | D97: -- | E97: -- | F97: 010/0016/B | G97: OCUPADO | H97: RESIDENCIAL | I97: PROPRIETÁRIO RESIDENTE | J97: CRISTIANE DE JESUS SOARES | K97: 382532181 | L97: 32136750836 | AJ97: 6014.2024/0006500-4 | BC97: =IF(AY97-KG97=0,"",AY97-O97) | BD97: =IF(AND(AI97<>"SIM",AI97="UH"),"AA","INDENIZAÇÃO") -> INDENIZAÇÃO | BE97: =IF(AND(AY97<>"AGUARDANDO",AY97<>"",N97="AUXÍLIO ALUGUEL ATÉ INDENIZAÇÃO"),"SIM","NÃO") -> NÃO
A98: 85 | B98: JD. VITÓRIA | C98: FASE 1 - CÓRREGO | D98: -- | E98: -- | F98: 010/0017/B | G98: OCUPADO | H98: RESIDENCIAL | I98: PROPRIETÁRIO RESIDENTE | J98: CRISTINA SANTOS RAMOS | K98: 29.078.255-7 | L98: 271.855.188-73 | AJ98: 6014.2024/0006500-4 | BC98: =IF(AY98-KG98=0,"",AY98-O98) | BD98: =IF(AND(AI98<>"SIM",AI98="UH"),"AA","INDENIZAÇÃO") -> INDENIZAÇÃO | BE98: =IF(AND(AY98<>"AGUARDANDO",AY98<>"",N98="AUXÍLIO ALUGUEL ATÉ INDENIZAÇÃO"),"SIM","NÃO") -> NÃO
A99: 86 | B99: JD. VITÓRIA | C99: FASE 1 - CÓRREGO | D99: -- | E99: -- | F99: 010/0018/A | G99: OCUPADO | H99: MISTO | I99: PROPRIETÁRIO RESIDENTE | J99: MARIA JOSÉ DA SILVA LEITE SCHINEIDER | K99: 30.199.688-X | L99: 254.784.018-97 | M99: CONCLUÍDO | N99: INDENIZAÇÃO | O99: 45819 | P99: N/A | Q99: N/A | R99: N/A | S99: N/A | T99: N/A | U99: N/A | V99: N/A | W99: N/A | X99: N/A | Y99: N/A | Z99: N/A | AB99: MARIA JOSÉ DA SILVA LEITE SCHINEIDER | AC99: 30.199.688-X | AD99: 254.784.018-97 | AE99: PROPRIETÁRIO RESIDENTE | AF99: CONCLUÍDO | AG99: 47150.49 | AH99: 60000 | AI99: SIM | AJ99: 6014.2024/0006500-4 | AK99: 123203596 | AL99: FINALIZADO | AM99: FINALIZADO | AN99: SEM PENDÊNCIA | AP99: 6014.2025/0004205-7 | AQ99: FINALIZADO | AR99: FINALIZADO | AS99: FINALIZADO | AT99: FINALIZADO | AU99: 45909 | AV99: FINALIZADO | AW99: FINALIZADO | AX99: 45915 | AY99: 45915 | AZ99: 45965 | BA99: LIBERADO DEMOLIÇÃO | BB99: FINALIZADO | BC99: =IF(AY99-KG99=0,"",AY99-O99) -> 96 | BD99: =IF(AND(AI99<>"SIM",AI99="UH"),"AA","INDENIZAÇÃO") -> INDENIZAÇÃO | BE99: =IF(AND(AY99<>"AGUARDANDO",AY99<>"",N99="AUXÍLIO ALUGUEL ATÉ INDENIZAÇÃO"),"SIM","NÃO") -> NÃO | BF99: N/A | BG99: N/A | BH99: N/A | BI99: FINALIZADO | BJ99: FINALIZADO | BK99: 45937 | BL99: FINALIZADO | BM99: AGUARDANDO
A100: 87 | B100: JD. VITÓRIA | C100: FASE 1 - CÓRREGO | D100: -- | E100: -- | F100: 010/0018/B | G100: OCUPADO | H100: RESIDENCIAL | I100: PROPRIETÁRIO RESIDENTE | J100: CLAUDIA TALITA DA SILVA SCHINIDER | K100: 57.552.269-4 | L100: 522.477.468-37 | M100: CONCLUÍDO | N100: INDENIZAÇÃO | O100: 45819 | P100: N/A | Q100: N/A | R100: N/A | S100: N/A | T100: N/A | U100: N/A | V100: N/A | W100: N/A | X100: N/A | Y100: N/A | Z100: N/A | AB100: CLAUDIA TALITA DA SILVA SCHINIDER | AC100: 57.552.269-4 | AD100: 522.477.468-37 | AE100: PROPRIETÁRIO RESIDENTE | AF100: CONCLUÍDO | AG100: 9207.33 | AH100: 39207.33 | AI100: SIM | AJ100: 6014.2024/0006500-4 | AK100: 123205888 | AL100: FINALIZADO | AM100: FINALIZADO | AN100: SEM PENDÊNCIA | AP100: 6014.2025/0004207-3 | AQ100: FINALIZADO | AR100: FINALIZADO | AS100: FINALIZADO | AT100: FINALIZADO | AU100: 45909 | AV100: FINALIZADO | AW100: FINALIZADO | AX100: 45915 | AY100: 45915 | AZ100: 45965 | BA100: LIBERADO DEMOLIÇÃO | BB100: FINALIZADO | BC100: =IF(AY100-KG100=0,"",AY100-O100) -> 96 | BD100: =IF(AND(AI100<>"SIM",AI100="UH"),"AA","INDENIZAÇÃO") -> INDENIZAÇÃO | BE100: =IF(AND(AY100<>"AGUARDANDO",AY100<>"",N100="AUXÍLIO ALUGUEL ATÉ INDENIZAÇÃO"),"SIM","NÃO") -> NÃO | BF100: N/A | BG100: N/A | BH100: N/A | BI100: FINALIZADO | BJ100: FINALIZADO | BK100: 45937 | BL100: FINALIZADO | BM100: AGUARDANDO
A101: 88 | B101: JD. VITÓRIA | C101: FASE 1 - CÓRREGO | D101: -- | E101: -- | F101: 010/0018/C | G101: OCUPADO | H101: RESIDENCIAL | I101: PROPRIETÁRIO RESIDENTE | J101: ESMERALDA DA SILVA SCHINIDER | K101: 57.552.741-9 | L101: 522.478.368-28 | M101: CONCLUÍDO | N101: INDENIZAÇÃO | O101: 45819 | P101: N/A | Q101: N/A | R101: N/A | S101: N/A | T101: N/A | U101: N/A | V101: N/A | W101: N/A | X101: N/A | Y101: N/A | Z101: N/A | AB101: ESMERALDA DA SILVA SCHINIDER | AC101: 57.552.741-9 | AD101: 522.478.368-28 | AE101: PROPRIETÁRIO RESIDENTE | AF101: CONCLUÍDO | AG101: 20707.27 | AH101: 50707.27 | AI101: SIM | AJ101: 6014.2024/0006500-4 | AK101: 123521384 | AL101: FINALIZADO | AM101: FINALIZADO | AN101: SEM PENDÊNCIA | AP101: 6014.2025/0004208-1 | AQ101: FINALIZADO | AR101: FINALIZADO | AS101: FINALIZADO | AT101: FINALIZADO | AU101: 45909 | AV101: FINALIZADO | AW101: FINALIZADO | AX101: 45915 | AY101: 45915 | AZ101: 45965 | BA101: LIBERADO DEMOLIÇÃO | BB101: FINALIZADO | BC101: =IF(AY101-KG101=0,"",AY101-O101) -> 96 | BD101: =IF(AND(AI101<>"SIM",AI101="UH"),"AA","INDENIZAÇÃO") -> INDENIZAÇÃO | BE101: =IF(AND(AY101<>"AGUARDANDO",AY101<>"",N101="AUXÍLIO ALUGUEL ATÉ INDENIZAÇÃO"),"SIM","NÃO") -> NÃO | BF101: N/A | BG101: N/A | BH101: N/A | BI101: FINALIZADO | BJ101: FINALIZADO | BK101: 45937 | BL101: FINALIZADO | BM101: AGUARDANDO
A102: 89 | B102: JD. VITÓRIA | C102: FASE 1 - CÓRREGO | D102: -- | E102: -- | F102: 010/0019/A | G102: OCUPADO | H102: RESIDENCIAL | I102: PROPRIETÁRIO RESIDENTE | J102: MANOEL LUÍS GOMES | K102: 64.913.278-6 | L102: 193.458.588-22 | M102: CONCLUÍDO | N102: INDENIZAÇÃO | O102: 46097 | P102: N/A | Q102: N/A | R102: N/A | S102: N/A | T102: N/A | U102: N/A | V102: N/A | W102: N/A | X102: N/A | Y102: N/A | Z102: N/A | AB102: MANOEL LUÍS GOMES | AC102: 64.913.278-6 | AD102: 193.458.588-22 | AE102: PROPRIETÁRIO RESIDENTE | AF102: CONCLUÍDO | AG102: 5958.99 | AH102: 35958.99 | AI102: SIM | AJ102: 6014.2024/0006500-4 | AK102: 152799980 | AL102: FINALIZADO | AM102: FINALIZADO | AN102: SEM PENDÊNCIA | AP102: 6014.2026/0002361-5 | AQ102: FINALIZADO | AR102: FINALIZADO | AS102: FINALIZADO | AT102: FINALIZADO | AU102: 46174 | AV102: FINALIZADO | AW102: FINALIZADO | AX102: 46183 | AY102: 46183 | AZ102: AGUARDANDO | BA102: LIBERADO DEMOLIÇÃO | BB102: FINALIZADO | BC102: =IF(AY102-KG102=0,"",AY102-O102) -> 86 | BD102: =IF(AND(AI102<>"SIM",AI102="UH"),"AA","INDENIZAÇÃO") -> INDENIZAÇÃO | BE102: =IF(AND(AY102<>"AGUARDANDO",AY102<>"",N102="AUXÍLIO ALUGUEL ATÉ INDENIZAÇÃO"),"SIM","NÃO") -> NÃO | BF102: N/A | BG102: N/A | BH102: N/A | BI102: AGUARDANDO ELABORAÇÃO
A103: 90 | B103: JD. VITÓRIA | C103: FASE 1 - CÓRREGO | D103: -- | E103: -- | F103: 010/0019/A | G103: OCUPADO | H103: RESIDENCIAL | I103: COABITANTE | J103: MINE SENE GUIAPARREDA GOMES | AJ103: 6014.2024/0006500-4 | BC103: =IF(AY103-KG103=0,"",AY103-O103) | BD103: =IF(AND(AI103<>"SIM",AI103="UH"),"AA","INDENIZAÇÃO") -> INDENIZAÇÃO | BE103: =IF(AND(AY103<>"AGUARDANDO",AY103<>"",N103="AUXÍLIO ALUGUEL ATÉ INDENIZAÇÃO"),"SIM","NÃO") -> NÃO
...

Sheet EMAIL
E2: PUBLICAÇÃO DOC
E3: PREVISÃO PAGAMENTO | F3: 024/0030/B | H3: 029/0024/C
A4: ÁREA | B4: SELO | C4: TITULAR | D4: PREVISÃO PAGAMENTO | E4: CONFIRMAÇÃO PAGAMENTO | F4: 024/0041/A | H4: 029/0023/E
A5: JD. VITÓRIA | B5: 016/0026/B | C5: LUZINETE GUILHERME ALVES FERREIRA | D5: 46259 | F5: 029/0007/A | H5: 029/0022/B
F6: 024/0052/A | H6: 031/0033/Q
F7: 024/0070/E | H7: 031/0022/E
F8: 024/0079/C | H8: 031/0020/C
F9: 024/0088/B | H9: 029/0069/D
F10: 024/0099/A | H10: 031/0033/K
F11: 024/0102/D | H11: 029/0016/B
F12: 024/0105/B | H12: 024/0099/A
A14: JD. VITÓRIA | B14: 010/0019/A | C14: MANOEL LUÍS GOMES | D14: 46183 | F14: 029/0007/B | H14: 031/0039/C
A15: JD. VITÓRIA | B15: 010/0020/A | C15: SIONE PINHEIRO ROSA | D15: 46183 | F15: 029/0016/B | H15: 029/0081/A
F16: 029/0022/B | H16: 024/0052/A
F17: 029/0023/E | H17: 029/0035/B
F18: 029/0024/C | H18: 029/0027/A
F19: 029/0035/B | H19: 029/0069/B
A20: JD. VITÓRIA | B20: 015/0022/A | C20: GABRIEL FREITAS DA SILVA | D20: 45915 | F20: 029/0036/F | H20: 031/0028/D
A21: JD. VITÓRIA | B21: 016/0005/A | C21: RAIMUNDO DE OLIVEIRA | D21: 45915 | F21: 029/0039/B | H21: 029/0067/A
A22: JD. VITÓRIA | B22: 016/0010/A | C22: MONICA DE MELO LINO | D22: 45915 | F22: 029/0045/A | H22: 029/0007/A
A23: JD. VITÓRIA | B23: 016/0019/B | C23: MAIARA RIBEIRO DIAS | D23: 45915 | F23: 029/0061/A | H23: 029/0070/C
A24: JD. VITÓRIA | B24: 016/0019/C | C24: FRANCISCO PAULINO DIAS | D24: 45915 | F24: 029/0064/A | H24: 029/0007/B
A25: JD. VITÓRIA | B25: 016/0021/A | C25: DANIELLE DOS ANJOS RIPARDO | D25: 45915 | F25: 029/0064/F | H25: 029/0070/B
A26: JD. VITÓRIA | B26: 016/0021/B | C26: JOSÉ MARIA RIPARDO | D26: 45916 | F26: 029/0066/A | H26: 029/0045/A
A27: JD. VITÓRIA | B27: 016/0024/A | C27: MICAELA ARAGÃO FELIX DA SILVA | D27: 45915 | F27: 029/0066/B | H27: 024/0102/D
A28: JD. VITÓRIA | B28: 016/0025/A | C28: CLAUDIANA BISPO DOS SANTOS | D28: 45915 | F28: 029/0066/E | H28: 024/0041/A
A29: JD. VITÓRIA | B29: 016/0025/B | C29: KAUÊ DOS SANTOS SANTANA | D29: 45915 | F29: 029/0067/A | H29: 031/0035/A
A30: JD. VITÓRIA | B30: 016/0027/A | C30: JANAINA GOMES DE OLIVEIRA | D30: 45915 | F30: 029/0067/F | H30: 031/0067/B
A31: JD. VITÓRIA | B31: 016/0031/A | C31: FERNANDA DE PONTES | D31: 45917 | F31: 029/0069/B | H31: 024/0077/B
F32: 029/0069/C | H32: 033/0016/C
F33: 029/0069/D | H33: 029/0069/C
F34: 029/0070/B | H34: 029/0061/A
F35: 029/0070/C | H35: 029/0066/B
F36: 029/0071/B | H36: 029/0071/D
F37: 029/0071/D | H37: 031/0058/A
F38: 029/0071/E | H38: 029/0036/F
F39: 029/0080/E | H39: 031/0067/A
F40: 029/0081/A | H40: 031/0028/L
F41: 029/0083/A | H41: 024/0105/A
A42: PARAISÓPOLIS/ANTONICO | B42: 025/0006/L | C42: DENISE SILVA COSTA | D42: 44840 | F42: 029/0085/G | H42: 029/0064/F
A43: PARAISÓPOLIS/ANTONICO | B43: 025/0009/A | C43: ALEANE DOS SANTOS DE PAULA | F43: 029/0086/B | H43: 031/0025/A
A44: PARAISÓPOLIS/ANTONICO | B44: 025/0009/F | C44: LARISSA MONIQUE LEITE | F44: 031/0004/C | H44: 024/0051/A
A45: PARAISÓPOLIS/ANTONICO | B45: 025/0009/J | C45: VANDERLEIA FERREIRA DA CRUZ | F45: 031/0014/A | H45: 024/0030/B
A46: PARAISÓPOLIS/ANTONICO | B46: 025/0010/B | C46: ANA CLÁUDIA RODRIGUES DE SOUSA | D46: 44992 | F46: 031/0015/D | H46: 029/0083/A
A47: PARAISÓPOLIS/ANTONICO | B47: 025/0010/C | C47: VITOR TRINDADE ROCHA | D47: 45013 | F47: 031/0020/B | H47: 031/0004/C
A48: PARAISÓPOLIS/ANTONICO | B48: 025/0013/A | C48: MIRIAM CAMILO DE ANDRADE | D48: 45013 | F48: 031/0020/C | H48: 031/0014/A
A49: PARAISÓPOLIS/ANTONICO | B49: 025/0013/C | C49: ALEX JESUS DE SOUSA | D49: N/A | F49: 031/0022/B | H49: 033/0029/B
A50: PARAISÓPOLIS/ANTONICO | B50: 025/0016/E | C50: CARLOS SANTOS CASTRO | D50: 45013 | F50: 031/0022/E | H50: 029/0071/E
A51: PARAISÓPOLIS/ANTONICO | B51: 025/0018/F | C51: ANA CLAUDIA MARCIANO | D51: N/A | F51: 031/0025/A | H51: 031/0033/E
A52: PARAISÓPOLIS/ANTONICO | B52: 025/0019/A | C52: ANDRÉ LUIS DOS SANTOS | D52: N/A | F52: 031/0028/D | H52: 024/0070/E
A53: PARAISÓPOLIS/ANTONICO | B53: 025/0019/H | C53: GLÓRIA DE FÁTIMA SANTOS MATOS | D53: 44840 | F53: 031/0028/L | H53: 024/0079/C
A54: PARAISÓPOLIS/ANTONICO | B54: 025/0020/E | C54: DANIELLA DO NASCIMENTO JESUS | D54: 44816 | F54: 031/0031/B | H54: 031/0015/D
A55: PARAISÓPOLIS/ANTONICO | B55: 025/0020/F | C55: GIRLENE PEREIRA DO NASCIMENTO | F55: 031/0033/E | H55: 033/0030/A
A56: PARAISÓPOLIS/ANTONICO | B56: 025/0021/D | C56: AMANDA MARIA ALVES DA SILVA | D56: 44840 | F56: 031/0033/K | H56: 024/0041/B
A57: PARAISÓPOLIS/ANTONICO | B57: 025/0023/E | C57: FRANCISCA GABRIELA DE SOUZA | D57: 44862 | F57: 031/0033/Q | H57: 031/0020/B
A58: PARAISÓPOLIS/ANTONICO | B58: 025/0025/M | C58: EDUARDA DE SOUSA SILVA | D58: N/A | F58: 031/0035/A | H58: 031/0035/B
A59: PARAISÓPOLIS/ANTONICO | B59: 025/0031/B | C59: FRANCISCO MARCIO VIEIRA DO NASCIMENTO | D59: 44840 | F59: 031/0035/B | H59: 029/0085/G
A60: PARAISÓPOLIS/ANTONICO | B60: 027/0005/A | C60: DESIRÉE SANTOS DE MOURA | D60: 44889 | F60: 031/0039/C | H60: 031/0022/B
A61: PARAISÓPOLIS/ANTONICO | B61: 027/0005/F | C61: SILVIO IGOR DOS SANTOS COSTA | D61: 44922 | F61: 031/0058/A | H61: 029/0067/F
A62: PARAISÓPOLIS/ANTONICO | B62: 027/0005/G | C62: FABIOLA SILVA DE MELO | D62: 44961 | F62: 031/0067/A | H62: 024/0088/B
A63: PARAISÓPOLIS/ANTONICO | B63: 027/0005/H | C63: LUIS GUSTAVO COUTINHO DOS SANTOS | D63: 44840 | F63: 031/0067/B | H63: 029/0039/B
A64: PARAISÓPOLIS/ANTONICO | B64: 027/0008/D | C64: EDCARLOS BATISTA LIMA | D64: 44869 | F64: 033/0016/C
A65: PARAISÓPOLIS/ANTONICO | B65: 027/0010/A | C65: LUCILENE DOS SANTOS SILVA | D65: 44840 | F65: 033/0029/B
A66: PARAISÓPOLIS/ANTONICO | B66: 027/0014/D | C66: JOSILENE MARIA NASCIMENTO DA SILVA | D66: 44840 | F66: 033/0030/A
A67: PARAISÓPOLIS/ANTONICO | B67: 027/0014/E | C67: MARIA IRENE DA SILVA | D67: 44869
A68: PARAISÓPOLIS/ANTONICO | B68: 027/0014/F | C68: FRANCISCA DAS CHAGAS SOARES | D68: 44840
A69: PARAISÓPOLIS/ANTONICO | B69: 027/0014/G | C69: MARIA CÉLIA DA SILVA | D69: 44840
A70: PARAISÓPOLIS/ANTONICO | B70: 027/0014/H | C70: JOSEFA PEREIRA DE ARAÚJO CRUZ | D70: 44840
A71: PARAISÓPOLIS/ANTONICO | B71: 027/0016/B | C71: FRANCISCO DAS CHAGAS CASTRO | D71: 44840
A72: PARAISÓPOLIS/ANTONICO | B72: 027/0016/C | C72: MÁRCIO GOMES DA MOTA | D72: N/A
A73: PARAISÓPOLIS/ANTONICO | B73: 029/0018/A | C73: DANIELLE PATRICIA ALVES | D73: 44853
A74: PARAISÓPOLIS/ANTONICO | B74: 029/0024/D | C74: ISAILMA SILVA SOUZA | D74: 45148
A75: PARAISÓPOLIS/ANTONICO | B75: 029/0025/A | C75: RENATO FERNANDES DA SILVA
A76: PARAISÓPOLIS/ANTONICO | B76: 029/0036/L | C76: CLÉIA DAMASCENO | D76: 45013
A77: PARAISÓPOLIS/ANTONICO | B77: 029/0036/M | C77: LUCIANA PEREIRA DE SOUZA | D77: 44961
A78: PARAISÓPOLIS/ANTONICO | B78: 029/0036/N | C78: FERNANDO ARAUJO DA SILVA | D78: 44923
A79: PARAISÓPOLIS/ANTONICO | B79: 029/0036/O | C79: MARIA ANTONIA CARVALHO SAMPAIO SANTOS | D79: 45013
A80: PARAISÓPOLIS/ANTONICO | B80: 029/0042/A | C80: CARLOS DA SILVA BARBOSA | D80: 45148
A81: PARAISÓPOLIS/ANTONICO | B81: 029/0042/B | C81: DIRCEU DA SILVA BARBOSA
A82: PARAISÓPOLIS/ANTONICO | B82: 029/0054/E | C82: JADI DE JESUS SILVA
A83: PARAISÓPOLIS/ANTONICO | B83: 029/0066/C | C83: DAMIÃO DOS SANTOS MEDEIROS
A84: PARAISÓPOLIS/ANTONICO | B84: 029/0085/D | C84: JOSÉ GERALDO CARLOS DOS SANTOS
A85: PARAISÓPOLIS/ANTONICO | B85: 031/0006/C | C85: SILVANEIDE DE LIMA SOUZA
A86: PARAISÓPOLIS/ANTONICO | B86: 031/0009/A | C86: GABRIELA DAS DORES NASCIMENTO DE JESUS
A87: PARAISÓPOLIS/ANTONICO | B87: 031/0009/B | C87: SAMANTHA DAS DORES OLIVEIRA
A88: PARAISÓPOLIS/ANTONICO | B88: 031/0010/A | C88: JAÍLSON ALVES TELES | D88: 45056
A89: PARAISÓPOLIS/ANTONICO | B89: 031/0017/F | C89: CAMILA BERNARDO DA CRUZ SILVA | D89: 45013
A90: PARAISÓPOLIS/ANTONICO | B90: 031/0017/G | C90: NATÁLIA DE ALMEIDA DE BARROS | D90: 45097
A91: PARAISÓPOLIS/ANTONICO | B91: 031/0018/A | C91: ALEXANDRE DOS SANTOS RIBEIRO | D91: 44816
A92: PARAISÓPOLIS/ANTONICO | B92: 031/0023/B | C92: DANIELA GOMES DE CARVALHO
A93: PARAISÓPOLIS/ANTONICO | B93: 031/0023/C | C93: QUEZIANE ALVES DO NASCIMENTO | D93: N/A
A94: PARAISÓPOLIS/ANTONICO | B94: 031/0026/E | C94: VIVIANE DA SILVA ALMEIDA
A95: PARAISÓPOLIS/ANTONICO | B95: 031/0032/C | C95: ANTONIA CAMILA CASSIMIRO BARBOSA
A96: PARAISÓPOLIS/ANTONICO | B96: 031/0034/E | C96: DAMARYS BRITO DA SILVA | D96: 44877
A97: PARAISÓPOLIS/ANTONICO | B97: 031/0034/H | C97: GISELY MAIANA DE OLIVEIRA SANTOS | D97: 44876
A98: PARAISÓPOLIS/ANTONICO | B98: 031/0034/I | C98: LINA MARIA DA CONCEIÇÃO DE SOUSA | D98: 44910
A99: PARAISÓPOLIS/ANTONICO | B99: 031/0034/K | C99: VÂNIA DE OLIVEIRA | D99: 45148
A100: PARAISÓPOLIS/ANTONICO | B100: 031/0036/A | C100: MARISVALDO DE JESUS PEREIRA | D100: 45065
A101: PARAISÓPOLIS/ANTONICO | B101: 031/0053/A | C101: INGRIDES MORAIS DE ARAUJO FERNANDES | D101: 45049
A102: PARAISÓPOLIS/ANTONICO | B102: 031/0058/B | C102: JOSÉ VALDI DO NASCIMENTO | D102: 45065
...

Sheet Listas (não utilizar)
A1: Área | B1: Condomínio | C1: Bloco | D1: Apartamento | E1: SITAH / CAIXA | F1: Status CAIXA | G1: Adequacao Imovel | H1: Renúncia | I1: Pendência | J1: Pendências / Reprovados caixa
A2: ALTO DA ALEGRIA | B2: AVILA | C2: 1 | D2: 101 | E2: AGENDADO | F2: APROVADO | G2: NÃO | H2: NÃO | I2: CRAS | J2: RENDA SUPERIOR
A3: ALTO DA ALEGRIA (OBRAS) | B3: BARCELONA | C3: 2 | D3: 102 | E3: AGUARDANDO OFICIO | F3: REPROVADO | G3: FÍSICA | H3: RENDA | I3: CRAS + DOCUMENTOS | J3: CADMUT
A4: ALTO DA ALEGRIA (RESERVA) | B4: BILBAO | C4: 3 | D4: 103 | E4: ATENDIMENTO CANCELADO | F4: PENDENCIA | G4: VISUAL | H4: CADIN | I4: DOCUMENTOS | J4: CADIN
A5: ANTERO GOMES | B5: CEUTA | C5: 4 | D5: 104 | E5: CADMUT | F5: SEM DOSSIE | G5: INTELECTUAL | H5: ESTADO CIVIL | I5: CADIN
A6: CANTINHO DO CEU / GAIVOTAS | B6: IBIZA | C6: 5 | D6: 201 | E6: CHACARA DO CONDE | G6: AUDITIVA | H6: SEPARACAO | I6: CRAS + CADIN
A7: CANTINHO DO CEU / OBRAS | B7: LEAO | C7: 6 | D7: 202 | E7: CONFLITO | G7: NANISMO | I7: R.LI.AV.
A8: CASTRO ALVES | B8: MADRID | C8: 7 | D8: 203 | E8: ENVIADO CAIXA | I8: IEME
A9: COCAIA | B9: MELILLA | C9: 8 | D9: 204 | E9: FALECEU
A10: ERUNDINA | B10: PAMPLONA | C10: 9 | D10: 301 | E10: FALTANTE DOSSIÊ
A11: FUMACA | B11: SALAMANCA | C11: 10 | D11: 302 | E11: HABISP ACERTO DE ÁREA
A12: GUAICURI (OBRAS) | B12: TERUEL | C12: 11 | D12: 303 | E12: HABISP AGUARDANDO CRÍTICA
A13: GUAICURI / CIDADE JULIA | B13: VALENCIA | C13: 12 | D13: 304 | E13: HABISP PEND DE ATUALIZ CADASTRAL
A14: JARDIM MIRNA | B14: VALVERDE | C14: 13 | D14: 401 | E14: INDENIZACAO
A15: JARDIM SELMA II | B15: VITORIA | C15: 14 | D15: 402 | E15: PENDENCIA
A16: JARDIM TUBO | C16: 15 | D16: 403 | E16: PERMUTA
A17: LEBLON | D17: 404 | E17: PESQUISA SMADS
A18: MARGINAL DOIS / FUNDAO | D18: 501 | E18: REANALISE
A19: MATA VIRGEM / JD ELDORADO | D19: 502 | E19: RECLUSO
A20: NEBLINA | D20: 503 | E20: RELATÓRIO SOCIAL
A21: NORONHA | D21: 504 | E21: RENDA SUPERIOR
A22: NOVA GRAJAU | E22: RESISTENTE
A23: NOVA MARILDA | E23: TROCA DE TITULARIDADE
A24: NOVA VARGINHA
A25: PABREU / PRAINHA
A26: PENDENCIA GABINETE
A27: PILAO / APURA
A28: PILAO / DOIS
A29: PILAO / PAULISTAS
A30: SANTA AMELIA
A31: VALE VERDE / MONTE VERDE
A32: VILA BREJINHO
A33: VILA NASCENTE
A34: ZR / COSTA BRANCA
A35: VILA RUBI

Sheet QUANT COND
A1: CONDOMINIOS | B1: QUANT
A2: AVILA | B2: =COUNTIF(#REF!,'QUANT COND'!A2) -> #REF!
A3: BARCELONA | B3: =COUNTIF(#REF!,'QUANT COND'!A3) -> #REF!
A4: BILBAO | B4: =COUNTIF(#REF!,'QUANT COND'!A4) -> #REF!
A5: CEUTA | B5: =COUNTIF(#REF!,'QUANT COND'!A5) -> #REF!
A6: IBIZA | B6: =COUNTIF(#REF!,'QUANT COND'!A6) -> #REF!
A7: LEAO | B7: =COUNTIF(#REF!,'QUANT COND'!A7) -> #REF!
A8: MADRID | B8: =COUNTIF(#REF!,'QUANT COND'!A8) -> #REF!
A9: MELILLA | B9: =COUNTIF(#REF!,'QUANT COND'!A9) -> #REF!
A10: PAMPLONA | B10: =COUNTIF(#REF!,'QUANT COND'!A10) -> #REF!
A11: SALAMANCA | B11: =COUNTIF(#REF!,'QUANT COND'!A11) -> #REF!
A12: TERUEL | B12: =COUNTIF(#REF!,'QUANT COND'!A12) -> #REF!
A13: VALENCIA | B13: =COUNTIF(#REF!,'QUANT COND'!A13) -> #REF!
... A15: VITORIA | B15: =COUNTIF(#REF!,'QUANT COND'!A15) -> #REF!

Sheet OFÍCIOS
A1: PLANILHA DE CONFRONTO OFÍCIOS DE INDICAÇÃO COM ENVIADOS CAIXA ECONÔMICA FEDERAL - CEF
A2: TITULAR | B2: CPF | C2: Cônjuge | D2: CPF | E2: OFÍCIO | F2: DATA | G2: STATUS CEF | H2: DATA ENVIO CAIXA | I2: DUPLICIDADE OFÍCIO | J2: DATA | K2: DATA ENVIO CAIXA | L2: OFÍCIO DE INDICAÇÃO | M2: DATA OFÍCIO INDICAÇÃO | O2: NR OFICIO | P2: QUANT | Q2: APROV | R2: REPROV | S2: PEND | T2: SEM STATUS (ANÁLISE) | Y2: CEF BD | Z2: CEF OFICIOS | AA2: CEF PLANILHA
A3: ABEL MEDEIROS FILHO | B3: 27140979871 | E3: 1128 | F3: 42972 | G3: APROVADO | H3: 42979 | O3: 810 | P3: =COUNTIF(OFÍCIOS!E:E,O3) -> 156 | Q3: =COUNTIFS(OFÍCIOS!$E:$E,$O3,OFÍCIOS!$G:$G,"APROVADO") -> 149 | R3: =COUNTIFS(OFÍCIOS!$E:$E,$O3,OFÍCIOS!$G:$G,"REPROVADO") -> 3 | S3: =COUNTIFS(OFÍCIOS!$E:$E,$O3,OFÍCIOS!$G:$G,"PENDENCIA") -> 2 | T3: =COUNTIFS(OFÍCIOS!$E:$E,$O3,OFÍCIOS!$G:$G,"") -> 2 | U3: =SUM(Q3:T3) -> 156 | X3: FEITOS | Y3: 1850 | Z3: 1827 | AA3: =SUM(AA4:AA7) -> 1615
A4: ABELINA FERREIRA DOS SANTOS | B4: 39200633846 | O4: 1417 | P4: =COUNTIF(OFÍCIOS!E:E,O4) -> 42 | Q4: =COUNTIFS(OFÍCIOS!$E:$E,$O4,OFÍCIOS!$G:$G,"APROVADO") -> 36 | R4: =COUNTIFS(OFÍCIOS!$E:$E,$O4,OFÍCIOS!$G:$G,"REPROVADO") -> 3 | S4: =COUNTIFS(OFÍCIOS!$E:$E,$O4,OFÍCIOS!$G:$G,"PENDENCIA") -> 3 | T4: =COUNTIFS(OFÍCIOS!$E:$E,$O4,OFÍCIOS!$G:$G,"") -> 0 | U4: =SUM(Q4:T4) -> 42 | X4: APROVADOS | Y4: 1517 | Z4: 1427 | AA4: 1559
A5: ABIGAIL DE OLIVEIRA PAULINO | B5: 75489104872 | E5: 1752 | F5: 43051 | G5: APROVADO | H5: 43089 | L5: 1759 | O5: 1359 | P5: =COUNTIF(OFÍCIOS!E:E,O5) -> 14 | Q5: =COUNTIFS(OFÍCIOS!$E:$E,$O5,OFÍCIOS!$G:$G,"APROVADO") -> 13 | R5: =COUNTIFS(OFÍCIOS!$E:$E,$O5,OFÍCIOS!$G:$G,"REPROVADO") -> 1 | S5: =COUNTIFS(OFÍCIOS!$E:$E,$O5,OFÍCIOS!$G:$G,"PENDENCIA") -> 0 | T5: =COUNTIFS(OFÍCIOS!$E:$E,$O5,OFÍCIOS!$G:$G,"") -> 0 | U5: =SUM(Q5:T5) -> 14 | X5: REPROVADOS | Y5: 73 | Z5: 79 | AA5: 28
A6: ABILIO OLIVEIRA SANTOS | B6: 43286003620 | O6: 1350 | P6: =COUNTIF(OFÍCIOS!E:E,O6) -> 79 | Q6: =COUNTIFS(OFÍCIOS!$E:$E,$O6,OFÍCIOS!$G:$G,"APROVADO") -> 75 | R6: =COUNTIFS(OFÍCIOS!$E:$E,$O6,OFÍCIOS!$G:$G,"REPROVADO") -> 3 | S6: =COUNTIFS(OFÍCIOS!$E:$E,$O6,OFÍCIOS!$G:$G,"PENDENCIA") -> 0 | T6: =COUNTIFS(OFÍCIOS!$E:$E,$O6,OFÍCIOS!$G:$G,"") -> 1 | U6: =SUM(Q6:T6) -> 79 | X6: PENDENCIAS | Y6: 36 | Z6: 32 | AA6: 11
A7: ABRAHAO SANTOS SILVA | O7: 1343 | P7: =COUNTIF(OFÍCIOS!E:E,O7) -> 6 | Q7: =COUNTIFS(OFÍCIOS!$E:$E,$O7,OFÍCIOS!$G:$G,"APROVADO") -> 5 | R7: =COUNTIFS(OFÍCIOS!$E:$E,$O7,OFÍCIOS!$G:$G,"REPROVADO") -> 0 | S7: =COUNTIFS(OFÍCIOS!$E:$E,$O7,OFÍCIOS!$G:$G,"PENDENCIA") -> 0 | T7: =COUNTIFS(OFÍCIOS!$E:$E,$O7,OFÍCIOS!$G:$G,"") -> 1 | U7: =SUM(Q7:T7) -> 6 | X7: SS / ANALISE | Y7: 224 | Z7: 275 | AA7: 17
A8: ADAIR DA SILVA BARROS | B8: 97443271620 | E8: 1106 | F8: 42965 | G8: APROVADO | H8: 42978 | O8: 1267 | P8: =COUNTIF(OFÍCIOS!E:E,O8) -> 34 | Q8: =COUNTIFS(OFÍCIOS!$E:$E,$O8,OFÍCIOS!$G:$G,"APROVADO") -> 28 | R8: =COUNTIFS(OFÍCIOS!$E:$E,$O8,OFÍCIOS!$G:$G,"REPROVADO") -> 5 | S8: =COUNTIFS(OFÍCIOS!$E:$E,$O8,OFÍCIOS!$G:$G,"PENDENCIA") -> 1 | T8: =COUNTIFS(OFÍCIOS!$E:$E,$O8,OFÍCIOS!$G:$G,"") -> 0 | U8: =SUM(Q8:T8) -> 34
A9: ADALBERTO CARVALHO DE OLIVEIRA | B9: 98058690597 | E9: 423 | F9: 43182 | G9: APROVADO | O9: 1262 | P9: =COUNTIF(OFÍCIOS!E:E,O9) -> 8 | Q9: =COUNTIFS(OFÍCIOS!$E:$E,$O9,OFÍCIOS!$G:$G,"APROVADO") -> 7 | R9: =COUNTIFS(OFÍCIOS!$E:$E,$O9,OFÍCIOS!$G:$G,"REPROVADO") -> 1 | S9: =COUNTIFS(OFÍCIOS!$E:$E,$O9,OFÍCIOS!$G:$G,"PENDENCIA") -> 0 | T9: =COUNTIFS(OFÍCIOS!$E:$E,$O9,OFÍCIOS!$G:$G,"") -> 0 | U9: =SUM(Q9:T9) -> 8
A10: ADALBERTO CAVALCANTE DOS SANTOS | B10: 38088438888 | O10: 1106 | P10: =COUNTIF(OFÍCIOS!E:E,O10) -> 78 | Q10: =COUNTIFS(OFÍCIOS!$E:$E,$O10,OFÍCIOS!$G:$G,"APROVADO") -> 73 | R10: =COUNTIFS(OFÍCIOS!$E:$E,$O10,OFÍCIOS!$G:$G,"REPROVADO") -> 5 | S10: =COUNTIFS(OFÍCIOS!$E:$E,$O10,OFÍCIOS!$G:$G,"PENDENCIA") -> 0 | T10: =COUNTIFS(OFÍCIOS!$E:$E,$O10,OFÍCIOS!$G:$G,"") -> 0 | U10: =SUM(Q10:T10) -> 78
A11: ADALMA MOREIRA DA ROCHA | B11: 26939799869 | E11: 573 | F11: 43224 | O11: 1128 | P11: =COUNTIF(OFÍCIOS!E:E,O11) -> 92 | Q11: =COUNTIFS(OFÍCIOS!$E:$E,$O11,OFÍCIOS!$G:$G,"APROVADO") -> 91 | R11: =COUNTIFS(OFÍCIOS!$E:$E,$O11,OFÍCIOS!$G:$G,"REPROVADO") -> 1 | S11: =COUNTIFS(OFÍCIOS!$E:$E,$O11,OFÍCIOS!$G:$G,"PENDENCIA") -> 0 | T11: =COUNTIFS(OFÍCIOS!$E:$E,$O11,OFÍCIOS!$G:$G,"") -> 0 | U11: =SUM(Q11:T11) -> 92
A12: ADAMILTON PEREIRA DA SILVA ( ALANA ) | B12: 34470559873 | E12: 292 | F12: 43168 | G12: APROVADO | H12: 43182 | L12: 318 | O12: 1214 | P12: =COUNTIF(OFÍCIOS!E:E,O12) -> 76 | Q12: =COUNTIFS(OFÍCIOS!$E:$E,$O12,OFÍCIOS!$G:$G,"APROVADO") -> 71 | R12: =COUNTIFS(OFÍCIOS!$E:$E,$O12,OFÍCIOS!$G:$G,"REPROVADO") -> 3 | S12: =COUNTIFS(OFÍCIOS!$E:$E,$O12,OFÍCIOS!$G:$G,"PENDENCIA") -> 0 | T12: =COUNTIFS(OFÍCIOS!$E:$E,$O12,OFÍCIOS!$G:$G,"") -> 2 | U12: =SUM(Q12:T12) -> 76
A13: ADAO MENDES AGOSTINHO | B13: 14369564808 | O13: 1241 | P13: =COUNTIF(OFÍCIOS!E:E,O13) -> 33 | Q13: =COUNTIFS(OFÍCIOS!$E:$E,$O13,OFÍCIOS!$G:$G,"APROVADO") -> 32 | R13: =COUNTIFS(OFÍCIOS!$E:$E,$O13,OFÍCIOS!$G:$G,"REPROVADO") -> 0 | S13: =COUNTIFS(OFÍCIOS!$E:$E,$O13,OFÍCIOS!$G:$G,"PENDENCIA") -> 1 | T13: =COUNTIFS(OFÍCIOS!$E:$E,$O13,OFÍCIOS!$G:$G,"") -> 0 | U13: =SUM(Q13:T13) -> 33
A14: ADEGMARIO DOS SANTOS | B14: 39544185844 | E14: 810 | F14: 42915 | G14: APROVADO | H14: 42921 | L14: 568-17 | O14: 1422 | P14: =COUNTIF(OFÍCIOS!E:E,O14) -> 7 | Q14: =COUNTIFS(OFÍCIOS!$E:$E,$O14,OFÍCIOS!$G:$G,"APROVADO") -> 7 | R14: =COUNTIFS(OFÍCIOS!$E:$E,$O14,OFÍCIOS!$G:$G,"REPROVADO") -> 0 | S14: =COUNTIFS(OFÍCIOS!$E:$E,$O14,OFÍCIOS!$G:$G,"PENDENCIA") -> 0 | T14: =COUNTIFS(OFÍCIOS!$E:$E,$O14,OFÍCIOS!$G:$G,"") -> 0 | U14: =SUM(Q14:T14) -> 7
A15: ADEILDA GABRIELA CAITANO SILVA | B15: 38772276860 | C15: LUCIANO MANOEL DA SILVA | D15: 3808243457 | O15: 1439 | P15: =COUNTIF(OFÍCIOS!E:E,O15) -> 16 | Q15: =COUNTIFS(OFÍCIOS!$E:$E,$O15,OFÍCIOS!$G:$G,"APROVADO") -> 14 | R15: =COUNTIFS(OFÍCIOS!$E:$E,$O15,OFÍCIOS!$G:$G,"REPROVADO") -> 1 | S15: =COUNTIFS(OFÍCIOS!$E:$E,$O15,OFÍCIOS!$G:$G,"PENDENCIA") -> 1 | T15: =COUNTIFS(OFÍCIOS!$E:$E,$O15,OFÍCIOS!$G:$G,"") -> 0 | U15: =SUM(Q15:T15) -> 16
A16: ADEILDA RODRIGUES DE OLIVEIRA | B16: 21538837846 | C16: PEDRO LUIZ SANTOS OLIVEIRA | D16: 94203180520 | E16: 810 | F16: 42915 | G16: APROVADO | H16: 42921 | L16: 568-17 | O16: 1451 | P16: =COUNTIF(OFÍCIOS!E:E,O16) -> 4 | Q16: =COUNTIFS(OFÍCIOS!$E:$E,$O16,OFÍCIOS!$G:$G,"APROVADO") -> 3 | R16: =COUNTIFS(OFÍCIOS!$E:$E,$O16,OFÍCIOS!$G:$G,"REPROVADO") -> 1 | S16: =COUNTIFS(OFÍCIOS!$E:$E,$O16,OFÍCIOS!$G:$G,"PENDENCIA") -> 0 | T16: =COUNTIFS(OFÍCIOS!$E:$E,$O16,OFÍCIOS!$G:$G,"") -> 0 | U16: =SUM(Q16:T16) -> 4
A17: ADEILDO ADELINO DE CARVALHO | B17: 57455392591 | O17: 1470 | P17: =COUNTIF(OFÍCIOS!E:E,O17) -> 4 | Q17: =COUNTIFS(OFÍCIOS!$E:$E,$O17,OFÍCIOS!$G:$G,"APROVADO") -> 4 | R17: =COUNTIFS(OFÍCIOS!$E:$E,$O17,OFÍCIOS!$G:$G,"REPROVADO") -> 0 | S17: =COUNTIFS(OFÍCIOS!$E:$E,$O17,OFÍCIOS!$G:$G,"PENDENCIA") -> 0 | T17: =COUNTIFS(OFÍCIOS!$E:$E,$O17,OFÍCIOS!$G:$G,"") -> 0 | U17: =SUM(Q17:T17) -> 4
A18: ADELCIDES DA CONCEICAO ALMEIDA | B18: 5304941594 | E18: 1106 | F18: 42965 | G18: APROVADO | H18: 42978 | O18: 1489 | P18: =COUNTIF(OFÍCIOS!E:E,O18) -> 35 | Q18: =COUNTIFS(OFÍCIOS!$E:$E,$O18,OFÍCIOS!$G:$G,"APROVADO") -> 34 | R18: =COUNTIFS(OFÍCIOS!$E:$E,$O18,OFÍCIOS!$G:$G,"REPROVADO") -> 0 | S18: =COUNTIFS(OFÍCIOS!$E:$E,$O18,OFÍCIOS!$G:$G,"PENDENCIA") -> 1 | T18: =COUNTIFS(OFÍCIOS!$E:$E,$O18,OFÍCIOS!$G:$G,"") -> 0 | U18: =SUM(Q18:T18) -> 35
A19: ADELIA MARIA DE OLIVEIRA | B19: 21600057896 | E19: 262 | F19: 43160 | G19: REPROVADO | H19: 43164 | L19: 255 | O19: 1555 | P19: =COUNTIF(OFÍCIOS!E:E,O19) -> 25 | Q19: =COUNTIFS(OFÍCIOS!$E:$E,$O19,OFÍCIOS!$G:$G,"APROVADO") -> 22 | R19: =COUNTIFS(OFÍCIOS!$E:$E,$O19,OFÍCIOS!$G:$G,"REPROVADO") -> 1 | S19: =COUNTIFS(OFÍCIOS!$E:$E,$O19,OFÍCIOS!$G:$G,"PENDENCIA") -> 2 | T19: =COUNTIFS(OFÍCIOS!$E:$E,$O19,OFÍCIOS!$G:$G,"") -> 0 | U19: =SUM(Q19:T19) -> 25
A20: ADEMARIO FERREIRA DOS SANTOS | B20: 18419589802 | O20: 1570 | P20: =COUNTIF(OFÍCIOS!E:E,O20) -> 24 | Q20: =COUNTIFS(OFÍCIOS!$E:$E,$O20,OFÍCIOS!$G:$G,"APROVADO") -> 23 | R20: =COUNTIFS(OFÍCIOS!$E:$E,$O20,OFÍCIOS!$G:$G,"REPROVADO") -> 1 | S20: =COUNTIFS(OFÍCIOS!$E:$E,$O20,OFÍCIOS!$G:$G,"PENDENCIA") -> 0 | T20: =COUNTIFS(OFÍCIOS!$E:$E,$O20,OFÍCIOS!$G:$G,"") -> 0 | U20: =SUM(Q20:T20) -> 24
A21: ADEMIR DA SILVA LIMA | B21: 15538537846 | E21: 573 | F21: 43224 | O21: 1752 | P21: =COUNTIF(OFÍCIOS!E:E,O21) -> 89 | Q21: =COUNTIFS(OFÍCIOS!$E:$E,$O21,OFÍCIOS!$G:$G,"APROVADO") -> 80 | R21: =COUNTIFS(OFÍCIOS!$E:$E,$O21,OFÍCIOS!$G:$G,"REPROVADO") -> 2 | S21: =COUNTIFS(OFÍCIOS!$E:$E,$O21,OFÍCIOS!$G:$G,"PENDENCIA") -> 5 | T21: =COUNTIFS(OFÍCIOS!$E:$E,$O21,OFÍCIOS!$G:$G,"") -> 2 | U21: =SUM(Q21:T21) -> 89
A22: ADENILDE SANTOS DA SILVA | B22: 899837506 | E22: 1824 | F22: 43091 | G22: APROVADO | H22: 43097 | L22: 1828 | O22: 1824 | P22: =COUNTIF(OFÍCIOS!E:E,O22) -> 81 | Q22: =COUNTIFS(OFÍCIOS!$E:$E,$O22,OFÍCIOS!$G:$G,"APROVADO") -> 67 | R22: =COUNTIFS(OFÍCIOS!$E:$E,$O22,OFÍCIOS!$G:$G,"REPROVADO") -> 7 | S22: =COUNTIFS(OFÍCIOS!$E:$E,$O22,OFÍCIOS!$G:$G,"PENDENCIA") -> 6 | T22: =COUNTIFS(OFÍCIOS!$E:$E,$O22,OFÍCIOS!$G:$G,"") -> 1 | U22: =SUM(Q22:T22) -> 81
A23: ADENILSON DA CONCEICAO | B23: 36197160803 | E23: 229 | F23: 43151 | G23: APROVADO | L23: 232 | O23: 1628 | P23: =COUNTIF(OFÍCIOS!E:E,O23) -> 6 | Q23: =COUNTIFS(OFÍCIOS!$E:$E,$O23,OFÍCIOS!$G:$G,"APROVADO") -> 5 | R23: =COUNTIFS(OFÍCIOS!$E:$E,$O23,OFÍCIOS!$G:$G,"REPROVADO") -> 1 | S23: =COUNTIFS(OFÍCIOS!$E:$E,$O23,OFÍCIOS!$G:$G,"PENDENCIA") -> 0 | T23: =COUNTIFS(OFÍCIOS!$E:$E,$O23,OFÍCIOS!$G:$G,"") -> 0 | U23: =SUM(Q23:T23) -> 6
A24: ADENIR MODESTO RIBEIRO | B24: 39248826814 | E24: 292 | F24: 43168 | G24: APROVADO | H24: 43182 | L24: 318 | O24: 608 | P24: =COUNTIF(OFÍCIOS!E:E,O24) -> 35 | Q24: =COUNTIFS(OFÍCIOS!$E:$E,$O24,OFÍCIOS!$G:$G,"APROVADO") -> 31 | R24: =COUNTIFS(OFÍCIOS!$E:$E,$O24,OFÍCIOS!$G:$G,"REPROVADO") -> 3 | S24: =COUNTIFS(OFÍCIOS!$E:$E,$O24,OFÍCIOS!$G:$G,"PENDENCIA") -> 1 | T24: =COUNTIFS(OFÍCIOS!$E:$E,$O24,OFÍCIOS!$G:$G,"") -> 0 | U24: =SUM(Q24:T24) -> 35
A25: ADILINA FARIAS DO NASCIMENTO | B25: 48925276534 | E25: 229 | F25: 43151 | L25: 232 | O25: 527 | P25: =COUNTIF(OFÍCIOS!E:E,O25) -> 29 | Q25: =COUNTIFS(OFÍCIOS!$E:$E,$O25,OFÍCIOS!$G:$G,"APROVADO") -> 0 | R25: =COUNTIFS(OFÍCIOS!$E:$E,$O25,OFÍCIOS!$G:$G,"REPROVADO") -> 0 | S25: =COUNTIFS(OFÍCIOS!$E:$E,$O25,OFÍCIOS!$G:$G,"PENDENCIA") -> 0 | T25: =COUNTIFS(OFÍCIOS!$E:$E,$O25,OFÍCIOS!$G:$G,"") -> 29 | U25: =SUM(Q25:T25) -> 29
A26: ADILSON SOARES DA COSTA | O26: 509 | P26: =COUNTIF(OFÍCIOS!E:E,O26) -> 14 | Q26: =COUNTIFS(OFÍCIOS!$E:$E,$O26,OFÍCIOS!$G:$G,"APROVADO") -> 0 | R26: =COUNTIFS(OFÍCIOS!$E:$E,$O26,OFÍCIOS!$G:$G,"REPROVADO") -> 0 | S26: =COUNTIFS(OFÍCIOS!$E:$E,$O26,OFÍCIOS!$G:$G,"PENDENCIA") -> 0 | T26: =COUNTIFS(OFÍCIOS!$E:$E,$O26,OFÍCIOS!$G:$G,"") -> 14 | U26: =SUM(Q26:T26) -> 14
A27: ADMEIA BARBOSA DE SOUZA | B27: 25894152810 | C27: REINALDO SANTOS REIS | D27: 8263008808 | E27: 292 | F27: 43168 | G27: APROVADO | H27: 43182 | L27: 318 | O27: 292 | P27: =COUNTIF(OFÍCIOS!E:E,O27) -> 233 | Q27: =COUNTIFS(OFÍCIOS!$E:$E,$O27,OFÍCIOS!$G:$G,"APROVADO") -> 212 | R27: =COUNTIFS(OFÍCIOS!$E:$E,$O27,OFÍCIOS!$G:$G,"REPROVADO") -> 9 | S27: =COUNTIFS(OFÍCIOS!$E:$E,$O27,OFÍCIOS!$G:$G,"PENDENCIA") -> 0 | T27: =COUNTIFS(OFÍCIOS!$E:$E,$O27,OFÍCIOS!$G:$G,"") -> 12 | U27: =SUM(Q27:T27) -> 233
A28: ADONES FERREIRA JORGE | B28: 43026389587 | C28: EUNICE FELICIANA BRITO JORGE | D28: 29124464813 | E28: 485 | F28: 43196 | H28: 43206 | L28: 483 | O28: 573 | P28: =COUNTIF(OFÍCIOS!E:E,O28) -> 43 | Q28: =COUNTIFS(OFÍCIOS!$E:$E,$O28,OFÍCIOS!$G:$G,"APROVADO") -> 0 | R28: =COUNTIFS(OFÍCIOS!$E:$E,$O28,OFÍCIOS!$G:$G,"REPROVADO") -> 0 | S28: =COUNTIFS(OFÍCIOS!$E:$E,$O28,OFÍCIOS!$G:$G,"PENDENCIA") -> 0 | T28: =COUNTIFS(OFÍCIOS!$E:$E,$O28,OFÍCIOS!$G:$G,"") -> 43 | U28: =SUM(Q28:T28) -> 43
A29: ADRIANA ALVES DA SILVA | B29: 26245112885 | E29: 262 | F29: 43160 | G29: REPROVADO | H29: 43164 | L29: 255 | O29: 563 | P29: =COUNTIF(OFÍCIOS!E:E,O29) -> 64 | Q29: =COUNTIFS(OFÍCIOS!$E:$E,$O29,OFÍCIOS!$G:$G,"APROVADO") -> 0 | R29: =COUNTIFS(OFÍCIOS!$E:$E,$O29,OFÍCIOS!$G:$G,"REPROVADO") -> 0 | S29: =COUNTIFS(OFÍCIOS!$E:$E,$O29,OFÍCIOS!$G:$G,"PENDENCIA") -> 0 | T29: =COUNTIFS(OFÍCIOS!$E:$E,$O29,OFÍCIOS!$G:$G,"") -> 64 | U29: =SUM(Q29:T29) -> 64
A30: ADRIANA ALVES FERREIRA | B30: 36531080809 | C30: MARCIO ROSA DE MIRA | D30: 22485483892 | E30: 1489 | F30: 43038 | G30: APROVADO | L30: 1647-17 | O30: 443 | P30: =COUNTIF(OFÍCIOS!E:E,O30) -> 66 | Q30: =COUNTIFS(OFÍCIOS!$E:$E,$O30,OFÍCIOS!$G:$G,"APROVADO") -> 0 | R30: =COUNTIFS(OFÍCIOS!$E:$E,$O30,OFÍCIOS!$G:$G,"REPROVADO") -> 0 | S30: =COUNTIFS(OFÍCIOS!$E:$E,$O30,OFÍCIOS!$G:$G,"PENDENCIA") -> 0 | T30: =COUNTIFS(OFÍCIOS!$E:$E,$O30,OFÍCIOS!$G:$G,"") -> 66 | U30: =SUM(Q30:T30) -> 66
A31: ADRIANA APARECIDA ROBERTO | B31: 28147186819 | C31: CARLOS ANTONIO BATISTA DOS SANTOS | D31: 24499714400 | O31: 423 | P31: =COUNTIF(OFÍCIOS!E:E,O31) -> 9 | Q31: =COUNTIFS(OFÍCIOS!$E:$E,$O31,OFÍCIOS!$G:$G,"APROVADO") -> 7 | R31: =COUNTIFS(OFÍCIOS!$E:$E,$O31,OFÍCIOS!$G:$G,"REPROVADO") -> 1 | S31: =COUNTIFS(OFÍCIOS!$E:$E,$O31,OFÍCIOS!$G:$G,"PENDENCIA") -> 0 | T31: =COUNTIFS(OFÍCIOS!$E:$E,$O31,OFÍCIOS!$G:$G,"") -> 1 | U31: =SUM(Q31:T31) -> 9
A32: ADRIANA ARAUJO DE LIMA | B32: 37559228860 | C32: ALEXANDRO ARAUJO DE LIMA | D32: 28072024892 | E32: 1555 | F32: 43049 | G32: APROVADO | O32: 229 | P32: =COUNTIF(OFÍCIOS!E:E,O32) -> 89 | Q32: =COUNTIFS(OFÍCIOS!$E:$E,$O32,OFÍCIOS!$G:$G,"APROVADO") -> 81 | R32: =COUNTIFS(OFÍCIOS!$E:$E,$O32,OFÍCIOS!$G:$G,"REPROVADO") -> 2 | S32: =COUNTIFS(OFÍCIOS!$E:$E,$O32,OFÍCIOS!$G:$G,"PENDENCIA") -> 5 | T32: =COUNTIFS(OFÍCIOS!$E:$E,$O32,OFÍCIOS!$G:$G,"") -> 1 | U32: =SUM(Q32:T32) -> 89
A33: ADRIANA CORDEIRO MACHADO | B33: 23635229822 | C33: ANDERSON DE MORAIS SANTOS | D33: 21668057875 | E33: 262 | F33: 43160 | G33: APROVADO | H33: 43164 | L33: 255 | O33: 262 | P33: =COUNTIF(OFÍCIOS!E:E,O33) -> 224 | Q33: =COUNTIFS(OFÍCIOS!$E:$E,$O33,OFÍCIOS!$G:$G,"APROVADO") -> 181 | R33: =COUNTIFS(OFÍCIOS!$E:$E,$O33,OFÍCIOS!$G:$G,"REPROVADO") -> 15 | S33: =COUNTIFS(OFÍCIOS!$E:$E,$O33,OFÍCIOS!$G:$G,"PENDENCIA") -> 0 | T33: =COUNTIFS(OFÍCIOS!$E:$E,$O33,OFÍCIOS!$G:$G,"") -> 28 | U33: =SUM(Q33:T33) -> 224
A34: ADRIANA DA SILVA | O34: 117 | P34: =COUNTIF(OFÍCIOS!E:E,O34) -> 91 | Q34: =COUNTIFS(OFÍCIOS!$E:$E,$O34,OFÍCIOS!$G:$G,"APROVADO") -> 77 | R34: =COUNTIFS(OFÍCIOS!$E:$E,$O34,OFÍCIOS!$G:$G,"REPROVADO") -> 7 | S34: =COUNTIFS(OFÍCIOS!$E:$E,$O34,OFÍCIOS!$G:$G,"PENDENCIA") -> 5 | T34: =COUNTIFS(OFÍCIOS!$E:$E,$O34,OFÍCIOS!$G:$G,"") -> 2 | U34: =SUM(Q34:T34) -> 91
A35: ADRIANA DA SILVA SANTOS | B35: 40902634844 | C35: GUILHERME DE OLIVEIRA SOUZA | D35: 23795007895 | E35: 117 | F35: 43117 | G35: APROVADO | H35: 43151 | L35: 118-18 | O35: 485 | P35: =COUNTIF(OFÍCIOS!E:E,O35) -> 23 | Q35: =COUNTIFS(OFÍCIOS!$E:$E,$O35,OFÍCIOS!$G:$G,"APROVADO") -> 0 | R35: =COUNTIFS(OFÍCIOS!$E:$E,$O35,OFÍCIOS!$G:$G,"REPROVADO") -> 3 | S35: =COUNTIFS(OFÍCIOS!$E:$E,$O35,OFÍCIOS!$G:$G,"PENDENCIA") -> 0 | T35: =COUNTIFS(OFÍCIOS!$E:$E,$O35,OFÍCIOS!$G:$G,"") -> 20 | U35: =SUM(Q35:T35) -> 23
A36: ADRIANA DE SA ROCHA | B36: 39615629898 | C36: MARCELO FERNANDES LIMA | D36: 43328275894 | E36: 423 | F36: 43182 | G36: APROVADO | O36: 85 | P36: =COUNTIF(OFÍCIOS!E:E,O36) -> 93 | Q36: =COUNTIFS(OFÍCIOS!$E:$E,$O36,OFÍCIOS!$G:$G,"APROVADO") -> 86 | R36: =COUNTIFS(OFÍCIOS!$E:$E,$O36,OFÍCIOS!$G:$G,"REPROVADO") -> 4 | S36: =COUNTIFS(OFÍCIOS!$E:$E,$O36,OFÍCIOS!$G:$G,"PENDENCIA") -> 3 | T36: =COUNTIFS(OFÍCIOS!$E:$E,$O36,OFÍCIOS!$G:$G,"") -> 0 | U36: =SUM(Q36:T36) -> 93
A37: ADRIANA DOS SANTOS | P37: =COUNTIF(OFÍCIOS!E:E,O37) -> 0 | Q37: =COUNTIFS(OFÍCIOS!$E:$E,$O37,OFÍCIOS!$G:$G,"APROVADO") -> 0 | R37: =COUNTIFS(OFÍCIOS!$E:$E,$O37,OFÍCIOS!$G:$G,"REPROVADO") -> 0 | S37: =COUNTIFS(OFÍCIOS!$E:$E,$O37,OFÍCIOS!$G:$G,"PENDENCIA") -> 0 | T37: =COUNTIFS(OFÍCIOS!$E:$E,$O37,OFÍCIOS!$G:$G,"") -> 0 | U37: =SUM(Q37:T37) -> 0
A38: ADRIANA FERREIRA DA SILVA | C38: LOURIVAL CANDIDO SILVA | P38: =COUNTIF(OFÍCIOS!E:E,O38) -> 0 | Q38: =COUNTIFS(OFÍCIOS!$E:$E,$O38,OFÍCIOS!$G:$G,"APROVADO") -> 0 | R38: =COUNTIFS(OFÍCIOS!$E:$E,$O38,OFÍCIOS!$G:$G,"REPROVADO") -> 0 | S38: =COUNTIFS(OFÍCIOS!$E:$E,$O38,OFÍCIOS!$G:$G,"PENDENCIA") -> 0 | T38: =COUNTIFS(OFÍCIOS!$E:$E,$O38,OFÍCIOS!$G:$G,"") -> 0 | U38: =SUM(Q38:T38) -> 0
A39: ADRIANA HELENA DE MORAIS | B39: 14268808809 | E39: 262 | F39: 43160 | G39: APROVADO | H39: 43164 | L39: 255 | P39: =COUNTIF(OFÍCIOS!E:E,O39) -> 0 | Q39: =COUNTIFS(OFÍCIOS!$E:$E,$O39,OFÍCIOS!$G:$G,"APROVADO") -> 0 | R39: =COUNTIFS(OFÍCIOS!$E:$E,$O39,OFÍCIOS!$G:$G,"REPROVADO") -> 0 | S39: =COUNTIFS(OFÍCIOS!$E:$E,$O39,OFÍCIOS!$G:$G,"PENDENCIA") -> 0 | T39: =COUNTIFS(OFÍCIOS!$E:$E,$O39,OFÍCIOS!$G:$G,"") -> 0 | U39: =SUM(Q39:T39) -> 0
A40: ADRIANA JESUS DA CUNHA | B40: 29628693867 | E40: 292 | F40: 43168 | G40: APROVADO | H40: 43182 | L40: 318 | P40: =COUNTIF(OFÍCIOS!E:E,O40) -> 0 | Q40: =COUNTIFS(OFÍCIOS!$E:$E,$O40,OFÍCIOS!$G:$G,"APROVADO") -> 0 | R40: =COUNTIFS(OFÍCIOS!$E:$E,$O40,OFÍCIOS!$G:$G,"REPROVADO") -> 0 | S40: =COUNTIFS(OFÍCIOS!$E:$E,$O40,OFÍCIOS!$G:$G,"PENDENCIA") -> 0 | T40: =COUNTIFS(OFÍCIOS!$E:$E,$O40,OFÍCIOS!$G:$G,"") -> 0 | U40: =SUM(Q40:T40) -> 0
A41: ADRIANA LINO PEIXOTO | B41: 35762862844 | E41: 1106 | F41: 42965 | G41: APROVADO | H41: 42978 | P41: =COUNTIF(OFÍCIOS!E:E,O41) -> 0 | Q41: =COUNTIFS(OFÍCIOS!$E:$E,$O41,OFÍCIOS!$G:$G,"APROVADO") -> 0 | R41: =COUNTIFS(OFÍCIOS!$E:$E,$O41,OFÍCIOS!$G:$G,"REPROVADO") -> 0 | S41: =COUNTIFS(OFÍCIOS!$E:$E,$O41,OFÍCIOS!$G:$G,"PENDENCIA") -> 0 | T41: =COUNTIFS(OFÍCIOS!$E:$E,$O41,OFÍCIOS!$G:$G,"") -> 0 | U41: =SUM(Q41:T41) -> 0
A42: ADRIANA MARIA ALVES XAVIER (ALTERACAO DE NOME ADRIANA MARIA ALVES DOS SANTOS) | B42: 10201704412 | C42: CLAUDIO XAVIER SANTANA | D42: 33674895811 | E42: 262 | F42: 43160 | G42: APROVADO | H42: 43164 | L42: 255 | O42: TOTAIS | P42: =SUM(P3:P36) -> 1922 | Q42: =SUM(Q3:Q36) -> 1514 | R42: =SUM(R3:R36) -> 83 | S42: =SUM(S3:S36) -> 36 | T42: =SUM(T3:T36) -> 289 | U42: =SUM(U3:U36) -> 1922
A43: ADRIANA MEDEIROS DE OLIVEIRA SANTOS | B43: 35271487873 | C43: CLEITON SOUSA SANTOS | D43: 557351502 | E43: 1128 | F43: 42972 | G43: APROVADO | H43: 42979
A44: ADRIANA PEREIRA DE JESUS | B44: 22360217801 | E44: 1128 | F44: 42972 | G44: APROVADO | H44: 42979
A45: ADRIANA PINHEIRO MOREIRA | B45: 36930783862 | E45: 443 | F45: 43188 | H45: 43192
A46: ADRIANA PONCIANO DA SILVA | B46: 36647299866 | E46: 292 | F46: 43168 | G46: APROVADO | H46: 43182 | L46: 318
A47: ADRIANA PORTE | B47: 31801479895 | C47: ISAQUE PINTO DA SILVA | D47: 23103908873
A48: ADRIANA ROBERTA SILVA ANDRADE | B48: 28638653824 | C48: JOSE ROMILDO SILVA ANDRADE | D48: 50160249520
A49: ADRIANA ROQUE DOS SANTOS | B49: 17766101807 | C49: MARCOS ELIAS DOS SANTOS | D49: 31993041842 | E49: 1824 | F49: 43091 | G49: APROVADO | H49: 43097 | L49: 1828
A50: ADRIANA SABINO NOGUEIRA | B50: 17902799840 | C50: JOYCE CRISTINA NOGUEIRA DO CARMO | D50: 44230035896
A51: ADRIANA SANTANA SANTOS | B51: 49122403892 | C51: ETVALDO BERTO DA SILVA | D51: 1478139560 | E51: 608 | F51: 43012 | G51: APROVADO | H51: 43024 | O51: OFÍCIO DE REANÁLISE 019/18 - 05/06/18
A52: ADRIANA SANTOS RIBEIRO | B52: 37534302854 | C52: EDLANDIO BISPO SILVA | D52: 1689246502
A53: ADRIANA SEVERINO SANTANA | B53: 14699996841 | C53: FERNANDO FERREIRA SILVA | D53: 15089706883 | E53: 1128 | F53: 42972 | G53: APROVADO | H53: 42979
A54: ADRIANA TENORIO DA SILVA | B54: 47077408809
A55: ADRIANE MOREIRA DOS SANTOS | B55: 40396239838 | C55: JEFERSON DA SILVA DE JESUS | D55: 39420747883 | E55: 262 | F55: 43160 | G55: APROVADO | H55: 43164 | L55: 255
A56: ADRIANO ALVES BARBOSA | B56: 41333062877 | E56: 292 | F56: 43168 | G56: APROVADO | H56: 43182 | L56: 318
A57: ADRIANO HENRIQUE DA COSTA | B57: 38781151802
A58: ADRIANO PEREIRA DOS SANTOS
A59: ADRIELLE DOS PASSOS DE SOUZA | B59: 2428277219 | C59: DIVANILDO SOUZA DOS PASSOS | D59: 909805229 | E59: 810 | F59: 42915 | G59: APROVADO | H59: 42921 | L59: 568-17
A60: AGDA APARECIDA PEREIRA | B60: 16417464830
A61: AGNALDO ALTMANN | B61: 7104481800 | E61: 262 | F61: 43160 | G61: APROVADO | H61: 43164 | L61: 255
A62: AGNALDO LOPES GONCALVES FILHO | B62: 25023266800
A63: AGOSTINHO FERNANDES SILVA | B63: 3722493889 | C63: FRANCISCA GOMES DE OLIVEIRA | D63: 32416642871
A64: AIDEE MARIA DOS SANTOS | B64: 14519340845 | C64: SIORLANDIO DOS SANTOS FALCAO | D64: 88489795568 | E64: 262 | F64: 43160 | H64: 43164 | L64: 255
A65: AILTON WILLIAN MELLO | B65: 19266484806
A66: ALADIM PINHEIRO DOS SANTOS | B66: 15322188851
A67: ALAILTON COSTA DE SOUZA | B67: 36392955879 | C67: AMANDA CRISTINA SILVEIRA DA SILVA | D67: 5242864346 | E67: 117 | F67: 43117 | G67: APROVADO | H67: 43151 | L67: 118-18
A68: ALAN DE JESUS PASSOS | B68: 41482647800 | E68: 1262 | F68: 42997 | G68: APROVADO | H68: 43000
A69: ALBERT PEREIRA DOS SANTOS | B69: 47629183852
A70: ALBERTINA CANDIDO RIBEIRO GOMES | B70: 9882942490 | C70: DENIS JOSE GOMES | D70: 9704111460
A71: ALBERTINA PEREIRA COSTA | B71: 14777572870 | C71: EDIVALDO ALVES DE SOUZA | D71: 12874739898 | E71: 1824 | F71: 43091 | G71: APROVADO | H71: 43097 | L71: 1828
A72: ALCIDINEY DA SILVA | B72: 31996709895
A73: ALCILENE GUEDES DA SILVA | B73: 26824046850 | E73: 1824 | F73: 43091 | G73: APROVADO | H73: 43097 | L73: 1828
A74: ALCIONE BARBOSA DE SOUSA | B74: 3523524342 | E74: 85 | F74: 43109 | G74: APROVADO | H74: 43151
A75: ALDA DE JESUS GONCALVES | B75: 26940268855 | C75: JUCELINO ALVES DE LIMA
A76: ALDA MARIA DE JESUS | B76: 24828498885 | E76: 1489 | F76: 43038 | G76: APROVADO | L76: 1647-17
A77: ALDA REJANE SANTOS | B77: 11482307855 | E77: 85 | F77: 43109 | G77: APROVADO | H77: 43151
A78: ALDERLANDIA DE OLIVEIRA MONTEIRO | B78: 42352732808 | C78: JOSE SOARES DA SILVA | D78: 281893373 | E78: 1214 | F78: 42989 | G78: APROVADO | H78: 43000
A79: ALESILVIA RAIMUNDO DA SILVA NEVES | B79: 13480043801 | C79: CLAUDIO RIBEIRO NEVES | D79: 67141536604
A80: ALESSANDRA APARECIDA DE JESUS | B80: 31874522804 | E80: 292 | F80: 43168 | G80: APROVADO | H80: 43182 | L80: 318
A81: ALESSANDRA CABRAL DA SILVA | B81: 28889575824 | E81: 1241 | F81: 42992 | G81: APROVADO | H81: 42998
A82: ALESSANDRA JUVINA DA SILVA | B82: 21734589817 | E82: 229 | F82: 43151 | G82: APROVADO | L82: 232
A83: ALESSANDRA LIMA DA SILVA
A84: ALESSANDRA LUNA DA SILVA | B84: 18475875858
A85: ALESSANDRA MARQUES DOS SANTOS | B85: 40443882886 | E85: 509 | F85: 43203 | H85: 43213
A86: ALESSANDRA MARTINS DA SILVA | B86: 43053250802 | C86: IUDARLAN MARTINS DA SILVA | D86: 35893147880 | E86: 1128 | F86: 42972 | G86: APROVADO
A87: ALESSANDRA MILAGRES PIROTTI | B87: 28255807837 | E87: 292 | F87: 43168 | G87: APROVADO | L87: 318
A88: ALESSANDRA MONTEIRO DA SILVA | B88: 33617584837 | C88: ASTROGILDO APARECIDO CURY DE ARAUJO | D88: 26520094862 | E88: 608 | F88: 43012 | G88: APROVADO
A89: ALESSANDRA QUARESMA DA SILVA | B89: 38168161858 | C89: WALLACE DIEGO HENRIQUE BISPO | D89: 24059422835
A90: ALESSANDRO ARAUJO DA SILVA COSTA | B90: 38728353862 | C90: LIZIANE ROCHA DA SILVA COSTA | D90: 37650358828 | E90: 1417 | F90: 43017 | G90: APROVADO | L90: 1017-17
A91: ALEX DE JESUS PEREIRA | B91: 29479419858 | C91: JOILMA DE JESUS FERREIRA | D91: 71909656534
A92: ALEX JOSE CATARINO ASSUNCAO | B92: 37634689866 | E92: 443 | F92: 43188
A93: ALEXANDRA APARECIDA DA SILVA BARBOZA | B93: 22656606802 | E93: 1555 | F93: 43049 | G93: APROVADO
A94: ALEXANDRA SANTOS DE PAULA | B94: 4248144638 | E94: 229 | F94: 43151 | G94: APROVADO | L94: 232
A95: ALEXANDRE OLIVEIRA SILVA | B95: 29998933889
A96: ALEXANDRE SATELES DOS SANTOS | B96: 2963904533 | E96: 1489 | F96: 43038 | G96: APROVADO | L96: 1647-17
A97: ALEXANDRE VALENTIN DE SOUZA | B97: 23256005802 | E97: 1350 | F97: 43006 | G97: APROVADO
A98: ALEXSANDRA BORGES GONCALVES | B98: 3317260505 | C98: GILDECI FERREIRA CORDEIRO | D98: 92396607634
A99: ALEXSANDRA FRANCA DA SILVA | B99: 36234875890 | E99: 1128 | F99: 42972 | G99: APROVADO
A100: ALEXSANDRA MARIA DA SILVA | B100: 1243618469 | E100: 262 | F100: 43160 | G100: APROVADO | H100: 43164 | L100: 255
...

Sheet DEPLAN
E4: ÁREA | F4: SELO | G4: PROPRIETÁRIO | H4: CPF | I4: No PROCESSO SEI (INDENIZAÇÃO)
E5: JD. VITÓRIA | F5: 002/0002/A | G5: ELIAS FERREIRA DE SOUSA | H5: 530.102.098-60 | I5: 6014.2025/0004924-8
E6: JD. VITÓRIA | F6: 002/0053/A | G6: GEOVANE SOUZA SANTOS | H6: 429.418.998-39 | I6: 6014.2025/0008040-4
E7: JD. VITÓRIA | F7: 007/0041/A | G7: REINALDO MOREIRA SILVA | H7: 702.612.337-72 | I7: 6014.2025/0008179-6
E8: JD. VITÓRIA | F8: 007/0055/A | G8: IVANILDA PEREIRA DE SOUZA | H8: 346.774.738-89 | I8: 6014.2025/0005014-9
E9: JD. VITÓRIA | F9: 009/0012/A | G9: JACKSON NASCIMENTO DOS SANTOS | H9: 433.472.938-00 | I9: 6014.2025/0006392-5
E10: JD. VITÓRIA | F10: 009/0012/B | G10: ELIANE MARIA NASCIMENTO DOS SANTOS | H10: 012.722.274-05 | I10: 6014.2025/0006669-0
E11: JD. VITÓRIA | F11: 009/0012/C | G11: JOICE NASCIMENTO DOS SANTOS | H11: 506.567.788-30 | I11: 6014.2025/0006662-2
E12: JD. VITÓRIA | F12: 009/0020/A | G12: MILTON PEREIRA DOS SANTOS | H12: 011.914.478-63 | I12: 6014.2025/0005381-4
E13: JD. VITÓRIA | F13: 009/0023/A | G13: ELIZABETH DE MENDONÇA ALMEIDA SANTANA | H13: 064.108.154-50 | I13: 6014.2025/0007987-2
E14: JD. VITÓRIA | F14: 010/0009/A | G14: LUCIENE CARDOSO PEREIRA | H14: 256.444.508-06 | I14: 6014.2025/0006290-2
E15: JD. VITÓRIA | F15: 010/0012/A | G15: GLAUSIEL DE JESUS MACIEL | H15: 041.406.735.59 | I15: 6014.2025/0006005-5
... E26: JD. VITÓRIA | F26: 016/0029/A | G26: EDNA MARIA BEZERRA DOS REIS | H26: 316.803.158-54 | I26: 6014.2025/0005958-8
E43: JD. VITÓRIA
E44: JD. VITÓRIA
E45: JD. VITÓRIA
E46: JD. VITÓRIA
E47: JD. VITÓRIA
E48: JD. VITÓRIA
E49: JD. VITÓRIA
E50: JD. VITÓRIA
E51: JD. VITÓRIA
E52: JD. VITÓRIA
E53: JD. VITÓRIA

Sheet Quantitativo Fora da Demanda
A1: REPROVADOS QUE NÃO DEVERÃO SER REASSENTADOS NO ESPANHA | E1: APROVADOS SEM CONDOMÍNIO QUE DEVERÃO SER REASSENTADOS NO CHÁCARA DO CONDE
A2: ÁREA | B2: QTD | E2: ÁREA | F2: QTD
A3: AUXÍLIO ALUGUEL | B3: 39 | E3: AUXÍLIO ALUGUEL | F3: 54
A4: CANTINHO DO CÉU (OBRAS) | B4: 15 | E4: CANTINHO DO CÉU (OBRAS) SETORES: 138 E 140 | F4: 13
A5: FUMAÇA | B5: 7 | E5: FUMAÇA | F5: 15
A6: NEBLINA | B6: 2 | E6: NEBLINA | F6: 9
A7: LEBLON | B7: 0 | E7: LEBLON | F7: 9
A8: PABREU / PRAINHA | B8: 15 | E8: PABREU / PRAINHA | F8: 21
A9: TOTAL | B9: =SUM(B3:B8) -> 78 | E9: TOTAL | F9: =SUM(F3:F8) -> 121

Sheet Planilha3
B3: ÁREA | C3: FASE | D3: SELO | E3: PROPRIETÁRIO | F3: CPF | G3: STATUS | H3: VALOR INDENIZAÇÃO
B4: PARAISÓPOLIS/ANTONICO | C4: 2 | D4: 024/0005/B | E4: MARIA JOSE HONORIO SILVA | F4: 397.255.294-72 | G4: RECUSA INDENIZAÇÃO | H4: 66528.26
B5: PARAISÓPOLIS/ANTONICO | C5: 2 | D5: 024/0005/C | E5: DOUGLAS FELIX DA SILVA | F5: 350.792.428-50 | G5: RECUSA INDENIZAÇÃO | H5: 60000
B6: PARAISÓPOLIS/ANTONICO | C6: 2 | D6: 024/0005/D | E6: DOUGLAS FELIX DA SILVA | F6: 350.792.428-50 | G6: RECUSA INDENIZAÇÃO | H6: 60000
B7: PARAISÓPOLIS/ANTONICO | C7: 2 | D7: 024/0045/A | E7: JOVINA DE JESUS SANTANA | F7: 252.848.568-99 | G7: RECUSA INDENIZAÇÃO | H7: 71112.51
B8: PARAISÓPOLIS/ANTONICO | C8: 2 | D8: 024/0046/A | E8: JOÃO BRASILINO DE SOUSA | F8: 014.102.728-26 | G8: RECUSA INDENIZAÇÃO | H8: 100370.59
B9: PARAISÓPOLIS/ANTONICO | C9: 2 | D9: 024/0047/F | E9: ROSA HELENA DE SOUZA | F9: 291.466.998-48 | G9: RECUSA INDENIZAÇÃO | H9: 60000
B10: PARAISÓPOLIS/ANTONICO | C10: 2 | D10: 024/0053/A | E10: SELMA SOARES SANTOS DE OLIVEIRA | F10: 324.973.128-50 | G10: RECUSA INDENIZAÇÃO | H10: 60000
B11: PARAISÓPOLIS/ANTONICO | C11: 2 | D11: 024/0077/A | E11: PROPRIETÁRIO NÃO IDENTIFICADO | F11: -- | G11: RECUSA INDENIZAÇÃO | H11: 60000
B12: PARAISÓPOLIS/ANTONICO | C12: 2 | D12: 024/0077/B | E12: LUCIANA FRANCILINO DE LIMA | F12: 296.566.438-60 | G12: RECUSA INDENIZAÇÃO | H12: 87351.82
B13: PARAISÓPOLIS/ANTONICO | C13: 2 | D13: 024/0079/D | E13: EUDES GONÇALVES CAVALCANTE | F13: 064.025.638-46 | G13: RECUSA INDENIZAÇÃO | H13: 56418.89
B14: PARAISÓPOLIS/ANTONICO | C14: 2 | D14: 024/0079/G | E14: EUDES GONÇALVES CAVALCANTI | F14: 064.025.638-46 | G14: RECUSA INDENIZAÇÃO | H14: 60000
B15: PARAISÓPOLIS/ANTONICO | C15: 4 | D15: 029/0016/C | E15: ADINALDO GOMES DA SILVA | F15: 975.984.883-04 | G15: RECUSA INDENIZAÇÃO | H15: 60000
... B17: PARAISÓPOLIS/ANTONICO | C17: 4 | D17: 029/0086/D | E17: EDUARDO FERNANDES | F17: -- | G17: RECUSA INDENIZAÇÃO | H17: 60000
B23: PARAISÓPOLIS/ANTONICO | C23: 2 | D23: 024/0079/D | E23: EUDES GONÇALVES CAVALCANTE | F23: 064.025.638-46 | G23: ESTUDO DE CASO
B24: PARAISÓPOLIS/ANTONICO | C24: 2 | D24: 024/0079/E | E24: DANIELE COSTA | F24: 374.435.458-00 | G24: ESTUDO DE CASO
B25: PARAISÓPOLIS/ANTONICO | C25: 2 | D25: 024/0079/F | G25: ESTUDO DE CASO
B26: PARAISÓPOLIS/ANTONICO | C26: 2 | D26: 024/0079/G | E26: EUDES GONÇALVES CAVALCANTI | F26: 064.025.638-46 | G26: ESTUDO DE CASO
B27: PARAISÓPOLIS/ANTONICO | C27: 2 | D27: 024/0079/J | E27: ELIO NEVES DE SOUZA | F27: 350.318.858-40 | G27: RECUSA
B28: PARAISÓPOLIS/ANTONICO | C28: 2 | D28: 024/0082/A | E28: IVÃ CERQUEIRA LENARES | F28: 006.868.775-35 | G28: PENDENTE
B29: PARAISÓPOLIS/ANTONICO | C29: 2 | D29: 024/0082/D | E29: JOÃO VITOR DE SANTANA | F29: 534.193.048-70 | G29: ESTUDO DE CASO
B30: PARAISÓPOLIS/ANTONICO | C30: 2 | D30: 024/0088/K | E30: MARIA APARECIDA FLECKENSTEIN VIEIRA | F30: 304.821.048-21 | G30: ESTUDO DE CASO
B31: PARAISÓPOLIS/ANTONICO | C31: 2 | D31: 024/0088/M | E31: PROPRIETÁRIO NÃO IDENTIFICADO | F31: N/A | G31: PROPRIETÁRIO NÃO IDENTIFICADO
B32: PARAISÓPOLIS/ANTONICO | C32: 2 | D32: 027/0002/E | G32: PROPRIETÁRIO NÃO IDENTIFICADO
B33: PARAISÓPOLIS/ANTONICO | C33: 2 | D33: 027/0012/C | G33: PROPRIETÁRIO NÃO IDENTIFICADO

Sheet Planilha4
C6: ORDEM | D6: SELO | E6: DATA PAGAMENTO | F6: DATA ENTREGA IMÓVEL | G6: SITUAÇÃO ATUAL IMÓVEL
C7: 1 | D7: 024/0049/B | E7: 45068 | F7: AGUARDANDO | G7: LIBERADO DEMOLIÇÃO
C8: 2 | D8: 029/0036/O | E8: 45068 | F8: AGUARDANDO | G8: LIBERADO DEMOLIÇÃO
C9: 3 | D9: 031/0028/D | E9: 45068 | F9: 44894 | G9: DESCARACTERIZADO
C10: 4 | D10: 031/0034/H | E10: 45068 | F10: AGUARDANDO | G10: LIBERADO DEMOLIÇÃO
C11: 5 | D11: 024/0093/B | E11: 45065 | F11: AGUARDANDO | G11: LIBERADO DEMOLIÇÃO
C12: 6 | D12: 029/0036/P | E12: 45065 | F12: AGUARDANDO | G12: LIBERADO DEMOLIÇÃO
C13: 7 | D13: 029/0042/A | E13: 45065 | F13: AGUARDANDO | G13: LIBERADO DEMOLIÇÃO
C14: 8 | D14: 029/0081/A | E14: 45065 | F14: 44526 | G14: DEMOLIDO
C15: 9 | D15: 029/0083/A | E15: 45065 | F15: 44642 | G15: DEMOLIDO
C16: 10 | D16: 031/0020/B | E16: 45065 | F16: 44694 | G16: DESCARACTERIZADO
C17: 11 | D17: 031/0023/B | E17: 45065 | F17: AGUARDANDO | G17: LIBERADO DEMOLIÇÃO
C18: 12 | D18: 031/0024/A | E18: 45065 | F18: 44659 | G18: DESCARACTERIZADO
C19: 13 | D19: 024/0079/A | E19: 45064 | F19: AGUARDANDO | G19: LIBERADO DEMOLIÇÃO
C20: 14 | D20: 024/0082/H | E20: 45064 | F20: AGUARDANDO | G20: LIBERADO DEMOLIÇÃO
C21: 15 | D21: 029/0022/A | E21: 45064 | F21: AGUARDANDO | G21: LIBERADO DEMOLIÇÃO
C22: 16 | D22: 029/0022/D | E22: 45064 | F22: AGUARDANDO | G22: LIBERADO DEMOLIÇÃO
C23: 17 | D23: 029/0035/A | E23: 45064 | F23: 44859 | G23: DEMOLIDO
C24: 18 | D24: 029/0036/L | E24: 45064 | F24: AGUARDANDO | G24: LIBERADO DEMOLIÇÃO
C25: 19 | D25: 029/0036/N | E25: 45064 | F25: AGUARDANDO | G25: LIBERADO DEMOLIÇÃO
C26: 20 | D26: 031/0035/A | E26: 45064 | F26: 44643 | G26: DESCARACTERIZADO
C27: 21 | D27: 031/0035/F | E27: 45064 | F27: 44638 | G27: DESCARACTERIZADO
C28: 22 | D28: 031/0058/E | E28: 45064 | F28: AGUARDANDO | G28: LIBERADO DEMOLIÇÃO
C29: 23 | D29: 031/0058/H | E29: 45064 | F29: AGUARDANDO | G29: LIBERADO DEMOLIÇÃO
C30: 24 | D30: 031/0078/G | E30: 45064 | F30: AGUARDANDO | G30: LIBERADO DEMOLIÇÃO
C31: 25 | D31: 024/0004/B | E31: 45063 | F31: AGUARDANDO | G31: LIBERADO DEMOLIÇÃO
C32: 26 | D32: 024/0050/B | E32: 45063 | F32: AGUARDANDO | G32: LIBERADO DEMOLIÇÃO
C33: 27 | D33: 024/0074/A | E33: 45063 | F33: AGUARDANDO | G33: LIBERADO DEMOLIÇÃO
C34: 28 | D34: 024/0074/D | E34: 45063 | F34: AGUARDANDO | G34: LIBERADO DEMOLIÇÃO
C35: 29 | D35: 024/0078/B | E35: 45063 | F35: AGUARDANDO | G35: LIBERADO DEMOLIÇÃO
C36: 30 | D36: 024/0082/C | E36: 45063 | F36: AGUARDANDO | G36: LIBERADO DEMOLIÇÃO
C37: 31 | D37: 024/0093/A | E37: 45063 | F37: AGUARDANDO | G37: LIBERADO DEMOLIÇÃO
C38: 32 | D38: 031/0022/B | E38: 45063 | F38: 44655 | G38: DESCARACTERIZADO
C39: 33 | D39: 031/0028/L | E39: 45063 | F39: 44659 | G39: DESCARACTERIZADO
C40: 34 | D40: 031/0030/B | E40: 45063 | F40: AGUARDANDO | G40: LIBERADO DEMOLIÇÃO
C41: 35 | D41: 031/0030/C | E41: 45063 | F41: 44642 | G41: DESCARACTERIZADO
C42: 36 | D42: 031/0033/E | E42: 45063 | F42: 44638 | G42: DESCARACTERIZADO
C43: 37 | D43: 031/0034/A | E43: 45063 | F43: AGUARDANDO | G43: LIBERADO DEMOLIÇÃO
C44: 38 | D44: 031/0034/B | E44: 45063 | F44: AGUARDANDO | G44: LIBERADO DEMOLIÇÃO
C45: 39 | D45: 031/0034/E | E45: 45063 | F45: AGUARDANDO | G45: LIBERADO DEMOLIÇÃO
C46: 40 | D46: 031/0034/K | E46: 45063 | F46: AGUARDANDO | G46: LIBERADO DEMOLIÇÃO
C47: 41 | D47: 024/0049/C | E47: 45054 | F47: AGUARDANDO | G47: LIBERADO DEMOLIÇÃO
C48: 42 | D48: 029/0049/B | E48: 45051 | F48: AGUARDANDO | G48: LIBERADO DEMOLIÇÃO

Sheet Planilha5
D3: ÁREA | E3: No PROCESSO SEI (INDENIZAÇÃO) | F3: VALOR COM BONIFICAÇÃO
D4: PARAISÓPOLIS/ANTONICO | E4: 6014.2023/0002356-3 | F4: 60000
D5: PARAISÓPOLIS/ANTONICO | E5: 6014.2023/0001968-0 | F5: 53382.82
D6: PARAISÓPOLIS/ANTONICO | E6: 6014.2023/0001973-6 | F6: 55091.16
D7: PARAISÓPOLIS/ANTONICO | E7: 6014.2023/0001445-9 | F7: 71112.51
D8: PARAISÓPOLIS/ANTONICO | E8: 6014.2023/0002108-0 | F8: 60000
D9: PARAISÓPOLIS/ANTONICO | E9: 6014.2023/0001334-7 | F9: 60000
D10: PARAISÓPOLIS/ANTONICO | E10: 6014.2023/0001523-4 | F10: 60000
D11: PARAISÓPOLIS/ANTONICO | E11: 6014.2023/0001799-7 | F11: 60000
D12: PARAISÓPOLIS/ANTONICO | E12: 6014.2023/0000796-7 | F12: 48801.81
D13: PARAISÓPOLIS/ANTONICO | E13: 6014.2023/0003032-2 | F13: 60000
D14: PARAISÓPOLIS/ANTONICO | E14: 6014.2023/0001144-1 | F14: 48087.05
D15: PARAISÓPOLIS/ANTONICO | E15: 6014.2023/0002532-9 | F15: 56900.74
... D96: PARAISÓPOLIS/ANTONICO | E96: 6014.2023/0003154-0 | F96: 57433.2
E98: VALOR TOTAL | F98: =SUM(F4:F97) -> 4865724.7
