Workbook
Name Adequacao_Imovel: 'Listas (não utilizar)'!$G$2:$G$7
Name ADEQUAR: 'Listas (não utilizar)'!$G$2:$G$7
Name Apartamento: 'Listas (não utilizar)'!$D$2:$D$21
Name APROVCEF: #REF!
Name Área: 'Listas (não utilizar)'!$A$2:$A$28
Name AREAS: #REF!
Name AVILDATA: #REF!
Name AVILDATA1: #REF!
Name BARCDATA: #REF!
Name BILBDATA: #REF!
Name Bloco: 'Listas (não utilizar)'!$C$2:$C$16
Name CEF: #REF!
Name CEUTDATA: #REF!
Name Condomínio: 'Listas (não utilizar)'!$B$2:$B$15
Name INDDEMAND: #REF!
Name INDEMAND: #REF!
Name it: #REF!
Name Pendência: 'Listas (não utilizar)'!$I$2:$I$7
Name PLANCCO: #REF!
Name Renúncia: 'Listas (não utilizar)'!$H$2:$H$6
Name RetornoSMADS: '[1]Listas (não utilizar)'!$E$2:$E$3
Name selogo: #REF!
Name selomv: #REF!
Name selos_go: #REF!
Name selosgo: #REF!
Name selosgo1: #REF!
Name SITAH_CAIXA: 'Listas (não utilizar)'!$E$2:$E$9
Name StatusCAIXA: 'Listas (não utilizar)'!$F$2:$F$5
Name TEPROC: #REF!
Name TEPROC1: #REF!

Sheet Listas (não utilizar)
A1: Área | B1: Condomínio | C1: Bloco | D1: Apartamento | E1: SITAH / CAIXA | F1: Status CAIXA | G1: Adequacao Imovel | H1: Renúncia | I1: Pendência | J1: Pendências / Reprovados caixa
A2: ALTO DA ALEGRIA | B2: AVILA | C2: 1 | D2: 101 | E2: AGENDADO | F2: APROVADO | G2: NÃO | H2: NÃO | I2: CRAS | J2: RENDA SUPERIOR
A3: ALTO DA ALEGRIA (OBRAS) | B3: BARCELONA | C3: 2 | D3: 102 | E3: AGUARDANDO OFICIO | F3: REPROVADO | G3: FÍSICA | H3: RENDA | I3: CRAS + DOCUMENTOS | J3: CADMUT
A4: ALTO DA ALEGRIA (RESERVA) | B4: BILBAO | C4: 3 | D4: 103 | E4: ATENDIMENTO CANCELADO | F4: PENDENCIA | G4: VISUAL | H4: CADIN | I4: DOCUMENTOS | J4: CADIN
A5: ANTERO GOMES | B5: CEUTA | C5: 4 | D5: 104 | E5: CADMUT | F5: SEM DOSSIE | G5: INTELECTUAL | H5: ESTADO CIVIL | I5: CADIN
A6: CANTINHO DO CEU / GAIVOTAS | B6: IBIZA | C6: 5 | D6: 201 | E6: CHACARA DO CONDE | G6: AUDITIVA | H6: SEPARACAO | I6: CRAS + CADIN
A7: CANTINHO DO CEU / OBRAS | B7: LEAO | C7: 6 | D7: 202 | E7: CONFLITO | G7: NANISMO | I7: R.LI.AV.
A8: CASTRO ALVES | B8: MADRID | C8: 7 | D8: 203 | E8: ENVIADO CAIXA | I8: IEME
A9: COCAIA | B9: MELILLA | C9: 8 | D9: 204 | E9: FALECEU
A10: ERUNDINA | B10: PAMPLONA | C10: 9 | D10: 301 | E10: FALTANTE DOSSIÊ
A11: FUMACA | B11: SALAMANCA | C11: 10 | D11: 302 | E11: HABISP ACERTO DE ÁREA
A12: GUAICURI (OBRAS) | B12: TERUEL | C12: 11 | D12: 303 | E12: HABISP AGUARDANDO CRÍTICA
A13: GUAICURI / CIDADE JULIA | B13: VALENCIA | C13: 12 | D13: 304 | E13: HABISP PEND DE ATUALIZ CADASTRAL
A14: JARDIM MIRNA | B14: VALVERDE | C14: 13 | D14: 401 | E14: INDENIZACAO
A15: JARDIM SELMA II | B15: VITORIA | C15: 14 | D15: 402 | E15: PENDENCIA
A16: JARDIM TUBO | C16: 15 | D16: 403 | E16: PERMUTA
A17: LEBLON | D17: 404 | E17: PESQUISA SMADS
A18: MARGINAL DOIS / FUNDAO | D18: 501 | E18: REANALISE
A19: MATA VIRGEM / JD ELDORADO | D19: 502 | E19: RECLUSO
A20: NEBLINA | D20: 503 | E20: RELATÓRIO SOCIAL
A21: NORONHA | D21: 504 | E21: RENDA SUPERIOR
A22: NOVA GRAJAU | E22: RESISTENTE
A23: NOVA MARILDA | E23: TROCA DE TITULARIDADE
A24: NOVA VARGINHA
A25: PABREU / PRAINHA
A26: PENDENCIA GABINETE
A27: PILAO / APURA
A28: PILAO / DOIS
A29: PILAO / PAULISTAS
A30: SANTA AMELIA
A31: VALE VERDE / MONTE VERDE
A32: VILA BREJINHO
A33: VILA NASCENTE
A34: ZR / COSTA BRANCA
A35: VILA RUBI

Sheet QUANT COND
A1: CONDOMINIOS | B1: QUANT
A2: AVILA | B2: =COUNTIF(#REF!,'QUANT COND'!A2) -> #REF!
A3: BARCELONA | B3: =COUNTIF(#REF!,'QUANT COND'!A3) -> #REF!
A4: BILBAO | B4: =COUNTIF(#REF!,'QUANT COND'!A4) -> #REF!
A5: CEUTA | B5: =COUNTIF(#REF!,'QUANT COND'!A5) -> #REF!
A6: IBIZA | B6: =COUNTIF(#REF!,'QUANT COND'!A6) -> #REF!
A7: LEAO | B7: =COUNTIF(#REF!,'QUANT COND'!A7) -> #REF!
A8: MADRID | B8: =COUNTIF(#REF!,'QUANT COND'!A8) -> #REF!
A9: MELILLA | B9: =COUNTIF(#REF!,'QUANT COND'!A9) -> #REF!
A10: PAMPLONA | B10: =COUNTIF(#REF!,'QUANT COND'!A10) -> #REF!
A11: SALAMANCA | B11: =COUNTIF(#REF!,'QUANT COND'!A11) -> #REF!
A12: TERUEL | B12: =COUNTIF(#REF!,'QUANT COND'!A12) -> #REF!
A13: VALENCIA | B13: =COUNTIF(#REF!,'QUANT COND'!A13) -> #REF!
... A15: VITORIA | B15: =COUNTIF(#REF!,'QUANT COND'!A15) -> #REF!

Sheet OFÍCIOS
A1: PLANILHA DE CONFRONTO OFÍCIOS DE INDICAÇÃO COM ENVIADOS CAIXA ECONÔMICA FEDERAL - CEF
A2: TITULAR | B2: CPF | C2: Cônjuge | D2: CPF | E2: OFÍCIO | F2: DATA | G2: STATUS CEF | H2: DATA ENVIO CAIXA | I2: DUPLICIDADE OFÍCIO | J2: DATA | K2: DATA ENVIO CAIXA | L2: OFÍCIO DE INDICAÇÃO | M2: DATA OFÍCIO INDICAÇÃO | O2: NR OFICIO | P2: QUANT | Q2: APROV | R2: REPROV | S2: PEND | T2: SEM STATUS (ANÁLISE) | Y2: CEF BD | Z2: CEF OFICIOS | AA2: CEF PLANILHA
A3: ABEL MEDEIROS FILHO | B3: 27140979871 | E3: 1128 | F3: 42972 | G3: APROVADO | H3: 42979 | O3: 810 | P3: =COUNTIF(OFÍCIOS!E:E,O3) -> 156 | Q3: =COUNTIFS(OFÍCIOS!$E:$E,$O3,OFÍCIOS!$G:$G,"APROVADO") -> 149 | R3: =COUNTIFS(OFÍCIOS!$E:$E,$O3,OFÍCIOS!$G:$G,"REPROVADO") -> 3 | S3: =COUNTIFS(OFÍCIOS!$E:$E,$O3,OFÍCIOS!$G:$G,"PENDENCIA") -> 2 | T3: =COUNTIFS(OFÍCIOS!$E:$E,$O3,OFÍCIOS!$G:$G,"") -> 2 | U3: =SUM(Q3:T3) -> 156 | X3: FEITOS | Y3: 1850 | Z3: 1827 | AA3: =SUM(AA4:AA7) -> 1615
A4: ABELINA FERREIRA DOS SANTOS | B4: 39200633846 | O4: 1417 | P4: =COUNTIF(OFÍCIOS!E:E,O4) -> 42 | Q4: =COUNTIFS(OFÍCIOS!$E:$E,$O4,OFÍCIOS!$G:$G,"APROVADO") -> 36 | R4: =COUNTIFS(OFÍCIOS!$E:$E,$O4,OFÍCIOS!$G:$G,"REPROVADO") -> 3 | S4: =COUNTIFS(OFÍCIOS!$E:$E,$O4,OFÍCIOS!$G:$G,"PENDENCIA") -> 3 | T4: =COUNTIFS(OFÍCIOS!$E:$E,$O4,OFÍCIOS!$G:$G,"") -> 0 | U4: =SUM(Q4:T4) -> 42 | X4: APROVADOS | Y4: 1517 | Z4: 1427 | AA4: 1559
A5: ABIGAIL DE OLIVEIRA PAULINO | B5: 75489104872 | E5: 1752 | F5: 43051 | G5: APROVADO | H5: 43089 | L5: 1759 | O5: 1359 | P5: =COUNTIF(OFÍCIOS!E:E,O5) -> 14 | Q5: =COUNTIFS(OFÍCIOS!$E:$E,$O5,OFÍCIOS!$G:$G,"APROVADO") -> 13 | R5: =COUNTIFS(OFÍCIOS!$E:$E,$O5,OFÍCIOS!$G:$G,"REPROVADO") -> 1 | S5: =COUNTIFS(OFÍCIOS!$E:$E,$O5,OFÍCIOS!$G:$G,"PENDENCIA") -> 0 | T5: =COUNTIFS(OFÍCIOS!$E:$E,$O5,OFÍCIOS!$G:$G,"") -> 0 | U5: =SUM(Q5:T5) -> 14 | X5: REPROVADOS | Y5: 73 | Z5: 79 | AA5: 28
A6: ABILIO OLIVEIRA SANTOS | B6: 43286003620 | O6: 1350 | P6: =COUNTIF(OFÍCIOS!E:E,O6) -> 79 | Q6: =COUNTIFS(OFÍCIOS!$E:$E,$O6,OFÍCIOS!$G:$G,"APROVADO") -> 75 | R6: =COUNTIFS(OFÍCIOS!$E:$E,$O6,OFÍCIOS!$G:$G,"REPROVADO") -> 3 | S6: =COUNTIFS(OFÍCIOS!$E:$E,$O6,OFÍCIOS!$G:$G,"PENDENCIA") -> 0 | T6: =COUNTIFS(OFÍCIOS!$E:$E,$O6,OFÍCIOS!$G:$G,"") -> 1 | U6: =SUM(Q6:T6) -> 79 | X6: PENDENCIAS | Y6: 36 | Z6: 32 | AA6: 11
A7: ABRAHAO SANTOS SILVA | O7: 1343 | P7: =COUNTIF(OFÍCIOS!E:E,O7) -> 6 | Q7: =COUNTIFS(OFÍCIOS!$E:$E,$O7,OFÍCIOS!$G:$G,"APROVADO") -> 5 | R7: =COUNTIFS(OFÍCIOS!$E:$E,$O7,OFÍCIOS!$G:$G,"REPROVADO") -> 0 | S7: =COUNTIFS(OFÍCIOS!$E:$E,$O7,OFÍCIOS!$G:$G,"PENDENCIA") -> 0 | T7: =COUNTIFS(OFÍCIOS!$E:$E,$O7,OFÍCIOS!$G:$G,"") -> 1 | U7: =SUM(Q7:T7) -> 6 | X7: SS / ANALISE | Y7: 224 | Z7: 275 | AA7: 17
A8: ADAIR DA SILVA BARROS | B8: 97443271620 | E8: 1106 | F8: 42965 | G8: APROVADO | H8: 42978 | O8: 1267 | P8: =COUNTIF(OFÍCIOS!E:E,O8) -> 34 | Q8: =COUNTIFS(OFÍCIOS!$E:$E,$O8,OFÍCIOS!$G:$G,"APROVADO") -> 28 | R8: =COUNTIFS(OFÍCIOS!$E:$E,$O8,OFÍCIOS!$G:$G,"REPROVADO") -> 5 | S8: =COUNTIFS(OFÍCIOS!$E:$E,$O8,OFÍCIOS!$G:$G,"PENDENCIA") -> 1 | T8: =COUNTIFS(OFÍCIOS!$E:$E,$O8,OFÍCIOS!$G:$G,"") -> 0 | U8: =SUM(Q8:T8) -> 34
A9: ADALBERTO CARVALHO DE OLIVEIRA | B9: 98058690597 | E9: 423 | F9: 43182 | G9: APROVADO | O9: 1262 | P9: =COUNTIF(OFÍCIOS!E:E,O9) -> 8 | Q9: =COUNTIFS(OFÍCIOS!$E:$E,$O9,OFÍCIOS!$G:$G,"APROVADO") -> 7 | R9: =COUNTIFS(OFÍCIOS!$E:$E,$O9,OFÍCIOS!$G:$G,"REPROVADO") -> 1 | S9: =COUNTIFS(OFÍCIOS!$E:$E,$O9,OFÍCIOS!$G:$G,"PENDENCIA") -> 0 | T9: =COUNTIFS(OFÍCIOS!$E:$E,$O9,OFÍCIOS!$G:$G,"") -> 0 | U9: =SUM(Q9:T9) -> 8
A10: ADALBERTO CAVALCANTE DOS SANTOS | B10: 38088438888 | O10: 1106 | P10: =COUNTIF(OFÍCIOS!E:E,O10) -> 78 | Q10: =COUNTIFS(OFÍCIOS!$E:$E,$O10,OFÍCIOS!$G:$G,"APROVADO") -> 73 | R10: =COUNTIFS(OFÍCIOS!$E:$E,$O10,OFÍCIOS!$G:$G,"REPROVADO") -> 5 | S10: =COUNTIFS(OFÍCIOS!$E:$E,$O10,OFÍCIOS!$G:$G,"PENDENCIA") -> 0 | T10: =COUNTIFS(OFÍCIOS!$E:$E,$O10,OFÍCIOS!$G:$G,"") -> 0 | U10: =SUM(Q10:T10) -> 78
A11: ADALMA MOREIRA DA ROCHA | B11: 26939799869 | E11: 573 | F11: 43224 | O11: 1128 | P11: =COUNTIF(OFÍCIOS!E:E,O11) -> 92 | Q11: =COUNTIFS(OFÍCIOS!$E:$E,$O11,OFÍCIOS!$G:$G,"APROVADO") -> 91 | R11: =COUNTIFS(OFÍCIOS!$E:$E,$O11,OFÍCIOS!$G:$G,"REPROVADO") -> 1 | S11: =COUNTIFS(OFÍCIOS!$E:$E,$O11,OFÍCIOS!$G:$G,"PENDENCIA") -> 0 | T11: =COUNTIFS(OFÍCIOS!$E:$E,$O11,OFÍCIOS!$G:$G,"") -> 0 | U11: =SUM(Q11:T11) -> 92
A12: ADAMILTON PEREIRA DA SILVA ( ALANA ) | B12: 34470559873 | E12: 292 | F12: 43168 | G12: APROVADO | H12: 43182 | L12: 318 | O12: 1214 | P12: =COUNTIF(OFÍCIOS!E:E,O12) -> 76 | Q12: =COUNTIFS(OFÍCIOS!$E:$E,$O12,OFÍCIOS!$G:$G,"APROVADO") -> 71 | R12: =COUNTIFS(OFÍCIOS!$E:$E,$O12,OFÍCIOS!$G:$G,"REPROVADO") -> 3 | S12: =COUNTIFS(OFÍCIOS!$E:$E,$O12,OFÍCIOS!$G:$G,"PENDENCIA") -> 0 | T12: =COUNTIFS(OFÍCIOS!$E:$E,$O12,OFÍCIOS!$G:$G,"") -> 2 | U12: =SUM(Q12:T12) -> 76
A13: ADAO MENDES AGOSTINHO | B13: 14369564808 | O13: 1241 | P13: =COUNTIF(OFÍCIOS!E:E,O13) -> 33 | Q13: =COUNTIFS(OFÍCIOS!$E:$E,$O13,OFÍCIOS!$G:$G,"APROVADO") -> 32 | R13: =COUNTIFS(OFÍCIOS!$E:$E,$O13,OFÍCIOS!$G:$G,"REPROVADO") -> 0 | S13: =COUNTIFS(OFÍCIOS!$E:$E,$O13,OFÍCIOS!$G:$G,"PENDENCIA") -> 1 | T13: =COUNTIFS(OFÍCIOS!$E:$E,$O13,OFÍCIOS!$G:$G,"") -> 0 | U13: =SUM(Q13:T13) -> 33
A14: ADEGMARIO DOS SANTOS | B14: 39544185844 | E14: 810 | F14: 42915 | G14: APROVADO | H14: 42921 | L14: 568-17 | O14: 1422 | P14: =COUNTIF(OFÍCIOS!E:E,O14) -> 7 | Q14: =COUNTIFS(OFÍCIOS!$E:$E,$O14,OFÍCIOS!$G:$G,"APROVADO") -> 7 | R14: =COUNTIFS(OFÍCIOS!$E:$E,$O14,OFÍCIOS!$G:$G,"REPROVADO") -> 0 | S14: =COUNTIFS(OFÍCIOS!$E:$E,$O14,OFÍCIOS!$G:$G,"PENDENCIA") -> 0 | T14: =COUNTIFS(OFÍCIOS!$E:$E,$O14,OFÍCIOS!$G:$G,"") -> 0 | U14: =SUM(Q14:T14) -> 7
A15: ADEILDA GABRIELA CAITANO SILVA | B15: 38772276860 | C15: LUCIANO MANOEL DA SILVA | D15: 3808243457 | O15: 1439 | P15: =COUNTIF(OFÍCIOS!E:E,O15) -> 16 | Q15: =COUNTIFS(OFÍCIOS!$E:$E,$O15,OFÍCIOS!$G:$G,"APROVADO") -> 14 | R15: =COUNTIFS(OFÍCIOS!$E:$E,$O15,OFÍCIOS!$G:$G,"REPROVADO") -> 1 | S15: =COUNTIFS(OFÍCIOS!$E:$E,$O15,OFÍCIOS!$G:$G,"PENDENCIA") -> 1 | T15: =COUNTIFS(OFÍCIOS!$E:$E,$O15,OFÍCIOS!$G:$G,"") -> 0 | U15: =SUM(Q15:T15) -> 16
A16: ADEILDA RODRIGUES DE OLIVEIRA | B16: 21538837846 | C16: PEDRO LUIZ SANTOS OLIVEIRA | D16: 94203180520 | E16: 810 | F16: 42915 | G16: APROVADO | H16: 42921 | L16: 568-17 | O16: 1451 | P16: =COUNTIF(OFÍCIOS!E:E,O16) -> 4 | Q16: =COUNTIFS(OFÍCIOS!$E:$E,$O16,OFÍCIOS!$G:$G,"APROVADO") -> 3 | R16: =COUNTIFS(OFÍCIOS!$E:$E,$O16,OFÍCIOS!$G:$G,"REPROVADO") -> 1 | S16: =COUNTIFS(OFÍCIOS!$E:$E,$O16,OFÍCIOS!$G:$G,"PENDENCIA") -> 0 | T16: =COUNTIFS(OFÍCIOS!$E:$E,$O16,OFÍCIOS!$G:$G,"") -> 0 | U16: =SUM(Q16:T16) -> 4
A17: ADEILDO ADELINO DE CARVALHO | B17: 57455392591 | O17: 1470 | P17: =COUNTIF(OFÍCIOS!E:E,O17) -> 4 | Q17: =COUNTIFS(OFÍCIOS!$E:$E,$O17,OFÍCIOS!$G:$G,"APROVADO") -> 4 | R17: =COUNTIFS(OFÍCIOS!$E:$E,$O17,OFÍCIOS!$G:$G,"REPROVADO") -> 0 | S17: =COUNTIFS(OFÍCIOS!$E:$E,$O17,OFÍCIOS!$G:$G,"PENDENCIA") -> 0 | T17: =COUNTIFS(OFÍCIOS!$E:$E,$O17,OFÍCIOS!$G:$G,"") -> 0 | U17: =SUM(Q17:T17) -> 4
A18: ADELCIDES DA CONCEICAO ALMEIDA | B18: 5304941594 | E18: 1106 | F18: 42965 | G18: APROVADO | H18: 42978 | O18: 1489 | P18: =COUNTIF(OFÍCIOS!E:E,O18) -> 35 | Q18: =COUNTIFS(OFÍCIOS!$E:$E,$O18,OFÍCIOS!$G:$G,"APROVADO") -> 34 | R18: =COUNTIFS(OFÍCIOS!$E:$E,$O18,OFÍCIOS!$G:$G,"REPROVADO") -> 0 | S18: =COUNTIFS(OFÍCIOS!$E:$E,$O18,OFÍCIOS!$G:$G,"PENDENCIA") -> 1 | T18: =COUNTIFS(OFÍCIOS!$E:$E,$O18,OFÍCIOS!$G:$G,"") -> 0 | U18: =SUM(Q18:T18) -> 35
A19: ADELIA MARIA DE OLIVEIRA | B19: 21600057896 | E19: 262 | F19: 43160 | G19: REPROVADO | H19: 43164 | L19: 255 | O19: 1555 | P19: =COUNTIF(OFÍCIOS!E:E,O19) -> 25 | Q19: =COUNTIFS(OFÍCIOS!$E:$E,$O19,OFÍCIOS!$G:$G,"APROVADO") -> 22 | R19: =COUNTIFS(OFÍCIOS!$E:$E,$O19,OFÍCIOS!$G:$G,"REPROVADO") -> 1 | S19: =COUNTIFS(OFÍCIOS!$E:$E,$O19,OFÍCIOS!$G:$G,"PENDENCIA") -> 2 | T19: =COUNTIFS(OFÍCIOS!$E:$E,$O19,OFÍCIOS!$G:$G,"") -> 0 | U19: =SUM(Q19:T19) -> 25
A20: ADEMARIO FERREIRA DOS SANTOS | B20: 18419589802 | O20: 1570 | P20: =COUNTIF(OFÍCIOS!E:E,O20) -> 24 | Q20: =COUNTIFS(OFÍCIOS!$E:$E,$O20,OFÍCIOS!$G:$G,"APROVADO") -> 23 | R20: =COUNTIFS(OFÍCIOS!$E:$E,$O20,OFÍCIOS!$G:$G,"REPROVADO") -> 1 | S20: =COUNTIFS(OFÍCIOS!$E:$E,$O20,OFÍCIOS!$G:$G,"PENDENCIA") -> 0 | T20: =COUNTIFS(OFÍCIOS!$E:$E,$O20,OFÍCIOS!$G:$G,"") -> 0 | U20: =SUM(Q20:T20) -> 24
A21: ADEMIR DA SILVA LIMA | B21: 15538537846 | E21: 573 | F21: 43224 | O21: 1752 | P21: =COUNTIF(OFÍCIOS!E:E,O21) -> 89 | Q21: =COUNTIFS(OFÍCIOS!$E:$E,$O21,OFÍCIOS!$G:$G,"APROVADO") -> 80 | R21: =COUNTIFS(OFÍCIOS!$E:$E,$O21,OFÍCIOS!$G:$G,"REPROVADO") -> 2 | S21: =COUNTIFS(OFÍCIOS!$E:$E,$O21,OFÍCIOS!$G:$G,"PENDENCIA") -> 5 | T21: =COUNTIFS(OFÍCIOS!$E:$E,$O21,OFÍCIOS!$G:$G,"") -> 2 | U21: =SUM(Q21:T21) -> 89
A22: ADENILDE SANTOS DA SILVA | B22: 899837506 | E22: 1824 | F22: 43091 | G22: APROVADO | H22: 43097 | L22: 1828 | O22: 1824 | P22: =COUNTIF(OFÍCIOS!E:E,O22) -> 81 | Q22: =COUNTIFS(OFÍCIOS!$E:$E,$O22,OFÍCIOS!$G:$G,"APROVADO") -> 67 | R22: =COUNTIFS(OFÍCIOS!$E:$E,$O22,OFÍCIOS!$G:$G,"REPROVADO") -> 7 | S22: =COUNTIFS(OFÍCIOS!$E:$E,$O22,OFÍCIOS!$G:$G,"PENDENCIA") -> 6 | T22: =COUNTIFS(OFÍCIOS!$E:$E,$O22,OFÍCIOS!$G:$G,"") -> 1 | U22: =SUM(Q22:T22) -> 81
A23: ADENILSON DA CONCEICAO | B23: 36197160803 | E23: 229 | F23: 43151 | G23: APROVADO | L23: 232 | O23: 1628 | P23: =COUNTIF(OFÍCIOS!E:E,O23) -> 6 | Q23: =COUNTIFS(OFÍCIOS!$E:$E,$O23,OFÍCIOS!$G:$G,"APROVADO") -> 5 | R23: =COUNTIFS(OFÍCIOS!$E:$E,$O23,OFÍCIOS!$G:$G,"REPROVADO") -> 1 | S23: =COUNTIFS(OFÍCIOS!$E:$E,$O23,OFÍCIOS!$G:$G,"PENDENCIA") -> 0 | T23: =COUNTIFS(OFÍCIOS!$E:$E,$O23,OFÍCIOS!$G:$G,"") -> 0 | U23: =SUM(Q23:T23) -> 6
A24: ADENIR MODESTO RIBEIRO | B24: 39248826814 | E24: 292 | F24: 43168 | G24: APROVADO | H24: 43182 | L24: 318 | O24: 608 | P24: =COUNTIF(OFÍCIOS!E:E,O24) -> 35 | Q24: =COUNTIFS(OFÍCIOS!$E:$E,$O24,OFÍCIOS!$G:$G,"APROVADO") -> 31 | R24: =COUNTIFS(OFÍCIOS!$E:$E,$O24,OFÍCIOS!$G:$G,"REPROVADO") -> 3 | S24: =COUNTIFS(OFÍCIOS!$E:$E,$O24,OFÍCIOS!$G:$G,"PENDENCIA") -> 1 | T24: =COUNTIFS(OFÍCIOS!$E:$E,$O24,OFÍCIOS!$G:$G,"") -> 0 | U24: =SUM(Q24:T24) -> 35
A25: ADILINA FARIAS DO NASCIMENTO | B25: 48925276534 | E25: 229 | F25: 43151 | L25: 232 | O25: 527 | P25: =COUNTIF(OFÍCIOS!E:E,O25) -> 29 | Q25: =COUNTIFS(OFÍCIOS!$E:$E,$O25,OFÍCIOS!$G:$G,"APROVADO") -> 0 | R25: =COUNTIFS(OFÍCIOS!$E:$E,$O25,OFÍCIOS!$G:$G,"REPROVADO") -> 0 | S25: =COUNTIFS(OFÍCIOS!$E:$E,$O25,OFÍCIOS!$G:$G,"PENDENCIA") -> 0 | T25: =COUNTIFS(OFÍCIOS!$E:$E,$O25,OFÍCIOS!$G:$G,"") -> 29 | U25: =SUM(Q25:T25) -> 29
A26: ADILSON SOARES DA COSTA | O26: 509 | P26: =COUNTIF(OFÍCIOS!E:E,O26) -> 14 | Q26: =COUNTIFS(OFÍCIOS!$E:$E,$O26,OFÍCIOS!$G:$G,"APROVADO") -> 0 | R26: =COUNTIFS(OFÍCIOS!$E:$E,$O26,OFÍCIOS!$G:$G,"REPROVADO") -> 0 | S26: =COUNTIFS(OFÍCIOS!$E:$E,$O26,OFÍCIOS!$G:$G,"PENDENCIA") -> 0 | T26: =COUNTIFS(OFÍCIOS!$E:$E,$O26,OFÍCIOS!$G:$G,"") -> 14 | U26: =SUM(Q26:T26) -> 14
A27: ADMEIA BARBOSA DE SOUZA | B27: 25894152810 | C27: REINALDO SANTOS REIS | D27: 8263008808 | E27: 292 | F27: 43168 | G27: APROVADO | H27: 43182 | L27: 318 | O27: 292 | P27: =COUNTIF(OFÍCIOS!E:E,O27) -> 233 | Q27: =COUNTIFS(OFÍCIOS!$E:$E,$O27,OFÍCIOS!$G:$G,"APROVADO") -> 212 | R27: =COUNTIFS(OFÍCIOS!$E:$E,$O27,OFÍCIOS!$G:$G,"REPROVADO") -> 9 | S27: =COUNTIFS(OFÍCIOS!$E:$E,$O27,OFÍCIOS!$G:$G,"PENDENCIA") -> 0 | T27: =COUNTIFS(OFÍCIOS!$E:$E,$O27,OFÍCIOS!$G:$G,"") -> 12 | U27: =SUM(Q27:T27) -> 233
A28: ADONES FERREIRA JORGE | B28: 43026389587 | C28: EUNICE FELICIANA BRITO JORGE | D28: 29124464813 | E28: 485 | F28: 43196 | H28: 43206 | L28: 483 | O28: 573 | P28: =COUNTIF(OFÍCIOS!E:E,O28) -> 43 | Q28: =COUNTIFS(OFÍCIOS!$E:$E,$O28,OFÍCIOS!$G:$G,"APROVADO") -> 0 | R28: =COUNTIFS(OFÍCIOS!$E:$E,$O28,OFÍCIOS!$G:$G,"REPROVADO") -> 0 | S28: =COUNTIFS(OFÍCIOS!$E:$E,$O28,OFÍCIOS!$G:$G,"PENDENCIA") -> 0 | T28: =COUNTIFS(OFÍCIOS!$E:$E,$O28,OFÍCIOS!$G:$G,"") -> 43 | U28: =SUM(Q28:T28) -> 43
A29: ADRIANA ALVES DA SILVA | B29: 26245112885 | E29: 262 | F29: 43160 | G29: REPROVADO | H29: 43164 | L29: 255 | O29: 563 | P29: =COUNTIF(OFÍCIOS!E:E,O29) -> 64 | Q29: =COUNTIFS(OFÍCIOS!$E:$E,$O29,OFÍCIOS!$G:$G,"APROVADO") -> 0 | R29: =COUNTIFS(OFÍCIOS!$E:$E,$O29,OFÍCIOS!$G:$G,"REPROVADO") -> 0 | S29: =COUNTIFS(OFÍCIOS!$E:$E,$O29,OFÍCIOS!$G:$G,"PENDENCIA") -> 0 | T29: =COUNTIFS(OFÍCIOS!$E:$E,$O29,OFÍCIOS!$G:$G,"") -> 64 | U29: =SUM(Q29:T29) -> 64
A30: ADRIANA ALVES FERREIRA | B30: 36531080809 | C30: MARCIO ROSA DE MIRA | D30: 22485483892 | E30: 1489 | F30: 43038 | G30: APROVADO | L30: 1647-17 | O30: 443 | P30: =COUNTIF(OFÍCIOS!E:E,O30) -> 66 | Q30: =COUNTIFS(OFÍCIOS!$E:$E,$O30,OFÍCIOS!$G:$G,"APROVADO") -> 0 | R30: =COUNTIFS(OFÍCIOS!$E:$E,$O30,OFÍCIOS!$G:$G,"REPROVADO") -> 0 | S30: =COUNTIFS(OFÍCIOS!$E:$E,$O30,OFÍCIOS!$G:$G,"PENDENCIA") -> 0 | T30: =COUNTIFS(OFÍCIOS!$E:$E,$O30,OFÍCIOS!$G:$G,"") -> 66 | U30: =SUM(Q30:T30) -> 66
A31: ADRIANA APARECIDA ROBERTO | B31: 28147186819 | C31: CARLOS ANTONIO BATISTA DOS SANTOS | D31: 24499714400 | O31: 423 | P31: =COUNTIF(OFÍCIOS!E:E,O31) -> 9 | Q31: =COUNTIFS(OFÍCIOS!$E:$E,$O31,OFÍCIOS!$G:$G,"APROVADO") -> 7 | R31: =COUNTIFS(OFÍCIOS!$E:$E,$O31,OFÍCIOS!$G:$G,"REPROVADO") -> 1 | S31: =COUNTIFS(OFÍCIOS!$E:$E,$O31,OFÍCIOS!$G:$G,"PENDENCIA") -> 0 | T31: =COUNTIFS(OFÍCIOS!$E:$E,$O31,OFÍCIOS!$G:$G,"") -> 1 | U31: =SUM(Q31:T31) -> 9
A32: ADRIANA ARAUJO DE LIMA | B32: 37559228860 | C32: ALEXANDRO ARAUJO DE LIMA | D32: 28072024892 | E32: 1555 | F32: 43049 | G32: APROVADO | O32: 229 | P32: =COUNTIF(OFÍCIOS!E:E,O32) -> 89 | Q32: =COUNTIFS(OFÍCIOS!$E:$E,$O32,OFÍCIOS!$G:$G,"APROVADO") -> 81 | R32: =COUNTIFS(OFÍCIOS!$E:$E,$O32,OFÍCIOS!$G:$G,"REPROVADO") -> 2 | S32: =COUNTIFS(OFÍCIOS!$E:$E,$O32,OFÍCIOS!$G:$G,"PENDENCIA") -> 5 | T32: =COUNTIFS(OFÍCIOS!$E:$E,$O32,OFÍCIOS!$G:$G,"") -> 1 | U32: =SUM(Q32:T32) -> 89
A33: ADRIANA CORDEIRO MACHADO | B33: 23635229822 | C33: ANDERSON DE MORAIS SANTOS | D33: 21668057875 | E33: 262 | F33: 43160 | G33: APROVADO | H33: 43164 | L33: 255 | O33: 262 | P33: =COUNTIF(OFÍCIOS!E:E,O33) -> 224 | Q33: =COUNTIFS(OFÍCIOS!$E:$E,$O33,OFÍCIOS!$G:$G,"APROVADO") -> 181 | R33: =COUNTIFS(OFÍCIOS!$E:$E,$O33,OFÍCIOS!$G:$G,"REPROVADO") -> 15 | S33: =COUNTIFS(OFÍCIOS!$E:$E,$O33,OFÍCIOS!$G:$G,"PENDENCIA") -> 0 | T33: =COUNTIFS(OFÍCIOS!$E:$E,$O33,OFÍCIOS!$G:$G,"") -> 28 | U33: =SUM(Q33:T33) -> 224
A34: ADRIANA DA SILVA | O34: 117 | P34: =COUNTIF(OFÍCIOS!E:E,O34) -> 91 | Q34: =COUNTIFS(OFÍCIOS!$E:$E,$O34,OFÍCIOS!$G:$G,"APROVADO") -> 77 | R34: =COUNTIFS(OFÍCIOS!$E:$E,$O34,OFÍCIOS!$G:$G,"REPROVADO") -> 7 | S34: =COUNTIFS(OFÍCIOS!$E:$E,$O34,OFÍCIOS!$G:$G,"PENDENCIA") -> 5 | T34: =COUNTIFS(OFÍCIOS!$E:$E,$O34,OFÍCIOS!$G:$G,"") -> 2 | U34: =SUM(Q34:T34) -> 91
A35: ADRIANA DA SILVA SANTOS | B35: 40902634844 | C35: GUILHERME DE OLIVEIRA SOUZA | D35: 23795007895 | E35: 117 | F35: 43117 | G35: APROVADO | H35: 43151 | L35: 118-18 | O35: 485 | P35: =COUNTIF(OFÍCIOS!E:E,O35) -> 23 | Q35: =COUNTIFS(OFÍCIOS!$E:$E,$O35,OFÍCIOS!$G:$G,"APROVADO") -> 0 | R35: =COUNTIFS(OFÍCIOS!$E:$E,$O35,OFÍCIOS!$G:$G,"REPROVADO") -> 3 | S35: =COUNTIFS(OFÍCIOS!$E:$E,$O35,OFÍCIOS!$G:$G,"PENDENCIA") -> 0 | T35: =COUNTIFS(OFÍCIOS!$E:$E,$O35,OFÍCIOS!$G:$G,"") -> 20 | U35: =SUM(Q35:T35) -> 23
A36: ADRIANA DE SA ROCHA | B36: 39615629898 | C36: MARCELO FERNANDES LIMA | D36: 43328275894 | E36: 423 | F36: 43182 | G36: APROVADO | O36: 85 | P36: =COUNTIF(OFÍCIOS!E:E,O36) -> 93 | Q36: =COUNTIFS(OFÍCIOS!$E:$E,$O36,OFÍCIOS!$G:$G,"APROVADO") -> 86 | R36: =COUNTIFS(OFÍCIOS!$E:$E,$O36,OFÍCIOS!$G:$G,"REPROVADO") -> 4 | S36: =COUNTIFS(OFÍCIOS!$E:$E,$O36,OFÍCIOS!$G:$G,"PENDENCIA") -> 3 | T36: =COUNTIFS(OFÍCIOS!$E:$E,$O36,OFÍCIOS!$G:$G,"") -> 0 | U36: =SUM(Q36:T36) -> 93
A37: ADRIANA DOS SANTOS | P37: =COUNTIF(OFÍCIOS!E:E,O37) -> 0 | Q37: =COUNTIFS(OFÍCIOS!$E:$E,$O37,OFÍCIOS!$G:$G,"APROVADO") -> 0 | R37: =COUNTIFS(OFÍCIOS!$E:$E,$O37,OFÍCIOS!$G:$G,"REPROVADO") -> 0 | S37: =COUNTIFS(OFÍCIOS!$E:$E,$O37,OFÍCIOS!$G:$G,"PENDENCIA") -> 0 | T37: =COUNTIFS(OFÍCIOS!$E:$E,$O37,OFÍCIOS!$G:$G,"") -> 0 | U37: =SUM(Q37:T37) -> 0
A38: ADRIANA FERREIRA DA SILVA | C38: LOURIVAL CANDIDO SILVA | P38: =COUNTIF(OFÍCIOS!E:E,O38) -> 0 | Q38: =COUNTIFS(OFÍCIOS!$E:$E,$O38,OFÍCIOS!$G:$G,"APROVADO") -> 0 | R38: =COUNTIFS(OFÍCIOS!$E:$E,$O38,OFÍCIOS!$G:$G,"REPROVADO") -> 0 | S38: =COUNTIFS(OFÍCIOS!$E:$E,$O38,OFÍCIOS!$G:$G,"PENDENCIA") -> 0 | T38: =COUNTIFS(OFÍCIOS!$E:$E,$O38,OFÍCIOS!$G:$G,"") -> 0 | U38: =SUM(Q38:T38) -> 0
A39: ADRIANA HELENA DE MORAIS | B39: 14268808809 | E39: 262 | F39: 43160 | G39: APROVADO | H39: 43164 | L39: 255 | P39: =COUNTIF(OFÍCIOS!E:E,O39) -> 0 | Q39: =COUNTIFS(OFÍCIOS!$E:$E,$O39,OFÍCIOS!$G:$G,"APROVADO") -> 0 | R39: =COUNTIFS(OFÍCIOS!$E:$E,$O39,OFÍCIOS!$G:$G,"REPROVADO") -> 0 | S39: =COUNTIFS(OFÍCIOS!$E:$E,$O39,OFÍCIOS!$G:$G,"PENDENCIA") -> 0 | T39: =COUNTIFS(OFÍCIOS!$E:$E,$O39,OFÍCIOS!$G:$G,"") -> 0 | U39: =SUM(Q39:T39) -> 0
A40: ADRIANA JESUS DA CUNHA | B40: 29628693867 | E40: 292 | F40: 43168 | G40: APROVADO | H40: 43182 | L40: 318 | P40: =COUNTIF(OFÍCIOS!E:E,O40) -> 0 | Q40: =COUNTIFS(OFÍCIOS!$E:$E,$O40,OFÍCIOS!$G:$G,"APROVADO") -> 0 | R40: =COUNTIFS(OFÍCIOS!$E:$E,$O40,OFÍCIOS!$G:$G,"REPROVADO") -> 0 | S40: =COUNTIFS(OFÍCIOS!$E:$E,$O40,OFÍCIOS!$G:$G,"PENDENCIA") -> 0 | T40: =COUNTIFS(OFÍCIOS!$E:$E,$O40,OFÍCIOS!$G:$G,"") -> 0 | U40: =SUM(Q40:T40) -> 0
A41: ADRIANA LINO PEIXOTO | B41: 35762862844 | E41: 1106 | F41: 42965 | G41: APROVADO | H41: 42978 | P41: =COUNTIF(OFÍCIOS!E:E,O41) -> 0 | Q41: =COUNTIFS(OFÍCIOS!$E:$E,$O41,OFÍCIOS!$G:$G,"APROVADO") -> 0 | R41: =COUNTIFS(OFÍCIOS!$E:$E,$O41,OFÍCIOS!$G:$G,"REPROVADO") -> 0 | S41: =COUNTIFS(OFÍCIOS!$E:$E,$O41,OFÍCIOS!$G:$G,"PENDENCIA") -> 0 | T41: =COUNTIFS(OFÍCIOS!$E:$E,$O41,OFÍCIOS!$G:$G,"") -> 0 | U41: =SUM(Q41:T41) -> 0
A42: ADRIANA MARIA ALVES XAVIER (ALTERACAO DE NOME ADRIANA MARIA ALVES DOS SANTOS) | B42: 10201704412 | C42: CLAUDIO XAVIER SANTANA | D42: 33674895811 | E42: 262 | F42: 43160 | G42: APROVADO | H42: 43164 | L42: 255 | O42: TOTAIS | P42: =SUM(P3:P36) -> 1922 | Q42: =SUM(Q3:Q36) -> 1514 | R42: =SUM(R3:R36) -> 83 | S42: =SUM(S3:S36) -> 36 | T42: =SUM(T3:T36) -> 289 | U42: =SUM(U3:U36) -> 1922
A43: ADRIANA MEDEIROS DE OLIVEIRA SANTOS | B43: 35271487873 | C43: CLEITON SOUSA SANTOS | D43: 557351502 | E43: 1128 | F43: 42972 | G43: APROVADO | H43: 42979
A44: ADRIANA PEREIRA DE JESUS | B44: 22360217801 | E44: 1128 | F44: 42972 | G44: APROVADO | H44: 42979
A45: ADRIANA PINHEIRO MOREIRA | B45: 36930783862 | E45: 443 | F45: 43188 | H45: 43192
A46: ADRIANA PONCIANO DA SILVA | B46: 36647299866 | E46: 292 | F46: 43168 | G46: APROVADO | H46: 43182 | L46: 318
A47: ADRIANA PORTE | B47: 31801479895 | C47: ISAQUE PINTO DA SILVA | D47: 23103908873
A48: ADRIANA ROBERTA SILVA ANDRADE | B48: 28638653824 | C48: JOSE ROMILDO SILVA ANDRADE | D48: 50160249520
A49: ADRIANA ROQUE DOS SANTOS | B49: 17766101807 | C49: MARCOS ELIAS DOS SANTOS | D49: 31993041842 | E49: 1824 | F49: 43091 | G49: APROVADO | H49: 43097 | L49: 1828
A50: ADRIANA SABINO NOGUEIRA | B50: 17902799840 | C50: JOYCE CRISTINA NOGUEIRA DO CARMO | D50: 44230035896
A51: ADRIANA SANTANA SANTOS | B51: 49122403892 | C51: ETVALDO BERTO DA SILVA | D51: 1478139560 | E51: 608 | F51: 43012 | G51: APROVADO | H51: 43024 | O51: OFÍCIO DE REANÁLISE 019/18 - 05/06/18
A52: ADRIANA SANTOS RIBEIRO | B52: 37534302854 | C52: EDLANDIO BISPO SILVA | D52: 1689246502
A53: ADRIANA SEVERINO SANTANA | B53: 14699996841 | C53: FERNANDO FERREIRA SILVA | D53: 15089706883 | E53: 1128 | F53: 42972 | G53: APROVADO | H53: 42979
A54: ADRIANA TENORIO DA SILVA | B54: 47077408809
A55: ADRIANE MOREIRA DOS SANTOS | B55: 40396239838 | C55: JEFERSON DA SILVA DE JESUS | D55: 39420747883 | E55: 262 | F55: 43160 | G55: APROVADO | H55: 43164 | L55: 255
A56: ADRIANO ALVES BARBOSA | B56: 41333062877 | E56: 292 | F56: 43168 | G56: APROVADO | H56: 43182 | L56: 318
A57: ADRIANO HENRIQUE DA COSTA | B57: 38781151802
A58: ADRIANO PEREIRA DOS SANTOS
A59: ADRIELLE DOS PASSOS DE SOUZA | B59: 2428277219 | C59: DIVANILDO SOUZA DOS PASSOS | D59: 909805229 | E59: 810 | F59: 42915 | G59: APROVADO | H59: 42921 | L59: 568-17
A60: AGDA APARECIDA PEREIRA | B60: 16417464830
A61: AGNALDO ALTMANN | B61: 7104481800 | E61: 262 | F61: 43160 | G61: APROVADO | H61: 43164 | L61: 255
A62: AGNALDO LOPES GONCALVES FILHO | B62: 25023266800
A63: AGOSTINHO FERNANDES SILVA | B63: 3722493889 | C63: FRANCISCA GOMES DE OLIVEIRA | D63: 32416642871
A64: AIDEE MARIA DOS SANTOS | B64: 14519340845 | C64: SIORLANDIO DOS SANTOS FALCAO | D64: 88489795568 | E64: 262 | F64: 43160 | H64: 43164 | L64: 255
A65: AILTON WILLIAN MELLO | B65: 19266484806
A66: ALADIM PINHEIRO DOS SANTOS | B66: 15322188851
A67: ALAILTON COSTA DE SOUZA | B67: 36392955879 | C67: AMANDA CRISTINA SILVEIRA DA SILVA | D67: 5242864346 | E67: 117 | F67: 43117 | G67: APROVADO | H67: 43151 | L67: 118-18
A68: ALAN DE JESUS PASSOS | B68: 41482647800 | E68: 1262 | F68: 42997 | G68: APROVADO | H68: 43000
A69: ALBERT PEREIRA DOS SANTOS | B69: 47629183852
A70: ALBERTINA CANDIDO RIBEIRO GOMES | B70: 9882942490 | C70: DENIS JOSE GOMES | D70: 9704111460
A71: ALBERTINA PEREIRA COSTA | B71: 14777572870 | C71: EDIVALDO ALVES DE SOUZA | D71: 12874739898 | E71: 1824 | F71: 43091 | G71: APROVADO | H71: 43097 | L71: 1828
A72: ALCIDINEY DA SILVA | B72: 31996709895
A73: ALCILENE GUEDES DA SILVA | B73: 26824046850 | E73: 1824 | F73: 43091 | G73: APROVADO | H73: 43097 | L73: 1828
A74: ALCIONE BARBOSA DE SOUSA | B74: 3523524342 | E74: 85 | F74: 43109 | G74: APROVADO | H74: 43151
A75: ALDA DE JESUS GONCALVES | B75: 26940268855 | C75: JUCELINO ALVES DE LIMA
A76: ALDA MARIA DE JESUS | B76: 24828498885 | E76: 1489 | F76: 43038 | G76: APROVADO | L76: 1647-17
A77: ALDA REJANE SANTOS | B77: 11482307855 | E77: 85 | F77: 43109 | G77: APROVADO | H77: 43151
A78: ALDERLANDIA DE OLIVEIRA MONTEIRO | B78: 42352732808 | C78: JOSE SOARES DA SILVA | D78: 281893373 | E78: 1214 | F78: 42989 | G78: APROVADO | H78: 43000
A79: ALESILVIA RAIMUNDO DA SILVA NEVES | B79: 13480043801 | C79: CLAUDIO RIBEIRO NEVES | D79: 67141536604
A80: ALESSANDRA APARECIDA DE JESUS | B80: 31874522804 | E80: 292 | F80: 43168 | G80: APROVADO | H80: 43182 | L80: 318
A81: ALESSANDRA CABRAL DA SILVA | B81: 28889575824 | E81: 1241 | F81: 42992 | G81: APROVADO | H81: 42998
A82: ALESSANDRA JUVINA DA SILVA | B82: 21734589817 | E82: 229 | F82: 43151 | G82: APROVADO | L82: 232
A83: ALESSANDRA LIMA DA SILVA
A84: ALESSANDRA LUNA DA SILVA | B84: 18475875858
A85: ALESSANDRA MARQUES DOS SANTOS | B85: 40443882886 | E85: 509 | F85: 43203 | H85: 43213
A86: ALESSANDRA MARTINS DA SILVA | B86: 43053250802 | C86: IUDARLAN MARTINS DA SILVA | D86: 35893147880 | E86: 1128 | F86: 42972 | G86: APROVADO
A87: ALESSANDRA MILAGRES PIROTTI | B87: 28255807837 | E87: 292 | F87: 43168 | G87: APROVADO | L87: 318
A88: ALESSANDRA MONTEIRO DA SILVA | B88: 33617584837 | C88: ASTROGILDO APARECIDO CURY DE ARAUJO | D88: 26520094862 | E88: 608 | F88: 43012 | G88: APROVADO
A89: ALESSANDRA QUARESMA DA SILVA | B89: 38168161858 | C89: WALLACE DIEGO HENRIQUE BISPO | D89: 24059422835
A90: ALESSANDRO ARAUJO DA SILVA COSTA | B90: 38728353862 | C90: LIZIANE ROCHA DA SILVA COSTA | D90: 37650358828 | E90: 1417 | F90: 43017 | G90: APROVADO | L90: 1017-17
A91: ALEX DE JESUS PEREIRA | B91: 29479419858 | C91: JOILMA DE JESUS FERREIRA | D91: 71909656534
A92: ALEX JOSE CATARINO ASSUNCAO | B92: 37634689866 | E92: 443 | F92: 43188
A93: ALEXANDRA APARECIDA DA SILVA BARBOZA | B93: 22656606802 | E93: 1555 | F93: 43049 | G93: APROVADO
A94: ALEXANDRA SANTOS DE PAULA | B94: 4248144638 | E94: 229 | F94: 43151 | G94: APROVADO | L94: 232
A95: ALEXANDRE OLIVEIRA SILVA | B95: 29998933889
A96: ALEXANDRE SATELES DOS SANTOS | B96: 2963904533 | E96: 1489 | F96: 43038 | G96: APROVADO | L96: 1647-17
A97: ALEXANDRE VALENTIN DE SOUZA | B97: 23256005802 | E97: 1350 | F97: 43006 | G97: APROVADO
A98: ALEXSANDRA BORGES GONCALVES | B98: 3317260505 | C98: GILDECI FERREIRA CORDEIRO | D98: 92396607634
A99: ALEXSANDRA FRANCA DA SILVA | B99: 36234875890 | E99: 1128 | F99: 42972 | G99: APROVADO
A100: ALEXSANDRA MARIA DA SILVA | B100: 1243618469 | E100: 262 | F100: 43160 | G100: APROVADO | H100: 43164 | L100: 255
...

Sheet PRIORIDADES
A3: INFORMAÇÕES INICIAIS | O3: INFORMAÇÕES AUXÍLIO ALUGUEL | AA3: INFORMAÇÕES INDENIZAÇÃO | BG3: PROCESSO ATENDIMENTO HABITACIONAL
A4: ORDEM | B4: ÁREA | C4: TRECHO | D4: FASE | E4: PRIORIDADE | F4: SELO | G4: SITUAÇÃO INICIAL IMÓVEL | H4: USO IMÓVEL | I4: SITUAÇÃO DO RESIDENTE | J4: TITULAR | K4: RG | L4: CPF | M4: CADASTRO HABITA SAMPA | N4: OPÇÃO DE ATENDIMENTO HABITACIONAL | O4: SOLICITAÇÃO AUXÍLIO ALUGUEL ÁREA | P4: No PROCESSO SEI (AUXÍLIO ALUGUEL) | Q4: ANÁLISE DTS CADASTRO + CHECAGEM DUPLO | R4: INSTRUÇÃO PROCESSO SEI DTS | S4: ANÁLISE CTS ASSINATURA GABINETE | T4: DATA PUBLICAÇÃO DIÁRIO OFICIAL | U4: CONFECÇÃO TERMO | V4: ENVIO TERMO CARTÃO | W4: PREVISÃO PAGAMENTO | X4: DATA SAQUE | Y4: DATA MUDANÇA | Z4: OBSERVAÇÕES AA | AA4: PROPRIETÁRIO | AB4: RG | AC4: CPF | AD4: SITUAÇÃO DO PROPRIETÁRIO | AE4: CADASTRO HABITASAMPA | AF4: VALOR AVALIAÇÃO | AG4: VALOR INDENIZAÇÃO | AH4: ACEITA VALOR INDENIZAÇÃO | AI4: Nº SEI LAUDOS AVALIAÇÃO | AJ4: Nº DOCUMENTO LAUDO | AK4: RECEBIMENTO TERMO CTS | AL4: CONFERÊNCIA TERMO CTS | AM4: ENVIO ASSINATURA CTS | AN4: ENVIO ASSINATURA GAB | AO4: RETORNO TERMO GAB | AP4: ENVIO TERMO DTS | AQ4: EM CORREÇÃO | AR4: STATUS TERMO INDENIZAÇÃO | AS4: PENDÊNCIA | AT4: OBSERVAÇÕES INDENIZAÇÃO | AU4: No PROCESSO SEI (INDENIZAÇÃO) | AV4: INSTRUÇÃO PROCESSO SEI DTS | AW4: ASSINATURA DIRETOR DTS | AX4: ELABORAÇÃO DESPACHO CTS | AY4: ASSINATURA DESPACHO GABINETE | AZ4: PUBLICAÇÃO DIÁRIO OFICIAL | BA4: ENCAMINHAMENTO DAF/DIF CTS | BB4: LIBERAÇÃO PAGAMENTO DAF/DIF | BC4: PREVISÃO PAGAMENTO | BD4: DATA PAGAMENTO | BE4: DATA ENTREGA IMÓVEL | BF4: SITUAÇÃO ATUAL IMÓVEL | BG4: STATUS | BH4: DIAS TOTAIS | BI4: OPÇÃO ATENDIMENTO | BJ4: NECESSITA BLOQUEIO AA | BK4: SOLICITAÇÃO BLOQUEIO AA DTS | BL4: SOLICITAÇÃO BLOQUEIO AA | BM4: DATA BLOQUEIO AA | BN4: DESPACHO EXCLUSÃO GABINETE | BO4: ASSINATURA DESPACHO GABINETE | BP4: PUBLICAÇÃO DOC | BQ4: ENCAMINHAMENTO SOLICITAÇÃO EXCLUSÃO DEPLAN | BR4: ENCERRAMENTO PROCESSO DTS
A5: 1 | B5: JD. PANTANAL | C5: NOVO HORIZONTE | D5: 1 | E5: -- | F5: 001/0001/A | G5: OCUPADO | H5: RESIDENCIAL | I5: PROPRIETÁRIO RESIDENTE | J5: ARIANA APARECIDA DE PAULA | K5: -- | L5: 403.154.248-85 | M5: CADASTRADO | N5: AUXÍLIO ALUGUEL UH | O5: 45986 | P5: 6014.2025/0007513-3 | Q5: 45985 | R5: 45986 | S5: 45987 | T5: 45992 | U5: OK | V5: OK | W5: 45999 | X5: 46000 | Y5: 46017 | AA5: ARIANA APARECIDA DE PAULA | AB5: -- | AC5: 403.154.248-85 | AD5: PROPRIETÁRIO RESIDENTE | AE5: CADASTRADO | AF5: N.A | AG5: N.A | AH5: UH | AI5: 6014.2025/0007373-4 | AK5: 45979 | AL5: 45979 | AM5: 45979 | AN5: 45979 | AO5: 45979 | AP5: 45979 | AR5: =IF(AQ5="SIM","AGUARDANDO CORREÇÃO",IF(AP5<>"","FINALIZADO",IF(AO5<>"","AGUARDANDO ENVIO DTS",IF(AN5<>"","AGUARDANDO ASSINATURA GAB",IF(AM5<>"","AGUARDANDO ASSINATURA CTS",IF(AL5<>"","AGUARDANDO ENVIO ASSINATURA CTS",IF(AK5<>"","AGUARDANDO CONFERÊNCIA",""))))))) -> FINALIZADO | BE5: 46017 | BF5: DEMOLIDO | BH5: =IFERROR(IF(BD5-KI5=0,"",BD5-AK5),"") | BI5: =IF(AND(AH5<>"SIM",AH5="UH"),"AA","INDENIZAÇÃO") -> AA | BJ5: =IF(AND(BD5<>"AGUARDANDO",BD5<>"",N5="AUXÍLIO ALUGUEL ATÉ INDENIZAÇÃO"),"SIM","NÃO") -> NÃO
A6: 2 | B6: JD. PANTANAL | C6: VILA DA PAZ | D6: 1 | E6: -- | F6: 001/0001/A | G6: OCUPADO | H6: RESIDENCIAL | I6: INQUILINO | J6: KISSY KATAIANA SANTOS SILVA | K6: -- | L6: 421.459.738-93 | M6: CADASTRADO | N6: AUXÍLIO ALUGUEL UH | O6: PENDENTE | P6: 6014.2025/0007513-3 | AA6: GABRIEL ROCHA RODRIGUES | AB6: 39.394.079-2 | AC6: 367.570.418-12 | AD6: PROPRIETÁRIO NÃO RESIDENTE | AE6: CADASTRADO | AF6: 62160.58 | AG6: 62160.58 | AH6: SIM | AI6: 6014.2025/0007373-4 | AJ6: 160375813 | AK6: 46080 | AL6: 46080 | AM6: 46080 | AN6: 46080 | AO6: 46080 | AP6: 46080 | AR6: =IF(AQ6="SIM","AGUARDANDO CORREÇÃO",IF(AP6<>"","FINALIZADO",IF(AO6<>"","AGUARDANDO ENVIO DTS",IF(AN6<>"","AGUARDANDO ASSINATURA GAB",IF(AM6<>"","AGUARDANDO ASSINATURA CTS",IF(AL6<>"","AGUARDANDO ENVIO ASSINATURA CTS",IF(AK6<>"","AGUARDANDO CONFERÊNCIA",""))))))) -> FINALIZADO | AS6: SEM PENDÊNCIA | AU6: 6014.2026/0005831-1 | AV6: FINALIZADO | AW6: FINALIZADO | AX6: EM BLOCO | BF6: OCUPADO | BH6: =IFERROR(IF(BD6-KI6=0,"",BD6-AK6),"") | BI6: =IF(AND(AH6<>"SIM",AH6="UH"),"AA","INDENIZAÇÃO") -> INDENIZAÇÃO | BJ6: =IF(AND(BD6<>"AGUARDANDO",BD6<>"",N6="AUXÍLIO ALUGUEL ATÉ INDENIZAÇÃO"),"SIM","NÃO") -> NÃO
A7: 3 | B7: JD. PANTANAL | C7: SÃO MARTINHO VÁRZEA | D7: 1 | E7: -- | F7: 001/0001/A | G7: OCUPADO | H7: COMERCIAL | I7: PROPRIETÁRIO NÃO RESIDENTE | J7: ADENILSON BATISTA FERREIRA | K7: 24.743.676-8 | L7: 468.366.675-87 | M7: CADASTRADO | N7: INDENIZAÇÃO | O7: N.A | P7: N.A | Q7: N.A | R7: N.A | S7: N.A | T7: N.A | U7: N.A | V7: N.A | W7: N.A | X7: N.A | AA7: ADENILSON BATISTA FERREIRA | AB7: 24.743.676-8 | AC7: 468.366.675-87 | AD7: PROPRIETÁRIO NÃO RESIDENTE | AE7: CADASTRADO | AF7: 54401.18 | AG7: 60000 | AH7: SIM | AI7: 6014.2025/0007373-4 | AJ7: 147744665 | AK7: 45988 | AL7: 45988 | AM7: 45988 | AN7: 45988 | AO7: 45988 | AP7: 45988 | AR7: =IF(AQ7="SIM","AGUARDANDO CORREÇÃO",IF(AP7<>"","FINALIZADO",IF(AO7<>"","AGUARDANDO ENVIO DTS",IF(AN7<>"","AGUARDANDO ASSINATURA GAB",IF(AM7<>"","AGUARDANDO ASSINATURA CTS",IF(AL7<>"","AGUARDANDO ENVIO ASSINATURA CTS",IF(AK7<>"","AGUARDANDO CONFERÊNCIA",""))))))) -> FINALIZADO | AS7: SEM PENDÊNCIA | AU7: 6014.2025/0008612-7 | AV7: FINALIZADO | AW7: FINALIZADO | AX7: FINALIZADO | AY7: FINALIZADO | AZ7: 46024 | BA7: FINALIZADO | BB7: FINALIZADO | BC7: 46038 | BD7: 46038 | BE7: AGUARDANDO | BF7: LIBERADO DEMOLIÇÃO | BG7: FINALIZADO | BH7: =IFERROR(IF(BD7-KI7=0,"",BD7-AK7),"") -> 50 | BI7: =IF(AND(AH7<>"SIM",AH7="UH"),"AA","INDENIZAÇÃO") -> INDENIZAÇÃO | BJ7: =IF(AND(BD7<>"AGUARDANDO",BD7<>"",N7="AUXÍLIO ALUGUEL ATÉ INDENIZAÇÃO"),"SIM","NÃO") -> NÃO | BK7: N/A | BL7: N/A | BM7: N/A | BN7: FINALIZADO | BO7: FINALIZADO | BP7: 46128 | BQ7: FINALIZADO | BR7: AGUARDANDO
A8: 4 | B8: JD. PANTANAL | C8: VILA DA PAZ | D8: 1 | E8: -- | F8: 001/0001/B | G8: OCUPADO | H8: RESIDENCIAL | I8: PROPRIETÁRIO RESIDENTE | J8: KLEINY SIRLANE DA ROCHA | K8: _ | L8: 260.215.948-43 | M8: CADASTRADO | N8: INDENIZAÇÃO | P8: N.A | Q8: N.A | R8: N.A | S8: N.A | T8: N.A | U8: N.A | V8: N.A | W8: N.A | X8: N.A | AA8: KLEINY SIRLANE DA ROCHA | AB8: _ | AC8: 260.215.948-43 | AD8: PROPRIETÁRIO RESIDENTE | AE8: CADASTRADO | AF8: 91776.57 | AG8: 91776.57 | AH8: SIM | AI8: 6014.2025/0007373-4 | AJ8: 153000357 | AK8: 46112 | AL8: 46112 | AM8: 46112 | AN8: 46112 | AO8: 46112 | AP8: 46112 | AR8: =IF(AQ8="SIM","AGUARDANDO CORREÇÃO",IF(AP8<>"","FINALIZADO",IF(AO8<>"","AGUARDANDO ENVIO DTS",IF(AN8<>"","AGUARDANDO ASSINATURA GAB",IF(AM8<>"","AGUARDANDO ASSINATURA CTS",IF(AL8<>"","AGUARDANDO ENVIO ASSINATURA CTS",IF(AK8<>"","AGUARDANDO CONFERÊNCIA",""))))))) -> FINALIZADO | AS8: SEM PENDÊNCIA | AU8: 6014.2026/0001975-8 | AV8: FINALIZADO | AW8: FINALIZADO | AX8: FINALIZADO | AY8: FINALIZADO | AZ8: 46189 | BA8: FINALIZADO | BB8: FINALIZADO | BC8: 46196 | BD8: 46196 | BE8: AGUARDANDO | BF8: LIBERADO DEMOLIÇÃO | BG8: FINALIZADO | BH8: =IFERROR(IF(BD8-KI8=0,"",BD8-AK8),"") -> 84 | BI8: =IF(AND(AH8<>"SIM",AH8="UH"),"AA","INDENIZAÇÃO") -> INDENIZAÇÃO | BJ8: =IF(AND(BD8<>"AGUARDANDO",BD8<>"",N8="AUXÍLIO ALUGUEL ATÉ INDENIZAÇÃO"),"SIM","NÃO") -> NÃO | BK8: N/A | BL8: N/A | BM8: N/A | BN8: FINALIZADO | BO8: FINALIZADO | BP8: 46224 | BQ8: FINALIZADO | BR8: AGUARDANDO
A9: 5 | B9: JD. PANTANAL | C9: VILA DA PAZ | D9: 1 | E9: -- | F9: 001/0001/C | G9: OCUPADO | H9: RESIDENCIAL | I9: PROPRIETÁRIO NÃO RESIDENTE | J9: JULIA DA ROCHA RODRIGUES | K9: _ | L9: 367.978.788-02 | O9: N.A | P9: N.A | Q9: N.A | R9: N.A | S9: N.A | T9: N.A | U9: N.A | V9: N.A | W9: N.A | X9: N.A | AA9: JULIA DA ROCHA RODRIGUES | AB9: _ | AC9: 367.978.788-02 | AD9: PROPRIETÁRIO NÃO RESIDENTE | AE9: CADASTRADO | AF9: 93714.3 | AG9: 93714.3 | AH9: SIM | AI9: 6014.2025/0007373-4 | AJ9: 161384436 | AK9: 46258 | AL9: 46258 | AM9: 46258 | AN9: 46258 | AR9: =IF(AQ9="SIM","AGUARDANDO CORREÇÃO",IF(AP9<>"","FINALIZADO",IF(AO9<>"","AGUARDANDO ENVIO DTS",IF(AN9<>"","AGUARDANDO ASSINATURA GAB",IF(AM9<>"","AGUARDANDO ASSINATURA CTS",IF(AL9<>"","AGUARDANDO ENVIO ASSINATURA CTS",IF(AK9<>"","AGUARDANDO CONFERÊNCIA",""))))))) -> AGUARDANDO ASSINATURA GAB | AS9: TERMO ASSINADO SECRETÁRIO | BH9: =IFERROR(IF(BD9-KI9=0,"",BD9-AK9),"") | BI9: =IF(AND(AH9<>"SIM",AH9="UH"),"AA","INDENIZAÇÃO") -> INDENIZAÇÃO | BJ9: =IF(AND(BD9<>"AGUARDANDO",BD9<>"",N9="AUXÍLIO ALUGUEL ATÉ INDENIZAÇÃO"),"SIM","NÃO") -> NÃO
A10: 6 | B10: JD. PANTANAL | C10: NOVO HORIZONTE | D10: 1 | E10: -- | F10: 001/0002/A | G10: OCUPADO | H10: GARAGEM | I10: PROPRIETÁRIO NÃO RESIDENTE | J10: CARLINDO ELOI DA SILVA | K10: 38.470.928 | L10: 659.657.734-87 | M10: CADASTRADO | N10: INDENIZAÇÃO | O10: N.A | P10: N.A | Q10: N.A | R10: N.A | S10: N.A | T10: N.A | U10: N.A | V10: N.A | W10: N.A | X10: N.A | AA10: CARLINDO ELOI DA SILVA | AB10: 38.470.928 | AC10: 659.657.734-87 | AD10: PROPRIETÁRIO NÃO RESIDENTE | AE10: CADASTRADO | AI10: 6014.2025/0007373-4 | AK10: 46037 | AL10: 46037 | AM10: 46037 | AN10: 46037 | AO10: 46037 | AP10: 46037 | AR10: =IF(AQ10="SIM","AGUARDANDO CORREÇÃO",IF(AP10<>"","FINALIZADO",IF(AO10<>"","AGUARDANDO ENVIO DTS",IF(AN10<>"","AGUARDANDO ASSINATURA GAB",IF(AM10<>"","AGUARDANDO ASSINATURA CTS",IF(AL10<>"","AGUARDANDO ENVIO ASSINATURA CTS",IF(AK10<>"","AGUARDANDO CONFERÊNCIA",""))))))) -> FINALIZADO | BH10: =IFERROR(IF(BD10-KI10=0,"",BD10-AK10),"") | BI10: =IF(AND(AH10<>"SIM",AH10="UH"),"AA","INDENIZAÇÃO") -> INDENIZAÇÃO | BJ10: =IF(AND(BD10<>"AGUARDANDO",BD10<>"",N10="AUXÍLIO ALUGUEL ATÉ INDENIZAÇÃO"),"SIM","NÃO") -> NÃO
A11: 7 | B11: JD. PANTANAL | C11: TERRA PROMETIDA | D11: 1 | E11: -- | F11: 001/0002/A | G11: OCUPADO | H11: RESIDENCIAL | I11: PROPRIETÁRIO RESIDENTE | J11: MARIA GILDENIA BENTO ALVES | K11: 64.948.618- | L11: 094.955.464-27 | M11: CADASTRADO | N11: AUXÍLIO ALUGUEL UH | O11: 45986 | P11: 6014.2025/0007513-3 | Q11: 45985 | R11: 45986 | S11: 45987 | T11: 45992 | U11: OK | V11: OK | W11: 45999 | X11: 46000 | Y11: 46017 | AA11: MARIA GILDENIA BENTO ALVES | AB11: 64.948.618- | AC11: 094.955.464-27 | AD11: PROPRIETÁRIO RESIDENTE | AE11: CADASTRADO | AF11: N.A | AG11: N.A | AH11: UH | AI11: 6014.2025/0007373-4 | AK11: 45979 | AL11: 45979 | AM11: 45979 | AN11: 45979 | AO11: 45979 | AP11: 45979 | AR11: =IF(AQ11="SIM","AGUARDANDO CORREÇÃO",IF(AP11<>"","FINALIZADO",IF(AO11<>"","AGUARDANDO ENVIO DTS",IF(AN11<>"","AGUARDANDO ASSINATURA GAB",IF(AM11<>"","AGUARDANDO ASSINATURA CTS",IF(AL11<>"","AGUARDANDO ENVIO ASSINATURA CTS",IF(AK11<>"","AGUARDANDO CONFERÊNCIA",""))))))) -> FINALIZADO | BE11: 46017 | BF11: DEMOLIDO | BH11: =IFERROR(IF(BD11-KI11=0,"",BD11-AK11),"") | BI11: =IF(AND(AH11<>"SIM",AH11="UH"),"AA","INDENIZAÇÃO") -> AA | BJ11: =IF(AND(BD11<>"AGUARDANDO",BD11<>"",N11="AUXÍLIO ALUGUEL ATÉ INDENIZAÇÃO"),"SIM","NÃO") -> NÃO
A12: 8 | B12: JD. PANTANAL | C12: SÃO MARTINHO VÁRZEA | D12: 1 | E12: -- | F12: 001/0002/A | G12: OCUPADO | H12: RESIDENCIAL | I12: PROPRIETÁRIO RESIDENTE | J12: LUZIANE JESUS DA SILVA | K12: -- | L12: 237.785.408-74 | M12: CADASTRADO | N12: INDENIZAÇÃO | O12: N.A | P12: N.A | Q12: N.A | R12: N.A | S12: N.A | T12: N.A | U12: N.A | V12: N.A | W12: N.A | X12: N.A | AA12: LUZIANE JESUS DA SILVA | AB12: -- | AC12: 237.785.408-74 | AD12: PROPRIETÁRIO RESIDENTE | AE12: CADASTRADO | AF12: 20634.24 | AG12: =AF12+30000 -> 50634.24 | AH12: SIM | AI12: 6014.2025/0007373-4 | AJ12: 147744826 | AK12: 46001 | AL12: 46001 | AM12: 46001 | AN12: 46001 | AO12: 46001 | AP12: 46001 | AR12: =IF(AQ12="SIM","AGUARDANDO CORREÇÃO",IF(AP12<>"","FINALIZADO",IF(AO12<>"","AGUARDANDO ENVIO DTS",IF(AN12<>"","AGUARDANDO ASSINATURA GAB",IF(AM12<>"","AGUARDANDO ASSINATURA CTS",IF(AL12<>"","AGUARDANDO ENVIO ASSINATURA CTS",IF(AK12<>"","AGUARDANDO CONFERÊNCIA",""))))))) -> FINALIZADO | AS12: SEM PENDÊNCIA | AU12: 6014.2025/0008616-0 | AV12: FINALIZADO | AW12: FINALIZADO | AX12: FINALIZADO | AY12: FINALIZADO | AZ12: 46024 | BA12: FINALIZADO | BB12: FINALIZADO | BC12: 46037 | BD12: 46037 | BE12: AGUARDANDO | BF12: LIBERADO DEMOLIÇÃO | BG12: FINALIZADO | BH12: =IFERROR(IF(BD12-KI12=0,"",BD12-AK12),"") -> 36 | BI12: =IF(AND(AH12<>"SIM",AH12="UH"),"AA","INDENIZAÇÃO") -> INDENIZAÇÃO | BJ12: =IF(AND(BD12<>"AGUARDANDO",BD12<>"",N12="AUXÍLIO ALUGUEL ATÉ INDENIZAÇÃO"),"SIM","NÃO") -> NÃO | BK12: N/A | BL12: N/A | BM12: N/A | BN12: FINALIZADO | BO12: FINALIZADO | BP12: 46128 | BQ12: FINALIZADO | BR12: AGUARDANDO
A13: 9 | B13: JD. PANTANAL | C13: TERRA PROMETIDA | D13: 1 | E13: -- | F13: 001/0002/B | G13: OCUPADO | H13: RESIDENCIAL | I13: PROPRIETÁRIO RESIDENTE | J13: FRANCISCA SOARES DOS SANTOS | K13: 23.458.574-2 | L13: 155.316.448-25 | M13: CADASTRADO | N13: AUXÍLIO ALUGUEL UH | O13: 46044 | P13: 6014.2025/0007513-3 | Q13: 46043 | R13: 46044 | S13: 46045 | T13: 46155 | U13: OK | V13: OK | W13: 46055 | X13: 46063 | Y13: 46017 | AA13: FRANCISCA SOARES DOS SANTOS | AB13: 23.458.574-2 | AC13: 155.316.448-25 | AD13: PROPRIETÁRIO RESIDENTE | AE13: CADASTRADO | AF13: N.A | AG13: N.A | AH13: UH | AI13: 6014.2025/0007373-4 | AK13: 46041 | AL13: 46041 | AM13: 46041 | AN13: 46041 | AO13: 46041 | AP13: 46041 | AR13: =IF(AQ13="SIM","AGUARDANDO CORREÇÃO",IF(AP13<>"","FINALIZADO",IF(AO13<>"","AGUARDANDO ENVIO DTS",IF(AN13<>"","AGUARDANDO ASSINATURA GAB",IF(AM13<>"","AGUARDANDO ASSINATURA CTS",IF(AL13<>"","AGUARDANDO ENVIO ASSINATURA CTS",IF(AK13<>"","AGUARDANDO CONFERÊNCIA",""))))))) -> FINALIZADO | BE13: 46017 | BF13: DEMOLIDO | BH13: =IFERROR(IF(BD13-KI13=0,"",BD13-AK13),"") | BI13: =IF(AND(AH13<>"SIM",AH13="UH"),"AA","INDENIZAÇÃO") -> AA | BJ13: =IF(AND(BD13<>"AGUARDANDO",BD13<>"",N13="AUXÍLIO ALUGUEL ATÉ INDENIZAÇÃO"),"SIM","NÃO") -> NÃO
A14: 10 | B14: JD. PANTANAL | C14: SÃO MARTINHO VÁRZEA | D14: 1 | E14: -- | F14: 001/0002/B | G14: OCUPADO | H14: RESIDENCIAL | I14: PROPRIETÁRIO RESIDENTE | J14: JESANIA CRISTINA OSÓRIO DA SILVA | K14: -- | L14: 360.808.578.55 | M14: CADASTRADO | N14: AUXÍLIO ALUGUEL UH | O14: 46084 | P14: 6014.2025/0007513-3 | Q14: 46083 | R14: 46084 | S14: 46087 | T14: 46090 | U14: OK | V14: OK | W14: 46101 | X14: 46101 | AA14: JESANIA CRISTINA OSÓRIO DA SILVA | AB14: -- | AC14: 360.808.578.55 | AD14: PROPRIETÁRIO RESIDENTE | AE14: CADASTRADO | AF14: N.A | AG14: N.A | AH14: UH | AI14: 6014.2025/0007373-4 | AK14: 46084 | AL14: 46084 | AM14: 46084 | AN14: 46084 | AO14: 46084 | AP14: 46084 | AR14: =IF(AQ14="SIM","AGUARDANDO CORREÇÃO",IF(AP14<>"","FINALIZADO",IF(AO14<>"","AGUARDANDO ENVIO DTS",IF(AN14<>"","AGUARDANDO ASSINATURA GAB",IF(AM14<>"","AGUARDANDO ASSINATURA CTS",IF(AL14<>"","AGUARDANDO ENVIO ASSINATURA CTS",IF(AK14<>"","AGUARDANDO CONFERÊNCIA",""))))))) -> FINALIZADO | BH14: =IFERROR(IF(BD14-KI14=0,"",BD14-AK14),"") | BI14: =IF(AND(AH14<>"SIM",AH14="UH"),"AA","INDENIZAÇÃO") -> AA | BJ14: =IF(AND(BD14<>"AGUARDANDO",BD14<>"",N14="AUXÍLIO ALUGUEL ATÉ INDENIZAÇÃO"),"SIM","NÃO") -> NÃO
A15: 11 | B15: JD. PANTANAL | C15: SÃO MARTINHO VÁRZEA | D15: 1 | E15: -- | F15: 001/0002/C | G15: OCUPADO | H15: RESIDENCIAL | I15: PROPRIETÁRIO RESIDENTE | J15: GABRIEL MIRANDA DOS SANTOS | K15: 58.626.407-3 | L15: 587.339.488-10 | M15: CADASTRADO | N15: INDENIZAÇÃO | O15: N.A | P15: N.A | Q15: N.A | R15: N.A | S15: N.A | T15: N.A | U15: N.A | V15: N.A | W15: N.A | X15: N.A | AA15: GABRIEL MIRANDA DOS SANTOS | AB15: 58.626.407-3 | AC15: 587.339.488-10 | AD15: PROPRIETÁRIO RESIDENTE | AE15: CADASTRADO | AF15: 20185.43 | AG15: =AF15+30000 -> 50185.43 | AH15: SIM | AI15: 6014.2025/0007373-4 | AJ15: 149592865 | AK15: 46059 | AL15: 46059 | AM15: 46059 | AN15: 46059 | AR15: =IF(AQ15="SIM","AGUARDANDO CORREÇÃO",IF(AP15<>"","FINALIZADO",IF(AO15<>"","AGUARDANDO ENVIO DTS",IF(AN15<>"","AGUARDANDO ASSINATURA GAB",IF(AM15<>"","AGUARDANDO ASSINATURA CTS",IF(AL15<>"","AGUARDANDO ENVIO ASSINATURA CTS",IF(AK15<>"","AGUARDANDO CONFERÊNCIA",""))))))) -> AGUARDANDO ASSINATURA GAB | BH15: =IFERROR(IF(BD15-KI15=0,"",BD15-AK15),"") | BI15: =IF(AND(AH15<>"SIM",AH15="UH"),"AA","INDENIZAÇÃO") -> INDENIZAÇÃO | BJ15: =IF(AND(BD15<>"AGUARDANDO",BD15<>"",N15="AUXÍLIO ALUGUEL ATÉ INDENIZAÇÃO"),"SIM","NÃO") -> NÃO
A16: 12 | B16: JD. PANTANAL | C16: SÃO MARTINHO VÁRZEA | D16: 1 | E16: -- | F16: 001/0002/D | G16: OCUPADO | H16: RESIDENCIAL | I16: PROPRIETÁRIO RESIDENTE | J16: ROSILDA RIBEIRO DOS SANTOS | K16: 13.497.334-82 | L16: 034.194.515-39 | M16: CADASTRADO | N16: AUXÍLIO ALUGUEL UH | O16: 45986 | P16: 6014.2025/0007513-3 | Q16: 45985 | R16: 45986 | S16: 45987 | T16: 45992 | U16: OK | V16: OK | W16: 45999 | X16: 46009 | AA16: ROSILDA RIBEIRO DOS SANTOS | AB16: 13.497.334-82 | AC16: 034.194.515-39 | AD16: PROPRIETÁRIO RESIDENTE | AE16: CADASTRADO | AF16: N.A | AG16: N.A | AH16: UH | AI16: 6014.2025/0007373-4 | AK16: 45980 | AL16: 45980 | AM16: 45980 | AN16: 45980 | AO16: 45980 | AP16: 45980 | AR16: =IF(AQ16="SIM","AGUARDANDO CORREÇÃO",IF(AP16<>"","FINALIZADO",IF(AO16<>"","AGUARDANDO ENVIO DTS",IF(AN16<>"","AGUARDANDO ASSINATURA GAB",IF(AM16<>"","AGUARDANDO ASSINATURA CTS",IF(AL16<>"","AGUARDANDO ENVIO ASSINATURA CTS",IF(AK16<>"","AGUARDANDO CONFERÊNCIA",""))))))) -> FINALIZADO | BH16: =IFERROR(IF(BD16-KI16=0,"",BD16-AK16),"") | BI16: =IF(AND(AH16<>"SIM",AH16="UH"),"AA","INDENIZAÇÃO") -> AA | BJ16: =IF(AND(BD16<>"AGUARDANDO",BD16<>"",N16="AUXÍLIO ALUGUEL ATÉ INDENIZAÇÃO"),"SIM","NÃO") -> NÃO
A17: 13 | B17: JD. PANTANAL | C17: SÃO MARTINHO VÁRZEA | D17: 1 | E17: -- | F17: 001/0002/E | G17: OCUPADO | H17: RESIDENCIAL | I17: PROPRIETÁRIO RESIDENTE | J17: GIVALDO TAVARES DE SOUZA | K17: 62.620.783-6 | L17: 093.716.044-09 | M17: CADASTRADO | N17: INDENIZAÇÃO | O17: N.A | P17: N.A | Q17: N.A | R17: N.A | S17: N.A | T17: N.A | U17: N.A | V17: N.A | W17: N.A | X17: N.A | AA17: GIVALDO TAVARES DE SOUZA | AB17: 62.620.783-6 | AC17: 093.716.044-09 | AD17: PROPRIETÁRIO RESIDENTE | AE17: CADASTRADO | AF17: 30184.77 | AG17: 60000 | AH17: SIM | AI17: 6014.2025/0007373-4 | AJ17: 154259974 | AK17: 46086 | AL17: 46086 | AM17: 46086 | AN17: 46086 | AO17: 46086 | AP17: 46086 | AR17: =IF(AQ17="SIM","AGUARDANDO CORREÇÃO",IF(AP17<>"","FINALIZADO",IF(AO17<>"","AGUARDANDO ENVIO DTS",IF(AN17<>"","AGUARDANDO ASSINATURA GAB",IF(AM17<>"","AGUARDANDO ASSINATURA CTS",IF(AL17<>"","AGUARDANDO ENVIO ASSINATURA CTS",IF(AK17<>"","AGUARDANDO CONFERÊNCIA",""))))))) -> FINALIZADO | AS17: SEM PENDÊNCIA | AU17: 6014.2026/0001162-5 | AV17: FINALIZADO | AW17: FINALIZADO | AX17: FINALIZADO | AY17: FINALIZADO | AZ17: 46174 | BA17: FINALIZADO | BB17: FINALIZADO | BC17: 46182 | BD17: 46182 | BE17: AGUARDANDO | BF17: LIBERADO DEMOLIÇÃO | BG17: FINALIZADO | BH17: =IFERROR(IF(BD17-KI17=0,"",BD17-AK17),"") -> 96 | BI17: =IF(AND(AH17<>"SIM",AH17="UH"),"AA","INDENIZAÇÃO") -> INDENIZAÇÃO | BJ17: =IF(AND(BD17<>"AGUARDANDO",BD17<>"",N17="AUXÍLIO ALUGUEL ATÉ INDENIZAÇÃO"),"SIM","NÃO") -> NÃO | BK17: N/A | BL17: N/A | BM17: N/A | BN17: FINALIZADO | BO17: FINALIZADO | BP17: 46224 | BQ17: FINALIZADO | BR17: AGUARDANDO
A18: 14 | B18: JD. PANTANAL | C18: SÃO MARTINHO VÁRZEA | D18: 1 | E18: -- | F18: 001/0002/F | G18: OCUPADO | H18: RESIDENCIAL | I18: PROPRIETÁRIO RESIDENTE | J18: KARINA TENORIO AZEVEDO | K18: 38.439.503-X | L18: 447.989.178-18 | M18: CADASTRADO | N18: AUXÍLIO ALUGUEL UH | O18: 46002 | P18: 6014.2025/0007513-3 | Q18: 45999 | R18: 46006 | S18: 46006 | T18: 46009 | U18: OK | V18: OK | W18: 46014 | X18: 46017 | AA18: KARINA TENORIO AZEVEDO | AB18: 38.439.503-X | AC18: 447.989.178-18 | AD18: PROPRIETÁRIO RESIDENTE | AE18: CADASTRADO | AF18: N.A | AG18: N.A | AH18: UH | AI18: 6014.2025/0007373-4 | AK18: 45988 | AL18: 45988 | AM18: 45988 | AN18: 45988 | AO18: 45988 | AP18: 45988 | AR18: =IF(AQ18="SIM","AGUARDANDO CORREÇÃO",IF(AP18<>"","FINALIZADO",IF(AO18<>"","AGUARDANDO ENVIO DTS",IF(AN18<>"","AGUARDANDO ASSINATURA GAB",IF(AM18<>"","AGUARDANDO ASSINATURA CTS",IF(AL18<>"","AGUARDANDO ENVIO ASSINATURA CTS",IF(AK18<>"","AGUARDANDO CONFERÊNCIA",""))))))) -> FINALIZADO | BH18: =IFERROR(IF(BD18-KI18=0,"",BD18-AK18),"") | BI18: =IF(AND(AH18<>"SIM",AH18="UH"),"AA","INDENIZAÇÃO") -> AA | BJ18: =IF(AND(BD18<>"AGUARDANDO",BD18<>"",N18="AUXÍLIO ALUGUEL ATÉ INDENIZAÇÃO"),"SIM","NÃO") -> NÃO
A19: 15 | B19: JD. PANTANAL | C19: SÃO MARTINHO VÁRZEA | D19: 1 | E19: -- | F19: 001/0002/G | G19: OCUPADO | H19: RESIDENCIAL | I19: PROPRIETÁRIO RESIDENTE | J19: GILFRAN CARNEIRO VIANA | K19: -- | L19: 62.458.105-58 | M19: CADASTRADO | N19: INDENIZAÇÃO | O19: N.A | P19: N.A | Q19: N.A | R19: N.A | S19: N.A | T19: N.A | U19: N.A | V19: N.A | W19: N.A | X19: N.A | AA19: ANA MARIA DOS SANTOS | AB19: 57.162.248.3 | AC19: 595.893.418.02 | AD19: PROPRIETÁRIO NÃO RESIDENTE | AE19: CADASTRADO | AF19: 20634.24 | AG19: =AF19+30000 -> 50634.24 | AH19: SIM | AI19: 6014.2025/0007373-4 | AJ19: 147744898 | AK19: 46045 | AL19: 46045 | AM19: 46045 | AN19: 46045 | AO19: 46045 | AP19: 46045 | AR19: =IF(AQ19="SIM","AGUARDANDO CORREÇÃO",IF(AP19<>"","FINALIZADO",IF(AO19<>"","AGUARDANDO ENVIO DTS",IF(AN19<>"","AGUARDANDO ASSINATURA GAB",IF(AM19<>"","AGUARDANDO ASSINATURA CTS",IF(AL19<>"","AGUARDANDO ENVIO ASSINATURA CTS",IF(AK19<>"","AGUARDANDO CONFERÊNCIA",""))))))) -> FINALIZADO | AS19: SEM PENDÊNCIA | AU19: 6014.2026/0000450-5 | AV19: FINALIZADO | AW19: FINALIZADO | AX19: FINALIZADO | AY19: FINALIZADO | AZ19: 46071 | BA19: FINALIZADO | BB19: FINALIZADO | BC19: 46093 | BD19: 46093 | BE19: AGUARDANDO | BF19: LIBERADO DEMOLIÇÃO | BG19: FINALIZADO | BH19: =IFERROR(IF(BD19-KI19=0,"",BD19-AK19),"") -> 48 | BI19: =IF(AND(AH19<>"SIM",AH19="UH"),"AA","INDENIZAÇÃO") -> INDENIZAÇÃO | BJ19: =IF(AND(BD19<>"AGUARDANDO",BD19<>"",N19="AUXÍLIO ALUGUEL ATÉ INDENIZAÇÃO"),"SIM","NÃO") -> NÃO | BK19: N/A | BL19: N/A | BM19: N/A | BN19: FINALIZADO | BO19: FINALIZADO | BP19: 46128 | BQ19: FINALIZADO | BR19: AGUARDANDO
A20: 16 | B20: JD. PANTANAL | C20: SÃO MARTINHO VÁRZEA | D20: 1 | E20: -- | F20: 001/0002/H | G20: OCUPADO | H20: RESIDENCIAL | I20: PROPRIETÁRIO RESIDENTE | J20: MÉRCIA LOPES SILVA | K20: 41.317.212-0 | L20: 051.115.775-48 | M20: CADASTRADO | N20: INDENIZAÇÃO | O20: N.A | P20: N.A | Q20: N.A | R20: N.A | S20: N.A | T20: N.A | U20: N.A | V20: N.A | W20: N.A | X20: N.A | AA20: MÉRCIA LOPES SILVA | AB20: 41.317.212-0 | AC20: 051.115.775-48 | AD20: PROPRIETÁRIO RESIDENTE | AE20: CADASTRO | AF20: 17173.63 | AG20: 47173.63 | AH20: SIM | AI20: 6014.2025/0007373-4 | AJ20: 149594350 | AK20: 46099 | AL20: 46099 | AM20: 46099 | AN20: 46099 | AO20: 46099 | AP20: 46099 | AR20: =IF(AQ20="SIM","AGUARDANDO CORREÇÃO",IF(AP20<>"","FINALIZADO",IF(AO20<>"","AGUARDANDO ENVIO DTS",IF(AN20<>"","AGUARDANDO ASSINATURA GAB",IF(AM20<>"","AGUARDANDO ASSINATURA CTS",IF(AL20<>"","AGUARDANDO ENVIO ASSINATURA CTS",IF(AK20<>"","AGUARDANDO CONFERÊNCIA",""))))))) -> FINALIZADO | AS20: SEM PENDÊNCIA | AU20: 6014.2026/0000683-4 | AV20: FINALIZADO | AW20: FINALIZADO | AX20: FINALIZADO | AY20: FINALIZADO | AZ20: 46153 | BA20: FINALIZADO | BB20: FINALIZADO | BC20: 46157 | BD20: 46157 | BE20: AGUARDANDO | BF20: LIBERADO DEMOLIÇÃO | BG20: FINALIZADO | BH20: =IFERROR(IF(BD20-KI20=0,"",BD20-AK20),"") -> 58 | BI20: =IF(AND(AH20<>"SIM",AH20="UH"),"AA","INDENIZAÇÃO") -> INDENIZAÇÃO | BJ20: =IF(AND(BD20<>"AGUARDANDO",BD20<>"",N20="AUXÍLIO ALUGUEL ATÉ INDENIZAÇÃO"),"SIM","NÃO") -> NÃO | BK20: N/A | BL20: N/A | BM20: N/A | BN20: FINALIZADO | BO20: FINALIZADO | BP20: 46195 | BQ20: FINALIZADO | BR20: AGUARDANDO
A21: 17 | B21: JD. PANTANAL | C21: SÃO MARTINHO VÁRZEA | D21: 1 | E21: -- | F21: 001/0002/I | G21: OCUPADO | H21: RESIDENCIAL | I21: PROPRIETÁRIO NÃO RESIDENTE | J21: FRANCISCO CIRILO DA COSTA NETO | K21: 56.300.779-5 | L21: 042.698.233-99 | M21: CADASTRADO | N21: INDENIZAÇÃO | O21: N.A | P21: N.A | Q21: N.A | R21: N.A | S21: N.A | T21: N.A | U21: N.A | V21: N.A | W21: N.A | X21: N.A | AA21: FRANCISCO CIRILO DA COSTA NETO | AB21: 56.300.779-5 | AC21: 042.698.233-99 | AD21: PROPRIETÁRIO RESIDENTE | AE21: CADASTRADO | AF21: 34404.25 | AG21: 60000 | AH21: SIM | AI21: 6014.2025/0007373-4 | AJ21: 147744978 | AK21: 46001 | AL21: 46001 | AM21: 46001 | AN21: 46001 | AO21: 46001 | AP21: 46001 | AR21: =IF(AQ21="SIM","AGUARDANDO CORREÇÃO",IF(AP21<>"","FINALIZADO",IF(AO21<>"","AGUARDANDO ENVIO DTS",IF(AN21<>"","AGUARDANDO ASSINATURA GAB",IF(AM21<>"","AGUARDANDO ASSINATURA CTS",IF(AL21<>"","AGUARDANDO ENVIO ASSINATURA CTS",IF(AK21<>"","AGUARDANDO CONFERÊNCIA",""))))))) -> FINALIZADO | AS21: SEM PENDÊNCIA | AU21: 6014.2025/0008621-6 | AV21: FINALIZADO | AW21: FINALIZADO | AX21: FINALIZADO | AY21: FINALIZADO | AZ21: 46024 | BA21: FINALIZADO | BB21: FINALIZADO | BC21: 46037 | BD21: 46037 | BE21: AGUARDANDO | BF21: LIBERADO DEMOLIÇÃO | BG21: FINALIZADO | BH21: =IFERROR(IF(BD21-KI21=0,"",BD21-AK21),"") -> 36 | BI21: =IF(AND(AH21<>"SIM",AH21="UH"),"AA","INDENIZAÇÃO") -> INDENIZAÇÃO | BJ21: =IF(AND(BD21<>"AGUARDANDO",BD21<>"",N21="AUXÍLIO ALUGUEL ATÉ INDENIZAÇÃO"),"SIM","NÃO") -> NÃO | BK21: N/A | BL21: N/A | BM21: N/A | BN21: FINALIZADO | BO21: FINALIZADO | BP21: 46128 | BQ21: FINALIZADO | BR21: AGUARDANDO
A22: 18 | B22: JD. PANTANAL | C22: NOVO HORIZONTE | D22: 1 | E22: -- | F22: 001/0003/A | G22: OCUPADO | H22: GARAGEM | I22: PROPRIETÁRIO NÃO RESIDENTE | J22: ALEX RODRIGUES DE SOUZA | K22: 42.483.537 | L22: 071.643.266-81 | M22: CADASTRADO | N22: INDENIZAÇÃO | O22: N.A | P22: N.A | Q22: N.A | R22: N.A | S22: N.A | T22: N.A | U22: N.A | V22: N.A | W22: N.A | X22: N.A | AI22: 6014.2025/0007373-4 | AK22: 46037 | AL22: 46037 | AM22: 46037 | AN22: 46037 | AO22: 46037 | AP22: 46037 | AR22: =IF(AQ22="SIM","AGUARDANDO CORREÇÃO",IF(AP22<>"","FINALIZADO",IF(AO22<>"","AGUARDANDO ENVIO DTS",IF(AN22<>"","AGUARDANDO ASSINATURA GAB",IF(AM22<>"","AGUARDANDO ASSINATURA CTS",IF(AL22<>"","AGUARDANDO ENVIO ASSINATURA CTS",IF(AK22<>"","AGUARDANDO CONFERÊNCIA",""))))))) -> FINALIZADO | BH22: =IFERROR(IF(BD22-KI22=0,"",BD22-AK22),"") | BI22: =IF(AND(AH22<>"SIM",AH22="UH"),"AA","INDENIZAÇÃO") -> INDENIZAÇÃO | BJ22: =IF(AND(BD22<>"AGUARDANDO",BD22<>"",N22="AUXÍLIO ALUGUEL ATÉ INDENIZAÇÃO"),"SIM","NÃO") -> NÃO
A23: 19 | B23: JD. PANTANAL | C23: SÃO MARTINHO VÁRZEA | D23: 1 | E23: -- | F23: 001/0003/A | G23: OCUPADO | H23: RESIDENCIAL | I23: PROPRIETÁRIO RESIDENTE | J23: JUCELIA DE JESUS | K23: 12593055-03 | L23: 779.056.015-87 | M23: CADASTRADO | N23: AUXÍLIO ALUGUEL UH | O23: 46106 | P23: 6014.2025/0007513-3 | Q23: 46106 | R23: 46107 | S23: 46111 | T23: 46087 | U23: OK | V23: OK | W23: 46132 | X23: 46129 | AA23: JUCELIA DE JESUS | AB23: 12593055-03 | AC23: 779.056.015-87 | AD23: PROPRIETÁRIO RESIDENTE | AE23: CADASTRADO | AF23: N.A | AG23: N.A | AH23: UH | AI23: 6014.2025/0007373-4 | AK23: 46001 | AL23: 46001 | AM23: 46001 | AN23: 46001 | AO23: 46001 | AP23: 46001 | AR23: =IF(AQ23="SIM","AGUARDANDO CORREÇÃO",IF(AP23<>"","FINALIZADO",IF(AO23<>"","AGUARDANDO ENVIO DTS",IF(AN23<>"","AGUARDANDO ASSINATURA GAB",IF(AM23<>"","AGUARDANDO ASSINATURA CTS",IF(AL23<>"","AGUARDANDO ENVIO ASSINATURA CTS",IF(AK23<>"","AGUARDANDO CONFERÊNCIA",""))))))) -> FINALIZADO | BH23: =IFERROR(IF(BD23-KI23=0,"",BD23-AK23),"") | BI23: =IF(AND(AH23<>"SIM",AH23="UH"),"AA","INDENIZAÇÃO") -> AA | BJ23: =IF(AND(BD23<>"AGUARDANDO",BD23<>"",N23="AUXÍLIO ALUGUEL ATÉ INDENIZAÇÃO"),"SIM","NÃO") -> NÃO
A24: 20 | B24: JD. PANTANAL | C24: TERRA PROMETIDA | D24: 1 | E24: -- | F24: 001/0003/A | G24: OCUPADO | H24: RESIDENCIAL | I24: PROPRIETÁRIO RESIDENTE | J24: MOISÉS GUERRA SANTOS | K24: 41.157.942-3 | L24: 297.627.628-51 | M24: CADASTRADO | N24: AUXÍLIO ALUGUEL UH | O24: 46002 | P24: 6014.2025/0007513-3 | Q24: 45999 | R24: 46006 | S24: 46006 | T24: 46009 | U24: OK | V24: OK | W24: 46014 | X24: 46017 | Y24: 46017 | AA24: MOISÉS GUERRA SANTOS | AB24: 41.157.942-3 | AC24: 297.627.628-51 | AD24: PROPRIETÁRIO RESIDENTE | AE24: CADASTRADO | AF24: N.A | AG24: N.A | AH24: UH | AI24: 6014.2025/0007373-4 | AK24: 45996 | AL24: 45996 | AM24: 45996 | AN24: 45996 | AO24: 45996 | AP24: 45996 | AR24: =IF(AQ24="SIM","AGUARDANDO CORREÇÃO",IF(AP24<>"","FINALIZADO",IF(AO24<>"","AGUARDANDO ENVIO DTS",IF(AN24<>"","AGUARDANDO ASSINATURA GAB",IF(AM24<>"","AGUARDANDO ASSINATURA CTS",IF(AL24<>"","AGUARDANDO ENVIO ASSINATURA CTS",IF(AK24<>"","AGUARDANDO CONFERÊNCIA",""))))))) -> FINALIZADO | BE24: 46017 | BF24: DEMOLIDO | BH24: =IFERROR(IF(BD24-KI24=0,"",BD24-AK24),"") | BI24: =IF(AND(AH24<>"SIM",AH24="UH"),"AA","INDENIZAÇÃO") -> AA | BJ24: =IF(AND(BD24<>"AGUARDANDO",BD24<>"",N24="AUXÍLIO ALUGUEL ATÉ INDENIZAÇÃO"),"SIM","NÃO") -> NÃO
A25: 21 | B25: JD. PANTANAL | C25: TERRA PROMETIDA | D25: 1 | E25: -- | F25: 001/0004/A | G25: OCUPADO | H25: RESIDENCIAL | I25: PROPRIETÁRIO RESIDENTE | J25: JOSÉ ALMIR ROCHA DA SILVA | K25: 67.486.680-0 | L25: 107.758.984-06 | M25: CADASTRADO | N25: AUXÍLIO ALUGUEL UH | O25: 45986 | P25: 6014.2025/0007513-3 | Q25: 45985 | R25: 45986 | S25: 45987 | T25: 45992 | U25: OK | V25: OK | W25: 45999 | X25: 46000 | Y25: 46017 | AA25: JOSÉ ALMIR ROCHA DA SILVA | AB25: 67.486.680-0 | AC25: 107.758.984-06 | AD25: PROPRIETÁRIO RESIDENTE | AE25: CADASTRADO | AF25: N.A | AG25: N.A | AH25: UH | AI25: 6014.2025/0007373-4 | AK25: 45979 | AL25: 45979 | AM25: 45979 | AN25: 45979 | AO25: 45979 | AP25: 45979 | AR25: =IF(AQ25="SIM","AGUARDANDO CORREÇÃO",IF(AP25<>"","FINALIZADO",IF(AO25<>"","AGUARDANDO ENVIO DTS",IF(AN25<>"","AGUARDANDO ASSINATURA GAB",IF(AM25<>"","AGUARDANDO ASSINATURA CTS",IF(AL25<>"","AGUARDANDO ENVIO ASSINATURA CTS",IF(AK25<>"","AGUARDANDO CONFERÊNCIA",""))))))) -> FINALIZADO | BE25: 46017 | BF25: DEMOLIDO | BH25: =IFERROR(IF(BD25-KI25=0,"",BD25-AK25),"") | BI25: =IF(AND(AH25<>"SIM",AH25="UH"),"AA","INDENIZAÇÃO") -> AA | BJ25: =IF(AND(BD25<>"AGUARDANDO",BD25<>"",N25="AUXÍLIO ALUGUEL ATÉ INDENIZAÇÃO"),"SIM","NÃO") -> NÃO
A26: 22 | B26: JD. PANTANAL | C26: SÃO MARTINHO VÁRZEA | D26: 1 | E26: -- | F26: 001/0004/A | G26: OCUPADO | H26: RESIDENCIAL | I26: PROPRIETÁRIO RESIDENTE | J26: KARINY SOARES ALVES | K26: 48.263.444-3 | L26: 400.738.458-41 | M26: CADASTRADO | N26: INDENIZAÇÃO | O26: N.A | P26: N.A | Q26: N.A | R26: N.A | S26: N.A | T26: N.A | U26: N.A | V26: N.A | W26: N.A | X26: N.A | AA26: KARINY SOARES ALVES | AB26: 48.263.444-3 | AC26: 400.738.458-41 | AD26: PROPRIETÁRIO RESIDENTE | AE26: CADASTRADO | AF26: 30397.82 | AG26: 60000 | AH26: SIM | AI26: 6014.2025/0007373-4 | AJ26: 146670420 | AK26: 45995 | AL26: 45995 | AM26: 45995 | AN26: 45995 | AO26: 45995 | AP26: 45995 | AR26: =IF(AQ26="SIM","AGUARDANDO CORREÇÃO",IF(AP26<>"","FINALIZADO",IF(AO26<>"","AGUARDANDO ENVIO DTS",IF(AN26<>"","AGUARDANDO ASSINATURA GAB",IF(AM26<>"","AGUARDANDO ASSINATURA CTS",IF(AL26<>"","AGUARDANDO ENVIO ASSINATURA CTS",IF(AK26<>"","AGUARDANDO CONFERÊNCIA",""))))))) -> FINALIZADO | AS26: SEM PENDÊNCIA | AU26: 6014.2025/0008617-8 | AV26: FINALIZADO | AW26: FINALIZADO | AX26: FINALIZADO | AY26: FINALIZADO | AZ26: 46024 | BA26: FINALIZADO | BB26: FINALIZADO | BC26: 46038 | BD26: 46038 | BE26: AGUARDANDO | BF26: LIBERADO DEMOLIÇÃO | BG26: FINALIZADO | BH26: =IFERROR(IF(BD26-KI26=0,"",BD26-AK26),"") -> 43 | BI26: =IF(AND(AH26<>"SIM",AH26="UH"),"AA","INDENIZAÇÃO") -> INDENIZAÇÃO | BJ26: =IF(AND(BD26<>"AGUARDANDO",BD26<>"",N26="AUXÍLIO ALUGUEL ATÉ INDENIZAÇÃO"),"SIM","NÃO") -> NÃO | BK26: N/A | BL26: N/A | BM26: N/A | BN26: FINALIZADO | BO26: FINALIZADO | BP26: 46128 | BQ26: FINALIZADO | BR26: AGUARDANDO
A27: 23 | B27: JD. PANTANAL | C27: NOVO HORIZONTE | D27: 1 | E27: -- | F27: 001/0004/AF2 | G27: OCUPADO | H27: RESIDENCIAL | I27: PROPRIETÁRIO RESIDENTE | J27: VALDELICE SILVA DE SOUZA | K27: 36.113.625-0 | L27: 306.868.168-54 | M27: CADASTRADO | N27: AUXÍLIO ALUGUEL UH | O27: 46058 | P27: 6014.2025/0007513-3 | Q27: 46058 | R27: 46058 | S27: 46059 | T27: 46063 | U27: OK | V27: OK | W27: 46073 | X27: 46104 | AA27: VALDELICE SILVA DE SOUZA | AB27: 36.113.625-0 | AC27: 306.868.168-54 | AD27: PROPRIETÁRIO RESIDENTE | AE27: CADASTRADO | AF27: N.A | AG27: N.A | AH27: UH | AI27: 6014.2025/0007373-4 | AK27: 46050 | AL27: 46050 | AM27: 46050 | AN27: 46050 | AO27: 46050 | AP27: 46050 | AR27: =IF(AQ27="SIM","AGUARDANDO CORREÇÃO",IF(AP27<>"","FINALIZADO",IF(AO27<>"","AGUARDANDO ENVIO DTS",IF(AN27<>"","AGUARDANDO ASSINATURA GAB",IF(AM27<>"","AGUARDANDO ASSINATURA CTS",IF(AL27<>"","AGUARDANDO ENVIO ASSINATURA CTS",IF(AK27<>"","AGUARDANDO CONFERÊNCIA",""))))))) -> FINALIZADO | BH27: =IFERROR(IF(BD27-KI27=0,"",BD27-AK27),"") | BI27: =IF(AND(AH27<>"SIM",AH27="UH"),"AA","INDENIZAÇÃO") -> AA | BJ27: =IF(AND(BD27<>"AGUARDANDO",BD27<>"",N27="AUXÍLIO ALUGUEL ATÉ INDENIZAÇÃO"),"SIM","NÃO") -> NÃO
A28: 24 | B28: JD. PANTANAL | C28: NOVO HORIZONTE | D28: 1 | E28: -- | F28: 001/0005/A | G28: OCUPADO | H28: RESIDENCIAL | I28: PROPRIETÁRIO RESIDENTE | J28: LUCAS GERALDO DOS SANTOS | K28: 42.641.652-1 | L28: 424.164.178-43 | M28: CADASTRADO | N28: AUXÍLIO ALUGUEL UH | O28: 46044 | P28: 6014.2025/0007513-3 | Q28: 46043 | R28: 46044 | S28: 46045 | T28: 46155 | U28: OK | V28: OK | W28: 46055 | X28: 46056 | AA28: LUCAS GERALDO DOS SANTOS | AB28: 42.641.652-1 | AC28: 424.164.178-43 | AD28: PROPRIETÁRIO RESIDENTE | AE28: CADASTRADO | AF28: N.A | AG28: N.A | AH28: UH | AI28: 6014.2025/0007373-4 | AK28: 46037 | AL28: 46037 | AM28: 46037 | AN28: 46037 | AO28: 46037 | AP28: 46037 | AR28: =IF(AQ28="SIM","AGUARDANDO CORREÇÃO",IF(AP28<>"","FINALIZADO",IF(AO28<>"","AGUARDANDO ENVIO DTS",IF(AN28<>"","AGUARDANDO ASSINATURA GAB",IF(AM28<>"","AGUARDANDO ASSINATURA CTS",IF(AL28<>"","AGUARDANDO ENVIO ASSINATURA CTS",IF(AK28<>"","AGUARDANDO CONFERÊNCIA",""))))))) -> FINALIZADO | BH28: =IFERROR(IF(BD28-KI28=0,"",BD28-AK28),"") | BI28: =IF(AND(AH28<>"SIM",AH28="UH"),"AA","INDENIZAÇÃO") -> AA | BJ28: =IF(AND(BD28<>"AGUARDANDO",BD28<>"",N28="AUXÍLIO ALUGUEL ATÉ INDENIZAÇÃO"),"SIM","NÃO") -> NÃO
A29: 25 | B29: JD. PANTANAL | C29: TERRA PROMETIDA | D29: 1 | E29: -- | F29: 001/0005/A | G29: OCUPADO | H29: RESIDENCIAL | I29: PROPRIETÁRIO RESIDENTE | J29: CECILIO BORGES DE SANTANA | K29: 01.353.707-52 | L29: 144.230.305-00 | M29: CADASTRADO | N29: AUXÍLIO ALUGUEL UH | O29: 46002 | P29: 6014.2025/0007513-3 | Q29: 45999 | R29: 46006 | S29: 46006 | T29: 46009 | U29: OK | V29: OK | W29: 46014 | X29: 46017 | Y29: 46017 | AA29: CECILIO BORGES DE SANTANA | AB29: 01.353.707-52 | AC29: 144.230.305-00 | AD29: PROPRIETÁRIO RESIDENTE | AE29: CADASTRADO | AF29: N.A | AG29: N.A | AH29: UH | AI29: 6014.2025/0007373-4 | AK29: 45996 | AL29: 45996 | AM29: 45996 | AN29: 45996 | AO29: 45996 | AP29: 45996 | AR29: =IF(AQ29="SIM","AGUARDANDO CORREÇÃO",IF(AP29<>"","FINALIZADO",IF(AO29<>"","AGUARDANDO ENVIO DTS",IF(AN29<>"","AGUARDANDO ASSINATURA GAB",IF(AM29<>"","AGUARDANDO ASSINATURA CTS",IF(AL29<>"","AGUARDANDO ENVIO ASSINATURA CTS",IF(AK29<>"","AGUARDANDO CONFERÊNCIA",""))))))) -> FINALIZADO | BE29: 46017 | BF29: DEMOLIDO | BH29: =IFERROR(IF(BD29-KI29=0,"",BD29-AK29),"") | BI29: =IF(AND(AH29<>"SIM",AH29="UH"),"AA","INDENIZAÇÃO") -> AA | BJ29: =IF(AND(BD29<>"AGUARDANDO",BD29<>"",N29="AUXÍLIO ALUGUEL ATÉ INDENIZAÇÃO"),"SIM","NÃO") -> NÃO
A30: 26 | B30: JD. PANTANAL | C30: SÃO MARTINHO VÁRZEA | D30: 1 | E30: -- | F30: 001/0005/A | G30: OCUPADO | H30: RESIDENCIAL | I30: PROPRIETÁRIO RESIDENTE | J30: JOSE ANDRE COELHO | K30: 38.520.790-6 | L30: 689.398.683-15 | M30: CADASTRADO | N30: INDENIZAÇÃO | O30: N.A | P30: N.A | Q30: N.A | R30: N.A | S30: N.A | T30: N.A | U30: N.A | V30: N.A | W30: N.A | X30: N.A | AA30: JOSE ANDRE COELHO | AB30: 38.520.790-6 | AC30: 689.398.683-15 | AD30: PROPRIETÁRIO RESIDENTE | AE30: CADASTRADO | AF30: 96282.33 | AG30: 96282.33 | AH30: SIM | AI30: 6014.2025/0007373-4 | AJ30: 146654114 | AK30: 46038 | AL30: 46038 | AM30: 46038 | AN30: 46038 | AO30: 46038 | AP30: 46038 | AR30: =IF(AQ30="SIM","AGUARDANDO CORREÇÃO",IF(AP30<>"","FINALIZADO",IF(AO30<>"","AGUARDANDO ENVIO DTS",IF(AN30<>"","AGUARDANDO ASSINATURA GAB",IF(AM30<>"","AGUARDANDO ASSINATURA CTS",IF(AL30<>"","AGUARDANDO ENVIO ASSINATURA CTS",IF(AK30<>"","AGUARDANDO CONFERÊNCIA",""))))))) -> FINALIZADO | AS30: SEM PENDÊNCIA | AU30: 6014.2026/0001005-0 | AV30: FINALIZADO | AW30: FINALIZADO | AX30: FINALIZADO | AY30: FINALIZADO | AZ30: 46085 | BA30: FINALIZADO | BB30: FINALIZADO | BC30: 46092 | BD30: 46092 | BE30: AGUARDANDO | BF30: LIBERADO DEMOLIÇÃO | BG30: FINALIZADO | BH30: =IFERROR(IF(BD30-KI30=0,"",BD30-AK30),"") -> 54 | BI30: =IF(AND(AH30<>"SIM",AH30="UH"),"AA","INDENIZAÇÃO") -> INDENIZAÇÃO | BJ30: =IF(AND(BD30<>"AGUARDANDO",BD30<>"",N30="AUXÍLIO ALUGUEL ATÉ INDENIZAÇÃO"),"SIM","NÃO") -> NÃO | BK30: N/A | BL30: N/A | BM30: N/A | BN30: FINALIZADO | BO30: FINALIZADO | BP30: 46128 | BQ30: FINALIZADO | BR30: AGUARDANDO
A31: 27 | B31: JD. PANTANAL | C31: NOVO HORIZONTE | D31: 1 | E31: -- | F31: 001/0005/AF2 | G31: OCUPADO | H31: COABITAÇÃO | I31: COABITAÇÃO | J31: LUIS AMADEU DA SILVA | K31: 37.843.968-6 | L31: 022.361.004-69 | M31: CADASTRADO | N31: AUXÍLIO ALUGUEL UH | O31: 46044 | P31: 6014.2025/0007513-3 | Q31: 46043 | R31: 46044 | S31: 46045 | T31: 46155 | U31: OK | V31: OK | W31: 46055 | X31: 46063 | AA31: LUIS AMADEU DA SILVA | AB31: 37.843.968-6 | AC31: 022.361.004-69 | AD31: PROPRIETÁRIO RESIDENTE | AE31: CADASTRADO | AF31: N.A | AG31: N.A | AH31: UH | AI31: 6014.2025/0007373-4 | AK31: 46038 | AL31: 46038 | AM31: 46038 | AN31: 46038 | AO31: 46038 | AP31: 46038 | AR31: =IF(AQ31="SIM","AGUARDANDO CORREÇÃO",IF(AP31<>"","FINALIZADO",IF(AO31<>"","AGUARDANDO ENVIO DTS",IF(AN31<>"","AGUARDANDO ASSINATURA GAB",IF(AM31<>"","AGUARDANDO ASSINATURA CTS",IF(AL31<>"","AGUARDANDO ENVIO ASSINATURA CTS",IF(AK31<>"","AGUARDANDO CONFERÊNCIA",""))))))) -> FINALIZADO | BH31: =IFERROR(IF(BD31-KI31=0,"",BD31-AK31),"") | BI31: =IF(AND(AH31<>"SIM",AH31="UH"),"AA","INDENIZAÇÃO") -> AA | BJ31: =IF(AND(BD31<>"AGUARDANDO",BD31<>"",N31="AUXÍLIO ALUGUEL ATÉ INDENIZAÇÃO"),"SIM","NÃO") -> NÃO
A32: 28 | B32: JD. PANTANAL | C32: NOVO HORIZONTE | D32: 1 | E32: -- | F32: 001/0005/B | G32: OCUPADO | H32: RESIDENCIAL | I32: PROPRIETÁRIO RESIDENTE | J32: GABRIEL DOS SANTOS OLIVEIRA | K32: 52.393.186 | L32: 451.473.188-95 | M32: CADASTRADO | N32: AUXÍLIO ALUGUEL UH | O32: 46044 | P32: 6014.2025/0007513-3 | Q32: 46043 | R32: 46044 | S32: 46045 | T32: 46155 | U32: OK | V32: OK | W32: 46055 | X32: 46056 | AA32: GABRIEL DOS SANTOS OLIVEIRA | AB32: 52.393.186 | AC32: 451.473.188-95 | AD32: PROPRIETÁRIO RESIDENTE | AE32: CADASTRADO | AF32: N.A | AG32: N.A | AH32: UH | AI32: 6014.2025/0007373-4 | AK32: 46037 | AL32: 46037 | AM32: 46037 | AN32: 46037 | AO32: 46037 | AP32: 46037 | AR32: =IF(AQ32="SIM","AGUARDANDO CORREÇÃO",IF(AP32<>"","FINALIZADO",IF(AO32<>"","AGUARDANDO ENVIO DTS",IF(AN32<>"","AGUARDANDO ASSINATURA GAB",IF(AM32<>"","AGUARDANDO ASSINATURA CTS",IF(AL32<>"","AGUARDANDO ENVIO ASSINATURA CTS",IF(AK32<>"","AGUARDANDO CONFERÊNCIA",""))))))) -> FINALIZADO | BH32: =IFERROR(IF(BD32-KI32=0,"",BD32-AK32),"") | BI32: =IF(AND(AH32<>"SIM",AH32="UH"),"AA","INDENIZAÇÃO") -> AA | BJ32: =IF(AND(BD32<>"AGUARDANDO",BD32<>"",N32="AUXÍLIO ALUGUEL ATÉ INDENIZAÇÃO"),"SIM","NÃO") -> NÃO
A33: 29 | B33: JD. PANTANAL | C33: TERRA PROMETIDA | D33: 1 | E33: -- | F33: 001/0006/A | G33: VAZIO | H33: CONSTRUÇÃO | I33: PROPRIETÁRIO NÃO RESIDENTE | J33: ROSA MARIA BATISTA DO NASCIMENTO | K33: 29.195.128-4 | L33: 196.176.518-74 | M33: CADASTRADO | N33: NÃO TEM DIREITO ATENDIMENTO | O33: N.A | P33: N.A | Q33: N.A | R33: N.A | S33: N.A | T33: N.A | U33: N.A | V33: N.A | W33: N.A | X33: N.A | AA33: ROSA MARIA BATISTA DO NASCIMENTO | AB33: -- | AC33: 196.176.518-74 | AD33: PROPRIETÁRIO RESIDENTE | AE33: CADASTRADO | AF33: N/A | AG33: N/A | AH33: N/A | AI33: 6014.2025/0007373-4 | AK33: 46050 | AL33: 46050 | AM33: 46050 | AN33: 46050 | AO33: 46050 | AP33: 46050 | AR33: =IF(AQ33="SIM","AGUARDANDO CORREÇÃO",IF(AP33<>"","FINALIZADO",IF(AO33<>"","AGUARDANDO ENVIO DTS",IF(AN33<>"","AGUARDANDO ASSINATURA GAB",IF(AM33<>"","AGUARDANDO ASSINATURA CTS",IF(AL33<>"","AGUARDANDO ENVIO ASSINATURA CTS",IF(AK33<>"","AGUARDANDO CONFERÊNCIA",""))))))) -> FINALIZADO | BE33: 46017 | BF33: DEMOLIDO | BH33: =IFERROR(IF(BD33-KI33=0,"",BD33-AK33),"") | BI33: =IF(AND(AH33<>"SIM",AH33="UH"),"AA","INDENIZAÇÃO") -> INDENIZAÇÃO | BJ33: =IF(AND(BD33<>"AGUARDANDO",BD33<>"",N33="AUXÍLIO ALUGUEL ATÉ INDENIZAÇÃO"),"SIM","NÃO") -> NÃO
A34: 30 | B34: JD. PANTANAL | C34: SÃO MARTINHO VÁRZEA | D34: 1 | E34: -- | F34: 001/0006/A | G34: OCUPADO | H34: RESIDENCIAL | I34: PROPRIETÁRIO RESIDENTE | J34: AMANDA OLIVEIRA ROCHA FERREIRA DOS SANTOS | K34: 39.088.600-2 | L34: 468.091.408-40 | M34: CADASTRADO | N34: INDENIZAÇÃO | O34: N.A | P34: N.A | Q34: N.A | R34: N.A | S34: N.A | T34: N.A | U34: N.A | V34: N.A | W34: N.A | X34: N.A | AA34: AMANDA OLIVEIRA ROCHA FERREIRA DOS SANTOS | AB34: 39.088.600-2 | AC34: 468.091.408-40 | AD34: PROPRIETÁRIO RESIDENTE | AE34: CADASTRADO | AF34: 69121.22 | AG34: 69121.22 | AH34: SIM | AI34: 6014.2025/0007373-4 | AJ34: 147746233 | AK34: 46020 | AL34: 46020 | AM34: 46020 | AN34: 46020 | AO34: 46020 | AP34: 46020 | AR34: =IF(AQ34="SIM","AGUARDANDO CORREÇÃO",IF(AP34<>"","FINALIZADO",IF(AO34<>"","AGUARDANDO ENVIO DTS",IF(AN34<>"","AGUARDANDO ASSINATURA GAB",IF(AM34<>"","AGUARDANDO ASSINATURA CTS",IF(AL34<>"","AGUARDANDO ENVIO ASSINATURA CTS",IF(AK34<>"","AGUARDANDO CONFERÊNCIA",""))))))) -> FINALIZADO | AS34: SEM PENDÊNCIA | AU34: 6014.2026/0000443-2 | AV34: FINALIZADO | AW34: FINALIZADO | AX34: FINALIZADO | AY34: FINALIZADO | AZ34: 46062 | BA34: FINALIZADO | BB34: FINALIZADO | BC34: 46066 | BD34: 46092 | BE34: AGUARDANDO | BF34: LIBERADO DEMOLIÇÃO | BG34: FINALIZADO | BH34: =IFERROR(IF(BD34-KI34=0,"",BD34-AK34),"") -> 72 | BI34: =IF(AND(AH34<>"SIM",AH34="UH"),"AA","INDENIZAÇÃO") -> INDENIZAÇÃO | BJ34: =IF(AND(BD34<>"AGUARDANDO",BD34<>"",N34="AUXÍLIO ALUGUEL ATÉ INDENIZAÇÃO"),"SIM","NÃO") -> NÃO | BK34: N/A | BL34: N/A | BM34: N/A | BN34: FINALIZADO | BO34: FINALIZADO | BP34: 46128 | BQ34: FINALIZADO | BR34: AGUARDANDO
A35: 31 | B35: JD. PANTANAL | C35: NOVO HORIZONTE | D35: 1 | E35: -- | F35: 001/0006/A | G35: OCUPADO | H35: RESIDENCIAL | I35: PROPRIETÁRIO RESIDENTE | J35: GREICE KELLE SANTOS SILVA | K35: 49.099.808-2 | L35: 421.459.728-11 | M35: CADASTRADO | N35: INDENIZAÇÃO | O35: N.A | P35: N.A | Q35: N.A | R35: N.A | S35: N.A | T35: N.A | U35: N.A | V35: N.A | W35: N.A | X35: N.A | AA35: GREICE KELLE SANTOS SILVA | AB35: 49.099.808-2 | AC35: 421.459.728-11 | AD35: PROPRIETÁRIO RESIDENTE | AE35: CADASTRADO | AF35: 2613.32 | AG35: =AF35+30000 -> 32613.32 | AH35: SIM | AI35: 6014.2025/0007373-4 | AJ35: 147746233 | AK35: 46079 | AL35: 46079 | AM35: 46079 | AN35: 46079 | AO35: 46079 | AP35: 46079 | AR35: =IF(AQ35="SIM","AGUARDANDO CORREÇÃO",IF(AP35<>"","FINALIZADO",IF(AO35<>"","AGUARDANDO ENVIO DTS",IF(AN35<>"","AGUARDANDO ASSINATURA GAB",IF(AM35<>"","AGUARDANDO ASSINATURA CTS",IF(AL35<>"","AGUARDANDO ENVIO ASSINATURA CTS",IF(AK35<>"","AGUARDANDO CONFERÊNCIA",""))))))) -> FINALIZADO | AS35: SEM PENDÊNCIA | AU35: 6014.2026/0001045-9 | AV35: FINALIZADO | AW35: FINALIZADO | AX35: FINALIZADO | AY35: FINALIZADO | AZ35: 46140 | BA35: FINALIZADO | BB35: FINALIZADO | BC35: 46161 | BD35: 46161 | BE35: AGUARDANDO | BF35: LIBERADO DEMOLIÇÃO | BG35: FINALIZADO | BH35: =IFERROR(IF(BD35-KI35=0,"",BD35-AK35),"") -> 82 | BI35: =IF(AND(AH35<>"SIM",AH35="UH"),"AA","INDENIZAÇÃO") -> INDENIZAÇÃO | BJ35: =IF(AND(BD35<>"AGUARDANDO",BD35<>"",N35="AUXÍLIO ALUGUEL ATÉ INDENIZAÇÃO"),"SIM","NÃO") -> NÃO | BK35: N/A | BL35: N/A | BM35: N/A | BN35: FINALIZADO | BO35: FINALIZADO | BP35: 46195 | BQ35: FINALIZADO | BR35: AGUARDANDO
A36: 32 | B36: JD. PANTANAL | C36: SÃO MARTINHO VÁRZEA | D36: 1 | E36: -- | F36: 001/0006/B | G36: OCUPADO | H36: COMERCIAL | I36: PROPRIETÁRIO NÃO RESIDENTE | J36: MARCOS AURÉLIO BARBOSA DA COSTA | K36: 69.452-5 | L36: 037.436.641-19 | M36: CADASTRADO | N36: INDENIZAÇÃO | O36: N.A | P36: N.A | Q36: N.A | R36: N.A | S36: N.A | T36: N.A | U36: N.A | V36: N.A | W36: N.A | X36: N.A | AA36: LEILA COUTO | AB36: 25.702.521-2 | AC36: 164.800.528-46 | AD36: PROPRIETÁRIO NÃO RESIDENTE | AE36: CADASTRADO | AF36: 58762.46 | AG36: 60000 | AH36: SIM | AI36: 6014.2025/0007373-4 | AJ36: 147746279 | AK36: 46020 | AL36: 46020 | AM36: 46020 | AN36: 46020 | AO36: 46020 | AP36: 46020 | AR36: =IF(AQ36="SIM","AGUARDANDO CORREÇÃO",IF(AP36<>"","FINALIZADO",IF(AO36<>"","AGUARDANDO ENVIO DTS",IF(AN36<>"","AGUARDANDO ASSINATURA GAB",IF(AM36<>"","AGUARDANDO ASSINATURA CTS",IF(AL36<>"","AGUARDANDO ENVIO ASSINATURA CTS",IF(AK36<>"","AGUARDANDO CONFERÊNCIA",""))))))) -> FINALIZADO | AS36: SEM PENDÊNCIA | AU36: 6014.2026/0000963-9 | AV36: FINALIZADO | AW36: FINALIZADO | AX36: FINALIZADO | AY36: FINALIZADO | AZ36: 46085 | BA36: FINALIZADO | BB36: FINALIZADO | BC36: 46092 | BD36: 46092 | BE36: AGUARDANDO | BF36: LIBERADO DEMOLIÇÃO | BG36: FINALIZADO | BH36: =IFERROR(IF(BD36-KI36=0,"",BD36-AK36),"") -> 72 | BI36: =IF(AND(AH36<>"SIM",AH36="UH"),"AA","INDENIZAÇÃO") -> INDENIZAÇÃO | BJ36: =IF(AND(BD36<>"AGUARDANDO",BD36<>"",N36="AUXÍLIO ALUGUEL ATÉ INDENIZAÇÃO"),"SIM","NÃO") -> NÃO | BK36: N/A | BL36: N/A | BM36: N/A | BN36: FINALIZADO | BO36: FINALIZADO | BP36: 46128 | BQ36: FINALIZADO | BR36: AGUARDANDO
A37: 33 | B37: JD. PANTANAL | C37: NOVO HORIZONTE | D37: 1 | E37: -- | F37: 001/0007/A | G37: OCUPADO | H37: RESIDENCIAL | I37: PROPRIETÁRIO RESIDENTE | J37: GEISIMARA DE JESUS BATISTA | K37: -- | L37: 349.886.018-62 | M37: CADASTRADO | N37: AUXÍLIO ALUGUEL UH | O37: 46044 | P37: 6014.2025/0007513-3 | Q37: 46043 | R37: 46044 | S37: 46045 | T37: 46155 | U37: OK | V37: OK | W37: 46055 | X37: 46056 | AA37: GEISIMARA DE JESUS BATISTA | AB37: -- | AC37: 349.886.018-62 | AD37: PROPRIETÁRIO RESIDENTE | AE37: CADASTRADO | AF37: N.A | AG37: N.A | AH37: UH | AI37: 6014.2025/0007373-4 | AK37: 46037 | AL37: 46037 | AM37: 46037 | AN37: 46037 | AO37: 46037 | AP37: 46037 | AR37: =IF(AQ37="SIM","AGUARDANDO CORREÇÃO",IF(AP37<>"","FINALIZADO",IF(AO37<>"","AGUARDANDO ENVIO DTS",IF(AN37<>"","AGUARDANDO ASSINATURA GAB",IF(AM37<>"","AGUARDANDO ASSINATURA CTS",IF(AL37<>"","AGUARDANDO ENVIO ASSINATURA CTS",IF(AK37<>"","AGUARDANDO CONFERÊNCIA",""))))))) -> FINALIZADO | BH37: =IFERROR(IF(BD37-KI37=0,"",BD37-AK37),"") | BI37: =IF(AND(AH37<>"SIM",AH37="UH"),"AA","INDENIZAÇÃO") -> AA | BJ37: =IF(AND(BD37<>"AGUARDANDO",BD37<>"",N37="AUXÍLIO ALUGUEL ATÉ INDENIZAÇÃO"),"SIM","NÃO") -> NÃO
A38: 34 | B38: JD. PANTANAL | C38: TERRA PROMETIDA | D38: 1 | E38: -- | F38: 001/0007/A | G38: OCUPADO | H38: RESIDENCIAL | I38: PROPRIETÁRIO RESIDENTE | J38: NICOLE SANTOS SILVA | K38: 52.818.068-X | L38: 451.034.548-82 | M38: CADASTRADO | N38: AUXÍLIO ALUGUEL UH | O38: 45986 | P38: 6014.2025/0007513-3 | Q38: 45985 | R38: 45986 | S38: 45987 | T38: 45992 | U38: OK | V38: OK | W38: 45999 | X38: 46000 | Y38: 46017 | AA38: NICOLE SANTOS SILVA | AB38: 52.818.068-X | AC38: 451.034.548-82 | AD38: PROPRIETÁRIO RESIDENTE | AE38: CADASTRADO | AF38: N.A | AG38: N.A | AH38: UH | AI38: 6014.2025/0007373-4 | AK38: 45979 | AL38: 45979 | AM38: 45979 | AN38: 45979 | AO38: 45979 | AP38: 45979 | AR38: =IF(AQ38="SIM","AGUARDANDO CORREÇÃO",IF(AP38<>"","FINALIZADO",IF(AO38<>"","AGUARDANDO ENVIO DTS",IF(AN38<>"","AGUARDANDO ASSINATURA GAB",IF(AM38<>"","AGUARDANDO ASSINATURA CTS",IF(AL38<>"","AGUARDANDO ENVIO ASSINATURA CTS",IF(AK38<>"","AGUARDANDO CONFERÊNCIA",""))))))) -> FINALIZADO | BE38: 46017 | BF38: DEMOLIDO | BH38: =IFERROR(IF(BD38-KI38=0,"",BD38-AK38),"") | BI38: =IF(AND(AH38<>"SIM",AH38="UH"),"AA","INDENIZAÇÃO") -> AA | BJ38: =IF(AND(BD38<>"AGUARDANDO",BD38<>"",N38="AUXÍLIO ALUGUEL ATÉ INDENIZAÇÃO"),"SIM","NÃO") -> NÃO
A39: 35 | B39: JD. PANTANAL | C39: SÃO MARTINHO VÁRZEA | D39: 1 | E39: -- | F39: 001/0007/A | G39: OCUPADO | H39: RESIDENCIAL | I39: PROPRIETÁRIO RESIDENTE | J39: BEATRIZ SOUZA MORAES DA SILVA | K39: 38.726.824-8 | L39: 443.862.368-56 | M39: CADASTRADO | N39: INDENIZAÇÃO | O39: N.A | P39: N.A | Q39: N.A | R39: N.A | S39: N.A | T39: N.A | U39: N.A | V39: N.A | W39: N.A | X39: N.A | AA39: BEATRIZ SOUZA MORAES DA SILVA | AB39: 38.726.824-8 | AC39: 443.862.368-56 | AD39: PROPRIETÁRIO RESIDENTE | AE39: CADASTRADO | AF39: 32549.34 | AG39: 60000 | AH39: SIM | AI39: 6014.2025/0007373-4 | AJ39: 147746658 | AK39: 46045 | AL39: 46045 | AM39: 46045 | AN39: 46045 | AO39: 46045 | AP39: 46045 | AR39: =IF(AQ39="SIM","AGUARDANDO CORREÇÃO",IF(AP39<>"","FINALIZADO",IF(AO39<>"","AGUARDANDO ENVIO DTS",IF(AN39<>"","AGUARDANDO ASSINATURA GAB",IF(AM39<>"","AGUARDANDO ASSINATURA CTS",IF(AL39<>"","AGUARDANDO ENVIO ASSINATURA CTS",IF(AK39<>"","AGUARDANDO CONFERÊNCIA",""))))))) -> FINALIZADO | AS39: SEM PENDÊNCIA | AU39: 6014.2026/0000843-8 | AV39: FINALIZADO | AW39: FINALIZADO | AX39: FINALIZADO | AY39: FINALIZADO | AZ39: 46085 | BA39: FINALIZADO | BB39: FINALIZADO | BC39: 46092 | BD39: 46092 | BE39: AGUARDANDO | BF39: LIBERADO DEMOLIÇÃO | BG39: FINALIZADO | BH39: =IFERROR(IF(BD39-KI39=0,"",BD39-AK39),"") -> 47 | BI39: =IF(AND(AH39<>"SIM",AH39="UH"),"AA","INDENIZAÇÃO") -> INDENIZAÇÃO | BJ39: =IF(AND(BD39<>"AGUARDANDO",BD39<>"",N39="AUXÍLIO ALUGUEL ATÉ INDENIZAÇÃO"),"SIM","NÃO") -> NÃO | BK39: N/A | BL39: N/A | BM39: N/A | BN39: FINALIZADO | BO39: FINALIZADO | BP39: 46128 | BQ39: FINALIZADO | BR39: AGUARDANDO
A40: 36 | B40: JD. PANTANAL | C40: TERRA PROMETIDA | D40: 1 | E40: -- | F40: 001/0008/A | G40: OCUPADO | H40: RESIDENCIAL | I40: PROPRIETÁRIO RESIDENTE | J40: MARCOS MARINHO DA SILVA | K40: 57.393.306-6 | L40: 023.663.194-28 | M40: CADASTRADO | N40: AUXÍLIO ALUGUEL UH | O40: 45986 | P40: 6014.2025/0007513-3 | Q40: 45985 | R40: 45986 | S40: 45987 | T40: 45992 | U40: OK | V40: OK | W40: 45999 | X40: 46000 | Y40: 46017 | AA40: MARCOS MARINHO DA SILVA | AB40: 57.393.306-6 | AC40: 023.663.194-28 | AD40: PROPRIETÁRIO RESIDENTE | AE40: CADASTRADO | AF40: N.A | AG40: N.A | AH40: UH | AI40: 6014.2025/0007373-4 | AK40: 45979 | AL40: 45979 | AM40: 45979 | AN40: 45979 | AO40: 45979 | AP40: 45979 | AR40: =IF(AQ40="SIM","AGUARDANDO CORREÇÃO",IF(AP40<>"","FINALIZADO",IF(AO40<>"","AGUARDANDO ENVIO DTS",IF(AN40<>"","AGUARDANDO ASSINATURA GAB",IF(AM40<>"","AGUARDANDO ASSINATURA CTS",IF(AL40<>"","AGUARDANDO ENVIO ASSINATURA CTS",IF(AK40<>"","AGUARDANDO CONFERÊNCIA",""))))))) -> FINALIZADO | BE40: 46017 | BF40: DEMOLIDO | BH40: =IFERROR(IF(BD40-KI40=0,"",BD40-AK40),"") | BI40: =IF(AND(AH40<>"SIM",AH40="UH"),"AA","INDENIZAÇÃO") -> AA | BJ40: =IF(AND(BD40<>"AGUARDANDO",BD40<>"",N40="AUXÍLIO ALUGUEL ATÉ INDENIZAÇÃO"),"SIM","NÃO") -> NÃO
A41: 37 | B41: JD. PANTANAL | C41: SÃO MARTINHO VÁRZEA | D41: 1 | E41: -- | F41: 001/0008/A | G41: OCUPADO | H41: MISTO | I41: PROPRIETÁRIO RESIDENTE | J41: JOICE VIEIRA GOMES | K41: 57.910.911-2 | L41: 087.724.714-50 | M41: CADASTRADO | N41: INDENIZAÇÃO | O41: N.A | P41: N.A | Q41: N.A | R41: N.A | S41: N.A | T41: N.A | U41: N.A | V41: N.A | W41: N.A | X41: N.A | AA41: JOICE VIEIRA GOMES | AB41: 57.910.911-2 | AC41: 087.724.714-50 | AD41: PROPRIETÁRIO RESIDENTE | AE41: CADASTRADO | AF41: 47592.04 | AG41: 60000 | AH41: SIM | AI41: 6014.2025/0007373-4 | AJ41: 147747048 | AK41: 46045 | AL41: 46045 | AM41: 46045 | AN41: 46045 | AO41: 46045 | AP41: 46045 | AR41: =IF(AQ41="SIM","AGUARDANDO CORREÇÃO",IF(AP41<>"","FINALIZADO",IF(AO41<>"","AGUARDANDO ENVIO DTS",IF(AN41<>"","AGUARDANDO ASSINATURA GAB",IF(AM41<>"","AGUARDANDO ASSINATURA CTS",IF(AL41<>"","AGUARDANDO ENVIO ASSINATURA CTS",IF(AK41<>"","AGUARDANDO CONFERÊNCIA",""))))))) -> FINALIZADO | AS41: SEM PENDÊNCIA | AU41: 6014.2026/0000981-7 | AV41: FINALIZADO | AW41: FINALIZADO | AX41: FINALIZADO | AY41: FINALIZADO | AZ41: 46085 | BA41: FINALIZADO | BB41: FINALIZADO | BC41: 46092 | BD41: 46092 | BE41: AGUARDANDO | BF41: LIBERADO DEMOLIÇÃO | BG41: FINALIZADO | BH41: =IFERROR(IF(BD41-KI41=0,"",BD41-AK41),"") -> 47 | BI41: =IF(AND(AH41<>"SIM",AH41="UH"),"AA","INDENIZAÇÃO") -> INDENIZAÇÃO | BJ41: =IF(AND(BD41<>"AGUARDANDO",BD41<>"",N41="AUXÍLIO ALUGUEL ATÉ INDENIZAÇÃO"),"SIM","NÃO") -> NÃO | BK41: N/A | BL41: N/A | BM41: N/A | BN41: FINALIZADO | BO41: FINALIZADO | BP41: 46128 | BQ41: FINALIZADO | BR41: AGUARDANDO
A42: 38 | B42: JD. PANTANAL | C42: NOVO HORIZONTE | D42: 1 | E42: -- | F42: 001/0008/A | G42: OCUPADO | H42: RESIDENCIAL | I42: PROPRIETÁRIO RESIDENTE | J42: ROSELI APARECIDA CARDOSO DOS SANTOS | K42: 23.553.256-3 | L42: 297.937.398-27 | M42: CADASTRADO | N42: INDENIZAÇÃO | O42: N.A | P42: N.A | Q42: N.A | R42: N.A | S42: N.A | T42: N.A | U42: N.A | V42: N.A | W42: N.A | X42: N.A | AA42: ROSELI APARECIDA CARDOSO DOS SANTOS | AB42: 23.553.256-3 | AC42: 297.937.398-27 | AD42: PROPRIETÁRIO RESIDENTE | AE42: CADASTRADO | AF42: 24189.38 | AG42: 54189.38 | AH42: SIM | AI42: 6014.2025/0007373-4 | AJ42: 150957778 | AK42: 46093 | AL42: 46093 | AM42: 46093 | AN42: 46093 | AO42: 46093 | AP42: 46093 | AR42: =IF(AQ42="SIM","AGUARDANDO CORREÇÃO",IF(AP42<>"","FINALIZADO",IF(AO42<>"","AGUARDANDO ENVIO DTS",IF(AN42<>"","AGUARDANDO ASSINATURA GAB",IF(AM42<>"","AGUARDANDO ASSINATURA CTS",IF(AL42<>"","AGUARDANDO ENVIO ASSINATURA CTS",IF(AK42<>"","AGUARDANDO CONFERÊNCIA",""))))))) -> FINALIZADO | AS42: SEM PENDÊNCIA | AU42: 6014.2026/0001565-5 | AV42: FINALIZADO | AW42: FINALIZADO | AX42: FINALIZADO | AY42: FINALIZADO | AZ42: 46128 | BA42: FINALIZADO | BB42: FINALIZADO | BC42: 46136 | BD42: 46136 | BE42: AGUARDANDO | BF42: LIBERADO DEMOLIÇÃO | BG42: FINALIZADO | BH42: =IFERROR(IF(BD42-KI42=0,"",BD42-AK42),"") -> 43 | BI42: =IF(AND(AH42<>"SIM",AH42="UH"),"AA","INDENIZAÇÃO") -> INDENIZAÇÃO | BJ42: =IF(AND(BD42<>"AGUARDANDO",BD42<>"",N42="AUXÍLIO ALUGUEL ATÉ INDENIZAÇÃO"),"SIM","NÃO") -> NÃO | BK42: N/A | BL42: N/A | BM42: N/A | BN42: FINALIZADO | BO42: FINALIZADO | BP42: 46195 | BQ42: FINALIZADO | BR42: AGUARDANDO
A43: 39 | B43: JD. PANTANAL | C43: TERRA PROMETIDA | D43: 1 | E43: -- | F43: 001/0009/A | G43: OCUPADO | H43: RESIDENCIAL | I43: PROPRIETÁRIO RESIDENTE | J43: ALINE BRITO FEITOSA | K43: 47.398.253-5 | L43: 416.896.138-90 | M43: CADASTRADO | N43: AUXÍLIO ALUGUEL UH | O43: 45986 | P43: 6014.2025/0007513-3 | Q43: 45985 | R43: 45986 | S43: 45987 | T43: 45992 | U43: OK | V43: OK | W43: 45999 | X43: 46000 | Y43: 46017 | AA43: ALINE BRITO FEITOSA | AB43: 47.398.253-5 | AC43: 416.896.138-90 | AD43: PROPRIETÁRIO RESIDENTE | AE43: CADASTRADO | AF43: N.A | AG43: N.A | AH43: UH | AI43: 6014.2025/0007373-4 | AK43: 45979 | AL43: 45979 | AM43: 45979 | AN43: 45979 | AO43: 45979 | AP43: 45979 | AR43: =IF(AQ43="SIM","AGUARDANDO CORREÇÃO",IF(AP43<>"","FINALIZADO",IF(AO43<>"","AGUARDANDO ENVIO DTS",IF(AN43<>"","AGUARDANDO ASSINATURA GAB",IF(AM43<>"","AGUARDANDO ASSINATURA CTS",IF(AL43<>"","AGUARDANDO ENVIO ASSINATURA CTS",IF(AK43<>"","AGUARDANDO CONFERÊNCIA",""))))))) -> FINALIZADO | BE43: 46017 | BF43: DEMOLIDO | BH43: =IFERROR(IF(BD43-KI43=0,"",BD43-AK43),"") | BI43: =IF(AND(AH43<>"SIM",AH43="UH"),"AA","INDENIZAÇÃO") -> AA | BJ43: =IF(AND(BD43<>"AGUARDANDO",BD43<>"",N43="AUXÍLIO ALUGUEL ATÉ INDENIZAÇÃO"),"SIM","NÃO") -> NÃO
A44: 40 | B44: JD. PANTANAL | C44: NOVO HORIZONTE | D44: 1 | E44: -- | F44: 001/0009/A | G44: OCUPADO | H44: MISTO | I44: PROPRIETÁRIO RESIDENTE | J44: RAFAELA CARDOSO DE SOUZA | K44: 60.539.394-1 | L44: 525.982.878-00 | M44: CADASTRADO | N44: INDENIZAÇÃO | O44: N.A | P44: N.A | Q44: N.A | R44: N.A | S44: N.A | T44: N.A | U44: N.A | V44: N.A | W44: N.A | X44: N.A | AA44: RAFAELA CARDOSO DE SOUZA | AB44: 60.539.394-1 | AC44: 525.982.878-00 | AD44: PROPRIETÁRIO RESIDENTE | AE44: CADASTRADO | AF44: 69809.19 | AG44: 69809.19 | AH44: SIM | AI44: 6014.2025/0007373-4 | AJ44: 150958177 | AK44: 46079 | AL44: 46079 | AM44: 46079 | AN44: 46079 | AO44: 46079 | AP44: 46079 | AR44: =IF(AQ44="SIM","AGUARDANDO CORREÇÃO",IF(AP44<>"","FINALIZADO",IF(AO44<>"","AGUARDANDO ENVIO DTS",IF(AN44<>"","AGUARDANDO ASSINATURA GAB",IF(AM44<>"","AGUARDANDO ASSINATURA CTS",IF(AL44<>"","AGUARDANDO ENVIO ASSINATURA CTS",IF(AK44<>"","AGUARDANDO CONFERÊNCIA",""))))))) -> FINALIZADO | AS44: SEM PENDÊNCIA | AU44: 6014.2026/0001049-1 | AV44: FINALIZADO | AW44: FINALIZADO | AX44: FINALIZADO | AY44: FINALIZADO | AZ44: 46118 | BA44: FINALIZADO | BB44: FINALIZADO | BC44: 46122 | BD44: 46122 | BE44: AGUARDANDO | BF44: LIBERADO DEMOLIÇÃO | BG44: FINALIZADO | BH44: =IFERROR(IF(BD44-KI44=0,"",BD44-AK44),"") -> 43 | BI44: =IF(AND(AH44<>"SIM",AH44="UH"),"AA","INDENIZAÇÃO") -> INDENIZAÇÃO | BJ44: =IF(AND(BD44<>"AGUARDANDO",BD44<>"",N44="AUXÍLIO ALUGUEL ATÉ INDENIZAÇÃO"),"SIM","NÃO") -> NÃO | BK44: N/A | BL44: N/A | BM44: N/A | BN44: FINALIZADO | BO44: FINALIZADO | BP44: 46195 | BQ44: FINALIZADO | BR44: AGUARDANDO
A45: 41 | B45: JD. PANTANAL | C45: SÃO MARTINHO VÁRZEA | D45: 1 | E45: -- | F45: 001/0009/A | G45: OCUPADO | H45: RESIDENCIAL | I45: PROPRIETÁRIO RESIDENTE | J45: LORISVAL JESUS DOS SANTOS | K45: 66.909.459-6 | L45: 082.624.395-97 | M45: CADASTRADO | N45: INDENIZAÇÃO | O45: N.A | P45: N.A | Q45: N.A | R45: N.A | S45: N.A | T45: N.A | U45: N.A | V45: N.A | W45: N.A | X45: N.A | AA45: LORISVAL JESUS DOS SANTOS | AB45: 66.909.459-6 | AC45: 082.624.395-97 | AD45: PROPRIETÁRIO RESIDENTE | AE45: CADASTRADO | AF45: 38389.07 | AG45: 60000 | AH45: SIM | AI45: 6014.2025/0007373-4 | AJ45: 147747118 | AK45: 46065 | AL45: 46065 | AM45: 46065 | AN45: 46065 | AO45: 46065 | AP45: 46065 | AR45: =IF(AQ45="SIM","AGUARDANDO CORREÇÃO",IF(AP45<>"","FINALIZADO",IF(AO45<>"","AGUARDANDO ENVIO DTS",IF(AN45<>"","AGUARDANDO ASSINATURA GAB",IF(AM45<>"","AGUARDANDO ASSINATURA CTS",IF(AL45<>"","AGUARDANDO ENVIO ASSINATURA CTS",IF(AK45<>"","AGUARDANDO CONFERÊNCIA",""))))))) -> FINALIZADO | AS45: SEM PENDÊNCIA | AU45: 6014.2026/0000625-7 | AV45: FINALIZADO | AW45: FINALIZADO | AX45: FINALIZADO | AY45: FINALIZADO | AZ45: 46153 | BA45: FINALIZADO | BB45: FINALIZADO | BC45: 46157 | BD45: 46157 | BE45: AGUARDANDO | BF45: LIBERADO DEMOLIÇÃO | BG45: FINALIZADO | BH45: =IFERROR(IF(BD45-KI45=0,"",BD45-AK45),"") -> 92 | BI45: =IF(AND(AH45<>"SIM",AH45="UH"),"AA","INDENIZAÇÃO") -> INDENIZAÇÃO | BJ45: =IF(AND(BD45<>"AGUARDANDO",BD45<>"",N45="AUXÍLIO ALUGUEL ATÉ INDENIZAÇÃO"),"SIM","NÃO") -> NÃO | BK45: N/A | BL45: N/A | BM45: N/A | BN45: FINALIZADO | BO45: FINALIZADO | BP45: 46195 | BQ45: FINALIZADO | BR45: AGUARDANDO
A46: 42 | B46: JD. PANTANAL | C46: TERRA PROMETIDA | D46: 1 | E46: -- | F46: 001/0009/B | G46: OCUPADO | H46: RESIDENCIAL | I46: PROPRIETÁRIO RESIDENTE | J46: ALESSANDRO SANTOS MATOS | K46: 33.969.709-X | L46: 398.341.268-83 | M46: CADASTRADO | N46: AUXÍLIO ALUGUEL UH | O46: 45986 | P46: 6014.2025/0007513-3 | Q46: 45985 | R46: 45986 | S46: 45987 | T46: 45992 | U46: OK | V46: OK | W46: 45999 | X46: 46000 | Y46: 46017 | AA46: ALESSANDRO SANTOS MATOS | AB46: 398.341.268-83 | AC46: 471.022.558-37 | AD46: PROPRIETÁRIO RESIDENTE | AE46: CADASTRADO | AF46: N.A | AG46: N.A | AH46: UH | AI46: 6014.2025/0007373-4 | AK46: 45979 | AL46: 45979 | AM46: 45979 | AN46: 45979 | AO46: 45979 | AP46: 45979 | AR46: =IF(AQ46="SIM","AGUARDANDO CORREÇÃO",IF(AP46<>"","FINALIZADO",IF(AO46<>"","AGUARDANDO ENVIO DTS",IF(AN46<>"","AGUARDANDO ASSINATURA GAB",IF(AM46<>"","AGUARDANDO ASSINATURA CTS",IF(AL46<>"","AGUARDANDO ENVIO ASSINATURA CTS",IF(AK46<>"","AGUARDANDO CONFERÊNCIA",""))))))) -> FINALIZADO | BE46: 46017 | BF46: DEMOLIDO | BH46: =IFERROR(IF(BD46-KI46=0,"",BD46-AK46),"") | BI46: =IF(AND(AH46<>"SIM",AH46="UH"),"AA","INDENIZAÇÃO") -> AA | BJ46: =IF(AND(BD46<>"AGUARDANDO",BD46<>"",N46="AUXÍLIO ALUGUEL ATÉ INDENIZAÇÃO"),"SIM","NÃO") -> NÃO
A47: 43 | B47: JD. PANTANAL | C47: TERRA PROMETIDA | D47: 1 | E47: -- | F47: 001/0009/C | G47: OCUPADO | H47: RESIDENCIAL | I47: PROPRIETÁRIO RESIDENTE | J47: VICTÓRIA GABRIELA NATALINE INEZ | K47: -- | L47: 514.132.538-57 | M47: CADASTRADO | N47: AUXÍLIO ALUGUEL UH | O47: 45986 | P47: 6014.2025/0007513-3 | Q47: 45985 | R47: 45986 | S47: 45987 | T47: 45992 | U47: OK | V47: OK | W47: 45999 | X47: 46000 | Y47: 46017 | AA47: VICTÓRIA GABRIELA NATALINE INEZ | AB47: 56.212.584-X | AC47: 514.132.538-57 | AD47: PROPRIETÁRIO RESIDENTE | AE47: CADASTRADO | AF47: N.A | AG47: N.A | AH47: UH | AI47: 6014.2025/0007373-4 | AK47: 45979 | AL47: 45979 | AM47: 45979 | AN47: 45979 | AO47: 45979 | AP47: 45979 | AR47: =IF(AQ47="SIM","AGUARDANDO CORREÇÃO",IF(AP47<>"","FINALIZADO",IF(AO47<>"","AGUARDANDO ENVIO DTS",IF(AN47<>"","AGUARDANDO ASSINATURA GAB",IF(AM47<>"","AGUARDANDO ASSINATURA CTS",IF(AL47<>"","AGUARDANDO ENVIO ASSINATURA CTS",IF(AK47<>"","AGUARDANDO CONFERÊNCIA",""))))))) -> FINALIZADO | BE47: 46017 | BF47: DEMOLIDO | BH47: =IFERROR(IF(BD47-KI47=0,"",BD47-AK47),"") | BI47: =IF(AND(AH47<>"SIM",AH47="UH"),"AA","INDENIZAÇÃO") -> AA | BJ47: =IF(AND(BD47<>"AGUARDANDO",BD47<>"",N47="AUXÍLIO ALUGUEL ATÉ INDENIZAÇÃO"),"SIM","NÃO") -> NÃO
A48: 44 | B48: JD. PANTANAL | C48: TERRA PROMETIDA | D48: 1 | E48: -- | F48: 001/0010/A | G48: OCUPADO | H48: RESIDENCIAL | I48: PROPRIETÁRIO RESIDENTE | J48: POLIANNA BARBOSA FEITOSA DE OLIVEIRA | K48: _ | L48: 022.548.782-98 | M48: CADASTRADO | N48: AUXÍLIO ALUGUEL UH | O48: 46002 | P48: 6014.2025/0007513-3 | Q48: 45999 | R48: 46006 | S48: 46006 | T48: 46009 | U48: OK | V48: OK | W48: 46014 | X48: 46000 | Y48: 46017 | AA48: POLIANNA BARBOSA FEITOSA DE OLIVEIRA | AB48: _ | AC48: 022.548.782-98 | AD48: PROPRIETÁRIO RESIDENTE | AE48: CADASTRADO | AF48: N.A | AG48: N.A | AH48: UH | AI48: 6014.2025/0007373-4 | AK48: 45996 | AL48: 45996 | AM48: 45996 | AN48: 45996 | AO48: 45996 | AP48: 45996 | AR48: =IF(AQ48="SIM","AGUARDANDO CORREÇÃO",IF(AP48<>"","FINALIZADO",IF(AO48<>"","AGUARDANDO ENVIO DTS",IF(AN48<>"","AGUARDANDO ASSINATURA GAB",IF(AM48<>"","AGUARDANDO ASSINATURA CTS",IF(AL48<>"","AGUARDANDO ENVIO ASSINATURA CTS",IF(AK48<>"","AGUARDANDO CONFERÊNCIA",""))))))) -> FINALIZADO | BE48: 46017 | BF48: DEMOLIDO | BH48: =IFERROR(IF(BD48-KI48=0,"",BD48-AK48),"") | BI48: =IF(AND(AH48<>"SIM",AH48="UH"),"AA","INDENIZAÇÃO") -> AA | BJ48: =IF(AND(BD48<>"AGUARDANDO",BD48<>"",N48="AUXÍLIO ALUGUEL ATÉ INDENIZAÇÃO"),"SIM","NÃO") -> NÃO
A49: 45 | B49: JD. PANTANAL | C49: NOVO HORIZONTE | D49: 1 | E49: -- | F49: 001/0010/A | G49: OCUPADO | H49: RESIDENCIAL | I49: PROPRIETÁRIO RESIDENTE | J49: ALESSANDRA DOS SANTOS OLIVEIRA | K49: 38.869.459-2 | L49: 387.790.678-83 | M49: CADASTRADO | N49: INDENIZAÇÃO | O49: N.A | P49: N.A | Q49: N.A | R49: N.A | S49: N.A | T49: N.A | U49: N.A | V49: N.A | W49: N.A | X49: N.A | AA49: ALESSANDRA DOS SANTOS OLIVEIRA | AB49: 38.869.459-2 | AC49: 387.790.678-83 | AD49: PROPRIETÁRIO RESIDENTE | AE49: CADASTRADO | AF49: 35792.87 | AG49: 60000 | AH49: SIM | AI49: 6014.2025/0007373-4 | AJ49: 150958274 | AK49: 46086 | AL49: 46086 | AM49: 46086 | AN49: 46086 | AO49: 46086 | AP49: 46086 | AR49: =IF(AQ49="SIM","AGUARDANDO CORREÇÃO",IF(AP49<>"","FINALIZADO",IF(AO49<>"","AGUARDANDO ENVIO DTS",IF(AN49<>"","AGUARDANDO ASSINATURA GAB",IF(AM49<>"","AGUARDANDO ASSINATURA CTS",IF(AL49<>"","AGUARDANDO ENVIO ASSINATURA CTS",IF(AK49<>"","AGUARDANDO CONFERÊNCIA",""))))))) -> FINALIZADO | AS49: SEM PENDÊNCIA | AU49: 6014.2026/0001182-0 | AV49: FINALIZADO | AW49: FINALIZADO | AX49: FINALIZADO | AY49: FINALIZADO | AZ49: 46128 | BA49: FINALIZADO | BB49: FINALIZADO | BC49: 46139 | BD49: 46139 | BE49: AGUARDANDO | BF49: LIBERADO DEMOLIÇÃO | BG49: FINALIZADO | BH49: =IFERROR(IF(BD49-KI49=0,"",BD49-AK49),"") -> 53 | BI49: =IF(AND(AH49<>"SIM",AH49="UH"),"AA","INDENIZAÇÃO") -> INDENIZAÇÃO | BJ49: =IF(AND(BD49<>"AGUARDANDO",BD49<>"",N49="AUXÍLIO ALUGUEL ATÉ INDENIZAÇÃO"),"SIM","NÃO") -> NÃO | BK49: N/A | BL49: N/A | BM49: N/A | BN49: FINALIZADO | BO49: FINALIZADO | BP49: 46195 | BQ49: FINALIZADO | BR49: AGUARDANDO
A50: 46 | B50: JD. PANTANAL | C50: NOVO HORIZONTE | D50: 1 | E50: -- | F50: 001/0010/AF2 | G50: OCUPADO | H50: COABITAÇÃO | I50: COABITAÇÃO | J50: HELENA TALINEZ NATASHA ROSÂNGELA DOS SANTOS GALDINO | K50: 57.618.016-6 | L50: 536.299.838-20 | M50: CADASTRADO | N50: AUXÍLIO ALUGUEL UH | O50: 46044 | P50: 6014.2025/0007513-3 | Q50: 46043 | R50: 46044 | S50: 46045 | T50: 46155 | U50: OK | V50: OK | W50: 46055 | X50: 46078 | AA50: HELENA TALINEZ NATASHA ROSÂNGELA DOS SANTOS GALDINO | AB50: 57.618.016-6 | AC50: 536.299.838-20 | AD50: PROPRIETÁRIO RESIDENTE | AE50: CADASTRADO | AF50: N.A | AG50: N.A | AH50: UH | AI50: 6014.2025/0007373-4 | AK50: 46037 | AL50: 46037 | AM50: 46037 | AN50: 46037 | AO50: 46037 | AP50: 46037 | AR50: =IF(AQ50="SIM","AGUARDANDO CORREÇÃO",IF(AP50<>"","FINALIZADO",IF(AO50<>"","AGUARDANDO ENVIO DTS",IF(AN50<>"","AGUARDANDO ASSINATURA GAB",IF(AM50<>"","AGUARDANDO ASSINATURA CTS",IF(AL50<>"","AGUARDANDO ENVIO ASSINATURA CTS",IF(AK50<>"","AGUARDANDO CONFERÊNCIA",""))))))) -> FINALIZADO | BH50: =IFERROR(IF(BD50-KI50=0,"",BD50-AK50),"") | BI50: =IF(AND(AH50<>"SIM",AH50="UH"),"AA","INDENIZAÇÃO") -> AA | BJ50: =IF(AND(BD50<>"AGUARDANDO",BD50<>"",N50="AUXÍLIO ALUGUEL ATÉ INDENIZAÇÃO"),"SIM","NÃO") -> NÃO
A51: 47 | B51: JD. PANTANAL | C51: TERRA PROMETIDA | D51: 1 | E51: -- | F51: 001/0011/A | G51: OCUPADO | H51: RESIDENCIAL | I51: PROPRIETÁRIO RESIDENTE | J51: LARISSA DOS SANTOS COELHO | K51: 59.751.718-6 | L51: 495.648.528-03 | M51: CADASTRADO | N51: AUXÍLIO ALUGUEL UH | O51: 45986 | P51: 6014.2025/0007513-3 | Q51: 45985 | R51: 45986 | S51: 45987 | T51: 45992 | U51: OK | V51: OK | W51: 45999 | X51: 46000 | Y51: 46017 | AA51: LARISSA DOS SANTOS COELHO | AB51: 59.751.718-6 | AC51: 495.648.528-03 | AD51: PROPRIETÁRIO RESIDENTE | AE51: CADASTRADO | AF51: N.A | AG51: N.A | AH51: UH | AI51: 6014.2025/0007373-4 | AK51: 45979 | AL51: 45979 | AM51: 45979 | AN51: 45979 | AO51: 45979 | AP51: 45979 | AR51: =IF(AQ51="SIM","AGUARDANDO CORREÇÃO",IF(AP51<>"","FINALIZADO",IF(AO51<>"","AGUARDANDO ENVIO DTS",IF(AN51<>"","AGUARDANDO ASSINATURA GAB",IF(AM51<>"","AGUARDANDO ASSINATURA CTS",IF(AL51<>"","AGUARDANDO ENVIO ASSINATURA CTS",IF(AK51<>"","AGUARDANDO CONFERÊNCIA",""))))))) -> FINALIZADO | BE51: 46017 | BF51: DEMOLIDO | BH51: =IFERROR(IF(BD51-KI51=0,"",BD51-AK51),"") | BI51: =IF(AND(AH51<>"SIM",AH51="UH"),"AA","INDENIZAÇÃO") -> AA | BJ51: =IF(AND(BD51<>"AGUARDANDO",BD51<>"",N51="AUXÍLIO ALUGUEL ATÉ INDENIZAÇÃO"),"SIM","NÃO") -> NÃO
A52: 48 | B52: JD. PANTANAL | C52: NOVO HORIZONTE | D52: 1 | E52: -- | F52: 001/0011/A | G52: CONSTRUÇÃO | H52: CONSTRUÇÃO | I52: PROPRIETÁRIO NÃO RESIDENTE | J52: ROMERILTON PEREIRA DA SILVA | K52: 34.369.668-X | L52: 367.817.428-09 | M52: CADASTRADO | N52: INDENIZAÇÃO | O52: N.A | P52: N.A | Q52: N.A | R52: N.A | S52: N.A | T52: N.A | U52: N.A | V52: N.A | W52: N.A | X52: N.A | AA52: JAYNE MEDEIROS SOUZA | AB52: -- | AC52: 526.752.688-60 | AD52: PROPRIETÁRIO NÃO RESIDENTE | AE52: CADASTRADO | AF52: 1702.35 | AG52: 1702.35 | AH52: SIM | AI52: 6014.2025/0007373-4 | AK52: 46090 | AL52: 46090 | AM52: 46090 | AN52: 46090 | AO52: 46090 | AP52: 46090 | AR52: =IF(AQ52="SIM","AGUARDANDO CORREÇÃO",IF(AP52<>"","FINALIZADO",IF(AO52<>"","AGUARDANDO ENVIO DTS",IF(AN52<>"","AGUARDANDO ASSINATURA GAB",IF(AM52<>"","AGUARDANDO ASSINATURA CTS",IF(AL52<>"","AGUARDANDO ENVIO ASSINATURA CTS",IF(AK52<>"","AGUARDANDO CONFERÊNCIA",""))))))) -> FINALIZADO | BH52: =IFERROR(IF(BD52-KI52=0,"",BD52-AK52),"") | BI52: =IF(AND(AH52<>"SIM",AH52="UH"),"AA","INDENIZAÇÃO") -> INDENIZAÇÃO | BJ52: =IF(AND(BD52<>"AGUARDANDO",BD52<>"",N52="AUXÍLIO ALUGUEL ATÉ INDENIZAÇÃO"),"SIM","NÃO") -> NÃO
A53: 49 | B53: JD. PANTANAL | C53: TERRA PROMETIDA | D53: 1 | E53: -- | F53: 001/0012/A | G53: OCUPADO | H53: RESIDENCIAL | I53: PROPRIETÁRIO RESIDENTE | J53: VITORIA MORAIS DOS SANTOS | K53: 60.075.168-5 | L53: 547.277.498-58 | M53: CADASTRADO | N53: AUXÍLIO ALUGUEL UH | O53: 45986 | P53: 6014.2025/0007513-3 | Q53: 45985 | R53: 45986 | S53: 45987 | T53: 45992 | U53: OK | V53: OK | W53: 45999 | X53: 46000 | Y53: 46017 | AA53: VITORIA MORAIS DOS SANTOS | AB53: 60.075.168-5 | AC53: 547.277.498-58 | AD53: PROPRIETÁRIO RESIDENTE | AE53: CADASTRADO | AF53: N.A | AG53: N.A | AH53: UH | AI53: 6014.2025/0007373-4 | AK53: 45979 | AL53: 45979 | AM53: 45979 | AN53: 45979 | AO53: 45979 | AP53: 45979 | AR53: =IF(AQ53="SIM","AGUARDANDO CORREÇÃO",IF(AP53<>"","FINALIZADO",IF(AO53<>"","AGUARDANDO ENVIO DTS",IF(AN53<>"","AGUARDANDO ASSINATURA GAB",IF(AM53<>"","AGUARDANDO ASSINATURA CTS",IF(AL53<>"","AGUARDANDO ENVIO ASSINATURA CTS",IF(AK53<>"","AGUARDANDO CONFERÊNCIA",""))))))) -> FINALIZADO | BE53: 46017 | BF53: DEMOLIDO | BH53: =IFERROR(IF(BD53-KI53=0,"",BD53-AK53),"") | BI53: =IF(AND(AH53<>"SIM",AH53="UH"),"AA","INDENIZAÇÃO") -> AA | BJ53: =IF(AND(BD53<>"AGUARDANDO",BD53<>"",N53="AUXÍLIO ALUGUEL ATÉ INDENIZAÇÃO"),"SIM","NÃO") -> NÃO
A54: 50 | B54: JD. PANTANAL | C54: NOVO HORIZONTE | D54: 1 | E54: -- | F54: 001/0012/A | G54: OCUPADO | H54: RESIDENCIAL | I54: PROPRIETÁRIO RESIDENTE | J54: JUSTINO DOS SANTOS | K54: 56.922.639-9 | L54: 892.112.605-82 | M54: CADASTRADO | N54: AUXÍLIO ALUGUEL UH | O54: 46058 | P54: 6014.2025/0007513-3 | Q54: 46058 | R54: 46058 | S54: 46059 | T54: 46063 | U54: OK | V54: OK | W54: 46073 | X54: 46078 | AA54: JUSTINO DOS SANTOS | AB54: 56.922.639-9 | AC54: 892.112.605-82 | AD54: PROPRIETÁRIO RESIDENTE | AE54: CADASTRADO | AF54: N.A | AG54: N.A | AH54: UH | AI54: 6014.2025/0007373-4 | AK54: 46064 | AL54: 46064 | AM54: 46064 | AN54: 46064 | AO54: 46064 | AP54: 46064 | AR54: =IF(AQ54="SIM","AGUARDANDO CORREÇÃO",IF(AP54<>"","FINALIZADO",IF(AO54<>"","AGUARDANDO ENVIO DTS",IF(AN54<>"","AGUARDANDO ASSINATURA GAB",IF(AM54<>"","AGUARDANDO ASSINATURA CTS",IF(AL54<>"","AGUARDANDO ENVIO ASSINATURA CTS",IF(AK54<>"","AGUARDANDO CONFERÊNCIA",""))))))) -> FINALIZADO | BH54: =IFERROR(IF(BD54-KI54=0,"",BD54-AK54),"") | BI54: =IF(AND(AH54<>"SIM",AH54="UH"),"AA","INDENIZAÇÃO") -> AA | BJ54: =IF(AND(BD54<>"AGUARDANDO",BD54<>"",N54="AUXÍLIO ALUGUEL ATÉ INDENIZAÇÃO"),"SIM","NÃO") -> NÃO
A55: 51 | B55: JD. PANTANAL | C55: TERRA PROMETIDA | D55: 1 | E55: -- | F55: 001/0012/B | G55: OCUPADO | H55: RESIDENCIAL | I55: PROPRIETÁRIO RESIDENTE | J55: CAROLINA MORAIS DOS SANTOS | K55: 45.664.410-6 | L55: 482.333.558-95 | M55: CADASTRADO | N55: AUXÍLIO ALUGUEL UH | O55: 45986 | P55: 6014.2025/0007513-3 | Q55: 45985 | R55: 45986 | S55: 45987 | T55: 45992 | U55: OK | V55: OK | W55: 45999 | X55: 46000 | Y55: 46017 | AA55: CAROLINA MORAIS DOS SANTOS | AB55: 45.664.410-6 | AC55: 482.333.558-95 | AD55: PROPRIETÁRIO RESIDENTE | AE55: CADASTRADO | AF55: N.A | AG55: N.A | AH55: UH | AI55: 6014.2025/0007373-4 | AK55: 45979 | AL55: 45979 | AM55: 45979 | AN55: 45979 | AO55: 45979 | AP55: 45979 | AR55: =IF(AQ55="SIM","AGUARDANDO CORREÇÃO",IF(AP55<>"","FINALIZADO",IF(AO55<>"","AGUARDANDO ENVIO DTS",IF(AN55<>"","AGUARDANDO ASSINATURA GAB",IF(AM55<>"","AGUARDANDO ASSINATURA CTS",IF(AL55<>"","AGUARDANDO ENVIO ASSINATURA CTS",IF(AK55<>"","AGUARDANDO CONFERÊNCIA",""))))))) -> FINALIZADO | BE55: 46017 | BF55: DEMOLIDO | BH55: =IFERROR(IF(BD55-KI55=0,"",BD55-AK55),"") | BI55: =IF(AND(AH55<>"SIM",AH55="UH"),"AA","INDENIZAÇÃO") -> AA | BJ55: =IF(AND(BD55<>"AGUARDANDO",BD55<>"",N55="AUXÍLIO ALUGUEL ATÉ INDENIZAÇÃO"),"SIM","NÃO") -> NÃO
A56: 52 | B56: JD. PANTANAL | C56: TERRA PROMETIDA | D56: 1 | E56: -- | F56: 001/0013/A | G56: OCUPADO | H56: RESIDENCIAL | I56: PROPRIETÁRIO RESIDENTE | J56: TATIANE DE OLIVEIRA ANDRIOTI | K56: 42.836.595-4 | L56: 397.478.998-76 | M56: CADASTRADO | N56: AUXÍLIO ALUGUEL UH | O56: 45986 | P56: 6014.2025/0007513-3 | Q56: 45985 | R56: 45986 | S56: 45987 | T56: 45992 | U56: OK | V56: OK | W56: 45999 | X56: 46000 | Y56: 46017 | AA56: TATIANE DE OLIVEIRA ANDRIOTI | AB56: 42.836.595-4 | AC56: 397.478.998-76 | AD56: PROPRIETÁRIO RESIDENTE | AE56: CADASTRADO | AF56: N.A | AG56: N.A | AH56: UH | AI56: 6014.2025/0007373-4 | AK56: 45979 | AL56: 45979 | AM56: 45979 | AN56: 45979 | AO56: 45979 | AP56: 45979 | AR56: =IF(AQ56="SIM","AGUARDANDO CORREÇÃO",IF(AP56<>"","FINALIZADO",IF(AO56<>"","AGUARDANDO ENVIO DTS",IF(AN56<>"","AGUARDANDO ASSINATURA GAB",IF(AM56<>"","AGUARDANDO ASSINATURA CTS",IF(AL56<>"","AGUARDANDO ENVIO ASSINATURA CTS",IF(AK56<>"","AGUARDANDO CONFERÊNCIA",""))))))) -> FINALIZADO | BE56: 46017 | BF56: DEMOLIDO | BH56: =IFERROR(IF(BD56-KI56=0,"",BD56-AK56),"") | BI56: =IF(AND(AH56<>"SIM",AH56="UH"),"AA","INDENIZAÇÃO") -> AA | BJ56: =IF(AND(BD56<>"AGUARDANDO",BD56<>"",N56="AUXÍLIO ALUGUEL ATÉ INDENIZAÇÃO"),"SIM","NÃO") -> NÃO
A57: 53 | B57: JD. PANTANAL | C57: NOVO HORIZONTE | D57: 1 | E57: -- | F57: 001/0013/A | G57: OCUPADO | H57: RESIDENCIAL | I57: PROPRIETÁRIO RESIDENTE | J57: SIVALDO MENEZES DOS SANTOS | K57: 39.159.374-2 | L57: 341.349.258-60 | M57: CADASTRADO | N57: AUXÍLIO ALUGUEL UH | O57: 46065 | P57: 6014.2025/0007513-3 | Q57: 46072 | R57: 46072 | S57: 46080 | T57: 46083 | U57: OK | V57: OK | W57: 46055 | X57: 46091 | AA57: SIVALDO MENEZES DOS SANTOS | AB57: 39.159.374-2 | AC57: 341.349.258-60 | AD57: PROPRIETÁRIO RESIDENTE | AE57: CADASTRADO | AF57: N.A | AG57: N.A | AH57: UH | AI57: 6014.2025/0007373-4 | AK57: 46064 | AL57: 46064 | AM57: 46064 | AN57: 46064 | AO57: 46064 | AP57: 46064 | AR57: =IF(AQ57="SIM","AGUARDANDO CORREÇÃO",IF(AP57<>"","FINALIZADO",IF(AO57<>"","AGUARDANDO ENVIO DTS",IF(AN57<>"","AGUARDANDO ASSINATURA GAB",IF(AM57<>"","AGUARDANDO ASSINATURA CTS",IF(AL57<>"","AGUARDANDO ENVIO ASSINATURA CTS",IF(AK57<>"","AGUARDANDO CONFERÊNCIA",""))))))) -> FINALIZADO | BH57: =IFERROR(IF(BD57-KI57=0,"",BD57-AK57),"") | BI57: =IF(AND(AH57<>"SIM",AH57="UH"),"AA","INDENIZAÇÃO") -> AA | BJ57: =IF(AND(BD57<>"AGUARDANDO",BD57<>"",N57="AUXÍLIO ALUGUEL ATÉ INDENIZAÇÃO"),"SIM","NÃO") -> NÃO
A58: 54 | B58: JD. PANTANAL | C58: TERRA PROMETIDA | D58: 1 | E58: -- | F58: 001/0014/A | G58: OCUPADO | H58: RESIDENCIAL | I58: PROPRIETÁRIO RESIDENTE | J58: ANA PAULA MOREIRA SANTOS | K58: 37.008.771-9 | L58: 328.002.508-79 | M58: CADASTRADO | N58: AUXÍLIO ALUGUEL UH | O58: 45986 | P58: 6014.2025/0007513-3 | Q58: 45985 | R58: 45986 | S58: 45987 | T58: 45992 | U58: OK | V58: OK | W58: 45999 | X58: 46000 | Y58: 46017 | AA58: ANA PAULA MOREIRA SANTOS | AB58: 37.008.771-9 | AC58: 328.002.508-79 | AD58: PROPRIETÁRIO RESIDENTE | AE58: CADASTRADO | AF58: N.A | AG58: N.A | AH58: UH | AI58: 6014.2025/0007373-4 | AK58: 45979 | AL58: 45979 | AM58: 45979 | AN58: 45979 | AO58: 45979 | AP58: 45979 | AR58: =IF(AQ58="SIM","AGUARDANDO CORREÇÃO",IF(AP58<>"","FINALIZADO",IF(AO58<>"","AGUARDANDO ENVIO DTS",IF(AN58<>"","AGUARDANDO ASSINATURA GAB",IF(AM58<>"","AGUARDANDO ASSINATURA CTS",IF(AL58<>"","AGUARDANDO ENVIO ASSINATURA CTS",IF(AK58<>"","AGUARDANDO CONFERÊNCIA",""))))))) -> FINALIZADO | BE58: 46017 | BF58: DEMOLIDO | BH58: =IFERROR(IF(BD58-KI58=0,"",BD58-AK58),"") | BI58: =IF(AND(AH58<>"SIM",AH58="UH"),"AA","INDENIZAÇÃO") -> AA | BJ58: =IF(AND(BD58<>"AGUARDANDO",BD58<>"",N58="AUXÍLIO ALUGUEL ATÉ INDENIZAÇÃO"),"SIM","NÃO") -> NÃO
A59: 55 | B59: JD. PANTANAL | C59: NOVO HORIZONTE | D59: 1 | E59: -- | F59: 001/0014/A | G59: OCUPADO | H59: RESIDENCIAL | I59: PROPRIETÁRIO RESIDENTE | J59: EVERTON FARIAS GUALBERTO | K59: 42.747.437-1 | L59: 426.126.298-31 | M59: CADASTRADO | N59: AUXÍLIO ALUGUEL UH | O59: 46044 | P59: 6014.2025/0007513-3 | Q59: 46043 | R59: 46044 | S59: 46045 | T59: 46155 | U59: OK | V59: OK | W59: 46055 | X59: 46078 | AA59: EVERTON FARIAS GUALBERTO | AB59: 42.747.437-1 | AC59: 426.126.298-31 | AD59: PROPRIETÁRIO RESIDENTE | AE59: CADASTRADO | AF59: N.A | AG59: N.A | AH59: UH | AI59: 6014.2025/0007373-4 | AK59: 46037 | AL59: 46037 | AM59: 46037 | AN59: 46037 | AO59: 46037 | AP59: 46037 | AR59: =IF(AQ59="SIM","AGUARDANDO CORREÇÃO",IF(AP59<>"","FINALIZADO",IF(AO59<>"","AGUARDANDO ENVIO DTS",IF(AN59<>"","AGUARDANDO ASSINATURA GAB",IF(AM59<>"","AGUARDANDO ASSINATURA CTS",IF(AL59<>"","AGUARDANDO ENVIO ASSINATURA CTS",IF(AK59<>"","AGUARDANDO CONFERÊNCIA",""))))))) -> FINALIZADO | BH59: =IFERROR(IF(BD59-KI59=0,"",BD59-AK59),"") | BI59: =IF(AND(AH59<>"SIM",AH59="UH"),"AA","INDENIZAÇÃO") -> AA | BJ59: =IF(AND(BD59<>"AGUARDANDO",BD59<>"",N59="AUXÍLIO ALUGUEL ATÉ INDENIZAÇÃO"),"SIM","NÃO") -> NÃO
A60: 56 | B60: JD. PANTANAL | C60: TERRA PROMETIDA | D60: 1 | E60: -- | F60: 001/0015/A | G60: OCUPADO | H60: RESIDENCIAL | I60: PROPRIETÁRIO RESIDENTE | J60: CLEUVOCIR PACHECO FERREIRA | K60: 26.726.183-4 | L60: 652.847.201-72 | M60: CADASTRADO | N60: INDENIZAÇÃO | O60: N.A | P60: N.A | Q60: N.A | R60: N.A | S60: N.A | T60: N.A | U60: N.A | V60: N.A | W60: N.A | X60: N.A | AA60: CLEUVOCIR PACHECO FERREIRA | AC60: 652.847.201-72 | AD60: PROPRIETÁRIO RESIDENTE | AE60: CADASTRADO | AF60: 28123.49 | AG60: =AF60+30000 -> 58123.49 | AH60: SIM | AI60: 6014.2025/0007373-4 | AJ60: 146037757 | AK60: 45979 | AL60: 45979 | AM60: 45979 | AN60: 45979 | AO60: 45979 | AP60: 45979 | AR60: =IF(AQ60="SIM","AGUARDANDO CORREÇÃO",IF(AP60<>"","FINALIZADO",IF(AO60<>"","AGUARDANDO ENVIO DTS",IF(AN60<>"","AGUARDANDO ASSINATURA GAB",IF(AM60<>"","AGUARDANDO ASSINATURA CTS",IF(AL60<>"","AGUARDANDO ENVIO ASSINATURA CTS",IF(AK60<>"","AGUARDANDO CONFERÊNCIA",""))))))) -> FINALIZADO | AS60: SEM PENDÊNCIA | AU60: 6014.2025/0008103-6 | AV60: FINALIZADO | AW60: FINALIZADO | AX60: FINALIZADO | AY60: FINALIZADO | AZ60: 46008 | BA60: FINALIZADO | BB60: FINALIZADO | BC60: 46014 | BD60: 46014 | BE60: 46017 | BF60: DEMOLIDO | BG60: FINALIZADO | BH60: =IFERROR(IF(BD60-KI60=0,"",BD60-AK60),"") -> 35 | BI60: =IF(AND(AH60<>"SIM",AH60="UH"),"AA","INDENIZAÇÃO") -> INDENIZAÇÃO | BJ60: =IF(AND(BD60<>"AGUARDANDO",BD60<>"",N60="AUXÍLIO ALUGUEL ATÉ INDENIZAÇÃO"),"SIM","NÃO") -> NÃO | BK60: N/A | BL60: N/A | BM60: N/A | BN60: FINALIZADO | BO60: FINALIZADO | BP60: 46128 | BQ60: FINALIZADO | BR60: AGUARDANDO
A61: 57 | B61: JD. PANTANAL | C61: NOVO HORIZONTE | D61: 1 | E61: -- | F61: 001/0015/A | G61: OCUPADO | H61: RESIDENCIAL | I61: PROPRIETÁRIO RESIDENTE | J61: JOSÉ ROBERTO PEREIRA DE LUCENA | K61: 38.147.098-2 | L61: 692.493.774-87 | M61: CADASTRADO | N61: AUXÍLIO ALUGUEL UH | O61: 46058 | P61: 6014.2025/0007513-3 | Q61: 46058 | R61: 46058 | S61: 46059 | T61: 46063 | U61: OK | V61: OK | W61: 46073 | X61: 46062 | AA61: JOSÉ ROBERTO PEREIRA DE LUCENA | AB61: 38.147.098-2 | AC61: 692.493.774-87 | AD61: PROPRIETÁRIO RESIDENTE | AE61: CADASTRADO | AF61: N.A | AG61: N.A | AH61: UH | AI61: 6014.2025/0007373-4 | AK61: 46064 | AL61: 46064 | AM61: 46064 | AN61: 46064 | AO61: 46064 | AP61: 46064 | AR61: =IF(AQ61="SIM","AGUARDANDO CORREÇÃO",IF(AP61<>"","FINALIZADO",IF(AO61<>"","AGUARDANDO ENVIO DTS",IF(AN61<>"","AGUARDANDO ASSINATURA GAB",IF(AM61<>"","AGUARDANDO ASSINATURA CTS",IF(AL61<>"","AGUARDANDO ENVIO ASSINATURA CTS",IF(AK61<>"","AGUARDANDO CONFERÊNCIA",""))))))) -> FINALIZADO | BH61: =IFERROR(IF(BD61-KI61=0,"",BD61-AK61),"") | BI61: =IF(AND(AH61<>"SIM",AH61="UH"),"AA","INDENIZAÇÃO") -> AA | BJ61: =IF(AND(BD61<>"AGUARDANDO",BD61<>"",N61="AUXÍLIO ALUGUEL ATÉ INDENIZAÇÃO"),"SIM","NÃO") -> NÃO
A62: 58 | B62: JD. PANTANAL | C62: TERRA PROMETIDA | D62: 1 | E62: -- | F62: 001/0016/A | G62: OCUPADO | H62: RESIDENCIAL | I62: PROPRIETÁRIO RESIDENTE | J62: EDINALDO PEREIRA ROCHA | K62: 59.932.769-8 | L62: 497.061.105-00 | M62: CADASTRADO | N62: AUXÍLIO ALUGUEL UH | O62: 45986 | P62: 6014.2025/0007513-3 | Q62: 45985 | R62: 45986 | S62: 45987 | T62: 45992 | U62: OK | V62: OK | W62: 45999 | X62: 46115 | Y62: 46017 | AA62: EDINALDO PEREIRA ROCHA | AB62: 59.932.769-8 | AC62: 497.061.105-00 | AD62: PROPRIETÁRIO RESIDENTE | AE62: CADASTRADO | AF62: N.A | AG62: N.A | AH62: UH | AI62: 6014.2025/0007373-4 | AK62: 45979 | AL62: 45979 | AM62: 45979 | AN62: 45979 | AO62: 45979 | AP62: 45979 | AR62: =IF(AQ62="SIM","AGUARDANDO CORREÇÃO",IF(AP62<>"","FINALIZADO",IF(AO62<>"","AGUARDANDO ENVIO DTS",IF(AN62<>"","AGUARDANDO ASSINATURA GAB",IF(AM62<>"","AGUARDANDO ASSINATURA CTS",IF(AL62<>"","AGUARDANDO ENVIO ASSINATURA CTS",IF(AK62<>"","AGUARDANDO CONFERÊNCIA",""))))))) -> FINALIZADO | BE62: 46017 | BF62: DEMOLIDO | BH62: =IFERROR(IF(BD62-KI62=0,"",BD62-AK62),"") | BI62: =IF(AND(AH62<>"SIM",AH62="UH"),"AA","INDENIZAÇÃO") -> AA | BJ62: =IF(AND(BD62<>"AGUARDANDO",BD62<>"",N62="AUXÍLIO ALUGUEL ATÉ INDENIZAÇÃO"),"SIM","NÃO") -> NÃO
A63: 59 | B63: JD. PANTANAL | C63: NOVO HORIZONTE | D63: 1 | E63: -- | F63: 001/0016/A | G63: OCUPADO | H63: MISTO | I63: PROPRIETÁRIO RESIDENTE | J63: JOÃO ROBERTO RIBAS PAIVA | K63: 34.083.633-7 | L63: 284.624.008-64 | M63: CADASTRADO | N63: AUXÍLIO ALUGUEL UH | O63: 46044 | P63: 6014.2025/0007513-3 | Q63: 46043 | R63: 46044 | S63: 46045 | T63: 46155 | U63: OK | V63: OK | W63: 46055 | X63: 46062 | AA63: JOÃO ROBERTO RIBAS PAIVA | AB63: 34.083.633-7 | AC63: 284.624.008-64 | AD63: PROPRIETÁRIO RESIDENTE | AE63: CADASTRADO | AF63: N.A | AG63: N.A | AH63: UH | AI63: 6014.2025/0007373-4 | AK63: 46037 | AL63: 46037 | AM63: 46037 | AN63: 46037 | AO63: 46037 | AP63: 46037 | AR63: =IF(AQ63="SIM","AGUARDANDO CORREÇÃO",IF(AP63<>"","FINALIZADO",IF(AO63<>"","AGUARDANDO ENVIO DTS",IF(AN63<>"","AGUARDANDO ASSINATURA GAB",IF(AM63<>"","AGUARDANDO ASSINATURA CTS",IF(AL63<>"","AGUARDANDO ENVIO ASSINATURA CTS",IF(AK63<>"","AGUARDANDO CONFERÊNCIA",""))))))) -> FINALIZADO | BH63: =IFERROR(IF(BD63-KI63=0,"",BD63-AK63),"") | BI63: =IF(AND(AH63<>"SIM",AH63="UH"),"AA","INDENIZAÇÃO") -> AA | BJ63: =IF(AND(BD63<>"AGUARDANDO",BD63<>"",N63="AUXÍLIO ALUGUEL ATÉ INDENIZAÇÃO"),"SIM","NÃO") -> NÃO
A64: 60 | B64: JD. PANTANAL | C64: TERRA PROMETIDA | D64: 1 | E64: -- | F64: 001/0017/A | G64: OCUPADO | H64: RESIDENCIAL | I64: PROPRIETÁRIO RESIDENTE | J64: CLAYTON AUGUSTO DOS SANTOS | K64: 63.361.783-0 | L64: 533.128.298-95 | M64: CADASTRADO | N64: AUXÍLIO ALUGUEL UH | O64: 45986 | P64: 6014.2025/0007513-3 | Q64: 45985 | R64: 45986 | S64: 45987 | T64: 45992 | U64: OK | V64: OK | W64: 45999 | X64: 46000 | Y64: 46017 | AA64: CLAYTON AUGUSTO DOS SANTOS | AB64: 63.361.783-0 | AC64: 533.128.298-95 | AD64: PROPRIETÁRIO RESIDENTE | AE64: CADASTRADO | AF64: N.A | AG64: N.A | AH64: UH | AI64: 6014.2025/0007373-4 | AK64: 45979 | AL64: 45979 | AM64: 45979 | AN64: 45979 | AO64: 45979 | AP64: 45979 | AR64: =IF(AQ64="SIM","AGUARDANDO CORREÇÃO",IF(AP64<>"","FINALIZADO",IF(AO64<>"","AGUARDANDO ENVIO DTS",IF(AN64<>"","AGUARDANDO ASSINATURA GAB",IF(AM64<>"","AGUARDANDO ASSINATURA CTS",IF(AL64<>"","AGUARDANDO ENVIO ASSINATURA CTS",IF(AK64<>"","AGUARDANDO CONFERÊNCIA",""))))))) -> FINALIZADO | BE64: 46017 | BF64: DEMOLIDO | BH64: =IFERROR(IF(BD64-KI64=0,"",BD64-AK64),"") | BI64: =IF(AND(AH64<>"SIM",AH64="UH"),"AA","INDENIZAÇÃO") -> AA | BJ64: =IF(AND(BD64<>"AGUARDANDO",BD64<>"",N64="AUXÍLIO ALUGUEL ATÉ INDENIZAÇÃO"),"SIM","NÃO") -> NÃO
A65: 61 | B65: JD. PANTANAL | C65: NOVO HORIZONTE | D65: 1 | E65: -- | F65: 001/0017/A | G65: CONSTRUÇÃO | H65: CONSTRUÇÃO | I65: PROPRIETÁRIO NÃO RESIDENTE | J65: ROBERTO FRANCISCO NETO | K65: -- | L65: 034.705.005-09 | M65: CADASTRADO | N65: INDENIZAÇÃO | O65: N.A | P65: N.A | Q65: N.A | R65: N.A | S65: N.A | T65: N.A | U65: N.A | V65: N.A | W65: N.A | X65: N.A | AA65: ROBERTO FRANCISCO NETO | AB65: -- | AC65: 034.705.005-09 | AD65: PROPRIETÁRIO NÃO RESIDENTE | AE65: CADASTRADO | AF65: 2975.66 | AG65: 2975.66 | AH65: SIM | AI65: 6014.2025/0007373-4 | AJ65: 151538567 | AK65: 46086 | AL65: 46086 | AM65: 46086 | AN65: 46086 | AO65: 46086 | AP65: 46086 | AR65: =IF(AQ65="SIM","AGUARDANDO CORREÇÃO",IF(AP65<>"","FINALIZADO",IF(AO65<>"","AGUARDANDO ENVIO DTS",IF(AN65<>"","AGUARDANDO ASSINATURA GAB",IF(AM65<>"","AGUARDANDO ASSINATURA CTS",IF(AL65<>"","AGUARDANDO ENVIO ASSINATURA CTS",IF(AK65<>"","AGUARDANDO CONFERÊNCIA",""))))))) -> FINALIZADO | AS65: SEM PENDÊNCIA | AU65: 6014.2026/0002706-8 | AV65: FINALIZADO | AW65: FINALIZADO | AX65: FINALIZADO | AY65: FINALIZADO | AZ65: 46153 | BA65: FINALIZADO | BB65: FINALIZADO | BC65: 46157 | BD65: 46157 | BE65: AGUARDANDO | BF65: LIBERADO DEMOLIÇÃO | BG65: FINALIZADO | BH65: =IFERROR(IF(BD65-KI65=0,"",BD65-AK65),"") -> 71 | BI65: =IF(AND(AH65<>"SIM",AH65="UH"),"AA","INDENIZAÇÃO") -> INDENIZAÇÃO | BJ65: =IF(AND(BD65<>"AGUARDANDO",BD65<>"",N65="AUXÍLIO ALUGUEL ATÉ INDENIZAÇÃO"),"SIM","NÃO") -> NÃO | BK65: N/A | BL65: N/A | BM65: N/A | BN65: FINALIZADO | BO65: FINALIZADO | BP65: 46195 | BQ65: FINALIZADO | BR65: AGUARDANDO
A66: 62 | B66: JD. PANTANAL | C66: TERRA PROMETIDA | D66: 1 | E66: -- | F66: 001/0018/A | G66: OCUPADO | H66: RESIDENCIAL | I66: PROPRIETÁRIO RESIDENTE | J66: CRISLANE DE SOUZA BOMFIM | K66: 62.008.592-7 | L66: 581.689.438-21 | M66: CADASTRADO | N66: AUXÍLIO ALUGUEL UH | O66: 46002 | P66: 6014.2025/0007513-3 | Q66: 45999 | R66: 46006 | S66: 46006 | T66: 46009 | U66: OK | V66: OK | W66: 46014 | X66: 46000 | Y66: 46017 | AA66: CRISLANE DE SOUZA BOMFIM | AB66: 62.008.592-7 | AC66: 581.689.438-21 | AD66: PROPRIETÁRIO RESIDENTE | AE66: CADASTRADO | AF66: N.A | AG66: N.A | AH66: UH | AI66: 6014.2025/0007373-4 | AK66: 45979 | AL66: 45979 | AM66: 45979 | AN66: 45979 | AO66: 45979 | AP66: 45979 | AR66: =IF(AQ66="SIM","AGUARDANDO CORREÇÃO",IF(AP66<>"","FINALIZADO",IF(AO66<>"","AGUARDANDO ENVIO DTS",IF(AN66<>"","AGUARDANDO ASSINATURA GAB",IF(AM66<>"","AGUARDANDO ASSINATURA CTS",IF(AL66<>"","AGUARDANDO ENVIO ASSINATURA CTS",IF(AK66<>"","AGUARDANDO CONFERÊNCIA",""))))))) -> FINALIZADO | BE66: 46017 | BF66: DEMOLIDO | BH66: =IFERROR(IF(BD66-KI66=0,"",BD66-AK66),"") | BI66: =IF(AND(AH66<>"SIM",AH66="UH"),"AA","INDENIZAÇÃO") -> AA | BJ66: =IF(AND(BD66<>"AGUARDANDO",BD66<>"",N66="AUXÍLIO ALUGUEL ATÉ INDENIZAÇÃO"),"SIM","NÃO") -> NÃO
A67: 63 | B67: JD. PANTANAL | C67: TERRA PROMETIDA | D67: 1 | E67: -- | F67: 001/0019/A | G67: OCUPADO | H67: RESIDENCIAL | I67: PROPRIETÁRIO RESIDENTE | J67: KETELLYM VITORIA OLIVEIRA SILVA | K67: 58.275.733.2 | L67: 025.339.388-40 | M67: CADASTRADO | N67: AUXÍLIO ALUGUEL UH | O67: 45986 | P67: 6014.2025/0007513-3 | Q67: 45985 | R67: 45986 | S67: 45987 | T67: 45992 | U67: OK | V67: OK | W67: 45999 | X67: 46000 | Y67: 46017 | AA67: KETELLYM VITORIA OLIVEIRA SILVA | AB67: 58.275.733.2 | AC67: 025.339.388-40 | AD67: PROPRIETÁRIO RESIDENTE | AE67: CADASTRADO | AF67: N.A | AG67: N.A | AH67: UH | AI67: 6014.2025/0007373-4 | AK67: 45979 | AL67: 45979 | AM67: 45979 | AN67: 45979 | AO67: 45979 | AP67: 45979 | AR67: =IF(AQ67="SIM","AGUARDANDO CORREÇÃO",IF(AP67<>"","FINALIZADO",IF(AO67<>"","AGUARDANDO ENVIO DTS",IF(AN67<>"","AGUARDANDO ASSINATURA GAB",IF(AM67<>"","AGUARDANDO ASSINATURA CTS",IF(AL67<>"","AGUARDANDO ENVIO ASSINATURA CTS",IF(AK67<>"","AGUARDANDO CONFERÊNCIA",""))))))) -> FINALIZADO | BE67: 46017 | BF67: DEMOLIDO | BH67: =IFERROR(IF(BD67-KI67=0,"",BD67-AK67),"") | BI67: =IF(AND(AH67<>"SIM",AH67="UH"),"AA","INDENIZAÇÃO") -> AA | BJ67: =IF(AND(BD67<>"AGUARDANDO",BD67<>"",N67="AUXÍLIO ALUGUEL ATÉ INDENIZAÇÃO"),"SIM","NÃO") -> NÃO
A68: 64 | B68: JD. PANTANAL | C68: TERRA PROMETIDA | D68: 1 | E68: -- | F68: 001/0020/A | G68: OCUPADO | H68: RESIDENCIAL | I68: PROPRIETÁRIO RESIDENTE | J68: GABRIELE LOPES DE SOUZA JORGE | K68: 59.420.536-0 | L68: 582.161.348-51 | M68: CADASTRADO | N68: AUXÍLIO ALUGUEL UH | O68: 45986 | P68: 6014.2025/0007513-3 | Q68: 45985 | R68: 45986 | S68: 45987 | T68: 45992 | U68: OK | V68: OK | W68: 45999 | X68: 46000 | Y68: 46017 | AA68: GABRIELE LOPES DE SOUZA JORGE | AB68: 59.420.536-0 | AC68: 582.161.348-51 | AD68: PROPRIETÁRIO RESIDENTE | AE68: CADASTRADO | AF68: N.A | AG68: N.A | AH68: UH | AI68: 6014.2025/0007373-4 | AK68: 45979 | AL68: 45979 | AM68: 45979 | AN68: 45979 | AO68: 45979 | AP68: 45979 | AR68: =IF(AQ68="SIM","AGUARDANDO CORREÇÃO",IF(AP68<>"","FINALIZADO",IF(AO68<>"","AGUARDANDO ENVIO DTS",IF(AN68<>"","AGUARDANDO ASSINATURA GAB",IF(AM68<>"","AGUARDANDO ASSINATURA CTS",IF(AL68<>"","AGUARDANDO ENVIO ASSINATURA CTS",IF(AK68<>"","AGUARDANDO CONFERÊNCIA",""))))))) -> FINALIZADO | BE68: 46017 | BF68: DEMOLIDO | BH68: =IFERROR(IF(BD68-KI68=0,"",BD68-AK68),"") | BI68: =IF(AND(AH68<>"SIM",AH68="UH"),"AA","INDENIZAÇÃO") -> AA | BJ68: =IF(AND(BD68<>"AGUARDANDO",BD68<>"",N68="AUXÍLIO ALUGUEL ATÉ INDENIZAÇÃO"),"SIM","NÃO") -> NÃO
A69: 65 | B69: JD. PANTANAL | C69: TERRA PROMETIDA | D69: 1 | E69: -- | F69: 001/0021/A | G69: OCUPADO | H69: RESIDENCIAL | I69: PROPRIETÁRIO RESIDENTE | J69: MARIA APARECIDA DOS SANTOS | K69: 34.567.287-2 | L69: 009.942.777-09 | M69: CADASTRADO | N69: AUXÍLIO ALUGUEL UH | O69: 45986 | P69: 6014.2025/0007513-3 | Q69: 45985 | R69: 45986 | S69: 45987 | T69: 45992 | U69: OK | V69: OK | W69: 45999 | X69: 46000 | Y69: 46017 | AA69: MARIA APARECIDA DOS SANTOS | AB69: 34.567.287-2 | AC69: 009.942.777-09 | AD69: PROPRIETÁRIO RESIDENTE | AE69: CADASTRADO | AF69: N.A | AG69: N.A | AH69: UH | AI69: 6014.2025/0007373-4 | AK69: 45979 | AL69: 45979 | AM69: 45979 | AN69: 45979 | AO69: 45979 | AP69: 45979 | AR69: =IF(AQ69="SIM","AGUARDANDO CORREÇÃO",IF(AP69<>"","FINALIZADO",IF(AO69<>"","AGUARDANDO ENVIO DTS",IF(AN69<>"","AGUARDANDO ASSINATURA GAB",IF(AM69<>"","AGUARDANDO ASSINATURA CTS",IF(AL69<>"","AGUARDANDO ENVIO ASSINATURA CTS",IF(AK69<>"","AGUARDANDO CONFERÊNCIA",""))))))) -> FINALIZADO | BE69: 46017 | BF69: DEMOLIDO | BH69: =IFERROR(IF(BD69-KI69=0,"",BD69-AK69),"") | BI69: =IF(AND(AH69<>"SIM",AH69="UH"),"AA","INDENIZAÇÃO") -> AA | BJ69: =IF(AND(BD69<>"AGUARDANDO",BD69<>"",N69="AUXÍLIO ALUGUEL ATÉ INDENIZAÇÃO"),"SIM","NÃO") -> NÃO
A70: 66 | B70: JD. PANTANAL | C70: TERRA PROMETIDA | D70: 1 | E70: -- | F70: 001/0022/A | G70: OCUPADO | H70: RESIDENCIAL | I70: PROPRIETÁRIO RESIDENTE | J70: JULIANA CAMILA DOS SANTOS | K70: 47.871.516-X | L70: 474.652.078-00 | M70: CADASTRADO | N70: INDENIZAÇÃO | O70: N.A | P70: N.A | Q70: N.A | R70: N.A | S70: N.A | T70: N.A | U70: N.A | V70: N.A | W70: N.A | X70: N.A | AA70: JULIANA CAMILA DOS SANTOS | AB70: 47.871.516-X | AC70: 474.652.078-00 | AD70: PROPRIETÁRIO RESIDENTE | AE70: CADASTRADO | AF70: 22200.14 | AG70: =AF70+30000 -> 52200.14 | AH70: SIM | AI70: 6014.2025/0007373-4 | AJ70: 146037864 | AK70: 46038 | AL70: 46038 | AM70: 46038 | AN70: 46038 | AO70: 46038 | AP70: 46038 | AR70: =IF(AQ70="SIM","AGUARDANDO CORREÇÃO",IF(AP70<>"","FINALIZADO",IF(AO70<>"","AGUARDANDO ENVIO DTS",IF(AN70<>"","AGUARDANDO ASSINATURA GAB",IF(AM70<>"","AGUARDANDO ASSINATURA CTS",IF(AL70<>"","AGUARDANDO ENVIO ASSINATURA CTS",IF(AK70<>"","AGUARDANDO CONFERÊNCIA",""))))))) -> FINALIZADO | AS70: SEM PENDÊNCIA | AU70: 6014.2026/0000446-7 | AV70: FINALIZADO | AW70: FINALIZADO | AX70: FINALIZADO | AY70: FINALIZADO | AZ70: 46062 | BA70: FINALIZADO | BB70: FINALIZADO | BC70: 46066 | BD70: 46066 | BE70: 46017 | BF70: DEMOLIDO | BG70: FINALIZADO | BH70: =IFERROR(IF(BD70-KI70=0,"",BD70-AK70),"") -> 28 | BI70: =IF(AND(AH70<>"SIM",AH70="UH"),"AA","INDENIZAÇÃO") -> INDENIZAÇÃO | BJ70: =IF(AND(BD70<>"AGUARDANDO",BD70<>"",N70="AUXÍLIO ALUGUEL ATÉ INDENIZAÇÃO"),"SIM","NÃO") -> NÃO | BK70: N/A | BL70: N/A | BM70: N/A | BN70: FINALIZADO | BO70: FINALIZADO | BP70: 46128 | BQ70: FINALIZADO | BR70: AGUARDANDO
A71: 67 | B71: JD. PANTANAL | C71: TERRA PROMETIDA | D71: 1 | E71: _ | F71: 001/0023/A | G71: OCUPADO | H71: RESIDENCIAL | I71: PROPRIETÁRIO RESIDENTE | J71: NEUSA RIGHI PEREIRA DA SILVA | K71: 22.709.733.6 | L71: 359.204.528-89 | M71: CADASTRADO | N71: AUXÍLIO ALUGUEL UH | O71: 45986 | P71: 6014.2025/0007513-3 | Q71: 45985 | R71: 45986 | S71: 45987 | T71: 45992 | U71: OK | V71: OK | W71: 45999 | X71: 46000 | Y71: 46017 | AA71: NEUSA RIGHI PEREIRA DA SILVA | AB71: 22.709.733.6 | AC71: 359.204.528-89 | AD71: PROPRIETÁRIO RESIDENTE | AE71: CADASTRADO | AF71: N.A | AG71: N.A | AH71: UH | AI71: 6014.2025/0007373-4 | AK71: 45979 | AL71: 45979 | AM71: 45979 | AN71: 45979 | AO71: 45979 | AP71: 45979 | AR71: =IF(AQ71="SIM","AGUARDANDO CORREÇÃO",IF(AP71<>"","FINALIZADO",IF(AO71<>"","AGUARDANDO ENVIO DTS",IF(AN71<>"","AGUARDANDO ASSINATURA GAB",IF(AM71<>"","AGUARDANDO ASSINATURA CTS",IF(AL71<>"","AGUARDANDO ENVIO ASSINATURA CTS",IF(AK71<>"","AGUARDANDO CONFERÊNCIA",""))))))) -> FINALIZADO | BE71: 46017 | BF71: DEMOLIDO | BH71: =IFERROR(IF(BD71-KI71=0,"",BD71-AK71),"") | BI71: =IF(AND(AH71<>"SIM",AH71="UH"),"AA","INDENIZAÇÃO") -> AA | BJ71: =IF(AND(BD71<>"AGUARDANDO",BD71<>"",N71="AUXÍLIO ALUGUEL ATÉ INDENIZAÇÃO"),"SIM","NÃO") -> NÃO
A72: 68 | B72: JD. PANTANAL | C72: TERRA PROMETIDA | D72: 1 | E72: _ | F72: 001/0024/A | G72: OCUPADO | H72: RESIDENCIAL | I72: PROPRIETÁRIO RESIDENTE | J72: ALEXANDRE MARIN FERREIRA | K72: 43.752.484-X | L72: 336.487.618-54 | M72: CADASTRADO | N72: AUXÍLIO ALUGUEL UH | O72: 46002 | P72: 6014.2025/0007513-3 | Q72: 45999 | R72: 46006 | S72: 46006 | T72: 46009 | U72: OK | V72: OK | W72: 46014 | X72: 46017 | Y72: 46017 | AA72: ALEXANDRE MARIN FERREIRA | AB72: 43.752.484-X | AC72: 336.487.618-54 | AD72: PROPRIETÁRIO RESIDENTE | AE72: CADASTRADO | AF72: N.A | AG72: N.A | AH72: UH | AI72: 6014.2025/0007373-4 | AK72: 45996 | AL72: 45996 | AM72: 45996 | AN72: 45996 | AO72: 45996 | AP72: 45996 | AR72: =IF(AQ72="SIM","AGUARDANDO CORREÇÃO",IF(AP72<>"","FINALIZADO",IF(AO72<>"","AGUARDANDO ENVIO DTS",IF(AN72<>"","AGUARDANDO ASSINATURA GAB",IF(AM72<>"","AGUARDANDO ASSINATURA CTS",IF(AL72<>"","AGUARDANDO ENVIO ASSINATURA CTS",IF(AK72<>"","AGUARDANDO CONFERÊNCIA",""))))))) -> FINALIZADO | BE72: 46017 | BF72: DEMOLIDO | BH72: =IFERROR(IF(BD72-KI72=0,"",BD72-AK72),"") | BI72: =IF(AND(AH72<>"SIM",AH72="UH"),"AA","INDENIZAÇÃO") -> AA | BJ72: =IF(AND(BD72<>"AGUARDANDO",BD72<>"",N72="AUXÍLIO ALUGUEL ATÉ INDENIZAÇÃO"),"SIM","NÃO") -> NÃO
A73: 69 | B73: JD. PANTANAL | C73: TERRA PROMETIDA | D73: 1 | E73: -- | F73: 001/0025/A | G73: OCUPADO | H73: RESIDENCIAL | I73: PROPRIETÁRIO RESIDENTE | J73: JUCIENE MARIA DAS DORES | K73: 53.185.129-1 | L73: 008.996.255-92 | M73: CADASTRADO | N73: AUXÍLIO ALUGUEL UH | O73: 45986 | P73: 6014.2025/0007513-3 | Q73: 45985 | R73: 45986 | S73: 45987 | T73: 45992 | U73: OK | V73: OK | W73: 45999 | X73: 46001 | Y73: 46017 | AA73: JUCIENE MARIA DAS DORES | AB73: 53.185.129-1 | AC73: 008.996.255-92 | AD73: PROPRIETÁRIO RESIDENTE | AE73: CADASTRADO | AF73: N.A | AG73: N.A | AH73: UH | AI73: 6014.2025/0007373-4 | AK73: 45979 | AL73: 45979 | AM73: 45979 | AN73: 45979 | AO73: 45979 | AP73: 45979 | AR73: =IF(AQ73="SIM","AGUARDANDO CORREÇÃO",IF(AP73<>"","FINALIZADO",IF(AO73<>"","AGUARDANDO ENVIO DTS",IF(AN73<>"","AGUARDANDO ASSINATURA GAB",IF(AM73<>"","AGUARDANDO ASSINATURA CTS",IF(AL73<>"","AGUARDANDO ENVIO ASSINATURA CTS",IF(AK73<>"","AGUARDANDO CONFERÊNCIA",""))))))) -> FINALIZADO | BE73: 46017 | BF73: DEMOLIDO | BH73: =IFERROR(IF(BD73-KI73=0,"",BD73-AK73),"") | BI73: =IF(AND(AH73<>"SIM",AH73="UH"),"AA","INDENIZAÇÃO") -> AA | BJ73: =IF(AND(BD73<>"AGUARDANDO",BD73<>"",N73="AUXÍLIO ALUGUEL ATÉ INDENIZAÇÃO"),"SIM","NÃO") -> NÃO
A74: 70 | B74: JD. PANTANAL | C74: TERRA PROMETIDA | D74: 1 | E74: -- | F74: 001/0026/A | G74: OCUPADO | H74: RESIDENCIAL | I74: PROPRIETÁRIO RESIDENTE | J74: PAULO ROGERIO SANTOS DA SILVA | K74: 23.343.353-3 | L74: 193.477.028-03 | M74: CADASTRADO | N74: AUXÍLIO ALUGUEL UH | O74: 46002 | P74: 6014.2025/0007513-3 | Q74: 45999 | R74: 46006 | S74: 46006 | T74: 46009 | U74: OK | V74: OK | W74: 46014 | X74: 46017 | Y74: 46017 | AA74: PAULO ROGERIO SANTOS DA SILVA | AB74: 23.343.353-3 | AC74: 193.477.028-03 | AD74: PROPRIETÁRIO RESIDENTE | AE74: CADASTRADO | AF74: N.A | AG74: N.A | AH74: UH | AI74: 6014.2025/0007373-4 | AK74: 45995 | AL74: 45995 | AM74: 45995 | AN74: 45995 | AO74: 45995 | AP74: 45995 | AR74: =IF(AQ74="SIM","AGUARDANDO CORREÇÃO",IF(AP74<>"","FINALIZADO",IF(AO74<>"","AGUARDANDO ENVIO DTS",IF(AN74<>"","AGUARDANDO ASSINATURA GAB",IF(AM74<>"","AGUARDANDO ASSINATURA CTS",IF(AL74<>"","AGUARDANDO ENVIO ASSINATURA CTS",IF(AK74<>"","AGUARDANDO CONFERÊNCIA",""))))))) -> FINALIZADO | BE74: 46017 | BF74: DEMOLIDO | BH74: =IFERROR(IF(BD74-KI74=0,"",BD74-AK74),"") | BI74: =IF(AND(AH74<>"SIM",AH74="UH"),"AA","INDENIZAÇÃO") -> AA | BJ74: =IF(AND(BD74<>"AGUARDANDO",BD74<>"",N74="AUXÍLIO ALUGUEL ATÉ INDENIZAÇÃO"),"SIM","NÃO") -> NÃO
A75: 71 | B75: JD. PANTANAL | C75: TERRA PROMETIDA | D75: 1 | E75: -- | F75: 001/0026/B | G75: OCUPADO | H75: RESIDENCIAL | I75: PROPRIETÁRIO RESIDENTE | J75: CHEILA GARCIA PAES | K75: 25.996.273-9 | L75: 186.095.688-22 | M75: CADASTRADO | N75: AUXÍLIO ALUGUEL UH | O75: 46031 | P75: 6014.2025/0007513-3 | Q75: 46030 | R75: 46031 | S75: 46036 | T75: 46045 | U75: OK | V75: OK | W75: 46055 | X75: 46056 | Y75: 46017 | AA75: CHEILA GARCIA PAES | AB75: 25.996.273-9 | AC75: 186.095.688-22 | AD75: PROPRIETÁRIO RESIDENTE | AE75: CADASTRADO | AF75: N.A | AG75: N.A | AH75: UH | AI75: 6014.2025/0007373-4 | AK75: 45979 | AL75: 45979 | AM75: 45979 | AN75: 45979 | AO75: 45979 | AP75: 45979 | AR75: =IF(AQ75="SIM","AGUARDANDO CORREÇÃO",IF(AP75<>"","FINALIZADO",IF(AO75<>"","AGUARDANDO ENVIO DTS",IF(AN75<>"","AGUARDANDO ASSINATURA GAB",IF(AM75<>"","AGUARDANDO ASSINATURA CTS",IF(AL75<>"","AGUARDANDO ENVIO ASSINATURA CTS",IF(AK75<>"","AGUARDANDO CONFERÊNCIA",""))))))) -> FINALIZADO | BE75: 46017 | BF75: DEMOLIDO | BH75: =IFERROR(IF(BD75-KI75=0,"",BD75-AK75),"") | BI75: =IF(AND(AH75<>"SIM",AH75="UH"),"AA","INDENIZAÇÃO") -> AA | BJ75: =IF(AND(BD75<>"AGUARDANDO",BD75<>"",N75="AUXÍLIO ALUGUEL ATÉ INDENIZAÇÃO"),"SIM","NÃO") -> NÃO
A76: 72 | B76: JD. PANTANAL | C76: TERRA PROMETIDA | D76: 1 | E76: -- | F76: 001/0027/A | G76: OCUPADO | H76: RESIDENCIAL | I76: PROPRIETÁRIO RESIDENTE | J76: ESEQUIAS TAVARES RODRIGUES | K76: 21.394.107-7 | L76: 168.906.318-11 | M76: CADASTRADO | N76: INDENIZAÇÃO | O76: N.A | P76: N.A | Q76: N.A | R76: N.A | S76: N.A | T76: N.A | U76: N.A | V76: N.A | W76: N.A | X76: N.A | AA76: ESEQUIAS TAVARES RODRIGUES | AB76: 21.394.107-7 | AC76: 168.906.318-11 | AD76: PROPRIETÁRIO RESIDENTE | AE76: CADASTRADO | AF76: 29437.08 | AG76: =AF76+30000 -> 59437.08 | AH76: SIM | AI76: 6014.2025/0007373-4 | AJ76: 149594572 | AK76: 46045 | AL76: 46045 | AM76: 46045 | AN76: 46045 | AO76: 46045 | AP76: 46045 | AR76: =IF(AQ76="SIM","AGUARDANDO CORREÇÃO",IF(AP76<>"","FINALIZADO",IF(AO76<>"","AGUARDANDO ENVIO DTS",IF(AN76<>"","AGUARDANDO ASSINATURA GAB",IF(AM76<>"","AGUARDANDO ASSINATURA CTS",IF(AL76<>"","AGUARDANDO ENVIO ASSINATURA CTS",IF(AK76<>"","AGUARDANDO CONFERÊNCIA",""))))))) -> FINALIZADO | AS76: SEM PENDÊNCIA | AU76: 6014.2026/0000470-0 | AV76: FINALIZADO | AW76: FINALIZADO | AX76: FINALIZADO | AY76: FINALIZADO | AZ76: 46062 | BA76: FINALIZADO | BB76: FINALIZADO | BC76: 46066 | BD76: 46066 | BE76: 46017 | BF76: DEMOLIDO | BG76: FINALIZADO | BH76: =IFERROR(IF(BD76-KI76=0,"",BD76-AK76),"") -> 21 | BI76: =IF(AND(AH76<>"SIM",AH76="UH"),"AA","INDENIZAÇÃO") -> INDENIZAÇÃO | BJ76: =IF(AND(BD76<>"AGUARDANDO",BD76<>"",N76="AUXÍLIO ALUGUEL ATÉ INDENIZAÇÃO"),"SIM","NÃO") -> NÃO | BK76: N/A | BL76: N/A | BM76: N/A | BN76: FINALIZADO | BO76: FINALIZADO | BP76: 46128 | BQ76: FINALIZADO | BR76: AGUARDANDO
A77: 73 | B77: JD. PANTANAL | C77: TERRA PROMETIDA | D77: 1 | E77: -- | F77: 001/0028/A | G77: OCUPADO | H77: RESIDENCIAL | I77: PROPRIETÁRIO RESIDENTE | J77: LARISSA GLEICE DA SILVA SOUZA | K77: 55.006.204-X | L77: 140.812.244-80 | M77: CADASTRADO | N77: AUXÍLIO ALUGUEL UH | O77: 45986 | P77: 6014.2025/0007513-3 | Q77: 45985 | R77: 45986 | S77: 45987 | T77: 45992 | U77: OK | V77: OK | W77: 45999 | X77: 46000 | Y77: 46017 | AA77: LARISSA GLEICE DA SILVA SOUZA | AB77: 55.006.204-X | AC77: 140.812.244-80 | AD77: PROPRIETÁRIO RESIDENTE | AE77: CADASTRADO | AF77: N.A | AG77: N.A | AH77: UH | AI77: 6014.2025/0007373-4 | AK77: 45979 | AL77: 45979 | AM77: 45979 | AN77: 45979 | AO77: 45979 | AP77: 45979 | AR77: =IF(AQ77="SIM","AGUARDANDO CORREÇÃO",IF(AP77<>"","FINALIZADO",IF(AO77<>"","AGUARDANDO ENVIO DTS",IF(AN77<>"","AGUARDANDO ASSINATURA GAB",IF(AM77<>"","AGUARDANDO ASSINATURA CTS",IF(AL77<>"","AGUARDANDO ENVIO ASSINATURA CTS",IF(AK77<>"","AGUARDANDO CONFERÊNCIA",""))))))) -> FINALIZADO | BE77: 46017 | BF77: DEMOLIDO | BH77: =IFERROR(IF(BD77-KI77=0,"",BD77-AK77),"") | BI77: =IF(AND(AH77<>"SIM",AH77="UH"),"AA","INDENIZAÇÃO") -> AA | BJ77: =IF(AND(BD77<>"AGUARDANDO",BD77<>"",N77="AUXÍLIO ALUGUEL ATÉ INDENIZAÇÃO"),"SIM","NÃO") -> NÃO
A78: 74 | B78: JD. PANTANAL | C78: TERRA PROMETIDA | D78: 1 | E78: -- | F78: 001/0029/A | G78: OCUPADO | H78: RESIDENCIAL | I78: PROPRIETÁRIO RESIDENTE | J78: JOEL ALEXANDRE BORGES | K78: 56.076.297-5 | L78: 193.396.198-89 | M78: CADASTRADO | N78: AUXÍLIO ALUGUEL UH | O78: 45986 | P78: 6014.2025/0007513-3 | Q78: 45985 | R78: 45986 | S78: 45987 | T78: 45992 | U78: OK | V78: OK | W78: 45999 | X78: 46000 | Y78: 46017 | AA78: JOEL ALEXANDRE BORGES | AB78: 56.076.297-5 | AC78: 193.396.198-89 | AD78: PROPRIETÁRIO RESIDENTE | AE78: CADASTRADO | AF78: N.A | AG78: N.A | AH78: UH | AI78: 6014.2025/0007373-4 | AK78: 45979 | AL78: 45979 | AM78: 45979 | AN78: 45979 | AO78: 45979 | AP78: 45979 | AR78: =IF(AQ78="SIM","AGUARDANDO CORREÇÃO",IF(AP78<>"","FINALIZADO",IF(AO78<>"","AGUARDANDO ENVIO DTS",IF(AN78<>"","AGUARDANDO ASSINATURA GAB",IF(AM78<>"","AGUARDANDO ASSINATURA CTS",IF(AL78<>"","AGUARDANDO ENVIO ASSINATURA CTS",IF(AK78<>"","AGUARDANDO CONFERÊNCIA",""))))))) -> FINALIZADO | BE78: 46017 | BF78: DEMOLIDO | BH78: =IFERROR(IF(BD78-KI78=0,"",BD78-AK78),"") | BI78: =IF(AND(AH78<>"SIM",AH78="UH"),"AA","INDENIZAÇÃO") -> AA | BJ78: =IF(AND(BD78<>"AGUARDANDO",BD78<>"",N78="AUXÍLIO ALUGUEL ATÉ INDENIZAÇÃO"),"SIM","NÃO") -> NÃO
A79: 75 | B79: JD. PANTANAL | C79: TERRA PROMETIDA | D79: 1 | E79: -- | F79: 001/0030/A | G79: OCUPADO | H79: RESIDENCIAL | I79: PROPRIETÁRIO RESIDENTE | J79: CICERO LEONOR SERAFIM | K79: 36.662.648 | L79: 122.373.034-44 | M79: CADASTRADO | N79: AUXÍLIO ALUGUEL UH | O79: 46002 | P79: 6014.2025/0007513-3 | Q79: 45999 | R79: 46006 | S79: 46006 | T79: 46009 | U79: OK | V79: OK | W79: 46014 | X79: 46017 | Y79: 46017 | AA79: CICERO LEONOR SERAFIM | AB79: 36.662.648 | AC79: 122.373.034-44 | AD79: PROPRIETÁRIO RESIDENTE | AE79: CADASTRADO | AF79: N.A | AG79: N.A | AH79: UH | AI79: 6014.2025/0007373-4 | AK79: 45996 | AL79: 45996 | AM79: 45996 | AN79: 45996 | AO79: 45996 | AP79: 45996 | AR79: =IF(AQ79="SIM","AGUARDANDO CORREÇÃO",IF(AP79<>"","FINALIZADO",IF(AO79<>"","AGUARDANDO ENVIO DTS",IF(AN79<>"","AGUARDANDO ASSINATURA GAB",IF(AM79<>"","AGUARDANDO ASSINATURA CTS",IF(AL79<>"","AGUARDANDO ENVIO ASSINATURA CTS",IF(AK79<>"","AGUARDANDO CONFERÊNCIA",""))))))) -> FINALIZADO | BE79: 46017 | BF79: DEMOLIDO | BH79: =IFERROR(IF(BD79-KI79=0,"",BD79-AK79),"") | BI79: =IF(AND(AH79<>"SIM",AH79="UH"),"AA","INDENIZAÇÃO") -> AA | BJ79: =IF(AND(BD79<>"AGUARDANDO",BD79<>"",N79="AUXÍLIO ALUGUEL ATÉ INDENIZAÇÃO"),"SIM","NÃO") -> NÃO
A80: 76 | B80: JD. PANTANAL | C80: TERRA PROMETIDA | D80: 1 | E80: -- | F80: 001/0030/B | G80: OCUPADO | H80: RESIDENCIAL | I80: PROPRIETÁRIO RESIDENTE | J80: PATRICIA APARECIDA ALVES GRANZOTTI | K80: 69.378.106-3 | L80: 270.886.538-26 | M80: CADASTRADO | N80: AUXÍLIO ALUGUEL UH | O80: 45986 | P80: 6014.2025/0007513-3 | Q80: 45985 | R80: 45986 | S80: 45987 | T80: 45992 | U80: OK | V80: OK | W80: 45999 | X80: 46001 | Y80: 46017 | AA80: PATRICIA APARECIDA ALVES GRANZOTTI | AB80: 69.378.106-3 | AC80: 270.886.538-26 | AD80: PROPRIETÁRIO RESIDENTE | AE80: CADASTRADO | AF80: N.A | AG80: N.A | AH80: UH | AI80: 6014.2025/0007373-4 | AK80: 45979 | AL80: 45979 | AM80: 45979 | AN80: 45979 | AO80: 45979 | AP80: 45979 | AR80: =IF(AQ80="SIM","AGUARDANDO CORREÇÃO",IF(AP80<>"","FINALIZADO",IF(AO80<>"","AGUARDANDO ENVIO DTS",IF(AN80<>"","AGUARDANDO ASSINATURA GAB",IF(AM80<>"","AGUARDANDO ASSINATURA CTS",IF(AL80<>"","AGUARDANDO ENVIO ASSINATURA CTS",IF(AK80<>"","AGUARDANDO CONFERÊNCIA",""))))))) -> FINALIZADO | BE80: 46017 | BF80: DEMOLIDO | BH80: =IFERROR(IF(BD80-KI80=0,"",BD80-AK80),"") | BI80: =IF(AND(AH80<>"SIM",AH80="UH"),"AA","INDENIZAÇÃO") -> AA | BJ80: =IF(AND(BD80<>"AGUARDANDO",BD80<>"",N80="AUXÍLIO ALUGUEL ATÉ INDENIZAÇÃO"),"SIM","NÃO") -> NÃO
A81: 77 | B81: JD. PANTANAL | C81: TERRA PROMETIDA | D81: 1 | E81: -- | F81: 001/0031/A | G81: OCUPADO | H81: RESIDENCIAL | I81: PROPRIETÁRIO RESIDENTE | J81: DANIELE GRANZOTTI GENU | K81: 57.665.092-4 | L81: 529.889.978-10 | M81: CADASTRADO | N81: AUXÍLIO ALUGUEL UH | O81: 45986 | P81: 6014.2025/0007513-3 | Q81: 45985 | R81: 45986 | S81: 45987 | T81: 45992 | U81: OK | V81: OK | W81: 45999 | X81: 46000 | Y81: 46017 | AA81: DANIELE GRANZOTTI GENU | AB81: 57.665.092-4 | AC81: 529.889.978-10 | AD81: PROPRIETÁRIO RESIDENTE | AE81: CADASTRADO | AF81: N.A | AG81: N.A | AH81: UH | AI81: 6014.2025/0007373-4 | AK81: 45979 | AL81: 45979 | AM81: 45979 | AN81: 45979 | AO81: 45979 | AP81: 45979 | AR81: =IF(AQ81="SIM","AGUARDANDO CORREÇÃO",IF(AP81<>"","FINALIZADO",IF(AO81<>"","AGUARDANDO ENVIO DTS",IF(AN81<>"","AGUARDANDO ASSINATURA GAB",IF(AM81<>"","AGUARDANDO ASSINATURA CTS",IF(AL81<>"","AGUARDANDO ENVIO ASSINATURA CTS",IF(AK81<>"","AGUARDANDO CONFERÊNCIA",""))))))) -> FINALIZADO | BE81: 46017 | BF81: DEMOLIDO | BH81: =IFERROR(IF(BD81-KI81=0,"",BD81-AK81),"") | BI81: =IF(AND(AH81<>"SIM",AH81="UH"),"AA","INDENIZAÇÃO") -> AA | BJ81: =IF(AND(BD81<>"AGUARDANDO",BD81<>"",N81="AUXÍLIO ALUGUEL ATÉ INDENIZAÇÃO"),"SIM","NÃO") -> NÃO
A82: 78 | B82: JD. PANTANAL | C82: TERRA PROMETIDA | D82: 1 | E82: -- | F82: 001/0032/A | G82: OCUPADO | H82: RESIDENCIAL | I82: PROPRIETÁRIO RESIDENTE | J82: PRISCILA DE ARAUJO MONTEIRO | K82: 37.104.985-4 | L82: 380.741.148-80 | M82: CADASTRADO | N82: AUXÍLIO ALUGUEL UH | O82: 45986 | P82: 6014.2025/0007513-3 | Q82: 45985 | R82: 45986 | S82: 45987 | T82: 45992 | U82: OK | V82: OK | W82: 45999 | X82: 46000 | Y82: 46017 | AA82: PRISCILA DE ARAUJO MONTEIRO | AB82: 37.104.985-4 | AC82: 380.741.148-80 | AD82: PROPRIETÁRIO RESIDENTE | AE82: CADASTRADO | AF82: N.A | AG82: N.A | AH82: UH | AI82: 6014.2025/0007373-4 | AK82: 45979 | AL82: 45979 | AM82: 45979 | AN82: 45979 | AO82: 45979 | AP82: 45979 | AR82: =IF(AQ82="SIM","AGUARDANDO CORREÇÃO",IF(AP82<>"","FINALIZADO",IF(AO82<>"","AGUARDANDO ENVIO DTS",IF(AN82<>"","AGUARDANDO ASSINATURA GAB",IF(AM82<>"","AGUARDANDO ASSINATURA CTS",IF(AL82<>"","AGUARDANDO ENVIO ASSINATURA CTS",IF(AK82<>"","AGUARDANDO CONFERÊNCIA",""))))))) -> FINALIZADO | BE82: 46017 | BF82: DEMOLIDO | BH82: =IFERROR(IF(BD82-KI82=0,"",BD82-AK82),"") | BI82: =IF(AND(AH82<>"SIM",AH82="UH"),"AA","INDENIZAÇÃO") -> AA | BJ82: =IF(AND(BD82<>"AGUARDANDO",BD82<>"",N82="AUXÍLIO ALUGUEL ATÉ INDENIZAÇÃO"),"SIM","NÃO") -> NÃO
A83: 79 | B83: JD. PANTANAL | C83: TERRA PROMETIDA | D83: 1 | E83: -- | F83: 001/0033/A | G83: OCUPADO | H83: RESIDENCIAL | I83: PROPRIETÁRIO RESIDENTE | J83: FRANCISCO DOS SANTOS CARVALHO | K83: _ | L83: 665.497.523-53 | M83: CADASTRADO | N83: INDENIZAÇÃO | O83: N.A | P83: N.A | Q83: N.A | R83: N.A | S83: N.A | T83: N.A | U83: N.A | V83: N.A | W83: N.A | X83: N.A | AA83: FRANCISCO DOS SANTOS CARVALHO | AB83: -- | AC83: 665.497.523-53 | AD83: PROPRIETÁRIO RESIDENTE | AE83: CADASTRADO | AF83: 8992.46 | AG83: =AF83+30000 -> 38992.46 | AH83: SIM | AI83: 6014.2025/0007373-4 | AJ83: 146663098 | AK83: 45979 | AL83: 45979 | AM83: 45979 | AN83: 45979 | AO83: 45979 | AP83: 45979 | AR83: =IF(AQ83="SIM","AGUARDANDO CORREÇÃO",IF(AP83<>"","FINALIZADO",IF(AO83<>"","AGUARDANDO ENVIO DTS",IF(AN83<>"","AGUARDANDO ASSINATURA GAB",IF(AM83<>"","AGUARDANDO ASSINATURA CTS",IF(AL83<>"","AGUARDANDO ENVIO ASSINATURA CTS",IF(AK83<>"","AGUARDANDO CONFERÊNCIA",""))))))) -> FINALIZADO | AS83: SEM PENDÊNCIA | AU83: 6014.2025/0008122-2 | AV83: FINALIZADO | AW83: FINALIZADO | AX83: FINALIZADO | AY83: FINALIZADO | AZ83: 46008 | BA83: FINALIZADO | BB83: FINALIZADO | BC83: 46014 | BD83: 46014 | BE83: 46017 | BF83: DEMOLIDO | BG83: FINALIZADO | BH83: =IFERROR(IF(BD83-KI83=0,"",BD83-AK83),"") -> 35 | BI83: =IF(AND(AH83<>"SIM",AH83="UH"),"AA","INDENIZAÇÃO") -> INDENIZAÇÃO | BJ83: =IF(AND(BD83<>"AGUARDANDO",BD83<>"",N83="AUXÍLIO ALUGUEL ATÉ INDENIZAÇÃO"),"SIM","NÃO") -> NÃO | BK83: N/A | BL83: N/A | BM83: N/A | BN83: FINALIZADO | BO83: FINALIZADO | BP83: 46128 | BQ83: FINALIZADO | BR83: AGUARDANDO
A84: 80 | B84: JD. PANTANAL | C84: TERRA PROMETIDA | D84: 1 | E84: -- | F84: 001/0034/A | G84: OCUPADO | H84: RESIDENCIAL | I84: INQUILINO | J84: CARLOS EDUARDO DE OLIVEIRA | K84: 44.926.922-X | L84: 239.791.038-11 | M84: CADASTRADO | N84: AUXÍLIO ALUGUEL UH | O84: 45986 | P84: 6014.2025/0007513-3 | Q84: 45985 | R84: 45986 | S84: 45987 | T84: 45992 | U84: OK | V84: OK | W84: 45999 | X84: 46006 | Y84: 46017 | AA84: THIAGO WILLIAN LIMA NABAT | AB84: 64.040.634-8 | AC84: 584.545.628-26 | AD84: PROPRIETÁRIO NÃO RESIDENTE | AE84: CADASTRADO | AF84: 7579.04 | AG84: 7579.04 | AH84: SIM | AI84: 6014.2025/0007373-4 | AJ84: 146038241 | AK84: 45979 | AL84: 45979 | AM84: 45979 | AN84: 45979 | AO84: 45979 | AP84: 45979 | AR84: =IF(AQ84="SIM","AGUARDANDO CORREÇÃO",IF(AP84<>"","FINALIZADO",IF(AO84<>"","AGUARDANDO ENVIO DTS",IF(AN84<>"","AGUARDANDO ASSINATURA GAB",IF(AM84<>"","AGUARDANDO ASSINATURA CTS",IF(AL84<>"","AGUARDANDO ENVIO ASSINATURA CTS",IF(AK84<>"","AGUARDANDO CONFERÊNCIA",""))))))) -> FINALIZADO | AS84: SEM PENDÊNCIA | AU84: 6014.2025/0008124-9 | AV84: FINALIZADO | AW84: FINALIZADO | AX84: FINALIZADO | AY84: FINALIZADO | AZ84: 46056 | BA84: FINALIZADO | BB84: FINALIZADO | BC84: 46063 | BD84: 46063 | BE84: 46017 | BF84: DEMOLIDO | BG84: FINALIZADO | BH84: =IFERROR(IF(BD84-KI84=0,"",BD84-AK84),"") -> 84 | BI84: =IF(AND(AH84<>"SIM",AH84="UH"),"AA","INDENIZAÇÃO") -> INDENIZAÇÃO | BJ84: =IF(AND(BD84<>"AGUARDANDO",BD84<>"",N84="AUXÍLIO ALUGUEL ATÉ INDENIZAÇÃO"),"SIM","NÃO") -> NÃO | BK84: N/A | BL84: N/A | BM84: N/A | BN84: FINALIZADO | BO84: FINALIZADO | BP84: 46182 | BQ84: FINALIZADO | BR84: AGUARDANDO
A85: 81 | B85: JD. PANTANAL | C85: TERRA PROMETIDA | D85: 1 | E85: -- | F85: 001/0035/A | G85: OCUPADO | H85: RESIDENCIAL | I85: PROPRIETÁRIO RESIDENTE | J85: MAILSON DE JESUS SANTOS | K85: -- | L85: 037.614.295-25 | M85: CADASTRADO | N85: INDENIZAÇÃO | O85: N.A | P85: N.A | Q85: N.A | R85: N.A | S85: N.A | T85: N.A | U85: N.A | V85: N.A | W85: N.A | X85: N.A | AA85: MAILSON DE JESUS SANTOS | AB85: -- | AC85: 037.614.295-25 | AD85: PROPRIETÁRIO RESIDENTE | AE85: CADASTRADO | AF85: 43946.14 | AG85: 60000 | AH85: SIM | AI85: 6014.2025/0007373-4 | AJ85: 146038334 | AK85: 45979 | AL85: 45979 | AM85: 45979 | AN85: 45979 | AO85: 45979 | AP85: 45979 | AR85: =IF(AQ85="SIM","AGUARDANDO CORREÇÃO",IF(AP85<>"","FINALIZADO",IF(AO85<>"","AGUARDANDO ENVIO DTS",IF(AN85<>"","AGUARDANDO ASSINATURA GAB",IF(AM85<>"","AGUARDANDO ASSINATURA CTS",IF(AL85<>"","AGUARDANDO ENVIO ASSINATURA CTS",IF(AK85<>"","AGUARDANDO CONFERÊNCIA",""))))))) -> FINALIZADO | AS85: SEM PENDÊNCIA | AU85: 6014.2025/0008125-7 | AV85: FINALIZADO | AW85: FINALIZADO | AX85: FINALIZADO | AY85: FINALIZADO | AZ85: 46008 | BA85: FINALIZADO | BB85: FINALIZADO | BC85: 46014 | BD85: 46379 | BE85: 46017 | BF85: DEMOLIDO | BG85: FINALIZADO | BH85: =IFERROR(IF(BD85-KI85=0,"",BD85-AK85),"") -> 400 | BI85: =IF(AND(AH85<>"SIM",AH85="UH"),"AA","INDENIZAÇÃO") -> INDENIZAÇÃO | BJ85: =IF(AND(BD85<>"AGUARDANDO",BD85<>"",N85="AUXÍLIO ALUGUEL ATÉ INDENIZAÇÃO"),"SIM","NÃO") -> NÃO | BK85: N/A | BL85: N/A | BM85: N/A | BN85: FINALIZADO | BO85: FINALIZADO | BP85: 46182 | BQ85: FINALIZADO | BR85: AGUARDANDO
A86: 82 | B86: JD. PANTANAL | C86: TERRA PROMETIDA | D86: 1 | E86: -- | F86: 001/0036/A | G86: OCUPADO | H86: RESIDENCIAL | I86: PROPRIETÁRIO RESIDENTE | J86: CIBELE APARECIDA DA SILVA | K86: 22.012.369-X | L86: 285.579.088-30 | M86: CADASTRADO | N86: AUXÍLIO ALUGUEL UH | O86: 45986 | P86: 6014.2025/0007513-3 | Q86: 45985 | R86: 45986 | S86: 45987 | T86: 45992 | U86: OK | V86: OK | W86: 45999 | X86: 46002 | Y86: 46017 | AA86: CIBELE APARECIDA DA SILVA | AB86: 22.012.369-X | AC86: 285.579.088-30 | AD86: PROPRIETÁRIO RESIDENTE | AE86: CADASTRADO | AF86: N.A | AG86: N.A | AH86: UH | AI86: 6014.2025/0007373-4 | AK86: 45979 | AL86: 45979 | AM86: 45979 | AN86: 45979 | AO86: 45979 | AP86: 45979 | AR86: =IF(AQ86="SIM","AGUARDANDO CORREÇÃO",IF(AP86<>"","FINALIZADO",IF(AO86<>"","AGUARDANDO ENVIO DTS",IF(AN86<>"","AGUARDANDO ASSINATURA GAB",IF(AM86<>"","AGUARDANDO ASSINATURA CTS",IF(AL86<>"","AGUARDANDO ENVIO ASSINATURA CTS",IF(AK86<>"","AGUARDANDO CONFERÊNCIA",""))))))) -> FINALIZADO | BE86: 46017 | BF86: DEMOLIDO | BH86: =IFERROR(IF(BD86-KI86=0,"",BD86-AK86),"") | BI86: =IF(AND(AH86<>"SIM",AH86="UH"),"AA","INDENIZAÇÃO") -> AA | BJ86: =IF(AND(BD86<>"AGUARDANDO",BD86<>"",N86="AUXÍLIO ALUGUEL ATÉ INDENIZAÇÃO"),"SIM","NÃO") -> NÃO
A87: 83 | B87: JD. PANTANAL | C87: TERRA PROMETIDA | D87: 1 | E87: -- | F87: 001/0037/A | G87: OCUPADO | H87: RESIDENCIAL | I87: PROPRIETÁRIO RESIDENTE | J87: MANFLINIS GOMES DE OLIVEIRA | K87: 29.158.615-6 | L87: 188.012.488-22 | M87: CADASTRADO | N87: INDENIZAÇÃO | O87: N.A | P87: N.A | Q87: N.A | R87: N.A | S87: N.A | T87: N.A | U87: N.A | V87: N.A | W87: N.A | X87: N.A | AA87: MANFLINIS GOMES DE OLIVEIRA | AB87: 29.158.615-6 | AC87: 188.012.488-22 | AD87: PROPRIETÁRIO RESIDENTE | AE87: CADASTRADO | AF87: 13745.32 | AG87: =AF87+30000 -> 43745.32 | AH87: SIM | AI87: 6014.2025/0007373-4 | AJ87: 149645583 | AK87: 46045 | AL87: 46045 | AM87: 46045 | AN87: 46045 | AO87: 46045 | AP87: 46045 | AR87: =IF(AQ87="SIM","AGUARDANDO CORREÇÃO",IF(AP87<>"","FINALIZADO",IF(AO87<>"","AGUARDANDO ENVIO DTS",IF(AN87<>"","AGUARDANDO ASSINATURA GAB",IF(AM87<>"","AGUARDANDO ASSINATURA CTS",IF(AL87<>"","AGUARDANDO ENVIO ASSINATURA CTS",IF(AK87<>"","AGUARDANDO CONFERÊNCIA",""))))))) -> FINALIZADO | AS87: SEM PENDÊNCIA | AU87: 6014.2026/0000476-9 | AV87: FINALIZADO | AW87: FINALIZADO | AX87: FINALIZADO | AY87: FINALIZADO | AZ87: 46062 | BA87: FINALIZADO | BB87: FINALIZADO | BC87: 46066 | BD87: 46066 | BE87: 46017 | BF87: DEMOLIDO | BG87: FINALIZADO | BH87: =IFERROR(IF(BD87-KI87=0,"",BD87-AK87),"") -> 21 | BI87: =IF(AND(AH87<>"SIM",AH87="UH"),"AA","INDENIZAÇÃO") -> INDENIZAÇÃO | BJ87: =IF(AND(BD87<>"AGUARDANDO",BD87<>"",N87="AUXÍLIO ALUGUEL ATÉ INDENIZAÇÃO"),"SIM","NÃO") -> NÃO | BK87: N/A | BL87: N/A | BM87: N/A | BN87: FINALIZADO | BO87: FINALIZADO | BP87: 46182 | BQ87: FINALIZADO | BR87: AGUARDANDO
A88: 84 | B88: JD. PANTANAL | C88: TERRA PROMETIDA | D88: 1 | E88: -- | F88: 001/0038/A | G88: OCUPADO | H88: RESIDENCIAL | I88: PROPRIETÁRIO RESIDENTE | J88: MATEUS JOSE DA ROCHA | K88: 19.652.528-7 | L88: 142.528.298-95 | M88: CADASTRADO | N88: INDENIZAÇÃO | O88: N.A | P88: N.A | Q88: N.A | R88: N.A | S88: N.A | T88: N.A | U88: N.A | V88: N.A | W88: N.A | X88: N.A | AA88: MATEUS JOSE DA ROCHA | AB88: 19.652.528-7 | AC88: 142.528.298-95 | AD88: PROPRIETÁRIO RESIDENTE | AE88: CADASTRADO | AF88: 47897.7 | AG88: 60000 | AH88: SIM | AI88: 6014.2025/0007373-4 | AJ88: 146038870 | AK88: 45979 | AL88: 45979 | AM88: 45979 | AN88: 45979 | AO88: 45979 | AP88: 45979 | AR88: =IF(AQ88="SIM","AGUARDANDO CORREÇÃO",IF(AP88<>"","FINALIZADO",IF(AO88<>"","AGUARDANDO ENVIO DTS",IF(AN88<>"","AGUARDANDO ASSINATURA GAB",IF(AM88<>"","AGUARDANDO ASSINATURA CTS",IF(AL88<>"","AGUARDANDO ENVIO ASSINATURA CTS",IF(AK88<>"","AGUARDANDO CONFERÊNCIA",""))))))) -> FINALIZADO | AS88: SEM PENDÊNCIA | AU88: 6014.2025/0008126-5 | AV88: FINALIZADO | AW88: FINALIZADO | AX88: FINALIZADO | AY88: FINALIZADO | AZ88: 46014 | BA88: FINALIZADO | BB88: FINALIZADO | BC88: 46021 | BD88: 46021 | BE88: 46017 | BF88: DEMOLIDO | BG88: FINALIZADO | BH88: =IFERROR(IF(BD88-KI88=0,"",BD88-AK88),"") -> 42 | BI88: =IF(AND(AH88<>"SIM",AH88="UH"),"AA","INDENIZAÇÃO") -> INDENIZAÇÃO | BJ88: =IF(AND(BD88<>"AGUARDANDO",BD88<>"",N88="AUXÍLIO ALUGUEL ATÉ INDENIZAÇÃO"),"SIM","NÃO") -> NÃO | BK88: N/A | BL88: N/A | BM88: N/A | BN88: FINALIZADO | BO88: FINALIZADO | BP88: 46182 | BQ88: FINALIZADO | BR88: AGUARDANDO
A89: 85 | B89: JD. PANTANAL | C89: TERRA PROMETIDA | D89: 1 | E89: -- | F89: 001/0039/A | G89: OCUPADO | H89: RESIDENCIAL | I89: PROPRIETÁRIO RESIDENTE | J89: VALDITE MARIA DE OLIVEIRA | K89: 28.327.943-6 | L89: 290.029.388-02 | M89: CADASTRADO | N89: INDENIZAÇÃO | O89: N.A | P89: N.A | Q89: N.A | R89: N.A | S89: N.A | T89: N.A | U89: N.A | V89: N.A | W89: N.A | X89: N.A | AA89: VALDITE MARIA DE OLIVEIRA | AB89: 28.327.943-6 | AC89: 290.029.388-02 | AD89: PROPRIETÁRIO RESIDENTE | AE89: CADASTRADO | AF89: 66297.96 | AG89: 66297.96 | AH89: SIM | AI89: 6014.2025/0007373-4 | AJ89: 146038990 | AK89: 45979 | AL89: 45979 | AM89: 45979 | AN89: 45979 | AO89: 45979 | AP89: 45979 | AR89: =IF(AQ89="SIM","AGUARDANDO CORREÇÃO",IF(AP89<>"","FINALIZADO",IF(AO89<>"","AGUARDANDO ENVIO DTS",IF(AN89<>"","AGUARDANDO ASSINATURA GAB",IF(AM89<>"","AGUARDANDO ASSINATURA CTS",IF(AL89<>"","AGUARDANDO ENVIO ASSINATURA CTS",IF(AK89<>"","AGUARDANDO CONFERÊNCIA",""))))))) -> FINALIZADO | AS89: SEM PENDÊNCIA | AU89: 6014.2025/0008131-1 | AV89: FINALIZADO | AW89: FINALIZADO | AX89: FINALIZADO | AY89: FINALIZADO | AZ89: 46014 | BA89: FINALIZADO | BB89: FINALIZADO | BC89: 46021 | BD89: 46021 | BE89: 46017 | BF89: DEMOLIDO | BG89: FINALIZADO | BH89: =IFERROR(IF(BD89-KI89=0,"",BD89-AK89),"") -> 42 | BI89: =IF(AND(AH89<>"SIM",AH89="UH"),"AA","INDENIZAÇÃO") -> INDENIZAÇÃO | BJ89: =IF(AND(BD89<>"AGUARDANDO",BD89<>"",N89="AUXÍLIO ALUGUEL ATÉ INDENIZAÇÃO"),"SIM","NÃO") -> NÃO | BK89: N/A | BL89: N/A | BM89: N/A | BN89: FINALIZADO | BO89: FINALIZADO | BP89: 46182 | BQ89: FINALIZADO | BR89: AGUARDANDO
A90: 86 | B90: JD. PANTANAL | C90: TERRA PROMETIDA | D90: 1 | E90: -- | F90: 001/0040/A | G90: OCUPADO | H90: RESIDENCIAL | I90: PROPRIETÁRIO RESIDENTE | J90: JÉSSICA SANTOS SILVA | K90: 50.185.663-8 | L90: 389.451.458-26 | M90: CADASTRADO | N90: AUXÍLIO ALUGUEL UH | O90: 45986 | P90: 6014.2025/0007513-3 | Q90: 45985 | R90: 45986 | S90: 45987 | T90: 45992 | U90: OK | V90: OK | W90: 45999 | X90: 46006 | Y90: 46017 | AA90: JÉSSICA SANTOS SILVA | AB90: 50.185.663-8 | AC90: 389.451.458-26 | AD90: PROPRIETÁRIO RESIDENTE | AE90: CADASTRADO | AF90: N.A | AG90: N.A | AH90: UH | AI90: 6014.2025/0007373-4 | AK90: 45979 | AL90: 45979 | AM90: 45979 | AN90: 45979 | AO90: 45979 | AP90: 45979 | AR90: =IF(AQ90="SIM","AGUARDANDO CORREÇÃO",IF(AP90<>"","FINALIZADO",IF(AO90<>"","AGUARDANDO ENVIO DTS",IF(AN90<>"","AGUARDANDO ASSINATURA GAB",IF(AM90<>"","AGUARDANDO ASSINATURA CTS",IF(AL90<>"","AGUARDANDO ENVIO ASSINATURA CTS",IF(AK90<>"","AGUARDANDO CONFERÊNCIA",""))))))) -> FINALIZADO | BE90: 46017 | BF90: DEMOLIDO | BH90: =IFERROR(IF(BD90-KI90=0,"",BD90-AK90),"") | BI90: =IF(AND(AH90<>"SIM",AH90="UH"),"AA","INDENIZAÇÃO") -> AA | BJ90: =IF(AND(BD90<>"AGUARDANDO",BD90<>"",N90="AUXÍLIO ALUGUEL ATÉ INDENIZAÇÃO"),"SIM","NÃO") -> NÃO
A91: 87 | B91: JD. PANTANAL | C91: TERRA PROMETIDA | D91: 1 | E91: -- | F91: 001/0041/A | G91: OCUPADO | H91: RESIDENCIAL | I91: PROPRIETÁRIO RESIDENTE | J91: VITOR SANTOS DA SILVA | K91: 39.110.454-8 | L91: 518.299.308-00 | M91: CADASTRADO | N91: AUXÍLIO ALUGUEL UH | O91: 46044 | P91: 6014.2025/0007513-3 | Q91: 46043 | R91: 46044 | S91: 46045 | T91: 46155 | U91: OK | V91: OK | W91: 46055 | X91: 46059 | Y91: 46017 | AA91: VITOR SANTOS DA SILVA | AB91: 39.110.454-8 | AC91: 518.299.308-00 | AD91: PROPRIETÁRIO RESIDENTE | AE91: CADASTRADO | AF91: N.A | AG91: N.A | AH91: UH | AI91: 6014.2025/0007373-4 | AK91: 46041 | AL91: 46041 | AM91: 46041 | AN91: 46041 | AO91: 46041 | AP91: 46041 | AR91: =IF(AQ91="SIM","AGUARDANDO CORREÇÃO",IF(AP91<>"","FINALIZADO",IF(AO91<>"","AGUARDANDO ENVIO DTS",IF(AN91<>"","AGUARDANDO ASSINATURA GAB",IF(AM91<>"","AGUARDANDO ASSINATURA CTS",IF(AL91<>"","AGUARDANDO ENVIO ASSINATURA CTS",IF(AK91<>"","AGUARDANDO CONFERÊNCIA",""))))))) -> FINALIZADO | BE91: 46017 | BF91: DEMOLIDO | BH91: =IFERROR(IF(BD91-KI91=0,"",BD91-AK91),"") | BI91: =IF(AND(AH91<>"SIM",AH91="UH"),"AA","INDENIZAÇÃO") -> AA | BJ91: =IF(AND(BD91<>"AGUARDANDO",BD91<>"",N91="AUXÍLIO ALUGUEL ATÉ INDENIZAÇÃO"),"SIM","NÃO") -> NÃO
A92: 88 | B92: JD. PANTANAL | C92: TERRA PROMETIDA | D92: 1 | E92: -- | F92: 001/0042/A | G92: OCUPADO | H92: RESIDENCIAL | I92: PROPRIETÁRIO RESIDENTE | J92: MARCELA COSTA DE LIMA | K92: 49.142.800-5 | L92: 461.180.098-99 | M92: CADASTRADO | N92: AUXÍLIO ALUGUEL UH | O92: 45986 | P92: 6014.2025/0007513-3 | Q92: 45985 | R92: 45986 | S92: 45987 | T92: 45992 | U92: OK | V92: OK | W92: 45999 | X92: 46000 | Y92: 46017 | AA92: MARCELA COSTA DE LIMA | AB92: 49.142.800-5 | AC92: 461.180.098-99 | AD92: PROPRIETÁRIO RESIDENTE | AE92: CADASTRADO | AF92: N.A | AG92: N.A | AH92: UH | AI92: 6014.2025/0007373-4 | AK92: 45979 | AL92: 45979 | AM92: 45979 | AN92: 45979 | AO92: 45979 | AP92: 45979 | AR92: =IF(AQ92="SIM","AGUARDANDO CORREÇÃO",IF(AP92<>"","FINALIZADO",IF(AO92<>"","AGUARDANDO ENVIO DTS",IF(AN92<>"","AGUARDANDO ASSINATURA GAB",IF(AM92<>"","AGUARDANDO ASSINATURA CTS",IF(AL92<>"","AGUARDANDO ENVIO ASSINATURA CTS",IF(AK92<>"","AGUARDANDO CONFERÊNCIA",""))))))) -> FINALIZADO | BE92: 46017 | BF92: DEMOLIDO | BH92: =IFERROR(IF(BD92-KI92=0,"",BD92-AK92),"") | BI92: =IF(AND(AH92<>"SIM",AH92="UH"),"AA","INDENIZAÇÃO") -> AA | BJ92: =IF(AND(BD92<>"AGUARDANDO",BD92<>"",N92="AUXÍLIO ALUGUEL ATÉ INDENIZAÇÃO"),"SIM","NÃO") -> NÃO
A93: 89 | B93: JD. PANTANAL | C93: TERRA PROMETIDA | D93: 1 | E93: -- | F93: 001/0043/A | G93: OCUPADO | H93: RESIDENCIAL | I93: PROPRIETÁRIO RESIDENTE | J93: LARISSA PAULA DA SILVA | K93: 54.839.513-5 | L93: 530.988.528-52 | M93: CADASTRADO | N93: AUXÍLIO ALUGUEL UH | O93: 45986 | P93: 6014.2025/0007513-3 | Q93: 45985 | R93: 45986 | S93: 45987 | T93: 45992 | U93: OK | V93: OK | W93: 45999 | X93: 46000 | Y93: 46017 | AA93: LARISSA PAULA DA SILVA | AB93: 54.839.513-5 | AC93: 530.988.528-52 | AD93: PROPRIETÁRIO RESIDENTE | AE93: CADASTRADO | AF93: N.A | AG93: N.A | AH93: UH | AI93: 6014.2025/0007373-4 | AK93: 45979 | AL93: 45979 | AM93: 45979 | AN93: 45979 | AO93: 45979 | AP93: 45979 | AR93: =IF(AQ93="SIM","AGUARDANDO CORREÇÃO",IF(AP93<>"","FINALIZADO",IF(AO93<>"","AGUARDANDO ENVIO DTS",IF(AN93<>"","AGUARDANDO ASSINATURA GAB",IF(AM93<>"","AGUARDANDO ASSINATURA CTS",IF(AL93<>"","AGUARDANDO ENVIO ASSINATURA CTS",IF(AK93<>"","AGUARDANDO CONFERÊNCIA",""))))))) -> FINALIZADO | BE93: 46017 | BF93: DEMOLIDO | BH93: =IFERROR(IF(BD93-KI93=0,"",BD93-AK93),"") | BI93: =IF(AND(AH93<>"SIM",AH93="UH"),"AA","INDENIZAÇÃO") -> AA | BJ93: =IF(AND(BD93<>"AGUARDANDO",BD93<>"",N93="AUXÍLIO ALUGUEL ATÉ INDENIZAÇÃO"),"SIM","NÃO") -> NÃO
A94: 90 | B94: JD. PANTANAL | C94: TERRA PROMETIDA | D94: 1 | E94: -- | F94: 001/0044/A | G94: OCUPADO | H94: RESIDENCIAL | I94: PROPRIETÁRIO RESIDENTE | J94: SILVIO LUCIANO AZEVEDO | K94: -- | L94: 170.191.398-41 | M94: CADASTRADO | N94: AUXÍLIO ALUGUEL UH | O94: 45986 | P94: 6014.2025/0007513-3 | Q94: 45985 | R94: 45986 | S94: 45987 | T94: 45992 | U94: OK | V94: OK | W94: 45999 | X94: 46000 | Y94: 46017 | AA94: SILVIO LUCIANO AZEVEDO | AB94: -- | AC94: 170.191.398-41 | AD94: PROPRIETÁRIO RESIDENTE | AE94: CADASTRADO | AF94: N.A | AG94: N.A | AH94: UH | AI94: 6014.2025/0007373-4 | AK94: 45979 | AL94: 45979 | AM94: 45979 | AN94: 45979 | AO94: 45979 | AP94: 45979 | AR94: =IF(AQ94="SIM","AGUARDANDO CORREÇÃO",IF(AP94<>"","FINALIZADO",IF(AO94<>"","AGUARDANDO ENVIO DTS",IF(AN94<>"","AGUARDANDO ASSINATURA GAB",IF(AM94<>"","AGUARDANDO ASSINATURA CTS",IF(AL94<>"","AGUARDANDO ENVIO ASSINATURA CTS",IF(AK94<>"","AGUARDANDO CONFERÊNCIA",""))))))) -> FINALIZADO | BE94: 46017 | BF94: DEMOLIDO | BH94: =IFERROR(IF(BD94-KI94=0,"",BD94-AK94),"") | BI94: =IF(AND(AH94<>"SIM",AH94="UH"),"AA","INDENIZAÇÃO") -> AA | BJ94: =IF(AND(BD94<>"AGUARDANDO",BD94<>"",N94="AUXÍLIO ALUGUEL ATÉ INDENIZAÇÃO"),"SIM","NÃO") -> NÃO
A95: 91 | B95: JD. PANTANAL | C95: TERRA PROMETIDA | D95: 1 | E95: -- | F95: 002/0001/A | G95: OCUPADO | H95: RESIDENCIAL | I95: PROPRIETÁRIO RESIDENTE | J95: GABRIELA DE LIMA MACEDO | K95: 36.190.607-9 | L95: 454.674.508-75 | M95: CADASTRADO | N95: INDENIZAÇÃO | O95: N.A | P95: N.A | Q95: N.A | R95: N.A | S95: N.A | T95: N.A | U95: N.A | V95: N.A | W95: N.A | X95: N.A | AA95: GABRIELA DE LIMA MACEDO | AB95: 36.190.607-9 | AC95: 454.674.508-75 | AD95: PROPRIETÁRIO RESIDENTE | AE95: CADASTRADO | AF95: 41067.25 | AG95: 60000 | AH95: SIM | AI95: 6014.2025/0007373-4 | AJ95: 146039739 | AK95: 45979 | AL95: 45979 | AM95: 45979 | AN95: 45979 | AO95: 45979 | AP95: 45979 | AR95: =IF(AQ95="SIM","AGUARDANDO CORREÇÃO",IF(AP95<>"","FINALIZADO",IF(AO95<>"","AGUARDANDO ENVIO DTS",IF(AN95<>"","AGUARDANDO ASSINATURA GAB",IF(AM95<>"","AGUARDANDO ASSINATURA CTS",IF(AL95<>"","AGUARDANDO ENVIO ASSINATURA CTS",IF(AK95<>"","AGUARDANDO CONFERÊNCIA",""))))))) -> FINALIZADO | AS95: SEM PENDÊNCIA | AU95: 6014.2025/0008155-9 | AV95: FINALIZADO | AW95: FINALIZADO | AX95: FINALIZADO | AY95: FINALIZADO | AZ95: 46009 | BA95: FINALIZADO | BB95: FINALIZADO | BC95: 46017 | BD95: 46017 | BE95: 46017 | BF95: DEMOLIDO | BG95: FINALIZADO | BH95: =IFERROR(IF(BD95-KI95=0,"",BD95-AK95),"") -> 38 | BI95: =IF(AND(AH95<>"SIM",AH95="UH"),"AA","INDENIZAÇÃO") -> INDENIZAÇÃO | BJ95: =IF(AND(BD95<>"AGUARDANDO",BD95<>"",N95="AUXÍLIO ALUGUEL ATÉ INDENIZAÇÃO"),"SIM","NÃO") -> NÃO | BK95: N/A | BL95: N/A | BM95: N/A | BN95: FINALIZADO | BO95: FINALIZADO | BP95: 46182 | BQ95: FINALIZADO | BR95: AGUARDANDO
A96: 92 | B96: JD. PANTANAL | C96: NOVO HORIZONTE | D96: 1 | E96: -- | F96: 002/0001/A | G96: OCUPADO | H96: RESIDENCIAL | I96: PROPRIETÁRIO RESIDENTE | J96: LUANA KELLY DA SILVA SOUSA | K96: 50.829.275-X | L96: 034.502.993-36 | M96: CADASTRADO | N96: INDENIZAÇÃO | O96: N.A | P96: N.A | Q96: N.A | R96: N.A | S96: N.A | T96: N.A | U96: N.A | V96: N.A | W96: N.A | X96: N.A | AA96: LUANA KELLY DA SILVA SOUSA | AB96: 50.829.275-X | AC96: 034.502.993-36 | AD96: PROPRIETÁRIO RESIDENTE | AE96: CADASTRADO | AF96: 61670.74 | AG96: 61670.74 | AH96: SIM | AI96: 6014.2025/0007373-4 | AJ96: 151544320 | AK96: 46093 | AL96: 46093 | AM96: 46093 | AN96: 46093 | AO96: 46093 | AP96: 46093 | AR96: =IF(AQ96="SIM","AGUARDANDO CORREÇÃO",IF(AP96<>"","FINALIZADO",IF(AO96<>"","AGUARDANDO ENVIO DTS",IF(AN96<>"","AGUARDANDO ASSINATURA GAB",IF(AM96<>"","AGUARDANDO ASSINATURA CTS",IF(AL96<>"","AGUARDANDO ENVIO ASSINATURA CTS",IF(AK96<>"","AGUARDANDO CONFERÊNCIA",""))))))) -> FINALIZADO | AS96: SEM PENDÊNCIA | AU96: 6014.2026/0001329-6 | AV96: FINALIZADO | AW96: FINALIZADO | AX96: FINALIZADO | AY96: FINALIZADO | AZ96: 46150 | BA96: FINALIZADO | BB96: FINALIZADO | BC96: 46192 | BD96: 46192 | BE96: AGUARDANDO | BF96: OCUPADO | BG96: FINALIZADO | BH96: =IFERROR(IF(BD96-KI96=0,"",BD96-AK96),"") -> 99 | BI96: =IF(AND(AH96<>"SIM",AH96="UH"),"AA","INDENIZAÇÃO") -> INDENIZAÇÃO | BJ96: =IF(AND(BD96<>"AGUARDANDO",BD96<>"",N96="AUXÍLIO ALUGUEL ATÉ INDENIZAÇÃO"),"SIM","NÃO") -> NÃO | BK96: N/A | BL96: N/A | BM96: N/A | BN96: FINALIZADO | BO96: FINALIZADO | BP96: 46224 | BQ96: FINALIZADO | BR96: AGUARDANDO
A97: 93 | B97: JD. PANTANAL | C97: VILA DA PAZ | D97: 1 | E97: -- | F97: 002/0001/A | G97: VAZIO | I97: PROPRIETÁRIO NÃO RESIDENTE | J97: HENRIQUE DA SILVA ALBUQUERQUE | K97: 38.148.243-1 | L97: 520.509.058-82 | M97: CADASTRADO | N97: INDENIZAÇÃO | O97: N.A | P97: N.A | Q97: N.A | R97: N.A | S97: N.A | T97: N.A | U97: N.A | V97: N.A | W97: N.A | X97: N.A | Y97: N.A | AA97: HENRIQUE DA SILVA ALBUQUERQUE | AB97: 38.148.243-1 | AC97: 520.509.058-82 | AD97: PROPRIETÁRIO NÃO RESIDENTE | AE97: CADASTRADO | AF97: 28264.6 | AG97: 58264.6 | AH97: SIM | AI97: 6014.2025/0007373-4 | AJ97: 158033452 | AK97: 46185 | AL97: 46185 | AM97: 46185 | AN97: 46185 | AO97: 46185 | AP97: 46185 | AR97: =IF(AQ97="SIM","AGUARDANDO CORREÇÃO",IF(AP97<>"","FINALIZADO",IF(AO97<>"","AGUARDANDO ENVIO DTS",IF(AN97<>"","AGUARDANDO ASSINATURA GAB",IF(AM97<>"","AGUARDANDO ASSINATURA CTS",IF(AL97<>"","AGUARDANDO ENVIO ASSINATURA CTS",IF(AK97<>"","AGUARDANDO CONFERÊNCIA",""))))))) -> FINALIZADO | AS97: SEM PENDÊNCIA | AU97: 6014.2026/0004025-0 | AV97: FINALIZADO | AW97: FINALIZADO | AX97: FINALIZADO | AY97: FINALIZADO | AZ97: 46233 | BA97: FINALIZADO | BB97: FINALIZADO | BC97: 46234 | BD97: 46234 | BE97: AGUARDANDO | BF97: LIBERADO DEMOLIÇÃO | BG97: FINALIZADO | BH97: =IFERROR(IF(BD97-KI97=0,"",BD97-AK97),"") -> 49 | BI97: =IF(AND(AH97<>"SIM",AH97="UH"),"AA","INDENIZAÇÃO") -> INDENIZAÇÃO | BJ97: =IF(AND(BD97<>"AGUARDANDO",BD97<>"",N97="AUXÍLIO ALUGUEL ATÉ INDENIZAÇÃO"),"SIM","NÃO") -> NÃO | BK97: N/A | BL97: N/A | BM97: N/A | BN97: FINALIZADO | BO97: FINALIZADO | BP97: 46269 | BQ97: AGUARDANDO PUBLICAÇÃO DOC
A98: 94 | B98: JD. PANTANAL | C98: VILA DA PAZ | D98: 1 | E98: -- | F98: 002/0001/B | G98: OCUPADO | H98: RESIDENCIAL | I98: INQUILINO | J98: MARIA LUCILEY DE JESUS SANTANA | K98: 59.184.381-X | L98: 020.049.635-22 | M98: CADASTRADO | N98: AUXÍLIO ALUGUEL UH | O98: 46126 | P98: 6014.2025/0007513-3 | Q98: 46126 | R98: 46126 | S98: 46136 | T98: 46140 | U98: OK | V98: OK | W98: 46153 | X98: 46182 | Y98: _ | AA98: JOSUEL SANTOS DE JESUS | AB98: 44.860.244.1 | AC98: 236.862.568.27 | AD98: PROPRIETÁRIO NÃO RESIDENTE | AE98: CADASTRADO | AF98: 56124.06 | AG98: 56124.06 | AH98: SIM | AI98: 6014.2025/0007373-4 | AJ98: 158033997 | AK98: 46206 | AL98: 46206 | AM98: 46206 | AN98: 46206 | AO98: 46206 | AP98: 46206 | AR98: =IF(AQ98="SIM","AGUARDANDO CORREÇÃO",IF(AP98<>"","FINALIZADO",IF(AO98<>"","AGUARDANDO ENVIO DTS",IF(AN98<>"","AGUARDANDO ASSINATURA GAB",IF(AM98<>"","AGUARDANDO ASSINATURA CTS",IF(AL98<>"","AGUARDANDO ENVIO ASSINATURA CTS",IF(AK98<>"","AGUARDANDO CONFERÊNCIA",""))))))) -> FINALIZADO | AS98: SEM PENDÊNCIA | AU98: 6014.2026/0005802-8 | AV98: FINALIZADO | AW98: FINALIZADO | AX98: AGUARDANDO CONFERÊNCIA | BF98: OCUPADO | BH98: =IFERROR(IF(BD98-KI98=0,"",BD98-AK98),"") | BI98: =IF(AND(AH98<>"SIM",AH98="UH"),"AA","INDENIZAÇÃO") -> INDENIZAÇÃO | BJ98: =IF(AND(BD98<>"AGUARDANDO",BD98<>"",N98="AUXÍLIO ALUGUEL ATÉ INDENIZAÇÃO"),"SIM","NÃO") -> NÃO
A99: 95 | B99: JD. PANTANAL | C99: VILA DA PAZ | D99: 1 | E99: -- | F99: 002/0001/C | G99: OCUPADO | H99: RESIDENCIAL | I99: INQUILINO | J99: JACQUELYNE DINIZ DE ALMEIDLA | K99: 40.663.607 | L99: 340.910.488-70 | M99: CADASTRADO | N99: AUXÍLIO ALUGUEL UH | O99: 46176 | P99: 6014.2025/0007513-3 | Q99: 46174 | R99: 46176 | S99: 46202 | T99: 46204 | U99: OK | V99: OK | W99: 46223 | AA99: TONI NASCIMENTO DE SOUSA | AB99: 40.511.480.1 | AC99: 371.542.778-74 | AD99: PROPRIETÁRIO NÃO RESIDENTE | AE99: CADASTRADO | AF99: 74383.57 | AG99: 74383.57 | AH99: SIM | AI99: 6014.2025/0007373-4 | AJ99: 158034573 | AK99: 46188 | AL99: 46188 | AM99: 46188 | AN99: 46188 | AO99: 46188 | AP99: 46188 | AR99: =IF(AQ99="SIM","AGUARDANDO CORREÇÃO",IF(AP99<>"","FINALIZADO",IF(AO99<>"","AGUARDANDO ENVIO DTS",IF(AN99<>"","AGUARDANDO ASSINATURA GAB",IF(AM99<>"","AGUARDANDO ASSINATURA CTS",IF(AL99<>"","AGUARDANDO ENVIO ASSINATURA CTS",IF(AK99<>"","AGUARDANDO CONFERÊNCIA",""))))))) -> FINALIZADO | AS99: SEM PENDÊNCIA | AU99: 6014.2026/0004026-9 | AV99: FINALIZADO | AW99: FINALIZADO | AX99: FINALIZADO | AY99: FINALIZADO | AZ99: 46233 | BA99: FINALIZADO | BB99: FINALIZADO | BC99: 46234 | BD99: 46234 | BE99: AGUARDANDO | BF99: LIBERADO DEMOLIÇÃO | BG99: FINALIZADO | BH99: =IFERROR(IF(BD99-KI99=0,"",BD99-AK99),"") -> 46 | BI99: =IF(AND(AH99<>"SIM",AH99="UH"),"AA","INDENIZAÇÃO") -> INDENIZAÇÃO | BJ99: =IF(AND(BD99<>"AGUARDANDO",BD99<>"",N99="AUXÍLIO ALUGUEL ATÉ INDENIZAÇÃO"),"SIM","NÃO") -> NÃO | BK99: N/A | BL99: N/A | BM99: N/A | BN99: FINALIZADO | BO99: FINALIZADO | BP99: 46269 | BQ99: AGUARDANDO PUBLICAÇÃO DOC
A100: 96 | B100: JD. PANTANAL | C100: VILA DA PAZ | D100: 1 | E100: -- | F100: 002/0002/A | G100: OCUPADO | H100: MISTO | I100: INQUILINO | J100: ALEXSANDRA ISABEL BEZERRA | K100: 33.090.188-6 | L100: 277.122.718-52 | M100: CADASTRADO | N100: AUXÍLIO ALUGUEL UH | O100: 46176 | P100: 6014.2025/0007513-3 | Q100: 46174 | R100: 46176 | S100: 46202 | T100: 46204 | U100: OK | V100: OK | W100: 46223 | AA100: KAIQUE ALBUQUERQUE DE SOUSA | AB100: _ | AC100: 536.567.318-29 | AD100: PROPRIETÁRIO NÃO RESIDENTE | AE100: CADASTRADO | AF100: 46888.6 | AG100: 46888.6 | AH100: SIM | AI100: 6014.2025/0007373-4 | AJ100: 158034716 | AK100: 46206 | AL100: 46206 | AM100: 46206 | AN100: 46206 | AO100: 46206 | AP100: 46206 | AR100: =IF(AQ100="SIM","AGUARDANDO CORREÇÃO",IF(AP100<>"","FINALIZADO",IF(AO100<>"","AGUARDANDO ENVIO DTS",IF(AN100<>"","AGUARDANDO ASSINATURA GAB",IF(AM100<>"","AGUARDANDO ASSINATURA CTS",IF(AL100<>"","AGUARDANDO ENVIO ASSINATURA CTS",IF(AK100<>"","AGUARDANDO CONFERÊNCIA",""))))))) -> FINALIZADO | AS100: SEM PENDÊNCIA | AU100: 6014.2026/0005800-1 | AV100: FINALIZADO | AW100: FINALIZADO | AX100: AGUARDANDO CONFERÊNCIA | BF100: OCUPADO | BH100: =IFERROR(IF(BD100-KI100=0,"",BD100-AK100),"") | BI100: =IF(AND(AH100<>"SIM",AH100="UH"),"AA","INDENIZAÇÃO") -> INDENIZAÇÃO | BJ100: =IF(AND(BD100<>"AGUARDANDO",BD100<>"",N100="AUXÍLIO ALUGUEL ATÉ INDENIZAÇÃO"),"SIM","NÃO") -> NÃO
A101: 97 | B101: JD. PANTANAL | C101: TERRA PROMETIDA | D101: 1 | E101: -- | F101: 002/0002/A | G101: OCUPADO | H101: RESIDENCIAL | I101: PROPRIETÁRIO RESIDENTE | J101: MÁRCIA RUBEN DE MACÊDO | K101: 44.872.797-3 | L101: 388.514.338-01 | M101: CADASTRADO | N101: AUXÍLIO ALUGUEL UH | O101: 45986 | P101: 6014.2025/0007513-3 | Q101: 45985 | R101: 45986 | S101: 45987 | T101: 45992 | U101: OK | V101: OK | W101: 45999 | X101: 46000 | Y101: 46017 | AA101: MÁRCIA RUBEN DE MACÊDO | AB101: 44.872.797-3 | AC101: 388.514.338-01 | AD101: PROPRIETÁRIO RESIDENTE | AE101: CADASTRADO | AF101: N.A | AG101: N.A | AH101: UH | AI101: 6014.2025/0007373-4 | AK101: 45979 | AL101: 45979 | AM101: 45979 | AN101: 45979 | AO101: 45979 | AP101: 45979 | AR101: =IF(AQ101="SIM","AGUARDANDO CORREÇÃO",IF(AP101<>"","FINALIZADO",IF(AO101<>"","AGUARDANDO ENVIO DTS",IF(AN101<>"","AGUARDANDO ASSINATURA GAB",IF(AM101<>"","AGUARDANDO ASSINATURA CTS",IF(AL101<>"","AGUARDANDO ENVIO ASSINATURA CTS",IF(AK101<>"","AGUARDANDO CONFERÊNCIA",""))))))) -> FINALIZADO | BE101: 46017 | BF101: DEMOLIDO | BH101: =IFERROR(IF(BD101-KI101=0,"",BD101-AK101),"") | BI101: =IF(AND(AH101<>"SIM",AH101="UH"),"AA","INDENIZAÇÃO") -> AA | BJ101: =IF(AND(BD101<>"AGUARDANDO",BD101<>"",N101="AUXÍLIO ALUGUEL ATÉ INDENIZAÇÃO"),"SIM","NÃO") -> NÃO
A102: 98 | B102: JD. PANTANAL | C102: NOVO HORIZONTE | D102: 1 | E102: -- | F102: 002/0002/A | G102: CONSTRUÇÃO | H102: CONSTRUÇÃO | I102: PROPRIETÁRIO NÃO RESIDENTE | J102: CLEMENS MARTINS DA CRUZ | K102: -- | L102: 142.323.228/33 | M102: CADASTRADO | N102: INDENIZAÇÃO | O102: N.A | P102: N.A | Q102: N.A | R102: N.A | S102: N.A | T102: N.A | U102: N.A | V102: N.A | W102: N.A | X102: N.A | AA102: CLEMENS MARTINS DA CRUZ | AB102: -- | AC102: 142.323.228/33 | AD102: PROPRIETÁRIO NÃO RESIDENTE | AE102: CADASTRADO | AF102: 3074.65 | AG102: 3074.65 | AH102: SIM | AI102: 6014.2025/0007373-4 | AJ102: 151545344 | AK102: 46086 | AL102: 46086 | AM102: 46086 | AN102: 46086 | AO102: 46086 | AP102: 46086 | AR102: =IF(AQ102="SIM","AGUARDANDO CORREÇÃO",IF(AP102<>"","FINALIZADO",IF(AO102<>"","AGUARDANDO ENVIO DTS",IF(AN102<>"","AGUARDANDO ASSINATURA GAB",IF(AM102<>"","AGUARDANDO ASSINATURA CTS",IF(AL102<>"","AGUARDANDO ENVIO ASSINATURA CTS",IF(AK102<>"","AGUARDANDO CONFERÊNCIA",""))))))) -> FINALIZADO | AS102: SEM PENDÊNCIA | AU102: 6014.2026/0002211-2 | AV102: FINALIZADO | AW102: FINALIZADO | AX102: FINALIZADO | AY102: FINALIZADO | AZ102: 46128 | BA102: FINALIZADO | BB102: FINALIZADO | BC102: 46139 | BD102: 46139 | BE102: AGUARDANDO | BF102: LIBERADO DEMOLIÇÃO | BG102: FINALIZADO | BH102: =IFERROR(IF(BD102-KI102=0,"",BD102-AK102),"") -> 53 | BI102: =IF(AND(AH102<>"SIM",AH102="UH"),"AA","INDENIZAÇÃO") -> INDENIZAÇÃO | BJ102: =IF(AND(BD102<>"AGUARDANDO",BD102<>"",N102="AUXÍLIO ALUGUEL ATÉ INDENIZAÇÃO"),"SIM","NÃO") -> NÃO | BK102: N/A | BL102: N/A | BM102: N/A | BN102: FINALIZADO | BO102: FINALIZADO | BP102: 46195 | BQ102: FINALIZADO | BR102: AGUARDANDO
...

Sheet EMAIL
E1: PUBLICAÇÃO DOC
E2: PREVISÃO PAGAMENTO
E3: CONFIRMAÇÃO PAGAMENTO
A5: ÁREA | B5: TRECHO | C5: SELO | D5: TITULAR | E5: CONFIRMAÇÃO PAGAMENTO
A6: JD. PANTANAL | B6: VILA DA PAZ | C6: 007/0002/A | D6: MARCIA SOUZA DA CRUZ | E6: 46267
A7: JD. PANTANAL | B7: SÃO MARTINHO VÁRZEA | C7: 007/0014/A | D7: SANTIELLE RAMONE SOUSA | E7: 46261
A36: JD. PANTANAL | B36: VILA DA PAZ | C36: 002/0016/B | D36: EBER LEITE DA SILVA | E36: 46237
A37: JD. PANTANAL | B37: VILA DA PAZ | C37: 002/0022/C | D37: TAMIRES RODRIGUES BATISTA DA SILVA | E37: 46237
A38: JD. PANTANAL | B38: VILA DA PAZ | C38: 002/0023/A | D38: EMILLYN GONÇALVES CALIXTA DE OLIVEIRA | E38: 46237
A39: JD. PANTANAL | B39: VILA DA PAZ | C39: 002/0024/A | D39: CARLEILTON MACEDO CORREIA | E39: 46237
A40: JD. PANTANAL | B40: VILA DA PAZ | C40: 002/0034/A | D40: JACQUELINE APARECIDA DOS SANTOS | E40: 46237
A41: JD. PANTANAL | B41: SÃO MARTINHO VÁRZEA | C41: 003/0003/A | D41: JACIARA MARIA DE JESUS | E41: 46237
A42: JD. PANTANAL | B42: VILA DA PAZ | C42: 004/0009/A | D42: GESIVALDO BATISTA DE JESUS | E42: 46237
A43: JD. PANTANAL | B43: VILA DA PAZ | C43: 007/0001/B | D43: LUCIA HELENA SANTOS DE MELO | E43: 46237
A60: PARAISÓPOLIS/ANTONICO | C60: 031/0023/B | D60: DANIELA GOMES DE CARVALHO
A61: PARAISÓPOLIS/ANTONICO | C61: 031/0023/C | D61: QUEZIANE ALVES DO NASCIMENTO | E61: N/A
A62: PARAISÓPOLIS/ANTONICO | C62: 031/0026/E | D62: VIVIANE DA SILVA ALMEIDA
A63: PARAISÓPOLIS/ANTONICO | C63: 031/0032/C | D63: ANTONIA CAMILA CASSIMIRO BARBOSA
A64: PARAISÓPOLIS/ANTONICO | C64: 031/0034/E | D64: DAMARYS BRITO DA SILVA | E64: 44877
A65: PARAISÓPOLIS/ANTONICO | C65: 031/0034/H | D65: GISELY MAIANA DE OLIVEIRA SANTOS | E65: 44876
A66: PARAISÓPOLIS/ANTONICO | C66: 031/0034/I | D66: LINA MARIA DA CONCEIÇÃO DE SOUSA | E66: 44910
A67: PARAISÓPOLIS/ANTONICO | C67: 031/0034/K | D67: VÂNIA DE OLIVEIRA | E67: 45148
A68: PARAISÓPOLIS/ANTONICO | C68: 031/0036/A | D68: MARISVALDO DE JESUS PEREIRA | E68: 45065
A69: PARAISÓPOLIS/ANTONICO | C69: 031/0053/A | D69: INGRIDES MORAIS DE ARAUJO FERNANDES | E69: 45049
A70: PARAISÓPOLIS/ANTONICO | C70: 031/0058/B | D70: JOSÉ VALDI DO NASCIMENTO | E70: 45065
A71: PARAISÓPOLIS/ANTONICO | C71: 031/0058/E | D71: VIVIANA SOARES DE PASSOS | E71: 44922
A72: PARAISÓPOLIS/ANTONICO | C72: 031/0058/H | D72: JULIANA SANTOS DA SILVA | E72: 44961
A73: PARAISÓPOLIS/ANTONICO | C73: 031/0078/A | D73: MARCOS VINICIUS ALMEIDA SANTANA SANTOS | E73: N/A
A74: PARAISÓPOLIS/ANTONICO | C74: 031/0078/B | D74: MARIA JOSE JULIÃO DOS SANTOS | E74: 45049
A75: PARAISÓPOLIS/ANTONICO | C75: 033/0029/C | D75: LEONARDO SILVA SANTOS | E75: N/A
A76: PARAISÓPOLIS/ANTONICO | C76: 035/0029/A | D76: DEBORA JESUS DE ARAUJO | E76: N/A
E77: N/A
E78: 44910
E79: 44840
E80: N/A
E81: N/A
E82: 44877
E83: N/A
E84: N/A
E85: 44840
E86: N/A
E87: N/A
E88: N/A
E89: N/A
C90: 025/0006/K | E90: N/A
C91: 025/0006/L | E91: N/A
C92: 025/0007/A | E92: N/A
C93: 025/0007/B | E93: N/A
C94: 025/0007/C | E94: N/A
C95: 025/0007/D
C96: 025/0007/E
C97: 025/0008/A | E97: 45013
C98: 025/0008/B | E98: 45013
C99: 025/0008/C | E99: N/A
C100: 025/0009/A | E100: N/A
C101: 025/0009/B | E101: 44853
C102: 025/0009/C | E102: 44840
C103: 025/0009/D | E103: 44840
C104: 025/0009/E
C105: 025/0009/F | E105: 44910
C106: 025/0009/G | E106: 44961
C107: 025/0009/H | E107: N/A
C108: 025/0009/I | E108: N/A
C109: 025/0009/J | E109: 44862
C110: 025/0009/K | E110: 44877
C111: 025/0010/A | E111: 44840
C112: 025/0010/B | E112: N/A
C113: 025/0010/C | E113: 44840
C114: 025/0010/D | E114: N/A
C115: 025/0010/E | E115: N/A
C116: 025/0010/F | E116: 44840
C117: 025/0010/G | E117: 44877
C118: 025/0010/H | E118: 44890
C119: 025/0010/I | E119: 45013
C120: 025/0011/A | E120: 45013
C121: 025/0012/A
C122: 025/0012/B
C123: 025/0012/C
C124: 025/0012/D
C125: 025/0012/E
C126: 025/0013/A
C127: 025/0013/B
C128: 025/0013/C
C129: 025/0013/D | E129: 45105
C130: 025/0014/A
C131: 025/0014/B
C132: 025/0014/C
C133: 025/0015/A
C134: 025/0015/B | E134: 45105
C135: 025/0016/A
C136: 025/0016/B
C137: 025/0016/C | E137: 45049
C138: 025/0016/D
C139: 025/0016/E
C140: 025/0017/A
C141: 025/0017/B
C142: 025/0018/A
C143: 025/0018/B | E143: 45056
C144: 025/0018/C | E144: 45056
C145: 025/0018/D | E145: 45056
...

Sheet DEPLAN
F4: ÁREA | G4: SELO | H4: PROPRIETÁRIO | I4: CPF | J4: No PROCESSO SEI (INDENIZAÇÃO)
F5: JD. PANTANAL | G5: 001/0001/B | H5: KLEINY SIRLANE DA ROCHA | I5: 260.215.948-43 | J5: 6014.2026/0001975-8
F6: JD. PANTANAL | G6: 001/0002/E | H6: GIVALDO TAVARES DE SOUZA | I6: 093.716.044-09 | J6: 6014.2026/0001162-5
F7: JD. PANTANAL | G7: 002/0001/A | H7: LUANA KELLY DA SILVA SOUSA | I7: 034.502.993-36 | J7: 6014.2026/0001329-6
F8: JD. PANTANAL | G8: 002/0005/A | H8: VANESSA RODRIGUES DA SILVA | I8: 323.751.018-12 | J8: 6014.2026/0001991-0
F9: JD. PANTANAL | G9: 002/0017/A | H9: LUCILENE LUZIA DE OLIVEIRA FIGUEIREDO | I9: 380.912.818-03 | J9: 6014.2026/0000988-4
F10: JD. PANTANAL | G10: 002/0018/D | H10: ERICLES DE SOUSA SILVA | I10: 238.839.638-79 | J10: 6014.2026/0001938-3
F11: JD. PANTANAL | G11: 002/0020/A | H11: MARIA DAS DORES BASTOS DA SILVA | I11: 168.852.338-38 | J11: 6014.2026/0002717-3
F12: JD. PANTANAL | G12: 002/0020/B | H12: REGIANE DE JESUS COSTA MENDES | I12: 604.814.853-41 | J12: 6014.2026/0000596-0
F13: JD. PANTANAL | G13: 002/0030/A | H13: GILSON JOAO DOS SANTOS | I13: 344.392.948-63 | J13: 6014.2026/0001992-8
F14: JD. PANTANAL | G14: 003/0006/A | H14: JADILSON DA SILVA PINHEIRO | I14: 429.143.478-20 | J14: 6014.2026/0000977-9
F15: JD. PANTANAL | G15: 003/0007/A | H15: GEISILANE DIAS DE ANDRADE | I15: 511.269.098-40 | J15: 6014.2026/0001161-7
... F43: JD. PANTANAL | G43: 013/0021/A | H43: GILMARIO DANTAS JACOB | I43: 354.306.028-76 | J43: 6014.2025/0008164-8

Sheet Planilha1
A1: INFORMAÇÕES INICIAIS
A2: ORDEM | B2: ÁREA | C2: TRECHO | D2: SELO | E2: TITULAR | F2: CPF | G2: VALOR AVALIAÇÃO | H2: VALOR INDENIZAÇÃO | I2: Nº SEI LAUDOS AVALIAÇÃO | J2: Nº DOCUMENTO LAUDO | K2: TERMO INDENIZAÇÃO
A3: 447 | B3: JD. PANTANAL | C3: VILA DA PAZ | D3: 008/0002/A | E3: GRACIELE MACIEL DE OLIVEIRA | F3: 115.513.796-51 | G3: 127293.82 | H3: 127293.82 | I3: 6014.2025/0007373-4 | J3: 161832124
B4: JD. PANTANAL | C4: VILA DA PAZ | D4: 002/0014/A | E4: MARIA AGUIAR DA SILVA DOS SANTOS | F4: 334.980.998-76 | G4: 102856.87 | H4: 102856.87 | I4: 6014.2025/0007373-4 | J4: 160376178 | K4: AGUARDANDO ASSINATURA SECRETÁRIO

Sheet VALIDAÇÕES
B3: JD. PANTANAL | C3: SÃO MARTINHO DA VÁRZEA | D3: OCUPADO | E3: RESIDENCIAL | F3: PROPRIETÁRIO NÃO RESIDENTE | G3: INDENIZAÇÃO | H3: CADASTRADO | I3: PROPRIETÁRIO NÃO RESIDENTE | J3: SIM
C4: VILA PAZ | D4: VAZIO | E4: COMERCIAL | F4: PROPRIETÁRIO RESIDENTE | G4: AUXÍLIO ALUGUEL UH | H4: NÃO CADASTRADO | I4: PROPRIETÁRIO RESIDENTE | J4: NÃO
C5: NOVO HORIZONTE | D5: CONSTRUÇÃO | E5: MISTO | F5: INQULINO | G5: VERBA ATENDIMENTO HABITACIONAL
C6: TERRA PROMETIDA | D6: DEMOLIDO | F6: COABITAÇÃO | G6: NÃO TEM DIREITO ATENDIMENTO
C7: CHÁCARA 3 MENINAS | G7: AA ATÉ INDENIZAÇÃO
