Workbook
Name Adequacao_Imovel: 'Listas (não utilizar)'!$G$2:$G$7
Name ADEQUAR: 'Listas (não utilizar)'!$G$2:$G$7
Name Apartamento: 'Listas (não utilizar)'!$D$2:$D$21
Name APROVCEF: #REF!
Name Área: 'Listas (não utilizar)'!$A$2:$A$28
Name AREAS: #REF!
Name AVILDATA: #REF!
Name AVILDATA1: #REF!
Name BARCDATA: #REF!
Name BILBDATA: #REF!
Name Bloco: 'Listas (não utilizar)'!$C$2:$C$16
Name CEF: #REF!
Name CEUTDATA: #REF!
Name Condomínio: 'Listas (não utilizar)'!$B$2:$B$15
Name INDDEMAND: #REF!
Name INDEMAND: #REF!
Name it: #REF!
Name Pendência: 'Listas (não utilizar)'!$I$2:$I$7
Name PLANCCO: #REF!
Name Renúncia: 'Listas (não utilizar)'!$H$2:$H$6
Name RetornoSMADS: '[1]Listas (não utilizar)'!$E$2:$E$3
Name selogo: #REF!
Name selomv: #REF!
Name selos_go: #REF!
Name selosgo: #REF!
Name selosgo1: #REF!
Name SITAH_CAIXA: 'Listas (não utilizar)'!$E$2:$E$9
Name StatusCAIXA: 'Listas (não utilizar)'!$F$2:$F$5
Name TEPROC: #REF!
Name TEPROC1: #REF!

Sheet PRIORIDADES
C3: 2 | D3: PRIORITÁRIO | G3: OCUPADO | H3: RESIDENCIAL | I3: PROPRIETÁRIO NÃO RESIDENTE | M3: CADASTRADO | N3: INDENIZAÇÃO | P3: SIM | R3: SIM | X3: SAQUE PENDENTE | AE3: PROPRIETÁRIO NÃO RESIDENTE | AF3: CADASTRADO | AI3: SIM | AK3: SIM | AM3: COMPLETA | AN3: SEM PENDÊNCIAS
C4: 4 | G4: VAZIO | H4: COMERCIAL | I4: PROPRIETÁRIO RESIDENTE | M4: NÃO CADASTRADO | N4: AUXÍLIO ALUGUEL UH | P4: NÃO | R4: NÃO | AE4: PROPRIETÁRIO RESIDENTE | AF4: NÃO CADASTRADO | AI4: NÃO | AK4: NÃO | AM4: PENDENTE | AN4: FALTA TERMO
G5: OCUPADO/RISCO | H5: MISTO | I5: INQULINO | N5: RECUSA AUXÍLIO ALUGUEL UH | AI5: UH | AK5: N/A | AN5: FALTA DOCS
G6: CONSTRUÇÃO | N6: NÃO TEM DIREITO ATENDIMENTO | AI6: ESTUDO DE CASO | AK6: PENDENTE | AN6: FALTA TERMO E DOCS
G7: DEMOLIDO
G8: DESCARACTERIZADO
G9: DESABADO
AP10: AGUARDANDO
A12: INFORMAÇÕES INICIAIS | P12: INFORMAÇÕES AUXÍLIO ALUGUEL | AB12: INFORMAÇÕES INDENIZAÇÃO | BB12: PROCESSO ATENDIMENTO HABITACIONAL
A13: ORDEM | B13: ÁREA | C13: FASE | D13: TRECHO | E13: PRIORIDADE | F13: SELO | G13: SITUAÇÃO INICIAL IMÓVEL | H13: USO IMÓVEL | I13: SITUAÇÃO DO RESIDENTE | J13: TITULAR | K13: RG | L13: CPF | M13: CADASTRO HABITA SAMPA | N13: OPÇÃO DE ATENDIMENTO HABITACIONAL | O13: ENVIO DADOS | P13: SOLICITAÇÃO AUXÍLIO ALUGUEL ÁREA | Q13: No PROCESSO SEI (AUXÍLIO ALUGUEL) | R13: ANÁLISE DTS CADASTRO + CHECAGEM DUPLO | S13: INSTRUÇÃO PROCESSO SEI DTS | T13: ANÁLISE CTS ASSINATURA GABINETE | U13: DATA PUBLICAÇÃO DIÁRIO OFICIAL | V13: CONFECÇÃO TERMO | W13: ENVIO TERMO CARTÃO | X13: PREVISÃO PAGAMENTO | Y13: DATA SAQUE | Z13: DATA MUDANÇA | AA13: OBSERVAÇÕES AA | AB13: PROPRIETÁRIO | AC13: RG | AD13: CPF | AE13: SITUAÇÃO DO PROPRIETÁRIO | AF13: CADASTRO HABITASAMPA | AG13: VALOR AVALIAÇÃO | AH13: VALOR FINAL INDENIZAÇÃO C/ BONIFICAÇÃO | AI13: ACEITA VALOR INDENIZAÇÃO | AJ13: Nº SEI LAUDOS AVALIAÇÃO | AK13: Nº DOCUMENTO LAUDO | AL13: TERMO INDENIZAÇÃO | AM13: DOSSIÊ | AN13: PENDÊNCIA | AO13: OBSERVAÇÕES INDENIZAÇÃO | AP13: No PROCESSO SEI (INDENIZAÇÃO) | AQ13: INSTRUÇÃO PROCESSO SEI DTS | AR13: ASSINATURA DIRETOR DTS | AS13: ELABORAÇÃO DESPACHO CTS | AT13: ASSINATURA DESPACHO GABINETE | AU13: PUBLICAÇÃO DIÁRIO OFICIAL | AV13: ENCAMINHAMENTO DAF/DIF CTS | AW13: LIBERAÇÃO PAGAMENTO DAF/DIF | AX13: PREVISÃO PAGAMENTO | AY13: DATA PAGAMENTO | AZ13: DATA ENTREGA IMÓVEL | BA13: SITUAÇÃO ATUAL IMÓVEL | BB13: STATUS | BC13: DIAS TOTAIS | BD13: OPÇÃO ATENDIMENTO | BE13: NECESSITA BLOQUEIO AA | BF13: SOLICITAÇÃO BLOQUEIO AA DTS | BG13: DATA SOLICITAÇÃO BLOQUEIO AA | BH13: DATA BLOQUEIO AA | BI13: DESPACHO EXCLUSÃO GABINETE | BJ13: ASSINATURA DESPACHO GABINETE | BK13: PUBLICAÇÃO DOC | BL13: ENCAMINHAMENTO SOLICITAÇÃO EXCLUSÃO DEPLAN | BM13: ENCERRAMENTO PROCESSO DTS
A14: 1 | B14: PARAISÓPOLIS/ANTONICO | C14: 1 | D14: 022 | E14: -- | F14: 022/0004/A | G14: OCUPADO | H14: RESIDENCIAL | I14: PROPRIETÁRIO RESIDENTE | J14: PRISCILA SILVA LIMA | K14: 45.750.631-3 | L14: 230.081.618-04 | M14: CADASTRADO | N14: AUXÍLIO ALUGUEL UH | O14: 45513 | P14: 45513 | Q14: 6014.2021/0000734-3 | R14: 45513 | S14: 45520 | T14: 45520 | U14: 45540 | V14: 45540 | W14: 45540 | X14: 45555 | Y14: 20-set-24 | AB14: PRISCILA SILVA LIMA | AC14: 45.750.631-3 | AD14: 230.081.618-04 | AE14: PROPRIETÁRIO RESIDENTE | AF14: CADASTRADO | AG14: 0 | AH14: 0 | AI14: UH | AJ14: 6014.2024/0003834-1 | AK14: FINALIZADO | AL14: N/A | AM14: N/A | AN14: N/A | AP14: N/A | AQ14: N/A | AR14: N/A | AS14: N/A | AT14: N/A | AU14: N/A | AV14: N/A | AW14: N/A | AZ14: 45596 | BA14: DESCARACTERIZADO | BC14: =IF(AY14-KD14=0,"",AY14-O14) | BD14: =IF(AND(AI14<>"SIM",AI14="UH"),"AA","INDENIZAÇÃO") -> AA | BE14: =IF(AND(AY14<>"AGUARDANDO",AY14<>"",N14="AUXÍLIO ALUGUEL ATÉ INDENIZAÇÃO"),"SIM","NÃO") -> NÃO
A15: 2 | B15: PARAISÓPOLIS/ANTONICO | C15: 1 | D15: 022 | E15: -- | F15: 022/0004/B | G15: OCUPADO | H15: RESIDENCIAL | I15: INQUILINO | J15: LAIANE BELARMINA DOS SANTOS | K15: 50.026.091-6 | L15: 427.190.128-82 | M15: CADASTRADO | N15: AUXÍLIO ALUGUEL UH | O15: 45513 | P15: 45513 | Q15: 6014.2021/0000734-3 | R15: 45513 | S15: 45520 | T15: 45520 | U15: 45540 | V15: 45540 | W15: 45540 | X15: 45555 | Y15: 24-set-24 | AB15: MARLENE BELARMINA DOS SANTOS MACEDO | AC15: 15.439.464-6 | AD15: 470.080755-53 | AE15: PROPRIETÁRIO NÃO RESIDENTE | AF15: CADASTRADO | AG15: 30697.43 | AH15: =AG15 -> 30697.43 | AI15: SIM | AJ15: 6014.2024/0003834-1 | AK15: FINALIZADO | AL15: FINALIZADO | AM15: FINALIZADO | AN15: SEM PENDÊNCIA | AP15: 6014.2024/0004757-0 | AQ15: FINALIZADO | AR15: FINALIZADO | AS15: FINALIZADO | AT15: FINALIZADO | AU15: 45597 | AV15: FINALIZADO | AW15: FINALIZADO | AX15: 45615 | AY15: 45615 | AZ15: 45993 | BA15: LIBERADO DEMOLIÇÃO | BB15: FINALIZADO | BC15: =IF(AY15-KD15=0,"",AY15-O15) -> 102 | BD15: =IF(AND(AI15<>"SIM",AI15="UH"),"AA","INDENIZAÇÃO") -> INDENIZAÇÃO | BE15: =IF(AND(AY15<>"AGUARDANDO",AY15<>"",N15="AUXÍLIO ALUGUEL ATÉ INDENIZAÇÃO"),"SIM","NÃO") -> NÃO | BF15: N/A | BG15: N/A | BH15: N/A | BI15: FINALIZADO | BJ15: FINALIZADO | BK15: 45635 | BL15: FINALIZADO | BM15: FINALIZADO
A16: 3 | B16: PARAISÓPOLIS/ANTONICO | C16: 2 | D16: 024 | E16: URG | F16: 024/0001/A | G16: OCUPADO | H16: RESIDENCIAL | I16: INQUILINO | J16: JORGE OLIVEIRA SANTOS | K16: 20.372.964-10 | L16: 079.557.355-36 | M16: CADASTRADO | N16: AUXÍLIO ALUGUEL UH | O16: 45118 | P16: 45121 | Q16: 6014.2021/0000734-3 | R16: 45125 | S16: 45126 | T16: 45138 | U16: 45142 | V16: 45142 | W16: 45142 | X16: 45159 | Y16: 45160 | Z16: 45202 | AB16: ALEXANDRE RODRIGUES FERREIRA | AC16: 60.410.535-6 | AD16: 075.483.425-51 | AE16: PROPRIETÁRIO NÃO RESIDENTE | AF16: CADASTRADO | AG16: 32907.08 | AH16: 60000 | AI16: SIM | AJ16: 6014.2022/0000163-0 | AK16: FINALIZADO | AL16: FINALIZADO | AM16: FINALIZADO | AN16: SEM PENDÊNCIA | AP16: 6014.2023/0002356-3 | AQ16: FINALIZADO | AR16: FINALIZADO | AS16: FINALIZADO | AT16: FINALIZADO | AU16: 45180 | AV16: FINALIZADO | AW16: FINALIZADO | AX16: 45202 | AY16: 45202 | AZ16: 45202 | BA16: DEMOLIDO | BB16: FINALIZADO | BC16: =IF(AY16-KD16=0,"",AY16-O16) -> 84 | BD16: =IF(AND(AI16<>"SIM",AI16="UH"),"AA","INDENIZAÇÃO") -> INDENIZAÇÃO | BE16: =IF(AND(AY16<>"AGUARDANDO",AY16<>"",N16="AUXÍLIO ALUGUEL ATÉ INDENIZAÇÃO"),"SIM","NÃO") -> NÃO | BF16: N/A | BG16: N/A | BH16: N/A | BI16: FINALIZADO | BJ16: FINALIZADO | BK16: 45303 | BL16: FINALIZADO | BM16: FINALIZADO
A17: 4 | B17: PARAISÓPOLIS/ANTONICO | C17: 2 | D17: 024 | E17: URG | F17: 024/0001/B | G17: OCUPADO | H17: RESIDENCIAL | I17: PROPRIETÁRIO RESIDENTE | J17: GINEILDA MARIA DE LOIOLA | K17: 50.543.365-5 | L17: 918.687.853-00 | M17: CADASTRADO | N17: INDENIZAÇÃO | O17: 44866 | P17: N/A | Q17: N/A | R17: N/A | S17: N/A | T17: N/A | U17: N/A | V17: N/A | W17: N/A | X17: N/A | Y17: N/A | Z17: N/A | AB17: GINEILDA MARIA DE LOIOLA | AC17: 50.543.365-5 | AD17: 918.687.853-00 | AE17: PROPRIETÁRIO RESIDENTE | AF17: CADASTRADO | AG17: =AH17-30000 -> 28361.19 | AH17: 58361.19 | AI17: SIM | AJ17: 6014.2022/0000163-0 | AK17: FINALIZADO | AL17: FINALIZADO | AM17: FINALIZADO | AN17: SEM PENDÊNCIA | AP17: 6014.2022/0003753-8 | AQ17: FINALIZADO | AR17: FINALIZADO | AS17: FINALIZADO | AT17: FINALIZADO | AU17: 44992 | AV17: FINALIZADO | AW17: FINALIZADO | AX17: 45014 | AY17: 45029 | AZ17: 45048 | BA17: DESCARACTERIZADO | BB17: FINALIZADO | BC17: =IF(AY17-KD17=0,"",AY17-O17) -> 163 | BD17: =IF(AND(AI17<>"SIM",AI17="UH"),"AA","INDENIZAÇÃO") -> INDENIZAÇÃO | BE17: =IF(AND(AY17<>"AGUARDANDO",AY17<>"",N17="AUXÍLIO ALUGUEL ATÉ INDENIZAÇÃO"),"SIM","NÃO") -> NÃO | BF17: N/A | BG17: N/A | BH17: N/A | BI17: FINALIZADO | BJ17: FINALIZADO | BK17: 45175 | BL17: FINALIZADO | BM17: FINALIZADO
A18: 5 | B18: PARAISÓPOLIS/ANTONICO | C18: 2 | D18: 024 | E18: URG | F18: 024/0002/A | G18: OCUPADO | H18: RESIDENCIAL | I18: PROPRIETÁRIO RESIDENTE | J18: CARLOS ALBERTO MIRANDA DOS ANJOS | K18: 30.866.690-2 | L18: 073.573.568-92 | M18: CADASTRADO | N18: INDENIZAÇÃO | O18: 44866 | P18: N/A | Q18: N/A | R18: N/A | S18: N/A | T18: N/A | U18: N/A | V18: N/A | W18: N/A | X18: N/A | Y18: N/A | Z18: N/A | AB18: CARLOS ALBERTO MIRANDA DOS ANJOS | AC18: 30.866.690-2 | AD18: 073.573.568-92 | AE18: PROPRIETÁRIO RESIDENTE | AF18: CADASTRADO | AG18: 44132 | AH18: 60000 | AI18: SIM | AJ18: 6014.2022/0000163-0 | AK18: FINALIZADO | AL18: FINALIZADO | AM18: FINALIZADO | AN18: SEM PENDÊNCIA | AP18: 6014.2022/0004094-6 | AQ18: FINALIZADO | AR18: FINALIZADO | AS18: FINALIZADO | AT18: FINALIZADO | AU18: 44992 | AV18: FINALIZADO | AW18: FINALIZADO | AX18: 45014 | AY18: 45014 | AZ18: 45055 | BA18: DESCARACTERIZADO | BB18: FINALIZADO | BC18: =IF(AY18-KD18=0,"",AY18-O18) -> 148 | BD18: =IF(AND(AI18<>"SIM",AI18="UH"),"AA","INDENIZAÇÃO") -> INDENIZAÇÃO | BE18: =IF(AND(AY18<>"AGUARDANDO",AY18<>"",N18="AUXÍLIO ALUGUEL ATÉ INDENIZAÇÃO"),"SIM","NÃO") -> NÃO | BF18: N/A | BG18: N/A | BH18: N/A | BI18: FINALIZADO | BJ18: FINALIZADO | BK18: 45175 | BL18: FINALIZADO | BM18: FINALIZADO
A19: 6 | B19: PARAISÓPOLIS/ANTONICO | C19: 2 | D19: 024 | E19: URG | F19: 024/0002/B | G19: OCUPADO | H19: RESIDENCIAL | I19: PROPRIETÁRIO RESIDENTE | J19: SUZANA DE OLIVEIRA LIMA | K19: 41.043.062-6 | L19: 314.835.758-29 | M19: CADASTRADO | N19: INDENIZAÇÃO | O19: 44866 | P19: N/A | Q19: N/A | R19: N/A | S19: N/A | T19: N/A | U19: N/A | V19: N/A | W19: N/A | X19: N/A | Y19: N/A | Z19: N/A | AB19: SUZANA DE OLIVEIRA LIMA | AC19: 41.043.062-6 | AD19: 314.835.758-29 | AE19: PROPRIETÁRIO RESIDENTE | AF19: CADASTRADO | AG19: 43831.3 | AH19: 60000 | AI19: SIM | AJ19: 6014.2022/0000163-0 | AK19: FINALIZADO | AL19: FINALIZADO | AM19: FINALIZADO | AN19: SEM PENDÊNCIA | AP19: 6014.2022/0004095-4 | AQ19: FINALIZADO | AR19: FINALIZADO | AS19: FINALIZADO | AT19: FINALIZADO | AU19: 44992 | AV19: FINALIZADO | AW19: FINALIZADO | AX19: 45016 | AY19: 45016 | AZ19: 45027 | BA19: DESCARACTERIZADO | BB19: FINALIZADO | BC19: =IF(AY19-KD19=0,"",AY19-O19) -> 150 | BD19: =IF(AND(AI19<>"SIM",AI19="UH"),"AA","INDENIZAÇÃO") -> INDENIZAÇÃO | BE19: =IF(AND(AY19<>"AGUARDANDO",AY19<>"",N19="AUXÍLIO ALUGUEL ATÉ INDENIZAÇÃO"),"SIM","NÃO") -> NÃO | BF19: N/A | BG19: N/A | BH19: N/A | BI19: FINALIZADO | BJ19: FINALIZADO | BK19: 45175 | BL19: FINALIZADO | BM19: FINALIZADO
A20: 7 | B20: PARAISÓPOLIS/ANTONICO | C20: 2 | D20: 024 | E20: URG | F20: 024/0003/A | G20: OCUPADO | H20: RESIDENCIAL | I20: INQUILINO | J20: JOSE MARCIO LOPES DA SILVA | K20: 33.771.900-7 | L20: 622.409.195-15 | M20: CADASTRADO | N20: AUXÍLIO ALUGUEL UH | O20: 45066 | P20: 45457 | Q20: 6014.2021/0000734-3 | R20: 45470 | S20: 45476 | T20: 45509 | U20: 45510 | V20: 45540 | W20: 45540 | X20: 45555 | Y20: 23-set-24 | Z20: 45594 | AA20: AA BLOQUEADO - RECUSA ENTREGAR IMÓVEL | AB20: GRACILIANO SANTOS BISPO | AC20: 54.028.579-1 | AD20: 052.278.458-21 | AE20: PROPRIETÁRIO NÃO RESIDENTE | AF20: CADASTRADO | AG20: =AH20 -> 84686.08 | AH20: 84686.08 | AI20: SIM | AJ20: 6014.2022/0000163-0 | AK20: FINALIZADO | AL20: FINALIZADO | AM20: FINALIZADO | AN20: SEM PENDÊNCIA | AO20: RESISTENTE | AP20: 6014.2024/0002783-8 | AQ20: FINALIZADO | AR20: FINALIZADO | AS20: FINALIZADO | AT20: FINALIZADO | AU20: 45524 | AV20: FINALIZADO | AW20: FINALIZADO | AX20: 45530 | AY20: 45530 | AZ20: 45594 | BA20: DESCARACTERIZADO | BB20: FINALIZADO | BC20: =IF(AY20-KD20=0,"",AY20-O20) -> 464 | BD20: =IF(AND(AI20<>"SIM",AI20="UH"),"AA","INDENIZAÇÃO") -> INDENIZAÇÃO | BE20: =IF(AND(AY20<>"AGUARDANDO",AY20<>"",N20="AUXÍLIO ALUGUEL ATÉ INDENIZAÇÃO"),"SIM","NÃO") -> NÃO | BF20: N/A | BG20: N/A | BH20: N/A | BI20: FINALIZADO | BJ20: FINALIZADO | BK20: 45621 | BL20: FINALIZADO | BM20: AGUARDANDO
A21: 8 | B21: PARAISÓPOLIS/ANTONICO | C21: 2 | D21: 024 | E21: URG | F21: 024/0004/AF1 | G21: OCUPADO | H21: RESIDENCIAL | I21: INQUILINO | J21: ANNE SARAH ALVES LIMA | K21: 68.039.443-6 | L21: 117.438.746-77 | M21: CADASTRADO | N21: AUXÍLIO ALUGUEL UH | O21: 44987 | P21: 44988 | Q21: 6014.2021/0000734-3 | R21: FINALIZADO | S21: 45015 | T21: 45012 | U21: 45014 | V21: 45016 | W21: 45022 | X21: 45036 | Y21: 45049 | Z21: 45173 | AB21: RONILDO SOARES FERREIRA | AC21: 66.250.703-4 | AD21: 911.251.115-34 | AE21: PROPRIETÁRIO NÃO RESIDENTE | AF21: CADASTRADO | AG21: 106215.4 | AH21: 106215.4 | AI21: SIM | AJ21: 6014.2022/0000163-0 | AK21: FINALIZADO | AL21: FINALIZADO | AM21: FINALIZADO | AN21: SEM PENDÊNCIA | AO21: MOBILIZAÇÃO AGENDADA PARA DIA 21/11/2022 | AP21: 6014.2023/0000856-4 | AQ21: FINALIZADO | AR21: FINALIZADO | AS21: FINALIZADO | AT21: FINALIZADO | AU21: 45148 | AV21: FINALIZADO | AW21: FINALIZADO | AX21: 45160 | AY21: 45160 | AZ21: 45173 | BA21: DESCARACTERIZADO | BB21: FINALIZADO | BC21: =IF(AY21-KD21=0,"",AY21-O21) -> 173 | BD21: =IF(AND(AI21<>"SIM",AI21="UH"),"AA","INDENIZAÇÃO") -> INDENIZAÇÃO | BE21: =IF(AND(AY21<>"AGUARDANDO",AY21<>"",N21="AUXÍLIO ALUGUEL ATÉ INDENIZAÇÃO"),"SIM","NÃO") -> NÃO | BF21: N/A | BG21: N/A | BH21: N/A | BI21: FINALIZADO | BJ21: FINALIZADO | BK21: 45303 | BL21: FINALIZADO | BM21: FINALIZADO
A22: 9 | B22: PARAISÓPOLIS/ANTONICO | C22: 2 | D22: 024 | E22: URG | F22: 024/0004/B | G22: OCUPADO | H22: RESIDENCIAL | I22: PROPRIETÁRIO RESIDENTE | J22: EURICO DUTRA DA SILVA | K22: 9.091.805-8 | L22: 679.590.088-68 | M22: CADASTRADO | N22: INDENIZAÇÃO | O22: 44866 | P22: N/A | Q22: N/A | R22: N/A | S22: N/A | T22: N/A | U22: N/A | V22: N/A | W22: N/A | X22: N/A | Y22: N/A | Z22: N/A | AB22: EURICO DUTRA DA SILVA | AC22: 9.091.805-8 | AD22: 679.590.088-68 | AE22: PROPRIETÁRIO RESIDENTE | AF22: CADASTRADO | AG22: 50767.94 | AH22: 60000 | AI22: SIM | AJ22: 6014.2022/0000163-0 | AK22: FINALIZADO | AL22: FINALIZADO | AM22: FINALIZADO | AN22: SEM PENDÊNCIA | AP22: 6014.2023/0000410-0 | AQ22: FINALIZADO | AR22: FINALIZADO | AS22: FINALIZADO | AT22: FINALIZADO | AU22: 45013 | AV22: FINALIZADO | AW22: FINALIZADO | AX22: 45063 | AY22: 45063 | AZ22: 45082 | BA22: DESCARACTERIZADO | BB22: FINALIZADO | BC22: =IF(AY22-KD22=0,"",AY22-O22) -> 197 | BD22: =IF(AND(AI22<>"SIM",AI22="UH"),"AA","INDENIZAÇÃO") -> INDENIZAÇÃO | BE22: =IF(AND(AY22<>"AGUARDANDO",AY22<>"",N22="AUXÍLIO ALUGUEL ATÉ INDENIZAÇÃO"),"SIM","NÃO") -> NÃO | BF22: N/A | BG22: N/A | BH22: N/A | BI22: FINALIZADO | BJ22: FINALIZADO | BK22: 45175 | BL22: FINALIZADO | BM22: FINALIZADO
A23: 10 | B23: PARAISÓPOLIS/ANTONICO | C23: 2 | D23: 024 | E23: 0 | F23: 024/0005/A | G23: OCUPADO | H23: RESIDENCIAL | I23: PROPRIETÁRIO RESIDENTE | J23: JOÃO FELIX DA SILVA FILHO | K23: 34.755.587-1 | L23: 195.477.574-15 | M23: CADASTRADO | N23: AUXÍLIO ALUGUEL UH | O23: 44671 | P23: 44671 | Q23: 6014.2021/0000734-3 | R23: FINALIZADO | S23: FINALIZADO | T23: FINALIZADO | U23: 44693 | V23: 44693 | W23: 44693 | X23: 44713 | Y23: 44718 | Z23: 44725 | AB23: JOÃO FELIX DA SILVA FILHO | AC23: 34.755.587-1 | AD23: 195.477.574-15 | AE23: PROPRIETÁRIO RESIDENTE | AF23: N/A | AG23: 8228.41 | AH23: 38228.41 | AI23: UH | AJ23: 6014.2022/0000163-0 | AK23: N/A | AL23: N/A | AM23: N/A | AN23: N/A | AP23: N/A | AQ23: N/A | AR23: N/A | AS23: N/A | AT23: N/A | AU23: N/A | AV23: N/A | AW23: N/A | AX23: =X23 -> 44713 | AY23: 44713 | AZ23: 44725 | BA23: DEMOLIDO | BB23: FINALIZADO | BC23: =IF(AY23-KD23=0,"",AY23-O23) -> 42 | BD23: =IF(AND(AI23<>"SIM",AI23="UH"),"AA","INDENIZAÇÃO") -> AA | BE23: =IF(AND(AY23<>"AGUARDANDO",AY23<>"",N23="AUXÍLIO ALUGUEL ATÉ INDENIZAÇÃO"),"SIM","NÃO") -> NÃO | BF23: N/A | BG23: N/A | BH23: N/A | BI23: N/A | BJ23: N/A | BK23: N/A | BL23: N/A | BM23: FINALIZADO
A24: 11 | B24: PARAISÓPOLIS/ANTONICO | C24: 2 | D24: 024 | E24: URG | F24: 024/0005/B | G24: OCUPADO | H24: RESIDENCIAL | I24: PROPRIETÁRIO RESIDENTE | J24: MARIA JOSE HONORIO SILVA | K24: 34.808.793-7 | L24: 397.255.294-72 | M24: CADASTRADO | N24: INDENIZAÇÃO | O24: 45610 | P24: N/A | Q24: N/A | R24: N/A | S24: N/A | T24: N/A | U24: N/A | V24: N/A | W24: N/A | X24: N/A | Y24: N/A | Z24: N/A | AA24: RESISTENTE | AB24: MARIA JOSE HONORIO SILVA | AC24: 34.808.793-7 | AD24: 397.255.294-72 | AE24: PROPRIETÁRIO RESIDENTE | AF24: CADASTRADO | AG24: 66528.26 | AH24: 66528.26 | AI24: SIM | AJ24: 6014.2022/0000163-0 | AK24: FINALIZADO | AL24: FINALIZADO | AM24: FINALIZADO | AN24: SEM PENDÊNCIA | AO24: RESISTENTE | AP24: 6014.2024/0005858-0 | AQ24: FINALIZADO | AR24: FINALIZADO | AS24: FINALIZADO | AT24: FINALIZADO | AU24: 45755 | AV24: FINALIZADO | AW24: FINALIZADO | AX24: 45763 | AY24: 45763 | AZ24: 45538 | BA24: DEMOLIDO | BB24: FINALIZADO | BC24: =IF(AY24-KD24=0,"",AY24-O24) -> 153 | BD24: =IF(AND(AI24<>"SIM",AI24="UH"),"AA","INDENIZAÇÃO") -> INDENIZAÇÃO | BE24: =IF(AND(AY24<>"AGUARDANDO",AY24<>"",N24="AUXÍLIO ALUGUEL ATÉ INDENIZAÇÃO"),"SIM","NÃO") -> NÃO | BF24: N/A | BG24: N/A | BH24: N/A | BI24: FINALIZADO | BJ24: FINALIZADO | BK24: 45790 | BL24: FINALIZADO | BM24: AGUARDANDO
A25: 12 | B25: PARAISÓPOLIS/ANTONICO | C25: 2 | D25: 024 | E25: URG | F25: 024/0005/C | G25: OCUPADO | H25: RESIDENCIAL | I25: PROPRIETÁRIO RESIDENTE | J25: DOUGLAS FELIX DA SILVA | K25: 32.702.611-X | L25: 350.792.428-50 | M25: CADASTRADO | N25: AUXÍLIO ALUGUEL UH | O25: 45770 | P25: PENDENTE | Q25: 6014.2021/0000734-3 | R25: FINALIZADO | S25: FINALIZADO | T25: FINALIZADO | U25: FINALIZADO | V25: FINALIZADO | W25: FINALIZADO | X25: 45848 | Y25: 45854 | Z25: 45538 | AB25: DOUGLAS FELIX DA SILVA | AC25: 32.702.611-X | AD25: 350.792.428-50 | AE25: PROPRIETÁRIO RESIDENTE | AF25: CADASTRADO | AG25: 45817.58 | AH25: 60000 | AI25: UH | AJ25: N/A | AK25: N/A | AL25: N/A | AM25: N/A | AN25: N/A | AO25: RESISTENTE | AP25: 6014.2024/0003624-1 | AQ25: N/A | AR25: N/A | AS25: N/A | AT25: N/A | AU25: N/A | AV25: N/A | AW25: N/A | AZ25: 45538 | BA25: DEMOLIDO | BB25: RESISTENTE | BC25: =IF(AY25-KD25=0,"",AY25-O25) | BD25: =IF(AND(AI25<>"SIM",AI25="UH"),"AA","INDENIZAÇÃO") -> AA | BE25: =IF(AND(AY25<>"AGUARDANDO",AY25<>"",N25="AUXÍLIO ALUGUEL ATÉ INDENIZAÇÃO"),"SIM","NÃO") -> NÃO
A26: 13 | B26: PARAISÓPOLIS/ANTONICO | C26: 2 | D26: 024 | E26: URG | F26: 024/0005/D | G26: OCUPADO | H26: COMERCIAL | I26: PROPRIETÁRIO RESIDENTE | J26: MELISSA SANTOS CORREIA | K26: 59.383.150-0 | L26: 550.872.238.69 | M26: CADASTRADO | N26: INDENIZAÇÃO | O26: 45700 | P26: N/A | Q26: N/A | R26: N/A | S26: N/A | T26: N/A | U26: N/A | V26: N/A | W26: N/A | X26: N/A | Y26: N/A | Z26: N/A | AB26: MELISSA SANTOS CORREIA | AC26: 59.383.150-0 | AD26: 550.872.238.69 | AE26: PROPRIETÁRIO RESIDENTE | AF26: CADASTRADO | AG26: 39672.55 | AH26: 60000 | AI26: SIM | AJ26: 6014.2022/0000163-0 | AK26: 149276600 | AL26: FINALIZADO | AM26: FINALIZADO | AN26: SEM PENDÊNCIA | AP26: 6014.2025/0001188-7 | AQ26: FINALIZADO | AR26: FINALIZADO | AS26: FINALIZADO | AT26: FINALIZADO | AU26: 46142 | AV26: FINALIZADO | AW26: FINALIZADO | AX26: 46149 | AY26: 46149 | AZ26: 45538 | BA26: DEMOLIDO | BB26: FINALIZADO | BC26: =IF(AY26-KD26=0,"",AY26-O26) -> 449 | BD26: =IF(AND(AI26<>"SIM",AI26="UH"),"AA","INDENIZAÇÃO") -> INDENIZAÇÃO | BE26: =IF(AND(AY26<>"AGUARDANDO",AY26<>"",N26="AUXÍLIO ALUGUEL ATÉ INDENIZAÇÃO"),"SIM","NÃO") -> NÃO | BF26: N/A | BG26: N/A | BH26: N/A | BI26: FINALIZADO | BJ26: FINALIZADO | BK26: 46224 | BL26: FINALIZADO | BM26: AGUARDANDO
A27: 14 | B27: PARAISÓPOLIS/ANTONICO | C27: 2 | D27: 024 | E27: URG | F27: 024/0005/E | G27: VAZIO | H27: VAZIO | I27: SELO CANCELADO | J27: N/A | K27: N/A | L27: N/A | M27: N/A | N27: SELO CANCELADO | O27: 44866 | P27: N/A | Q27: N/A | R27: N/A | S27: N/A | T27: N/A | U27: N/A | V27: N/A | W27: N/A | X27: N/A | Y27: N/A | Z27: N/A | AB27: N/A | AC27: N/A | AD27: N/A | AE27: SELO CANCELADO | AF27: N/A | AG27: 22351.07 | AH27: 52351.07 | AI27: SELO CANCELADO | AJ27: 6014.2022/0000163-0 | AK27: N/A | AL27: N/A | AM27: N/A | AN27: N/A | AP27: N/A | AQ27: N/A | AR27: N/A | AS27: N/A | AT27: N/A | AU27: N/A | AV27: N/A | AW27: N/A | AX27: N/A | AY27: N/A | AZ27: 44725 | BA27: DEMOLIDO | BB27: FINALIZADO | BC27: N/A | BD27: =IF(AND(AI27<>"SIM",AI27="UH"),"AA","INDENIZAÇÃO") -> INDENIZAÇÃO | BE27: =IF(AND(AY27<>"AGUARDANDO",AY27<>"",N27="AUXÍLIO ALUGUEL ATÉ INDENIZAÇÃO"),"SIM","NÃO") -> NÃO | BF27: N/A | BG27: N/A | BH27: N/A | BI27: N/A | BJ27: N/A | BK27: N/A | BL27: N/A | BM27: FINALIZADO
A28: 15 | B28: PARAISÓPOLIS/ANTONICO | C28: 2 | D28: 024 | E28: URG | F28: 024/0029/A | G28: OCUPADO | H28: RESIDENCIAL | I28: PROPRIETÁRIO RESIDENTE | J28: JANAINA MOTA DA SILVA | K28: 39.155.046-9 | L28: 400.120.708-74 | M28: CADASTRADO | N28: INDENIZAÇÃO | O28: 45083 | P28: N/A | Q28: N/A | R28: N/A | S28: N/A | T28: N/A | U28: N/A | V28: N/A | W28: N/A | X28: N/A | Y28: N/A | Z28: N/A | AB28: JANAINA MOTA DA SILVA | AC28: 39.155.046-9 | AD28: 400.120.708-74 | AE28: PROPRIETÁRIO RESIDENTE | AF28: CADASTRADO | AG28: =AH28-30000 -> 23382.82 | AH28: 53382.82 | AI28: SIM | AJ28: 6014.2022/0000163-0 | AK28: FINALIZADO | AL28: FINALIZADO | AM28: FINALIZADO | AN28: SEM PENDÊNCIA | AP28: 6014.2023/0001968-0 | AQ28: FINALIZADO | AR28: FINALIZADO | AS28: FINALIZADO | AT28: FINALIZADO | AU28: 45278 | AV28: FINALIZADO | AW28: FINALIZADO | AX28: 45295 | AY28: 45300 | AZ28: 45301 | BA28: DESCARACTERIZADO | BB28: FINALIZADO | BC28: =IF(AY28-KD28=0,"",AY28-O28) -> 217 | BD28: =IF(AND(AI28<>"SIM",AI28="UH"),"AA","INDENIZAÇÃO") -> INDENIZAÇÃO | BE28: =IF(AND(AY28<>"AGUARDANDO",AY28<>"",N28="AUXÍLIO ALUGUEL ATÉ INDENIZAÇÃO"),"SIM","NÃO") -> NÃO | BF28: N/A | BG28: N/A | BH28: N/A | BI28: FINALIZADO | BJ28: FINALIZADO | BK28: 45378 | BL28: FINALIZADO | BM28: FINALIZADO
A29: 16 | B29: PARAISÓPOLIS/ANTONICO | C29: 2 | D29: 024 | E29: URG | F29: 024/0029/B | G29: OCUPADO | H29: RESIDENCIAL | I29: PROPRIETÁRIO RESIDENTE | J29: MARIA CHAVES DE CARVALHO | K29: 55.420.866-0 | L29: 018.257.863-13 | M29: CADASTRADO | N29: INDENIZAÇÃO | O29: 45083 | P29: N/A | Q29: N/A | R29: N/A | S29: N/A | T29: N/A | U29: N/A | V29: N/A | W29: N/A | X29: N/A | Y29: N/A | Z29: N/A | AB29: MARIA CHAVES DE CARVALHO | AC29: 55.420.866-0 | AD29: 018.257.863-13 | AE29: PROPRIETÁRIO RESIDENTE | AF29: CADASTRADO | AG29: =AH29-30000 -> 25091.16 | AH29: 55091.16 | AI29: SIM | AJ29: 6014.2022/0000163-0 | AK29: FINALIZADO | AL29: FINALIZADO | AM29: FINALIZADO | AN29: SEM PENDÊNCIA | AP29: 6014.2023/0001973-6 | AQ29: FINALIZADO | AR29: FINALIZADO | AS29: FINALIZADO | AT29: FINALIZADO | AU29: 45224 | AV29: FINALIZADO | AW29: FINALIZADO | AX29: 45243 | AY29: 45243 | AZ29: 45251 | BA29: DESCARACTERIZADO | BB29: FINALIZADO | BC29: =IF(AY29-KD29=0,"",AY29-O29) -> 160 | BD29: =IF(AND(AI29<>"SIM",AI29="UH"),"AA","INDENIZAÇÃO") -> INDENIZAÇÃO | BE29: =IF(AND(AY29<>"AGUARDANDO",AY29<>"",N29="AUXÍLIO ALUGUEL ATÉ INDENIZAÇÃO"),"SIM","NÃO") -> NÃO | BF29: N/A | BG29: N/A | BH29: N/A | BI29: FINALIZADO | BJ29: FINALIZADO | BK29: 45378 | BL29: FINALIZADO | BM29: FINALIZADO
A30: 17 | B30: PARAISÓPOLIS/ANTONICO | C30: 2 | D30: 024 | E30: URG | F30: 024/0030/A | G30: OCUPADO | H30: RESIDENCIAL | I30: PROPRIETÁRIO RESIDENTE | J30: ELAINE DOS SANTOS BOMFIM | K30: 53.408.597-0 | L30: 504.010.478-22 | M30: CADASTRADO | N30: INDENIZAÇÃO | O30: 44844 | P30: N/A | Q30: N/A | R30: N/A | S30: N/A | T30: N/A | U30: N/A | V30: N/A | W30: N/A | X30: N/A | Y30: N/A | Z30: N/A | AB30: ELAINE DOS SANTOS BOMFIM | AC30: 53.408.597-0 | AD30: 504.010.478-22 | AE30: PROPRIETÁRIO RESIDENTE | AF30: CADASTRADO | AG30: 33285.94 | AH30: 60000 | AI30: SIM | AJ30: 6014.2022/0000163-0 | AK30: FINALIZADO | AL30: FINALIZADO | AM30: FINALIZADO | AN30: SEM PENDÊNCIA | AO30: RECUSA ENTREGAR IMÓVEL | AP30: 6014.2022/0003314-1 | AQ30: FINALIZADO | AR30: FINALIZADO | AS30: FINALIZADO | AT30: FINALIZADO | AU30: 44869 | AV30: FINALIZADO | AW30: FINALIZADO | AX30: 44887 | AY30: 44887 | AZ30: 45031 | BA30: DESCARACTERIZADO | BB30: FINALIZADO | BC30: =IF(AY30-KD30=0,"",AY30-O30) -> 43 | BD30: =IF(AND(AI30<>"SIM",AI30="UH"),"AA","INDENIZAÇÃO") -> INDENIZAÇÃO | BE30: =IF(AND(AY30<>"AGUARDANDO",AY30<>"",N30="AUXÍLIO ALUGUEL ATÉ INDENIZAÇÃO"),"SIM","NÃO") -> NÃO | BF30: N/A | BG30: N/A | BH30: N/A | BI30: FINALIZADO | BJ30: FINALIZADO | BK30: 45057 | BL30: FINALIZADO | BM30: FINALIZADO
A31: 18 | B31: PARAISÓPOLIS/ANTONICO | C31: 2 | D31: 024 | E31: 0 | F31: 024/0030/B | G31: OCUPADO | H31: RESIDENCIAL | I31: PROPRIETÁRIO RESIDENTE | J31: OSMAR DOS SANTOS SOUSA | K31: 22.697.907-6 | L31: 134.831.788-48 | M31: CADASTRADO | N31: AUXÍLIO ALUGUEL ATÉ INDENIZAÇÃO | O31: 44844 | P31: 44671 | Q31: 6013.2022/0004909-3 | R31: FINALIZADO | S31: FINALIZADO | T31: FINALIZADO | U31: 44693 | V31: 44698 | W31: 44698 | X31: 44713 | Y31: 44719 | Z31: 44748 | AA31: BLOQUEADO - POR PAGAMENTO DE INDENIZAÇÃO | AB31: OSMAR DOS SANTOS SOUSA | AC31: 22.697.907-6 | AD31: 134.831.788-48 | AE31: PROPRIETÁRIO RESIDENTE | AF31: CADASTRADO | AG31: 20968.45 | AH31: 50968.45 | AI31: SIM | AJ31: 6014.2022/0000163-0 | AK31: FINALIZADO | AL31: FINALIZADO | AM31: FINALIZADO | AN31: SEM PENDÊNCIA | AP31: 6014.2022/0003318-4 | AQ31: FINALIZADO | AR31: FINALIZADO | AS31: FINALIZADO | AT31: FINALIZADO | AU31: 44869 | AV31: FINALIZADO | AW31: FINALIZADO | AX31: 44888 | AY31: 44888 | AZ31: 44748 | BA31: DESCARACTERIZADO | BB31: FINALIZADO | BC31: =IF(AY31-KD31=0,"",AY31-O31) -> 44 | BD31: =IF(AND(AI31<>"SIM",AI31="UH"),"AA","INDENIZAÇÃO") -> INDENIZAÇÃO | BE31: =IF(AND(AY31<>"AGUARDANDO",AY31<>"",N31="AUXÍLIO ALUGUEL ATÉ INDENIZAÇÃO"),"SIM","NÃO") -> SIM | BF31: FINALIZADO | BG31: 44916 | BH31: 44916 | BI31: FINALIZADO | BJ31: FINALIZADO | BK31: 45057 | BL31: FINALIZADO | BM31: FINALIZADO
A32: 19 | B32: PARAISÓPOLIS/ANTONICO | C32: 2 | D32: 024 | E32: URG | F32: 024/0031/A | G32: OCUPADO | H32: RESIDENCIAL | I32: PROPRIETÁRIO RESIDENTE | J32: GEREMIAS DA SILVA CHAVES | K32: 50.671.906-6 | L32: 451.881.958-60 | M32: CADASTRADO | N32: INDENIZAÇÃO | O32: 44844 | P32: N/A | Q32: N/A | R32: N/A | S32: N/A | T32: N/A | U32: N/A | V32: N/A | W32: N/A | X32: N/A | Y32: N/A | Z32: N/A | AB32: GEREMIAS DA SILVA CHAVES | AC32: 50.671.906-6 | AD32: 451.881.958-60 | AE32: PROPRIETÁRIO RESIDENTE | AF32: CADASTRADO | AG32: 18391.36 | AH32: 48391.36 | AI32: SIM | AJ32: 6014.2022/0000163-0 | AK32: FINALIZADO | AL32: FINALIZADO | AM32: FINALIZADO | AN32: SEM PENDÊNCIA | AP32: 6014.2022/0003319-2 | AQ32: FINALIZADO | AR32: FINALIZADO | AS32: FINALIZADO | AT32: FINALIZADO | AU32: 44869 | AV32: FINALIZADO | AW32: FINALIZADO | AX32: 45020 | AY32: 45020 | AZ32: 45026 | BA32: DESCARACTERIZADO | BB32: FINALIZADO | BC32: =IF(AY32-KD32=0,"",AY32-O32) -> 176 | BD32: =IF(AND(AI32<>"SIM",AI32="UH"),"AA","INDENIZAÇÃO") -> INDENIZAÇÃO | BE32: =IF(AND(AY32<>"AGUARDANDO",AY32<>"",N32="AUXÍLIO ALUGUEL ATÉ INDENIZAÇÃO"),"SIM","NÃO") -> NÃO | BF32: N/A | BG32: N/A | BH32: N/A | BI32: FINALIZADO | BJ32: FINALIZADO | BK32: 45175 | BL32: FINALIZADO | BM32: FINALIZADO
A33: 20 | B33: PARAISÓPOLIS/ANTONICO | C33: 2 | D33: 024 | E33: URG | F33: 024/0031/B | G33: OCUPADO | H33: RESIDENCIAL | I33: INQUILINO | J33: ANDRELY CARVALHO DE CASTRO | K33: 52.022.971-X | L33: 069.650.965-27 | M33: CADASTRADO | N33: AUXÍLIO ALUGUEL UH | O33: 44844 | P33: 44844 | Q33: 6014.2021/0000734-3 | R33: FINALIZADO | S33: FINALIZADO | T33: FINALIZADO | U33: 44859 | V33: 44859 | W33: 44859 | X33: 44875 | Y33: 44875 | Z33: 44875 | AB33: FRANCISCA MARIA ALCANTARA CHAVES | AC33: 50.671.326-X | AD33: 841.759.073-00 | AE33: PROPRIETÁRIO NÃO RESIDENTE | AF33: CADASTRADO | AG33: 21948.03 | AH33: 51948.03 | AI33: SIM | AJ33: 6014.2022/0000163-0 | AK33: FINALIZADO | AL33: FINALIZADO | AM33: FINALIZADO | AN33: SEM PENDÊNCIA | AP33: 6014.2022/0003489-0 | AQ33: FINALIZADO | AR33: FINALIZADO | AS33: FINALIZADO | AT33: FINALIZADO | AU33: 44889 | AV33: FINALIZADO | AW33: FINALIZADO | AX33: 44604 | AY33: 44604 | AZ33: 44922 | BA33: DESCARACTERIZADO | BB33: FINALIZADO | BC33: =IF(AY33-KD33=0,"",AY33-O33) -> -240 | BD33: =IF(AND(AI33<>"SIM",AI33="UH"),"AA","INDENIZAÇÃO") -> INDENIZAÇÃO | BE33: =IF(AND(AY33<>"AGUARDANDO",AY33<>"",N33="AUXÍLIO ALUGUEL ATÉ INDENIZAÇÃO"),"SIM","NÃO") -> NÃO | BF33: N/A | BG33: N/A | BH33: N/A | BI33: FINALIZADO | BJ33: FINALIZADO | BK33: 45057 | BL33: FINALIZADO | BM33: FINALIZADO
A34: 21 | B34: PARAISÓPOLIS/ANTONICO | C34: 2 | D34: 024 | E34: URG | F34: 024/0031/C | G34: OCUPADO | H34: RESIDENCIAL | I34: PROPRIETÁRIO RESIDENTE | J34: ANTONIO FRANCISCO CHAVES | K34: 54.896.484-1 | L34: 482.205.903-00 | M34: CADASTRADO | N34: INDENIZAÇÃO | O34: 44788 | P34: N/A | Q34: N/A | R34: N/A | S34: N/A | T34: N/A | U34: N/A | V34: N/A | W34: N/A | X34: N/A | Y34: N/A | Z34: N/A | AB34: ANTONIO FRANCISCO CHAVES | AC34: 54.896.484-1 | AD34: 482.205.903-00 | AE34: PROPRIETÁRIO RESIDENTE | AF34: CADASTRADO | AG34: 36299.56 | AH34: 60000 | AI34: SIM | AJ34: 6014.2022/0000163-0 | AK34: FINALIZADO | AL34: FINALIZADO | AM34: FINALIZADO | AN34: SEM PENDÊNCIA | AP34: 6014.2022/0003413-0 | AQ34: FINALIZADO | AR34: FINALIZADO | AS34: FINALIZADO | AT34: FINALIZADO | AU34: 44877 | AV34: FINALIZADO | AW34: FINALIZADO | AX34: 44894 | AY34: 44894 | AZ34: 44933 | BA34: DESCARACTERIZADO | BB34: FINALIZADO | BC34: =IF(AY34-KD34=0,"",AY34-O34) -> 106 | BD34: =IF(AND(AI34<>"SIM",AI34="UH"),"AA","INDENIZAÇÃO") -> INDENIZAÇÃO | BE34: =IF(AND(AY34<>"AGUARDANDO",AY34<>"",N34="AUXÍLIO ALUGUEL ATÉ INDENIZAÇÃO"),"SIM","NÃO") -> NÃO | BF34: N/A | BG34: N/A | BH34: N/A | BI34: FINALIZADO | BJ34: FINALIZADO | BK34: 45057 | BL34: FINALIZADO | BM34: FINALIZADO
A35: 22 | B35: PARAISÓPOLIS/ANTONICO | C35: 2 | D35: 024 | E35: URG | F35: 024/0031/D | G35: OCUPADO | H35: RESIDENCIAL | I35: PROPRIETÁRIO RESIDENTE | J35: JOSINEIA RIBEIRO SANTANA | K35: 33.299.250-0 | L35: 284.739.748-59 | M35: CADASTRADO | N35: INDENIZAÇÃO | O35: 44844 | P35: N/A | Q35: N/A | R35: N/A | S35: N/A | T35: N/A | U35: N/A | V35: N/A | W35: N/A | X35: N/A | Y35: N/A | Z35: N/A | AB35: JOSINEIA RIBEIRO SANTANA | AC35: 33.299.250-0 | AD35: 284.739.748-59 | AE35: PROPRIETÁRIO RESIDENTE | AF35: CADASTRADO | AG35: 17885.25 | AH35: 47885.25 | AI35: SIM | AJ35: 6014.2022/0000163-0 | AK35: FINALIZADO | AL35: FINALIZADO | AM35: FINALIZADO | AN35: SEM PENDÊNCIA | AP35: 6014.2022/0003286-2 | AQ35: FINALIZADO | AR35: FINALIZADO | AS35: FINALIZADO | AT35: FINALIZADO | AU35: 44869 | AV35: FINALIZADO | AW35: FINALIZADO | AX35: 44886 | AY35: 44887 | AZ35: 44890 | BA35: DESCARACTERIZADO | BB35: FINALIZADO | BC35: =IF(AY35-KD35=0,"",AY35-O35) -> 43 | BD35: =IF(AND(AI35<>"SIM",AI35="UH"),"AA","INDENIZAÇÃO") -> INDENIZAÇÃO | BE35: =IF(AND(AY35<>"AGUARDANDO",AY35<>"",N35="AUXÍLIO ALUGUEL ATÉ INDENIZAÇÃO"),"SIM","NÃO") -> NÃO | BF35: N/A | BG35: N/A | BH35: N/A | BI35: FINALIZADO | BJ35: FINALIZADO | BK35: 45057 | BL35: FINALIZADO | BM35: FINALIZADO
A36: 23 | B36: PARAISÓPOLIS/ANTONICO | C36: 2 | D36: 024 | E36: URG | F36: 024/0031/E | G36: OCUPADO | H36: RESIDENCIAL | I36: PROPRIETÁRIO RESIDENTE | J36: MARIA DO SOCORRO SILVA MENDES | K36: 36.581.031-9 | L36: 503.853.993-91 | M36: CADASTRADO | N36: AUXÍLIO ALUGUEL UH | O36: 44866 | P36: 44844 | Q36: 6014.2021/0000734-3 | R36: FINALIZADO | S36: FINALIZADO | T36: FINALIZADO | U36: 44859 | V36: FINALIZADO | W36: 44859 | X36: 44875 | Y36: 44881 | Z36: 44881 | AB36: MARIA DO SOCORRO SILVA MENDES | AC36: 36.581.031-9 | AD36: 503.853.993-91 | AE36: PROPRIETÁRIO RESIDENTE | AF36: N/A | AG36: 17331.66 | AH36: 47331.66 | AI36: UH | AJ36: 6014.2022/0000163-0 | AK36: N/A | AL36: N/A | AM36: N/A | AN36: N/A | AP36: N/A | AQ36: N/A | AR36: N/A | AS36: N/A | AT36: N/A | AU36: N/A | AV36: N/A | AW36: N/A | AX36: 44875 | AY36: 44881 | AZ36: 44881 | BA36: DESCARACTERIZADO | BB36: FINALIZADO | BC36: =IF(AY36-KD36=0,"",AY36-O36) -> 15 | BD36: =IF(AND(AI36<>"SIM",AI36="UH"),"AA","INDENIZAÇÃO") -> AA | BE36: =IF(AND(AY36<>"AGUARDANDO",AY36<>"",N36="AUXÍLIO ALUGUEL ATÉ INDENIZAÇÃO"),"SIM","NÃO") -> NÃO | BF36: N/A | BG36: N/A | BH36: N/A | BI36: N/A | BJ36: N/A | BK36: N/A | BL36: N/A | BM36: FINALIZADO
A37: 24 | B37: PARAISÓPOLIS/ANTONICO | C37: 2 | D37: 024 | E37: URG | F37: 024/0032/A | G37: OCUPADO | H37: RESIDENCIAL | I37: PROPRIETÁRIO RESIDENTE | J37: VANDERLEI SILVA PEREIRA | K37: 49.464.277-4 | L37: 388.374.528-61 | M37: CADASTRADO | N37: INDENIZAÇÃO | O37: 44844 | P37: N/A | Q37: N/A | R37: N/A | S37: N/A | T37: N/A | U37: N/A | V37: N/A | W37: N/A | X37: N/A | Y37: N/A | Z37: N/A | AB37: VANDERLEI SILVA PEREIRA | AC37: 49.464.277-4 | AD37: 388.374.528-61 | AE37: PROPRIETÁRIO RESIDENTE | AF37: CADASTRADO | AG37: 9670.04 | AH37: 39670.04 | AI37: SIM | AJ37: 6014.2022/0000163-0 | AK37: FINALIZADO | AL37: FINALIZADO | AM37: FINALIZADO | AN37: SEM PENDÊNCIA | AP37: 6014.2022/0003320-6 | AQ37: FINALIZADO | AR37: FINALIZADO | AS37: FINALIZADO | AT37: FINALIZADO | AU37: 44869 | AV37: FINALIZADO | AW37: FINALIZADO | AX37: 44886 | AY37: 44887 | AZ37: 44894 | BA37: DESCARACTERIZADO | BB37: FINALIZADO | BC37: =IF(AY37-KD37=0,"",AY37-O37) -> 43 | BD37: =IF(AND(AI37<>"SIM",AI37="UH"),"AA","INDENIZAÇÃO") -> INDENIZAÇÃO | BE37: =IF(AND(AY37<>"AGUARDANDO",AY37<>"",N37="AUXÍLIO ALUGUEL ATÉ INDENIZAÇÃO"),"SIM","NÃO") -> NÃO | BF37: N/A | BG37: N/A | BH37: N/A | BI37: FINALIZADO | BJ37: FINALIZADO | BK37: 45057 | BL37: FINALIZADO | BM37: FINALIZADO
A38: 25 | B38: PARAISÓPOLIS/ANTONICO | C38: 2 | D38: 024 | E38: URG | F38: 024/0035/A | G38: OCUPADO | H38: RESIDENCIAL | I38: PROPRIETÁRIO RESIDENTE | J38: MARIA DAS GRAÇAS DIAS DE MORAES | K38: 27.670.236-0 | L38: 186.997.498-05 | M38: CADASTRADO | N38: AUXÍLIO ALUGUEL ATÉ INDENIZAÇÃO | O38: 44788 | P38: 45042 | Q38: 6014.2021/0000734-3 | R38: 45068 | S38: 45068 | T38: 45070 | U38: 45076 | V38: 45125 | W38: 45125 | X38: 45159 | Y38: 45160 | Z38: 45040 | AA38: MUNÍCIPE RECEBERÁ 4 MESES DE AA PELA CONSTRUTORA PARA DESOCUPAR IMÓVEL | AB38: MARIA DAS GRAÇAS DIAS DE MORAES | AC38: 27.670.236-0 | AD38: 186.997.498-05 | AE38: PROPRIETÁRIO RESIDENTE | AF38: CADASTRADO | AG38: =AH38-30000 -> 22249.02 | AH38: 52249.02 | AI38: SIM | AJ38: 6014.2022/0000163-0 | AK38: FINALIZADO | AL38: FINALIZADO | AM38: FINALIZADO | AN38: SEM PENDÊNCIA | AP38: 6014.2023/0004425-0 | AQ38: FINALIZADO | AR38: FINALIZADO | AS38: FINALIZADO | AT38: FINALIZADO | AU38: 45387 | AV38: FINALIZADO | AW38: FINALIZADO | AX38: 45394 | AY38: 45394 | AZ38: 45040 | BA38: DEMOLIDO | BB38: FINALIZADO | BC38: =IF(AY38-KD38=0,"",AY38-O38) -> 606 | BD38: =IF(AND(AI38<>"SIM",AI38="UH"),"AA","INDENIZAÇÃO") -> INDENIZAÇÃO | BE38: =IF(AND(AY38<>"AGUARDANDO",AY38<>"",N38="AUXÍLIO ALUGUEL ATÉ INDENIZAÇÃO"),"SIM","NÃO") -> SIM | BF38: FINALIZADO | BG38: 45421 | BH38: 45421 | BI38: FINALIZADO | BJ38: FINALIZADO | BK38: 45483 | BL38: FINALIZADO | BM38: AGUARDANDO
A39: 26 | B39: PARAISÓPOLIS/ANTONICO | C39: 2 | D39: 024 | E39: 0 | F39: 024/0035/B | G39: OCUPADO | H39: RESIDENCIAL | I39: INQUILINO | J39: BRUNO BEZERRA CUPERTINO | K39: 38.115.309-5 | L39: 487.843.668-93 | M39: CADASTRADO | N39: AUXÍLIO ALUGUEL UH | O39: 44788 | P39: 44746 | Q39: 6014.2021/0000734-3 | R39: FINALIZADO | S39: FINALIZADO | T39: FINALIZADO | U39: 44776 | V39: 44782 | W39: 44782 | X39: 44795 | Y39: 44799 | Z39: 44837 | AB39: CEZAR LOREDO NETTO | AC39: 43.889.739-0 | AD39: 402.384.138-29 | AE39: PROPRIETÁRIO NÃO RESIDENTE | AF39: CADASTRADO | AG39: 30308.12 | AH39: 60000 | AI39: SIM | AJ39: 6014.2022/0000163-0 | AK39: FINALIZADO | AL39: FINALIZADO | AM39: FINALIZADO | AN39: SEM PENDÊNCIA | AP39: 6014.2022/0002870-9 | AQ39: FINALIZADO | AR39: FINALIZADO | AS39: FINALIZADO | AT39: FINALIZADO | AU39: 44840 | AV39: FINALIZADO | AW39: FINALIZADO | AX39: 44852 | AY39: 44852 | AZ39: 44837 | BA39: DESCARACTERIZADO | BB39: FINALIZADO | BC39: =IF(AY39-KD39=0,"",AY39-O39) -> 64 | BD39: =IF(AND(AI39<>"SIM",AI39="UH"),"AA","INDENIZAÇÃO") -> INDENIZAÇÃO | BE39: =IF(AND(AY39<>"AGUARDANDO",AY39<>"",N39="AUXÍLIO ALUGUEL ATÉ INDENIZAÇÃO"),"SIM","NÃO") -> NÃO | BF39: N/A | BG39: N/A | BH39: N/A | BI39: FINALIZADO | BJ39: FINALIZADO | BK39: 45057 | BL39: FINALIZADO | BM39: FINALIZADO
A40: 27 | B40: PARAISÓPOLIS/ANTONICO | C40: 2 | D40: 024 | E40: 0 | F40: 024/0036/A | G40: OCUPADO | H40: RESIDENCIAL | I40: INQUILINO | J40: NAYANE ALVES DE SOUSA | K40: 2846210 | L40: 044.606.643-56 | M40: CADASTRADO | N40: AUXÍLIO ALUGUEL UH | O40: 44844 | P40: 44671 | Q40: 6014.2021/0000734-3 | R40: FINALIZADO | S40: FINALIZADO | T40: FINALIZADO | U40: 44693 | V40: 44693 | W40: 44693 | X40: 44713 | Y40: 44720 | Z40: 44725 | AB40: MARIA DO CARMO APRIGIO | AC40: 37.187.670-9 | AD40: 322.862.768-38 | AE40: PROPRIETÁRIO NÃO RESIDENTE | AF40: CADASTRADO | AG40: 15340.39 | AH40: 45340.39 | AI40: SIM | AJ40: 6014.2022/0000163-0 | AK40: FINALIZADO | AL40: FINALIZADO | AM40: FINALIZADO | AN40: SEM PENDÊNCIA | AP40: 6014.2022/0003634-5 | AQ40: FINALIZADO | AR40: FINALIZADO | AS40: FINALIZADO | AT40: FINALIZADO | AU40: 44816 | AV40: FINALIZADO | AW40: FINALIZADO | AX40: 44914 | AY40: 44914 | AZ40: 44725 | BA40: DEMOLIDO | BB40: FINALIZADO | BC40: =IF(AY40-KD40=0,"",AY40-O40) -> 70 | BD40: =IF(AND(AI40<>"SIM",AI40="UH"),"AA","INDENIZAÇÃO") -> INDENIZAÇÃO | BE40: =IF(AND(AY40<>"AGUARDANDO",AY40<>"",N40="AUXÍLIO ALUGUEL ATÉ INDENIZAÇÃO"),"SIM","NÃO") -> NÃO | BF40: N/A | BG40: N/A | BH40: N/A | BI40: FINALIZADO | BJ40: FINALIZADO | BK40: 45057 | BL40: FINALIZADO | BM40: FINALIZADO
A41: 28 | B41: PARAISÓPOLIS/ANTONICO | C41: 2 | D41: 024 | E41: 0 | F41: 024/0036/B | G41: OCUPADO | H41: RESIDENCIAL | I41: PROPRIETÁRIO RESIDENTE | J41: AILDA NUNES DE OLIVEIRA ARAÚJO | K41: 56.715.594-8 | L41: 458.793.008-38 | M41: CADASTRADO | N41: INDENIZAÇÃO | O41: 44844 | P41: N/A | Q41: N/A | R41: N/A | S41: N/A | T41: N/A | U41: N/A | V41: N/A | W41: N/A | X41: N/A | Y41: N/A | Z41: N/A | AB41: AILDA NUNES DE OLIVEIRA ARAÚJO | AC41: 56.715.594-8 | AD41: 458.793.008-38 | AE41: PROPRIETÁRIO RESIDENTE | AF41: CADASTRADO | AG41: 13501.61 | AH41: 43501.61 | AI41: SIM | AJ41: 6014.2022/0000163-0 | AK41: FINALIZADO | AL41: FINALIZADO | AM41: FINALIZADO | AN41: SEM PENDÊNCIA | AP41: 6014.2022/0003262-5 | AQ41: FINALIZADO | AR41: FINALIZADO | AS41: FINALIZADO | AT41: FINALIZADO | AU41: 44877 | AV41: FINALIZADO | AW41: FINALIZADO | AX41: 44894 | AY41: 44894 | AZ41: 44894 | BA41: DEMOLIDO | BB41: FINALIZADO | BC41: =IF(AY41-KD41=0,"",AY41-O41) -> 50 | BD41: =IF(AND(AI41<>"SIM",AI41="UH"),"AA","INDENIZAÇÃO") -> INDENIZAÇÃO | BE41: =IF(AND(AY41<>"AGUARDANDO",AY41<>"",N41="AUXÍLIO ALUGUEL ATÉ INDENIZAÇÃO"),"SIM","NÃO") -> NÃO | BF41: N/A | BG41: N/A | BH41: N/A | BI41: FINALIZADO | BJ41: FINALIZADO | BK41: 45057 | BL41: FINALIZADO | BM41: FINALIZADO
A42: 29 | B42: PARAISÓPOLIS/ANTONICO | C42: 2 | D42: 024 | E42: URG | F42: 024/0036/C | G42: OCUPADO | H42: RESIDENCIAL | I42: INQUILINO | J42: MARLENE MARIA DE JESUS | K42: 24.816.448-X | L42: 146.680.448-30 | M42: CADASTRADO | N42: AUXÍLIO ALUGUEL UH | O42: 44844 | P42: 44774 | Q42: 6014.2021/0000734-3 | R42: FINALIZADO | S42: FINALIZADO | T42: FINALIZADO | U42: 44813 | V42: 44818 | W42: 44818 | X42: 44837 | Y42: 44841 | Z42: 44873 | AB42: INÊS DE OLIVEIRA | AC42: 55.224.980-4 | AD42: 001.126.885-94 | AE42: PROPRIETÁRIO NÃO RESIDENTE | AF42: CADASTRADO | AG42: 10219.17 | AH42: 40219.17 | AI42: SIM | AJ42: 6014.2022/0000163-0 | AK42: FINALIZADO | AL42: FINALIZADO | AM42: FINALIZADO | AN42: SEM PENDÊNCIA | AP42: 6014.2022/0003332-0 | AQ42: FINALIZADO | AR42: FINALIZADO | AS42: FINALIZADO | AT42: FINALIZADO | AU42: 44877 | AV42: FINALIZADO | AW42: FINALIZADO | AX42: 44894 | AY42: 44894 | AZ42: 44873 | BA42: DEMOLIDO | BB42: FINALIZADO | BC42: =IF(AY42-KD42=0,"",AY42-O42) -> 50 | BD42: =IF(AND(AI42<>"SIM",AI42="UH"),"AA","INDENIZAÇÃO") -> INDENIZAÇÃO | BE42: =IF(AND(AY42<>"AGUARDANDO",AY42<>"",N42="AUXÍLIO ALUGUEL ATÉ INDENIZAÇÃO"),"SIM","NÃO") -> NÃO | BF42: N/A | BG42: N/A | BH42: N/A | BI42: FINALIZADO | BJ42: FINALIZADO | BK42: 45057 | BL42: FINALIZADO | BM42: FINALIZADO
A43: 30 | B43: PARAISÓPOLIS/ANTONICO | C43: 2 | D43: 024 | E43: URG | F43: 024/0036/D | G43: OCUPADO | H43: RESIDENCIAL | I43: PROPRIETÁRIO RESIDENTE | J43: ADAILTON PANTALEÃO DA SILVA | K43: 35.904.704-X | L43: 077.047.244-36 | M43: CADASTRADO | N43: INDENIZAÇÃO | O43: 44844 | P43: N/A | Q43: N/A | R43: N/A | S43: N/A | T43: N/A | U43: N/A | V43: N/A | W43: N/A | X43: N/A | Y43: N/A | Z43: N/A | AB43: ADAILTON PANTALEÃO DA SILVA | AC43: 35.904.704-X | AD43: 077.047.244-36 | AE43: PROPRIETÁRIO RESIDENTE | AF43: CADASTRADO | AG43: 16131.9 | AH43: 46131.9 | AI43: SIM | AJ43: 6014.2022/0000163-0 | AK43: FINALIZADO | AL43: FINALIZADO | AM43: FINALIZADO | AN43: SEM PENDÊNCIA | AP43: 6014.2022/0003263-3 | AQ43: FINALIZADO | AR43: FINALIZADO | AS43: FINALIZADO | AT43: FINALIZADO | AU43: 44867 | AV43: FINALIZADO | AW43: FINALIZADO | AX43: 44886 | AY43: 44887 | AZ43: 44877 | BA43: DEMOLIDO | BB43: FINALIZADO | BC43: =IF(AY43-KD43=0,"",AY43-O43) -> 43 | BD43: =IF(AND(AI43<>"SIM",AI43="UH"),"AA","INDENIZAÇÃO") -> INDENIZAÇÃO | BE43: =IF(AND(AY43<>"AGUARDANDO",AY43<>"",N43="AUXÍLIO ALUGUEL ATÉ INDENIZAÇÃO"),"SIM","NÃO") -> NÃO | BF43: N/A | BG43: N/A | BH43: N/A | BI43: FINALIZADO | BJ43: FINALIZADO | BK43: 45057 | BL43: FINALIZADO | BM43: FINALIZADO
A44: 31 | B44: PARAISÓPOLIS/ANTONICO | C44: 2 | D44: 024 | E44: URG | F44: 024/0037/A | G44: VAZIO | H44: RESIDENCIAL | I44: INQUILINO | J44: EGIDIO PEREIRA DOS SANTOS | K44: 36.778.347-2 | L44: 291.565.258-93 | M44: CADASTRADO | N44: AUXÍLIO ALUGUEL UH | O44: 44788 | P44: 44834 | Q44: 6014.2021/0000734-3 | R44: FINALIZADO | S44: FINALIZADO | T44: FINALIZADO | U44: 44859 | V44: 44859 | W44: 44859 | X44: 44875 | Y44: 44879 | Z44: 44748 | AB44: HELENO ANTÔNIO DE SANTANA | AC44: 11.116.727-9 | AD44: 060.366.028-20 | AE44: PROPRIETÁRIO NÃO RESIDENTE | AF44: CADASTRADO | AG44: 11468.94 | AH44: 41468.94 | AI44: SIM | AJ44: 6014.2022/0000163-0 | AK44: FINALIZADO | AL44: FINALIZADO | AM44: FINALIZADO | AN44: SEM PENDÊNCIA | AP44: 6014.2022/0003352-4 | AQ44: FINALIZADO | AR44: FINALIZADO | AS44: FINALIZADO | AT44: FINALIZADO | AU44: 44877 | AV44: FINALIZADO | AW44: FINALIZADO | AX44: 44917 | AY44: 44917 | AZ44: 44949 | BA44: DEMOLIDO | BB44: FINALIZADO | BC44: =IF(AY44-KD44=0,"",AY44-O44) -> 129 | BD44: =IF(AND(AI44<>"SIM",AI44="UH"),"AA","INDENIZAÇÃO") -> INDENIZAÇÃO | BE44: =IF(AND(AY44<>"AGUARDANDO",AY44<>"",N44="AUXÍLIO ALUGUEL ATÉ INDENIZAÇÃO"),"SIM","NÃO") -> NÃO | BF44: N/A | BG44: N/A | BH44: N/A | BI44: FINALIZADO | BJ44: FINALIZADO | BK44: 45057 | BL44: FINALIZADO | BM44: FINALIZADO
A45: 32 | B45: PARAISÓPOLIS/ANTONICO | C45: 2 | D45: 024 | E45: 0 | F45: 024/0037/B | G45: OCUPADO | H45: RESIDENCIAL | I45: PROPRIETÁRIO RESIDENTE | J45: LAIANE MAIARA DA SILVA | K45: 38.287.969-7 | L45: 238.952.268-82 | M45: CADASTRADO | N45: AUXÍLIO ALUGUEL UH | O45: 44788 | P45: 44788 | Q45: 6014.2021/0000734-3 | R45: FINALIZADO | S45: FINALIZADO | T45: FINALIZADO | U45: 44819 | V45: FINALIZADO | W45: FINALIZADO | X45: 44835 | Y45: 44835 | Z45: 44848 | AB45: LAIANE MAIARA DA SILVA | AC45: 38.287.969-7 | AD45: 238.952.268-82 | AE45: PROPRIETÁRIO RESIDENTE | AF45: N/A | AG45: 5503.89 | AH45: 35503.89 | AI45: UH | AJ45: 6014.2022/0000163-0 | AK45: N/A | AL45: N/A | AM45: N/A | AN45: N/A | AP45: N/A | AQ45: N/A | AR45: N/A | AS45: N/A | AT45: N/A | AU45: N/A | AV45: N/A | AW45: N/A | AX45: =X45 -> 44835 | AY45: =Y45 -> 44835 | AZ45: 44848 | BA45: DEMOLIDO | BB45: FINALIZADO | BC45: =IF(AY45-KD45=0,"",AY45-O45) -> 47 | BD45: =IF(AND(AI45<>"SIM",AI45="UH"),"AA","INDENIZAÇÃO") -> AA | BE45: =IF(AND(AY45<>"AGUARDANDO",AY45<>"",N45="AUXÍLIO ALUGUEL ATÉ INDENIZAÇÃO"),"SIM","NÃO") -> NÃO | BF45: N/A | BG45: N/A | BH45: N/A | BI45: N/A | BJ45: N/A | BK45: N/A | BL45: N/A | BM45: FINALIZADO
A46: 33 | B46: PARAISÓPOLIS/ANTONICO | C46: 2 | D46: 024 | E46: URG | F46: 024/0037/C | G46: OCUPADO | H46: RESIDENCIAL | I46: PROPRIETÁRIO RESIDENTE | J46: LARISSE SUANY DA SILVA | K46: 38.287.961-2 | L46: 502.056.378-17 | M46: CADASTRADO | N46: AUXÍLIO ALUGUEL UH | O46: 44788 | P46: 44748 | Q46: 6014.2021/0000734-3 | R46: FINALIZADO | S46: FINALIZADO | T46: FINALIZADO | U46: 44883 | V46: FINALIZADO | W46: FINALIZADO | X46: 44915 | Y46: 44928 | Z46: 44998 | AB46: LARISSE SUANY DA SILVA | AC46: 38.287.961-2 | AD46: 502.056.378-17 | AE46: PROPRIETÁRIO RESIDENTE | AF46: N/A | AG46: 14753.95 | AH46: 44753.95 | AI46: UH | AJ46: 6014.2022/0000163-0 | AK46: N/A | AL46: N/A | AM46: N/A | AN46: N/A | AP46: N/A | AQ46: N/A | AR46: N/A | AS46: N/A | AT46: N/A | AU46: N/A | AV46: N/A | AW46: N/A | AX46: 44915 | AY46: 44928 | AZ46: 44998 | BA46: DEMOLIDO | BB46: FINALIZADO | BC46: =IF(AY46-KD46=0,"",AY46-O46) -> 140 | BD46: =IF(AND(AI46<>"SIM",AI46="UH"),"AA","INDENIZAÇÃO") -> AA | BE46: =IF(AND(AY46<>"AGUARDANDO",AY46<>"",N46="AUXÍLIO ALUGUEL ATÉ INDENIZAÇÃO"),"SIM","NÃO") -> NÃO | BF46: N/A | BG46: N/A | BH46: N/A | BI46: N/A | BJ46: N/A | BK46: N/A | BL46: N/A | BM46: FINALIZADO
A47: 34 | B47: PARAISÓPOLIS/ANTONICO | C47: 2 | D47: 024 | E47: 0 | F47: 024/0037/D | G47: OCUPADO | H47: RESIDENCIAL | I47: PROPRIETÁRIO RESIDENTE | J47: ANDREIA NERES DA SILVA | K47: 30.831.406-2 | L47: 259.944.988-07 | M47: CADASTRADO | N47: AUXÍLIO ALUGUEL UH | O47: 44671 | P47: 44671 | Q47: 6014.2021/0000734-3 | R47: FINALIZADO | S47: FINALIZADO | T47: FINALIZADO | U47: 44693 | V47: FINALIZADO | W47: FINALIZADO | X47: 44713 | Y47: 44715 | Z47: 44923 | AB47: ANDREIA NERES DA SILVA | AC47: 30.831.406-2 | AD47: 259.944.988-07 | AE47: PROPRIETÁRIO RESIDENTE | AF47: N/A | AG47: 15035.49 | AH47: 45035.49 | AI47: UH | AJ47: 6014.2022/0000163-0 | AK47: N/A | AL47: N/A | AM47: N/A | AN47: N/A | AP47: N/A | AQ47: N/A | AR47: N/A | AS47: N/A | AT47: N/A | AU47: N/A | AV47: N/A | AW47: N/A | AX47: =X47 -> 44713 | AY47: =Y47 -> 44715 | AZ47: 44923 | BA47: DEMOLIDO | BB47: FINALIZADO | BC47: =IF(AY47-KD47=0,"",AY47-O47) -> 44 | BD47: =IF(AND(AI47<>"SIM",AI47="UH"),"AA","INDENIZAÇÃO") -> AA | BE47: =IF(AND(AY47<>"AGUARDANDO",AY47<>"",N47="AUXÍLIO ALUGUEL ATÉ INDENIZAÇÃO"),"SIM","NÃO") -> NÃO | BF47: N/A | BG47: N/A | BH47: N/A | BI47: N/A | BJ47: N/A | BK47: N/A | BL47: N/A | BM47: FINALIZADO
A48: 35 | B48: PARAISÓPOLIS/ANTONICO | C48: 2 | D48: 024 | E48: 0 | F48: 024/0037/E | G48: OCUPADO | H48: RESIDENCIAL | I48: PROPRIETÁRIO RESIDENTE | J48: YAGO NERES DA SILVA LEITE | K48: 53.074.294-9 | L48: 471.941.518-04 | M48: CADASTRADO | N48: AUXÍLIO ALUGUEL UH | O48: 44788 | P48: 44788 | Q48: 6014.2021/0000734-3 | R48: FINALIZADO | S48: FINALIZADO | T48: FINALIZADO | U48: 44805 | V48: FINALIZADO | W48: FINALIZADO | X48: 44470 | Y48: 44495 | Z48: 44799 | AB48: YAGO NERES DA SILVA LEITE | AC48: 53.074.294-9 | AD48: 471.941.518-04 | AE48: PROPRIETÁRIO RESIDENTE | AF48: N/A | AG48: 4464.43 | AH48: 34464.43 | AI48: UH | AJ48: 6014.2022/0000163-0 | AK48: N/A | AL48: N/A | AM48: N/A | AN48: N/A | AP48: N/A | AQ48: N/A | AR48: N/A | AS48: N/A | AT48: N/A | AU48: N/A | AV48: N/A | AW48: N/A | AX48: =X48 -> 44470 | AY48: =Y48 -> 44495 | AZ48: =AY48+2 -> 44497 | BA48: DEMOLIDO | BB48: FINALIZADO | BC48: =IF(AY48-KD48=0,"",AY48-O48) -> -293 | BD48: =IF(AND(AI48<>"SIM",AI48="UH"),"AA","INDENIZAÇÃO") -> AA | BE48: =IF(AND(AY48<>"AGUARDANDO",AY48<>"",N48="AUXÍLIO ALUGUEL ATÉ INDENIZAÇÃO"),"SIM","NÃO") -> NÃO | BF48: N/A | BG48: N/A | BH48: N/A | BI48: N/A | BJ48: N/A | BK48: N/A | BL48: N/A | BM48: FINALIZADO
A49: 36 | B49: PARAISÓPOLIS/ANTONICO | C49: 2 | D49: 024 | E49: URG | F49: 024/0037/F | G49: OCUPADO | H49: RESIDENCIAL | I49: INQUILINO | J49: JOSÉ VALTER DA SILVA | K49: 52.312.019-9 | L49: 357.418.018-70 | M49: CADASTRADO | N49: AUXÍLIO ALUGUEL UH | O49: 44788 | P49: 44788 | Q49: 6014.2021/0000734-3 | R49: FINALIZADO | S49: FINALIZADO | T49: FINALIZADO | U49: 44776 | V49: 44782 | W49: 44782 | X49: 44795 | Y49: 44797 | Z49: 44848 | AB49: ROSILDA MARIA DE JESUS | AC49: 23.398.268-2 | AD49: 165.830.848-48 | AE49: PROPRIETÁRIO NÃO RESIDENTE | AF49: CADASTRADO | AG49: 17824.84 | AH49: 47824.84 | AI49: SIM | AJ49: 6014.2022/0000163-0 | AK49: FINALIZADO | AL49: FINALIZADO | AM49: FINALIZADO | AN49: SEM PENDÊNCIA | AP49: 6014.2022/0003161-0 | AQ49: FINALIZADO | AR49: FINALIZADO | AS49: FINALIZADO | AT49: FINALIZADO | AU49: 44853 | AV49: FINALIZADO | AW49: FINALIZADO | AX49: 44865 | AY49: 44865 | AZ49: =AY49+2 -> 44867 | BA49: DEMOLIDO | BB49: FINALIZADO | BC49: =IF(AY49-KD49=0,"",AY49-O49) -> 77 | BD49: =IF(AND(AI49<>"SIM",AI49="UH"),"AA","INDENIZAÇÃO") -> INDENIZAÇÃO | BE49: =IF(AND(AY49<>"AGUARDANDO",AY49<>"",N49="AUXÍLIO ALUGUEL ATÉ INDENIZAÇÃO"),"SIM","NÃO") -> NÃO | BF49: N/A | BG49: N/A | BH49: N/A | BI49: FINALIZADO | BJ49: FINALIZADO | BK49: 45057 | BL49: FINALIZADO | BM49: FINALIZADO
A50: 37 | B50: PARAISÓPOLIS/ANTONICO | C50: 2 | D50: 024 | E50: 0 | F50: 024/0037/G | G50: OCUPADO | H50: RESIDENCIAL | I50: PROPRIETÁRIO RESIDENTE | J50: THIAGO ROCHA OLIVEIRA | K50: 60.309.651-7 | L50: 027.480.635-54 | M50: CADASTRADO | N50: AUXÍLIO ALUGUEL UH | O50: 44788 | P50: 44718 | Q50: 6014.2021/0000734-3 | R50: FINALIZADO | S50: FINALIZADO | T50: FINALIZADO | U50: 44776 | V50: 44782 | W50: 44782 | X50: 44795 | Y50: 44798 | Z50: 44827 | AA50: REMOÇÃO AGENDADA PARA DIA 23/09/2022 | AB50: THIAGO ROCHA OLIVEIRA | AC50: 60.309.651-7 | AD50: 027.480.635-54 | AE50: PROPRIETÁRIO RESIDENTE | AF50: N/A | AG50: 34852.26 | AH50: 60000 | AI50: UH | AJ50: 6014.2022/0000163-0 | AK50: N/A | AL50: N/A | AM50: N/A | AN50: N/A | AP50: N/A | AQ50: N/A | AR50: N/A | AS50: N/A | AT50: N/A | AU50: N/A | AV50: N/A | AW50: N/A | AX50: =X50 -> 44795 | AY50: =Y50 -> 44798 | AZ50: =AY50+2 -> 44800 | BA50: DEMOLIDO | BB50: FINALIZADO | BC50: =IF(AY50-KD50=0,"",AY50-O50) -> 10 | BD50: =IF(AND(AI50<>"SIM",AI50="UH"),"AA","INDENIZAÇÃO") -> AA | BE50: =IF(AND(AY50<>"AGUARDANDO",AY50<>"",N50="AUXÍLIO ALUGUEL ATÉ INDENIZAÇÃO"),"SIM","NÃO") -> NÃO | BF50: N/A | BG50: N/A | BH50: N/A | BI50: N/A | BJ50: N/A | BK50: N/A | BL50: N/A | BM50: FINALIZADO
A51: 38 | B51: PARAISÓPOLIS/ANTONICO | C51: 2 | D51: 024 | E51: 0 | F51: 024/0038/A | G51: OCUPADO | H51: RESIDENCIAL | I51: PROPRIETÁRIO RESIDENTE | J51: FILIPE JÚNIO SILVA DO NASCIMENTO | K51: 65.319.470-5 | L51: 102.996.774-19 | M51: CADASTRADO | N51: INDENIZAÇÃO | O51: 44788 | P51: N/A | Q51: N/A | R51: N/A | S51: N/A | T51: N/A | U51: N/A | V51: N/A | W51: N/A | X51: N/A | Y51: N/A | Z51: N/A | AB51: FILIPE JÚNIO SILVA DO NASCIMENTO | AC51: 65.319.470-5 | AD51: 102.996.774-19 | AE51: PROPRIETÁRIO RESIDENTE | AF51: CADASTRADO | AG51: 20533.57 | AH51: 50533.57 | AI51: SIM | AJ51: 6014.2022/0000163-0 | AK51: FINALIZADO | AL51: FINALIZADO | AM51: FINALIZADO | AN51: SEM PENDÊNCIA | AP51: 6014.2022/0002739-7 | AQ51: FINALIZADO | AR51: FINALIZADO | AS51: FINALIZADO | AT51: FINALIZADO | AU51: 44840 | AV51: FINALIZADO | AW51: FINALIZADO | AX51: 44865 | AY51: 44865 | AZ51: 44818 | BA51: DEMOLIDO | BB51: FINALIZADO | BC51: =IF(AY51-KD51=0,"",AY51-O51) -> 77 | BD51: =IF(AND(AI51<>"SIM",AI51="UH"),"AA","INDENIZAÇÃO") -> INDENIZAÇÃO | BE51: =IF(AND(AY51<>"AGUARDANDO",AY51<>"",N51="AUXÍLIO ALUGUEL ATÉ INDENIZAÇÃO"),"SIM","NÃO") -> NÃO | BF51: N/A | BG51: N/A | BH51: N/A | BI51: FINALIZADO | BJ51: FINALIZADO | BK51: 45057 | BL51: FINALIZADO | BM51: FINALIZADO
A52: 39 | B52: PARAISÓPOLIS/ANTONICO | C52: 2 | D52: 024 | E52: URG | F52: 024/0039/A | G52: OCUPADO | H52: RESIDENCIAL | I52: INQUILINO | J52: ANGELA DA SILVA PAIXÃO | K52: 63.686.538-1 | L52: 796.422.924-91 | M52: CADASTRADO | N52: AUXÍLIO ALUGUEL UH | O52: 44788 | P52: 44746 | Q52: 6014.2021/0000734-3 | R52: FINALIZADO | S52: FINALIZADO | T52: FINALIZADO | U52: 44776 | V52: 44782 | W52: 44782 | X52: 44795 | Y52: 44803 | Z52: 44901 | AB52: VALDENICE MARIA DA SILVA | AC52: 35.820.402-1 | AD52: 343.363.498-00 | AE52: PROPRIETÁRIO NÃO RESIDENTE | AF52: CADASTRADO | AG52: 45597.77 | AH52: 60000 | AI52: SIM | AJ52: 6014.2022/0000163-0 | AK52: FINALIZADO | AL52: FINALIZADO | AM52: FINALIZADO | AN52: SEM PENDÊNCIA | AP52: 6014.2022/0003157-2 | AQ52: FINALIZADO | AR52: FINALIZADO | AS52: FINALIZADO | AT52: FINALIZADO | AU52: 44869 | AV52: FINALIZADO | AW52: FINALIZADO | AX52: 44886 | AY52: 44887 | AZ52: 44901 | BA52: DESCARACTERIZADO | BB52: FINALIZADO | BC52: =IF(AY52-KD52=0,"",AY52-O52) -> 99 | BD52: =IF(AND(AI52<>"SIM",AI52="UH"),"AA","INDENIZAÇÃO") -> INDENIZAÇÃO | BE52: =IF(AND(AY52<>"AGUARDANDO",AY52<>"",N52="AUXÍLIO ALUGUEL ATÉ INDENIZAÇÃO"),"SIM","NÃO") -> NÃO | BF52: N/A | BG52: N/A | BH52: N/A | BI52: FINALIZADO | BJ52: FINALIZADO | BK52: 45057 | BL52: FINALIZADO | BM52: FINALIZADO
A53: 40 | B53: PARAISÓPOLIS/ANTONICO | C53: 2 | D53: 024 | E53: URG | F53: 024/0039/B | G53: OCUPADO | H53: RESIDENCIAL | I53: PROPRIETÁRIO RESIDENTE | J53: GILBERTO COIMBRA DOS SANTOS | K53: 30.870.786-2 | L53: 278.025.848-92 | M53: CADASTRADO | N53: INDENIZAÇÃO | O53: 44788 | P53: N/A | Q53: N/A | R53: N/A | S53: N/A | T53: N/A | U53: N/A | V53: N/A | W53: N/A | X53: N/A | Y53: N/A | Z53: N/A | AB53: GILBERTO COIMBRA DOS SANTOS | AC53: 30.870.786-2 | AD53: 278.025.848-92 | AE53: PROPRIETÁRIO RESIDENTE | AF53: CADASTRADO | AG53: 63293.12 | AH53: 63293.12 | AI53: SIM | AJ53: 6014.2022/0000163-0 | AK53: FINALIZADO | AL53: FINALIZADO | AM53: FINALIZADO | AN53: SEM PENDÊNCIA | AO53: RECUSA ENTREGAR IMÓVEL | AP53: 6014.2022/0003160-2 | AQ53: FINALIZADO | AR53: FINALIZADO | AS53: FINALIZADO | AT53: FINALIZADO | AU53: 44853 | AV53: FINALIZADO | AW53: FINALIZADO | AX53: 44865 | AY53: 44865 | AZ53: 45082 | BA53: DESCARACTERIZADO | BB53: FINALIZADO | BC53: =IF(AY53-KD53=0,"",AY53-O53) -> 77 | BD53: =IF(AND(AI53<>"SIM",AI53="UH"),"AA","INDENIZAÇÃO") -> INDENIZAÇÃO | BE53: =IF(AND(AY53<>"AGUARDANDO",AY53<>"",N53="AUXÍLIO ALUGUEL ATÉ INDENIZAÇÃO"),"SIM","NÃO") -> NÃO | BF53: N/A | BG53: N/A | BH53: N/A | BI53: FINALIZADO | BJ53: FINALIZADO | BK53: 45057 | BL53: FINALIZADO | BM53: FINALIZADO
A54: 41 | B54: PARAISÓPOLIS/ANTONICO | C54: 2 | D54: 024 | E54: 0 | F54: 024/0040/A | G54: OCUPADO | H54: RESIDENCIAL | I54: PROPRIETÁRIO RESIDENTE | J54: SOLANGE SANTOS DE FREITAS | K54: 62.819.524-2 | L54: 016.016.645-40 | M54: CADASTRADO | N54: AUXÍLIO ALUGUEL UH | O54: 44788 | P54: 44720 | Q54: 6014.2021/0000734-3 | R54: FINALIZADO | S54: FINALIZADO | T54: FINALIZADO | U54: 44776 | V54: FINALIZADO | W54: FINALIZADO | X54: 44866 | Y54: 44876 | Z54: 44848 | AB54: SOLANGE SANTOS DE FREITAS | AC54: 62.819.524-2 | AD54: 016.016.645-40 | AE54: PROPRIETÁRIO RESIDENTE | AF54: N/A | AG54: 23158.23 | AH54: 53158.23 | AI54: UH | AJ54: 6014.2022/0000163-0 | AK54: N/A | AL54: N/A | AM54: N/A | AN54: N/A | AP54: N/A | AQ54: N/A | AR54: N/A | AS54: N/A | AT54: N/A | AU54: N/A | AV54: N/A | AW54: N/A | AX54: 44866 | AY54: 44876 | AZ54: 44848 | BA54: DESCARACTERIZADO | BB54: FINALIZADO | BC54: =IF(AY54-KD54=0,"",AY54-O54) -> 88 | BD54: =IF(AND(AI54<>"SIM",AI54="UH"),"AA","INDENIZAÇÃO") -> AA | BE54: =IF(AND(AY54<>"AGUARDANDO",AY54<>"",N54="AUXÍLIO ALUGUEL ATÉ INDENIZAÇÃO"),"SIM","NÃO") -> NÃO | BF54: N/A | BG54: N/A | BH54: N/A | BI54: N/A | BJ54: N/A | BK54: N/A | BL54: N/A | BM54: FINALIZADO
A55: 42 | B55: PARAISÓPOLIS/ANTONICO | C55: 2 | D55: 024 | E55: 0 | F55: 024/0041/A | G55: OCUPADO | H55: RESIDENCIAL | I55: PROPRIETÁRIO RESIDENTE | J55: LAELSON DOS SANTOS | K55: 53.931.689-1 | L55: 049.591.225-52 | M55: CADASTRADO | N55: AUXÍLIO ALUGUEL ATÉ INDENIZAÇÃO | O55: 44844 | P55: 44642 | Q55: 6013.2022/0004909-3 | R55: FINALIZADO | S55: FINALIZADO | T55: FINALIZADO | U55: 44656 | V55: 44659 | W55: 44659 | X55: 44673 | Y55: 44676 | Z55: 44698 | AA55: EXCLUÍDO | AB55: LAELSON DOS SANTOS | AC55: 53.931.689-1 | AD55: 049.591.225-52 | AE55: PROPRIETÁRIO RESIDENTE | AF55: CADASTRADO | AG55: 5323.66 | AH55: 35323.66 | AI55: SIM | AJ55: 6014.2022/0000163-0 | AK55: FINALIZADO | AL55: FINALIZADO | AM55: FINALIZADO | AN55: SEM PENDÊNCIA | AP55: 6014.2022/0003259-5 | AQ55: FINALIZADO | AR55: FINALIZADO | AS55: FINALIZADO | AT55: FINALIZADO | AU55: 44869 | AV55: FINALIZADO | AW55: FINALIZADO | AX55: 45015 | AY55: 45029 | AZ55: 44698 | BA55: DEMOLIDO | BB55: FINALIZADO | BC55: =IF(AY55-KD55=0,"",AY55-O55) -> 185 | BD55: =IF(AND(AI55<>"SIM",AI55="UH"),"AA","INDENIZAÇÃO") -> INDENIZAÇÃO | BE55: =IF(AND(AY55<>"AGUARDANDO",AY55<>"",N55="AUXÍLIO ALUGUEL ATÉ INDENIZAÇÃO"),"SIM","NÃO") -> SIM | BF55: FINALIZADO | BG55: 45006 | BH55: 45006 | BI55: FINALIZADO | BJ55: FINALIZADO | BK55: 45175 | BL55: FINALIZADO | BM55: FINALIZADO
A56: 43 | B56: PARAISÓPOLIS/ANTONICO | C56: 2 | D56: 024 | E56: 0 | F56: 024/0041/B | G56: OCUPADO | H56: RESIDENCIAL | I56: PROPRIETÁRIO RESIDENTE | J56: SAMILIA VIEIRA SILVA | K56: 36.388.328-9 | L56: 427.660.428-14 | M56: CADASTRADO | N56: AUXÍLIO ALUGUEL ATÉ INDENIZAÇÃO | O56: 44844 | P56: 44642 | Q56: 6013.2022/0004909-3 | R56: FINALIZADO | S56: FINALIZADO | T56: FINALIZADO | U56: 44656 | V56: 44659 | W56: 44659 | X56: 44673 | Y56: 44677 | Z56: 44707 | AA56: BLOQUEADO - POR PAGAMENTO DE INDENIZAÇÃO | AB56: SAMILIA VIEIRA SILVA | AC56: 36.388.328-9 | AD56: 427.660.428-14 | AE56: PROPRIETÁRIO RESIDENTE | AF56: CADASTRADO | AG56: 24682.03 | AH56: 54682.03 | AI56: SIM | AJ56: 6014.2022/0000163-0 | AK56: FINALIZADO | AL56: FINALIZADO | AM56: FINALIZADO | AN56: SEM PENDÊNCIA | AP56: 6014.2022/0003353-2 | AQ56: FINALIZADO | AR56: FINALIZADO | AS56: FINALIZADO | AT56: FINALIZADO | AU56: 44877 | AV56: FINALIZADO | AW56: FINALIZADO | AX56: 44894 | AY56: 44894 | AZ56: 44894 | BA56: DEMOLIDO | BB56: FINALIZADO | BC56: =IF(AY56-KD56=0,"",AY56-O56) -> 50 | BD56: =IF(AND(AI56<>"SIM",AI56="UH"),"AA","INDENIZAÇÃO") -> INDENIZAÇÃO | BE56: =IF(AND(AY56<>"AGUARDANDO",AY56<>"",N56="AUXÍLIO ALUGUEL ATÉ INDENIZAÇÃO"),"SIM","NÃO") -> SIM | BF56: FINALIZADO | BG56: 44916 | BH56: 44916 | BI56: FINALIZADO | BJ56: FINALIZADO | BK56: 45057 | BL56: FINALIZADO | BM56: FINALIZADO
A57: 44 | B57: PARAISÓPOLIS/ANTONICO | C57: 2 | D57: 024 | E57: 0 | F57: 024/0041/C | G57: OCUPADO | H57: RESIDENCIAL | I57: PROPRIETÁRIO RESIDENTE | J57: FRANCISCO JONAS CANDEIRA COSTA | K57: 60460312 | L57: 149.213.438-45 | M57: CADASTRADO | N57: INDENIZAÇÃO | O57: 44788 | P57: N/A | Q57: N/A | R57: N/A | S57: N/A | T57: N/A | U57: N/A | V57: N/A | W57: N/A | X57: N/A | Y57: N/A | Z57: N/A | AB57: FRANCISCO JONAS CANDEIRA COSTA | AC57: 60460312 | AD57: 149.213.438-45 | AE57: PROPRIETÁRIO RESIDENTE | AF57: CADASTRADO | AG57: 31636.85 | AH57: 60000 | AI57: SIM | AJ57: 6014.2022/0000163-0 | AK57: FINALIZADO | AL57: FINALIZADO | AM57: FINALIZADO | AN57: SEM PENDÊNCIA | AP57: 6014.2022/0002844-0 | AQ57: FINALIZADO | AR57: FINALIZADO | AS57: FINALIZADO | AT57: FINALIZADO | AU57: 44842 | AV57: FINALIZADO | AW57: FINALIZADO | AX57: 44855 | AY57: 44855 | AZ57: 44858 | BA57: DEMOLIDO | BB57: FINALIZADO | BC57: =IF(AY57-KD57=0,"",AY57-O57) -> 67 | BD57: =IF(AND(AI57<>"SIM",AI57="UH"),"AA","INDENIZAÇÃO") -> INDENIZAÇÃO | BE57: =IF(AND(AY57<>"AGUARDANDO",AY57<>"",N57="AUXÍLIO ALUGUEL ATÉ INDENIZAÇÃO"),"SIM","NÃO") -> NÃO | BF57: N/A | BG57: N/A | BH57: N/A | BI57: FINALIZADO | BJ57: FINALIZADO | BK57: 45057 | BL57: FINALIZADO | BM57: FINALIZADO
A58: 45 | B58: PARAISÓPOLIS/ANTONICO | C58: 2 | D58: 024 | E58: 0 | F58: 024/0041/D | G58: OCUPADO | H58: RESIDENCIAL | I58: PROPRIETÁRIO RESIDENTE | J58: MARICÉLIA OLIMPIO DE OLIVEIRA | K58: 54.391.914-6 | L58: 104.115.434-82 | M58: CADASTRADO | N58: INDENIZAÇÃO | O58: 44788 | P58: N/A | Q58: N/A | R58: N/A | S58: N/A | T58: N/A | U58: N/A | V58: N/A | W58: N/A | X58: N/A | Y58: N/A | Z58: N/A | AB58: MARICÉLIA OLIMPIO DE OLIVEIRA | AC58: 54.391.914-6 | AD58: 104.115.434-82 | AE58: PROPRIETÁRIO RESIDENTE | AF58: CADASTRADO | AG58: 26954.05 | AH58: 56954.05 | AI58: SIM | AJ58: 6014.2022/0000163-0 | AK58: FINALIZADO | AL58: FINALIZADO | AM58: FINALIZADO | AN58: SEM PENDÊNCIA | AP58: 6014.2022/0002674-9 | AQ58: FINALIZADO | AR58: FINALIZADO | AS58: FINALIZADO | AT58: FINALIZADO | AU58: 44840 | AV58: FINALIZADO | AW58: FINALIZADO | AX58: 45020 | AY58: 45020 | AZ58: 44799 | BA58: DEMOLIDO | BB58: FINALIZADO | BC58: =IF(AY58-KD58=0,"",AY58-O58) -> 232 | BD58: =IF(AND(AI58<>"SIM",AI58="UH"),"AA","INDENIZAÇÃO") -> INDENIZAÇÃO | BE58: =IF(AND(AY58<>"AGUARDANDO",AY58<>"",N58="AUXÍLIO ALUGUEL ATÉ INDENIZAÇÃO"),"SIM","NÃO") -> NÃO | BF58: N/A | BG58: N/A | BH58: N/A | BI58: FINALIZADO | BJ58: FINALIZADO | BK58: 45175 | BL58: FINALIZADO | BM58: FINALIZADO
A59: 46 | B59: PARAISÓPOLIS/ANTONICO | C59: 2 | D59: 024 | E59: 0 | F59: 024/0042/A | G59: OCUPADO | H59: RESIDENCIAL | I59: INQUILINO | J59: EVILENE PEREIRA DA SILVA | K59: 64.602.866-2 | L59: 555.286.192-20 | M59: CADASTRADO | N59: NÃO TEM ATENDIMENTO | O59: 44788 | P59: N/A | Q59: N/A | R59: N/A | S59: N/A | T59: N/A | U59: N/A | V59: N/A | W59: N/A | X59: N/A | Y59: N/A | Z59: N/A | AA59: IDENTIFICADO DUPLO ATENDIMENTO | AB59: AUREO CRUZ DOS SANTOS | AC59: 55.388.279-X | AD59: 063.815.425-19 | AE59: PROPRIETÁRIO NÃO RESIDENTE | AF59: CADASTRADO | AG59: 11753.74 | AH59: 41753.74 | AI59: SIM | AJ59: 6014.2022/0000163-0 | AK59: FINALIZADO | AL59: FINALIZADO | AM59: FINALIZADO | AN59: SEM PENDÊNCIA | AP59: 6014.2022/0002952-7 | AQ59: FINALIZADO | AR59: FINALIZADO | AS59: FINALIZADO | AT59: FINALIZADO | AU59: 44853 | AV59: FINALIZADO | AW59: FINALIZADO | AX59: 44865 | AY59: 44865 | AZ59: 44806 | BA59: DEMOLIDO | BB59: FINALIZADO | BC59: =IF(AY59-KD59=0,"",AY59-O59) -> 77 | BD59: =IF(AND(AI59<>"SIM",AI59="UH"),"AA","INDENIZAÇÃO") -> INDENIZAÇÃO | BE59: =IF(AND(AY59<>"AGUARDANDO",AY59<>"",N59="AUXÍLIO ALUGUEL ATÉ INDENIZAÇÃO"),"SIM","NÃO") -> NÃO | BF59: N/A | BG59: N/A | BH59: N/A | BI59: FINALIZADO | BJ59: FINALIZADO | BK59: 45057 | BL59: FINALIZADO | BM59: FINALIZADO
A60: 47 | B60: PARAISÓPOLIS/ANTONICO | C60: 2 | D60: 024 | E60: 0 | F60: 024/0043/A | G60: OCUPADO | H60: RESIDENCIAL | I60: PROPRIETÁRIO RESIDENTE | J60: KARINA ALVES PEREIRA | K60: 59.908.173-9 | L60: 116.023.464-70 | M60: CADASTRADO | N60: AUXÍLIO ALUGUEL UH | O60: 44866 | P60: 44409 | Q60: 6014.2021/0000734-3 | R60: FINALIZADO | S60: FINALIZADO | T60: FINALIZADO | U60: 44454 | V60: 44454 | W60: 44454 | X60: 44470 | Y60: 44483 | Z60: 44933 | AB60: KARINA ALVES PEREIRA | AC60: 59.908.173-9 | AD60: 116.023.464-70 | AE60: PROPRIETÁRIO RESIDENTE | AF60: N/A | AG60: 0 | AH60: 0 | AI60: UH | AJ60: 6014.2022/0000163-0 | AK60: N/A | AL60: N/A | AM60: N/A | AN60: N/A | AP60: N/A | AQ60: N/A | AR60: N/A | AS60: N/A | AT60: N/A | AU60: N/A | AV60: N/A | AW60: N/A | AX60: =X60 -> 44470 | AY60: =Y60 -> 44483 | AZ60: 44933 | BA60: DEMOLIDO | BB60: FINALIZADO | BC60: =IF(AY60-KD60=0,"",AY60-O60) -> -383 | BD60: =IF(AND(AI60<>"SIM",AI60="UH"),"AA","INDENIZAÇÃO") -> AA | BE60: =IF(AND(AY60<>"AGUARDANDO",AY60<>"",N60="AUXÍLIO ALUGUEL ATÉ INDENIZAÇÃO"),"SIM","NÃO") -> NÃO | BF60: N/A | BG60: N/A | BH60: N/A | BI60: N/A | BJ60: N/A | BK60: N/A | BL60: N/A | BM60: FINALIZADO
A61: 48 | B61: PARAISÓPOLIS/ANTONICO | C61: 2 | D61: 024 | E61: URG | F61: 024/0044/B | G61: OCUPADO | H61: RESIDENCIAL | I61: PROPRIETÁRIO RESIDENTE | J61: VALERIA GOMES DA SILVA | K61: 47.623.224-7 | L61: 368.583.298-03 | M61: CADASTRADO | N61: INDENIZAÇÃO | O61: 44844 | P61: N/A | Q61: N/A | R61: N/A | S61: N/A | T61: N/A | U61: N/A | V61: N/A | W61: N/A | X61: N/A | Y61: N/A | Z61: N/A | AB61: VALERIA GOMES DA SILVA | AC61: 47.623.224-7 | AD61: 368.583.298-03 | AE61: PROPRIETÁRIO RESIDENTE | AF61: CADASTRADO | AG61: 14574.17 | AH61: 44574.17 | AI61: SIM | AJ61: 6014.2022/0000163-0 | AK61: FINALIZADO | AL61: FINALIZADO | AM61: FINALIZADO | AN61: SEM PENDÊNCIA | AP61: 6014.2022/0003715-5 | AQ61: FINALIZADO | AR61: FINALIZADO | AS61: FINALIZADO | AT61: FINALIZADO | AU61: 44961 | AV61: FINALIZADO | AW61: FINALIZADO | AX61: 45015 | AY61: 45015 | AZ61: 45030 | BA61: DESCARACTERIZADO | BB61: FINALIZADO | BC61: =IF(AY61-KD61=0,"",AY61-O61) -> 171 | BD61: =IF(AND(AI61<>"SIM",AI61="UH"),"AA","INDENIZAÇÃO") -> INDENIZAÇÃO | BE61: =IF(AND(AY61<>"AGUARDANDO",AY61<>"",N61="AUXÍLIO ALUGUEL ATÉ INDENIZAÇÃO"),"SIM","NÃO") -> NÃO | BF61: N/A | BG61: N/A | BH61: N/A | BI61: FINALIZADO | BJ61: FINALIZADO | BK61: 45175 | BL61: FINALIZADO | BM61: FINALIZADO
A62: 49 | B62: PARAISÓPOLIS/ANTONICO | C62: 2 | D62: 024 | E62: URG | F62: 024/0044/D | G62: OCUPADO | H62: COMERCIAL | I62: PROPRIETÁRIO RESIDENTE | J62: DANIEL AMORIM DE SOUZA | K62: 44.065.937-1 | L62: 356.360.568-85 | M62: CADASTRADO | N62: INDENIZAÇÃO COMÉRCIO | O62: 44866 | P62: N/A | Q62: N/A | R62: N/A | S62: N/A | T62: N/A | U62: N/A | V62: N/A | W62: N/A | X62: N/A | Y62: N/A | Z62: N/A | AB62: DANIEL AMORIM DE SOUZA | AC62: 44.065.937-1 | AD62: 356.360.568-85 | AE62: PROPRIETÁRIO RESIDENTE | AF62: CADASTRADO | AG62: 14577.78 | AH62: 60000 | AI62: SIM | AJ62: 6014.2022/0000163-0 | AK62: FINALIZADO | AL62: FINALIZADO | AM62: FINALIZADO | AN62: SEM PENDÊNCIA | AO62: CONVOCADO PARA COMPARECER EM 07.11.22 | AP62: 6014.2022/0003984-0 | AQ62: FINALIZADO | AR62: FINALIZADO | AS62: FINALIZADO | AT62: FINALIZADO | AU62: 44922 | AV62: FINALIZADO | AW62: FINALIZADO | AX62: 44924 | AY62: 44924 | AZ62: 44998 | BA62: DESCARACTERIZADO | BB62: FINALIZADO | BC62: =IF(AY62-KD62=0,"",AY62-O62) -> 58 | BD62: =IF(AND(AI62<>"SIM",AI62="UH"),"AA","INDENIZAÇÃO") -> INDENIZAÇÃO | BE62: =IF(AND(AY62<>"AGUARDANDO",AY62<>"",N62="AUXÍLIO ALUGUEL ATÉ INDENIZAÇÃO"),"SIM","NÃO") -> NÃO | BF62: N/A | BG62: N/A | BH62: N/A | BI62: FINALIZADO | BJ62: FINALIZADO | BK62: 45057 | BL62: FINALIZADO | BM62: FINALIZADO
A63: 50 | B63: PARAISÓPOLIS/ANTONICO | C63: 2 | D63: 024 | E63: URG | F63: 024/0044/E | G63: OCUPADO | H63: RESIDENCIAL | I63: PROPRIETÁRIO RESIDENTE | J63: EDIVALDO FERREIRA DA SILVA | K63: 54.522.382-9 | L63: 009.101.878-19 | M63: CADASTRADO | N63: INDENIZAÇÃO | O63: 44860 | P63: N/A | Q63: N/A | R63: N/A | S63: N/A | T63: N/A | U63: N/A | V63: N/A | W63: N/A | X63: N/A | Y63: N/A | Z63: N/A | AB63: EDIVALDO FERREIRA DA SILVA | AC63: 54.522.382-9 | AD63: 009.101.878-19 | AE63: PROPRIETÁRIO RESIDENTE | AF63: CADASTRADO | AG63: 55624.86 | AH63: 60000 | AI63: SIM | AJ63: 6014.2022/0000163-0 | AK63: FINALIZADO | AL63: FINALIZADO | AM63: FINALIZADO | AN63: SEM PENDÊNCIA | AP63: 6014.2022/0003496-2 | AQ63: FINALIZADO | AR63: FINALIZADO | AS63: FINALIZADO | AT63: FINALIZADO | AU63: 44889 | AV63: FINALIZADO | AW63: FINALIZADO | AX63: 44897 | AY63: 44897 | AZ63: 44935 | BA63: DESCARACTERIZADO | BB63: FINALIZADO | BC63: =IF(AY63-KD63=0,"",AY63-O63) -> 37 | BD63: =IF(AND(AI63<>"SIM",AI63="UH"),"AA","INDENIZAÇÃO") -> INDENIZAÇÃO | BE63: =IF(AND(AY63<>"AGUARDANDO",AY63<>"",N63="AUXÍLIO ALUGUEL ATÉ INDENIZAÇÃO"),"SIM","NÃO") -> NÃO | BF63: N/A | BG63: N/A | BH63: N/A | BI63: FINALIZADO | BJ63: FINALIZADO | BK63: 45057 | BL63: FINALIZADO | BM63: FINALIZADO
A64: 51 | B64: PARAISÓPOLIS/ANTONICO | C64: 2 | D64: 024 | E64: 0 | F64: 024/0044/F | G64: OCUPADO | H64: RESIDENCIAL | I64: INQUILINO | J64: KEVIN RODRIGUES BATISTA | K64: 38.761.764-4 | L64: 500.474.248-00 | M64: CADASTRADO | N64: AUXÍLIO ALUGUEL UH | O64: 44788 | P64: 44834 | Q64: 6014.2021/0000734-3 | R64: FINALIZADO | S64: FINALIZADO | T64: FINALIZADO | U64: 44859 | V64: 44859 | W64: 44859 | X64: 44875 | Y64: 44879 | Z64: 44879 | AB64: JOSIVANIA CAVALCANTE SANTOS | AC64: 3958738-0 | AD64: 129.201.765-39 | AE64: PROPRIETÁRIO NÃO RESIDENTE | AF64: CADASTRADO | AG64: 31048.54 | AH64: 60000 | AI64: SIM | AJ64: 6014.2022/0000163-0 | AK64: FINALIZADO | AL64: FINALIZADO | AM64: FINALIZADO | AN64: SEM PENDÊNCIA | AP64: 6014.2022/0002687-0 | AQ64: FINALIZADO | AR64: FINALIZADO | AS64: FINALIZADO | AT64: FINALIZADO | AU64: 44840 | AV64: FINALIZADO | AW64: FINALIZADO | AX64: 44855 | AY64: 44855 | AZ64: 44862 | BA64: DESCARACTERIZADO | BB64: FINALIZADO | BC64: =IF(AY64-KD64=0,"",AY64-O64) -> 67 | BD64: =IF(AND(AI64<>"SIM",AI64="UH"),"AA","INDENIZAÇÃO") -> INDENIZAÇÃO | BE64: =IF(AND(AY64<>"AGUARDANDO",AY64<>"",N64="AUXÍLIO ALUGUEL ATÉ INDENIZAÇÃO"),"SIM","NÃO") -> NÃO | BF64: N/A | BG64: N/A | BH64: N/A | BI64: FINALIZADO | BJ64: FINALIZADO | BK64: 45057 | BL64: FINALIZADO | BM64: FINALIZADO
A65: 52 | B65: PARAISÓPOLIS/ANTONICO | C65: 2 | D65: 024 | E65: URG | F65: 024/0045/A | G65: OCUPADO | H65: RESIDENCIAL | I65: PROPRIETÁRIO RESIDENTE | J65: JOVINA DE JESUS SANTANA | K65: 45.289.205-3 | L65: 252.848.568-99 | M65: CADASTRADO | N65: INDENIZAÇÃO | O65: 45051 | P65: N/A | Q65: N/A | R65: N/A | S65: N/A | T65: N/A | U65: N/A | V65: N/A | W65: N/A | X65: N/A | Y65: N/A | Z65: N/A | AA65: FOI SOLICITADO BLOQUEIO POIS PNR RECUSA INDENIZAÇÃO 19/06/23 DTS Sul - área pediu cancelamento do auxílio aluguel para o munícipe Luiz Claudio de Lima. Não será enviado pagamento até orientação da área. | AB65: JOVINA DE JESUS SANTANA | AC65: 45.289.205-3 | AD65: 252.848.568-99 | AE65: PROPRIETÁRIO RESIDENTE | AF65: CADASTRADO | AG65: 71112.51 | AH65: 71112.51 | AI65: SIM | AJ65: 6014.2022/0000163-0 | AK65: FINALIZADO | AL65: FINALIZADO | AM65: FINALIZADO | AN65: SEM PENDÊNCIA | AO65: RESISTENTE | AP65: 6014.2023/0001445-9 | AQ65: FINALIZADO | AR65: FINALIZADO | AS65: FINALIZADO | AT65: FINALIZADO | AU65: 45587 | AV65: FINALIZADO | AW65: FINALIZADO | AX65: 45590 | AY65: 45590 | AZ65: 45538 | BA65: DEMOLIDO | BB65: FINALIZADO | BC65: =IF(AY65-KD65=0,"",AY65-O65) -> 539 | BD65: =IF(AND(AI65<>"SIM",AI65="UH"),"AA","INDENIZAÇÃO") -> INDENIZAÇÃO | BE65: =IF(AND(AY65<>"AGUARDANDO",AY65<>"",N65="AUXÍLIO ALUGUEL ATÉ INDENIZAÇÃO"),"SIM","NÃO") -> NÃO | BF65: N/A | BG65: N/A | BH65: N/A | BI65: FINALIZADO | BJ65: FINALIZADO | BK65: 45621 | BL65: FINALIZADO | BM65: AGUARDANDO
A66: 53 | B66: PARAISÓPOLIS/ANTONICO | C66: 2 | D66: 024 | E66: URG | F66: 024/0046/A | G66: OCUPADO | H66: RESIDENCIAL | I66: PROPRIETÁRIO RESIDENTE | J66: JOÃO BRASILINO DE SOUSA | K66: 6.595.620-5 | L66: 014.102.728-26 | M66: CADASTRADO | N66: INDENIZAÇÃO | O66: 45539 | P66: N/A | Q66: N/A | R66: N/A | S66: N/A | T66: N/A | U66: N/A | V66: N/A | W66: N/A | X66: N/A | Y66: N/A | Z66: N/A | AB66: JOÃO BRASILINO DE SOUSA | AC66: 6.595.620-5 | AD66: 014.102.728-26 | AE66: PROPRIETÁRIO RESIDENTE | AF66: CADASTRADO | AG66: 100370.59 | AH66: 100370.59 | AI66: SIM | AJ66: 6014.2022/0000163-0 | AK66: FINALIZADO | AL66: FINALIZADO | AM66: FINALIZADO | AN66: SEM PENDÊNCIA | AO66: RESISTENTE | AP66: 6014.2024/0004270-5 | AQ66: FINALIZADO | AR66: FINALIZADO | AS66: FINALIZADO | AT66: FINALIZADO | AU66: 45587 | AV66: FINALIZADO | AW66: FINALIZADO | AX66: 45590 | AY66: 45590 | AZ66: 45538 | BA66: DEMOLIDO | BB66: FINALIZADO | BC66: =IF(AY66-KD66=0,"",AY66-O66) -> 51 | BD66: =IF(AND(AI66<>"SIM",AI66="UH"),"AA","INDENIZAÇÃO") -> INDENIZAÇÃO | BE66: =IF(AND(AY66<>"AGUARDANDO",AY66<>"",N66="AUXÍLIO ALUGUEL ATÉ INDENIZAÇÃO"),"SIM","NÃO") -> NÃO | BF66: N/A | BG66: N/A | BH66: N/A | BI66: FINALIZADO | BJ66: FINALIZADO | BK66: 45621 | BL66: FINALIZADO | BM66: AGUARDANDO
A67: 54 | B67: PARAISÓPOLIS/ANTONICO | C67: 2 | D67: 024 | E67: URG | F67: 024/0047/F | G67: OCUPADO | H67: RESIDENCIAL | I67: PROPRIETÁRIO RESIDENTE | J67: ROSA HELENA DE SOUZA | K67: 29.614.393-5 | L67: 291.466.998-48 | M67: CADASTRADO | N67: RESISTENTE | O67: 44866 | AB67: ROSA HELENA DE SOUZA | AC67: 29.614.393-5 | AD67: 291.466.998-48 | AE67: PROPRIETÁRIO RESIDENTE | AG67: 0 | AH67: 60000 | AI67: RESISTENTE | AJ67: 6014.2022/0000163-0 | AK67: FINALIZADO | AO67: RESISTENTE | AQ67: RESISTENTE | BA67: OCUPADO | BB67: RESISTENTE | BC67: =IF(AY67-KD67=0,"",AY67-O67) | BD67: =IF(AND(AI67<>"SIM",AI67="UH"),"AA","INDENIZAÇÃO") -> INDENIZAÇÃO | BE67: =IF(AND(AY67<>"AGUARDANDO",AY67<>"",N67="AUXÍLIO ALUGUEL ATÉ INDENIZAÇÃO"),"SIM","NÃO") -> NÃO
A68: 55 | B68: PARAISÓPOLIS/ANTONICO | C68: 2 | D68: 024 | E68: URG | F68: 024/0049/A | G68: OCUPADO | H68: RESIDENCIAL | I68: INQUILINO | J68: IGOR SOUZA DE JESUS | K68: 50.515.164-9 | L68: 465.224.188-78 | M68: CADASTRADO | N68: AUXÍLIO ALUGUEL UH | O68: 44866 | P68: 44889 | Q68: 6014.2021/0000734-3 | R68: FINALIZADO | S68: FINALIZADO | T68: FINALIZADO | U68: 44903 | V68: 44903 | W68: 44903 | X68: 44958 | Y68: 44958 | Z68: 45022 | AB68: EDEMAR HENRIQUE DE ARAUJO | AC68: 62.811.140-X | AD68: 029.786.275-81 | AE68: PROPRIETÁRIO NÃO RESIDENTE | AF68: CADASTRADO | AG68: =AH68-30000 -> 26550.43 | AH68: 56550.43 | AI68: SIM | AJ68: 6014.2022/0000163-0 | AK68: FINALIZADO | AL68: FINALIZADO | AM68: FINALIZADO | AN68: SEM PENDÊNCIA | AP68: 6014.2022/0003756-2 | AQ68: FINALIZADO | AR68: FINALIZADO | AS68: FINALIZADO | AT68: FINALIZADO | AU68: 44992 | AV68: FINALIZADO | AW68: FINALIZADO | AX68: 45016 | AY68: 45016 | AZ68: 45022 | BA68: DESCARACTERIZADO | BB68: FINALIZADO | BC68: =IF(AY68-KD68=0,"",AY68-O68) -> 150 | BD68: =IF(AND(AI68<>"SIM",AI68="UH"),"AA","INDENIZAÇÃO") -> INDENIZAÇÃO | BE68: =IF(AND(AY68<>"AGUARDANDO",AY68<>"",N68="AUXÍLIO ALUGUEL ATÉ INDENIZAÇÃO"),"SIM","NÃO") -> NÃO | BF68: N/A | BG68: N/A | BH68: N/A | BI68: FINALIZADO | BJ68: FINALIZADO | BK68: 45175 | BL68: FINALIZADO | BM68: FINALIZADO
A69: 56 | B69: PARAISÓPOLIS/ANTONICO | C69: 2 | D69: 024 | E69: URG | F69: 024/0049/B | G69: OCUPADO | H69: RESIDENCIAL | I69: INQUILINO | J69: LARISSA BELARMINA DOS SANTOS | K69: 53.287.750-0 | L69: 466.311.188-24 | M69: CADASTRADO | N69: AUXÍLIO ALUGUEL UH | O69: 44866 | P69: 44889 | Q69: 6014.2021/0000734-3 | R69: FINALIZADO | S69: FINALIZADO | T69: FINALIZADO | U69: 44903 | V69: 44903 | W69: 44903 | X69: 44958 | Y69: 44959 | Z69: 45080 | AB69: EDNA DE JESUS SANTOS | AC69: 33.968.651-5 | AD69: 494.068.988-37 | AE69: PROPRIETÁRIO NÃO RESIDENTE | AF69: CADASTRADO | AG69: 0 | AH69: 60000 | AI69: SIM | AJ69: 6014.2022/0000163-0 | AK69: FINALIZADO | AL69: FINALIZADO | AM69: FINALIZADO | AN69: SEM PENDÊNCIA | AP69: 6014.2022/0003755-4 | AQ69: FINALIZADO | AR69: FINALIZADO | AS69: FINALIZADO | AT69: FINALIZADO | AU69: 45013 | AV69: FINALIZADO | AW69: FINALIZADO | AX69: 45068 | AY69: 45068 | AZ69: 45080 | BA69: DESCARACTERIZADO | BB69: FINALIZADO | BC69: =IF(AY69-KD69=0,"",AY69-O69) -> 202 | BD69: =IF(AND(AI69<>"SIM",AI69="UH"),"AA","INDENIZAÇÃO") -> INDENIZAÇÃO | BE69: =IF(AND(AY69<>"AGUARDANDO",AY69<>"",N69="AUXÍLIO ALUGUEL ATÉ INDENIZAÇÃO"),"SIM","NÃO") -> NÃO | BF69: N/A | BG69: N/A | BH69: N/A | BI69: FINALIZADO | BJ69: FINALIZADO | BK69: 45175 | BL69: FINALIZADO | BM69: FINALIZADO
A70: 57 | B70: PARAISÓPOLIS/ANTONICO | C70: 2 | D70: 024 | E70: URG | F70: 024/0049/C | G70: OCUPADO | H70: RESIDENCIAL | I70: INQUILINO | J70: DAIANE VENANCIO DA SILVA | K70: 39.750.401-9 | L70: 495.178.508-08 | M70: CADASTRADO | N70: AUXÍLIO ALUGUEL UH | O70: 44889 | P70: 44889 | Q70: 6014.2021/0000734-3 | R70: FINALIZADO | S70: FINALIZADO | T70: FINALIZADO | U70: 44903 | V70: 44903 | W70: 44903 | X70: 44958 | Y70: 44958 | Z70: 45078 | AB70: RAIMUNDO DOS SANTOS | AC70: 54.440.038-0 | AD70: 012.867.045-29 | AE70: PROPRIETÁRIO NÃO RESIDENTE | AF70: CADASTRADO | AG70: 0 | AH70: 60000 | AI70: SIM | AJ70: 6014.2022/0000163-0 | AK70: FINALIZADO | AL70: FINALIZADO | AM70: FINALIZADO | AN70: SEM PENDÊNCIA | AP70: 6014.2022/0003757-0 | AQ70: FINALIZADO | AR70: FINALIZADO | AS70: FINALIZADO | AT70: FINALIZADO | AU70: 45013 | AV70: FINALIZADO | AW70: FINALIZADO | AX70: 45054 | AY70: 45054 | AZ70: 45078 | BA70: DESCARACTERIZADO | BB70: FINALIZADO | BC70: =IF(AY70-KD70=0,"",AY70-O70) -> 165 | BD70: =IF(AND(AI70<>"SIM",AI70="UH"),"AA","INDENIZAÇÃO") -> INDENIZAÇÃO | BE70: =IF(AND(AY70<>"AGUARDANDO",AY70<>"",N70="AUXÍLIO ALUGUEL ATÉ INDENIZAÇÃO"),"SIM","NÃO") -> NÃO | BF70: N/A | BG70: N/A | BH70: N/A | BI70: FINALIZADO | BJ70: FINALIZADO | BK70: 45175 | BL70: FINALIZADO | BM70: FINALIZADO
A71: 58 | B71: PARAISÓPOLIS/ANTONICO | C71: 2 | D71: 024 | E71: URG | F71: 024/0050/A | G71: OCUPADO | H71: RESIDENCIAL | I71: PROPRIETÁRIO RESIDENTE | J71: VITORIA CAROLINA SAMPAIO DE CASTRO | K71: 38.760.115-6 | L71: 351.584.248-96 | M71: CADASTRADO | N71: AUXÍLIO ALUGUEL UH | O71: 44866 | P71: 44889 | Q71: 6014.2021/0000734-3 | R71: FINALIZADO | S71: FINALIZADO | T71: FINALIZADO | U71: 44903 | V71: 44903 | W71: 44903 | X71: 44958 | Y71: 44957 | Z71: 44987 | AB71: VITORIA CAROLINA SAMPAIO DE CASTRO | AC71: 38.760.115-6 | AD71: 351.584.248-96 | AE71: PROPRIETÁRIO RESIDENTE | AF71: N/A | AG71: 29985.92 | AH71: 59985.92 | AI71: UH | AJ71: 6014.2022/0000163-0 | AK71: N/A | AL71: N/A | AM71: N/A | AN71: N/A | AP71: N/A | AQ71: N/A | AR71: N/A | AS71: N/A | AT71: N/A | AU71: N/A | AV71: N/A | AW71: N/A | AX71: 44958 | AY71: 44957 | AZ71: 44987 | BA71: DESCARACTERIZADO | BB71: FINALIZADO | BC71: =IF(AY71-KD71=0,"",AY71-O71) -> 91 | BD71: =IF(AND(AI71<>"SIM",AI71="UH"),"AA","INDENIZAÇÃO") -> AA | BE71: =IF(AND(AY71<>"AGUARDANDO",AY71<>"",N71="AUXÍLIO ALUGUEL ATÉ INDENIZAÇÃO"),"SIM","NÃO") -> NÃO | BF71: N/A | BG71: N/A | BH71: N/A | BI71: N/A | BJ71: N/A | BK71: N/A | BL71: N/A | BM71: FINALIZADO
A72: 59 | B72: PARAISÓPOLIS/ANTONICO | C72: 2 | D72: 024 | E72: URG | F72: 024/0050/B | G72: OCUPADO | H72: RESIDENCIAL | I72: PROPRIETÁRIO RESIDENTE | J72: ALEX ALVES BARBOSA | K72: 34.903.366-3 | L72: 301.093.958-24 | M72: CADASTRADO | N72: INDENIZAÇÃO | O72: 44866 | P72: N/A | Q72: N/A | R72: N/A | S72: N/A | T72: N/A | U72: N/A | V72: N/A | W72: N/A | X72: N/A | Y72: N/A | Z72: N/A | AB72: ALEX ALVES BARBOSA | AC72: 34.903.366-3 | AD72: 301.093.958-24 | AE72: PROPRIETÁRIO RESIDENTE | AF72: CADASTRADO | AG72: 74330.51 | AH72: 74330.51 | AI72: SIM | AJ72: 6014.2022/0000163-0 | AK72: FINALIZADO | AL72: FINALIZADO | AM72: FINALIZADO | AN72: SEM PENDÊNCIA | AP72: 6014.2023/0000323-6 | AQ72: FINALIZADO | AR72: FINALIZADO | AS72: FINALIZADO | AT72: FINALIZADO | AU72: 45013 | AV72: FINALIZADO | AW72: FINALIZADO | AX72: 45063 | AY72: 45063 | AZ72: 45100 | BA72: DESCARACTERIZADO | BB72: FINALIZADO | BC72: =IF(AY72-KD72=0,"",AY72-O72) -> 197 | BD72: =IF(AND(AI72<>"SIM",AI72="UH"),"AA","INDENIZAÇÃO") -> INDENIZAÇÃO | BE72: =IF(AND(AY72<>"AGUARDANDO",AY72<>"",N72="AUXÍLIO ALUGUEL ATÉ INDENIZAÇÃO"),"SIM","NÃO") -> NÃO | BF72: N/A | BG72: N/A | BH72: N/A | BI72: FINALIZADO | BJ72: FINALIZADO | BK72: 45175 | BL72: FINALIZADO | BM72: FINALIZADO
A73: 60 | B73: PARAISÓPOLIS/ANTONICO | C73: 2 | D73: 024 | E73: 0 | F73: 024/0050/C | G73: OCUPADO | H73: RESIDENCIAL | I73: PROPRIETÁRIO RESIDENTE | J73: CLAUDETE SAMPAIO DE SOUZA | K73: 35196426 | L73: 293.995.958-70 | M73: CADASTRADO | N73: AUXÍLIO ALUGUEL UH | O73: 44866 | P73: 44671 | Q73: 6014.2021/0000734-3 | R73: FINALIZADO | S73: FINALIZADO | T73: FINALIZADO | U73: 44693 | V73: 44693 | W73: 44693 | X73: 44713 | Y73: 44715 | Z73: 44890 | AB73: CLAUDETE SAMPAIO DE SOUZA | AC73: 35196426 | AD73: 293.995.958-70 | AE73: PROPRIETÁRIO RESIDENTE | AF73: N/A | AG73: 34569.16 | AH73: 60000 | AI73: UH | AJ73: 6014.2022/0000163-0 | AK73: N/A | AL73: N/A | AM73: N/A | AN73: N/A | AP73: N/A | AQ73: N/A | AR73: N/A | AS73: N/A | AT73: N/A | AU73: N/A | AV73: N/A | AW73: N/A | AX73: =X73 -> 44713 | AY73: =Y73 -> 44715 | AZ73: 44890 | BA73: DEMOLIDO | BB73: FINALIZADO | BC73: =IF(AY73-KD73=0,"",AY73-O73) -> -151 | BD73: =IF(AND(AI73<>"SIM",AI73="UH"),"AA","INDENIZAÇÃO") -> AA | BE73: =IF(AND(AY73<>"AGUARDANDO",AY73<>"",N73="AUXÍLIO ALUGUEL ATÉ INDENIZAÇÃO"),"SIM","NÃO") -> NÃO | BF73: N/A | BG73: N/A | BH73: N/A | BI73: N/A | BJ73: N/A | BK73: N/A | BL73: N/A | BM73: FINALIZADO
A74: 61 | B74: PARAISÓPOLIS/ANTONICO | C74: 2 | D74: 024 | E74: 0 | F74: 024/0050/D | G74: OCUPADO | H74: RESIDENCIAL | I74: PROPRIETÁRIO RESIDENTE | J74: BIANCA ALVES DE SOUZA | K74: 52.417.284-5 | L74: 474.881.268-07 | M74: CADASTRADO | N74: AUXÍLIO ALUGUEL UH | O74: 44788 | P74: 44671 | Q74: 6014.2021/0000734-3 | R74: FINALIZADO | S74: FINALIZADO | T74: FINALIZADO | U74: 44693 | V74: 44693 | W74: 44693 | X74: 44713 | Y74: 44727 | Z74: 44732 | AB74: BIANCA ALVES DE SOUZA | AC74: 52.417.284-5 | AD74: 474.881.268-07 | AE74: PROPRIETÁRIO RESIDENTE | AF74: N/A | AG74: 16409.86 | AH74: 46409.86 | AI74: UH | AJ74: 6014.2022/0000163-0 | AK74: N/A | AL74: N/A | AM74: N/A | AN74: N/A | AP74: N/A | AQ74: N/A | AR74: N/A | AS74: N/A | AT74: N/A | AU74: N/A | AV74: N/A | AW74: N/A | AX74: =X74 -> 44713 | AY74: =Y74 -> 44727 | AZ74: 44713 | BA74: DEMOLIDO | BB74: FINALIZADO | BC74: =IF(AY74-KD74=0,"",AY74-O74) -> -61 | BD74: =IF(AND(AI74<>"SIM",AI74="UH"),"AA","INDENIZAÇÃO") -> AA | BE74: =IF(AND(AY74<>"AGUARDANDO",AY74<>"",N74="AUXÍLIO ALUGUEL ATÉ INDENIZAÇÃO"),"SIM","NÃO") -> NÃO | BF74: N/A | BG74: N/A | BH74: N/A | BI74: N/A | BJ74: N/A | BK74: N/A | BL74: N/A | BM74: FINALIZADO
A75: 62 | B75: PARAISÓPOLIS/ANTONICO | C75: 2 | D75: 024 | E75: 0 | F75: 024/0051/A | G75: OCUPADO | H75: RESIDENCIAL | I75: PROPRIETÁRIO RESIDENTE | J75: NIVAN LEÃO DA SILVA | K75: 30.449.154-8 | L75: 065.178.078-02 | M75: CADASTRADO | N75: AUXÍLIO ALUGUEL ATÉ INDENIZAÇÃO | O75: 44788 | P75: 44671 | Q75: 6013.2022/0004909-3 | R75: FINALIZADO | S75: FINALIZADO | T75: FINALIZADO | U75: 44693 | V75: 44698 | W75: 44698 | X75: 44713 | Y75: BLOQUEADO | Z75: 44733 | AA75: BLOQUEADO - POR PAGAMENTO DE INDENIZAÇÃO | AB75: NIVAN LEÃO DA SILVA | AC75: 30.449.154-8 | AD75: 065.178.078-02 | AE75: PROPRIETÁRIO RESIDENTE | AF75: CADASTRADO | AG75: 9361.51 | AH75: 39361.51 | AI75: SIM | AJ75: 6014.2022/0000163-0 | AK75: FINALIZADO | AL75: FINALIZADO | AM75: FINALIZADO | AN75: SEM PENDÊNCIA | AP75: 6014.2022/0002677-3 | AQ75: FINALIZADO | AR75: FINALIZADO | AS75: FINALIZADO | AT75: FINALIZADO | AU75: 44840 | AV75: FINALIZADO | AW75: FINALIZADO | AX75: 44852 | AY75: 44852 | AZ75: 44799 | BA75: DEMOLIDO | BB75: FINALIZADO | BC75: =IF(AY75-KD75=0,"",AY75-O75) -> 64 | BD75: =IF(AND(AI75<>"SIM",AI75="UH"),"AA","INDENIZAÇÃO") -> INDENIZAÇÃO | BE75: =IF(AND(AY75<>"AGUARDANDO",AY75<>"",N75="AUXÍLIO ALUGUEL ATÉ INDENIZAÇÃO"),"SIM","NÃO") -> SIM | BF75: FINALIZADO | BG75: 44890 | BH75: 44890 | BI75: FINALIZADO | BJ75: FINALIZADO | BK75: 45057 | BL75: FINALIZADO | BM75: FINALIZADO
A76: 63 | B76: PARAISÓPOLIS/ANTONICO | C76: 2 | D76: 024 | E76: 0 | F76: 024/0052/A | G76: OCUPADO | H76: RESIDENCIAL | I76: PROPRIETÁRIO RESIDENTE | J76: GILVAN PRATES ANJOS | K76: 33.190.024-4 | L76: 260.943.538-03 | M76: CADASTRADO | N76: AUXÍLIO ALUGUEL ATÉ INDENIZAÇÃO | O76: 44788 | P76: 44671 | Q76: 6013.2022/0004909-3 | R76: FINALIZADO | S76: FINALIZADO | T76: FINALIZADO | U76: 44693 | V76: 44693 | W76: 44693 | X76: 44713 | Y76: 44715 | Z76: 44743 | AA76: BLOQUEADO - POR PAGAMENTO DE INDENIZAÇÃO | AB76: GILVAN PRATES ANJOS | AC76: 33.190.024-4 | AD76: 260.943.538-03 | AE76: PROPRIETÁRIO RESIDENTE | AF76: CADASTRADO | AG76: 23876.24 | AH76: 53876.24 | AI76: SIM | AJ76: 6014.2022/0000163-0 | AK76: FINALIZADO | AL76: FINALIZADO | AM76: FINALIZADO | AN76: SEM PENDÊNCIA | AP76: 6014.2022/0003638-8 | AQ76: FINALIZADO | AR76: FINALIZADO | AS76: FINALIZADO | AT76: FINALIZADO | AU76: 44816 | AV76: FINALIZADO | AW76: FINALIZADO | AX76: 44914 | AY76: 44914 | AZ76: 44743 | BA76: DEMOLIDO | BB76: FINALIZADO | BC76: =IF(AY76-KD76=0,"",AY76-O76) -> 126 | BD76: =IF(AND(AI76<>"SIM",AI76="UH"),"AA","INDENIZAÇÃO") -> INDENIZAÇÃO | BE76: =IF(AND(AY76<>"AGUARDANDO",AY76<>"",N76="AUXÍLIO ALUGUEL ATÉ INDENIZAÇÃO"),"SIM","NÃO") -> SIM | BF76: FINALIZADO | BG76: 44929 | BH76: 44929 | BI76: FINALIZADO | BJ76: FINALIZADO | BK76: 45057 | BL76: FINALIZADO | BM76: FINALIZADO
A77: 64 | B77: PARAISÓPOLIS/ANTONICO | C77: 2 | D77: 024 | E77: URG | F77: 024/0053/A | G77: OCUPADO | H77: RESIDENCIAL | I77: PROPRIETÁRIO RESIDENTE | J77: SELMA SOARES SANTOS DE OLIVEIRA | K77: 29.462.481-8 | L77: 324.973.128-50 | M77: CADASTRADO | N77: RESISTENTE | O77: 44788 | P77: N/A | Q77: N/A | R77: N/A | S77: N/A | T77: N/A | U77: N/A | V77: N/A | W77: N/A | X77: N/A | Y77: N/A | Z77: N/A | AB77: SELMA SOARES SANTOS DE OLIVEIRA | AC77: 29.462.481-8 | AD77: 324.973.128-50 | AE77: PROPRIETÁRIO RESIDENTE | AG77: 59130.53 | AH77: 60000 | AI77: RESISTENTE | AJ77: 6014.2022/0000163-0 | AK77: FINALIZADO | AO77: RESISTENTE | AP77: 6014.2024/0003626-8 | AQ77: RESISTENTE | AZ77: 45538 | BA77: DEMOLIDO | BB77: RESISTENTE | BC77: =IF(AY77-KD77=0,"",AY77-O77) | BD77: =IF(AND(AI77<>"SIM",AI77="UH"),"AA","INDENIZAÇÃO") -> INDENIZAÇÃO | BE77: =IF(AND(AY77<>"AGUARDANDO",AY77<>"",N77="AUXÍLIO ALUGUEL ATÉ INDENIZAÇÃO"),"SIM","NÃO") -> NÃO
A78: 65 | B78: PARAISÓPOLIS/ANTONICO | C78: 2 | D78: 024 | E78: 0 | F78: 024/0054/A | G78: OCUPADO | H78: RESIDENCIAL | I78: INQUILINO | J78: ADILSON JOSÉ DE SANTANA | K78: 58.819.266-1 | L78: 028.336.355-08 | M78: CADASTRADO | N78: AUXÍLIO ALUGUEL UH | O78: 44788 | P78: 44746 | Q78: 6014.2021/0000734-3 | R78: FINALIZADO | S78: FINALIZADO | T78: FINALIZADO | U78: 44776 | V78: 44782 | W78: 44782 | X78: 44795 | Y78: 44797 | Z78: 44799 | AB78: PAULO MANOEL BARSOSA | AC78: 68.4961-0 | AD78: 029.230.474-94 | AE78: PROPRIETÁRIO NÃO RESIDENTE | AF78: CADASTRADO | AG78: 12796.06 | AH78: 42796.06 | AI78: SIM | AJ78: 6014.2022/0000163-0 | AK78: FINALIZADO | AL78: FINALIZADO | AM78: FINALIZADO | AN78: SEM PENDÊNCIA | AP78: 6014.2022/0002747-8 | AQ78: FINALIZADO | AR78: FINALIZADO | AS78: FINALIZADO | AT78: FINALIZADO | AU78: 44840 | AV78: FINALIZADO | AW78: FINALIZADO | AX78: 44852 | AY78: 44852 | AZ78: 44852 | BA78: DEMOLIDO | BB78: FINALIZADO | BC78: =IF(AY78-KD78=0,"",AY78-O78) -> 64 | BD78: =IF(AND(AI78<>"SIM",AI78="UH"),"AA","INDENIZAÇÃO") -> INDENIZAÇÃO | BE78: =IF(AND(AY78<>"AGUARDANDO",AY78<>"",N78="AUXÍLIO ALUGUEL ATÉ INDENIZAÇÃO"),"SIM","NÃO") -> NÃO | BF78: N/A | BG78: N/A | BH78: N/A | BI78: FINALIZADO | BJ78: FINALIZADO | BK78: 45057 | BL78: FINALIZADO | BM78: FINALIZADO
A79: 66 | B79: PARAISÓPOLIS/ANTONICO | C79: 2 | D79: 024 | E79: URG | F79: 024/0054/B | G79: CONSTRUÇÃO | H79: RESIDENCIAL | I79: PROPRIETÁRIO NÃO RESIDENTE | J79: PAULA BELARMINA BARBOSA | K79: 52.853.399-X | L79: 485.845.548-31 | M79: NÃO CADASTRADO | N79: NÃO TEM ATENDIMENTO | O79: 44788 | P79: N/A | Q79: N/A | R79: N/A | S79: N/A | T79: N/A | U79: N/A | V79: N/A | W79: N/A | X79: N/A | Y79: N/A | Z79: N/A | AB79: PAULA BELARMINA BARBOSA | AC79: 52.853.399-X | AD79: 485.845.548-31 | AE79: PROPRIETÁRIO NÃO RESIDENTE | AF79: CADASTRADO | AG79: 10181.23 | AH79: 40181.23 | AI79: SIM | AJ79: 6014.2022/0000163-0 | AK79: FINALIZADO | AL79: FINALIZADO | AM79: FINALIZADO | AN79: SEM PENDÊNCIA | AP79: 6014.2022/0003196-3 | AQ79: FINALIZADO | AR79: FINALIZADO | AS79: FINALIZADO | AT79: FINALIZADO | AU79: 44862 | AV79: FINALIZADO | AW79: FINALIZADO | AX79: 44855 | AY79: 44887 | AZ79: 44877 | BA79: DEMOLIDO | BB79: FINALIZADO | BC79: =IF(AY79-KD79=0,"",AY79-O79) -> 99 | BD79: =IF(AND(AI79<>"SIM",AI79="UH"),"AA","INDENIZAÇÃO") -> INDENIZAÇÃO | BE79: =IF(AND(AY79<>"AGUARDANDO",AY79<>"",N79="AUXÍLIO ALUGUEL ATÉ INDENIZAÇÃO"),"SIM","NÃO") -> NÃO | BF79: N/A | BG79: N/A | BH79: N/A | BI79: FINALIZADO | BJ79: FINALIZADO | BK79: 45057 | BL79: FINALIZADO | BM79: FINALIZADO
A80: 67 | B80: PARAISÓPOLIS/ANTONICO | C80: 2 | D80: 024 | E80: URG | F80: 024/0054/C | G80: OCUPADO | H80: RESIDENCIAL | I80: PROPRIETÁRIO RESIDENTE | J80: JULIMAR DE SOUSA | K80: 36.690.926-5 | L80: 319.304.218-85 | M80: CADASTRADO | N80: AUXÍLIO ALUGUEL UH | O80: 45048 | P80: 45048 | Q80: 6014.2021/0000734-3 | R80: FINALIZADO | S80: 45050 | T80: 45058 | U80: 45061 | V80: 45061 | W80: 45061 | X80: 45078 | Y80: 45079 | Z80: DESABOU | AB80: JULIMAR DE SOUSA | AC80: 36.690.926-5 | AD80: 319.304.218-85 | AE80: PROPRIETÁRIO RESIDENTE | AF80: N/A | AG80: 0 | AH80: 0 | AI80: UH | AJ80: 6014.2022/0000163-0 | AK80: N/A | AL80: N/A | AM80: N/A | AN80: N/A | AO80: IMÓVEL DESABOU | AP80: N/A | AQ80: N/A | AR80: N/A | AS80: N/A | AT80: N/A | AU80: N/A | AV80: N/A | AW80: N/A | AX80: 45078 | AY80: 45079 | AZ80: 45089 | BA80: DEMOLIDO | BB80: FINALIZADO | BC80: =IF(AY80-KD80=0,"",AY80-O80) -> 31 | BD80: =IF(AND(AI80<>"SIM",AI80="UH"),"AA","INDENIZAÇÃO") -> AA | BE80: =IF(AND(AY80<>"AGUARDANDO",AY80<>"",N80="AUXÍLIO ALUGUEL ATÉ INDENIZAÇÃO"),"SIM","NÃO") -> NÃO | BF80: N/A | BG80: N/A | BH80: N/A | BI80: N/A | BJ80: N/A | BK80: N/A | BL80: N/A | BM80: FINALIZADO
A81: 68 | B81: PARAISÓPOLIS/ANTONICO | C81: 2 | D81: 024 | E81: 0 | F81: 024/0055/A | G81: OCUPADO | H81: RESIDENCIAL | I81: INQUILINO | J81: JOSÉ MAURICIO DA SILVA LOURENÇO | K81: 2007850410-9 | L81: 607.707.293-12 | M81: CADASTRADO | N81: AUXÍLIO ALUGUEL UH | O81: 44788 | P81: 44788 | Q81: 6014.2021/0000734-3 | R81: FINALIZADO | S81: FINALIZADO | T81: FINALIZADO | U81: 44813 | V81: FINALIZADO | W81: FINALIZADO | X81: 44839 | Y81: 44839 | Z81: 44825 | AB81: ARLENE DE AMORIM FURTADO | AC81: 66.551.872-9 | AD81: 067.111.663-02 | AE81: PROPRIETÁRIO NÃO RESIDENTE | AF81: CADASTRADO | AG81: 21849.51 | AH81: 51849.51 | AI81: SIM | AJ81: 6014.2022/0000163-0 | AK81: FINALIZADO | AL81: FINALIZADO | AM81: FINALIZADO | AN81: SEM PENDÊNCIA | AP81: 6014.2022/0002665-0 | AQ81: FINALIZADO | AR81: FINALIZADO | AS81: FINALIZADO | AT81: FINALIZADO | AU81: 44840 | AV81: FINALIZADO | AW81: FINALIZADO | AX81: 44852 | AY81: 44852 | AZ81: 44825 | BA81: DESCARACTERIZADO | BB81: FINALIZADO | BC81: =IF(AY81-KD81=0,"",AY81-O81) -> 64 | BD81: =IF(AND(AI81<>"SIM",AI81="UH"),"AA","INDENIZAÇÃO") -> INDENIZAÇÃO | BE81: =IF(AND(AY81<>"AGUARDANDO",AY81<>"",N81="AUXÍLIO ALUGUEL ATÉ INDENIZAÇÃO"),"SIM","NÃO") -> NÃO | BF81: N/A | BG81: N/A | BH81: N/A | BI81: FINALIZADO | BJ81: FINALIZADO | BK81: 45057 | BL81: FINALIZADO | BM81: FINALIZADO
A82: 69 | B82: PARAISÓPOLIS/ANTONICO | C82: 2 | D82: 024 | E82: URG | F82: 024/0055/B | G82: OCUPADO | H82: RESIDENCIAL | I82: INQUILINO | J82: KELLY SANTOS BRUNO | K82: 48.424.425-5 | L82: 453.054.968-29 | M82: CADASTRADO | N82: AUXÍLIO ALUGUEL UH | O82: 44788 | P82: 44671 | Q82: 6013.2022/0004909-3 | R82: FINALIZADO | S82: FINALIZADO | T82: FINALIZADO | U82: 44693 | V82: 44693 | W82: 44693 | X82: AGUARDANDO | Z82: 45054 | AA82: 21/06/23 - munícipe está com o cadastro em andamento para desmembramento do CPF da Queila. Aguardando DTS regularizar cadastro através de processo SEI. | AB82: QUEILA SANTOS BRUNO | AC82: 47.764.891-5 | AD82: 411.562.978-93 | AE82: PROPRIETÁRIO NÃO RESIDENTE | AF82: CADASTRADO | AG82: 23489.1 | AH82: 53489.1 | AI82: SIM | AJ82: 6014.2022/0000163-0 | AK82: FINALIZADO | AL82: FINALIZADO | AM82: FINALIZADO | AN82: SEM PENDÊNCIA | AO82: RECUSA ENTREGAR IMÓVEL | AP82: 6014.2022/0003497-0 | AQ82: FINALIZADO | AR82: FINALIZADO | AS82: FINALIZADO | AT82: FINALIZADO | AU82: 44889 | AV82: FINALIZADO | AW82: FINALIZADO | AX82: 44897 | AY82: 44897 | AZ82: 45054 | BA82: DESCARACTERIZADO | BB82: FINALIZADO | BC82: =IF(AY82-KD82=0,"",AY82-O82) -> 109 | BD82: =IF(AND(AI82<>"SIM",AI82="UH"),"AA","INDENIZAÇÃO") -> INDENIZAÇÃO | BE82: =IF(AND(AY82<>"AGUARDANDO",AY82<>"",N82="AUXÍLIO ALUGUEL ATÉ INDENIZAÇÃO"),"SIM","NÃO") -> NÃO | BF82: N/A | BG82: N/A | BH82: N/A | BI82: FINALIZADO | BJ82: FINALIZADO | BK82: 45057 | BL82: FINALIZADO | BM82: FINALIZADO
A83: 70 | B83: PARAISÓPOLIS/ANTONICO | C83: 2 | D83: 024 | E83: URG | F83: 024/0055/C | G83: OCUPADO | H83: RESIDENCIAL | I83: PROPRIETÁRIO RESIDENTE | J83: SOELMA BISPO DOS SANTOS | K83: 36.940.273-X | L83: 319.895.938-10 | M83: CADASTRADO | N83: INDENIZAÇÃO | O83: 44788 | P83: N/A | Q83: N/A | R83: N/A | S83: N/A | T83: N/A | U83: N/A | V83: N/A | W83: N/A | X83: N/A | Y83: N/A | Z83: N/A | AB83: SOELMA BISPO DOS SANTOS | AC83: 36.940.273-X | AD83: 319.895.938-10 | AE83: PROPRIETÁRIO RESIDENTE | AF83: CADASTRADO | AG83: 50406.3 | AH83: 60000 | AI83: SIM | AJ83: 6014.2022/0000163-0 | AK83: FINALIZADO | AL83: FINALIZADO | AM83: FINALIZADO | AN83: SEM PENDÊNCIA | AO83: MORADOR NÃO COMPARECEU NO PLANTÃO | AP83: 6014.2022/0004096-2 | AQ83: FINALIZADO | AR83: FINALIZADO | AS83: FINALIZADO | AT83: FINALIZADO | AU83: 44922 | AV83: FINALIZADO | AW83: FINALIZADO | AX83: 44924 | AY83: 44924 | AZ83: 45052 | BA83: DESCARACTERIZADO | BB83: FINALIZADO | BC83: =IF(AY83-KD83=0,"",AY83-O83) -> 136 | BD83: =IF(AND(AI83<>"SIM",AI83="UH"),"AA","INDENIZAÇÃO") -> INDENIZAÇÃO | BE83: =IF(AND(AY83<>"AGUARDANDO",AY83<>"",N83="AUXÍLIO ALUGUEL ATÉ INDENIZAÇÃO"),"SIM","NÃO") -> NÃO | BF83: N/A | BG83: N/A | BH83: N/A | BI83: FINALIZADO | BJ83: FINALIZADO | BK83: 45057 | BL83: FINALIZADO | BM83: FINALIZADO
A84: 71 | B84: PARAISÓPOLIS/ANTONICO | C84: 2 | D84: 024 | E84: URG | F84: 024/0056/A | G84: OCUPADO | H84: RESIDENCIAL | I84: INQUILINO | J84: MAGNO APARECIDO DA SILVA GOUVEIA | K84: 35.620.363-3 | L84: 440.074.278-44 | M84: CADASTRADO | N84: AUXÍLIO ALUGUEL UH | O84: 44788 | P84: 44897 | Q84: 6014.2021/0000734-3 | R84: FINALIZADO | S84: FINALIZADO | T84: FINALIZADO | U84: 44918 | V84: 44924 | W84: 44958 | X84: 44958 | Y84: 44963 | Z84: 45020 | AB84: JOSÉ DE ARIMATÉIA TOMÁS MONTEIRO | AC84: 52.797.828-0 | AD84: 022.689.344-89 | AE84: PROPRIETÁRIO NÃO RESIDENTE | AF84: CADASTRADO | AG84: =AH84-30000 -> 18642 | AH84: 48642 | AI84: SIM | AJ84: 6014.2022/0000163-0 | AK84: FINALIZADO | AL84: FINALIZADO | AM84: FINALIZADO | AN84: SEM PENDÊNCIA | AP84: 6014.2022/0004192-6 | AQ84: FINALIZADO | AR84: FINALIZADO | AS84: FINALIZADO | AT84: FINALIZADO | AU84: 44961 | AV84: FINALIZADO | AW84: FINALIZADO | AX84: 45015 | AY84: 45015 | AZ84: 45020 | BA84: DESCARACTERIZADO | BB84: FINALIZADO | BC84: =IF(AY84-KD84=0,"",AY84-O84) -> 227 | BD84: =IF(AND(AI84<>"SIM",AI84="UH"),"AA","INDENIZAÇÃO") -> INDENIZAÇÃO | BE84: =IF(AND(AY84<>"AGUARDANDO",AY84<>"",N84="AUXÍLIO ALUGUEL ATÉ INDENIZAÇÃO"),"SIM","NÃO") -> NÃO | BF84: N/A | BG84: N/A | BH84: N/A | BI84: FINALIZADO | BJ84: FINALIZADO | BK84: 45175 | BL84: FINALIZADO | BM84: FINALIZADO
A85: 72 | B85: PARAISÓPOLIS/ANTONICO | C85: 2 | D85: 024 | E85: 0 | F85: 024/0056/B | G85: OCUPADO | H85: RESIDENCIAL | I85: INQUILINO | J85: JONAS GONÇALVES DA SILVA DE JESUS | K85: 65.893.335-8 | L85: 087.094.855-54 | M85: CADASTRADO | N85: AUXÍLIO ALUGUEL UH | O85: 44788 | P85: 44788 | Q85: 6014.2021/0000734-3 | R85: FINALIZADO | S85: FINALIZADO | T85: FINALIZADO | U85: 44813 | V85: FINALIZADO | W85: FINALIZADO | X85: 44838 | Y85: 44854 | Z85: 44831 | AB85: BRUNO DA SILVA MIRANDA | AC85: 63.065.138-3 | AD85: 084.511.195-73 | AE85: PROPRIETÁRIO NÃO RESIDENTE | AF85: CADASTRADO | AG85: 14183.41 | AH85: 44183.41 | AI85: SIM | AJ85: 6014.2022/0000163-0 | AK85: FINALIZADO | AL85: FINALIZADO | AM85: FINALIZADO | AN85: SEM PENDÊNCIA | AP85: 6014.2022/0002834-2 | AQ85: FINALIZADO | AR85: FINALIZADO | AS85: FINALIZADO | AT85: FINALIZADO | AU85: 44840 | AV85: FINALIZADO | AW85: FINALIZADO | AX85: 44852 | AY85: 44852 | AZ85: 44831 | BA85: DEMOLIDO | BB85: FINALIZADO | BC85: =IF(AY85-KD85=0,"",AY85-O85) -> 64 | BD85: =IF(AND(AI85<>"SIM",AI85="UH"),"AA","INDENIZAÇÃO") -> INDENIZAÇÃO | BE85: =IF(AND(AY85<>"AGUARDANDO",AY85<>"",N85="AUXÍLIO ALUGUEL ATÉ INDENIZAÇÃO"),"SIM","NÃO") -> NÃO | BF85: N/A | BG85: N/A | BH85: N/A | BI85: FINALIZADO | BJ85: FINALIZADO | BK85: 45057 | BL85: FINALIZADO | BM85: FINALIZADO
A86: 73 | B86: PARAISÓPOLIS/ANTONICO | C86: 2 | D86: 024 | E86: 0 | F86: 024/0056/C | G86: OCUPADO | H86: RESIDENCIAL | I86: PROPRIETÁRIO RESIDENTE | J86: YWULLY CRISTINA FERREIRA DOS SANTOS | K86: 59.507.165-X | L86: 466.514.178-94 | M86: CADASTRADO | N86: AUXÍLIO ALUGUEL UH | O86: 45275 | P86: PENDENTE | Q86: 6014.2021/0000734-3 | R86: FINALIZADO | S86: FINALIZADO | T86: FINALIZADO | U86: FINALIZADO | V86: FINALIZADO | W86: FINALIZADO | X86: 45275 | Y86: 45282 | Z86: 45271 | AB86: YWULLY CRISTINA FERREIRA DOS SANTOS | AC86: 59.507.165-X | AD86: 466.514.178-94 | AE86: PROPRIETÁRIO RESIDENTE | AF86: CADASTRADO | AG86: 0 | AH86: 0 | AI86: UH | AJ86: 6014.2022/0000163-0 | AK86: FINALIZADO | AL86: N/A | AM86: N/A | AN86: N/A | AP86: N/A | AQ86: N/A | AR86: N/A | AS86: N/A | AT86: N/A | AU86: N/A | AV86: N/A | AW86: N/A | AZ86: 45271 | BA86: DEMOLIDO | BB86: AA PENDENTE
A87: 74 | B87: PARAISÓPOLIS/ANTONICO | C87: 2 | D87: 024 | E87: 0 | F87: 024/0057/A | G87: OCUPADO | H87: RESIDENCIAL | I87: PROPRIETÁRIO RESIDENTE | J87: ANDREIA LIMA GUIMARÃES SILVA | K87: 29.079.900-4 | L87: 270.915.658-00 | M87: CADASTRADO | N87: AUXÍLIO ALUGUEL ATÉ INDENIZAÇÃO | O87: 44844 | P87: 44591 | Q87: 6013.2022/0004909-3 | R87: FINALIZADO | S87: FINALIZADO | T87: FINALIZADO | U87: 44642 | V87: 44616 | W87: 44616 | X87: 44630 | Y87: 44634 | Z87: 44670 | AA87: BLOQUEADO - POR PAGAMENTO DE INDENIZAÇÃO | AB87: ANDREIA LIMA GUIMARÃES SILVA | AC87: 29.079.900-4 | AD87: 270.915.658-00 | AE87: PROPRIETÁRIO RESIDENTE | AF87: CADASTRADO | AG87: 26229.46 | AH87: 56229.46 | AI87: SIM | AJ87: 6014.2022/0000163-0 | AK87: FINALIZADO | AL87: FINALIZADO | AM87: FINALIZADO | AN87: SEM PENDÊNCIA | AP87: 6014.2022/0003298-6 | AQ87: FINALIZADO | AR87: FINALIZADO | AS87: FINALIZADO | AT87: FINALIZADO | AU87: 44869 | AV87: FINALIZADO | AW87: FINALIZADO | AX87: 44855 | AY87: 44887 | AZ87: 44670 | BA87: DESCARACTERIZADO | BB87: FINALIZADO | BC87: =IF(AY87-KD87=0,"",AY87-O87) -> 43 | BD87: =IF(AND(AI87<>"SIM",AI87="UH"),"AA","INDENIZAÇÃO") -> INDENIZAÇÃO | BE87: =IF(AND(AY87<>"AGUARDANDO",AY87<>"",N87="AUXÍLIO ALUGUEL ATÉ INDENIZAÇÃO"),"SIM","NÃO") -> SIM | BF87: FINALIZADO | BG87: 44916 | BH87: 44916 | BI87: FINALIZADO | BJ87: FINALIZADO | BK87: 45057 | BL87: FINALIZADO | BM87: FINALIZADO
A88: 75 | B88: PARAISÓPOLIS/ANTONICO | C88: 2 | D88: 024 | E88: URG | F88: 024/0057/B | G88: OCUPADO | H88: RESIDENCIAL | I88: INQUILINO | J88: RENATO DOS REIS CAVALCANTE | K88: 63.440.580-9 | L88: 070.518.295-99 | M88: CADASTRADO | N88: AUXÍLIO ALUGUEL UH | O88: 44788 | P88: 44834 | Q88: 6014.2021/0000734-3 | R88: FINALIZADO | S88: FINALIZADO | T88: FINALIZADO | U88: 44859 | V88: 44859 | W88: 44859 | X88: 44875 | Y88: 44875 | Z88: 44881 | AB88: GERILZA BRITO CAVALCANTE | AC88: 45.456.905-1 | AD88: 399.239.398-47 | AE88: PROPRIETÁRIO NÃO RESIDENTE | AF88: CADASTRADO | AG88: 36741.64 | AH88: 60000 | AI88: SIM | AJ88: 6014.2022/0000163-0 | AK88: FINALIZADO | AL88: FINALIZADO | AM88: FINALIZADO | AN88: SEM PENDÊNCIA | AP88: 6014.2022/0002673-0 | AQ88: FINALIZADO | AR88: FINALIZADO | AS88: FINALIZADO | AT88: FINALIZADO | AU88: 44840 | AV88: FINALIZADO | AW88: FINALIZADO | AX88: 44865 | AY88: 44865 | AZ88: 44881 | BA88: DESCARACTERIZADO | BB88: FINALIZADO | BC88: =IF(AY88-KD88=0,"",AY88-O88) -> 77 | BD88: =IF(AND(AI88<>"SIM",AI88="UH"),"AA","INDENIZAÇÃO") -> INDENIZAÇÃO | BE88: =IF(AND(AY88<>"AGUARDANDO",AY88<>"",N88="AUXÍLIO ALUGUEL ATÉ INDENIZAÇÃO"),"SIM","NÃO") -> NÃO | BF88: N/A | BG88: N/A | BH88: N/A | BI88: FINALIZADO | BJ88: FINALIZADO | BK88: 45057 | BL88: FINALIZADO | BM88: FINALIZADO
A89: 76 | B89: PARAISÓPOLIS/ANTONICO | C89: 2 | D89: 024 | E89: URG | F89: 024/0057/C | G89: OCUPADO | H89: RESIDENCIAL | I89: PROPRIETÁRIO RESIDENTE | J89: GERALDA HELENA DOS SANTOS PEREIRA | K89: 26.256.463-4 | L89: 260.940.648-79 | M89: CADASTRADO | N89: AUXÍLIO ALUGUEL UH | O89: 45275 | P89: PENDENTE | Q89: 6014.2021/0000734-3 | R89: FINALIZADO | S89: FINALIZADO | T89: FINALIZADO | U89: FINALIZADO | V89: FINALIZADO | W89: FINALIZADO | X89: 45275 | Y89: 22/15/2023 | Z89: 45271 | AB89: GERALDA HELENA DOS SANTOS PEREIRA | AC89: 26.256.463-4 | AD89: 260.940.648-79 | AE89: PROPRIETÁRIO RESIDENTE | AF89: CADASTRADO | AG89: 0 | AH89: 0 | AI89: UH | AJ89: 6014.2022/0000163-0 | AK89: FINALIZADO | AL89: N/A | AM89: N/A | AN89: N/A | AP89: N/A | AQ89: N/A | AR89: N/A | AS89: N/A | AT89: N/A | AU89: N/A | AV89: N/A | AW89: N/A | AZ89: 45271 | BA89: DEMOLIDO | BB89: AA PENDENTE
A90: 77 | B90: PARAISÓPOLIS/ANTONICO | C90: 2 | D90: 024 | E90: URG | F90: 024/0069/A | G90: OCUPADO | H90: RESIDENCIAL | I90: INQUILINO | J90: ADENILZA PAIXÃO SANTANA | K90: 1126875392 | L90: 035.838.415-06 | M90: CADASTRADO | N90: AUXÍLIO ALUGUEL UH | O90: 44788 | P90: 44788 | Q90: 6014.2021/0000734-3 | R90: FINALIZADO | S90: FINALIZADO | T90: FINALIZADO | U90: 44813 | V90: 44818 | W90: 44818 | X90: 44837 | Y90: 44837 | Z90: 44854 | AB90: LOURISMAR LIMA BRAGA | AC90: 58.630.460-5 | AD90: 041.042.205-31 | AE90: PROPRIETÁRIO NÃO RESIDENTE | AF90: CADASTRADO | AG90: 76304.56 | AH90: 76304.56 | AI90: SIM | AJ90: 6014.2022/0000163-0 | AK90: FINALIZADO | AL90: FINALIZADO | AM90: FINALIZADO | AN90: SEM PENDÊNCIA | AO90: AGUARDANDO REGULARIZAÇÃO CPF | AP90: 6014.2022/0002683-8 | AQ90: FINALIZADO | AR90: FINALIZADO | AS90: FINALIZADO | AT90: FINALIZADO | AU90: 44840 | AV90: FINALIZADO | AW90: FINALIZADO | AX90: 44901 | AY90: 44901 | AZ90: 44924 | BA90: DESCARACTERIZADO | BB90: FINALIZADO | BC90: =IF(AY90-KD90=0,"",AY90-O90) -> 113 | BD90: =IF(AND(AI90<>"SIM",AI90="UH"),"AA","INDENIZAÇÃO") -> INDENIZAÇÃO | BE90: =IF(AND(AY90<>"AGUARDANDO",AY90<>"",N90="AUXÍLIO ALUGUEL ATÉ INDENIZAÇÃO"),"SIM","NÃO") -> NÃO | BF90: N/A | BG90: N/A | BH90: N/A | BI90: FINALIZADO | BJ90: FINALIZADO | BK90: 45175 | BL90: FINALIZADO | BM90: FINALIZADO
A91: 78 | B91: PARAISÓPOLIS/ANTONICO | C91: 2 | D91: 024 | E91: URG | F91: 024/0070/A | G91: OCUPADO | H91: RESIDENCIAL | I91: PROPRIETÁRIO RESIDENTE | J91: HUGO DA SILVA | K91: 24.092.561-0 | L91: 412.972.704-44 | M91: CADASTRADO | N91: INDENIZAÇÃO | O91: 44788 | P91: N/A | Q91: N/A | R91: N/A | S91: N/A | T91: N/A | U91: N/A | V91: N/A | W91: N/A | X91: N/A | Y91: N/A | Z91: N/A | AB91: HUGO DA SILVA | AC91: 24.092.561-0 | AD91: 412.972.704-44 | AE91: PROPRIETÁRIO RESIDENTE | AF91: CADASTRADO | AG91: 13838.51 | AH91: 43838.51 | AI91: SIM | AJ91: 6014.2022/0000163-0 | AK91: FINALIZADO | AL91: FINALIZADO | AM91: FINALIZADO | AN91: SEM PENDÊNCIA | AP91: 6014.2022/0003261-7 | AQ91: FINALIZADO | AR91: FINALIZADO | AS91: FINALIZADO | AT91: FINALIZADO | AU91: 44869 | AV91: FINALIZADO | AW91: FINALIZADO | AX91: 44855 | AY91: 44887 | AZ91: 44890 | BA91: DESCARACTERIZADO | BB91: FINALIZADO | BC91: =IF(AY91-KD91=0,"",AY91-O91) -> 99 | BD91: =IF(AND(AI91<>"SIM",AI91="UH"),"AA","INDENIZAÇÃO") -> INDENIZAÇÃO | BE91: =IF(AND(AY91<>"AGUARDANDO",AY91<>"",N91="AUXÍLIO ALUGUEL ATÉ INDENIZAÇÃO"),"SIM","NÃO") -> NÃO | BF91: N/A | BG91: N/A | BH91: N/A | BI91: FINALIZADO | BJ91: FINALIZADO | BK91: 45057 | BL91: FINALIZADO | BM91: FINALIZADO
A92: 79 | B92: PARAISÓPOLIS/ANTONICO | C92: 2 | D92: 024 | E92: 0 | F92: 024/0070/B | G92: OCUPADO | H92: RESIDENCIAL | I92: INQUILINO | J92: VITÓRIA BEZERRA DE OLIVEIRA | K92: 63.677.981-6 | L92: 549.846.698-61 | M92: CADASTRADO | N92: AUXÍLIO ALUGUEL UH | O92: 44788 | P92: 44746 | Q92: 6014.2021/0000734-3 | R92: FINALIZADO | S92: FINALIZADO | T92: FINALIZADO | U92: 44813 | V92: 44818 | W92: 44818 | X92: 44840 | Y92: 44851 | Z92: 44844 | AB92: PATRICIA BEZERRA DE OLIVEIRA | AC92: 60.886.838-3 | AD92: 528.126.448-69 | AE92: PROPRIETÁRIO NÃO RESIDENTE | AF92: CADASTRADO | AG92: 23362.75 | AH92: 53362.75 | AI92: SIM | AJ92: 6014.2022/0000163-0 | AK92: FINALIZADO | AL92: FINALIZADO | AM92: FINALIZADO | AN92: SEM PENDÊNCIA | AP92: 6014.2022/0002679-0 | AQ92: FINALIZADO | AR92: FINALIZADO | AS92: FINALIZADO | AT92: FINALIZADO | AU92: 44840 | AV92: FINALIZADO | AW92: FINALIZADO | AX92: 44855 | AY92: 44855 | AZ92: 44844 | BA92: DESCARACTERIZADO | BB92: FINALIZADO | BC92: =IF(AY92-KD92=0,"",AY92-O92) -> 67 | BD92: =IF(AND(AI92<>"SIM",AI92="UH"),"AA","INDENIZAÇÃO") -> INDENIZAÇÃO | BE92: =IF(AND(AY92<>"AGUARDANDO",AY92<>"",N92="AUXÍLIO ALUGUEL ATÉ INDENIZAÇÃO"),"SIM","NÃO") -> NÃO | BF92: N/A | BG92: N/A | BH92: N/A | BI92: FINALIZADO | BJ92: FINALIZADO | BK92: 45057 | BL92: FINALIZADO | BM92: FINALIZADO
A93: 80 | B93: PARAISÓPOLIS/ANTONICO | C93: 2 | D93: 024 | E93: 0 | F93: 024/0070/C | G93: OCUPADO | H93: RESIDENCIAL | I93: INQUILINO | J93: RENILSON DE JESUS SILVA | K93: 52.081.320-0 | L93: 239.256.308-05 | M93: CADASTRADO | N93: AUXÍLIO ALUGUEL UH | O93: 44788 | P93: 44834 | Q93: 6014.2021/0000734-3 | R93: FINALIZADO | S93: FINALIZADO | T93: FINALIZADO | U93: 44859 | V93: 44859 | W93: 44859 | X93: 44875 | Y93: 44886 | Z93: 44831 | AB93: CARLOS JESUS DA SILVA | AC93: 54.017.037-9 | AD93: 348.045.058-06 | AE93: PROPRIETÁRIO NÃO RESIDENTE | AF93: CADASTRADO | AG93: 9595.06 | AH93: 39595.06 | AI93: SIM | AJ93: 6014.2022/0000163-0 | AK93: FINALIZADO | AL93: FINALIZADO | AM93: FINALIZADO | AN93: SEM PENDÊNCIA | AP93: 6014.2022/0002894-6 | AQ93: FINALIZADO | AR93: FINALIZADO | AS93: FINALIZADO | AT93: FINALIZADO | AU93: 44840 | AV93: FINALIZADO | AW93: FINALIZADO | AX93: 44852 | AY93: 44852 | AZ93: 44855 | BA93: DESCARACTERIZADO | BB93: FINALIZADO | BC93: =IF(AY93-KD93=0,"",AY93-O93) -> 64 | BD93: =IF(AND(AI93<>"SIM",AI93="UH"),"AA","INDENIZAÇÃO") -> INDENIZAÇÃO | BE93: =IF(AND(AY93<>"AGUARDANDO",AY93<>"",N93="AUXÍLIO ALUGUEL ATÉ INDENIZAÇÃO"),"SIM","NÃO") -> NÃO | BF93: N/A | BG93: N/A | BH93: N/A | BI93: FINALIZADO | BJ93: FINALIZADO | BK93: 45057 | BL93: FINALIZADO | BM93: FINALIZADO
A94: 81 | B94: PARAISÓPOLIS/ANTONICO | C94: 2 | D94: 024 | E94: URG | F94: 024/0070/D | G94: OCUPADO | H94: RESIDENCIAL | I94: INQUILINO | J94: JOSE SANTOS ALVES | K94: 37.640.432-2 | L94: 912.479.505-49 | M94: CADASTRADO | N94: AUXÍLIO ALUGUEL UH | O94: 44788 | P94: 44834 | Q94: 6014.2021/0000734-3 | R94: FINALIZADO | S94: FINALIZADO | T94: FINALIZADO | U94: 44859 | V94: 44859 | W94: 44859 | X94: 44875 | Y94: 44875 | Z94: 44894 | AA94: INQUILINA COM DIFICULDADE DE ENCONTRAR OUTRO IMÓVEL PARA ALUGAR | AB94: ADAILTON ALVES DOS SANTOS | AC94: 33.271.603-x | AD94: 531.627.655-87 | AE94: PROPRIETÁRIO NÃO RESIDENTE | AF94: CADASTRADO | AG94: 15534.74 | AH94: 45534.74 | AI94: SIM | AJ94: 6014.2022/0000163-0 | AK94: FINALIZADO | AL94: FINALIZADO | AM94: FINALIZADO | AN94: SEM PENDÊNCIA | AP94: 6014.2022/0002901-2 | AQ94: FINALIZADO | AR94: FINALIZADO | AS94: FINALIZADO | AT94: FINALIZADO | AU94: 44840 | AV94: FINALIZADO | AW94: FINALIZADO | AX94: 44854 | AY94: 44854 | AZ94: 44894 | BA94: DESCARACTERIZADO | BB94: FINALIZADO | BC94: =IF(AY94-KD94=0,"",AY94-O94) -> 66 | BD94: =IF(AND(AI94<>"SIM",AI94="UH"),"AA","INDENIZAÇÃO") -> INDENIZAÇÃO | BE94: =IF(AND(AY94<>"AGUARDANDO",AY94<>"",N94="AUXÍLIO ALUGUEL ATÉ INDENIZAÇÃO"),"SIM","NÃO") -> NÃO | BF94: N/A | BG94: N/A | BH94: N/A | BI94: FINALIZADO | BJ94: FINALIZADO | BK94: 45057 | BL94: FINALIZADO | BM94: FINALIZADO
A95: 82 | B95: PARAISÓPOLIS/ANTONICO | C95: 2 | D95: 024 | E95: 0 | F95: 024/0070/E | G95: OCUPADO | H95: RESIDENCIAL | I95: PROPRIETÁRIO RESIDENTE | J95: ROMÁRIO SANTANA DA SILVA | K95: 53.504.080-5 | L95: 441.838.678-51 | M95: CADASTRADO | N95: AUXÍLIO ALUGUEL ATÉ INDENIZAÇÃO | O95: 44788 | P95: 44671 | Q95: 6013.2022/0004909-3 | R95: FINALIZADO | S95: FINALIZADO | T95: FINALIZADO | U95: 44693 | V95: 44698 | W95: 44698 | X95: 44713 | Y95: 44725 | Z95: 44735 | AA95: BLOQUEADO - POR PAGAMENTO DE INDENIZAÇÃO | AB95: ROMÁRIO SANTANA DA SILVA | AC95: 53.504.080-5 | AD95: 441.838.678-51 | AE95: PROPRIETÁRIO RESIDENTE | AF95: CADASTRADO | AG95: 8222.06 | AH95: 38222.06 | AI95: SIM | AJ95: 6014.2022/0000163-0 | AK95: FINALIZADO | AL95: FINALIZADO | AM95: FINALIZADO | AN95: SEM PENDÊNCIA | AP95: 6014.2022/0002681-1 | AQ95: FINALIZADO | AR95: FINALIZADO | AS95: FINALIZADO | AT95: FINALIZADO | AU95: 44840 | AV95: FINALIZADO | AW95: FINALIZADO | AX95: 44852 | AY95: 44852 | AZ95: 44805 | BA95: DEMOLIDO | BB95: FINALIZADO | BC95: =IF(AY95-KD95=0,"",AY95-O95) -> 64 | BD95: =IF(AND(AI95<>"SIM",AI95="UH"),"AA","INDENIZAÇÃO") -> INDENIZAÇÃO | BE95: =IF(AND(AY95<>"AGUARDANDO",AY95<>"",N95="AUXÍLIO ALUGUEL ATÉ INDENIZAÇÃO"),"SIM","NÃO") -> SIM | BF95: FINALIZADO | BG95: 44890 | BH95: 44890 | BI95: FINALIZADO | BJ95: FINALIZADO | BK95: 45057 | BL95: FINALIZADO | BM95: FINALIZADO
A96: 83 | B96: PARAISÓPOLIS/ANTONICO | C96: 2 | D96: 024 | E96: 0 | F96: 024/0070/F | G96: VAZIO | H96: RESIDENCIAL | I96: PROPRIETÁRIO RESIDENTE | J96: PATRICIA PEREIRA TEIXEIRA | K96: 43.758.184-6 | L96: 358.941.798-66 | M96: CADASTRADO | N96: AUXÍLIO ALUGUEL UH | O96: 44788 | P96: 44788 | Q96: 6014.2021/0000734-3 | R96: FINALIZADO | S96: FINALIZADO | T96: FINALIZADO | U96: 44813 | V96: 44818 | W96: 44818 | X96: 44837 | Y96: 44840 | Z96: 44837 | AB96: PATRICIA PEREIRA TEIXEIRA | AC96: 43.758.184-6 | AD96: 358.941.798-66 | AE96: PROPRIETÁRIO RESIDENTE | AF96: N/A | AG96: 37035.02 | AH96: 60000 | AI96: UH | AJ96: 6014.2022/0000163-0 | AK96: N/A | AL96: N/A | AM96: N/A | AN96: N/A | AP96: N/A | AQ96: N/A | AR96: N/A | AS96: N/A | AT96: N/A | AU96: N/A | AV96: N/A | AW96: N/A | AX96: =X96 -> 44837 | AY96: =Y96 -> 44840 | AZ96: 44837 | BA96: DESCARACTERIZADO | BB96: FINALIZADO | BC96: =IF(AY96-KD96=0,"",AY96-O96) -> 52 | BD96: =IF(AND(AI96<>"SIM",AI96="UH"),"AA","INDENIZAÇÃO") -> AA | BE96: =IF(AND(AY96<>"AGUARDANDO",AY96<>"",N96="AUXÍLIO ALUGUEL ATÉ INDENIZAÇÃO"),"SIM","NÃO") -> NÃO | BF96: N/A | BG96: N/A | BH96: N/A | BI96: N/A | BJ96: N/A | BK96: N/A | BL96: N/A | BM96: FINALIZADO
A97: 84 | B97: PARAISÓPOLIS/ANTONICO | C97: 2 | D97: 024 | E97: URG | F97: 024/0071/A | G97: OCUPADO | H97: RESIDENCIAL | I97: INQUILINO | J97: SILVANI PEREIRA TEIXEIRA | K97: 43.763.340-8 | L97: 402.027.318-98 | M97: CADASTRADO | N97: AUXÍLIO ALUGUEL UH | O97: 44788 | P97: 44889 | Q97: 6014.2021/0000734-3 | R97: FINALIZADO | S97: FINALIZADO | T97: FINALIZADO | U97: 44813 | V97: 44818 | W97: 44818 | X97: 44630 | Y97: 44722 | Z97: 44841 | AB97: VITÓRIA DA SILVA MEDEIROS | AC97: 41.041.99-0 | AD97: 340.791.928-00 | AE97: PROPRIETÁRIO NÃO RESIDENTE | AF97: CADASTRADO | AG97: 31623.31 | AH97: 60000 | AI97: SIM | AJ97: 6014.2022/0000163-0 | AK97: FINALIZADO | AL97: FINALIZADO | AM97: FINALIZADO | AN97: SEM PENDÊNCIA | AP97: 6014.2022/0003047-9 | AQ97: FINALIZADO | AR97: FINALIZADO | AS97: FINALIZADO | AT97: FINALIZADO | AU97: 44853 | AV97: FINALIZADO | AW97: FINALIZADO | AX97: 44865 | AY97: 44865 | AZ97: 44935 | BA97: DESCARACTERIZADO | BB97: FINALIZADO | BC97: =IF(AY97-KD97=0,"",AY97-O97) -> 77 | BD97: =IF(AND(AI97<>"SIM",AI97="UH"),"AA","INDENIZAÇÃO") -> INDENIZAÇÃO | BE97: =IF(AND(AY97<>"AGUARDANDO",AY97<>"",N97="AUXÍLIO ALUGUEL ATÉ INDENIZAÇÃO"),"SIM","NÃO") -> NÃO | BF97: N/A | BG97: N/A | BH97: N/A | BI97: FINALIZADO | BJ97: FINALIZADO | BK97: 45057 | BL97: FINALIZADO | BM97: FINALIZADO
A98: 85 | B98: PARAISÓPOLIS/ANTONICO | C98: 2 | D98: 024 | E98: URG | F98: 024/0071/B | G98: OCUPADO | H98: RESIDENCIAL | I98: INQUILINO | J98: LUANA BRITO | K98: 50.486.333-2 | L98: 021.848.845-96 | M98: CADASTRADO | N98: AUXÍLIO ALUGUEL UH | O98: 45083 | P98: 45090 | Q98: 6014.2021/0000734-3 | R98: 45093 | S98: 45096 | T98: 45111 | U98: 45112 | V98: 45112 | W98: 45112 | X98: 45127 | Y98: 45128 | Z98: 45265 | AB98: WALDECI MARQUES CARDOSO FILHO | AC98: 69.053.393-7 | AD98: 066.836.953-18 | AE98: PROPRIETÁRIO NÃO RESIDENTE | AF98: CADASTRADO | AG98: 79265.55 | AH98: 79265.55 | AI98: SIM | AJ98: 6014.2022/0000163-0 | AK98: FINALIZADO | AL98: FINALIZADO | AM98: FINALIZADO | AN98: SEM PENDÊNCIA | AP98: 6014.2023/0001964-7 | AQ98: FINALIZADO | AR98: FINALIZADO | AS98: FINALIZADO | AT98: FINALIZADO | AU98: 45148 | AV98: FINALIZADO | AW98: FINALIZADO | AX98: 45160 | AY98: 45160 | AZ98: 45265 | BA98: DESCARACTERIZADO | BB98: FINALIZADO | BC98: =IF(AY98-KD98=0,"",AY98-O98) -> 77 | BD98: =IF(AND(AI98<>"SIM",AI98="UH"),"AA","INDENIZAÇÃO") -> INDENIZAÇÃO | BE98: =IF(AND(AY98<>"AGUARDANDO",AY98<>"",N98="AUXÍLIO ALUGUEL ATÉ INDENIZAÇÃO"),"SIM","NÃO") -> NÃO | BF98: N/A | BG98: N/A | BH98: N/A | BI98: FINALIZADO | BJ98: FINALIZADO | BK98: 45303 | BL98: FINALIZADO | BM98: FINALIZADO
A99: 86 | B99: PARAISÓPOLIS/ANTONICO | C99: 2 | D99: 024 | E99: URG | F99: 024/0071/C | G99: OCUPADO | H99: RESIDENCIAL | I99: INQUILINO | J99: EDIVANIA ALVES PEREIRA | K99: 14293532 87 | L99: 039.532.515-38 | M99: CADASTRADO | N99: AUXÍLIO ALUGUEL UH | O99: 44889 | P99: 44889 | Q99: 6014.2021/0000734-3 | R99: FINALIZADO | S99: FINALIZADO | T99: FINALIZADO | U99: 44903 | V99: 44903 | W99: 44903 | X99: 44958 | Y99: 44960 | Z99: 45348 | AB99: CRISTINE DE LIMA BRITO | AC99: 20.689.460-09 | AD99: 078.993.665-85 | AE99: PROPRIETÁRIO NÃO RESIDENTE | AF99: CADASTRADO | AG99: 38204.78 | AH99: 60000 | AI99: SIM | AJ99: 6014.2022/0000163-0 | AK99: FINALIZADO | AL99: FINALIZADO | AM99: FINALIZADO | AN99: SEM PENDÊNCIA | AO99: MORADORA FORA DO ESTADO - FOI ENVIADA CÓPIA TERMO | AP99: 6014.2023/0002108-0 | AQ99: FINALIZADO | AR99: FINALIZADO | AS99: FINALIZADO | AT99: FINALIZADO | AU99: 45278 | AV99: FINALIZADO | AW99: FINALIZADO | AX99: 45294 | AY99: 45300 | AZ99: 45348 | BA99: DEMOLIDO | BB99: FINALIZADO | BC99: =IF(AY99-KD99=0,"",AY99-O99) -> 411 | BD99: =IF(AND(AI99<>"SIM",AI99="UH"),"AA","INDENIZAÇÃO") -> INDENIZAÇÃO | BE99: =IF(AND(AY99<>"AGUARDANDO",AY99<>"",N99="AUXÍLIO ALUGUEL ATÉ INDENIZAÇÃO"),"SIM","NÃO") -> NÃO | BF99: N/A | BG99: N/A | BH99: N/A | BI99: FINALIZADO | BJ99: FINALIZADO | BK99: 45378 | BL99: FINALIZADO | BM99: FINALIZADO
A100: 87 | B100: PARAISÓPOLIS/ANTONICO | C100: 2 | D100: 024 | E100: URG | F100: 024/0074/A | G100: OCUPADO | H100: RESIDENCIAL | I100: INQUILINO | J100: STEPHANI OLIVEIRA DOS SANTOS COSTA | K100: 38.246.276-2 | L100: 495.627.538-24 | M100: CADASTRADO | N100: AUXÍLIO ALUGUEL UH | O100: 44866 | P100: 44889 | Q100: 6014.2021/0000734-3 | R100: FINALIZADO | S100: FINALIZADO | T100: FINALIZADO | U100: 44903 | V100: 44903 | W100: 44903 | X100: 44958 | Y100: 44958 | Z100: 45069 | AB100: PRISCILA SILVA ROLT | AC100: 48.357.345-0 | AD100: 391.248.498-80 | AE100: PROPRIETÁRIO NÃO RESIDENTE | AF100: CADASTRADO | AG100: 0 | AH100: 60000 | AI100: SIM | AJ100: 6014.2022/0000163-0 | AK100: FINALIZADO | AL100: FINALIZADO | AM100: FINALIZADO | AN100: SEM PENDÊNCIA | AP100: 6014.2022/0003758-9 | AQ100: FINALIZADO | AR100: FINALIZADO | AS100: FINALIZADO | AT100: FINALIZADO | AU100: 45013 | AV100: FINALIZADO | AW100: FINALIZADO | AX100: 45063 | AY100: 45063 | AZ100: 45069 | BA100: DESCARACTERIZADO | BB100: FINALIZADO | BC100: =IF(AY100-KD100=0,"",AY100-O100) -> 197 | BD100: =IF(AND(AI100<>"SIM",AI100="UH"),"AA","INDENIZAÇÃO") -> INDENIZAÇÃO | BE100: =IF(AND(AY100<>"AGUARDANDO",AY100<>"",N100="AUXÍLIO ALUGUEL ATÉ INDENIZAÇÃO"),"SIM","NÃO") -> NÃO | BF100: N/A | BG100: N/A | BH100: N/A | BI100: FINALIZADO | BJ100: FINALIZADO | BK100: 45175 | BL100: FINALIZADO | BM100: FINALIZADO
A101: 88 | B101: PARAISÓPOLIS/ANTONICO | C101: 2 | D101: 024 | E101: URG | F101: 024/0074/B | G101: OCUPADO | H101: RESIDENCIAL | I101: INQUILINO | J101: ANDREA APARECIDA QUIRINO | K101: 35.079.616-6 | L101: 324.991.728-19 | M101: CADASTRADO | N101: AUXÍLIO ALUGUEL UH | O101: 44866 | P101: 44889 | Q101: 6014.2021/0000734-3 | R101: FINALIZADO | S101: FINALIZADO | T101: FINALIZADO | U101: 44903 | V101: 44903 | W101: 44903 | X101: 44958 | Y101: 44958 | Z101: 45022 | AB101: AGUINALDO FERREIRA GUILHERME | AC101: 30.094.485-8 | AD101: 372.781.426-87 | AE101: PROPRIETÁRIO NÃO RESIDENTE | AF101: CADASTRADO | AG101: 0 | AH101: 60000 | AI101: SIM | AJ101: 6014.2022/0000163-0 | AK101: FINALIZADO | AL101: FINALIZADO | AM101: FINALIZADO | AN101: SEM PENDÊNCIA | AP101: 6014.2022/0003759-7 | AQ101: FINALIZADO | AR101: FINALIZADO | AS101: FINALIZADO | AT101: FINALIZADO | AU101: 44961 | AV101: FINALIZADO | AW101: FINALIZADO | AX101: 45015 | AY101: 45015 | AZ101: 45022 | BA101: DESCARACTERIZADO | BB101: FINALIZADO | BC101: =IF(AY101-KD101=0,"",AY101-O101) -> 149 | BD101: =IF(AND(AI101<>"SIM",AI101="UH"),"AA","INDENIZAÇÃO") -> INDENIZAÇÃO | BE101: =IF(AND(AY101<>"AGUARDANDO",AY101<>"",N101="AUXÍLIO ALUGUEL ATÉ INDENIZAÇÃO"),"SIM","NÃO") -> NÃO | BF101: N/A | BG101: N/A | BH101: N/A | BI101: FINALIZADO | BJ101: FINALIZADO | BK101: 45175 | BL101: FINALIZADO | BM101: FINALIZADO
A102: 89 | B102: PARAISÓPOLIS/ANTONICO | C102: 2 | D102: 024 | E102: URG | F102: 024/0074/C | G102: OCUPADO | H102: RESIDENCIAL | I102: INQUILINO | J102: AFRISIO VIRGINIO DOS SANTOS | K102: 50.430.230-9 | L102: 314.455.978-45 | M102: CADASTRADO | N102: AUXÍLIO ALUGUEL UH | O102: 44844 | P102: 44889 | Q102: 6014.2021/0000734-3 | R102: FINALIZADO | S102: FINALIZADO | T102: FINALIZADO | U102: 44903 | V102: 44903 | W102: 44973 | X102: 44958 | Y102: 44974 | Z102: 45019 | AA102: Emissão de um novo cartão em 16/02/2023 | AB102: VERINA DOS SANTOS SILVA | AC102: 53.526.629-7 | AD102: 001.624.147-90 | AE102: PROPRIETÁRIO NÃO RESIDENTE | AF102: CADASTRADO | AG102: 62209.27 | AH102: 62209.27 | AI102: SIM | AJ102: 6014.2022/0000163-0 | AK102: FINALIZADO | AL102: FINALIZADO | AM102: FINALIZADO | AN102: SEM PENDÊNCIA | AP102: 6014.2022/0004097-0 | AQ102: FINALIZADO | AR102: FINALIZADO | AS102: FINALIZADO | AT102: FINALIZADO | AU102: 44923 | AV102: FINALIZADO | AW102: FINALIZADO | AX102: 44924 | AY102: 44924 | AZ102: 45019 | BA102: DESCARACTERIZADO | BB102: FINALIZADO | BC102: =IF(AY102-KD102=0,"",AY102-O102) -> 80 | BD102: =IF(AND(AI102<>"SIM",AI102="UH"),"AA","INDENIZAÇÃO") -> INDENIZAÇÃO | BE102: =IF(AND(AY102<>"AGUARDANDO",AY102<>"",N102="AUXÍLIO ALUGUEL ATÉ INDENIZAÇÃO"),"SIM","NÃO") -> NÃO | BF102: N/A | BG102: N/A | BH102: N/A | BI102: FINALIZADO | BJ102: FINALIZADO | BK102: 45057 | BL102: FINALIZADO | BM102: FINALIZADO
A103: 90 | B103: PARAISÓPOLIS/ANTONICO | C103: 2 | D103: 024 | E103: URG | F103: 024/0074/D | G103: VAZIO | H103: RESIDENCIAL | I103: PROPRIETÁRIO NÃO RESIDENTE | J103: SARAH CAROLINE SILVA GUILHERME | K103: 38.807.486-3 | L103: 429.835.748-14 | M103: CADASTRADO | N103: INDENIZAÇÃO | O103: 44866 | P103: N/A | Q103: N/A | R103: N/A | S103: N/A | T103: N/A | U103: N/A | V103: N/A | W103: N/A | X103: N/A | Y103: N/A | Z103: N/A | AB103: SARAH CAROLINE SILVA GUILHERME | AC103: 38.807.486-3 | AD103: 429.835.748-14 | AE103: PROPRIETÁRIO NÃO RESIDENTE | AF103: CADASTRADO | AG103: 30461.79 | AH103: 60000 | AI103: SIM | AJ103: 6014.2022/0000163-0 | AK103: FINALIZADO | AL103: FINALIZADO | AM103: FINALIZADO | AN103: SEM PENDÊNCIA | AP103: 6014.2023/0000457-7 | AQ103: FINALIZADO | AR103: FINALIZADO | AS103: FINALIZADO | AT103: FINALIZADO | AU103: 45013 | AV103: FINALIZADO | AW103: FINALIZADO | AX103: 45063 | AY103: 45063 | AZ103: 45082 | BA103: DESCARACTERIZADO | BB103: FINALIZADO | BC103: =IF(AY103-KD103=0,"",AY103-O103) -> 197 | BD103: =IF(AND(AI103<>"SIM",AI103="UH"),"AA","INDENIZAÇÃO") -> INDENIZAÇÃO | BE103: =IF(AND(AY103<>"AGUARDANDO",AY103<>"",N103="AUXÍLIO ALUGUEL ATÉ INDENIZAÇÃO"),"SIM","NÃO") -> NÃO | BF103: N/A | BG103: N/A | BH103: N/A | BI103: FINALIZADO | BJ103: FINALIZADO | BK103: 45175 | BL103: FINALIZADO | BM103: FINALIZADO
...

Sheet EMAIL
F2: PUBLICAÇÃO DOC
F3: PREVISÃO PAGAMENTO | M3: 024/0030/B | O3: 029/0024/C
A4: ÁREA | B4: FASE | C4: SELO | D4: TITULAR | E4: PREVISÃO PAGAMENTO | F4: CONFIRMAÇÃO PAGAMENTO | G4: ÁREA | H4: SELO | I4: PROPRIETÁRIO | J4: CPF | K4: No PROCESSO SEI (INDENIZAÇÃO) | M4: 024/0041/A | O4: 029/0023/E
A5: PARAISÓPOLIS/ANTONICO | B5: 3 | C5: 025/0025/S | D5: BEATRIZ LIMA DOS SANTOS | E5: 46259 | G5: PARAISÓPOLIS/ANTONICO | H5: 027/0009/B | I5: MATHEUS DA SILVA COSTA | J5: 484.521.348-60 | K5: 6014.2024/0005253-0 | M5: 024/0052/A | O5: 031/0033/Q
G6: PARAISÓPOLIS/ANTONICO | H6: 031/0020/G | I6: EDILSON GUIMARÃES DE CARVALHO | J6: 418.009.058-90 | K6: 6014.2024/0003508-3 | M6: 024/0055/B | O6: 029/0066/A
M7: 024/0070/E | O7: 031/0022/E
M8: 024/0077/B | O8: 031/0031/B
M9: 024/0079/C | O9: 031/0020/C
M10: 024/0099/A | O10: 031/0033/K
M11: 024/0102/D | O11: 029/0016/B
M12: 024/0105/A | O12: 029/0066/E
M13: 024/0105/B | O13: 024/0099/A
M14: 029/0007/A | O14: 029/0022/B
M15: 029/0016/B | O15: 029/0081/A
M16: 029/0022/B | O16: 024/0052/A
M17: 029/0023/E | O17: 029/0035/B
M18: 029/0024/C | O18: 029/0027/A
... M22: 029/0045/A | O22: 029/0007/A
A23: PARAISÓPOLIS/ANTONICO | B23: 4 | C23: 031/0078/A | D23: MARIA JOSÉ DOS SANTOS | E23: 45300 | M23: 029/0061/A | O23: 029/0070/C
A24: PARAISÓPOLIS/ANTONICO | B24: 4 | C24: 031/0078/B | D24: BRUNO DA SILVA MARQUES | E24: 45300 | M24: 029/0064/A | O24: 029/0007/B
A25: PARAISÓPOLIS/ANTONICO | B25: 4 | C25: 031/0078/E | D25: JURACEMA RIBEIRO DE JESUS DIAS | E25: 45300 | M25: 029/0064/F | O25: 029/0070/B
A26: PARAISÓPOLIS/ANTONICO | D26: MARIA JOSÉ DOS SANTOS | M26: 029/0066/A | O26: 029/0045/A
A27: PARAISÓPOLIS/ANTONICO | D27: BRUNO DA SILVA MARQUES | M27: 029/0066/B | O27: 024/0102/D
A28: PARAISÓPOLIS/ANTONICO | D28: JURACEMA RIBEIRO DE JESUS DIAS | M28: 029/0066/E | O28: 024/0041/A
A29: PARAISÓPOLIS/ANTONICO | D29: MARIA JOSÉ DOS SANTOS | M29: 029/0067/A | O29: 031/0035/A
D30: BRUNO DA SILVA MARQUES | M30: 029/0067/F | O30: 031/0067/B
D31: JURACEMA RIBEIRO DE JESUS DIAS | M31: 029/0069/B | O31: 024/0077/B
D32: MARIA JOSÉ DOS SANTOS | M32: 029/0069/C | O32: 033/0016/C
D33: BRUNO DA SILVA MARQUES | M33: 029/0069/D | O33: 029/0069/C
D34: JURACEMA RIBEIRO DE JESUS DIAS | M34: 029/0070/B | O34: 029/0061/A
D35: MARIA JOSÉ DOS SANTOS | M35: 029/0070/C | O35: 029/0066/B
A36: PARAISÓPOLIS/ANTONICO | B36: 4 | C36: 031/0033/Q | D36: BRUNO DA SILVA MARQUES | E36: 45247 | M36: 029/0071/B | O36: 029/0071/D
A37: PARAISÓPOLIS/ANTONICO | B37: 4 | C37: 031/0034/I | D37: JURACEMA RIBEIRO DE JESUS DIAS | E37: 45247 | M37: 029/0071/D | O37: 031/0058/A
A38: PARAISÓPOLIS/ANTONICO | B38: 4 | C38: 031/0034/J | D38: MARIA JOSÉ DOS SANTOS | E38: 45244 | M38: 029/0071/E | O38: 029/0036/F
A39: PARAISÓPOLIS/ANTONICO | B39: 4 | C39: 031/0040/C | D39: BRUNO DA SILVA MARQUES | E39: 45243 | M39: 029/0080/E | O39: 031/0067/A
A40: PARAISÓPOLIS/ANTONICO | B40: 4 | C40: 031/0076/B | D40: JURACEMA RIBEIRO DE JESUS DIAS | E40: 45243 | M40: 029/0081/A | O40: 031/0028/L
A41: PARAISÓPOLIS/ANTONICO | B41: 4 | C41: 031/0076/C | D41: MARIA JOSÉ DOS SANTOS | E41: 45243 | M41: 029/0083/A | O41: 024/0105/A
A42: PARAISÓPOLIS/ANTONICO | B42: 4 | C42: 031/0076/D | D42: BRUNO DA SILVA MARQUES | E42: 45243 | M42: 029/0085/G | O42: 029/0064/F
D43: JURACEMA RIBEIRO DE JESUS DIAS | M43: 029/0086/B | O43: 031/0025/A
D44: MARIA JOSÉ DOS SANTOS | M44: 031/0004/C | O44: 024/0051/A
D45: BRUNO DA SILVA MARQUES | M45: 031/0014/A | O45: 024/0030/B
D46: JURACEMA RIBEIRO DE JESUS DIAS | M46: 031/0015/D | O46: 029/0083/A
D47: MARIA JOSÉ DOS SANTOS | M47: 031/0020/B | O47: 031/0004/C
D48: BRUNO DA SILVA MARQUES | M48: 031/0020/C | O48: 031/0014/A
D49: JURACEMA RIBEIRO DE JESUS DIAS | M49: 031/0022/B | O49: 033/0029/B
A50: PARAISÓPOLIS/ANTONICO | B50: 4 | C50: 031/0034/J | D50: MARIA JOSÉ DOS SANTOS | E50: 45224 | M50: 031/0022/E | O50: 029/0071/E
A51: PARAISÓPOLIS/ANTONICO | B51: 4 | C51: 031/0040/C | D51: BRUNO DA SILVA MARQUES | E51: 45224 | M51: 031/0025/A | O51: 031/0033/E
A52: PARAISÓPOLIS/ANTONICO | B52: 4 | C52: 031/0076/B | D52: JURACEMA RIBEIRO DE JESUS DIAS | E52: 45224 | M52: 031/0028/D | O52: 024/0070/E
A53: PARAISÓPOLIS/ANTONICO | B53: 4 | C53: 031/0076/C | D53: MARIA JOSÉ DOS SANTOS | E53: 45224 | M53: 031/0028/L | O53: 024/0079/C
A54: PARAISÓPOLIS/ANTONICO | B54: 4 | C54: 031/0076/D | D54: BRUNO DA SILVA MARQUES | E54: 45224 | M54: 031/0031/B | O54: 031/0015/D
D55: JURACEMA RIBEIRO DE JESUS DIAS | M55: 031/0033/E | O55: 033/0030/A
D56: MARIA JOSÉ DOS SANTOS | M56: 031/0033/K | O56: 024/0041/B
D57: BRUNO DA SILVA MARQUES | M57: 031/0033/Q | O57: 031/0020/B
D58: JURACEMA RIBEIRO DE JESUS DIAS | M58: 031/0035/A | O58: 031/0035/B
D59: MARIA JOSÉ DOS SANTOS | M59: 031/0035/B | O59: 029/0085/G
D60: BRUNO DA SILVA MARQUES | M60: 031/0039/C | O60: 031/0022/B
D61: JURACEMA RIBEIRO DE JESUS DIAS | M61: 031/0058/A | O61: 029/0067/F
D62: MARIA JOSÉ DOS SANTOS | M62: 031/0067/A | O62: 024/0088/B
D63: BRUNO DA SILVA MARQUES | M63: 031/0067/B | O63: 029/0039/B
D64: JURACEMA RIBEIRO DE JESUS DIAS | M64: 033/0016/C
D65: MARIA JOSÉ DOS SANTOS | M65: 033/0029/B
D66: BRUNO DA SILVA MARQUES | M66: 033/0030/A
D67: JURACEMA RIBEIRO DE JESUS DIAS
D68: MARIA JOSÉ DOS SANTOS
D69: BRUNO DA SILVA MARQUES
A70: PARAISÓPOLIS/ANTONICO | B70: 3 | C70: 027/0014/H | D70: JURACEMA RIBEIRO DE JESUS DIAS | E70: 45224
A71: PARAISÓPOLIS/ANTONICO | B71: 3 | C71: 027/0016/B | D71: MARIA JOSÉ DOS SANTOS | E71: 45224
A72: PARAISÓPOLIS/ANTONICO | B72: 3 | C72: 027/0016/C | D72: BRUNO DA SILVA MARQUES | E72: 45224
A73: PARAISÓPOLIS/ANTONICO | B73: 4 | C73: 029/0018/A | D73: JURACEMA RIBEIRO DE JESUS DIAS | E73: 45224
A74: PARAISÓPOLIS/ANTONICO | B74: 4 | C74: 029/0024/D | D74: MARIA JOSÉ DOS SANTOS | E74: 45224
A75: PARAISÓPOLIS/ANTONICO | B75: 4 | C75: 029/0025/A | D75: BRUNO DA SILVA MARQUES | E75: 45224
A76: PARAISÓPOLIS/ANTONICO | B76: 4 | C76: 029/0036/L | D76: JURACEMA RIBEIRO DE JESUS DIAS | E76: 45224
A77: PARAISÓPOLIS/ANTONICO | B77: 4 | C77: 029/0036/M | D77: MARIA JOSÉ DOS SANTOS | E77: 45224
A78: PARAISÓPOLIS/ANTONICO | B78: 4 | C78: 029/0036/N | D78: BRUNO DA SILVA MARQUES | E78: 45224
A79: PARAISÓPOLIS/ANTONICO | B79: 4 | C79: 029/0036/O | D79: JURACEMA RIBEIRO DE JESUS DIAS | E79: 45224
A80: PARAISÓPOLIS/ANTONICO | B80: 4 | C80: 029/0042/A | D80: MARIA JOSÉ DOS SANTOS | E80: 45224
A81: PARAISÓPOLIS/ANTONICO | B81: 4 | C81: 029/0042/B | D81: BRUNO DA SILVA MARQUES | E81: 45224
... A104: PARAISÓPOLIS/ANTONICO | B104: 4 | C104: 031/0058/H | D104: MARIA JOSÉ DOS SANTOS | E104: 45224
A105: PARAISÓPOLIS/ANTONICO | B105: 4 | C105: 031/0078/A | D105: BRUNO DA SILVA MARQUES | E105: N/A
A106: PARAISÓPOLIS/ANTONICO | B106: 4 | C106: 031/0078/B | D106: JURACEMA RIBEIRO DE JESUS DIAS | E106: 45049
A107: PARAISÓPOLIS/ANTONICO | B107: 5 | C107: 033/0029/C | D107: MARIA JOSÉ DOS SANTOS | E107: N/A
A108: PARAISÓPOLIS/ANTONICO | B108: 5 | C108: 035/0029/A | D108: BRUNO DA SILVA MARQUES | E108: N/A
D109: JURACEMA RIBEIRO DE JESUS DIAS | E109: N/A
D110: MARIA JOSÉ DOS SANTOS | E110: 44910
D111: BRUNO DA SILVA MARQUES | E111: 44840
D112: JURACEMA RIBEIRO DE JESUS DIAS | E112: N/A
D113: MARIA JOSÉ DOS SANTOS | E113: N/A
D114: BRUNO DA SILVA MARQUES | E114: 44877
D115: JURACEMA RIBEIRO DE JESUS DIAS | E115: N/A
D116: MARIA JOSÉ DOS SANTOS | E116: N/A
D117: BRUNO DA SILVA MARQUES | E117: 44840
D118: JURACEMA RIBEIRO DE JESUS DIAS | E118: N/A
D119: MARIA JOSÉ DOS SANTOS | E119: N/A
D120: BRUNO DA SILVA MARQUES | E120: N/A
D121: JURACEMA RIBEIRO DE JESUS DIAS | E121: N/A
C122: 025/0006/K | D122: MARIA JOSÉ DOS SANTOS | E122: N/A
C123: 025/0006/L | D123: BRUNO DA SILVA MARQUES | E123: N/A
C124: 025/0007/A | D124: JURACEMA RIBEIRO DE JESUS DIAS | E124: N/A
C125: 025/0007/B | D125: MARIA JOSÉ DOS SANTOS | E125: N/A
C126: 025/0007/C | D126: BRUNO DA SILVA MARQUES | E126: N/A
...

Sheet Quantitativo Fora da Demanda
A1: REPROVADOS QUE NÃO DEVERÃO SER REASSENTADOS NO ESPANHA | E1: APROVADOS SEM CONDOMÍNIO QUE DEVERÃO SER REASSENTADOS NO CHÁCARA DO CONDE
A2: ÁREA | B2: QTD | E2: ÁREA | F2: QTD
A3: AUXÍLIO ALUGUEL | B3: 39 | E3: AUXÍLIO ALUGUEL | F3: 54
A4: CANTINHO DO CÉU (OBRAS) | B4: 15 | E4: CANTINHO DO CÉU (OBRAS) SETORES: 138 E 140 | F4: 13
A5: FUMAÇA | B5: 7 | E5: FUMAÇA | F5: 15
A6: NEBLINA | B6: 2 | E6: NEBLINA | F6: 9
A7: LEBLON | B7: 0 | E7: LEBLON | F7: 9
A8: PABREU / PRAINHA | B8: 15 | E8: PABREU / PRAINHA | F8: 21
A9: TOTAL | B9: =SUM(B3:B8) -> 78 | E9: TOTAL | F9: =SUM(F3:F8) -> 121

Sheet Listas (não utilizar)
A1: Área | B1: Condomínio | C1: Bloco | D1: Apartamento | E1: SITAH / CAIXA | F1: Status CAIXA | G1: Adequacao Imovel | H1: Renúncia | I1: Pendência | J1: Pendências / Reprovados caixa
A2: ALTO DA ALEGRIA | B2: AVILA | C2: 1 | D2: 101 | E2: AGENDADO | F2: APROVADO | G2: NÃO | H2: NÃO | I2: CRAS | J2: RENDA SUPERIOR
A3: ALTO DA ALEGRIA (OBRAS) | B3: BARCELONA | C3: 2 | D3: 102 | E3: AGUARDANDO OFICIO | F3: REPROVADO | G3: FÍSICA | H3: RENDA | I3: CRAS + DOCUMENTOS | J3: CADMUT
A4: ALTO DA ALEGRIA (RESERVA) | B4: BILBAO | C4: 3 | D4: 103 | E4: ATENDIMENTO CANCELADO | F4: PENDENCIA | G4: VISUAL | H4: CADIN | I4: DOCUMENTOS | J4: CADIN
A5: ANTERO GOMES | B5: CEUTA | C5: 4 | D5: 104 | E5: CADMUT | F5: SEM DOSSIE | G5: INTELECTUAL | H5: ESTADO CIVIL | I5: CADIN
A6: CANTINHO DO CEU / GAIVOTAS | B6: IBIZA | C6: 5 | D6: 201 | E6: CHACARA DO CONDE | G6: AUDITIVA | H6: SEPARACAO | I6: CRAS + CADIN
A7: CANTINHO DO CEU / OBRAS | B7: LEAO | C7: 6 | D7: 202 | E7: CONFLITO | G7: NANISMO | I7: R.LI.AV.
A8: CASTRO ALVES | B8: MADRID | C8: 7 | D8: 203 | E8: ENVIADO CAIXA | I8: IEME
A9: COCAIA | B9: MELILLA | C9: 8 | D9: 204 | E9: FALECEU
A10: ERUNDINA | B10: PAMPLONA | C10: 9 | D10: 301 | E10: FALTANTE DOSSIÊ
A11: FUMACA | B11: SALAMANCA | C11: 10 | D11: 302 | E11: HABISP ACERTO DE ÁREA
A12: GUAICURI (OBRAS) | B12: TERUEL | C12: 11 | D12: 303 | E12: HABISP AGUARDANDO CRÍTICA
A13: GUAICURI / CIDADE JULIA | B13: VALENCIA | C13: 12 | D13: 304 | E13: HABISP PEND DE ATUALIZ CADASTRAL
A14: JARDIM MIRNA | B14: VALVERDE | C14: 13 | D14: 401 | E14: INDENIZACAO
A15: JARDIM SELMA II | B15: VITORIA | C15: 14 | D15: 402 | E15: PENDENCIA
A16: JARDIM TUBO | C16: 15 | D16: 403 | E16: PERMUTA
A17: LEBLON | D17: 404 | E17: PESQUISA SMADS
A18: MARGINAL DOIS / FUNDAO | D18: 501 | E18: REANALISE
A19: MATA VIRGEM / JD ELDORADO | D19: 502 | E19: RECLUSO
A20: NEBLINA | D20: 503 | E20: RELATÓRIO SOCIAL
A21: NORONHA | D21: 504 | E21: RENDA SUPERIOR
A22: NOVA GRAJAU | E22: RESISTENTE
A23: NOVA MARILDA | E23: TROCA DE TITULARIDADE
A24: NOVA VARGINHA
A25: PABREU / PRAINHA
A26: PENDENCIA GABINETE
A27: PILAO / APURA
A28: PILAO / DOIS
A29: PILAO / PAULISTAS
A30: SANTA AMELIA
A31: VALE VERDE / MONTE VERDE
A32: VILA BREJINHO
A33: VILA NASCENTE
A34: ZR / COSTA BRANCA
A35: VILA RUBI

Sheet QUANT COND
A1: CONDOMINIOS | B1: QUANT
A2: AVILA | B2: =COUNTIF(#REF!,'QUANT COND'!A2) -> #REF!
A3: BARCELONA | B3: =COUNTIF(#REF!,'QUANT COND'!A3) -> #REF!
A4: BILBAO | B4: =COUNTIF(#REF!,'QUANT COND'!A4) -> #REF!
A5: CEUTA | B5: =COUNTIF(#REF!,'QUANT COND'!A5) -> #REF!
A6: IBIZA | B6: =COUNTIF(#REF!,'QUANT COND'!A6) -> #REF!
A7: LEAO | B7: =COUNTIF(#REF!,'QUANT COND'!A7) -> #REF!
A8: MADRID | B8: =COUNTIF(#REF!,'QUANT COND'!A8) -> #REF!
A9: MELILLA | B9: =COUNTIF(#REF!,'QUANT COND'!A9) -> #REF!
A10: PAMPLONA | B10: =COUNTIF(#REF!,'QUANT COND'!A10) -> #REF!
A11: SALAMANCA | B11: =COUNTIF(#REF!,'QUANT COND'!A11) -> #REF!
A12: TERUEL | B12: =COUNTIF(#REF!,'QUANT COND'!A12) -> #REF!
A13: VALENCIA | B13: =COUNTIF(#REF!,'QUANT COND'!A13) -> #REF!
... A15: VITORIA | B15: =COUNTIF(#REF!,'QUANT COND'!A15) -> #REF!

Sheet OFÍCIOS
A1: PLANILHA DE CONFRONTO OFÍCIOS DE INDICAÇÃO COM ENVIADOS CAIXA ECONÔMICA FEDERAL - CEF
A2: TITULAR | B2: CPF | C2: Cônjuge | D2: CPF | E2: OFÍCIO | F2: DATA | G2: STATUS CEF | H2: DATA ENVIO CAIXA | I2: DUPLICIDADE OFÍCIO | J2: DATA | K2: DATA ENVIO CAIXA | L2: OFÍCIO DE INDICAÇÃO | M2: DATA OFÍCIO INDICAÇÃO | O2: NR OFICIO | P2: QUANT | Q2: APROV | R2: REPROV | S2: PEND | T2: SEM STATUS (ANÁLISE) | Y2: CEF BD | Z2: CEF OFICIOS | AA2: CEF PLANILHA
A3: ABEL MEDEIROS FILHO | B3: 27140979871 | E3: 1128 | F3: 42972 | G3: APROVADO | H3: 42979 | O3: 810 | P3: =COUNTIF(OFÍCIOS!E:E,O3) -> 156 | Q3: =COUNTIFS(OFÍCIOS!$E:$E,$O3,OFÍCIOS!$G:$G,"APROVADO") -> 149 | R3: =COUNTIFS(OFÍCIOS!$E:$E,$O3,OFÍCIOS!$G:$G,"REPROVADO") -> 3 | S3: =COUNTIFS(OFÍCIOS!$E:$E,$O3,OFÍCIOS!$G:$G,"PENDENCIA") -> 2 | T3: =COUNTIFS(OFÍCIOS!$E:$E,$O3,OFÍCIOS!$G:$G,"") -> 2 | U3: =SUM(Q3:T3) -> 156 | X3: FEITOS | Y3: 1850 | Z3: 1827 | AA3: =SUM(AA4:AA7) -> 1615
A4: ABELINA FERREIRA DOS SANTOS | B4: 39200633846 | O4: 1417 | P4: =COUNTIF(OFÍCIOS!E:E,O4) -> 42 | Q4: =COUNTIFS(OFÍCIOS!$E:$E,$O4,OFÍCIOS!$G:$G,"APROVADO") -> 36 | R4: =COUNTIFS(OFÍCIOS!$E:$E,$O4,OFÍCIOS!$G:$G,"REPROVADO") -> 3 | S4: =COUNTIFS(OFÍCIOS!$E:$E,$O4,OFÍCIOS!$G:$G,"PENDENCIA") -> 3 | T4: =COUNTIFS(OFÍCIOS!$E:$E,$O4,OFÍCIOS!$G:$G,"") -> 0 | U4: =SUM(Q4:T4) -> 42 | X4: APROVADOS | Y4: 1517 | Z4: 1427 | AA4: 1559
A5: ABIGAIL DE OLIVEIRA PAULINO | B5: 75489104872 | E5: 1752 | F5: 43051 | G5: APROVADO | H5: 43089 | L5: 1759 | O5: 1359 | P5: =COUNTIF(OFÍCIOS!E:E,O5) -> 14 | Q5: =COUNTIFS(OFÍCIOS!$E:$E,$O5,OFÍCIOS!$G:$G,"APROVADO") -> 13 | R5: =COUNTIFS(OFÍCIOS!$E:$E,$O5,OFÍCIOS!$G:$G,"REPROVADO") -> 1 | S5: =COUNTIFS(OFÍCIOS!$E:$E,$O5,OFÍCIOS!$G:$G,"PENDENCIA") -> 0 | T5: =COUNTIFS(OFÍCIOS!$E:$E,$O5,OFÍCIOS!$G:$G,"") -> 0 | U5: =SUM(Q5:T5) -> 14 | X5: REPROVADOS | Y5: 73 | Z5: 79 | AA5: 28
A6: ABILIO OLIVEIRA SANTOS | B6: 43286003620 | O6: 1350 | P6: =COUNTIF(OFÍCIOS!E:E,O6) -> 79 | Q6: =COUNTIFS(OFÍCIOS!$E:$E,$O6,OFÍCIOS!$G:$G,"APROVADO") -> 75 | R6: =COUNTIFS(OFÍCIOS!$E:$E,$O6,OFÍCIOS!$G:$G,"REPROVADO") -> 3 | S6: =COUNTIFS(OFÍCIOS!$E:$E,$O6,OFÍCIOS!$G:$G,"PENDENCIA") -> 0 | T6: =COUNTIFS(OFÍCIOS!$E:$E,$O6,OFÍCIOS!$G:$G,"") -> 1 | U6: =SUM(Q6:T6) -> 79 | X6: PENDENCIAS | Y6: 36 | Z6: 32 | AA6: 11
A7: ABRAHAO SANTOS SILVA | O7: 1343 | P7: =COUNTIF(OFÍCIOS!E:E,O7) -> 6 | Q7: =COUNTIFS(OFÍCIOS!$E:$E,$O7,OFÍCIOS!$G:$G,"APROVADO") -> 5 | R7: =COUNTIFS(OFÍCIOS!$E:$E,$O7,OFÍCIOS!$G:$G,"REPROVADO") -> 0 | S7: =COUNTIFS(OFÍCIOS!$E:$E,$O7,OFÍCIOS!$G:$G,"PENDENCIA") -> 0 | T7: =COUNTIFS(OFÍCIOS!$E:$E,$O7,OFÍCIOS!$G:$G,"") -> 1 | U7: =SUM(Q7:T7) -> 6 | X7: SS / ANALISE | Y7: 224 | Z7: 275 | AA7: 17
A8: ADAIR DA SILVA BARROS | B8: 97443271620 | E8: 1106 | F8: 42965 | G8: APROVADO | H8: 42978 | O8: 1267 | P8: =COUNTIF(OFÍCIOS!E:E,O8) -> 34 | Q8: =COUNTIFS(OFÍCIOS!$E:$E,$O8,OFÍCIOS!$G:$G,"APROVADO") -> 28 | R8: =COUNTIFS(OFÍCIOS!$E:$E,$O8,OFÍCIOS!$G:$G,"REPROVADO") -> 5 | S8: =COUNTIFS(OFÍCIOS!$E:$E,$O8,OFÍCIOS!$G:$G,"PENDENCIA") -> 1 | T8: =COUNTIFS(OFÍCIOS!$E:$E,$O8,OFÍCIOS!$G:$G,"") -> 0 | U8: =SUM(Q8:T8) -> 34
A9: ADALBERTO CARVALHO DE OLIVEIRA | B9: 98058690597 | E9: 423 | F9: 43182 | G9: APROVADO | O9: 1262 | P9: =COUNTIF(OFÍCIOS!E:E,O9) -> 8 | Q9: =COUNTIFS(OFÍCIOS!$E:$E,$O9,OFÍCIOS!$G:$G,"APROVADO") -> 7 | R9: =COUNTIFS(OFÍCIOS!$E:$E,$O9,OFÍCIOS!$G:$G,"REPROVADO") -> 1 | S9: =COUNTIFS(OFÍCIOS!$E:$E,$O9,OFÍCIOS!$G:$G,"PENDENCIA") -> 0 | T9: =COUNTIFS(OFÍCIOS!$E:$E,$O9,OFÍCIOS!$G:$G,"") -> 0 | U9: =SUM(Q9:T9) -> 8
A10: ADALBERTO CAVALCANTE DOS SANTOS | B10: 38088438888 | O10: 1106 | P10: =COUNTIF(OFÍCIOS!E:E,O10) -> 78 | Q10: =COUNTIFS(OFÍCIOS!$E:$E,$O10,OFÍCIOS!$G:$G,"APROVADO") -> 73 | R10: =COUNTIFS(OFÍCIOS!$E:$E,$O10,OFÍCIOS!$G:$G,"REPROVADO") -> 5 | S10: =COUNTIFS(OFÍCIOS!$E:$E,$O10,OFÍCIOS!$G:$G,"PENDENCIA") -> 0 | T10: =COUNTIFS(OFÍCIOS!$E:$E,$O10,OFÍCIOS!$G:$G,"") -> 0 | U10: =SUM(Q10:T10) -> 78
A11: ADALMA MOREIRA DA ROCHA | B11: 26939799869 | E11: 573 | F11: 43224 | O11: 1128 | P11: =COUNTIF(OFÍCIOS!E:E,O11) -> 92 | Q11: =COUNTIFS(OFÍCIOS!$E:$E,$O11,OFÍCIOS!$G:$G,"APROVADO") -> 91 | R11: =COUNTIFS(OFÍCIOS!$E:$E,$O11,OFÍCIOS!$G:$G,"REPROVADO") -> 1 | S11: =COUNTIFS(OFÍCIOS!$E:$E,$O11,OFÍCIOS!$G:$G,"PENDENCIA") -> 0 | T11: =COUNTIFS(OFÍCIOS!$E:$E,$O11,OFÍCIOS!$G:$G,"") -> 0 | U11: =SUM(Q11:T11) -> 92
A12: ADAMILTON PEREIRA DA SILVA ( ALANA ) | B12: 34470559873 | E12: 292 | F12: 43168 | G12: APROVADO | H12: 43182 | L12: 318 | O12: 1214 | P12: =COUNTIF(OFÍCIOS!E:E,O12) -> 76 | Q12: =COUNTIFS(OFÍCIOS!$E:$E,$O12,OFÍCIOS!$G:$G,"APROVADO") -> 71 | R12: =COUNTIFS(OFÍCIOS!$E:$E,$O12,OFÍCIOS!$G:$G,"REPROVADO") -> 3 | S12: =COUNTIFS(OFÍCIOS!$E:$E,$O12,OFÍCIOS!$G:$G,"PENDENCIA") -> 0 | T12: =COUNTIFS(OFÍCIOS!$E:$E,$O12,OFÍCIOS!$G:$G,"") -> 2 | U12: =SUM(Q12:T12) -> 76
A13: ADAO MENDES AGOSTINHO | B13: 14369564808 | O13: 1241 | P13: =COUNTIF(OFÍCIOS!E:E,O13) -> 33 | Q13: =COUNTIFS(OFÍCIOS!$E:$E,$O13,OFÍCIOS!$G:$G,"APROVADO") -> 32 | R13: =COUNTIFS(OFÍCIOS!$E:$E,$O13,OFÍCIOS!$G:$G,"REPROVADO") -> 0 | S13: =COUNTIFS(OFÍCIOS!$E:$E,$O13,OFÍCIOS!$G:$G,"PENDENCIA") -> 1 | T13: =COUNTIFS(OFÍCIOS!$E:$E,$O13,OFÍCIOS!$G:$G,"") -> 0 | U13: =SUM(Q13:T13) -> 33
A14: ADEGMARIO DOS SANTOS | B14: 39544185844 | E14: 810 | F14: 42915 | G14: APROVADO | H14: 42921 | L14: 568-17 | O14: 1422 | P14: =COUNTIF(OFÍCIOS!E:E,O14) -> 7 | Q14: =COUNTIFS(OFÍCIOS!$E:$E,$O14,OFÍCIOS!$G:$G,"APROVADO") -> 7 | R14: =COUNTIFS(OFÍCIOS!$E:$E,$O14,OFÍCIOS!$G:$G,"REPROVADO") -> 0 | S14: =COUNTIFS(OFÍCIOS!$E:$E,$O14,OFÍCIOS!$G:$G,"PENDENCIA") -> 0 | T14: =COUNTIFS(OFÍCIOS!$E:$E,$O14,OFÍCIOS!$G:$G,"") -> 0 | U14: =SUM(Q14:T14) -> 7
A15: ADEILDA GABRIELA CAITANO SILVA | B15: 38772276860 | C15: LUCIANO MANOEL DA SILVA | D15: 3808243457 | O15: 1439 | P15: =COUNTIF(OFÍCIOS!E:E,O15) -> 16 | Q15: =COUNTIFS(OFÍCIOS!$E:$E,$O15,OFÍCIOS!$G:$G,"APROVADO") -> 14 | R15: =COUNTIFS(OFÍCIOS!$E:$E,$O15,OFÍCIOS!$G:$G,"REPROVADO") -> 1 | S15: =COUNTIFS(OFÍCIOS!$E:$E,$O15,OFÍCIOS!$G:$G,"PENDENCIA") -> 1 | T15: =COUNTIFS(OFÍCIOS!$E:$E,$O15,OFÍCIOS!$G:$G,"") -> 0 | U15: =SUM(Q15:T15) -> 16
A16: ADEILDA RODRIGUES DE OLIVEIRA | B16: 21538837846 | C16: PEDRO LUIZ SANTOS OLIVEIRA | D16: 94203180520 | E16: 810 | F16: 42915 | G16: APROVADO | H16: 42921 | L16: 568-17 | O16: 1451 | P16: =COUNTIF(OFÍCIOS!E:E,O16) -> 4 | Q16: =COUNTIFS(OFÍCIOS!$E:$E,$O16,OFÍCIOS!$G:$G,"APROVADO") -> 3 | R16: =COUNTIFS(OFÍCIOS!$E:$E,$O16,OFÍCIOS!$G:$G,"REPROVADO") -> 1 | S16: =COUNTIFS(OFÍCIOS!$E:$E,$O16,OFÍCIOS!$G:$G,"PENDENCIA") -> 0 | T16: =COUNTIFS(OFÍCIOS!$E:$E,$O16,OFÍCIOS!$G:$G,"") -> 0 | U16: =SUM(Q16:T16) -> 4
A17: ADEILDO ADELINO DE CARVALHO | B17: 57455392591 | O17: 1470 | P17: =COUNTIF(OFÍCIOS!E:E,O17) -> 4 | Q17: =COUNTIFS(OFÍCIOS!$E:$E,$O17,OFÍCIOS!$G:$G,"APROVADO") -> 4 | R17: =COUNTIFS(OFÍCIOS!$E:$E,$O17,OFÍCIOS!$G:$G,"REPROVADO") -> 0 | S17: =COUNTIFS(OFÍCIOS!$E:$E,$O17,OFÍCIOS!$G:$G,"PENDENCIA") -> 0 | T17: =COUNTIFS(OFÍCIOS!$E:$E,$O17,OFÍCIOS!$G:$G,"") -> 0 | U17: =SUM(Q17:T17) -> 4
A18: ADELCIDES DA CONCEICAO ALMEIDA | B18: 5304941594 | E18: 1106 | F18: 42965 | G18: APROVADO | H18: 42978 | O18: 1489 | P18: =COUNTIF(OFÍCIOS!E:E,O18) -> 35 | Q18: =COUNTIFS(OFÍCIOS!$E:$E,$O18,OFÍCIOS!$G:$G,"APROVADO") -> 34 | R18: =COUNTIFS(OFÍCIOS!$E:$E,$O18,OFÍCIOS!$G:$G,"REPROVADO") -> 0 | S18: =COUNTIFS(OFÍCIOS!$E:$E,$O18,OFÍCIOS!$G:$G,"PENDENCIA") -> 1 | T18: =COUNTIFS(OFÍCIOS!$E:$E,$O18,OFÍCIOS!$G:$G,"") -> 0 | U18: =SUM(Q18:T18) -> 35
A19: ADELIA MARIA DE OLIVEIRA | B19: 21600057896 | E19: 262 | F19: 43160 | G19: REPROVADO | H19: 43164 | L19: 255 | O19: 1555 | P19: =COUNTIF(OFÍCIOS!E:E,O19) -> 25 | Q19: =COUNTIFS(OFÍCIOS!$E:$E,$O19,OFÍCIOS!$G:$G,"APROVADO") -> 22 | R19: =COUNTIFS(OFÍCIOS!$E:$E,$O19,OFÍCIOS!$G:$G,"REPROVADO") -> 1 | S19: =COUNTIFS(OFÍCIOS!$E:$E,$O19,OFÍCIOS!$G:$G,"PENDENCIA") -> 2 | T19: =COUNTIFS(OFÍCIOS!$E:$E,$O19,OFÍCIOS!$G:$G,"") -> 0 | U19: =SUM(Q19:T19) -> 25
A20: ADEMARIO FERREIRA DOS SANTOS | B20: 18419589802 | O20: 1570 | P20: =COUNTIF(OFÍCIOS!E:E,O20) -> 24 | Q20: =COUNTIFS(OFÍCIOS!$E:$E,$O20,OFÍCIOS!$G:$G,"APROVADO") -> 23 | R20: =COUNTIFS(OFÍCIOS!$E:$E,$O20,OFÍCIOS!$G:$G,"REPROVADO") -> 1 | S20: =COUNTIFS(OFÍCIOS!$E:$E,$O20,OFÍCIOS!$G:$G,"PENDENCIA") -> 0 | T20: =COUNTIFS(OFÍCIOS!$E:$E,$O20,OFÍCIOS!$G:$G,"") -> 0 | U20: =SUM(Q20:T20) -> 24
A21: ADEMIR DA SILVA LIMA | B21: 15538537846 | E21: 573 | F21: 43224 | O21: 1752 | P21: =COUNTIF(OFÍCIOS!E:E,O21) -> 89 | Q21: =COUNTIFS(OFÍCIOS!$E:$E,$O21,OFÍCIOS!$G:$G,"APROVADO") -> 80 | R21: =COUNTIFS(OFÍCIOS!$E:$E,$O21,OFÍCIOS!$G:$G,"REPROVADO") -> 2 | S21: =COUNTIFS(OFÍCIOS!$E:$E,$O21,OFÍCIOS!$G:$G,"PENDENCIA") -> 5 | T21: =COUNTIFS(OFÍCIOS!$E:$E,$O21,OFÍCIOS!$G:$G,"") -> 2 | U21: =SUM(Q21:T21) -> 89
A22: ADENILDE SANTOS DA SILVA | B22: 899837506 | E22: 1824 | F22: 43091 | G22: APROVADO | H22: 43097 | L22: 1828 | O22: 1824 | P22: =COUNTIF(OFÍCIOS!E:E,O22) -> 81 | Q22: =COUNTIFS(OFÍCIOS!$E:$E,$O22,OFÍCIOS!$G:$G,"APROVADO") -> 67 | R22: =COUNTIFS(OFÍCIOS!$E:$E,$O22,OFÍCIOS!$G:$G,"REPROVADO") -> 7 | S22: =COUNTIFS(OFÍCIOS!$E:$E,$O22,OFÍCIOS!$G:$G,"PENDENCIA") -> 6 | T22: =COUNTIFS(OFÍCIOS!$E:$E,$O22,OFÍCIOS!$G:$G,"") -> 1 | U22: =SUM(Q22:T22) -> 81
A23: ADENILSON DA CONCEICAO | B23: 36197160803 | E23: 229 | F23: 43151 | G23: APROVADO | L23: 232 | O23: 1628 | P23: =COUNTIF(OFÍCIOS!E:E,O23) -> 6 | Q23: =COUNTIFS(OFÍCIOS!$E:$E,$O23,OFÍCIOS!$G:$G,"APROVADO") -> 5 | R23: =COUNTIFS(OFÍCIOS!$E:$E,$O23,OFÍCIOS!$G:$G,"REPROVADO") -> 1 | S23: =COUNTIFS(OFÍCIOS!$E:$E,$O23,OFÍCIOS!$G:$G,"PENDENCIA") -> 0 | T23: =COUNTIFS(OFÍCIOS!$E:$E,$O23,OFÍCIOS!$G:$G,"") -> 0 | U23: =SUM(Q23:T23) -> 6
A24: ADENIR MODESTO RIBEIRO | B24: 39248826814 | E24: 292 | F24: 43168 | G24: APROVADO | H24: 43182 | L24: 318 | O24: 608 | P24: =COUNTIF(OFÍCIOS!E:E,O24) -> 35 | Q24: =COUNTIFS(OFÍCIOS!$E:$E,$O24,OFÍCIOS!$G:$G,"APROVADO") -> 31 | R24: =COUNTIFS(OFÍCIOS!$E:$E,$O24,OFÍCIOS!$G:$G,"REPROVADO") -> 3 | S24: =COUNTIFS(OFÍCIOS!$E:$E,$O24,OFÍCIOS!$G:$G,"PENDENCIA") -> 1 | T24: =COUNTIFS(OFÍCIOS!$E:$E,$O24,OFÍCIOS!$G:$G,"") -> 0 | U24: =SUM(Q24:T24) -> 35
A25: ADILINA FARIAS DO NASCIMENTO | B25: 48925276534 | E25: 229 | F25: 43151 | L25: 232 | O25: 527 | P25: =COUNTIF(OFÍCIOS!E:E,O25) -> 29 | Q25: =COUNTIFS(OFÍCIOS!$E:$E,$O25,OFÍCIOS!$G:$G,"APROVADO") -> 0 | R25: =COUNTIFS(OFÍCIOS!$E:$E,$O25,OFÍCIOS!$G:$G,"REPROVADO") -> 0 | S25: =COUNTIFS(OFÍCIOS!$E:$E,$O25,OFÍCIOS!$G:$G,"PENDENCIA") -> 0 | T25: =COUNTIFS(OFÍCIOS!$E:$E,$O25,OFÍCIOS!$G:$G,"") -> 29 | U25: =SUM(Q25:T25) -> 29
A26: ADILSON SOARES DA COSTA | O26: 509 | P26: =COUNTIF(OFÍCIOS!E:E,O26) -> 14 | Q26: =COUNTIFS(OFÍCIOS!$E:$E,$O26,OFÍCIOS!$G:$G,"APROVADO") -> 0 | R26: =COUNTIFS(OFÍCIOS!$E:$E,$O26,OFÍCIOS!$G:$G,"REPROVADO") -> 0 | S26: =COUNTIFS(OFÍCIOS!$E:$E,$O26,OFÍCIOS!$G:$G,"PENDENCIA") -> 0 | T26: =COUNTIFS(OFÍCIOS!$E:$E,$O26,OFÍCIOS!$G:$G,"") -> 14 | U26: =SUM(Q26:T26) -> 14
A27: ADMEIA BARBOSA DE SOUZA | B27: 25894152810 | C27: REINALDO SANTOS REIS | D27: 8263008808 | E27: 292 | F27: 43168 | G27: APROVADO | H27: 43182 | L27: 318 | O27: 292 | P27: =COUNTIF(OFÍCIOS!E:E,O27) -> 233 | Q27: =COUNTIFS(OFÍCIOS!$E:$E,$O27,OFÍCIOS!$G:$G,"APROVADO") -> 212 | R27: =COUNTIFS(OFÍCIOS!$E:$E,$O27,OFÍCIOS!$G:$G,"REPROVADO") -> 9 | S27: =COUNTIFS(OFÍCIOS!$E:$E,$O27,OFÍCIOS!$G:$G,"PENDENCIA") -> 0 | T27: =COUNTIFS(OFÍCIOS!$E:$E,$O27,OFÍCIOS!$G:$G,"") -> 12 | U27: =SUM(Q27:T27) -> 233
A28: ADONES FERREIRA JORGE | B28: 43026389587 | C28: EUNICE FELICIANA BRITO JORGE | D28: 29124464813 | E28: 485 | F28: 43196 | H28: 43206 | L28: 483 | O28: 573 | P28: =COUNTIF(OFÍCIOS!E:E,O28) -> 43 | Q28: =COUNTIFS(OFÍCIOS!$E:$E,$O28,OFÍCIOS!$G:$G,"APROVADO") -> 0 | R28: =COUNTIFS(OFÍCIOS!$E:$E,$O28,OFÍCIOS!$G:$G,"REPROVADO") -> 0 | S28: =COUNTIFS(OFÍCIOS!$E:$E,$O28,OFÍCIOS!$G:$G,"PENDENCIA") -> 0 | T28: =COUNTIFS(OFÍCIOS!$E:$E,$O28,OFÍCIOS!$G:$G,"") -> 43 | U28: =SUM(Q28:T28) -> 43
A29: ADRIANA ALVES DA SILVA | B29: 26245112885 | E29: 262 | F29: 43160 | G29: REPROVADO | H29: 43164 | L29: 255 | O29: 563 | P29: =COUNTIF(OFÍCIOS!E:E,O29) -> 64 | Q29: =COUNTIFS(OFÍCIOS!$E:$E,$O29,OFÍCIOS!$G:$G,"APROVADO") -> 0 | R29: =COUNTIFS(OFÍCIOS!$E:$E,$O29,OFÍCIOS!$G:$G,"REPROVADO") -> 0 | S29: =COUNTIFS(OFÍCIOS!$E:$E,$O29,OFÍCIOS!$G:$G,"PENDENCIA") -> 0 | T29: =COUNTIFS(OFÍCIOS!$E:$E,$O29,OFÍCIOS!$G:$G,"") -> 64 | U29: =SUM(Q29:T29) -> 64
A30: ADRIANA ALVES FERREIRA | B30: 36531080809 | C30: MARCIO ROSA DE MIRA | D30: 22485483892 | E30: 1489 | F30: 43038 | G30: APROVADO | L30: 1647-17 | O30: 443 | P30: =COUNTIF(OFÍCIOS!E:E,O30) -> 66 | Q30: =COUNTIFS(OFÍCIOS!$E:$E,$O30,OFÍCIOS!$G:$G,"APROVADO") -> 0 | R30: =COUNTIFS(OFÍCIOS!$E:$E,$O30,OFÍCIOS!$G:$G,"REPROVADO") -> 0 | S30: =COUNTIFS(OFÍCIOS!$E:$E,$O30,OFÍCIOS!$G:$G,"PENDENCIA") -> 0 | T30: =COUNTIFS(OFÍCIOS!$E:$E,$O30,OFÍCIOS!$G:$G,"") -> 66 | U30: =SUM(Q30:T30) -> 66
A31: ADRIANA APARECIDA ROBERTO | B31: 28147186819 | C31: CARLOS ANTONIO BATISTA DOS SANTOS | D31: 24499714400 | O31: 423 | P31: =COUNTIF(OFÍCIOS!E:E,O31) -> 9 | Q31: =COUNTIFS(OFÍCIOS!$E:$E,$O31,OFÍCIOS!$G:$G,"APROVADO") -> 7 | R31: =COUNTIFS(OFÍCIOS!$E:$E,$O31,OFÍCIOS!$G:$G,"REPROVADO") -> 1 | S31: =COUNTIFS(OFÍCIOS!$E:$E,$O31,OFÍCIOS!$G:$G,"PENDENCIA") -> 0 | T31: =COUNTIFS(OFÍCIOS!$E:$E,$O31,OFÍCIOS!$G:$G,"") -> 1 | U31: =SUM(Q31:T31) -> 9
A32: ADRIANA ARAUJO DE LIMA | B32: 37559228860 | C32: ALEXANDRO ARAUJO DE LIMA | D32: 28072024892 | E32: 1555 | F32: 43049 | G32: APROVADO | O32: 229 | P32: =COUNTIF(OFÍCIOS!E:E,O32) -> 89 | Q32: =COUNTIFS(OFÍCIOS!$E:$E,$O32,OFÍCIOS!$G:$G,"APROVADO") -> 81 | R32: =COUNTIFS(OFÍCIOS!$E:$E,$O32,OFÍCIOS!$G:$G,"REPROVADO") -> 2 | S32: =COUNTIFS(OFÍCIOS!$E:$E,$O32,OFÍCIOS!$G:$G,"PENDENCIA") -> 5 | T32: =COUNTIFS(OFÍCIOS!$E:$E,$O32,OFÍCIOS!$G:$G,"") -> 1 | U32: =SUM(Q32:T32) -> 89
A33: ADRIANA CORDEIRO MACHADO | B33: 23635229822 | C33: ANDERSON DE MORAIS SANTOS | D33: 21668057875 | E33: 262 | F33: 43160 | G33: APROVADO | H33: 43164 | L33: 255 | O33: 262 | P33: =COUNTIF(OFÍCIOS!E:E,O33) -> 224 | Q33: =COUNTIFS(OFÍCIOS!$E:$E,$O33,OFÍCIOS!$G:$G,"APROVADO") -> 181 | R33: =COUNTIFS(OFÍCIOS!$E:$E,$O33,OFÍCIOS!$G:$G,"REPROVADO") -> 15 | S33: =COUNTIFS(OFÍCIOS!$E:$E,$O33,OFÍCIOS!$G:$G,"PENDENCIA") -> 0 | T33: =COUNTIFS(OFÍCIOS!$E:$E,$O33,OFÍCIOS!$G:$G,"") -> 28 | U33: =SUM(Q33:T33) -> 224
A34: ADRIANA DA SILVA | O34: 117 | P34: =COUNTIF(OFÍCIOS!E:E,O34) -> 91 | Q34: =COUNTIFS(OFÍCIOS!$E:$E,$O34,OFÍCIOS!$G:$G,"APROVADO") -> 77 | R34: =COUNTIFS(OFÍCIOS!$E:$E,$O34,OFÍCIOS!$G:$G,"REPROVADO") -> 7 | S34: =COUNTIFS(OFÍCIOS!$E:$E,$O34,OFÍCIOS!$G:$G,"PENDENCIA") -> 5 | T34: =COUNTIFS(OFÍCIOS!$E:$E,$O34,OFÍCIOS!$G:$G,"") -> 2 | U34: =SUM(Q34:T34) -> 91
A35: ADRIANA DA SILVA SANTOS | B35: 40902634844 | C35: GUILHERME DE OLIVEIRA SOUZA | D35: 23795007895 | E35: 117 | F35: 43117 | G35: APROVADO | H35: 43151 | L35: 118-18 | O35: 485 | P35: =COUNTIF(OFÍCIOS!E:E,O35) -> 23 | Q35: =COUNTIFS(OFÍCIOS!$E:$E,$O35,OFÍCIOS!$G:$G,"APROVADO") -> 0 | R35: =COUNTIFS(OFÍCIOS!$E:$E,$O35,OFÍCIOS!$G:$G,"REPROVADO") -> 3 | S35: =COUNTIFS(OFÍCIOS!$E:$E,$O35,OFÍCIOS!$G:$G,"PENDENCIA") -> 0 | T35: =COUNTIFS(OFÍCIOS!$E:$E,$O35,OFÍCIOS!$G:$G,"") -> 20 | U35: =SUM(Q35:T35) -> 23
A36: ADRIANA DE SA ROCHA | B36: 39615629898 | C36: MARCELO FERNANDES LIMA | D36: 43328275894 | E36: 423 | F36: 43182 | G36: APROVADO | O36: 85 | P36: =COUNTIF(OFÍCIOS!E:E,O36) -> 93 | Q36: =COUNTIFS(OFÍCIOS!$E:$E,$O36,OFÍCIOS!$G:$G,"APROVADO") -> 86 | R36: =COUNTIFS(OFÍCIOS!$E:$E,$O36,OFÍCIOS!$G:$G,"REPROVADO") -> 4 | S36: =COUNTIFS(OFÍCIOS!$E:$E,$O36,OFÍCIOS!$G:$G,"PENDENCIA") -> 3 | T36: =COUNTIFS(OFÍCIOS!$E:$E,$O36,OFÍCIOS!$G:$G,"") -> 0 | U36: =SUM(Q36:T36) -> 93
A37: ADRIANA DOS SANTOS | P37: =COUNTIF(OFÍCIOS!E:E,O37) -> 0 | Q37: =COUNTIFS(OFÍCIOS!$E:$E,$O37,OFÍCIOS!$G:$G,"APROVADO") -> 0 | R37: =COUNTIFS(OFÍCIOS!$E:$E,$O37,OFÍCIOS!$G:$G,"REPROVADO") -> 0 | S37: =COUNTIFS(OFÍCIOS!$E:$E,$O37,OFÍCIOS!$G:$G,"PENDENCIA") -> 0 | T37: =COUNTIFS(OFÍCIOS!$E:$E,$O37,OFÍCIOS!$G:$G,"") -> 0 | U37: =SUM(Q37:T37) -> 0
A38: ADRIANA FERREIRA DA SILVA | C38: LOURIVAL CANDIDO SILVA | P38: =COUNTIF(OFÍCIOS!E:E,O38) -> 0 | Q38: =COUNTIFS(OFÍCIOS!$E:$E,$O38,OFÍCIOS!$G:$G,"APROVADO") -> 0 | R38: =COUNTIFS(OFÍCIOS!$E:$E,$O38,OFÍCIOS!$G:$G,"REPROVADO") -> 0 | S38: =COUNTIFS(OFÍCIOS!$E:$E,$O38,OFÍCIOS!$G:$G,"PENDENCIA") -> 0 | T38: =COUNTIFS(OFÍCIOS!$E:$E,$O38,OFÍCIOS!$G:$G,"") -> 0 | U38: =SUM(Q38:T38) -> 0
A39: ADRIANA HELENA DE MORAIS | B39: 14268808809 | E39: 262 | F39: 43160 | G39: APROVADO | H39: 43164 | L39: 255 | P39: =COUNTIF(OFÍCIOS!E:E,O39) -> 0 | Q39: =COUNTIFS(OFÍCIOS!$E:$E,$O39,OFÍCIOS!$G:$G,"APROVADO") -> 0 | R39: =COUNTIFS(OFÍCIOS!$E:$E,$O39,OFÍCIOS!$G:$G,"REPROVADO") -> 0 | S39: =COUNTIFS(OFÍCIOS!$E:$E,$O39,OFÍCIOS!$G:$G,"PENDENCIA") -> 0 | T39: =COUNTIFS(OFÍCIOS!$E:$E,$O39,OFÍCIOS!$G:$G,"") -> 0 | U39: =SUM(Q39:T39) -> 0
A40: ADRIANA JESUS DA CUNHA | B40: 29628693867 | E40: 292 | F40: 43168 | G40: APROVADO | H40: 43182 | L40: 318 | P40: =COUNTIF(OFÍCIOS!E:E,O40) -> 0 | Q40: =COUNTIFS(OFÍCIOS!$E:$E,$O40,OFÍCIOS!$G:$G,"APROVADO") -> 0 | R40: =COUNTIFS(OFÍCIOS!$E:$E,$O40,OFÍCIOS!$G:$G,"REPROVADO") -> 0 | S40: =COUNTIFS(OFÍCIOS!$E:$E,$O40,OFÍCIOS!$G:$G,"PENDENCIA") -> 0 | T40: =COUNTIFS(OFÍCIOS!$E:$E,$O40,OFÍCIOS!$G:$G,"") -> 0 | U40: =SUM(Q40:T40) -> 0
A41: ADRIANA LINO PEIXOTO | B41: 35762862844 | E41: 1106 | F41: 42965 | G41: APROVADO | H41: 42978 | P41: =COUNTIF(OFÍCIOS!E:E,O41) -> 0 | Q41: =COUNTIFS(OFÍCIOS!$E:$E,$O41,OFÍCIOS!$G:$G,"APROVADO") -> 0 | R41: =COUNTIFS(OFÍCIOS!$E:$E,$O41,OFÍCIOS!$G:$G,"REPROVADO") -> 0 | S41: =COUNTIFS(OFÍCIOS!$E:$E,$O41,OFÍCIOS!$G:$G,"PENDENCIA") -> 0 | T41: =COUNTIFS(OFÍCIOS!$E:$E,$O41,OFÍCIOS!$G:$G,"") -> 0 | U41: =SUM(Q41:T41) -> 0
A42: ADRIANA MARIA ALVES XAVIER (ALTERACAO DE NOME ADRIANA MARIA ALVES DOS SANTOS) | B42: 10201704412 | C42: CLAUDIO XAVIER SANTANA | D42: 33674895811 | E42: 262 | F42: 43160 | G42: APROVADO | H42: 43164 | L42: 255 | O42: TOTAIS | P42: =SUM(P3:P36) -> 1922 | Q42: =SUM(Q3:Q36) -> 1514 | R42: =SUM(R3:R36) -> 83 | S42: =SUM(S3:S36) -> 36 | T42: =SUM(T3:T36) -> 289 | U42: =SUM(U3:U36) -> 1922
A43: ADRIANA MEDEIROS DE OLIVEIRA SANTOS | B43: 35271487873 | C43: CLEITON SOUSA SANTOS | D43: 557351502 | E43: 1128 | F43: 42972 | G43: APROVADO | H43: 42979
A44: ADRIANA PEREIRA DE JESUS | B44: 22360217801 | E44: 1128 | F44: 42972 | G44: APROVADO | H44: 42979
A45: ADRIANA PINHEIRO MOREIRA | B45: 36930783862 | E45: 443 | F45: 43188 | H45: 43192
A46: ADRIANA PONCIANO DA SILVA | B46: 36647299866 | E46: 292 | F46: 43168 | G46: APROVADO | H46: 43182 | L46: 318
A47: ADRIANA PORTE | B47: 31801479895 | C47: ISAQUE PINTO DA SILVA | D47: 23103908873
A48: ADRIANA ROBERTA SILVA ANDRADE | B48: 28638653824 | C48: JOSE ROMILDO SILVA ANDRADE | D48: 50160249520
A49: ADRIANA ROQUE DOS SANTOS | B49: 17766101807 | C49: MARCOS ELIAS DOS SANTOS | D49: 31993041842 | E49: 1824 | F49: 43091 | G49: APROVADO | H49: 43097 | L49: 1828
A50: ADRIANA SABINO NOGUEIRA | B50: 17902799840 | C50: JOYCE CRISTINA NOGUEIRA DO CARMO | D50: 44230035896
A51: ADRIANA SANTANA SANTOS | B51: 49122403892 | C51: ETVALDO BERTO DA SILVA | D51: 1478139560 | E51: 608 | F51: 43012 | G51: APROVADO | H51: 43024 | O51: OFÍCIO DE REANÁLISE 019/18 - 05/06/18
A52: ADRIANA SANTOS RIBEIRO | B52: 37534302854 | C52: EDLANDIO BISPO SILVA | D52: 1689246502
A53: ADRIANA SEVERINO SANTANA | B53: 14699996841 | C53: FERNANDO FERREIRA SILVA | D53: 15089706883 | E53: 1128 | F53: 42972 | G53: APROVADO | H53: 42979
A54: ADRIANA TENORIO DA SILVA | B54: 47077408809
A55: ADRIANE MOREIRA DOS SANTOS | B55: 40396239838 | C55: JEFERSON DA SILVA DE JESUS | D55: 39420747883 | E55: 262 | F55: 43160 | G55: APROVADO | H55: 43164 | L55: 255
A56: ADRIANO ALVES BARBOSA | B56: 41333062877 | E56: 292 | F56: 43168 | G56: APROVADO | H56: 43182 | L56: 318
A57: ADRIANO HENRIQUE DA COSTA | B57: 38781151802
A58: ADRIANO PEREIRA DOS SANTOS
A59: ADRIELLE DOS PASSOS DE SOUZA | B59: 2428277219 | C59: DIVANILDO SOUZA DOS PASSOS | D59: 909805229 | E59: 810 | F59: 42915 | G59: APROVADO | H59: 42921 | L59: 568-17
A60: AGDA APARECIDA PEREIRA | B60: 16417464830
A61: AGNALDO ALTMANN | B61: 7104481800 | E61: 262 | F61: 43160 | G61: APROVADO | H61: 43164 | L61: 255
A62: AGNALDO LOPES GONCALVES FILHO | B62: 25023266800
A63: AGOSTINHO FERNANDES SILVA | B63: 3722493889 | C63: FRANCISCA GOMES DE OLIVEIRA | D63: 32416642871
A64: AIDEE MARIA DOS SANTOS | B64: 14519340845 | C64: SIORLANDIO DOS SANTOS FALCAO | D64: 88489795568 | E64: 262 | F64: 43160 | H64: 43164 | L64: 255
A65: AILTON WILLIAN MELLO | B65: 19266484806
A66: ALADIM PINHEIRO DOS SANTOS | B66: 15322188851
A67: ALAILTON COSTA DE SOUZA | B67: 36392955879 | C67: AMANDA CRISTINA SILVEIRA DA SILVA | D67: 5242864346 | E67: 117 | F67: 43117 | G67: APROVADO | H67: 43151 | L67: 118-18
A68: ALAN DE JESUS PASSOS | B68: 41482647800 | E68: 1262 | F68: 42997 | G68: APROVADO | H68: 43000
A69: ALBERT PEREIRA DOS SANTOS | B69: 47629183852
A70: ALBERTINA CANDIDO RIBEIRO GOMES | B70: 9882942490 | C70: DENIS JOSE GOMES | D70: 9704111460
A71: ALBERTINA PEREIRA COSTA | B71: 14777572870 | C71: EDIVALDO ALVES DE SOUZA | D71: 12874739898 | E71: 1824 | F71: 43091 | G71: APROVADO | H71: 43097 | L71: 1828
A72: ALCIDINEY DA SILVA | B72: 31996709895
A73: ALCILENE GUEDES DA SILVA | B73: 26824046850 | E73: 1824 | F73: 43091 | G73: APROVADO | H73: 43097 | L73: 1828
A74: ALCIONE BARBOSA DE SOUSA | B74: 3523524342 | E74: 85 | F74: 43109 | G74: APROVADO | H74: 43151
A75: ALDA DE JESUS GONCALVES | B75: 26940268855 | C75: JUCELINO ALVES DE LIMA
A76: ALDA MARIA DE JESUS | B76: 24828498885 | E76: 1489 | F76: 43038 | G76: APROVADO | L76: 1647-17
A77: ALDA REJANE SANTOS | B77: 11482307855 | E77: 85 | F77: 43109 | G77: APROVADO | H77: 43151
A78: ALDERLANDIA DE OLIVEIRA MONTEIRO | B78: 42352732808 | C78: JOSE SOARES DA SILVA | D78: 281893373 | E78: 1214 | F78: 42989 | G78: APROVADO | H78: 43000
A79: ALESILVIA RAIMUNDO DA SILVA NEVES | B79: 13480043801 | C79: CLAUDIO RIBEIRO NEVES | D79: 67141536604
A80: ALESSANDRA APARECIDA DE JESUS | B80: 31874522804 | E80: 292 | F80: 43168 | G80: APROVADO | H80: 43182 | L80: 318
A81: ALESSANDRA CABRAL DA SILVA | B81: 28889575824 | E81: 1241 | F81: 42992 | G81: APROVADO | H81: 42998
A82: ALESSANDRA JUVINA DA SILVA | B82: 21734589817 | E82: 229 | F82: 43151 | G82: APROVADO | L82: 232
A83: ALESSANDRA LIMA DA SILVA
A84: ALESSANDRA LUNA DA SILVA | B84: 18475875858
A85: ALESSANDRA MARQUES DOS SANTOS | B85: 40443882886 | E85: 509 | F85: 43203 | H85: 43213
A86: ALESSANDRA MARTINS DA SILVA | B86: 43053250802 | C86: IUDARLAN MARTINS DA SILVA | D86: 35893147880 | E86: 1128 | F86: 42972 | G86: APROVADO
A87: ALESSANDRA MILAGRES PIROTTI | B87: 28255807837 | E87: 292 | F87: 43168 | G87: APROVADO | L87: 318
A88: ALESSANDRA MONTEIRO DA SILVA | B88: 33617584837 | C88: ASTROGILDO APARECIDO CURY DE ARAUJO | D88: 26520094862 | E88: 608 | F88: 43012 | G88: APROVADO
A89: ALESSANDRA QUARESMA DA SILVA | B89: 38168161858 | C89: WALLACE DIEGO HENRIQUE BISPO | D89: 24059422835
A90: ALESSANDRO ARAUJO DA SILVA COSTA | B90: 38728353862 | C90: LIZIANE ROCHA DA SILVA COSTA | D90: 37650358828 | E90: 1417 | F90: 43017 | G90: APROVADO | L90: 1017-17
A91: ALEX DE JESUS PEREIRA | B91: 29479419858 | C91: JOILMA DE JESUS FERREIRA | D91: 71909656534
A92: ALEX JOSE CATARINO ASSUNCAO | B92: 37634689866 | E92: 443 | F92: 43188
A93: ALEXANDRA APARECIDA DA SILVA BARBOZA | B93: 22656606802 | E93: 1555 | F93: 43049 | G93: APROVADO
A94: ALEXANDRA SANTOS DE PAULA | B94: 4248144638 | E94: 229 | F94: 43151 | G94: APROVADO | L94: 232
A95: ALEXANDRE OLIVEIRA SILVA | B95: 29998933889
A96: ALEXANDRE SATELES DOS SANTOS | B96: 2963904533 | E96: 1489 | F96: 43038 | G96: APROVADO | L96: 1647-17
A97: ALEXANDRE VALENTIN DE SOUZA | B97: 23256005802 | E97: 1350 | F97: 43006 | G97: APROVADO
A98: ALEXSANDRA BORGES GONCALVES | B98: 3317260505 | C98: GILDECI FERREIRA CORDEIRO | D98: 92396607634
A99: ALEXSANDRA FRANCA DA SILVA | B99: 36234875890 | E99: 1128 | F99: 42972 | G99: APROVADO
A100: ALEXSANDRA MARIA DA SILVA | B100: 1243618469 | E100: 262 | F100: 43160 | G100: APROVADO | H100: 43164 | L100: 255
...

Sheet HABITA
O3: ÁREA | P3: PROPRIETÁRIO | Q3: CPF | R3: No PROCESSO SEI (INDENIZAÇÃO)
O4: PARAISÓPOLIS/ANTONICO | P4: MELISSA SANTOS CORREIA | Q4: 550.872.238.69 | R4: 6014.2025/0001188-7
O5: PARAISÓPOLIS/ANTONICO | P5: JOENILSON PEREIRA ALMEIDA | Q5: 126.356.098-96 | R5: 6014.2025/0002857-7
O6: PARAISÓPOLIS/ANTONICO | P6: JOSÉ BARRA NOVA DE MELO | Q6: 001.075.828-30 | R6: 6014.2026/0000335-5
O7: PARAISÓPOLIS/ANTONICO | P7: DAVI SANTOS ROSA | Q7: 214.736.748-67 | R7: 6014.2025/0007670-9
O8: PARAISÓPOLIS/ANTONICO | P8: JOÃO VICTOR BENTO DANTAS | Q8: 327.855.018-88 | R8: 6014.2025/0006531-6
O9: PARAISÓPOLIS/ANTONICO | P9: MARTA DOS SANTOS DANTAS | Q9: 351.979.678-38 | R9: 6014.2026/0000105-0
O10: PARAISÓPOLIS/ANTONICO | P10: VITOR DOS SANTOS DANTAS | Q10: 279.159.748-40 | R10: 6014.2025/0008502-3
O11: PARAISÓPOLIS/ANTONICO | P11: CONCEIÇÃO SANTOS PEREIRA | Q11: 356.755.828-51 | R11: 6014.2026/0000095-0
O12: PARAISÓPOLIS/ANTONICO | P12: WELLINGTON CAMPOS MACIEL | Q12: 386.292.458-08 | R12: 6014.2026/0000912-4
O13: PARAISÓPOLIS/ANTONICO | P13: MARIA DALVA DE SOUZA SOBRINHO DA SILVA | Q13: 387.226.198-36 | R13: 6014.2026/0000094-1
O14: PARAISÓPOLIS/ANTONICO | P14: EDJANE MARIA DA SILVA | Q14: 063.210.314-02 | R14: 6014.2026/0000264-2
... O20: PARAISÓPOLIS/ANTONICO | P20: MARIA CLAUDI DE ANDRADE | Q20: 579.912.355-72 | R20: 6014.2026/0000898-5
O38: PARAISÓPOLIS/ANTONICO
