Workbook
Name Adequacao_Imovel: 'Listas (não utilizar)'!$G$2:$G$7
Name ADEQUAR: 'Listas (não utilizar)'!$G$2:$G$7
Name Apartamento: 'Listas (não utilizar)'!$D$2:$D$21
Name APROVCEF: #REF!
Name Área: 'Listas (não utilizar)'!$A$2:$A$28
Name AREAS: #REF!
Name AVILDATA: #REF!
Name AVILDATA1: #REF!
Name BARCDATA: #REF!
Name BILBDATA: #REF!
Name Bloco: 'Listas (não utilizar)'!$C$2:$C$16
Name CEF: #REF!
Name CEUTDATA: #REF!
Name Condomínio: 'Listas (não utilizar)'!$B$2:$B$15
Name INDDEMAND: #REF!
Name INDEMAND: #REF!
Name it: #REF!
Name Pendência: 'Listas (não utilizar)'!$I$2:$I$7
Name PLANCCO: #REF!
Name Renúncia: 'Listas (não utilizar)'!$H$2:$H$6
Name RetornoSMADS: '[1]Listas (não utilizar)'!$E$2:$E$3
Name selogo: #REF!
Name selomv: #REF!
Name selos_go: #REF!
Name selosgo: #REF!
Name selosgo1: #REF!
Name SITAH_CAIXA: 'Listas (não utilizar)'!$E$2:$E$9
Name StatusCAIXA: 'Listas (não utilizar)'!$F$2:$F$5
Name TEPROC: #REF!
Name TEPROC1: #REF!

Sheet PRIORIDADES
C3: 2 | D3: PRIORITÁRIO | G3: OCUPADO | H3: RESIDENCIAL | I3: PROPRIETÁRIO NÃO RESIDENTE | M3: CADASTRADO | N3: INDENIZAÇÃO | P3: SIM | R3: SIM | X3: SAQUE PENDENTE | AE3: PROPRIETÁRIO NÃO RESIDENTE | AF3: CADASTRADO | AI3: SIM | AJ3: SIM | AM3: COMPLETA | AN3: SEM PENDÊNCIAS
C4: 4 | G4: VAZIO | H4: COMERCIAL | I4: PROPRIETÁRIO RESIDENTE | M4: NÃO CADASTRADO | N4: AUXÍLIO ALUGUEL UH | P4: NÃO | R4: NÃO | AE4: PROPRIETÁRIO RESIDENTE | AF4: NÃO CADASTRADO | AI4: NÃO | AJ4: NÃO | AM4: PENDENTE | AN4: FALTA TERMO
G5: OCUPADO/RISCO | H5: MISTO | I5: INQULINO | N5: RECUSA AUXÍLIO ALUGUEL UH | AI5: UH | AJ5: N/A | AN5: FALTA DOCS
G6: CONSTRUÇÃO | N6: NÃO TEM DIREITO ATENDIMENTO | AI6: ESTUDO DE CASO | AJ6: PENDENTE | AN6: FALTA TERMO E DOCS
G7: DEMOLIDO
G8: DESCARACTERIZADO
G9: DESABADO
AP10: AGUARDANDO
A12: INFORMAÇÕES INICIAIS | P12: INFORMAÇÕES AUXÍLIO ALUGUEL | AB12: INFORMAÇÕES INDENIZAÇÃO | BB12: PROCESSO ATENDIMENTO HABITACIONAL
A13: ORDEM | B13: ÁREA | C13: FASE | D13: TRECHO | E13: PRIORIDADE | F13: SELO | G13: SITUAÇÃO INICIAL IMÓVEL | H13: USO IMÓVEL | I13: SITUAÇÃO DO RESIDENTE | J13: TITULAR | K13: RG | L13: CPF | M13: CADASTRO HABITA SAMPA | N13: OPÇÃO DE ATENDIMENTO HABITACIONAL | O13: ENVIO DADOS | P13: SOLICITAÇÃO AUXÍLIO ALUGUEL ÁREA | Q13: No PROCESSO SEI (AUXÍLIO ALUGUEL) | R13: ANÁLISE DTS CADASTRO + CHECAGEM DUPLO | S13: INSTRUÇÃO PROCESSO SEI DTS | T13: ANÁLISE CTS ASSINATURA GABINETE | U13: DATA PUBLICAÇÃO DIÁRIO OFICIAL | V13: CONFECÇÃO TERMO | W13: ENVIO TERMO CARTÃO | X13: PREVISÃO PAGAMENTO | Y13: DATA SAQUE | Z13: DATA MUDANÇA | AA13: OBSERVAÇÕES AA | AB13: PROPRIETÁRIO | AC13: RG | AD13: CPF | AE13: SITUAÇÃO DO PROPRIETÁRIO | AF13: CADASTRO HABITASAMPA | AG13: VALOR AVALIAÇÃO | AH13: VALOR INDENIZAÇÃO | AI13: ACEITA VALOR INDENIZAÇÃO | AJ13: Nº SEI LAUDOS AVALIAÇÃO | AK13: Nº DOCUMENTO LAUDO | AL13: TERMO INDENIZAÇÃO | AM13: DOSSIÊ | AN13: PENDÊNCIA | AO13: OBSERVAÇÕES INDENIZAÇÃO | AP13: No PROCESSO SEI (INDENIZAÇÃO) | AQ13: INSTRUÇÃO PROCESSO SEI DTS | AR13: ASSINATURA DIRETOR DTS | AS13: ELABORAÇÃO DESPACHO CTS | AT13: ASSINATURA DESPACHO GABINETE | AU13: PUBLICAÇÃO DIÁRIO OFICIAL | AV13: ENCAMINHAMENTO DAF/DIF CTS | AW13: LIBERAÇÃO PAGAMENTO DAF/DIF | AX13: PREVISÃO PAGAMENTO | AY13: DATA PAGAMENTO | AZ13: DATA ENTREGA IMÓVEL | BA13: SITUAÇÃO ATUAL IMÓVEL | BB13: STATUS | BC13: DIAS TOTAIS | BD13: OPÇÃO ATENDIMENTO | BE13: NECESSITA BLOQUEIO AA | BF13: SOLICITAÇÃO BLOQUEIO AA DTS | BG13: SOLICITAÇÃO BLOQUEIO AA | BH13: DATA BLOQUEIO AA | BI13: DESPACHO EXCLUSÃO GABINETE | BJ13: ASSINATURA DESPACHO GABINETE | BK13: PUBLICAÇÃO DOC | BL13: ENCAMINHAMENTO SOLICITAÇÃO EXCLUSÃO DEPLAN | BM13: ENCERRAMENTO PROCESSO DTS
A14: 1 | B14: VIOLÃO III | C14: 1 | D14: -- | E14: -- | F14: 0010001A | G14: VAZIO | H14: MORADIA | J14: LEONARDO VINICIUS DE MELO | N14: INDENIZAÇÃO | AB14: MARIA EDCLÉCIA GOMES BEZERRA | AC14: 410.204.418-36 | AD14: 49.349.859-X | AE14: PROPRIETARIO RESIDENTE | AJ14: 6014.2025/0006976-1 | BC14: =IF(AY14-KD14=0,"",AY14-O14) | BD14: =IF(AND(AI14<>"SIM",AI14="UH"),"AA","INDENIZAÇÃO") -> INDENIZAÇÃO | BE14: =IF(AND(AY14<>"AGUARDANDO",AY14<>"",N14="AUXÍLIO ALUGUEL ATÉ INDENIZAÇÃO"),"SIM","NÃO") -> NÃO
A15: 2 | B15: VIOLÃO III | C15: 1 | D15: -- | E15: -- | F15: 0010002A | G15: OCUPADO | H15: MORADIA | I15: PROPRIETARIO RESIDENTE | J15: EDNELSON LIMA SANTOS | K15: 23.995.115-3 | L15: 182.415.438-08 | M15: CONCLUIDO | N15: AUXÍLIO ALUGUEL | O15: 45987 | P15: Finalizada | Q15: 6014.2025/0007038-7 | R15: Finalizado | S15: Finalizado | AB15: JOSÉ ERALDO BEZERRA | AC15: 677.779.964/87 | AD15: 37.579.271-5 | AE15: PROPRIETARIO RESIDENTE | BC15: =IF(AY15-KD15=0,"",AY15-O15) | BD15: =IF(AND(AI15<>"SIM",AI15="UH"),"AA","INDENIZAÇÃO") -> INDENIZAÇÃO | BE15: =IF(AND(AY15<>"AGUARDANDO",AY15<>"",N15="AUXÍLIO ALUGUEL ATÉ INDENIZAÇÃO"),"SIM","NÃO") -> NÃO
A16: 3 | B16: VIOLÃO III | C16: 1 | D16: -- | E16: -- | F16: 0010003A | G16: OCUPADO | H16: RESIDENCIAL | I16: PROPRIETARIO RESIDENTE | J16: JANETE DAMASCENA BORGES | K16: 56.993.863-2 | L16: 112360.248.42 | M16: CONCLUIDO | N16: AUXÍLIO ALUGUEL | O16: 45960 | P16: Finalizada | Q16: 6014.2025/0007038-7 | R16: Finalizado | S16: Finalizado | T16: Finalizado | U16: 45968 | V16: Finalizado | W16: 45980 | X16: 45993 | Y16: Aguardando | Z16: Aguardando | AB16: LUCICLEIDE DA SILVA | AC16: 293.033.358-80 | AD16: 36.359.677-X | AE16: PROPRIETARIO NÃO RESIDENTE | BC16: =IF(AY16-KD16=0,"",AY16-O16) | BD16: =IF(AND(AI16<>"SIM",AI16="UH"),"AA","INDENIZAÇÃO") -> INDENIZAÇÃO | BE16: =IF(AND(AY16<>"AGUARDANDO",AY16<>"",N16="AUXÍLIO ALUGUEL ATÉ INDENIZAÇÃO"),"SIM","NÃO") -> NÃO
A17: 4 | B17: VIOLÃO III | C17: 1 | D17: -- | E17: -- | F17: 0010004A | G17: OCUPADO | H17: COMÉRCIO | I17: PROPRIETARIO RESIDENTE | J17: ADRIANA CONCEIÇÃO DOS SANTOS | K17: 34.460.051-8 | L17: 339.934.348-54 | M17: CONCLUIDO | N17: INDENIZAÇÃO | O17: 45999 | P17: N/A | Q17: N/A | R17: N/A | S17: N/A | T17: N/A | U17: N/A | V17: N/A | W17: N/A | X17: N/A | Y17: N/A | Z17: N/A | AB17: ADRIANA CONCEIÇÃO DOS SANTOS | AC17: 34.460.051-8 | AD17: 339.934.348-54 | AE17: PROPRIETARIO RESIDENTE | AF17: CONCLUIDO | AG17: 17740.68 | AH17: 47740.68 | AI17: SIM | AJ17: 6014.2025/0006976-1 | AK17: 146475359 | AL17: FINALIZADO | AM17: FINALIZADO | AN17: SEM PENDÊNCIA | AP17: 6014.2025/0008113-3 | AQ17: FINALIZADO | AR17: FINALIZADO | AS17: FINALIZADO | AT17: FINALIZADO | AU17: 46013 | AV17: FINALIZADO | AW17: FINALIZADO | AX17: 46017 | AY17: 46017 | AZ17: AGUARDANDO | BA17: LIBERADO DEMOLIÇÃO | BB17: FINALIZADO | BC17: =IF(AY17-KD17=0,"",AY17-O17) -> 18 | BD17: =IF(AND(AI17<>"SIM",AI17="UH"),"AA","INDENIZAÇÃO") -> INDENIZAÇÃO | BE17: =IF(AND(AY17<>"AGUARDANDO",AY17<>"",N17="AUXÍLIO ALUGUEL ATÉ INDENIZAÇÃO"),"SIM","NÃO") -> NÃO | BF17: N/A | BG17: N/A | BH17: N/A | BI17: AGUARDANDO ELABORAÇÃO
A18: 5 | B18: VIOLÃO III | C18: 1 | D18: -- | E18: -- | F18: 0010005A | G18: OCUPADO | H18: RESIDENCIAL | I18: PROPRIETARIO RESIDENTE | J18: MARIANE MEDEIROS DE SÁ | K18: 47.489.953-6 | L18: 393.131.548-70 | M18: CONCLUIDO | N18: AUXÍLIO ALUGUEL | O18: 45960 | P18: Finalizada | Q18: 6014.2025/0007038-7 | R18: Finalizado | S18: Finalizado | T18: Finalizado | U18: 45968 | V18: Finalizado | W18: 45980 | X18: 45993 | Y18: Aguardando | Z18: Aguardando | AB18: EDENILDES MARIA NEVES CABRAL | AC18: 315.664.805-15 | AD18: 53.084.721-8 | AE18: PROPRIETARIO RESIDENTE | BC18: =IF(AY18-KD18=0,"",AY18-O18) | BD18: =IF(AND(AI18<>"SIM",AI18="UH"),"AA","INDENIZAÇÃO") -> INDENIZAÇÃO | BE18: =IF(AND(AY18<>"AGUARDANDO",AY18<>"",N18="AUXÍLIO ALUGUEL ATÉ INDENIZAÇÃO"),"SIM","NÃO") -> NÃO
A19: 6 | B19: VIOLÃO III | C19: 1 | D19: -- | E19: -- | F19: 0010008A | G19: OCUPADO | H19: COMÉRCIO | I19: PROPRIETARIO RESIDENTE | J19: EDUARDO HENRIQUE MARTINS LEITE | K19: 38.968.231-17 | L19: 532.052.748-90 | M19: CONCLUIDO | N19: INDENIZAÇÃO | O19: 45999 | P19: N/A | Q19: N/A | R19: N/A | S19: N/A | T19: N/A | U19: N/A | V19: N/A | W19: N/A | X19: N/A | Y19: N/A | Z19: N/A | AB19: EDUARDO HENRIQUE MARTINS LEITE | AC19: 38.968.231-17 | AD19: 532.052.748-90 | AE19: PROPRIETARIO RESIDENTE | AF19: CONCLUIDO | AG19: 25598.29 | AH19: 55598.29 | AI19: SIM | AJ19: 6014.2025/0006976-1 | AK19: 146468980 | AL19: FINALIZADO | AM19: FINALIZADO | AN19: SEM PENDÊNCIA | AO19: Comprovante de residência apresentado não está listado, dentre os que são aceitos, na instrução normativa - sehab nº 5 de 08 de Agosto de 2022. | AP19: 6014.2025/0008119-2 | AQ19: FINALIZADO | AR19: FINALIZADO | AS19: FINALIZADO | AT19: FINALIZADO | AU19: 46105 | AV19: FINALIZADO | AW19: FINALIZADO | AX19: 46119 | AY19: 46119 | AZ19: AGUARDANDO | BA19: LIBERADO DEMOLIÇÃO | BB19: FINALIZADO | BC19: =IF(AY19-KD19=0,"",AY19-O19) -> 120 | BD19: =IF(AND(AI19<>"SIM",AI19="UH"),"AA","INDENIZAÇÃO") -> INDENIZAÇÃO | BE19: =IF(AND(AY19<>"AGUARDANDO",AY19<>"",N19="AUXÍLIO ALUGUEL ATÉ INDENIZAÇÃO"),"SIM","NÃO") -> NÃO | BF19: N/A | BG19: N/A | BH19: N/A | BI19: AGUARDANDO ELABORAÇÃO
A20: 7 | B20: VIOLÃO III | C20: 1 | D20: -- | E20: -- | F20: 0010007A | G20: OCUPADO | H20: RESIDENCIAL | I20: INQUILINO | J20: RAQUEL SOARES DE OLIVEIRA | K20: - | L20: 348.492.908-17 | M20: CONCLUIDO | N20: AUXÍLIO ALUGUEL | O20: 46160 | P20: Finalizada | Q20: 6014.2025/0007038-7 | R20: Finalizado | S20: Finalizado | T20: Finalizado | U20: 45968 | V20: Finalizado | W20: 45980 | X20: 45993 | Y20: Aguardando | Z20: Aguardando | AB20: ROBERT DA SILVA BAPTISTA | AD20: 243.160.878-60 | AE20: PROPRIETARIO NÃO RESIDENTE | AF20: CONCLUIDO | AG20: 21635.93 | AH20: 21635.93 | AI20: SIM | AJ20: 6014.2025/0006976-1 | AK20: 151421068 | AL20: FINALIZADO | AM20: FINALIZADO | AN20: SEM PENDÊNCIA | AO20: AGUARDANDO CORREÇÃO- SITUAÇÃO DO PROPRIETÁRIO DIVERGENTE NA PLANILHA | AP20: 6014.2026/0003615-6 | AQ20: FINALIZADO | AR20: FINALIZADO | AS20: FINALIZADO | AT20: FINALIZADO | AU20: 46255 | AV20: FINALIZADO | AW20: FINALIZADO | AX20: 46260 | AY20: 46260 | AZ20: AGUARDANDO | BA20: LIBERADO DEMOLIÇÃO | BB20: FINALIZADO | BC20: =IF(AY20-KD20=0,"",AY20-O20) -> 100 | BD20: =IF(AND(AI20<>"SIM",AI20="UH"),"AA","INDENIZAÇÃO") -> INDENIZAÇÃO | BE20: =IF(AND(AY20<>"AGUARDANDO",AY20<>"",N20="AUXÍLIO ALUGUEL ATÉ INDENIZAÇÃO"),"SIM","NÃO") -> NÃO | BF20: N/A | BG20: N/A | BH20: N/A | BI20: AGUARDANDO ELABORAÇÃO
A21: 8 | B21: VIOLÃO III | C21: 1 | D21: -- | E21: -- | F21: 0010018A | G21: OCUPADO | H21: COMÉRCIO | I21: PROPRIETARIO RESIDENTE | J21: CAIO EDGAR SANTOS TOME | K21: 38.743.032-5 | L21: 564.859.818-10 | M21: CONCLUIDO | N21: INDENIZAÇÃO | O21: 45999 | P21: N/A | Q21: N/A | R21: N/A | S21: N/A | T21: N/A | U21: N/A | V21: N/A | W21: N/A | X21: N/A | Y21: N/A | Z21: N/A | AB21: CAIO EDGAR SANTOS TOME | AC21: 38.743.032-5 | AD21: 564.859.818-10 | AE21: PROPRIETARIO RESIDENTE | AF21: CONCLUIDO | AG21: 2414.67 | AH21: 32414.67 | AI21: SIM | AJ21: 6014.2025/0006976-1 | AK21: 146474567 | AL21: FINALIZADO | AM21: FINALIZADO | AN21: SEM PENDÊNCIA | AP21: 6014.2025/0008156-7 | AQ21: FINALIZADO | AR21: FINALIZADO | AS21: FINALIZADO | AT21: FINALIZADO | AU21: 46142 | AV21: FINALIZADO | AW21: FINALIZADO | AX21: 46153 | AY21: 46153 | AZ21: AGUARDANDO | BA21: LIBERADO DEMOLIÇÃO | BB21: FINALIZADO | BC21: =IF(AY21-KD21=0,"",AY21-O21) -> 154 | BD21: =IF(AND(AI21<>"SIM",AI21="UH"),"AA","INDENIZAÇÃO") -> INDENIZAÇÃO | BE21: =IF(AND(AY21<>"AGUARDANDO",AY21<>"",N21="AUXÍLIO ALUGUEL ATÉ INDENIZAÇÃO"),"SIM","NÃO") -> NÃO | BF21: N/A | BG21: N/A | BH21: N/A | BI21: AGUARDANDO ELABORAÇÃO
A22: 9 | B22: VIOLÃO III | C22: 1 | D22: -- | E22: -- | F22: 0010009A | G22: OCUPADO | H22: INSTITUCIONAL | I22: PROPRIETARIO RESIDENTE | J22: FLAVIA GIOVANNA DE LIMA SOUZA | K22: 39.120.433-6 | L22: 501.823.638-80 | M22: CONCLUIDO | N22: INDENIZAÇÃO | O22: 45999 | P22: N/A | Q22: N/A | R22: N/A | S22: N/A | T22: N/A | U22: N/A | V22: N/A | W22: N/A | X22: N/A | Y22: N/A | Z22: N/A | AB22: FLAVIA GIOVANNA DE LIMA SOUZA | AC22: 39.120.433-6 | AD22: 501.823.638-80 | AE22: PROPRIETARIO RESIDENTE | AF22: CONCLUIDO | AG22: 30181.61 | AH22: 60000 | AI22: SIM | AJ22: 6014.2025/0006976-1 | AK22: 146475434 | AL22: FINALIZADO | AM22: FINALIZADO | AN22: SEM PENDÊNCIA | AP22: 6014.2025/0008133-8 | AQ22: FINALIZADO | AR22: FINALIZADO | AS22: FINALIZADO | AT22: FINALIZADO | AU22: 46013 | AV22: FINALIZADO | AW22: FINALIZADO | AX22: 46017 | AY22: 46017 | AZ22: AGUARDANDO | BA22: LIBERADO DEMOLIÇÃO | BB22: FINALIZADO | BC22: =IF(AY22-KD22=0,"",AY22-O22) -> 18 | BD22: =IF(AND(AI22<>"SIM",AI22="UH"),"AA","INDENIZAÇÃO") -> INDENIZAÇÃO | BE22: =IF(AND(AY22<>"AGUARDANDO",AY22<>"",N22="AUXÍLIO ALUGUEL ATÉ INDENIZAÇÃO"),"SIM","NÃO") -> NÃO | BF22: N/A | BG22: N/A | BH22: N/A | BI22: AGUARDANDO ELABORAÇÃO
A23: 10 | B23: VIOLÃO III | C23: 1 | D23: -- | E23: -- | F23: 0010010A | G23: OCUPADO | H23: COMÉRCIO | I23: PROPRIETARIO RESIDENTE | J23: ELOI MUNICK DA SILVA SOUZA ABREU | K23: 44.474.099-5 | L23: 347.056.708-50 | M23: CONCLUIDO | N23: INDENIZAÇÃO | O23: 46079 | P23: N/A | Q23: N/A | R23: N/A | S23: N/A | T23: N/A | U23: N/A | V23: N/A | W23: N/A | X23: N/A | Y23: N/A | Z23: N/A | AB23: ELOI MUNICK DA SILVA SOUZA ABREU | AC23: 44.474.099-5 | AD23: 347.056.708-50 | AE23: PROPRIETARIO RESIDENTE | AF23: CONCLUIDO | AG23: 20915.33 | AH23: 50915.33 | AI23: SIM | AJ23: 6014.2025/0006976-1 | AK23: 147572559 | AL23: FINALIZADO | AM23: FINALIZADO | AN23: SEM PENDÊNCIA | AP23: 6014.2026/0001844-1 | AQ23: FINALIZADO | AR23: FINALIZADO | AS23: FINALIZADO | AT23: FINALIZADO | AU23: 46142 | AV23: FINALIZADO | AW23: FINALIZADO | AX23: 46153 | AY23: 46153 | AZ23: AGUARDANDO | BA23: LIBERADO DEMOLIÇÃO | BB23: FINALIZADO | BC23: =IF(AY23-KD23=0,"",AY23-O23) -> 74 | BD23: =IF(AND(AI23<>"SIM",AI23="UH"),"AA","INDENIZAÇÃO") -> INDENIZAÇÃO | BE23: =IF(AND(AY23<>"AGUARDANDO",AY23<>"",N23="AUXÍLIO ALUGUEL ATÉ INDENIZAÇÃO"),"SIM","NÃO") -> NÃO | BF23: N/A | BG23: N/A | BH23: N/A | BI23: AGUARDANDO ELABORAÇÃO
A24: 11 | B24: VIOLÃO III | C24: 1 | D24: -- | E24: -- | F24: 0010011A | G24: OCUPADO | H24: COMÉRCIO | I24: PROPRIETARIO RESIDENTE | J24: SILVANA APARECIDA BEZERRA TRINDADE | K24: 24.886.228-5 | L24: 264.526.768-81 | M24: CONCLUIDO | N24: INDENIZAÇÃO COMÉRCIO | O24: 45978 | P24: N/A | Q24: N/A | R24: N/A | S24: N/A | T24: N/A | U24: N/A | V24: N/A | W24: N/A | X24: N/A | Y24: N/A | Z24: N/A | AB24: SILVANA APARECIDA BEZERRA TRINDADE | AC24: 24.886.228-5 | AD24: 264.526.768-81 | AE24: PROPRIETARIO RESIDENTE | AF24: CONCLUIDO | AG24: 10084.18 | AH24: 40084.18 | AI24: SIM | AJ24: 6014.2025/0006976-1 | AK24: 145107701 | AL24: FINALIZADO | AM24: FINALIZADO | AN24: SEM PENDÊNCIA | AP24: 6014.2025/0007565-6 | AQ24: FINALIZADO | AR24: FINALIZADO | AS24: FINALIZADO | AT24: FINALIZADO | AU24: 46105 | AV24: FINALIZADO | AW24: FINALIZADO | AX24: 46119 | AY24: 46119 | AZ24: AGUARDANDO | BA24: LIBERADO DEMOLIÇÃO | BB24: FINALIZADO | BC24: =IF(AY24-KD24=0,"",AY24-O24) -> 141 | BD24: =IF(AND(AI24<>"SIM",AI24="UH"),"AA","INDENIZAÇÃO") -> INDENIZAÇÃO | BE24: =IF(AND(AY24<>"AGUARDANDO",AY24<>"",N24="AUXÍLIO ALUGUEL ATÉ INDENIZAÇÃO"),"SIM","NÃO") -> NÃO | BF24: N/A | BG24: N/A | BH24: N/A | BI24: AGUARDANDO ELABORAÇÃO
A25: 12 | B25: VIOLÃO III | C25: 1 | D25: -- | E25: -- | F25: 0010012A | G25: OCUPADO | H25: COMÉRCIO | I25: PROPRIETARIO RESIDENTE | J25: DIOGO PEDRO DA SILVA | K25: 42.913.718-7 | L25: 359.203.038-83 | M25: CONCLUIDO | N25: INDENIZAÇÃO | O25: 45999 | P25: N/A | Q25: N/A | R25: N/A | S25: N/A | T25: N/A | U25: N/A | V25: N/A | W25: N/A | X25: N/A | Y25: N/A | Z25: N/A | AB25: DIOGO PEDRO DA SILVA | AC25: 42.913.718-7 | AD25: 359.203.038-83 | AE25: PROPRIETARIO RESIDENTE | AF25: CONCLUIDO | AG25: 2395.12 | AH25: 32395.12 | AI25: SIM | AJ25: 6014.2025/0006976-1 | AK25: 146469069 | AL25: FINALIZADO | AM25: FINALIZADO | AN25: SEM PENDÊNCIA | AP25: 6014.2025/0008148-6 | AQ25: FINALIZADO | AR25: FINALIZADO | AS25: FINALIZADO | AT25: FINALIZADO | AU25: 46013 | AV25: FINALIZADO | AW25: FINALIZADO | AX25: 46017 | AY25: 46017 | AZ25: AGUARDANDO | BA25: LIBERADO DEMOLIÇÃO | BB25: FINALIZADO | BC25: =IF(AY25-KD25=0,"",AY25-O25) -> 18 | BD25: =IF(AND(AI25<>"SIM",AI25="UH"),"AA","INDENIZAÇÃO") -> INDENIZAÇÃO | BE25: =IF(AND(AY25<>"AGUARDANDO",AY25<>"",N25="AUXÍLIO ALUGUEL ATÉ INDENIZAÇÃO"),"SIM","NÃO") -> NÃO | BF25: N/A | BG25: N/A | BH25: N/A | BI25: AGUARDANDO ELABORAÇÃO
A26: 13 | B26: VIOLÃO III | C26: 1 | D26: -- | E26: -- | F26: 0010013A | G26: OCUPADO | H26: DOMITÓRIO | I26: PROPRIETARIO RESIDENTE | J26: MARCELE KATERINE ALVES | L26: 410.699.728-27 | AB26: ANA PAULA SANTANA SOUZA | AC26: 373.659.058/08 | AD26: 27.811.390-4 | AE26: PROPRIETARIO RESIDENTE | BC26: =IF(AY26-KD26=0,"",AY26-O26) | BD26: =IF(AND(AI26<>"SIM",AI26="UH"),"AA","INDENIZAÇÃO") -> INDENIZAÇÃO | BE26: =IF(AND(AY26<>"AGUARDANDO",AY26<>"",N26="AUXÍLIO ALUGUEL ATÉ INDENIZAÇÃO"),"SIM","NÃO") -> NÃO
A27: 14 | B27: VIOLÃO III | C27: 1 | D27: -- | E27: -- | F27: 0010014A | G27: OCUPADO | H27: MORADIA | I27: PROPRIETARIO RESIDENTE | J27: MARLON NASCIMENTO DA SILVA | K27: 38.851.169-2 | L27: 355.091.258-70 | N27: INDENIZAÇÃO | AB27: ALEXANDRO SANTANA SOUZA | AC27: 438.049.148-02 | AD27: 52.271.240-X | AE27: PROPRIETARIO RESIDENTE | AJ27: 6014.2025/0006976-1 | BC27: =IF(AY27-KD27=0,"",AY27-O27) | BD27: =IF(AND(AI27<>"SIM",AI27="UH"),"AA","INDENIZAÇÃO") -> INDENIZAÇÃO | BE27: =IF(AND(AY27<>"AGUARDANDO",AY27<>"",N27="AUXÍLIO ALUGUEL ATÉ INDENIZAÇÃO"),"SIM","NÃO") -> NÃO
A28: 15 | B28: VIOLÃO III | C28: 1 | D28: -- | E28: -- | F28: 0010016A | G28: OCUPADO | H28: COMÉRCIO | I28: PROPRIETARIO RESIDENTE | J28: DIEGO CAVALVANTE VIEIRA DE SÁ | K28: 39.119.926-2 | L28: 395.297.018-29 | M28: CONCLUIDO | N28: INDENIZAÇÃO COMÉRCIO | O28: 45978 | P28: N/A | Q28: N/A | R28: N/A | S28: N/A | T28: N/A | U28: N/A | V28: N/A | W28: N/A | X28: N/A | Y28: N/A | Z28: N/A | AB28: DIEGO CAVALVANTE VIEIRA DE SÁ | AC28: 39.119.926-2 | AD28: 395.297.018-29 | AE28: PROPRIETARIO RESIDENTE | AF28: CONCLUIDO | AG28: 14629.7 | AH28: 44629.7 | AI28: SIM | AJ28: 6014.2025/0006976-1 | AK28: 145107989 | AL28: FINALIZADO | AM28: FINALIZADO | AN28: SEM PENDÊNCIA | AP28: 6014.2025/0007536-2 | AQ28: FINALIZADO | AR28: FINALIZADO | AS28: FINALIZADO | AT28: FINALIZADO | AU28: 46017 | AV28: FINALIZADO | AW28: FINALIZADO | AX28: 46024 | AY28: 46024 | AZ28: AGUARDANDO | BA28: LIBERADO DEMOLIÇÃO | BB28: FINALIZADO | BC28: =IF(AY28-KD28=0,"",AY28-O28) -> 46 | BD28: =IF(AND(AI28<>"SIM",AI28="UH"),"AA","INDENIZAÇÃO") -> INDENIZAÇÃO | BE28: =IF(AND(AY28<>"AGUARDANDO",AY28<>"",N28="AUXÍLIO ALUGUEL ATÉ INDENIZAÇÃO"),"SIM","NÃO") -> NÃO | BF28: N/A | BG28: N/A | BH28: N/A | BI28: AGUARDANDO ELABORAÇÃO
A29: 16 | B29: VIOLÃO III | C29: 1 | D29: -- | E29: -- | F29: 0010017A | G29: VAZIO | H29: DEPÓSITO | J29: OSMARINO RIBEIRO DOS SANTOS | K29: 37.213.458-0-BA | L29: 345.334.785-49 | M29: CONCLUIDO | N29: INDENIZAÇÃO | AB29: JUSCINEIDE DE MACÊDO SANTANA | AC29: 022.989.403-36 | AD29: 50.915.027-5 | AE29: PROPRIETARIO RESIDENTE | AJ29: 6014.2025/0006976-1 | BC29: =IF(AY29-KD29=0,"",AY29-O29) | BD29: =IF(AND(AI29<>"SIM",AI29="UH"),"AA","INDENIZAÇÃO") -> INDENIZAÇÃO | BE29: =IF(AND(AY29<>"AGUARDANDO",AY29<>"",N29="AUXÍLIO ALUGUEL ATÉ INDENIZAÇÃO"),"SIM","NÃO") -> NÃO
A30: 17 | B30: VIOLÃO III | C30: 1 | D30: -- | E30: -- | F30: 0010006A | G30: OCUPADO | H30: COMÉRCIO | I30: PROPRIETARIO RESIDENTE | J30: MARIA DAYANA RODRIGUES LÔ | K30: 2009010275775-CE | L30: 603.861.133-94 | M30: CONCLUIDO | N30: INDENIZAÇÃO | O30: 46079 | P30: N/A | Q30: N/A | R30: N/A | S30: N/A | T30: N/A | U30: N/A | V30: N/A | W30: N/A | X30: N/A | Y30: N/A | Z30: N/A | AB30: MARIA DAYANA RODRIGUES LÔ | AC30: 2009010275775-CE | AD30: 603.861.133-94 | AE30: PROPRIETARIO RESIDENTE | AF30: CONCLUIDO | AG30: 25627.02 | AH30: 55627.02 | AI30: SIM | AJ30: 6014.2025/0006976-1 | AK30: 148882518 | AL30: FINALIZADO | AM30: FINALIZADO | AN30: SEM PENDÊNCIA | AP30: 6014.2026/0001839-5 | AQ30: FINALIZADO | AR30: FINALIZADO | AS30: FINALIZADO | AT30: FINALIZADO | AU30: 46142 | AV30: FINALIZADO | AW30: FINALIZADO | AX30: 46153 | AY30: 46153 | AZ30: AGUARDANDO | BA30: LIBERADO DEMOLIÇÃO | BB30: FINALIZADO | BC30: =IF(AY30-KD30=0,"",AY30-O30) -> 74 | BD30: =IF(AND(AI30<>"SIM",AI30="UH"),"AA","INDENIZAÇÃO") -> INDENIZAÇÃO | BE30: =IF(AND(AY30<>"AGUARDANDO",AY30<>"",N30="AUXÍLIO ALUGUEL ATÉ INDENIZAÇÃO"),"SIM","NÃO") -> NÃO | BF30: N/A | BG30: N/A | BH30: N/A | BI30: AGUARDANDO ELABORAÇÃO
A31: 18 | B31: VIOLÃO III | C31: 1 | D31: -- | E31: -- | F31: 0010019A | G31: OCUPADO | H31: MORADIA | I31: PROPRIETARIO RESIDENTE | J31: SILVANA FERNANDES DA SILVA BATISTA | K31: 284.195.998-83 | L31: 284.195.998-83 | M31: CONCLUIDO | N31: AUXÍLIO ALUGUEL | O31: 45987 | P31: Finalizada | Q31: 6014.2025/0007038-7 | R31: Finalizado | S31: Finalizado | AB31: ADILSON GOMES ROCHA | AC31: 354.750.938-65 | AD31: 53.179.453-2 | AE31: PROPRIETARIO RESIDENTE | BC31: =IF(AY31-KD31=0,"",AY31-O31) | BD31: =IF(AND(AI31<>"SIM",AI31="UH"),"AA","INDENIZAÇÃO") -> INDENIZAÇÃO | BE31: =IF(AND(AY31<>"AGUARDANDO",AY31<>"",N31="AUXÍLIO ALUGUEL ATÉ INDENIZAÇÃO"),"SIM","NÃO") -> NÃO
A32: 19 | B32: VIOLÃO III | C32: 1 | D32: -- | E32: -- | F32: 0010020A | G32: OCUPADO | H32: MORADIA | I32: PROPRIETARIO RESIDENTE | J32: JOSEFA MARIA DE SOUZA | K32: 33.890.191-7 | L32: 292.573.988-11 | N32: INDENIZAÇÃO | AB32: VITORIA VIERA DA SILVA PORTO | AC32: 504.741.198/23 | AD32: 53.829.431-0 | AE32: PROPRIETARIO RESIDENTE | AJ32: 6014.2025/0006976-1 | BC32: =IF(AY32-KD32=0,"",AY32-O32) | BD32: =IF(AND(AI32<>"SIM",AI32="UH"),"AA","INDENIZAÇÃO") -> INDENIZAÇÃO | BE32: =IF(AND(AY32<>"AGUARDANDO",AY32<>"",N32="AUXÍLIO ALUGUEL ATÉ INDENIZAÇÃO"),"SIM","NÃO") -> NÃO
A33: 20 | B33: VIOLÃO III | C33: 1 | D33: -- | E33: -- | F33: 0010021A | G33: OCUPADO | H33: MISTO | I33: PROPRIETARIO NÃO RESIDENTE | J33: NAIARA RIBEIRO DO NASCIMENTO ALMEIDA | K33: 48020699 | L33: 385.936.878-81 | N33: INDENIZAÇÃO | AB33: GUSTAVO ROCHA GOTARDO | AC33: 21.145.736-13 | AD33: 864.072.475-00 | AE33: PROPRIETARIO NÃO RESIDENTE | AJ33: 6014.2025/0006976-1 | BC33: =IF(AY33-KD33=0,"",AY33-O33) | BD33: =IF(AND(AI33<>"SIM",AI33="UH"),"AA","INDENIZAÇÃO") -> INDENIZAÇÃO | BE33: =IF(AND(AY33<>"AGUARDANDO",AY33<>"",N33="AUXÍLIO ALUGUEL ATÉ INDENIZAÇÃO"),"SIM","NÃO") -> NÃO
A34: 21 | B34: VIOLÃO III | C34: 1 | D34: -- | E34: -- | F34: 0010022A | G34: VAZIO | H34: CONSTRUÇÃO | J34: VALDINETE BONFIM DOS SANTOS SILVA | K34: 34.635.441-9 | L34: 298.799.678-01 | N34: INDENIZAÇÃO | AB34: ERICK FERREIRA DA SILVA | AC34: 541.725.068-60 | AD34: 56.769.551-7 | AE34: PROPRIETARIO RESIDENTE | AJ34: 6014.2025/0006976-1 | BC34: =IF(AY34-KD34=0,"",AY34-O34) | BD34: =IF(AND(AI34<>"SIM",AI34="UH"),"AA","INDENIZAÇÃO") -> INDENIZAÇÃO | BE34: =IF(AND(AY34<>"AGUARDANDO",AY34<>"",N34="AUXÍLIO ALUGUEL ATÉ INDENIZAÇÃO"),"SIM","NÃO") -> NÃO
A35: 22 | B35: VIOLÃO III | C35: 1 | D35: -- | E35: -- | F35: 0010023A | G35: OCUPADO | H35: MORADIA | I35: PROPRIETARIO RESIDENTE | J35: WELSEY DE OLIVEIRA AUGUSTO | K35: 38.540.375-6 | L35: 454.102.348-20 | N35: INDENIZAÇÃO | AB35: GINA MARIA DA SILVA FERREIRA | AC35: 342.470.298-60 | AD35: 43.407.904-2 | AE35: PROPRIETARIO RESIDENTE | AJ35: 6014.2025/0006976-1 | BC35: =IF(AY35-KD35=0,"",AY35-O35) | BD35: =IF(AND(AI35<>"SIM",AI35="UH"),"AA","INDENIZAÇÃO") -> INDENIZAÇÃO | BE35: =IF(AND(AY35<>"AGUARDANDO",AY35<>"",N35="AUXÍLIO ALUGUEL ATÉ INDENIZAÇÃO"),"SIM","NÃO") -> NÃO
A36: 23 | B36: VIOLÃO III | C36: 1 | D36: -- | E36: -- | F36: 0010024A | G36: OCUPADO | H36: MORADIA | I36: PROPRIETARIO RESIDENTE | J36: JADILSON MIRANDA DA SILVA | K36: 48.4158.284- | L36: 405.328.268-33 | N36: INDENIZAÇÃO | AB36: EDSON VICENTE DA SILVA | AC36: 356.613.068-06 | AD36: 40.573.869-9 | AE36: PROPRIETARIO RESIDENTE | AJ36: 6014.2025/0006976-1 | BC36: =IF(AY36-KD36=0,"",AY36-O36) | BD36: =IF(AND(AI36<>"SIM",AI36="UH"),"AA","INDENIZAÇÃO") -> INDENIZAÇÃO | BE36: =IF(AND(AY36<>"AGUARDANDO",AY36<>"",N36="AUXÍLIO ALUGUEL ATÉ INDENIZAÇÃO"),"SIM","NÃO") -> NÃO
A37: 24 | B37: VIOLÃO III | C37: 1 | D37: -- | E37: -- | F37: 0010025A | G37: OCUPADO | H37: MORADIA | I37: PROPRIETARIO RESIDENTE | J37: THAIS DA SILVA FARIAS | K37: 54.467.627-0 | L37: 562.089.588-22 | M37: CONCLUIDO | N37: INDENIZAÇÃO | AB37: TATIANE RAINHA DOS SANTOS | AC37: 127.328.156-08 | AD37: 43.767.855-0 | AE37: PROPRIETARIO RESIDENTE | AJ37: 6014.2025/0006976-1 | BC37: =IF(AY37-KD37=0,"",AY37-O37) | BD37: =IF(AND(AI37<>"SIM",AI37="UH"),"AA","INDENIZAÇÃO") -> INDENIZAÇÃO | BE37: =IF(AND(AY37<>"AGUARDANDO",AY37<>"",N37="AUXÍLIO ALUGUEL ATÉ INDENIZAÇÃO"),"SIM","NÃO") -> NÃO
A38: 25 | B38: VIOLÃO III | C38: 1 | D38: -- | E38: -- | F38: 0010026A | G38: OCUPADO | H38: RESIDENCIAL | I38: PROPRIETARIO RESIDENTE | J38: ROSILDA MARIA DA SILVA | K38: 54.289.830-5 | L38: 435.208.044-68 | M38: CONCLUIDO | N38: AUXÍLIO ALUGUEL | O38: 45960 | P38: Finalizada | Q38: 6014.2025/0007038-7 | R38: Finalizado | S38: Finalizado | T38: Finalizado | U38: 45968 | V38: Finalizado | W38: 45980 | X38: 45993 | Y38: Aguardando | Z38: Aguardando | AB38: ELIECI RAINHA DOS SANTOS | AC38: 086.758.688-55 | AD38: 19.512.082-6 | AE38: PROPRIETARIO RESIDENTE | BC38: =IF(AY38-KD38=0,"",AY38-O38) | BD38: =IF(AND(AI38<>"SIM",AI38="UH"),"AA","INDENIZAÇÃO") -> INDENIZAÇÃO | BE38: =IF(AND(AY38<>"AGUARDANDO",AY38<>"",N38="AUXÍLIO ALUGUEL ATÉ INDENIZAÇÃO"),"SIM","NÃO") -> NÃO
A39: 26 | B39: VIOLÃO III | C39: 1 | D39: -- | E39: -- | F39: 0010027A | G39: OCUPADO | H39: MORADIA | I39: PROPRIETARIO RESIDENTE | J39: JAQUELINE DA COSTA MONTEIRO | K39: 40.244.672-0 | L39: 061.236.644-84 | M39: CONCLUIDO | N39: INDENIZAÇÃO | AB39: EVELIN SAMANTA GOMES SILVA | AC39: 491.909.618/62 | AD39: 58.614.221-6 | AE39: PROPRIETARIO RESIDENTE | AJ39: 6014.2025/0006976-1 | BC39: =IF(AY39-KD39=0,"",AY39-O39) | BD39: =IF(AND(AI39<>"SIM",AI39="UH"),"AA","INDENIZAÇÃO") -> INDENIZAÇÃO | BE39: =IF(AND(AY39<>"AGUARDANDO",AY39<>"",N39="AUXÍLIO ALUGUEL ATÉ INDENIZAÇÃO"),"SIM","NÃO") -> NÃO
A40: 27 | B40: VIOLÃO III | C40: 1 | D40: -- | E40: -- | F40: 0010028A | G40: OCUPADO | H40: MORADIA | I40: PROPRIETARIO RESIDENTE | J40: ADRIELLE SILVA OLIVEIRA | K40: 55.115.634-X | L40: 509.672.978-85 | M40: CONCLUIDO | N40: AUXÍLIO ALUGUEL | O40: 45987 | P40: Finalizada | Q40: 6014.2025/0007038-7 | R40: Finalizado | S40: Finalizado | AB40: LEILA SILVANA DA SILVEIRA SIQUEIRA | AC40: 37.039.112--3 | AD40: 37.039.112-3 | AE40: PROPRIETARIO RESIDENTE | BC40: =IF(AY40-KD40=0,"",AY40-O40) | BD40: =IF(AND(AI40<>"SIM",AI40="UH"),"AA","INDENIZAÇÃO") -> INDENIZAÇÃO | BE40: =IF(AND(AY40<>"AGUARDANDO",AY40<>"",N40="AUXÍLIO ALUGUEL ATÉ INDENIZAÇÃO"),"SIM","NÃO") -> NÃO
A41: 28 | B41: VIOLÃO III | C41: 1 | D41: -- | E41: -- | F41: 0010029A | G41: OCUPADO | H41: MORADIA | I41: PROPRIETARIO RESIDENTE | J41: JARDILENE SILVA DOS SANTOS | K41: 43.871.217-1 | L41: 436.106.958-11 | N41: INDENIZAÇÃO | AB41: LAUDICEIA SOARES SILVA | AC41: 319.943.338/39 | AD41: 33.892.102-3 | AE41: PROPRIETARIO RESIDENTE | AJ41: 6014.2025/0006976-1 | BC41: =IF(AY41-KD41=0,"",AY41-O41) | BD41: =IF(AND(AI41<>"SIM",AI41="UH"),"AA","INDENIZAÇÃO") -> INDENIZAÇÃO | BE41: =IF(AND(AY41<>"AGUARDANDO",AY41<>"",N41="AUXÍLIO ALUGUEL ATÉ INDENIZAÇÃO"),"SIM","NÃO") -> NÃO
A42: 29 | B42: VIOLÃO III | C42: 1 | D42: -- | E42: -- | F42: 0010030A | G42: OCUPADO | H42: DORMITÓRIO | I42: PROPRIETARIO RESIDENTE | J42: ARTHUR FRANÇA CEZAR | K42: 49.371.646-4 | L42: 421.581.048-56 | AB42: MARIA APARECIDA XAVIER DOS SANTOS | AC42: 022.840.924/11 | AD42: 38.755.186-40028 | AE42: PROPRIETARIO RESIDENTE | BC42: =IF(AY42-KD42=0,"",AY42-O42) | BD42: =IF(AND(AI42<>"SIM",AI42="UH"),"AA","INDENIZAÇÃO") -> INDENIZAÇÃO | BE42: =IF(AND(AY42<>"AGUARDANDO",AY42<>"",N42="AUXÍLIO ALUGUEL ATÉ INDENIZAÇÃO"),"SIM","NÃO") -> NÃO
A43: 30 | B43: VIOLÃO III | C43: 1 | D43: -- | E43: -- | F43: 0010031A | G43: OCUPADO | H43: DORMITÓRIO | I43: PROPRIETARIO RESIDENTE | J43: FRANCISCO ERIVAN DOS SANTOZ SOUZA JUNIOR | K43: 45.884.500-0 | L43: 340.716.038-01 | AB43: VERA LÚCIA FERREIRA DA SILVA | AC43: 103.766.088/97 | AD43: 20.974.649-X | AE43: PROPRIETARIO RESIDENTE | BC43: =IF(AY43-KD43=0,"",AY43-O43) | BD43: =IF(AND(AI43<>"SIM",AI43="UH"),"AA","INDENIZAÇÃO") -> INDENIZAÇÃO | BE43: =IF(AND(AY43<>"AGUARDANDO",AY43<>"",N43="AUXÍLIO ALUGUEL ATÉ INDENIZAÇÃO"),"SIM","NÃO") -> NÃO
A44: 31 | B44: VIOLÃO III | C44: 1 | D44: -- | E44: -- | F44: 0010032A | G44: OCUPADO | H44: DORMITÓRIO | I44: PROPRIETARIO RESIDENTE | J44: THAIS THIANA DOS SANTOS LEÃO | K44: 38.755.771-4 | L44: 859.044.925-45 | AB44: ELZA MARIA VENÂNCIO | AC44: 172.372.178/60 | AD44: 27.498.261-4 | AE44: PROPRIETARIO RESIDENTE | BC44: =IF(AY44-KD44=0,"",AY44-O44) | BD44: =IF(AND(AI44<>"SIM",AI44="UH"),"AA","INDENIZAÇÃO") -> INDENIZAÇÃO | BE44: =IF(AND(AY44<>"AGUARDANDO",AY44<>"",N44="AUXÍLIO ALUGUEL ATÉ INDENIZAÇÃO"),"SIM","NÃO") -> NÃO
A45: 32 | B45: VIOLÃO III | C45: 1 | D45: -- | E45: -- | F45: 0010034A | G45: OCUPADO | H45: DORMITÓRIO | I45: PROPRIETARIO RESIDENTE | J45: MISAEL RUBENS DE OLIVEIRA | K45: 44.474.272-4 | L45: 380.139.478-66 | N45: INDENIZAÇÃO | AB45: KATIANE MÔNICA DA SILVA | AC45: 293.579.388/93 | AD45: 28.549.500-8 | AE45: PROPRIETARIO RESIDENTE | AJ45: 6014.2025/0006976-1 | BC45: =IF(AY45-KD45=0,"",AY45-O45) | BD45: =IF(AND(AI45<>"SIM",AI45="UH"),"AA","INDENIZAÇÃO") -> INDENIZAÇÃO | BE45: =IF(AND(AY45<>"AGUARDANDO",AY45<>"",N45="AUXÍLIO ALUGUEL ATÉ INDENIZAÇÃO"),"SIM","NÃO") -> NÃO
A46: 33 | B46: VIOLÃO III | C46: 1 | D46: -- | E46: -- | F46: 0010035A | G46: OCUPADO | H46: DORMITÓRIO | I46: PROPRIETARIO RESIDENTE | J46: CARLEANDRO SILVA SANTOS | K46: 32.360.767-6 | L46: 279.241.898-23 | N46: INDENIZAÇÃO | AB46: SIDNEI DE SOUZA ROYO | AC46: 339.395.408-38 | AD46: 36.053.320-6 | AE46: PROPRIETARIO RESIDENTE | AJ46: 6014.2025/0006976-1 | BC46: =IF(AY46-KD46=0,"",AY46-O46) | BD46: =IF(AND(AI46<>"SIM",AI46="UH"),"AA","INDENIZAÇÃO") -> INDENIZAÇÃO | BE46: =IF(AND(AY46<>"AGUARDANDO",AY46<>"",N46="AUXÍLIO ALUGUEL ATÉ INDENIZAÇÃO"),"SIM","NÃO") -> NÃO
A47: 34 | B47: VIOLÃO III | C47: 1 | D47: -- | E47: -- | F47: 0010035B | G47: OCUPADO | H47: DORMITÓRIO | I47: PROPRIETARIO RESIDENTE | J47: MIGUEL ANGEL GUARACHI VELASCO | L47: 901.787.598-48 | AB47: MARIA DAS NEVES SILVA LOPES | AC47: 226.791.188-47 | AD47: 38.990.952-X | AE47: PROPRIETARIO RESIDENTE | BC47: =IF(AY47-KD47=0,"",AY47-O47) | BD47: =IF(AND(AI47<>"SIM",AI47="UH"),"AA","INDENIZAÇÃO") -> INDENIZAÇÃO | BE47: =IF(AND(AY47<>"AGUARDANDO",AY47<>"",N47="AUXÍLIO ALUGUEL ATÉ INDENIZAÇÃO"),"SIM","NÃO") -> NÃO
A48: 35 | B48: VIOLÃO III | C48: 1 | D48: -- | E48: -- | F48: 001015A | G48: OCUPADO | H48: DORMITÓRIO | I48: PROPRIETARIO RESIDENTE | J48: LUIS CARLOS DOS SANTOS | AB48: NEUMA GOMES ROCHA | AC48: 358.269.808/42 | AD48: 54.991.299-X | AE48: PROPRIETARIO RESIDENTE | BC48: =IF(AY48-KD48=0,"",AY48-O48) | BD48: =IF(AND(AI48<>"SIM",AI48="UH"),"AA","INDENIZAÇÃO") -> INDENIZAÇÃO | BE48: =IF(AND(AY48<>"AGUARDANDO",AY48<>"",N48="AUXÍLIO ALUGUEL ATÉ INDENIZAÇÃO"),"SIM","NÃO") -> NÃO
A49: 36 | B49: VIOLÃO III | C49: 1 | D49: -- | E49: -- | F49: 001033A | G49: OCUPADO | H49: DORMITÓRIO | I49: PROPRIETARIO RESIDENTE | J49: JOSE ROBERTO DUARTE DE LIMA | K49: 28.756.969-x | L49: 253.971.618-02 | AB49: MARIA JOSÉ DA CONCEIÇÃO | AC49: 255.738.168/37 | AD49: 16.849.394-9 | AE49: PROPRIETARIO RESIDENTE | BC49: =IF(AY49-KD49=0,"",AY49-O49) | BD49: =IF(AND(AI49<>"SIM",AI49="UH"),"AA","INDENIZAÇÃO") -> INDENIZAÇÃO | BE49: =IF(AND(AY49<>"AGUARDANDO",AY49<>"",N49="AUXÍLIO ALUGUEL ATÉ INDENIZAÇÃO"),"SIM","NÃO") -> NÃO
A50: 37 | B50: VIOLÃO III | C50: 1 | D50: -- | E50: -- | F50: 0140066B | G50: OCUPADO | H50: RESIDENCIAL | I50: PROPRIETARIO RESIDENTE | J50: CLEUDIANE MEDINA DA CRUZ | K50: 63.150.543-X | L50: 045.180.753-74 | M50: CONCLUIDO | N50: INDENIZAÇÃO | AB50: CLEUDIANE MEDINA DA CRUZ | AC50: 045.180.753-74 | AD50: 63.150.543-X | AE50: PROPRIETARIO RESIDENTE | AJ50: 6014.2025/0006976-1 | BC50: =IF(AY50-KD50=0,"",AY50-O50) | BD50: =IF(AND(AI50<>"SIM",AI50="UH"),"AA","INDENIZAÇÃO") -> INDENIZAÇÃO | BE50: =IF(AND(AY50<>"AGUARDANDO",AY50<>"",N50="AUXÍLIO ALUGUEL ATÉ INDENIZAÇÃO"),"SIM","NÃO") -> NÃO
A51: 38 | B51: VIOLÃO III | C51: 1 | D51: -- | E51: -- | F51: 0140129A | G51: OCUPADO | H51: RESIDENCIAL | I51: PROPRIETARIO RESIDENTE | J51: VANDA LOPES OLIVEIRA SILVA | K51: 48.989.803-8 | L51: 232.535.398-22 | M51: CONCLUIDO | N51: INDENIZAÇÃO | AB51: VANDA LOPES OLIVEIRA SILVA | AC51: 232.535.398-22 | AD51: 48.989.803-8 | AE51: PROPRIETARIO RESIDENTE | AJ51: 6014.2025/0006976-1 | BC51: =IF(AY51-KD51=0,"",AY51-O51) | BD51: =IF(AND(AI51<>"SIM",AI51="UH"),"AA","INDENIZAÇÃO") -> INDENIZAÇÃO | BE51: =IF(AND(AY51<>"AGUARDANDO",AY51<>"",N51="AUXÍLIO ALUGUEL ATÉ INDENIZAÇÃO"),"SIM","NÃO") -> NÃO
A52: 39 | B52: VIOLÃO III | C52: 1 | D52: -- | E52: -- | F52: 0140130A | G52: OCUPADO | H52: RESIDENCIAL | I52: PROPRIETARIO RESIDENTE | J52: PAULO SANTOS DIAS | K52: 325462859 | L52: 711.496.605-97 | M52: CONCLUIDO | N52: INDENIZAÇÃO | AB52: PAULO SANTOS DIAS | AC52: 711.496.605-97 | AD52: 325462859 | AE52: PROPRIETARIO RESIDENTE | AJ52: 6014.2025/0006976-1 | BC52: =IF(AY52-KD52=0,"",AY52-O52) | BD52: =IF(AND(AI52<>"SIM",AI52="UH"),"AA","INDENIZAÇÃO") -> INDENIZAÇÃO | BE52: =IF(AND(AY52<>"AGUARDANDO",AY52<>"",N52="AUXÍLIO ALUGUEL ATÉ INDENIZAÇÃO"),"SIM","NÃO") -> NÃO
A53: 40 | B53: VIOLÃO III | C53: 1 | D53: -- | E53: -- | F53: 0140131A | G53: OCUPADO | H53: RESIDENCIAL | I53: PROPRIETARIO RESIDENTE | J53: MONIQUE PINTO SOUZA | K53: 36.052.059-5 | L53: 384.416.568-19 | M53: CONCLUIDO | N53: INDENIZAÇÃO | AB53: MONIQUE PINTO SOUZA | AC53: 384.416.568-19 | AD53: 36.052.059-5 | AE53: PROPRIETARIO RESIDENTE | AJ53: 6014.2025/0006976-1 | BC53: =IF(AY53-KD53=0,"",AY53-O53) | BD53: =IF(AND(AI53<>"SIM",AI53="UH"),"AA","INDENIZAÇÃO") -> INDENIZAÇÃO | BE53: =IF(AND(AY53<>"AGUARDANDO",AY53<>"",N53="AUXÍLIO ALUGUEL ATÉ INDENIZAÇÃO"),"SIM","NÃO") -> NÃO
A54: 41 | B54: VIOLÃO III | C54: 1 | D54: -- | E54: -- | F54: 0140132A | G54: OCUPADO | H54: RESIDENCIAL | I54: PROPRIETARIO RESIDENTE | J54: TERRENO VAZIO | M54: CONCLUIDO | AB54: TERRENO VAZIO | AE54: PROPRIETARIO RESIDENTE | BC54: =IF(AY54-KD54=0,"",AY54-O54) | BD54: =IF(AND(AI54<>"SIM",AI54="UH"),"AA","INDENIZAÇÃO") -> INDENIZAÇÃO | BE54: =IF(AND(AY54<>"AGUARDANDO",AY54<>"",N54="AUXÍLIO ALUGUEL ATÉ INDENIZAÇÃO"),"SIM","NÃO") -> NÃO
A55: 42 | B55: VIOLÃO III | C55: 1 | D55: -- | E55: -- | F55: 0140133A | G55: OCUPADO | H55: RESIDENCIAL | I55: PROPRIETARIO RESIDENTE | J55: JOSÉ ORLANDO DA CRUZ | K55: 57.985.220-9 | L55: 081.453.904-19 | M55: CONCLUIDO | N55: INDENIZAÇÃO | AB55: JOSÉ ORLANDO DA CRUZ | AC55: 081.453.904-19 | AD55: 57.985.220-9 | AE55: PROPRIETARIO RESIDENTE | AJ55: 6014.2025/0006976-1 | BC55: =IF(AY55-KD55=0,"",AY55-O55) | BD55: =IF(AND(AI55<>"SIM",AI55="UH"),"AA","INDENIZAÇÃO") -> INDENIZAÇÃO | BE55: =IF(AND(AY55<>"AGUARDANDO",AY55<>"",N55="AUXÍLIO ALUGUEL ATÉ INDENIZAÇÃO"),"SIM","NÃO") -> NÃO
A56: 43 | B56: VIOLÃO III | C56: 1 | D56: -- | E56: -- | F56: 0140134A | G56: OCUPADO | H56: RESIDENCIAL | I56: PROPRIETARIO RESIDENTE | J56: JOSIVAN MARIANO DA SILVA | K56: 37586025 | L56: 113.523.214-83 | M56: CONCLUIDO | N56: INDENIZAÇÃO | AB56: JOSIVAN MARIANO DA SILVA | AC56: 113.523.214-83 | AD56: 37586025 | AE56: PROPRIETARIO RESIDENTE | AJ56: 6014.2025/0006976-1 | BC56: =IF(AY56-KD56=0,"",AY56-O56) | BD56: =IF(AND(AI56<>"SIM",AI56="UH"),"AA","INDENIZAÇÃO") -> INDENIZAÇÃO | BE56: =IF(AND(AY56<>"AGUARDANDO",AY56<>"",N56="AUXÍLIO ALUGUEL ATÉ INDENIZAÇÃO"),"SIM","NÃO") -> NÃO
A57: 44 | B57: VIOLÃO III | C57: 1 | D57: -- | E57: -- | F57: 0140134B | G57: OCUPADO | H57: RESIDENCIAL | I57: PROPRIETARIO RESIDENTE | J57: GEOVANIA MARIANO DA SILVA | K57: 56.501.489-4 | L57: 235.585.438-66 | M57: CONCLUIDO | N57: INDENIZAÇÃO | AB57: GEOVANIA MARIANO DA SILVA | AC57: 235.585.438-66 | AD57: 56.501.489-4 | AE57: PROPRIETARIO RESIDENTE | AJ57: 6014.2025/0006976-1 | BC57: =IF(AY57-KD57=0,"",AY57-O57) | BD57: =IF(AND(AI57<>"SIM",AI57="UH"),"AA","INDENIZAÇÃO") -> INDENIZAÇÃO | BE57: =IF(AND(AY57<>"AGUARDANDO",AY57<>"",N57="AUXÍLIO ALUGUEL ATÉ INDENIZAÇÃO"),"SIM","NÃO") -> NÃO
A58: 45 | B58: VIOLÃO III | C58: 1 | D58: -- | E58: -- | F58: 0140135A | G58: OCUPADO | H58: RESIDENCIAL | I58: PROPRIETARIO RESIDENTE | J58: MARIA APARECIDA LOPES DE MORAES | K58: 21.568.007-8 | L58: 175.143.488-59 | M58: CONCLUIDO | N58: INDENIZAÇÃO | AB58: MARIA APARECIDA LOPES DE MORAES | AC58: 175.143.488-59 | AD58: 21.568.007-8 | AE58: PROPRIETARIO RESIDENTE | AJ58: 6014.2025/0006976-1 | BC58: =IF(AY58-KD58=0,"",AY58-O58) | BD58: =IF(AND(AI58<>"SIM",AI58="UH"),"AA","INDENIZAÇÃO") -> INDENIZAÇÃO | BE58: =IF(AND(AY58<>"AGUARDANDO",AY58<>"",N58="AUXÍLIO ALUGUEL ATÉ INDENIZAÇÃO"),"SIM","NÃO") -> NÃO
A59: 46 | B59: VIOLÃO III | C59: 1 | D59: -- | E59: -- | F59: 0140135B | G59: OCUPADO | H59: RESIDENCIAL | I59: PROPRIETARIO RESIDENTE | J59: ELINEIDE FILGUEIRA DOS SANTOS | K59: 55.412.321-6 | L59: 297.348.118-00 | M59: CONCLUIDO | N59: INDENIZAÇÃO | AB59: ELINEIDE FILGUEIRA DOS SANTOS | AC59: 297.348.118-00 | AD59: 55.412.321-6 | AE59: PROPRIETARIO RESIDENTE | AJ59: 6014.2025/0006976-1 | BC59: =IF(AY59-KD59=0,"",AY59-O59) | BD59: =IF(AND(AI59<>"SIM",AI59="UH"),"AA","INDENIZAÇÃO") -> INDENIZAÇÃO | BE59: =IF(AND(AY59<>"AGUARDANDO",AY59<>"",N59="AUXÍLIO ALUGUEL ATÉ INDENIZAÇÃO"),"SIM","NÃO") -> NÃO
A60: 47 | B60: VIOLÃO III | C60: 1 | D60: -- | E60: -- | F60: 0140135C | G60: OCUPADO | H60: RESIDENCIAL | I60: PROPRIETARIO RESIDENTE | J60: IZAC LOPES DE MORAES GARCIA | K60: 38.413.414.-2 | L60: 491.125.558-78 | M60: CONCLUIDO | N60: INDENIZAÇÃO | AB60: IZAC LOPES DE MORAES GARCIA | AC60: 491.125.558-78 | AD60: 38.413.414.-2 | AE60: PROPRIETARIO RESIDENTE | AJ60: 6014.2025/0006976-1 | BC60: =IF(AY60-KD60=0,"",AY60-O60) | BD60: =IF(AND(AI60<>"SIM",AI60="UH"),"AA","INDENIZAÇÃO") -> INDENIZAÇÃO | BE60: =IF(AND(AY60<>"AGUARDANDO",AY60<>"",N60="AUXÍLIO ALUGUEL ATÉ INDENIZAÇÃO"),"SIM","NÃO") -> NÃO
A61: 48 | B61: VIOLÃO III | C61: 1 | D61: -- | E61: -- | F61: 0140135D | G61: OCUPADO | H61: RESIDENCIAL | I61: PROPRIETARIO RESIDENTE | J61: LARISSA CRISTINA FILGUEIRA DOS SANTOS | K61: 39.851.068-4 | L61: 460.709.448-01 | M61: CONCLUIDO | N61: INDENIZAÇÃO | AB61: LARISSA CRISTINA FILGUEIRA DOS SANTOS | AC61: 39.851.068-4 | AD61: 460.709.448-01 | AE61: PROPRIETARIO RESIDENTE | AJ61: 6014.2025/0006976-1 | BC61: =IF(AY61-KD61=0,"",AY61-O61) | BD61: =IF(AND(AI61<>"SIM",AI61="UH"),"AA","INDENIZAÇÃO") -> INDENIZAÇÃO | BE61: =IF(AND(AY61<>"AGUARDANDO",AY61<>"",N61="AUXÍLIO ALUGUEL ATÉ INDENIZAÇÃO"),"SIM","NÃO") -> NÃO
A62: 49 | B62: VIOLÃO III | C62: 1 | D62: -- | E62: -- | F62: 0140136A | G62: OCUPADO | H62: RESIDENCIAL | I62: PROPRIETARIO RESIDENTE | J62: LUCAS BENEDITO DOS SANTOS | K62: 55.299.807-2 | L62: 482.199.648-04 | M62: CONCLUIDO | N62: INDENIZAÇÃO | AB62: LUCAS BENEDITO DOS SANTOS | AC62: 482.199.648-04 | AD62: 55.299.807-2 | AE62: PROPRIETARIO RESIDENTE | AJ62: 6014.2025/0006976-1 | BC62: =IF(AY62-KD62=0,"",AY62-O62) | BD62: =IF(AND(AI62<>"SIM",AI62="UH"),"AA","INDENIZAÇÃO") -> INDENIZAÇÃO | BE62: =IF(AND(AY62<>"AGUARDANDO",AY62<>"",N62="AUXÍLIO ALUGUEL ATÉ INDENIZAÇÃO"),"SIM","NÃO") -> NÃO
A63: 50 | B63: VIOLÃO III | C63: 1 | D63: -- | E63: -- | F63: 0140137A | G63: OCUPADO | H63: RESIDENCIAL | I63: PROPRIETARIO RESIDENTE | J63: ABEL BARBOSA DO NASCIMENTO | K63: 22.819.273-00 | L63: 270.899.588-09 | M63: CONCLUIDO | N63: INDENIZAÇÃO | AB63: ABEL BARBOSA DO NASCIMENTO | AC63: 270.899.588-09 | AD63: 22.819.273-00 | AE63: PROPRIETARIO RESIDENTE | AJ63: 6014.2025/0006976-1 | BC63: =IF(AY63-KD63=0,"",AY63-O63) | BD63: =IF(AND(AI63<>"SIM",AI63="UH"),"AA","INDENIZAÇÃO") -> INDENIZAÇÃO | BE63: =IF(AND(AY63<>"AGUARDANDO",AY63<>"",N63="AUXÍLIO ALUGUEL ATÉ INDENIZAÇÃO"),"SIM","NÃO") -> NÃO
A64: 51 | B64: VIOLÃO III | C64: 1 | D64: -- | E64: -- | F64: 0140137B | G64: OCUPADO | H64: RESIDENCIAL | I64: PROPRIETARIO RESIDENTE | J64: (NÃO ENCONTRAMOS MORADOR EM TODAS AS VISITAS) | M64: CONCLUIDO | AB64: (NÃO ENCONTRAMOS MORADOR EM TODAS AS VISITAS) | AE64: PROPRIETARIO RESIDENTE | BC64: =IF(AY64-KD64=0,"",AY64-O64) | BD64: =IF(AND(AI64<>"SIM",AI64="UH"),"AA","INDENIZAÇÃO") -> INDENIZAÇÃO | BE64: =IF(AND(AY64<>"AGUARDANDO",AY64<>"",N64="AUXÍLIO ALUGUEL ATÉ INDENIZAÇÃO"),"SIM","NÃO") -> NÃO
A65: 52 | B65: VIOLÃO III | C65: 1 | D65: -- | E65: -- | F65: 0140138A | G65: OCUPADO | H65: RESIDENCIAL | I65: PROPRIETARIO RESIDENTE | J65: SILVIA DAILETE DA COSTA DA SILVA | K65: 35.418.571-8 | L65: 357.226.418-98 | M65: CONCLUIDO | N65: INDENIZAÇÃO | AB65: SILVIA DAILETE DA COSTA DA SILVA | AC65: 35.418.571-8 | AD65: 357.226.418-98 | AE65: PROPRIETARIO RESIDENTE | AJ65: 6014.2025/0006976-1 | BC65: =IF(AY65-KD65=0,"",AY65-O65) | BD65: =IF(AND(AI65<>"SIM",AI65="UH"),"AA","INDENIZAÇÃO") -> INDENIZAÇÃO | BE65: =IF(AND(AY65<>"AGUARDANDO",AY65<>"",N65="AUXÍLIO ALUGUEL ATÉ INDENIZAÇÃO"),"SIM","NÃO") -> NÃO
A66: 53 | B66: VIOLÃO III | C66: 1 | D66: -- | E66: -- | F66: 0140139A | G66: OCUPADO | H66: RESIDENCIAL | I66: PROPRIETARIO RESIDENTE | J66: JOSÉ APARECIDO DOS SANTOS | K66: 53.448.929-1 | L66: 008.343.684-71 | M66: CONCLUIDO | N66: INDENIZAÇÃO | AB66: JOSÉ APARECIDO DOS SANTOS | AC66: 008.343.684-71 | AD66: 53.448.929-1 | AE66: PROPRIETARIO RESIDENTE | AJ66: 6014.2025/0006976-1 | BC66: =IF(AY66-KD66=0,"",AY66-O66) | BD66: =IF(AND(AI66<>"SIM",AI66="UH"),"AA","INDENIZAÇÃO") -> INDENIZAÇÃO | BE66: =IF(AND(AY66<>"AGUARDANDO",AY66<>"",N66="AUXÍLIO ALUGUEL ATÉ INDENIZAÇÃO"),"SIM","NÃO") -> NÃO
A67: 54 | B67: VIOLÃO III | C67: 1 | D67: -- | E67: -- | F67: 0140140A | G67: OCUPADO | H67: RESIDENCIAL | I67: PROPRIETARIO RESIDENTE | J67: GIRLENE SILVA SANTOS | K67: 54.271.082-1 | L67: 040.235.765-37 | M67: CONCLUIDO | N67: AUXÍLIO ALUGUEL | AB67: GIRLENE SILVA SANTOS | AC67: 040.235.765-37 | AD67: 54.271.082-1 | AE67: PROPRIETARIO RESIDENTE | BC67: =IF(AY67-KD67=0,"",AY67-O67) | BD67: =IF(AND(AI67<>"SIM",AI67="UH"),"AA","INDENIZAÇÃO") -> INDENIZAÇÃO | BE67: =IF(AND(AY67<>"AGUARDANDO",AY67<>"",N67="AUXÍLIO ALUGUEL ATÉ INDENIZAÇÃO"),"SIM","NÃO") -> NÃO

Sheet Quantitativo Fora da Demanda
A1: REPROVADOS QUE NÃO DEVERÃO SER REASSENTADOS NO ESPANHA | E1: APROVADOS SEM CONDOMÍNIO QUE DEVERÃO SER REASSENTADOS NO CHÁCARA DO CONDE
A2: ÁREA | B2: QTD | E2: ÁREA | F2: QTD
A3: AUXÍLIO ALUGUEL | B3: 39 | E3: AUXÍLIO ALUGUEL | F3: 54
A4: CANTINHO DO CÉU (OBRAS) | B4: 15 | E4: CANTINHO DO CÉU (OBRAS) SETORES: 138 E 140 | F4: 13
A5: FUMAÇA | B5: 7 | E5: FUMAÇA | F5: 15
A6: NEBLINA | B6: 2 | E6: NEBLINA | F6: 9
A7: LEBLON | B7: 0 | E7: LEBLON | F7: 9
A8: PABREU / PRAINHA | B8: 15 | E8: PABREU / PRAINHA | F8: 21
A9: TOTAL | B9: =SUM(B3:B8) -> 78 | E9: TOTAL | F9: =SUM(F3:F8) -> 121

Sheet Listas (não utilizar)
A1: Área | B1: Condomínio | C1: Bloco | D1: Apartamento | E1: SITAH / CAIXA | F1: Status CAIXA | G1: Adequacao Imovel | H1: Renúncia | I1: Pendência | J1: Pendências / Reprovados caixa
A2: ALTO DA ALEGRIA | B2: AVILA | C2: 1 | D2: 101 | E2: AGENDADO | F2: APROVADO | G2: NÃO | H2: NÃO | I2: CRAS | J2: RENDA SUPERIOR
A3: ALTO DA ALEGRIA (OBRAS) | B3: BARCELONA | C3: 2 | D3: 102 | E3: AGUARDANDO OFICIO | F3: REPROVADO | G3: FÍSICA | H3: RENDA | I3: CRAS + DOCUMENTOS | J3: CADMUT
A4: ALTO DA ALEGRIA (RESERVA) | B4: BILBAO | C4: 3 | D4: 103 | E4: ATENDIMENTO CANCELADO | F4: PENDENCIA | G4: VISUAL | H4: CADIN | I4: DOCUMENTOS | J4: CADIN
A5: ANTERO GOMES | B5: CEUTA | C5: 4 | D5: 104 | E5: CADMUT | F5: SEM DOSSIE | G5: INTELECTUAL | H5: ESTADO CIVIL | I5: CADIN
A6: CANTINHO DO CEU / GAIVOTAS | B6: IBIZA | C6: 5 | D6: 201 | E6: CHACARA DO CONDE | G6: AUDITIVA | H6: SEPARACAO | I6: CRAS + CADIN
A7: CANTINHO DO CEU / OBRAS | B7: LEAO | C7: 6 | D7: 202 | E7: CONFLITO | G7: NANISMO | I7: R.LI.AV.
A8: CASTRO ALVES | B8: MADRID | C8: 7 | D8: 203 | E8: ENVIADO CAIXA | I8: IEME
A9: COCAIA | B9: MELILLA | C9: 8 | D9: 204 | E9: FALECEU
A10: ERUNDINA | B10: PAMPLONA | C10: 9 | D10: 301 | E10: FALTANTE DOSSIÊ
A11: FUMACA | B11: SALAMANCA | C11: 10 | D11: 302 | E11: HABISP ACERTO DE ÁREA
A12: GUAICURI (OBRAS) | B12: TERUEL | C12: 11 | D12: 303 | E12: HABISP AGUARDANDO CRÍTICA
A13: GUAICURI / CIDADE JULIA | B13: VALENCIA | C13: 12 | D13: 304 | E13: HABISP PEND DE ATUALIZ CADASTRAL
A14: JARDIM MIRNA | B14: VALVERDE | C14: 13 | D14: 401 | E14: INDENIZACAO
A15: JARDIM SELMA II | B15: VITORIA | C15: 14 | D15: 402 | E15: PENDENCIA
A16: JARDIM TUBO | C16: 15 | D16: 403 | E16: PERMUTA
A17: LEBLON | D17: 404 | E17: PESQUISA SMADS
A18: MARGINAL DOIS / FUNDAO | D18: 501 | E18: REANALISE
A19: MATA VIRGEM / JD ELDORADO | D19: 502 | E19: RECLUSO
A20: NEBLINA | D20: 503 | E20: RELATÓRIO SOCIAL
A21: NORONHA | D21: 504 | E21: RENDA SUPERIOR
A22: NOVA GRAJAU | E22: RESISTENTE
A23: NOVA MARILDA | E23: TROCA DE TITULARIDADE
A24: NOVA VARGINHA
A25: PABREU / PRAINHA
A26: PENDENCIA GABINETE
A27: PILAO / APURA
A28: PILAO / DOIS
A29: PILAO / PAULISTAS
A30: SANTA AMELIA
A31: VALE VERDE / MONTE VERDE
A32: VILA BREJINHO
A33: VILA NASCENTE
A34: ZR / COSTA BRANCA
A35: VILA RUBI

Sheet QUANT COND
A1: CONDOMINIOS | B1: QUANT
A2: AVILA | B2: =COUNTIF(#REF!,'QUANT COND'!A2) -> #REF!
A3: BARCELONA | B3: =COUNTIF(#REF!,'QUANT COND'!A3) -> #REF!
A4: BILBAO | B4: =COUNTIF(#REF!,'QUANT COND'!A4) -> #REF!
A5: CEUTA | B5: =COUNTIF(#REF!,'QUANT COND'!A5) -> #REF!
A6: IBIZA | B6: =COUNTIF(#REF!,'QUANT COND'!A6) -> #REF!
A7: LEAO | B7: =COUNTIF(#REF!,'QUANT COND'!A7) -> #REF!
A8: MADRID | B8: =COUNTIF(#REF!,'QUANT COND'!A8) -> #REF!
A9: MELILLA | B9: =COUNTIF(#REF!,'QUANT COND'!A9) -> #REF!
A10: PAMPLONA | B10: =COUNTIF(#REF!,'QUANT COND'!A10) -> #REF!
A11: SALAMANCA | B11: =COUNTIF(#REF!,'QUANT COND'!A11) -> #REF!
A12: TERUEL | B12: =COUNTIF(#REF!,'QUANT COND'!A12) -> #REF!
A13: VALENCIA | B13: =COUNTIF(#REF!,'QUANT COND'!A13) -> #REF!
... A15: VITORIA | B15: =COUNTIF(#REF!,'QUANT COND'!A15) -> #REF!

Sheet OFÍCIOS
A1: PLANILHA DE CONFRONTO OFÍCIOS DE INDICAÇÃO COM ENVIADOS CAIXA ECONÔMICA FEDERAL - CEF
A2: TITULAR | B2: CPF | C2: Cônjuge | D2: CPF | E2: OFÍCIO | F2: DATA | G2: STATUS CEF | H2: DATA ENVIO CAIXA | I2: DUPLICIDADE OFÍCIO | J2: DATA | K2: DATA ENVIO CAIXA | L2: OFÍCIO DE INDICAÇÃO | M2: DATA OFÍCIO INDICAÇÃO | O2: NR OFICIO | P2: QUANT | Q2: APROV | R2: REPROV | S2: PEND | T2: SEM STATUS (ANÁLISE) | Y2: CEF BD | Z2: CEF OFICIOS | AA2: CEF PLANILHA
A3: ABEL MEDEIROS FILHO | B3: 27140979871 | E3: 1128 | F3: 42972 | G3: APROVADO | H3: 42979 | O3: 810 | P3: =COUNTIF(OFÍCIOS!E:E,O3) -> 156 | Q3: =COUNTIFS(OFÍCIOS!$E:$E,$O3,OFÍCIOS!$G:$G,"APROVADO") -> 149 | R3: =COUNTIFS(OFÍCIOS!$E:$E,$O3,OFÍCIOS!$G:$G,"REPROVADO") -> 3 | S3: =COUNTIFS(OFÍCIOS!$E:$E,$O3,OFÍCIOS!$G:$G,"PENDENCIA") -> 2 | T3: =COUNTIFS(OFÍCIOS!$E:$E,$O3,OFÍCIOS!$G:$G,"") -> 2 | U3: =SUM(Q3:T3) -> 156 | X3: FEITOS | Y3: 1850 | Z3: 1827 | AA3: =SUM(AA4:AA7) -> 1615
A4: ABELINA FERREIRA DOS SANTOS | B4: 39200633846 | O4: 1417 | P4: =COUNTIF(OFÍCIOS!E:E,O4) -> 42 | Q4: =COUNTIFS(OFÍCIOS!$E:$E,$O4,OFÍCIOS!$G:$G,"APROVADO") -> 36 | R4: =COUNTIFS(OFÍCIOS!$E:$E,$O4,OFÍCIOS!$G:$G,"REPROVADO") -> 3 | S4: =COUNTIFS(OFÍCIOS!$E:$E,$O4,OFÍCIOS!$G:$G,"PENDENCIA") -> 3 | T4: =COUNTIFS(OFÍCIOS!$E:$E,$O4,OFÍCIOS!$G:$G,"") -> 0 | U4: =SUM(Q4:T4) -> 42 | X4: APROVADOS | Y4: 1517 | Z4: 1427 | AA4: 1559
A5: ABIGAIL DE OLIVEIRA PAULINO | B5: 75489104872 | E5: 1752 | F5: 43051 | G5: APROVADO | H5: 43089 | L5: 1759 | O5: 1359 | P5: =COUNTIF(OFÍCIOS!E:E,O5) -> 14 | Q5: =COUNTIFS(OFÍCIOS!$E:$E,$O5,OFÍCIOS!$G:$G,"APROVADO") -> 13 | R5: =COUNTIFS(OFÍCIOS!$E:$E,$O5,OFÍCIOS!$G:$G,"REPROVADO") -> 1 | S5: =COUNTIFS(OFÍCIOS!$E:$E,$O5,OFÍCIOS!$G:$G,"PENDENCIA") -> 0 | T5: =COUNTIFS(OFÍCIOS!$E:$E,$O5,OFÍCIOS!$G:$G,"") -> 0 | U5: =SUM(Q5:T5) -> 14 | X5: REPROVADOS | Y5: 73 | Z5: 79 | AA5: 28
A6: ABILIO OLIVEIRA SANTOS | B6: 43286003620 | O6: 1350 | P6: =COUNTIF(OFÍCIOS!E:E,O6) -> 79 | Q6: =COUNTIFS(OFÍCIOS!$E:$E,$O6,OFÍCIOS!$G:$G,"APROVADO") -> 75 | R6: =COUNTIFS(OFÍCIOS!$E:$E,$O6,OFÍCIOS!$G:$G,"REPROVADO") -> 3 | S6: =COUNTIFS(OFÍCIOS!$E:$E,$O6,OFÍCIOS!$G:$G,"PENDENCIA") -> 0 | T6: =COUNTIFS(OFÍCIOS!$E:$E,$O6,OFÍCIOS!$G:$G,"") -> 1 | U6: =SUM(Q6:T6) -> 79 | X6: PENDENCIAS | Y6: 36 | Z6: 32 | AA6: 11
A7: ABRAHAO SANTOS SILVA | O7: 1343 | P7: =COUNTIF(OFÍCIOS!E:E,O7) -> 6 | Q7: =COUNTIFS(OFÍCIOS!$E:$E,$O7,OFÍCIOS!$G:$G,"APROVADO") -> 5 | R7: =COUNTIFS(OFÍCIOS!$E:$E,$O7,OFÍCIOS!$G:$G,"REPROVADO") -> 0 | S7: =COUNTIFS(OFÍCIOS!$E:$E,$O7,OFÍCIOS!$G:$G,"PENDENCIA") -> 0 | T7: =COUNTIFS(OFÍCIOS!$E:$E,$O7,OFÍCIOS!$G:$G,"") -> 1 | U7: =SUM(Q7:T7) -> 6 | X7: SS / ANALISE | Y7: 224 | Z7: 275 | AA7: 17
A8: ADAIR DA SILVA BARROS | B8: 97443271620 | E8: 1106 | F8: 42965 | G8: APROVADO | H8: 42978 | O8: 1267 | P8: =COUNTIF(OFÍCIOS!E:E,O8) -> 34 | Q8: =COUNTIFS(OFÍCIOS!$E:$E,$O8,OFÍCIOS!$G:$G,"APROVADO") -> 28 | R8: =COUNTIFS(OFÍCIOS!$E:$E,$O8,OFÍCIOS!$G:$G,"REPROVADO") -> 5 | S8: =COUNTIFS(OFÍCIOS!$E:$E,$O8,OFÍCIOS!$G:$G,"PENDENCIA") -> 1 | T8: =COUNTIFS(OFÍCIOS!$E:$E,$O8,OFÍCIOS!$G:$G,"") -> 0 | U8: =SUM(Q8:T8) -> 34
A9: ADALBERTO CARVALHO DE OLIVEIRA | B9: 98058690597 | E9: 423 | F9: 43182 | G9: APROVADO | O9: 1262 | P9: =COUNTIF(OFÍCIOS!E:E,O9) -> 8 | Q9: =COUNTIFS(OFÍCIOS!$E:$E,$O9,OFÍCIOS!$G:$G,"APROVADO") -> 7 | R9: =COUNTIFS(OFÍCIOS!$E:$E,$O9,OFÍCIOS!$G:$G,"REPROVADO") -> 1 | S9: =COUNTIFS(OFÍCIOS!$E:$E,$O9,OFÍCIOS!$G:$G,"PENDENCIA") -> 0 | T9: =COUNTIFS(OFÍCIOS!$E:$E,$O9,OFÍCIOS!$G:$G,"") -> 0 | U9: =SUM(Q9:T9) -> 8
A10: ADALBERTO CAVALCANTE DOS SANTOS | B10: 38088438888 | O10: 1106 | P10: =COUNTIF(OFÍCIOS!E:E,O10) -> 78 | Q10: =COUNTIFS(OFÍCIOS!$E:$E,$O10,OFÍCIOS!$G:$G,"APROVADO") -> 73 | R10: =COUNTIFS(OFÍCIOS!$E:$E,$O10,OFÍCIOS!$G:$G,"REPROVADO") -> 5 | S10: =COUNTIFS(OFÍCIOS!$E:$E,$O10,OFÍCIOS!$G:$G,"PENDENCIA") -> 0 | T10: =COUNTIFS(OFÍCIOS!$E:$E,$O10,OFÍCIOS!$G:$G,"") -> 0 | U10: =SUM(Q10:T10) -> 78
A11: ADALMA MOREIRA DA ROCHA | B11: 26939799869 | E11: 573 | F11: 43224 | O11: 1128 | P11: =COUNTIF(OFÍCIOS!E:E,O11) -> 92 | Q11: =COUNTIFS(OFÍCIOS!$E:$E,$O11,OFÍCIOS!$G:$G,"APROVADO") -> 91 | R11: =COUNTIFS(OFÍCIOS!$E:$E,$O11,OFÍCIOS!$G:$G,"REPROVADO") -> 1 | S11: =COUNTIFS(OFÍCIOS!$E:$E,$O11,OFÍCIOS!$G:$G,"PENDENCIA") -> 0 | T11: =COUNTIFS(OFÍCIOS!$E:$E,$O11,OFÍCIOS!$G:$G,"") -> 0 | U11: =SUM(Q11:T11) -> 92
A12: ADAMILTON PEREIRA DA SILVA ( ALANA ) | B12: 34470559873 | E12: 292 | F12: 43168 | G12: APROVADO | H12: 43182 | L12: 318 | O12: 1214 | P12: =COUNTIF(OFÍCIOS!E:E,O12) -> 76 | Q12: =COUNTIFS(OFÍCIOS!$E:$E,$O12,OFÍCIOS!$G:$G,"APROVADO") -> 71 | R12: =COUNTIFS(OFÍCIOS!$E:$E,$O12,OFÍCIOS!$G:$G,"REPROVADO") -> 3 | S12: =COUNTIFS(OFÍCIOS!$E:$E,$O12,OFÍCIOS!$G:$G,"PENDENCIA") -> 0 | T12: =COUNTIFS(OFÍCIOS!$E:$E,$O12,OFÍCIOS!$G:$G,"") -> 2 | U12: =SUM(Q12:T12) -> 76
A13: ADAO MENDES AGOSTINHO | B13: 14369564808 | O13: 1241 | P13: =COUNTIF(OFÍCIOS!E:E,O13) -> 33 | Q13: =COUNTIFS(OFÍCIOS!$E:$E,$O13,OFÍCIOS!$G:$G,"APROVADO") -> 32 | R13: =COUNTIFS(OFÍCIOS!$E:$E,$O13,OFÍCIOS!$G:$G,"REPROVADO") -> 0 | S13: =COUNTIFS(OFÍCIOS!$E:$E,$O13,OFÍCIOS!$G:$G,"PENDENCIA") -> 1 | T13: =COUNTIFS(OFÍCIOS!$E:$E,$O13,OFÍCIOS!$G:$G,"") -> 0 | U13: =SUM(Q13:T13) -> 33
A14: ADEGMARIO DOS SANTOS | B14: 39544185844 | E14: 810 | F14: 42915 | G14: APROVADO | H14: 42921 | L14: 568-17 | O14: 1422 | P14: =COUNTIF(OFÍCIOS!E:E,O14) -> 7 | Q14: =COUNTIFS(OFÍCIOS!$E:$E,$O14,OFÍCIOS!$G:$G,"APROVADO") -> 7 | R14: =COUNTIFS(OFÍCIOS!$E:$E,$O14,OFÍCIOS!$G:$G,"REPROVADO") -> 0 | S14: =COUNTIFS(OFÍCIOS!$E:$E,$O14,OFÍCIOS!$G:$G,"PENDENCIA") -> 0 | T14: =COUNTIFS(OFÍCIOS!$E:$E,$O14,OFÍCIOS!$G:$G,"") -> 0 | U14: =SUM(Q14:T14) -> 7
A15: ADEILDA GABRIELA CAITANO SILVA | B15: 38772276860 | C15: LUCIANO MANOEL DA SILVA | D15: 3808243457 | O15: 1439 | P15: =COUNTIF(OFÍCIOS!E:E,O15) -> 16 | Q15: =COUNTIFS(OFÍCIOS!$E:$E,$O15,OFÍCIOS!$G:$G,"APROVADO") -> 14 | R15: =COUNTIFS(OFÍCIOS!$E:$E,$O15,OFÍCIOS!$G:$G,"REPROVADO") -> 1 | S15: =COUNTIFS(OFÍCIOS!$E:$E,$O15,OFÍCIOS!$G:$G,"PENDENCIA") -> 1 | T15: =COUNTIFS(OFÍCIOS!$E:$E,$O15,OFÍCIOS!$G:$G,"") -> 0 | U15: =SUM(Q15:T15) -> 16
A16: ADEILDA RODRIGUES DE OLIVEIRA | B16: 21538837846 | C16: PEDRO LUIZ SANTOS OLIVEIRA | D16: 94203180520 | E16: 810 | F16: 42915 | G16: APROVADO | H16: 42921 | L16: 568-17 | O16: 1451 | P16: =COUNTIF(OFÍCIOS!E:E,O16) -> 4 | Q16: =COUNTIFS(OFÍCIOS!$E:$E,$O16,OFÍCIOS!$G:$G,"APROVADO") -> 3 | R16: =COUNTIFS(OFÍCIOS!$E:$E,$O16,OFÍCIOS!$G:$G,"REPROVADO") -> 1 | S16: =COUNTIFS(OFÍCIOS!$E:$E,$O16,OFÍCIOS!$G:$G,"PENDENCIA") -> 0 | T16: =COUNTIFS(OFÍCIOS!$E:$E,$O16,OFÍCIOS!$G:$G,"") -> 0 | U16: =SUM(Q16:T16) -> 4
A17: ADEILDO ADELINO DE CARVALHO | B17: 57455392591 | O17: 1470 | P17: =COUNTIF(OFÍCIOS!E:E,O17) -> 4 | Q17: =COUNTIFS(OFÍCIOS!$E:$E,$O17,OFÍCIOS!$G:$G,"APROVADO") -> 4 | R17: =COUNTIFS(OFÍCIOS!$E:$E,$O17,OFÍCIOS!$G:$G,"REPROVADO") -> 0 | S17: =COUNTIFS(OFÍCIOS!$E:$E,$O17,OFÍCIOS!$G:$G,"PENDENCIA") -> 0 | T17: =COUNTIFS(OFÍCIOS!$E:$E,$O17,OFÍCIOS!$G:$G,"") -> 0 | U17: =SUM(Q17:T17) -> 4
A18: ADELCIDES DA CONCEICAO ALMEIDA | B18: 5304941594 | E18: 1106 | F18: 42965 | G18: APROVADO | H18: 42978 | O18: 1489 | P18: =COUNTIF(OFÍCIOS!E:E,O18) -> 35 | Q18: =COUNTIFS(OFÍCIOS!$E:$E,$O18,OFÍCIOS!$G:$G,"APROVADO") -> 34 | R18: =COUNTIFS(OFÍCIOS!$E:$E,$O18,OFÍCIOS!$G:$G,"REPROVADO") -> 0 | S18: =COUNTIFS(OFÍCIOS!$E:$E,$O18,OFÍCIOS!$G:$G,"PENDENCIA") -> 1 | T18: =COUNTIFS(OFÍCIOS!$E:$E,$O18,OFÍCIOS!$G:$G,"") -> 0 | U18: =SUM(Q18:T18) -> 35
A19: ADELIA MARIA DE OLIVEIRA | B19: 21600057896 | E19: 262 | F19: 43160 | G19: REPROVADO | H19: 43164 | L19: 255 | O19: 1555 | P19: =COUNTIF(OFÍCIOS!E:E,O19) -> 25 | Q19: =COUNTIFS(OFÍCIOS!$E:$E,$O19,OFÍCIOS!$G:$G,"APROVADO") -> 22 | R19: =COUNTIFS(OFÍCIOS!$E:$E,$O19,OFÍCIOS!$G:$G,"REPROVADO") -> 1 | S19: =COUNTIFS(OFÍCIOS!$E:$E,$O19,OFÍCIOS!$G:$G,"PENDENCIA") -> 2 | T19: =COUNTIFS(OFÍCIOS!$E:$E,$O19,OFÍCIOS!$G:$G,"") -> 0 | U19: =SUM(Q19:T19) -> 25
A20: ADEMARIO FERREIRA DOS SANTOS | B20: 18419589802 | O20: 1570 | P20: =COUNTIF(OFÍCIOS!E:E,O20) -> 24 | Q20: =COUNTIFS(OFÍCIOS!$E:$E,$O20,OFÍCIOS!$G:$G,"APROVADO") -> 23 | R20: =COUNTIFS(OFÍCIOS!$E:$E,$O20,OFÍCIOS!$G:$G,"REPROVADO") -> 1 | S20: =COUNTIFS(OFÍCIOS!$E:$E,$O20,OFÍCIOS!$G:$G,"PENDENCIA") -> 0 | T20: =COUNTIFS(OFÍCIOS!$E:$E,$O20,OFÍCIOS!$G:$G,"") -> 0 | U20: =SUM(Q20:T20) -> 24
A21: ADEMIR DA SILVA LIMA | B21: 15538537846 | E21: 573 | F21: 43224 | O21: 1752 | P21: =COUNTIF(OFÍCIOS!E:E,O21) -> 89 | Q21: =COUNTIFS(OFÍCIOS!$E:$E,$O21,OFÍCIOS!$G:$G,"APROVADO") -> 80 | R21: =COUNTIFS(OFÍCIOS!$E:$E,$O21,OFÍCIOS!$G:$G,"REPROVADO") -> 2 | S21: =COUNTIFS(OFÍCIOS!$E:$E,$O21,OFÍCIOS!$G:$G,"PENDENCIA") -> 5 | T21: =COUNTIFS(OFÍCIOS!$E:$E,$O21,OFÍCIOS!$G:$G,"") -> 2 | U21: =SUM(Q21:T21) -> 89
A22: ADENILDE SANTOS DA SILVA | B22: 899837506 | E22: 1824 | F22: 43091 | G22: APROVADO | H22: 43097 | L22: 1828 | O22: 1824 | P22: =COUNTIF(OFÍCIOS!E:E,O22) -> 81 | Q22: =COUNTIFS(OFÍCIOS!$E:$E,$O22,OFÍCIOS!$G:$G,"APROVADO") -> 67 | R22: =COUNTIFS(OFÍCIOS!$E:$E,$O22,OFÍCIOS!$G:$G,"REPROVADO") -> 7 | S22: =COUNTIFS(OFÍCIOS!$E:$E,$O22,OFÍCIOS!$G:$G,"PENDENCIA") -> 6 | T22: =COUNTIFS(OFÍCIOS!$E:$E,$O22,OFÍCIOS!$G:$G,"") -> 1 | U22: =SUM(Q22:T22) -> 81
A23: ADENILSON DA CONCEICAO | B23: 36197160803 | E23: 229 | F23: 43151 | G23: APROVADO | L23: 232 | O23: 1628 | P23: =COUNTIF(OFÍCIOS!E:E,O23) -> 6 | Q23: =COUNTIFS(OFÍCIOS!$E:$E,$O23,OFÍCIOS!$G:$G,"APROVADO") -> 5 | R23: =COUNTIFS(OFÍCIOS!$E:$E,$O23,OFÍCIOS!$G:$G,"REPROVADO") -> 1 | S23: =COUNTIFS(OFÍCIOS!$E:$E,$O23,OFÍCIOS!$G:$G,"PENDENCIA") -> 0 | T23: =COUNTIFS(OFÍCIOS!$E:$E,$O23,OFÍCIOS!$G:$G,"") -> 0 | U23: =SUM(Q23:T23) -> 6
A24: ADENIR MODESTO RIBEIRO | B24: 39248826814 | E24: 292 | F24: 43168 | G24: APROVADO | H24: 43182 | L24: 318 | O24: 608 | P24: =COUNTIF(OFÍCIOS!E:E,O24) -> 35 | Q24: =COUNTIFS(OFÍCIOS!$E:$E,$O24,OFÍCIOS!$G:$G,"APROVADO") -> 31 | R24: =COUNTIFS(OFÍCIOS!$E:$E,$O24,OFÍCIOS!$G:$G,"REPROVADO") -> 3 | S24: =COUNTIFS(OFÍCIOS!$E:$E,$O24,OFÍCIOS!$G:$G,"PENDENCIA") -> 1 | T24: =COUNTIFS(OFÍCIOS!$E:$E,$O24,OFÍCIOS!$G:$G,"") -> 0 | U24: =SUM(Q24:T24) -> 35
A25: ADILINA FARIAS DO NASCIMENTO | B25: 48925276534 | E25: 229 | F25: 43151 | L25: 232 | O25: 527 | P25: =COUNTIF(OFÍCIOS!E:E,O25) -> 29 | Q25: =COUNTIFS(OFÍCIOS!$E:$E,$O25,OFÍCIOS!$G:$G,"APROVADO") -> 0 | R25: =COUNTIFS(OFÍCIOS!$E:$E,$O25,OFÍCIOS!$G:$G,"REPROVADO") -> 0 | S25: =COUNTIFS(OFÍCIOS!$E:$E,$O25,OFÍCIOS!$G:$G,"PENDENCIA") -> 0 | T25: =COUNTIFS(OFÍCIOS!$E:$E,$O25,OFÍCIOS!$G:$G,"") -> 29 | U25: =SUM(Q25:T25) -> 29
A26: ADILSON SOARES DA COSTA | O26: 509 | P26: =COUNTIF(OFÍCIOS!E:E,O26) -> 14 | Q26: =COUNTIFS(OFÍCIOS!$E:$E,$O26,OFÍCIOS!$G:$G,"APROVADO") -> 0 | R26: =COUNTIFS(OFÍCIOS!$E:$E,$O26,OFÍCIOS!$G:$G,"REPROVADO") -> 0 | S26: =COUNTIFS(OFÍCIOS!$E:$E,$O26,OFÍCIOS!$G:$G,"PENDENCIA") -> 0 | T26: =COUNTIFS(OFÍCIOS!$E:$E,$O26,OFÍCIOS!$G:$G,"") -> 14 | U26: =SUM(Q26:T26) -> 14
A27: ADMEIA BARBOSA DE SOUZA | B27: 25894152810 | C27: REINALDO SANTOS REIS | D27: 8263008808 | E27: 292 | F27: 43168 | G27: APROVADO | H27: 43182 | L27: 318 | O27: 292 | P27: =COUNTIF(OFÍCIOS!E:E,O27) -> 233 | Q27: =COUNTIFS(OFÍCIOS!$E:$E,$O27,OFÍCIOS!$G:$G,"APROVADO") -> 212 | R27: =COUNTIFS(OFÍCIOS!$E:$E,$O27,OFÍCIOS!$G:$G,"REPROVADO") -> 9 | S27: =COUNTIFS(OFÍCIOS!$E:$E,$O27,OFÍCIOS!$G:$G,"PENDENCIA") -> 0 | T27: =COUNTIFS(OFÍCIOS!$E:$E,$O27,OFÍCIOS!$G:$G,"") -> 12 | U27: =SUM(Q27:T27) -> 233
A28: ADONES FERREIRA JORGE | B28: 43026389587 | C28: EUNICE FELICIANA BRITO JORGE | D28: 29124464813 | E28: 485 | F28: 43196 | H28: 43206 | L28: 483 | O28: 573 | P28: =COUNTIF(OFÍCIOS!E:E,O28) -> 43 | Q28: =COUNTIFS(OFÍCIOS!$E:$E,$O28,OFÍCIOS!$G:$G,"APROVADO") -> 0 | R28: =COUNTIFS(OFÍCIOS!$E:$E,$O28,OFÍCIOS!$G:$G,"REPROVADO") -> 0 | S28: =COUNTIFS(OFÍCIOS!$E:$E,$O28,OFÍCIOS!$G:$G,"PENDENCIA") -> 0 | T28: =COUNTIFS(OFÍCIOS!$E:$E,$O28,OFÍCIOS!$G:$G,"") -> 43 | U28: =SUM(Q28:T28) -> 43
A29: ADRIANA ALVES DA SILVA | B29: 26245112885 | E29: 262 | F29: 43160 | G29: REPROVADO | H29: 43164 | L29: 255 | O29: 563 | P29: =COUNTIF(OFÍCIOS!E:E,O29) -> 64 | Q29: =COUNTIFS(OFÍCIOS!$E:$E,$O29,OFÍCIOS!$G:$G,"APROVADO") -> 0 | R29: =COUNTIFS(OFÍCIOS!$E:$E,$O29,OFÍCIOS!$G:$G,"REPROVADO") -> 0 | S29: =COUNTIFS(OFÍCIOS!$E:$E,$O29,OFÍCIOS!$G:$G,"PENDENCIA") -> 0 | T29: =COUNTIFS(OFÍCIOS!$E:$E,$O29,OFÍCIOS!$G:$G,"") -> 64 | U29: =SUM(Q29:T29) -> 64
A30: ADRIANA ALVES FERREIRA | B30: 36531080809 | C30: MARCIO ROSA DE MIRA | D30: 22485483892 | E30: 1489 | F30: 43038 | G30: APROVADO | L30: 1647-17 | O30: 443 | P30: =COUNTIF(OFÍCIOS!E:E,O30) -> 66 | Q30: =COUNTIFS(OFÍCIOS!$E:$E,$O30,OFÍCIOS!$G:$G,"APROVADO") -> 0 | R30: =COUNTIFS(OFÍCIOS!$E:$E,$O30,OFÍCIOS!$G:$G,"REPROVADO") -> 0 | S30: =COUNTIFS(OFÍCIOS!$E:$E,$O30,OFÍCIOS!$G:$G,"PENDENCIA") -> 0 | T30: =COUNTIFS(OFÍCIOS!$E:$E,$O30,OFÍCIOS!$G:$G,"") -> 66 | U30: =SUM(Q30:T30) -> 66
A31: ADRIANA APARECIDA ROBERTO | B31: 28147186819 | C31: CARLOS ANTONIO BATISTA DOS SANTOS | D31: 24499714400 | O31: 423 | P31: =COUNTIF(OFÍCIOS!E:E,O31) -> 9 | Q31: =COUNTIFS(OFÍCIOS!$E:$E,$O31,OFÍCIOS!$G:$G,"APROVADO") -> 7 | R31: =COUNTIFS(OFÍCIOS!$E:$E,$O31,OFÍCIOS!$G:$G,"REPROVADO") -> 1 | S31: =COUNTIFS(OFÍCIOS!$E:$E,$O31,OFÍCIOS!$G:$G,"PENDENCIA") -> 0 | T31: =COUNTIFS(OFÍCIOS!$E:$E,$O31,OFÍCIOS!$G:$G,"") -> 1 | U31: =SUM(Q31:T31) -> 9
A32: ADRIANA ARAUJO DE LIMA | B32: 37559228860 | C32: ALEXANDRO ARAUJO DE LIMA | D32: 28072024892 | E32: 1555 | F32: 43049 | G32: APROVADO | O32: 229 | P32: =COUNTIF(OFÍCIOS!E:E,O32) -> 89 | Q32: =COUNTIFS(OFÍCIOS!$E:$E,$O32,OFÍCIOS!$G:$G,"APROVADO") -> 81 | R32: =COUNTIFS(OFÍCIOS!$E:$E,$O32,OFÍCIOS!$G:$G,"REPROVADO") -> 2 | S32: =COUNTIFS(OFÍCIOS!$E:$E,$O32,OFÍCIOS!$G:$G,"PENDENCIA") -> 5 | T32: =COUNTIFS(OFÍCIOS!$E:$E,$O32,OFÍCIOS!$G:$G,"") -> 1 | U32: =SUM(Q32:T32) -> 89
A33: ADRIANA CORDEIRO MACHADO | B33: 23635229822 | C33: ANDERSON DE MORAIS SANTOS | D33: 21668057875 | E33: 262 | F33: 43160 | G33: APROVADO | H33: 43164 | L33: 255 | O33: 262 | P33: =COUNTIF(OFÍCIOS!E:E,O33) -> 224 | Q33: =COUNTIFS(OFÍCIOS!$E:$E,$O33,OFÍCIOS!$G:$G,"APROVADO") -> 181 | R33: =COUNTIFS(OFÍCIOS!$E:$E,$O33,OFÍCIOS!$G:$G,"REPROVADO") -> 15 | S33: =COUNTIFS(OFÍCIOS!$E:$E,$O33,OFÍCIOS!$G:$G,"PENDENCIA") -> 0 | T33: =COUNTIFS(OFÍCIOS!$E:$E,$O33,OFÍCIOS!$G:$G,"") -> 28 | U33: =SUM(Q33:T33) -> 224
A34: ADRIANA DA SILVA | O34: 117 | P34: =COUNTIF(OFÍCIOS!E:E,O34) -> 91 | Q34: =COUNTIFS(OFÍCIOS!$E:$E,$O34,OFÍCIOS!$G:$G,"APROVADO") -> 77 | R34: =COUNTIFS(OFÍCIOS!$E:$E,$O34,OFÍCIOS!$G:$G,"REPROVADO") -> 7 | S34: =COUNTIFS(OFÍCIOS!$E:$E,$O34,OFÍCIOS!$G:$G,"PENDENCIA") -> 5 | T34: =COUNTIFS(OFÍCIOS!$E:$E,$O34,OFÍCIOS!$G:$G,"") -> 2 | U34: =SUM(Q34:T34) -> 91
A35: ADRIANA DA SILVA SANTOS | B35: 40902634844 | C35: GUILHERME DE OLIVEIRA SOUZA | D35: 23795007895 | E35: 117 | F35: 43117 | G35: APROVADO | H35: 43151 | L35: 118-18 | O35: 485 | P35: =COUNTIF(OFÍCIOS!E:E,O35) -> 23 | Q35: =COUNTIFS(OFÍCIOS!$E:$E,$O35,OFÍCIOS!$G:$G,"APROVADO") -> 0 | R35: =COUNTIFS(OFÍCIOS!$E:$E,$O35,OFÍCIOS!$G:$G,"REPROVADO") -> 3 | S35: =COUNTIFS(OFÍCIOS!$E:$E,$O35,OFÍCIOS!$G:$G,"PENDENCIA") -> 0 | T35: =COUNTIFS(OFÍCIOS!$E:$E,$O35,OFÍCIOS!$G:$G,"") -> 20 | U35: =SUM(Q35:T35) -> 23
A36: ADRIANA DE SA ROCHA | B36: 39615629898 | C36: MARCELO FERNANDES LIMA | D36: 43328275894 | E36: 423 | F36: 43182 | G36: APROVADO | O36: 85 | P36: =COUNTIF(OFÍCIOS!E:E,O36) -> 93 | Q36: =COUNTIFS(OFÍCIOS!$E:$E,$O36,OFÍCIOS!$G:$G,"APROVADO") -> 86 | R36: =COUNTIFS(OFÍCIOS!$E:$E,$O36,OFÍCIOS!$G:$G,"REPROVADO") -> 4 | S36: =COUNTIFS(OFÍCIOS!$E:$E,$O36,OFÍCIOS!$G:$G,"PENDENCIA") -> 3 | T36: =COUNTIFS(OFÍCIOS!$E:$E,$O36,OFÍCIOS!$G:$G,"") -> 0 | U36: =SUM(Q36:T36) -> 93
A37: ADRIANA DOS SANTOS | P37: =COUNTIF(OFÍCIOS!E:E,O37) -> 0 | Q37: =COUNTIFS(OFÍCIOS!$E:$E,$O37,OFÍCIOS!$G:$G,"APROVADO") -> 0 | R37: =COUNTIFS(OFÍCIOS!$E:$E,$O37,OFÍCIOS!$G:$G,"REPROVADO") -> 0 | S37: =COUNTIFS(OFÍCIOS!$E:$E,$O37,OFÍCIOS!$G:$G,"PENDENCIA") -> 0 | T37: =COUNTIFS(OFÍCIOS!$E:$E,$O37,OFÍCIOS!$G:$G,"") -> 0 | U37: =SUM(Q37:T37) -> 0
A38: ADRIANA FERREIRA DA SILVA | C38: LOURIVAL CANDIDO SILVA | P38: =COUNTIF(OFÍCIOS!E:E,O38) -> 0 | Q38: =COUNTIFS(OFÍCIOS!$E:$E,$O38,OFÍCIOS!$G:$G,"APROVADO") -> 0 | R38: =COUNTIFS(OFÍCIOS!$E:$E,$O38,OFÍCIOS!$G:$G,"REPROVADO") -> 0 | S38: =COUNTIFS(OFÍCIOS!$E:$E,$O38,OFÍCIOS!$G:$G,"PENDENCIA") -> 0 | T38: =COUNTIFS(OFÍCIOS!$E:$E,$O38,OFÍCIOS!$G:$G,"") -> 0 | U38: =SUM(Q38:T38) -> 0
A39: ADRIANA HELENA DE MORAIS | B39: 14268808809 | E39: 262 | F39: 43160 | G39: APROVADO | H39: 43164 | L39: 255 | P39: =COUNTIF(OFÍCIOS!E:E,O39) -> 0 | Q39: =COUNTIFS(OFÍCIOS!$E:$E,$O39,OFÍCIOS!$G:$G,"APROVADO") -> 0 | R39: =COUNTIFS(OFÍCIOS!$E:$E,$O39,OFÍCIOS!$G:$G,"REPROVADO") -> 0 | S39: =COUNTIFS(OFÍCIOS!$E:$E,$O39,OFÍCIOS!$G:$G,"PENDENCIA") -> 0 | T39: =COUNTIFS(OFÍCIOS!$E:$E,$O39,OFÍCIOS!$G:$G,"") -> 0 | U39: =SUM(Q39:T39) -> 0
A40: ADRIANA JESUS DA CUNHA | B40: 29628693867 | E40: 292 | F40: 43168 | G40: APROVADO | H40: 43182 | L40: 318 | P40: =COUNTIF(OFÍCIOS!E:E,O40) -> 0 | Q40: =COUNTIFS(OFÍCIOS!$E:$E,$O40,OFÍCIOS!$G:$G,"APROVADO") -> 0 | R40: =COUNTIFS(OFÍCIOS!$E:$E,$O40,OFÍCIOS!$G:$G,"REPROVADO") -> 0 | S40: =COUNTIFS(OFÍCIOS!$E:$E,$O40,OFÍCIOS!$G:$G,"PENDENCIA") -> 0 | T40: =COUNTIFS(OFÍCIOS!$E:$E,$O40,OFÍCIOS!$G:$G,"") -> 0 | U40: =SUM(Q40:T40) -> 0
A41: ADRIANA LINO PEIXOTO | B41: 35762862844 | E41: 1106 | F41: 42965 | G41: APROVADO | H41: 42978 | P41: =COUNTIF(OFÍCIOS!E:E,O41) -> 0 | Q41: =COUNTIFS(OFÍCIOS!$E:$E,$O41,OFÍCIOS!$G:$G,"APROVADO") -> 0 | R41: =COUNTIFS(OFÍCIOS!$E:$E,$O41,OFÍCIOS!$G:$G,"REPROVADO") -> 0 | S41: =COUNTIFS(OFÍCIOS!$E:$E,$O41,OFÍCIOS!$G:$G,"PENDENCIA") -> 0 | T41: =COUNTIFS(OFÍCIOS!$E:$E,$O41,OFÍCIOS!$G:$G,"") -> 0 | U41: =SUM(Q41:T41) -> 0
A42: ADRIANA MARIA ALVES XAVIER (ALTERACAO DE NOME ADRIANA MARIA ALVES DOS SANTOS) | B42: 10201704412 | C42: CLAUDIO XAVIER SANTANA | D42: 33674895811 | E42: 262 | F42: 43160 | G42: APROVADO | H42: 43164 | L42: 255 | O42: TOTAIS | P42: =SUM(P3:P36) -> 1922 | Q42: =SUM(Q3:Q36) -> 1514 | R42: =SUM(R3:R36) -> 83 | S42: =SUM(S3:S36) -> 36 | T42: =SUM(T3:T36) -> 289 | U42: =SUM(U3:U36) -> 1922
A43: ADRIANA MEDEIROS DE OLIVEIRA SANTOS | B43: 35271487873 | C43: CLEITON SOUSA SANTOS | D43: 557351502 | E43: 1128 | F43: 42972 | G43: APROVADO | H43: 42979
A44: ADRIANA PEREIRA DE JESUS | B44: 22360217801 | E44: 1128 | F44: 42972 | G44: APROVADO | H44: 42979
A45: ADRIANA PINHEIRO MOREIRA | B45: 36930783862 | E45: 443 | F45: 43188 | H45: 43192
A46: ADRIANA PONCIANO DA SILVA | B46: 36647299866 | E46: 292 | F46: 43168 | G46: APROVADO | H46: 43182 | L46: 318
A47: ADRIANA PORTE | B47: 31801479895 | C47: ISAQUE PINTO DA SILVA | D47: 23103908873
A48: ADRIANA ROBERTA SILVA ANDRADE | B48: 28638653824 | C48: JOSE ROMILDO SILVA ANDRADE | D48: 50160249520
A49: ADRIANA ROQUE DOS SANTOS | B49: 17766101807 | C49: MARCOS ELIAS DOS SANTOS | D49: 31993041842 | E49: 1824 | F49: 43091 | G49: APROVADO | H49: 43097 | L49: 1828
A50: ADRIANA SABINO NOGUEIRA | B50: 17902799840 | C50: JOYCE CRISTINA NOGUEIRA DO CARMO | D50: 44230035896
A51: ADRIANA SANTANA SANTOS | B51: 49122403892 | C51: ETVALDO BERTO DA SILVA | D51: 1478139560 | E51: 608 | F51: 43012 | G51: APROVADO | H51: 43024 | O51: OFÍCIO DE REANÁLISE 019/18 - 05/06/18
A52: ADRIANA SANTOS RIBEIRO | B52: 37534302854 | C52: EDLANDIO BISPO SILVA | D52: 1689246502
A53: ADRIANA SEVERINO SANTANA | B53: 14699996841 | C53: FERNANDO FERREIRA SILVA | D53: 15089706883 | E53: 1128 | F53: 42972 | G53: APROVADO | H53: 42979
A54: ADRIANA TENORIO DA SILVA | B54: 47077408809
A55: ADRIANE MOREIRA DOS SANTOS | B55: 40396239838 | C55: JEFERSON DA SILVA DE JESUS | D55: 39420747883 | E55: 262 | F55: 43160 | G55: APROVADO | H55: 43164 | L55: 255
A56: ADRIANO ALVES BARBOSA | B56: 41333062877 | E56: 292 | F56: 43168 | G56: APROVADO | H56: 43182 | L56: 318
A57: ADRIANO HENRIQUE DA COSTA | B57: 38781151802
A58: ADRIANO PEREIRA DOS SANTOS
A59: ADRIELLE DOS PASSOS DE SOUZA | B59: 2428277219 | C59: DIVANILDO SOUZA DOS PASSOS | D59: 909805229 | E59: 810 | F59: 42915 | G59: APROVADO | H59: 42921 | L59: 568-17
A60: AGDA APARECIDA PEREIRA | B60: 16417464830
A61: AGNALDO ALTMANN | B61: 7104481800 | E61: 262 | F61: 43160 | G61: APROVADO | H61: 43164 | L61: 255
A62: AGNALDO LOPES GONCALVES FILHO | B62: 25023266800
A63: AGOSTINHO FERNANDES SILVA | B63: 3722493889 | C63: FRANCISCA GOMES DE OLIVEIRA | D63: 32416642871
A64: AIDEE MARIA DOS SANTOS | B64: 14519340845 | C64: SIORLANDIO DOS SANTOS FALCAO | D64: 88489795568 | E64: 262 | F64: 43160 | H64: 43164 | L64: 255
A65: AILTON WILLIAN MELLO | B65: 19266484806
A66: ALADIM PINHEIRO DOS SANTOS | B66: 15322188851
A67: ALAILTON COSTA DE SOUZA | B67: 36392955879 | C67: AMANDA CRISTINA SILVEIRA DA SILVA | D67: 5242864346 | E67: 117 | F67: 43117 | G67: APROVADO | H67: 43151 | L67: 118-18
A68: ALAN DE JESUS PASSOS | B68: 41482647800 | E68: 1262 | F68: 42997 | G68: APROVADO | H68: 43000
A69: ALBERT PEREIRA DOS SANTOS | B69: 47629183852
A70: ALBERTINA CANDIDO RIBEIRO GOMES | B70: 9882942490 | C70: DENIS JOSE GOMES | D70: 9704111460
A71: ALBERTINA PEREIRA COSTA | B71: 14777572870 | C71: EDIVALDO ALVES DE SOUZA | D71: 12874739898 | E71: 1824 | F71: 43091 | G71: APROVADO | H71: 43097 | L71: 1828
A72: ALCIDINEY DA SILVA | B72: 31996709895
A73: ALCILENE GUEDES DA SILVA | B73: 26824046850 | E73: 1824 | F73: 43091 | G73: APROVADO | H73: 43097 | L73: 1828
A74: ALCIONE BARBOSA DE SOUSA | B74: 3523524342 | E74: 85 | F74: 43109 | G74: APROVADO | H74: 43151
A75: ALDA DE JESUS GONCALVES | B75: 26940268855 | C75: JUCELINO ALVES DE LIMA
A76: ALDA MARIA DE JESUS | B76: 24828498885 | E76: 1489 | F76: 43038 | G76: APROVADO | L76: 1647-17
A77: ALDA REJANE SANTOS | B77: 11482307855 | E77: 85 | F77: 43109 | G77: APROVADO | H77: 43151
A78: ALDERLANDIA DE OLIVEIRA MONTEIRO | B78: 42352732808 | C78: JOSE SOARES DA SILVA | D78: 281893373 | E78: 1214 | F78: 42989 | G78: APROVADO | H78: 43000
A79: ALESILVIA RAIMUNDO DA SILVA NEVES | B79: 13480043801 | C79: CLAUDIO RIBEIRO NEVES | D79: 67141536604
A80: ALESSANDRA APARECIDA DE JESUS | B80: 31874522804 | E80: 292 | F80: 43168 | G80: APROVADO | H80: 43182 | L80: 318
A81: ALESSANDRA CABRAL DA SILVA | B81: 28889575824 | E81: 1241 | F81: 42992 | G81: APROVADO | H81: 42998
A82: ALESSANDRA JUVINA DA SILVA | B82: 21734589817 | E82: 229 | F82: 43151 | G82: APROVADO | L82: 232
A83: ALESSANDRA LIMA DA SILVA
A84: ALESSANDRA LUNA DA SILVA | B84: 18475875858
A85: ALESSANDRA MARQUES DOS SANTOS | B85: 40443882886 | E85: 509 | F85: 43203 | H85: 43213
A86: ALESSANDRA MARTINS DA SILVA | B86: 43053250802 | C86: IUDARLAN MARTINS DA SILVA | D86: 35893147880 | E86: 1128 | F86: 42972 | G86: APROVADO
A87: ALESSANDRA MILAGRES PIROTTI | B87: 28255807837 | E87: 292 | F87: 43168 | G87: APROVADO | L87: 318
A88: ALESSANDRA MONTEIRO DA SILVA | B88: 33617584837 | C88: ASTROGILDO APARECIDO CURY DE ARAUJO | D88: 26520094862 | E88: 608 | F88: 43012 | G88: APROVADO
A89: ALESSANDRA QUARESMA DA SILVA | B89: 38168161858 | C89: WALLACE DIEGO HENRIQUE BISPO | D89: 24059422835
A90: ALESSANDRO ARAUJO DA SILVA COSTA | B90: 38728353862 | C90: LIZIANE ROCHA DA SILVA COSTA | D90: 37650358828 | E90: 1417 | F90: 43017 | G90: APROVADO | L90: 1017-17
A91: ALEX DE JESUS PEREIRA | B91: 29479419858 | C91: JOILMA DE JESUS FERREIRA | D91: 71909656534
A92: ALEX JOSE CATARINO ASSUNCAO | B92: 37634689866 | E92: 443 | F92: 43188
A93: ALEXANDRA APARECIDA DA SILVA BARBOZA | B93: 22656606802 | E93: 1555 | F93: 43049 | G93: APROVADO
A94: ALEXANDRA SANTOS DE PAULA | B94: 4248144638 | E94: 229 | F94: 43151 | G94: APROVADO | L94: 232
A95: ALEXANDRE OLIVEIRA SILVA | B95: 29998933889
A96: ALEXANDRE SATELES DOS SANTOS | B96: 2963904533 | E96: 1489 | F96: 43038 | G96: APROVADO | L96: 1647-17
A97: ALEXANDRE VALENTIN DE SOUZA | B97: 23256005802 | E97: 1350 | F97: 43006 | G97: APROVADO
A98: ALEXSANDRA BORGES GONCALVES | B98: 3317260505 | C98: GILDECI FERREIRA CORDEIRO | D98: 92396607634
A99: ALEXSANDRA FRANCA DA SILVA | B99: 36234875890 | E99: 1128 | F99: 42972 | G99: APROVADO
A100: ALEXSANDRA MARIA DA SILVA | B100: 1243618469 | E100: 262 | F100: 43160 | G100: APROVADO | H100: 43164 | L100: 255
...

Sheet EMAIL
E2: PUBLICAÇÃO DOC
E3: PREVISÃO PAGAMENTO | F3: 024/0030/B | H3: 029/0024/C
A4: ÁREA | B4: SELO | C4: TITULAR | D4: CONFIRMAÇÃO PAGAMENTO | E4: CONFIRMAÇÃO PAGAMENTO | F4: 024/0041/A | H4: 029/0023/E
A5: VIOLÃO III | B5: 0010007A | C5: ROBERT DA SILVA BAPTISTA | D5: 46260 | F5: 024/0051/A | H5: 024/0057/A
F6: 024/0079/C | H6: 031/0020/C
F7: 024/0088/B | H7: 029/0069/D
F8: 024/0099/A | H8: 031/0033/K
F9: 029/0007/B | H9: 031/0039/C
F10: 029/0023/E | H10: 029/0035/B
F11: 029/0024/C | H11: 029/0027/A
F12: 029/0027/A | H12: 029/0064/A
F13: 029/0035/B | H13: 029/0069/B
F14: 029/0036/F | H14: 031/0028/D
F15: 029/0039/B | H15: 029/0067/A
F16: 029/0045/A | H16: 029/0007/A
F17: 029/0061/A | H17: 029/0070/C
F18: 029/0064/A | H18: 029/0007/B
A19: JD DA PAZ | B19: 013/0126/A | C19: CLAUDIA MARIA RUFINO DA SILVA | D19: 45384 | F19: 029/0064/F | H19: 029/0070/B
A20: JD DA PAZ | B20: 013/0126/C | C20: MIRIAN AMARO SILVA | D20: 45384 | F20: 029/0066/A | H20: 029/0045/A
A21: JD DA PAZ | B21: 013/0133/A | C21: JOSÉ CICERO DA SILVA | D21: 45384 | F21: 029/0066/B | H21: 024/0102/D
F22: 029/0066/E | H22: 024/0041/A
F23: 029/0067/A | H23: 031/0035/A
F24: 029/0067/F | H24: 031/0067/B
F25: 029/0069/B | H25: 024/0077/B
F26: 029/0069/C | H26: 033/0016/C
A27: PARAISÓPOLIS/ANTONICO | B27: 029/0035/C | C27: GLAUCIA APARECIDA FIDELIX DA SILVA | D27: 45247 | F27: 029/0069/D | H27: 029/0069/C
A28: PARAISÓPOLIS/ANTONICO | B28: 031/0020/C | C28: NATALINA MATIAS ALMEIDA DE SOUZA | D28: 45247 | F28: 029/0070/B | H28: 029/0061/A
A29: PARAISÓPOLIS/ANTONICO | B29: 031/0033/Q | C29: LEANDRO PEREIRA DE OLIVEIRA | D29: 45247 | F29: 029/0070/C | H29: 029/0066/B
A30: PARAISÓPOLIS/ANTONICO | B30: 031/0034/I | C30: APARECIDA RIBEIRO DA CRUZ | D30: 45247 | F30: 029/0071/B | H30: 029/0071/D
A31: PARAISÓPOLIS/ANTONICO | B31: 031/0034/J | C31: ELIAS GABRIEL SANTANA DE BRITO | D31: 45244 | F31: 029/0071/D | H31: 031/0058/A
A32: PARAISÓPOLIS/ANTONICO | B32: 031/0040/C | C32: FABIANA APARECIDA FRANCISCO | D32: 45243 | F32: 029/0071/E | H32: 029/0036/F
A33: PARAISÓPOLIS/ANTONICO | B33: 031/0076/B | C33: LUCIENE FERREIRA DA SILVA | D33: 45243 | F33: 029/0080/E | H33: 031/0067/A
A34: PARAISÓPOLIS/ANTONICO | B34: 031/0076/C | C34: ADILSON DE ASSIS GOMES | D34: 45243 | F34: 029/0081/A | H34: 031/0028/L
A35: PARAISÓPOLIS/ANTONICO | B35: 031/0076/D | C35: VIVALDO JOSÉ DE SANTANA FILHO | D35: 45243 | F35: 029/0083/A | H35: 024/0105/A
F36: 029/0085/G | H36: 029/0064/F
F37: 029/0086/B | H37: 031/0025/A
F38: 031/0004/C | H38: 024/0051/A
F39: 031/0014/A | H39: 024/0030/B
F40: 031/0015/D | H40: 029/0083/A
F41: 031/0020/B | H41: 031/0004/C
F42: 031/0020/C | H42: 031/0014/A
A43: PARAISÓPOLIS/ANTONICO | B43: 031/0034/J | C43: ELIAS GABRIEL SANTANA DE BRITO | D43: 45224 | F43: 031/0022/B | H43: 033/0029/B
A44: PARAISÓPOLIS/ANTONICO | B44: 031/0040/C | C44: FABIANA APARECIDA FRANCISCO | D44: 45224 | F44: 031/0022/E | H44: 029/0071/E
A45: PARAISÓPOLIS/ANTONICO | B45: 031/0076/B | C45: LUCIENE FERREIRA DA SILVA | D45: 45224 | F45: 031/0025/A | H45: 031/0033/E
A46: PARAISÓPOLIS/ANTONICO | B46: 031/0076/C | C46: ADILSON DE ASSIS GOMES | D46: 45224 | F46: 031/0028/D | H46: 024/0070/E
A47: PARAISÓPOLIS/ANTONICO | B47: 031/0076/D | C47: VIVALDO JOSÉ DE SANTANA FILHO | D47: 45224 | F47: 031/0028/L | H47: 024/0079/C
F48: 031/0031/B | H48: 031/0015/D
F49: 031/0033/E | H49: 033/0030/A
F50: 031/0033/K | H50: 024/0041/B
F51: 031/0033/Q | H51: 031/0020/B
F52: 031/0035/A | H52: 031/0035/B
F53: 031/0035/B | H53: 029/0085/G
F54: 031/0039/C | H54: 031/0022/B
F55: 031/0058/A | H55: 029/0067/F
F56: 031/0067/A | H56: 024/0088/B
F57: 031/0067/B | H57: 029/0039/B
F58: 033/0016/C
F59: 033/0029/B
F60: 033/0030/A
A63: PARAISÓPOLIS/ANTONICO | B63: 027/0014/H | C63: GERILZA BRITO CAVALCANTE | D63: 45224
A64: PARAISÓPOLIS/ANTONICO | B64: 027/0016/B | C64: LOURISMAR LIMA BRAGA | D64: 45224
A65: PARAISÓPOLIS/ANTONICO | B65: 027/0016/C | C65: HUGO DA SILVA | D65: 45224
A66: PARAISÓPOLIS/ANTONICO | B66: 029/0018/A | C66: PATRICIA BEZERRA DE OLIVEIRA | D66: 45224
A67: PARAISÓPOLIS/ANTONICO | B67: 029/0024/D | C67: CARLOS JESUS DA SILVA | D67: 45224
A68: PARAISÓPOLIS/ANTONICO | B68: 029/0025/A | C68: ADAILTON ALVES DOS SANTOS | D68: 45224
A69: PARAISÓPOLIS/ANTONICO | B69: 029/0036/L | C69: ROMÁRIO SANTANA DA SILVA | D69: 45224
A70: PARAISÓPOLIS/ANTONICO | B70: 029/0036/M | C70: PATRICIA PEREIRA TEIXEIRA | D70: 45224
A71: PARAISÓPOLIS/ANTONICO | B71: 029/0036/N | C71: VITÓRIA DA SILVA MEDEIROS | D71: 45224
A72: PARAISÓPOLIS/ANTONICO | B72: 029/0036/O | C72: WALDECI MARQUES CARDOSO FILHO | D72: 45224
A73: PARAISÓPOLIS/ANTONICO | B73: 029/0042/A | C73: CRISTINE DE LIMA BRITO | D73: 45224
A74: PARAISÓPOLIS/ANTONICO | B74: 029/0042/B | C74: PRISCILA SILVA ROLT | D74: 45224
... A91: PARAISÓPOLIS/ANTONICO | B91: 031/0034/I | C91: DANIELE COSTA | D91: 45224
A92: PARAISÓPOLIS/ANTONICO | B92: 031/0034/K | D92: 45224
A93: PARAISÓPOLIS/ANTONICO | B93: 031/0036/A | C93: EUDES GONÇALVES CAVALCANTI | D93: 45224
A94: PARAISÓPOLIS/ANTONICO | B94: 031/0053/A | C94: JOÃO VICTOR ARAUJO DOS SANTOS | D94: 45224
A95: PARAISÓPOLIS/ANTONICO | B95: 031/0058/B | C95: FLAVIO ARAUJO DOS SANTOS | D95: 45224
A96: PARAISÓPOLIS/ANTONICO | B96: 031/0058/E | C96: ELIO NEVES DE SOUZA | D96: 45224
A97: PARAISÓPOLIS/ANTONICO | B97: 031/0058/H | C97: IVA CERQUEIRA LENARES | D97: 45224
A98: PARAISÓPOLIS/ANTONICO | B98: 031/0078/A | C98: EDNALDO BARBOSA BATISTA | D98: N/A
A99: PARAISÓPOLIS/ANTONICO | B99: 031/0078/B | C99: MARIA JOSE PEREIRA BASTOS | D99: 45049
A100: PARAISÓPOLIS/ANTONICO | B100: 033/0029/C | C100: PABLO SANTANA DA SILVA | D100: N/A
A101: PARAISÓPOLIS/ANTONICO | B101: 035/0029/A | C101: ERNANDES GOMES DE OLIVEIRA | D101: N/A
C102: GILBERTO XAVIER DE SOUZA | D102: N/A
C103: ANA CLAUDIA PEREIRA DA SILVA | D103: 44910
C104: MAGDA GOMES LISBÔA | D104: 44840
C105: VALQUIRIA GOMES DA SILVA | D105: N/A
C106: IVALDO GOMES DA SILVA | D106: N/A
C107: GRACELINE DE BARROS COSTA | D107: 44877
C108: VANUSA GOMES DA SILVA | D108: N/A
C109: TIAGO GOMES DA SILVA | D109: N/A
C110: ERICA DE SOUZA DAS VIRGENS | D110: 44840
C111: ROSENILDO MOREIRA DOS SANTOS | D111: N/A
C112: MARCOS SILVA OLIVEIRA | D112: N/A
C113: ANA CRISTINA DE BARROS COSTA | D113: N/A
C114: ANDERSON NÓBREGA DE ARAÚJO | D114: N/A
B115: 025/0006/K | C115: JOSE REINALDO DA SILVA | D115: N/A
B116: 025/0006/L | C116: JOSINETE CARVALHO SILVA | D116: N/A
B117: 025/0007/A | C117: MARIA APARECIDA FLECKENSTEIN VIEIRA | D117: N/A
B118: 025/0007/B | C118: CAROLINA SILVA DO NASCIMENTO | D118: N/A
B119: 025/0007/C | C119: PROPRIETÁRIO NÃO IDENTIFICADO | D119: N/A
...

Sheet Planilha2
D4: ÁREA | E4: SELO | F4: PROPRIETÁRIO | G4: CPF | H4: No PROCESSO SEI (INDENIZAÇÃO)
D5: JARDIM MONTE ALEGRE | E5: 001/0002/C | F5: HUGO FÉLIX PEREIRA DA SILVA | G5: 480.070.948-22 | H5: 6014.2025/0004876-4
D6: JARDIM MONTE ALEGRE | E6: 001/0004/A | F6: DANIELA GISELIA DA SILVA | G6: 411.798.508-66 | H6: 6014.2025/0004546-3
D7: JARDIM MONTE ALEGRE | E7: 001/0007/B | F7: FRANCISCO ANTONIO SALES | G7: 441.086.948-56 | H7: 6014.2025/0003850-5
D8: JARDIM MONTE ALEGRE | E8: 001/0010/A | F8: JOSÉ GABRIEL DA SILVA | G8: 065.751.208-73 | H8: 6014.2025/0004882-9
D9: JARDIM MONTE ALEGRE | E9: 001/0011/A | F9: LÚCIA GARCIA NUNES NASCIMENTO | G9: 452.900.084-20 | H9: 6014.2025/0004390-8
D15: JARDIM MONTE ALEGRE | E15: 001/0018/B | F15: GUILHERME CATELI BARBOSA | G15: 535.389.928-86 | H15: 6014.2024/0005453-3
D16: JARDIM MONTE ALEGRE | E16: 001/0019/A | F16: SABRINA DE CAMPOS MASCARENHAS | G16: 533.629.768-24 | H16: 6014.2025/0000289-6
D17: JARDIM MONTE ALEGRE | E17: 001/0022/A | F17: DAVID LYE VEIRA | G17: 316.735.778-90 | H17: 6014.2024/0005451-7
D18: JARDIM MONTE ALEGRE | E18: 001/0022/B | F18: GABRIELLY ADRIANY VIEIRA | G18: 427.120.998-85 | H18: 6014.2024/0005450-9
